Workbook

Sheet Control
A4: Monthly F
A5: Monthly V
A6: Annual
A7: One-Time

Sheet DeleteThisPageThenSave
B2: OriginalFileName | C2: Echelon_Primary_TCO_v5_11_13_25.xlsx

Sheet Confidentiality&Non-Disclosure
B2: Confidentiality and Non-Disclosure All tools, software, documentation, processes, methodologies, and related materials provided by Arriba Advisors LLC (the “Proprietary Materials”) are proprietary and confidential. These Proprietary Materials are intended solely for the recipient’s authorized use and shall not be copied, shared, distributed, or disclosed to any third party without Arriba Advisor LLC’s prior written consent. Any unauthorized review, use, storage, reproduction, or distribution of the Tools is strictly prohibited. If you have received access to the Proprietary Materials in error or without authorization, please notify Arriba Advisor LLC immediately and delete or destroy any copies in your possession. This confidentiality obligation remains in effect even after the conclusion of the business relationship.

Sheet Line Items
O1: FIS | BB1: Jack Henry
B2: Years-> | D2: 7 | O2: CPI Bundle-> | Q2: 0.06 | BB2: Growth-> | BD2: 0 | BE2: *Variable items are minimums. No growth needs to be added.
B3: Growth-> | D3: 0.2 | O3: CPI Non-Bundle-> | Q3: 0.03 | BB3: CPI-> | BD3: 0.03 | CO3: CPI-> | CP3: 0.03
B4: Type (Monthly/Annual) | D4: Average Monthly QTY | E4: Quantity Per Year with Growth | O4: FIS | AP4: Type (Monthly/Annual) | AQ4: Average Monthly QTY | AR4: Quantity Per Year with Growth | BB4: Jack Henry | CC4: Type (Monthly/Annual) | CD4: Average Monthly QTY | CE4: Quantity Per Year with Growth | CO4: Vendor 3
C5: Proposal (11/2025) | E5: Year 1 Quantity | F5: Year 2 Quantity | G5: Year 3 Quantity | H5: Year 4 Quantity | I5: Year 5 Quantity | J5: Year 6 Quantity | K5: Year 7 Quantity | L5: Year 8 Quantity | M5: Year 9 Quantity | N5: Year 10 Quantity | O5: Solution Name/Description | P5: Category | Q5: Per Unit Rate | R5: Year 1 Monthly Cost | S5: Year 1 Cost | T5: Year 2 Cost | U5: Year 3 Cost | V5: Year 4 Cost | W5: Year 5 Cost | X5: Year 6 Cost | Y5: Year 7 Cost | Z5: Year 8 Cost | AA5: Year 9 Cost | AB5: Year 10 Cost | AC5: Year 1 CPI | AD5: Year 2 CPI | AE5: Year 3 CPI | AF5: Year 4 CPI | AG5: Year 5 CPI | AH5: Year 6 CPI | AI5: Year 7 CPI | AJ5: Year 8 CPI | AK5: Year 9 CPI | AL5: Year 10 CPI | AM5: CPI | AN5: Total Term Cost | AR5: Year 1 Quantity | AS5: Year 2 Quantity | AT5: Year 3 Quantity | AU5: Year 4 Quantity | AV5: Year 5 Quantity | AW5: Year 6 Quantity | AX5: Year 7 Quantity | AY5: Year 8 Quantity | AZ5: Year 9 Quantity | BA5: Year 10 Quantity | BB5: Solution Name/Description | BC5: Category | BD5: Per Unit Rate | BE5: Year 1 Monthly Cost | BF5: Year 1 Cost | BG5: Year 2 Cost | BH5: Year 3 Cost | BI5: Year 4 Cost | BJ5: Year 5 Cost | BK5: Year 6 Cost | BL5: Year 7 Cost | BM5: Year 8 Cost | BN5: Year 9 Cost | BO5: Year 10 Cost | BP5: Year 1 CPI | BQ5: Year 2 CPI | BR5: Year 3 CPI | BS5: Year 4 CPI | BT5: Year 5 CPI | BU5: Year 6 CPI | BV5: Year 7 CPI | BW5: Year 8 CPI | BX5: Year 9 CPI | BY5: Year 10 CPI | BZ5: CPI | CA5: Total Term Cost | CE5: Year 1 Quantity | CF5: Year 2 Quantity | CG5: Year 3 Quantity | CH5: Year 4 Quantity | CI5: Year 5 Quantity | CJ5: Year 6 Quantity | CK5: Year 7 Quantity | CL5: Year 8 Quantity | CM5: Year 9 Quantity | CN5: Year 10 Quantity | CO5: Solution Name/Description | CP5: Per Unit Rate | CQ5: Year 1 Monthly Cost | CR5: Year 1 Cost | CS5: Year 2 Cost | CT5: Year 3 Cost | CU5: Year 4 Cost | CV5: Year 5 Cost | CW5: Year 6 Cost | CX5: Year 7 Cost | CY5: Year 8 Cost | CZ5: Year 9 Cost | DA5: Year 10 Cost | DB5: Year 1 CPI | DC5: Year 2 CPI | DD5: Year 3 CPI | DE5: Year 4 CPI | DF5: Year 5 CPI | DG5: Year 6 CPI | DH5: Year 7 CPI | DI5: Year 8 CPI | DJ5: Year 9 CPI | DK5: Year 10 CPI | DL5: CPI | DM5: Total Term Cost
B6: Recurring Monthly and Annual Fees - Bundle FIS products | AP6: Recurring Monthly and Annual Fees Jack Henry Product | CC6: Recurring Monthly and Annual Fees
B7: Monthly F | C7: 1 | D7: =IFERROR(AVERAGE(C7:C7),0) -> 1 | E7: =IF($B7="Annual",1,IF($B7="Monthly F",12,IF($B7="Monthly V",D7*12,IF($B7="One-Time",1,D7*12)))) -> 12 | F7: 0 | G7: 0 | H7: 0 | I7: 0 | J7: 0 | K7: 0 | L7: 0 | M7: 0 | N7: 0 | O7: Year 1 CORE PROCESSING (Bundle) | P7: HORIZON CORE ACCOUNT PROCESSING | Q7: 15000 | R7: =S7/12 -> 15000 | S7: =IFERROR($Q7*E7,0) -> 180000 | T7: =IFERROR($Q7*F7,0) -> 0 | U7: =IFERROR($Q7*G7,0) -> 0 | V7: =IFERROR($Q7*H7,0) -> 0 | W7: =IFERROR($Q7*I7,0) -> 0 | X7: =IFERROR($Q7*J7,0) -> 0 | Y7: =IFERROR($Q7*K7,0) -> 0 | Z7: =IFERROR($Q7*L7,0) -> 0 | ... AB7: =IFERROR($Q7*N7,0) -> 0 | AD7: 0 | AE7: 0 | AF7: 0 | AG7: 0 | AH7: 0 | AI7: 0 | AJ7: 0 | AK7: 0 | AL7: 0 | AM7: =SUM(AC7:AL7) -> 0 | AN7: =SUM(AM7,S7:AB7) -> 180000 | AP7: Monthly V | AQ7: 5000 | AR7: =IF($AP7="Annual",1,IF($AP7="Monthly F",12,IF($AP7="Monthly V",AQ7*12,IF($AP7="One-Time",1,AQ7*12)))) -> 60000 | AS7: {=IFERROR(_xlfn.IFS(VALUE(MID(AS$5,6,1))>$D$2,0,$AP7="Annual",1,AR7=12,12,$AP7="Monthly V",AR7*(1+$BD$2),$AP7="Monthly F",12,$AP7="One-Time",0),AR7*(1+$BD$2))} -> 60000 | AT7: {=IFERROR(_xlfn.IFS(VALUE(MID(AT$5,6,1))>$D$2,0,$AP7="Annual",1,AS7=12,12,$AP7="Monthly V",AS7*(1+$BD$2),$AP7="Monthly F",12,$AP7="One-Time",0),AS7*(1+$BD$2))} -> 60000 | AU7: {=IFERROR(_xlfn.IFS(VALUE(MID(AU$5,6,1))>$D$2,0,$AP7="Annual",1,AT7=12,12,$AP7="Monthly V",AT7*(1+$BD$2),$AP7="Monthly F",12,$AP7="One-Time",0),AT7*(1+$BD$2))} -> 60000 | AV7: {=IFERROR(_xlfn.IFS(VALUE(MID(AV$5,6,1))>$D$2,0,$AP7="Annual",1,AU7=12,12,$AP7="Monthly V",AU7*(1+$BD$2),$AP7="Monthly F",12,$AP7="One-Time",0),AU7*(1+$BD$2))} -> 60000 | AW7: {=IFERROR(_xlfn.IFS(VALUE(MID(AW$5,6,1))>$D$2,0,$AP7="Annual",1,AV7=12,12,$AP7="Monthly V",AV7*(1+$BD$2),$AP7="Monthly F",12,$AP7="One-Time",0),AV7*(1+$BD$2))} -> 60000 | AX7: {=IFERROR(_xlfn.IFS(VALUE(MID(AX$5,6,1))>$D$2,0,$AP7="Annual",1,AW7=12,12,$AP7="Monthly V",AW7*(1+$BD$2),$AP7="Monthly F",12,$AP7="One-Time",0),AW7*(1+$BD$2))} -> 60000 | AY7: {=IFERROR(_xlfn.IFS(VALUE(MID(AY$5,6,1))>$D$2,0,$AP7="Annual",1,AX7=12,12,$AP7="Monthly V",AX7*(1+$D$3),$AP7="Monthly F",12,$AP7="One-Time",0),AX7*(1+$D$3))} -> 0 | AZ7: {=IFERROR(_xlfn.IFS(VALUE(MID(AZ$5,6,1))>$D$2,0,$AP7="Annual",1,AY7=12,12,$AP7="Monthly V",AY7*(1+$D$3),$AP7="Monthly F",12,$AP7="One-Time",0),AY7*(1+$D$3))} -> 0 | BA7: {=IFERROR(_xlfn.IFS(VALUE(MID(BA$5,6,2))>$D$2,0,$AP7="Annual",1,AZ7=12,12,$AP7="Monthly V",AZ7*(1+$D$3),$AP7="Monthly F",12,$AP7="One-Time",0),AZ7*(1+$D$3))} -> 0 | BB7: SilverLake System Bundle | BC7: SilverLake | BD7: 1.2181 | BE7: =BF7/12 -> 6090.5 | BF7: =IFERROR(AR7*$BD7,0) -> 73086 | BG7: =IFERROR(AS7*$BD7,0) -> 73086 | BH7: =IFERROR(AT7*$BD7,0) -> 73086 | BI7: =BH7*1.03 -> 75278.58 | BJ7: =BI7*1.03 -> 77536.937 | BK7: =BJ7*1.03 -> 79863.046 | BL7: =BK7*1.03 -> 82258.937 | BM7: =IFERROR(AY7*$BD7,0) -> 0 | BN7: =IFERROR(AZ7*$BD7,0) -> 0 | BO7: =IFERROR(BA7*$BD7,0) -> 0 | BQ7: =IF(VALUE(MID(BQ$5,6,1))<=$D$2,((1+$BD$3)^1-1)*BG7,0) -> 2192.58 | BR7: =IF(VALUE(MID(BR$5,6,1))<=$D$2,((1+$BD$3)^2-1)*BH7,0) -> 4450.9374 | BS7: =IF(VALUE(MID(BS$5,6,1))<=$D$2,((1+$BD$3)^3-1)*BI7,0) -> 6980.3569 | BT7: =IF(VALUE(MID(BT$5,6,1))<=$D$2,((1+$BD$3)^4-1)*BJ7,0) -> 9731.5687 | BU7: =IF(VALUE(MID(BU$5,6,1))<=$D$2,((1+$BD$3)^5-1)*BK7,0) -> 12720.113 | BV7: =IF(VALUE(MID(BV$5,6,1))<=$D$2,((1+$BD$3)^6-1)*BL7,0) -> 15962.536 | BW7: =IF(VALUE(MID(BW$5,6,1))<=$D$2,((1+$BD$3)^7-1)*BM7,0) -> 0 | BX7: =IF(VALUE(MID(BX$5,6,1))<=$D$2,((1+$BD$3)^8-1)*BN7,0) -> 0 | BY7: =IF(VALUE(MID(BY$5,6,2))<=$D$2,((1+$BD$3)^9-1)*BO7,0) -> 0 | BZ7: =SUM(BP7:BY7) -> 52038.091 | CA7: =SUM(BZ7,BF7:BO7) -> 586233.59 | CE7: =IF($CC7="Annual",1,IF($CC7="Monthly F",12,IF($CC7="Monthly V",CD7*12,IF($CC7="One-Time",1,CD7*12)))) -> 0 | CF7: {=IFERROR(_xlfn.IFS(VALUE(MID(CF$5,6,1))>$D$2,0,$CC7="Annual",1,CE7=12,12,$CC7="Monthly V",CE7*(1+$D$3),$CC7="Monthly F",12,$CC7="One-Time",0),CE7*(1+$D$3))} -> 0 | CG7: {=IFERROR(_xlfn.IFS(VALUE(MID(CG$5,6,1))>$D$2,0,$CC7="Annual",1,CF7=12,12,$CC7="Monthly V",CF7*(1+$D$3),$CC7="Monthly F",12,$CC7="One-Time",0),CF7*(1+$D$3))} -> 0 | CH7: {=IFERROR(_xlfn.IFS(VALUE(MID(CH$5,6,1))>$D$2,0,$CC7="Annual",1,CG7=12,12,$CC7="Monthly V",CG7*(1+$D$3),$CC7="Monthly F",12,$CC7="One-Time",0),CG7*(1+$D$3))} -> 0 | CI7: {=IFERROR(_xlfn.IFS(VALUE(MID(CI$5,6,1))>$D$2,0,$CC7="Annual",1,CH7=12,12,$CC7="Monthly V",CH7*(1+$D$3),$CC7="Monthly F",12,$CC7="One-Time",0),CH7*(1+$D$3))} -> 0 | CJ7: {=IFERROR(_xlfn.IFS(VALUE(MID(CJ$5,6,1))>$D$2,0,$CC7="Annual",1,CI7=12,12,$CC7="Monthly V",CI7*(1+$D$3),$CC7="Monthly F",12,$CC7="One-Time",0),CI7*(1+$D$3))} -> 0 | CK7: {=IFERROR(_xlfn.IFS(VALUE(MID(CK$5,6,1))>$D$2,0,$CC7="Annual",1,CJ7=12,12,$CC7="Monthly V",CJ7*(1+$D$3),$CC7="Monthly F",12,$CC7="One-Time",0),CJ7*(1+$D$3))} -> 0 | CL7: {=IFERROR(_xlfn.IFS(VALUE(MID(CL$5,6,1))>$D$2,0,$CC7="Annual",1,CK7=12,12,$CC7="Monthly V",CK7*(1+$D$3),$CC7="Monthly F",12,$CC7="One-Time",0),CK7*(1+$D$3))} -> 0 | CM7: {=IFERROR(_xlfn.IFS(VALUE(MID(CM$5,6,1))>$D$2,0,$CC7="Annual",1,CL7=12,12,$CC7="Monthly V",CL7*(1+$D$3),$CC7="Monthly F",12,$CC7="One-Time",0),CL7*(1+$D$3))} -> 0 | CN7: {=IFERROR(_xlfn.IFS(VALUE(MID(CN$5,6,2))>$D$2,0,$CC7="Annual",1,CM7=12,12,$CC7="Monthly V",CM7*(1+$D$3),$CC7="Monthly F",12,$CC7="One-Time",0),CM7*(1+$D$3))} -> 0 | CQ7: =CR7/12 -> 0 | CR7: =IFERROR(CE7*$CP7,0) -> 0 | CS7: =IFERROR(CF7*$CP7,0) -> 0 | CT7: =IFERROR(CG7*$CP7,0) -> 0 | CU7: =IFERROR(CH7*$CP7,0) -> 0 | CV7: =IFERROR(CI7*$CP7,0) -> 0 | CW7: =IFERROR(CJ7*$CP7,0) -> 0 | CX7: =IFERROR(CK7*$CP7,0) -> 0 | CY7: =IFERROR(CL7*$CP7,0) -> 0 | ... DA7: =IFERROR(CN7*$CP7,0) -> 0 | DC7: =IF(VALUE(MID(DC$5,6,1))<=$D$2,((1+$CP$3)^1-1)*CS7,0) -> 0 | DD7: =IF(VALUE(MID(DD$5,6,1))<=$D$2,((1+$CP$3)^2-1)*CT7,0) -> 0 | DE7: =IF(VALUE(MID(DE$5,6,1))<=$D$2,((1+$CP$3)^3-1)*CU7,0) -> 0 | DF7: =IF(VALUE(MID(DF$5,6,1))<=$D$2,((1+$CP$3)^4-1)*CV7,0) -> 0 | DG7: =IF(VALUE(MID(DG$5,6,1))<=$D$2,((1+$CP$3)^5-1)*CW7,0) -> 0 | DH7: =IF(VALUE(MID(DH$5,6,1))<=$D$2,((1+$CP$3)^6-1)*CX7,0) -> 0 | DI7: =IF(VALUE(MID(DI$5,6,1))<=$D$2,((1+$CP$3)^7-1)*CY7,0) -> 0 | DJ7: =IF(VALUE(MID(DJ$5,6,1))<=$D$2,((1+$CP$3)^8-1)*CZ7,0) -> 0 | DK7: =IF(VALUE(MID(DK$5,6,2))<=$D$2,((1+$CP$3)^9-1)*DA7,0) -> 0 | DL7: =SUM(DB7:DK7) -> 0 | DM7: =SUM(DL7,CR7:DA7) -> 0
B8: Monthly F | C8: 1 | D8: =IFERROR(AVERAGE(C8:C8),0) -> 1 | E8: 0 | F8: {=IFERROR(_xlfn.IFS(VALUE(MID(F$5,6,1))>$D$2,0,$B8="Annual",1,E8=12,12,$B8="Monthly V",E8*(1+$D$3),$B8="Monthly F",12,$B8="One-Time",0),E8*(1+$D$3))} -> 12 | G8: 0 | H8: 0 | I8: 0 | J8: 0 | K8: 0 | L8: 0 | M8: 0 | N8: 0 | O8: Year 2 CORE PROCESSING (Bundle) | P8: HORIZON CORE ACCOUNT PROCESSING | Q8: 17500 | R8: =S8/12 -> 0 | S8: =IFERROR($Q8*E8,0) -> 0 | T8: =IFERROR($Q8*F8,0) -> 210000 | U8: =IFERROR($Q8*G8,0) -> 0 | V8: =IFERROR($Q8*H8,0) -> 0 | W8: =IFERROR($Q8*I8,0) -> 0 | X8: =IFERROR($Q8*J8,0) -> 0 | Y8: =IFERROR($Q8*K8,0) -> 0 | Z8: =IFERROR($Q8*L8,0) -> 0 | ... AB8: =IFERROR($Q8*N8,0) -> 0 | AD8: 0 | AE8: 0 | AF8: 0 | AG8: 0 | AH8: 0 | AI8: 0 | AJ8: 0 | AK8: 0 | AL8: 0 | AM8: =SUM(AC8:AL8) -> 0 | AN8: =SUM(AM8,S8:AB8) -> 210000 | AP8: Monthly V | AQ8: 1 | AR8: =IF($AP8="Annual",1,IF($AP8="Monthly F",12,IF($AP8="Monthly V",AQ8*12,IF($AP8="One-Time",1,AQ8*12)))) -> 12 | AS8: {=IFERROR(_xlfn.IFS(VALUE(MID(AS$5,6,1))>$D$2,0,$AP8="Annual",1,AR8=12,12,$AP8="Monthly V",AR8*(1+$BD$2),$AP8="Monthly F",12,$AP8="One-Time",0),AR8*(1+$BD$2))} -> 12 | AT8: {=IFERROR(_xlfn.IFS(VALUE(MID(AT$5,6,1))>$D$2,0,$AP8="Annual",1,AS8=12,12,$AP8="Monthly V",AS8*(1+$BD$2),$AP8="Monthly F",12,$AP8="One-Time",0),AS8*(1+$BD$2))} -> 12 | AU8: {=IFERROR(_xlfn.IFS(VALUE(MID(AU$5,6,1))>$D$2,0,$AP8="Annual",1,AT8=12,12,$AP8="Monthly V",AT8*(1+$BD$2),$AP8="Monthly F",12,$AP8="One-Time",0),AT8*(1+$BD$2))} -> 12 | AV8: {=IFERROR(_xlfn.IFS(VALUE(MID(AV$5,6,1))>$D$2,0,$AP8="Annual",1,AU8=12,12,$AP8="Monthly V",AU8*(1+$BD$2),$AP8="Monthly F",12,$AP8="One-Time",0),AU8*(1+$BD$2))} -> 12 | AW8: {=IFERROR(_xlfn.IFS(VALUE(MID(AW$5,6,1))>$D$2,0,$AP8="Annual",1,AV8=12,12,$AP8="Monthly V",AV8*(1+$BD$2),$AP8="Monthly F",12,$AP8="One-Time",0),AV8*(1+$BD$2))} -> 12 | AX8: {=IFERROR(_xlfn.IFS(VALUE(MID(AX$5,6,1))>$D$2,0,$AP8="Annual",1,AW8=12,12,$AP8="Monthly V",AW8*(1+$BD$2),$AP8="Monthly F",12,$AP8="One-Time",0),AW8*(1+$BD$2))} -> 12 | AY8: {=IFERROR(_xlfn.IFS(VALUE(MID(AY$5,6,1))>$D$2,0,$AP8="Annual",1,AX8=12,12,$AP8="Monthly V",AX8*(1+$D$3),$AP8="Monthly F",12,$AP8="One-Time",0),AX8*(1+$D$3))} -> 0 | AZ8: {=IFERROR(_xlfn.IFS(VALUE(MID(AZ$5,6,1))>$D$2,0,$AP8="Annual",1,AY8=12,12,$AP8="Monthly V",AY8*(1+$D$3),$AP8="Monthly F",12,$AP8="One-Time",0),AY8*(1+$D$3))} -> 0 | BA8: {=IFERROR(_xlfn.IFS(VALUE(MID(BA$5,6,2))>$D$2,0,$AP8="Annual",1,AZ8=12,12,$AP8="Monthly V",AZ8*(1+$D$3),$AP8="Monthly F",12,$AP8="One-Time",0),AZ8*(1+$D$3))} -> 0 | BB8: Closed Accounts (PAP) | BC8: SilverLake | BD8: 0.25 | BE8: =BF8/12 -> 0.25 | BF8: =IFERROR(AR8*$BD8,0) -> 3 | BG8: =IFERROR(AS8*$BD8,0) -> 3 | BH8: =IFERROR(AT8*$BD8,0) -> 3 | BI8: =BH8*1.03 -> 3.09 | BJ8: =IFERROR(AV8*$BD8,0) -> 3 | BK8: =IFERROR(AW8*$BD8,0) -> 3 | BL8: =IFERROR(AX8*$BD8,0) -> 3 | BM8: =IFERROR(AY8*$BD8,0) -> 0 | BN8: =IFERROR(AZ8*$BD8,0) -> 0 | BO8: =IFERROR(BA8*$BD8,0) -> 0 | BQ8: =IF(VALUE(MID(BQ$5,6,1))<=$D$2,((1+$BD$3)^1-1)*BG8,0) -> 0.09 | BR8: =IF(VALUE(MID(BR$5,6,1))<=$D$2,((1+$BD$3)^2-1)*BH8,0) -> 0.1827 | BS8: =IF(VALUE(MID(BS$5,6,1))<=$D$2,((1+$BD$3)^3-1)*BI8,0) -> 0.28652643 | BT8: =IF(VALUE(MID(BT$5,6,1))<=$D$2,((1+$BD$3)^4-1)*BJ8,0) -> 0.37652643 | BU8: =IF(VALUE(MID(BU$5,6,1))<=$D$2,((1+$BD$3)^5-1)*BK8,0) -> 0.47782222 | BV8: =IF(VALUE(MID(BV$5,6,1))<=$D$2,((1+$BD$3)^6-1)*BL8,0) -> 0.58215689 | BW8: =IF(VALUE(MID(BW$5,6,1))<=$D$2,((1+$BD$3)^7-1)*BM8,0) -> 0 | BX8: =IF(VALUE(MID(BX$5,6,1))<=$D$2,((1+$BD$3)^8-1)*BN8,0) -> 0 | BY8: =IF(VALUE(MID(BY$5,6,2))<=$D$2,((1+$BD$3)^9-1)*BO8,0) -> 0 | BZ8: =SUM(BP8:BY8) -> 1.995732 | CA8: =SUM(BZ8,BF8:BO8) -> 23.085732 | CE8: =IF($CC8="Annual",1,IF($CC8="Monthly F",12,IF($CC8="Monthly V",CD8*12,IF($CC8="One-Time",1,CD8*12)))) -> 0 | CF8: {=IFERROR(_xlfn.IFS(VALUE(MID(CF$5,6,1))>$D$2,0,$CC8="Annual",1,CE8=12,12,$CC8="Monthly V",CE8*(1+$D$3),$CC8="Monthly F",12,$CC8="One-Time",0),CE8*(1+$D$3))} -> 0 | CG8: {=IFERROR(_xlfn.IFS(VALUE(MID(CG$5,6,1))>$D$2,0,$CC8="Annual",1,CF8=12,12,$CC8="Monthly V",CF8*(1+$D$3),$CC8="Monthly F",12,$CC8="One-Time",0),CF8*(1+$D$3))} -> 0 | CH8: {=IFERROR(_xlfn.IFS(VALUE(MID(CH$5,6,1))>$D$2,0,$CC8="Annual",1,CG8=12,12,$CC8="Monthly V",CG8*(1+$D$3),$CC8="Monthly F",12,$CC8="One-Time",0),CG8*(1+$D$3))} -> 0 | CI8: {=IFERROR(_xlfn.IFS(VALUE(MID(CI$5,6,1))>$D$2,0,$CC8="Annual",1,CH8=12,12,$CC8="Monthly V",CH8*(1+$D$3),$CC8="Monthly F",12,$CC8="One-Time",0),CH8*(1+$D$3))} -> 0 | CJ8: {=IFERROR(_xlfn.IFS(VALUE(MID(CJ$5,6,1))>$D$2,0,$CC8="Annual",1,CI8=12,12,$CC8="Monthly V",CI8*(1+$D$3),$CC8="Monthly F",12,$CC8="One-Time",0),CI8*(1+$D$3))} -> 0 | CK8: {=IFERROR(_xlfn.IFS(VALUE(MID(CK$5,6,1))>$D$2,0,$CC8="Annual",1,CJ8=12,12,$CC8="Monthly V",CJ8*(1+$D$3),$CC8="Monthly F",12,$CC8="One-Time",0),CJ8*(1+$D$3))} -> 0 | CL8: {=IFERROR(_xlfn.IFS(VALUE(MID(CL$5,6,1))>$D$2,0,$CC8="Annual",1,CK8=12,12,$CC8="Monthly V",CK8*(1+$D$3),$CC8="Monthly F",12,$CC8="One-Time",0),CK8*(1+$D$3))} -> 0 | CM8: {=IFERROR(_xlfn.IFS(VALUE(MID(CM$5,6,1))>$D$2,0,$CC8="Annual",1,CL8=12,12,$CC8="Monthly V",CL8*(1+$D$3),$CC8="Monthly F",12,$CC8="One-Time",0),CL8*(1+$D$3))} -> 0 | CN8: {=IFERROR(_xlfn.IFS(VALUE(MID(CN$5,6,2))>$D$2,0,$CC8="Annual",1,CM8=12,12,$CC8="Monthly V",CM8*(1+$D$3),$CC8="Monthly F",12,$CC8="One-Time",0),CM8*(1+$D$3))} -> 0 | CQ8: =CR8/12 -> 0 | CR8: =IFERROR(CE8*$CP8,0) -> 0 | CS8: =IFERROR(CF8*$CP8,0) -> 0 | CT8: =IFERROR(CG8*$CP8,0) -> 0 | CU8: =IFERROR(CH8*$CP8,0) -> 0 | CV8: =IFERROR(CI8*$CP8,0) -> 0 | CW8: =IFERROR(CJ8*$CP8,0) -> 0 | CX8: =IFERROR(CK8*$CP8,0) -> 0 | CY8: =IFERROR(CL8*$CP8,0) -> 0 | ... DA8: =IFERROR(CN8*$CP8,0) -> 0 | DC8: =IF(VALUE(MID(DC$5,6,1))<=$D$2,((1+$CP$3)^1-1)*CS8,0) -> 0 | DD8: =IF(VALUE(MID(DD$5,6,1))<=$D$2,((1+$CP$3)^2-1)*CT8,0) -> 0 | DE8: =IF(VALUE(MID(DE$5,6,1))<=$D$2,((1+$CP$3)^3-1)*CU8,0) -> 0 | DF8: =IF(VALUE(MID(DF$5,6,1))<=$D$2,((1+$CP$3)^4-1)*CV8,0) -> 0 | DG8: =IF(VALUE(MID(DG$5,6,1))<=$D$2,((1+$CP$3)^5-1)*CW8,0) -> 0 | DH8: =IF(VALUE(MID(DH$5,6,1))<=$D$2,((1+$CP$3)^6-1)*CX8,0) -> 0 | DI8: =IF(VALUE(MID(DI$5,6,1))<=$D$2,((1+$CP$3)^7-1)*CY8,0) -> 0 | DJ8: =IF(VALUE(MID(DJ$5,6,1))<=$D$2,((1+$CP$3)^8-1)*CZ8,0) -> 0 | DK8: =IF(VALUE(MID(DK$5,6,2))<=$D$2,((1+$CP$3)^9-1)*DA8,0) -> 0 | DL8: =SUM(DB8:DK8) -> 0 | DM8: =SUM(DL8,CR8:DA8) -> 0
B9: Monthly F | C9: 1 | D9: =IFERROR(AVERAGE(C9:C9),0) -> 1 | E9: 0 | F9: 0 | G9: {=IFERROR(_xlfn.IFS(VALUE(MID(G$5,6,1))>$D$2,0,$B9="Annual",1,F9=12,12,$B9="Monthly V",F9*(1+$D$3),$B9="Monthly F",12,$B9="One-Time",0),F9*(1+$D$3))} -> 12 | H9: 0 | I9: 0 | J9: 0 | K9: 0 | L9: 0 | M9: 0 | N9: 0 | O9: Year 3 CORE PROCESSING (Bundle) | P9: HORIZON CORE ACCOUNT PROCESSING | Q9: 22500 | R9: =S9/12 -> 0 | S9: =IFERROR($Q9*E9,0) -> 0 | T9: =IFERROR($Q9*F9,0) -> 0 | U9: =IFERROR($Q9*G9,0) -> 270000 | V9: =IFERROR($Q9*H9,0) -> 0 | W9: =IFERROR($Q9*I9,0) -> 0 | X9: =IFERROR($Q9*J9,0) -> 0 | Y9: =IFERROR($Q9*K9,0) -> 0 | Z9: =IFERROR($Q9*L9,0) -> 0 | ... AB9: =IFERROR($Q9*N9,0) -> 0 | AD9: 0 | AE9: 0 | AF9: 0 | AG9: 0 | AH9: 0 | AI9: 0 | AJ9: 0 | AK9: 0 | AL9: 0 | AM9: =SUM(AC9:AL9) -> 0 | AN9: =SUM(AM9,S9:AB9) -> 270000 | AP9: Monthly F | AQ9: 1 | AR9: =IF($AP9="Annual",1,IF($AP9="Monthly F",12,IF($AP9="Monthly V",AQ9*12,IF($AP9="One-Time",1,AQ9*12)))) -> 12 | AS9: {=IFERROR(_xlfn.IFS(VALUE(MID(AS$5,6,1))>$D$2,0,$AP9="Annual",1,AR9=12,12,$AP9="Monthly V",AR9*(1+$BD$2),$AP9="Monthly F",12,$AP9="One-Time",0),AR9*(1+$BD$2))} -> 12 | AT9: {=IFERROR(_xlfn.IFS(VALUE(MID(AT$5,6,1))>$D$2,0,$AP9="Annual",1,AS9=12,12,$AP9="Monthly V",AS9*(1+$BD$2),$AP9="Monthly F",12,$AP9="One-Time",0),AS9*(1+$BD$2))} -> 12 | AU9: {=IFERROR(_xlfn.IFS(VALUE(MID(AU$5,6,1))>$D$2,0,$AP9="Annual",1,AT9=12,12,$AP9="Monthly V",AT9*(1+$BD$2),$AP9="Monthly F",12,$AP9="One-Time",0),AT9*(1+$BD$2))} -> 12 | AV9: {=IFERROR(_xlfn.IFS(VALUE(MID(AV$5,6,1))>$D$2,0,$AP9="Annual",1,AU9=12,12,$AP9="Monthly V",AU9*(1+$BD$2),$AP9="Monthly F",12,$AP9="One-Time",0),AU9*(1+$BD$2))} -> 12 | AW9: {=IFERROR(_xlfn.IFS(VALUE(MID(AW$5,6,1))>$D$2,0,$AP9="Annual",1,AV9=12,12,$AP9="Monthly V",AV9*(1+$BD$2),$AP9="Monthly F",12,$AP9="One-Time",0),AV9*(1+$BD$2))} -> 12 | AX9: {=IFERROR(_xlfn.IFS(VALUE(MID(AX$5,6,1))>$D$2,0,$AP9="Annual",1,AW9=12,12,$AP9="Monthly V",AW9*(1+$BD$2),$AP9="Monthly F",12,$AP9="One-Time",0),AW9*(1+$BD$2))} -> 12 | AY9: {=IFERROR(_xlfn.IFS(VALUE(MID(AY$5,6,1))>$D$2,0,$AP9="Annual",1,AX9=12,12,$AP9="Monthly V",AX9*(1+$D$3),$AP9="Monthly F",12,$AP9="One-Time",0),AX9*(1+$D$3))} -> 0 | AZ9: {=IFERROR(_xlfn.IFS(VALUE(MID(AZ$5,6,1))>$D$2,0,$AP9="Annual",1,AY9=12,12,$AP9="Monthly V",AY9*(1+$D$3),$AP9="Monthly F",12,$AP9="One-Time",0),AY9*(1+$D$3))} -> 0 | BA9: {=IFERROR(_xlfn.IFS(VALUE(MID(BA$5,6,2))>$D$2,0,$AP9="Annual",1,AZ9=12,12,$AP9="Monthly V",AZ9*(1+$D$3),$AP9="Monthly F",12,$AP9="One-Time",0),AZ9*(1+$D$3))} -> 0 | BB9: Daily File Transfer Integration IntraFi | BC9: SilverLake | BD9: 225 | BE9: =BF9/12 -> 225 | BF9: =IFERROR(AR9*$BD9,0) -> 2700 | BG9: =IFERROR(AS9*$BD9,0) -> 2700 | BH9: =IFERROR(AT9*$BD9,0) -> 2700 | BI9: =BH9*1.03 -> 2781 | BJ9: =BI9*1.03 -> 2864.43 | BK9: =BJ9*1.03 -> 2950.3629 | BL9: =BK9*1.03 -> 3038.8738 | BM9: =IFERROR(AY9*$BD9,0) -> 0 | BN9: =IFERROR(AZ9*$BD9,0) -> 0 | BO9: =IFERROR(BA9*$BD9,0) -> 0 | BQ9: =IF(VALUE(MID(BQ$5,6,1))<=$D$2,((1+$BD$3)^1-1)*BG9,0) -> 81 | BR9: =IF(VALUE(MID(BR$5,6,1))<=$D$2,((1+$BD$3)^2-1)*BH9,0) -> 164.43 | BS9: =IF(VALUE(MID(BS$5,6,1))<=$D$2,((1+$BD$3)^3-1)*BI9,0) -> 257.87379 | BT9: =IF(VALUE(MID(BT$5,6,1))<=$D$2,((1+$BD$3)^4-1)*BJ9,0) -> 359.5112 | BU9: =IF(VALUE(MID(BU$5,6,1))<=$D$2,((1+$BD$3)^5-1)*BK9,0) -> 469.91632 | BV9: =IF(VALUE(MID(BV$5,6,1))<=$D$2,((1+$BD$3)^6-1)*BL9,0) -> 589.70044 | BW9: =IF(VALUE(MID(BW$5,6,1))<=$D$2,((1+$BD$3)^7-1)*BM9,0) -> 0 | BX9: =IF(VALUE(MID(BX$5,6,1))<=$D$2,((1+$BD$3)^8-1)*BN9,0) -> 0 | BY9: =IF(VALUE(MID(BY$5,6,2))<=$D$2,((1+$BD$3)^9-1)*BO9,0) -> 0 | BZ9: =SUM(BP9:BY9) -> 1922.4317 | CA9: =SUM(BZ9,BF9:BO9) -> 21657.098 | CE9: =IF($CC9="Annual",1,IF($CC9="Monthly F",12,IF($CC9="Monthly V",CD9*12,IF($CC9="One-Time",1,CD9*12)))) -> 0 | CF9: {=IFERROR(_xlfn.IFS(VALUE(MID(CF$5,6,1))>$D$2,0,$CC9="Annual",1,CE9=12,12,$CC9="Monthly V",CE9*(1+$D$3),$CC9="Monthly F",12,$CC9="One-Time",0),CE9*(1+$D$3))} -> 0 | CG9: {=IFERROR(_xlfn.IFS(VALUE(MID(CG$5,6,1))>$D$2,0,$CC9="Annual",1,CF9=12,12,$CC9="Monthly V",CF9*(1+$D$3),$CC9="Monthly F",12,$CC9="One-Time",0),CF9*(1+$D$3))} -> 0 | CH9: {=IFERROR(_xlfn.IFS(VALUE(MID(CH$5,6,1))>$D$2,0,$CC9="Annual",1,CG9=12,12,$CC9="Monthly V",CG9*(1+$D$3),$CC9="Monthly F",12,$CC9="One-Time",0),CG9*(1+$D$3))} -> 0 | CI9: {=IFERROR(_xlfn.IFS(VALUE(MID(CI$5,6,1))>$D$2,0,$CC9="Annual",1,CH9=12,12,$CC9="Monthly V",CH9*(1+$D$3),$CC9="Monthly F",12,$CC9="One-Time",0),CH9*(1+$D$3))} -> 0 | CJ9: {=IFERROR(_xlfn.IFS(VALUE(MID(CJ$5,6,1))>$D$2,0,$CC9="Annual",1,CI9=12,12,$CC9="Monthly V",CI9*(1+$D$3),$CC9="Monthly F",12,$CC9="One-Time",0),CI9*(1+$D$3))} -> 0 | CK9: {=IFERROR(_xlfn.IFS(VALUE(MID(CK$5,6,1))>$D$2,0,$CC9="Annual",1,CJ9=12,12,$CC9="Monthly V",CJ9*(1+$D$3),$CC9="Monthly F",12,$CC9="One-Time",0),CJ9*(1+$D$3))} -> 0 | CL9: {=IFERROR(_xlfn.IFS(VALUE(MID(CL$5,6,1))>$D$2,0,$CC9="Annual",1,CK9=12,12,$CC9="Monthly V",CK9*(1+$D$3),$CC9="Monthly F",12,$CC9="One-Time",0),CK9*(1+$D$3))} -> 0 | CM9: {=IFERROR(_xlfn.IFS(VALUE(MID(CM$5,6,1))>$D$2,0,$CC9="Annual",1,CL9=12,12,$CC9="Monthly V",CL9*(1+$D$3),$CC9="Monthly F",12,$CC9="One-Time",0),CL9*(1+$D$3))} -> 0 | CN9: {=IFERROR(_xlfn.IFS(VALUE(MID(CN$5,6,2))>$D$2,0,$CC9="Annual",1,CM9=12,12,$CC9="Monthly V",CM9*(1+$D$3),$CC9="Monthly F",12,$CC9="One-Time",0),CM9*(1+$D$3))} -> 0 | CQ9: =CR9/12 -> 0 | CR9: =IFERROR(CE9*$CP9,0) -> 0 | CS9: =IFERROR(CF9*$CP9,0) -> 0 | CT9: =IFERROR(CG9*$CP9,0) -> 0 | CU9: =IFERROR(CH9*$CP9,0) -> 0 | CV9: =IFERROR(CI9*$CP9,0) -> 0 | CW9: =IFERROR(CJ9*$CP9,0) -> 0 | CX9: =IFERROR(CK9*$CP9,0) -> 0 | CY9: =IFERROR(CL9*$CP9,0) -> 0 | ... DA9: =IFERROR(CN9*$CP9,0) -> 0 | DC9: =IF(VALUE(MID(DC$5,6,1))<=$D$2,((1+$CP$3)^1-1)*CS9,0) -> 0 | DD9: =IF(VALUE(MID(DD$5,6,1))<=$D$2,((1+$CP$3)^2-1)*CT9,0) -> 0 | DE9: =IF(VALUE(MID(DE$5,6,1))<=$D$2,((1+$CP$3)^3-1)*CU9,0) -> 0 | DF9: =IF(VALUE(MID(DF$5,6,1))<=$D$2,((1+$CP$3)^4-1)*CV9,0) -> 0 | DG9: =IF(VALUE(MID(DG$5,6,1))<=$D$2,((1+$CP$3)^5-1)*CW9,0) -> 0 | DH9: =IF(VALUE(MID(DH$5,6,1))<=$D$2,((1+$CP$3)^6-1)*CX9,0) -> 0 | DI9: =IF(VALUE(MID(DI$5,6,1))<=$D$2,((1+$CP$3)^7-1)*CY9,0) -> 0 | DJ9: =IF(VALUE(MID(DJ$5,6,1))<=$D$2,((1+$CP$3)^8-1)*CZ9,0) -> 0 | DK9: =IF(VALUE(MID(DK$5,6,2))<=$D$2,((1+$CP$3)^9-1)*DA9,0) -> 0 | DL9: =SUM(DB9:DK9) -> 0 | DM9: =SUM(DL9,CR9:DA9) -> 0
B10: Monthly F | C10: 1 | D10: =IFERROR(AVERAGE(C10:C10),0) -> 1 | E10: 0 | F10: 0 | G10: 0 | H10: {=IFERROR(_xlfn.IFS(VALUE(MID(H$5,6,1))>$D$2,0,$B10="Annual",1,G10=12,12,$B10="Monthly V",G10*(1+$D$3),$B10="Monthly F",12,$B10="One-Time",0),G10*(1+$D$3))} -> 12 | I10: 0 | J10: 0 | K10: 0 | L10: 0 | M10: 0 | N10: 0 | O10: Year 4 CORE PROCESSING (Bundle) | P10: HORIZON CORE ACCOUNT PROCESSING | Q10: 28000 | R10: =S10/12 -> 0 | S10: =IFERROR($Q10*E10,0) -> 0 | T10: =IFERROR($Q10*F10,0) -> 0 | U10: =IFERROR($Q10*G10,0) -> 0 | V10: =IFERROR($Q10*H10,0) -> 336000 | W10: =IFERROR($Q10*I10,0) -> 0 | X10: =IFERROR($Q10*J10,0) -> 0 | Y10: =IFERROR($Q10*K10,0) -> 0 | Z10: =IFERROR($Q10*L10,0) -> 0 | ... AB10: =IFERROR($Q10*N10,0) -> 0 | AD10: 0 | AE10: 0 | AF10: 0 | AG10: 0 | AH10: 0 | AI10: 0 | AJ10: 0 | AK10: 0 | AL10: 0 | AM10: =SUM(AC10:AL10) -> 0 | AN10: =SUM(AM10,S10:AB10) -> 336000 | AP10: Monthly V | AQ10: 5000 | AR10: =IF($AP10="Annual",1,IF($AP10="Monthly F",12,IF($AP10="Monthly V",AQ10*12,IF($AP10="One-Time",1,AQ10*12)))) -> 60000 | AS10: {=IFERROR(_xlfn.IFS(VALUE(MID(AS$5,6,1))>$D$2,0,$AP10="Annual",1,AR10=12,12,$AP10="Monthly V",AR10*(1+$BD$2),$AP10="Monthly F",12,$AP10="One-Time",0),AR10*(1+$BD$2))} -> 60000 | AT10: {=IFERROR(_xlfn.IFS(VALUE(MID(AT$5,6,1))>$D$2,0,$AP10="Annual",1,AS10=12,12,$AP10="Monthly V",AS10*(1+$BD$2),$AP10="Monthly F",12,$AP10="One-Time",0),AS10*(1+$BD$2))} -> 60000 | AU10: {=IFERROR(_xlfn.IFS(VALUE(MID(AU$5,6,1))>$D$2,0,$AP10="Annual",1,AT10=12,12,$AP10="Monthly V",AT10*(1+$BD$2),$AP10="Monthly F",12,$AP10="One-Time",0),AT10*(1+$BD$2))} -> 60000 | AV10: {=IFERROR(_xlfn.IFS(VALUE(MID(AV$5,6,1))>$D$2,0,$AP10="Annual",1,AU10=12,12,$AP10="Monthly V",AU10*(1+$BD$2),$AP10="Monthly F",12,$AP10="One-Time",0),AU10*(1+$BD$2))} -> 60000 | AW10: {=IFERROR(_xlfn.IFS(VALUE(MID(AW$5,6,1))>$D$2,0,$AP10="Annual",1,AV10=12,12,$AP10="Monthly V",AV10*(1+$BD$2),$AP10="Monthly F",12,$AP10="One-Time",0),AV10*(1+$BD$2))} -> 60000 | AX10: {=IFERROR(_xlfn.IFS(VALUE(MID(AX$5,6,1))>$D$2,0,$AP10="Annual",1,AW10=12,12,$AP10="Monthly V",AW10*(1+$BD$2),$AP10="Monthly F",12,$AP10="One-Time",0),AW10*(1+$BD$2))} -> 60000 | AY10: {=IFERROR(_xlfn.IFS(VALUE(MID(AY$5,6,1))>$D$2,0,$AP10="Annual",1,AX10=12,12,$AP10="Monthly V",AX10*(1+$D$3),$AP10="Monthly F",12,$AP10="One-Time",0),AX10*(1+$D$3))} -> 0 | AZ10: {=IFERROR(_xlfn.IFS(VALUE(MID(AZ$5,6,1))>$D$2,0,$AP10="Annual",1,AY10=12,12,$AP10="Monthly V",AY10*(1+$D$3),$AP10="Monthly F",12,$AP10="One-Time",0),AY10*(1+$D$3))} -> 0 | BA10: {=IFERROR(_xlfn.IFS(VALUE(MID(BA$5,6,2))>$D$2,0,$AP10="Annual",1,AZ10=12,12,$AP10="Monthly V",AZ10*(1+$D$3),$AP10="Monthly F",12,$AP10="One-Time",0),AZ10*(1+$D$3))} -> 0 | BB10: Hosted Xperience | BC10: Xperience | BD10: 0.0225 | BE10: =BF10/12 -> 112.5 | BF10: =IFERROR(AR10*$BD10,0) -> 1350 | BG10: =IFERROR(AS10*$BD10,0) -> 1350 | BH10: =IFERROR(AT10*$BD10,0) -> 1350 | BI10: =BH10*1.03 -> 1390.5 | BJ10: =BI10*1.03 -> 1432.215 | BK10: =BJ10*1.03 -> 1475.1815 | BL10: =BK10*1.03 -> 1519.4369 | BM10: =IFERROR(AY10*$BD10,0) -> 0 | BN10: =IFERROR(AZ10*$BD10,0) -> 0 | BO10: =IFERROR(BA10*$BD10,0) -> 0 | BQ10: =IF(VALUE(MID(BQ$5,6,1))<=$D$2,((1+$BD$3)^1-1)*BG10,0) -> 40.5 | BR10: =IF(VALUE(MID(BR$5,6,1))<=$D$2,((1+$BD$3)^2-1)*BH10,0) -> 82.215 | BS10: =IF(VALUE(MID(BS$5,6,1))<=$D$2,((1+$BD$3)^3-1)*BI10,0) -> 128.93689 | BT10: =IF(VALUE(MID(BT$5,6,1))<=$D$2,((1+$BD$3)^4-1)*BJ10,0) -> 179.7556 | BU10: =IF(VALUE(MID(BU$5,6,1))<=$D$2,((1+$BD$3)^5-1)*BK10,0) -> 234.95816 | BV10: =IF(VALUE(MID(BV$5,6,1))<=$D$2,((1+$BD$3)^6-1)*BL10,0) -> 294.85022 | BW10: =IF(VALUE(MID(BW$5,6,1))<=$D$2,((1+$BD$3)^7-1)*BM10,0) -> 0 | BX10: =IF(VALUE(MID(BX$5,6,1))<=$D$2,((1+$BD$3)^8-1)*BN10,0) -> 0 | BY10: =IF(VALUE(MID(BY$5,6,2))<=$D$2,((1+$BD$3)^9-1)*BO10,0) -> 0 | BZ10: =SUM(BP10:BY10) -> 961.21587 | CA10: =SUM(BZ10,BF10:BO10) -> 10828.549 | CE10: =IF($CC10="Annual",1,IF($CC10="Monthly F",12,IF($CC10="Monthly V",CD10*12,IF($CC10="One-Time",1,CD10*12)))) -> 0 | CF10: {=IFERROR(_xlfn.IFS(VALUE(MID(CF$5,6,1))>$D$2,0,$CC10="Annual",1,CE10=12,12,$CC10="Monthly V",CE10*(1+$D$3),$CC10="Monthly F",12,$CC10="One-Time",0),CE10*(1+$D$3))} -> 0 | CG10: {=IFERROR(_xlfn.IFS(VALUE(MID(CG$5,6,1))>$D$2,0,$CC10="Annual",1,CF10=12,12,$CC10="Monthly V",CF10*(1+$D$3),$CC10="Monthly F",12,$CC10="One-Time",0),CF10*(1+$D$3))} -> 0 | CH10: {=IFERROR(_xlfn.IFS(VALUE(MID(CH$5,6,1))>$D$2,0,$CC10="Annual",1,CG10=12,12,$CC10="Monthly V",CG10*(1+$D$3),$CC10="Monthly F",12,$CC10="One-Time",0),CG10*(1+$D$3))} -> 0 | CI10: {=IFERROR(_xlfn.IFS(VALUE(MID(CI$5,6,1))>$D$2,0,$CC10="Annual",1,CH10=12,12,$CC10="Monthly V",CH10*(1+$D$3),$CC10="Monthly F",12,$CC10="One-Time",0),CH10*(1+$D$3))} -> 0 | CJ10: {=IFERROR(_xlfn.IFS(VALUE(MID(CJ$5,6,1))>$D$2,0,$CC10="Annual",1,CI10=12,12,$CC10="Monthly V",CI10*(1+$D$3),$CC10="Monthly F",12,$CC10="One-Time",0),CI10*(1+$D$3))} -> 0 | CK10: {=IFERROR(_xlfn.IFS(VALUE(MID(CK$5,6,1))>$D$2,0,$CC10="Annual",1,CJ10=12,12,$CC10="Monthly V",CJ10*(1+$D$3),$CC10="Monthly F",12,$CC10="One-Time",0),CJ10*(1+$D$3))} -> 0 | CL10: {=IFERROR(_xlfn.IFS(VALUE(MID(CL$5,6,1))>$D$2,0,$CC10="Annual",1,CK10=12,12,$CC10="Monthly V",CK10*(1+$D$3),$CC10="Monthly F",12,$CC10="One-Time",0),CK10*(1+$D$3))} -> 0 | CM10: {=IFERROR(_xlfn.IFS(VALUE(MID(CM$5,6,1))>$D$2,0,$CC10="Annual",1,CL10=12,12,$CC10="Monthly V",CL10*(1+$D$3),$CC10="Monthly F",12,$CC10="One-Time",0),CL10*(1+$D$3))} -> 0 | CN10: {=IFERROR(_xlfn.IFS(VALUE(MID(CN$5,6,2))>$D$2,0,$CC10="Annual",1,CM10=12,12,$CC10="Monthly V",CM10*(1+$D$3),$CC10="Monthly F",12,$CC10="One-Time",0),CM10*(1+$D$3))} -> 0 | CQ10: =CR10/12 -> 0 | CR10: =IFERROR(CE10*$CP10,0) -> 0 | CS10: =IFERROR(CF10*$CP10,0) -> 0 | CT10: =IFERROR(CG10*$CP10,0) -> 0 | CU10: =IFERROR(CH10*$CP10,0) -> 0 | CV10: =IFERROR(CI10*$CP10,0) -> 0 | CW10: =IFERROR(CJ10*$CP10,0) -> 0 | CX10: =IFERROR(CK10*$CP10,0) -> 0 | CY10: =IFERROR(CL10*$CP10,0) -> 0 | ... DA10: =IFERROR(CN10*$CP10,0) -> 0 | DC10: =IF(VALUE(MID(DC$5,6,1))<=$D$2,((1+$CP$3)^1-1)*CS10,0) -> 0 | DD10: =IF(VALUE(MID(DD$5,6,1))<=$D$2,((1+$CP$3)^2-1)*CT10,0) -> 0 | DE10: =IF(VALUE(MID(DE$5,6,1))<=$D$2,((1+$CP$3)^3-1)*CU10,0) -> 0 | DF10: =IF(VALUE(MID(DF$5,6,1))<=$D$2,((1+$CP$3)^4-1)*CV10,0) -> 0 | DG10: =IF(VALUE(MID(DG$5,6,1))<=$D$2,((1+$CP$3)^5-1)*CW10,0) -> 0 | DH10: =IF(VALUE(MID(DH$5,6,1))<=$D$2,((1+$CP$3)^6-1)*CX10,0) -> 0 | DI10: =IF(VALUE(MID(DI$5,6,1))<=$D$2,((1+$CP$3)^7-1)*CY10,0) -> 0 | DJ10: =IF(VALUE(MID(DJ$5,6,1))<=$D$2,((1+$CP$3)^8-1)*CZ10,0) -> 0 | DK10: =IF(VALUE(MID(DK$5,6,2))<=$D$2,((1+$CP$3)^9-1)*DA10,0) -> 0 | DL10: =SUM(DB10:DK10) -> 0 | DM10: =SUM(DL10,CR10:DA10) -> 0
B11: Monthly F | C11: 1 | D11: =IFERROR(AVERAGE(C11:C11),0) -> 1 | E11: 0 | F11: 0 | G11: 0 | H11: 0 | I11: {=IFERROR(_xlfn.IFS(VALUE(MID(I$5,6,1))>$D$2,0,$B11="Annual",1,H11=12,12,$B11="Monthly V",H11*(1+$D$3),$B11="Monthly F",12,$B11="One-Time",0),H11*(1+$D$3))} -> 12 | J11: 0 | K11: 0 | L11: 0 | M11: 0 | N11: 0 | O11: Year 5 CORE PROCESSING (Bundle) | P11: HORIZON CORE ACCOUNT PROCESSING | Q11: 35000 | R11: =S11/12 -> 0 | S11: =IFERROR($Q11*E11,0) -> 0 | T11: =IFERROR($Q11*F11,0) -> 0 | U11: =IFERROR($Q11*G11,0) -> 0 | V11: =IFERROR($Q11*H11,0) -> 0 | W11: =IFERROR($Q11*I11,0) -> 420000 | X11: =IFERROR($Q11*J11,0) -> 0 | Y11: =IFERROR($Q11*K11,0) -> 0 | Z11: =IFERROR($Q11*L11,0) -> 0 | ... AB11: =IFERROR($Q11*N11,0) -> 0 | AD11: 0 | AE11: 0 | AF11: 0 | AG11: 0 | AH11: 0 | AI11: 0 | AJ11: 0 | AK11: 0 | AL11: 0 | AM11: =SUM(AC11:AL11) -> 0 | AN11: =SUM(AM11,S11:AB11) -> 420000 | AP11: Monthly V | AQ11: 5000 | AR11: =IF($AP11="Annual",1,IF($AP11="Monthly F",12,IF($AP11="Monthly V",AQ11*12,IF($AP11="One-Time",1,AQ11*12)))) -> 60000 | AS11: {=IFERROR(_xlfn.IFS(VALUE(MID(AS$5,6,1))>$D$2,0,$AP11="Annual",1,AR11=12,12,$AP11="Monthly V",AR11*(1+$BD$2),$AP11="Monthly F",12,$AP11="One-Time",0),AR11*(1+$BD$2))} -> 60000 | AT11: {=IFERROR(_xlfn.IFS(VALUE(MID(AT$5,6,1))>$D$2,0,$AP11="Annual",1,AS11=12,12,$AP11="Monthly V",AS11*(1+$BD$2),$AP11="Monthly F",12,$AP11="One-Time",0),AS11*(1+$BD$2))} -> 60000 | AU11: {=IFERROR(_xlfn.IFS(VALUE(MID(AU$5,6,1))>$D$2,0,$AP11="Annual",1,AT11=12,12,$AP11="Monthly V",AT11*(1+$BD$2),$AP11="Monthly F",12,$AP11="One-Time",0),AT11*(1+$BD$2))} -> 60000 | AV11: {=IFERROR(_xlfn.IFS(VALUE(MID(AV$5,6,1))>$D$2,0,$AP11="Annual",1,AU11=12,12,$AP11="Monthly V",AU11*(1+$BD$2),$AP11="Monthly F",12,$AP11="One-Time",0),AU11*(1+$BD$2))} -> 60000 | AW11: {=IFERROR(_xlfn.IFS(VALUE(MID(AW$5,6,1))>$D$2,0,$AP11="Annual",1,AV11=12,12,$AP11="Monthly V",AV11*(1+$BD$2),$AP11="Monthly F",12,$AP11="One-Time",0),AV11*(1+$BD$2))} -> 60000 | AX11: {=IFERROR(_xlfn.IFS(VALUE(MID(AX$5,6,1))>$D$2,0,$AP11="Annual",1,AW11=12,12,$AP11="Monthly V",AW11*(1+$BD$2),$AP11="Monthly F",12,$AP11="One-Time",0),AW11*(1+$BD$2))} -> 60000 | AY11: {=IFERROR(_xlfn.IFS(VALUE(MID(AY$5,6,1))>$D$2,0,$AP11="Annual",1,AX11=12,12,$AP11="Monthly V",AX11*(1+$D$3),$AP11="Monthly F",12,$AP11="One-Time",0),AX11*(1+$D$3))} -> 0 | AZ11: {=IFERROR(_xlfn.IFS(VALUE(MID(AZ$5,6,1))>$D$2,0,$AP11="Annual",1,AY11=12,12,$AP11="Monthly V",AY11*(1+$D$3),$AP11="Monthly F",12,$AP11="One-Time",0),AY11*(1+$D$3))} -> 0 | BA11: {=IFERROR(_xlfn.IFS(VALUE(MID(BA$5,6,2))>$D$2,0,$AP11="Annual",1,AZ11=12,12,$AP11="Monthly V",AZ11*(1+$D$3),$AP11="Monthly F",12,$AP11="One-Time",0),AZ11*(1+$D$3))} -> 0 | BB11: OnBoard Deposits | BC11: OnBoard | BD11: 0.1703 | BE11: =BF11/12 -> 851.5 | BF11: =IFERROR(AR11*$BD11,0) -> 10218 | BG11: =IFERROR(AS11*$BD11,0) -> 10218 | BH11: =IFERROR(AT11*$BD11,0) -> 10218 | BI11: =BH11*1.03 -> 10524.54 | BJ11: =BI11*1.03 -> 10840.276 | BK11: =BJ11*1.03 -> 11165.484 | BL11: =BK11*1.03 -> 11500.449 | BM11: =IFERROR(AY11*$BD11,0) -> 0 | BN11: =IFERROR(AZ11*$BD11,0) -> 0 | BO11: =IFERROR(BA11*$BD11,0) -> 0 | BQ11: =IF(VALUE(MID(BQ$5,6,1))<=$D$2,((1+$BD$3)^1-1)*BG11,0) -> 306.54 | BR11: =IF(VALUE(MID(BR$5,6,1))<=$D$2,((1+$BD$3)^2-1)*BH11,0) -> 622.2762 | BS11: =IF(VALUE(MID(BS$5,6,1))<=$D$2,((1+$BD$3)^3-1)*BI11,0) -> 975.90902 | BT11: =IF(VALUE(MID(BT$5,6,1))<=$D$2,((1+$BD$3)^4-1)*BJ11,0) -> 1360.5502 | BU11: =IF(VALUE(MID(BU$5,6,1))<=$D$2,((1+$BD$3)^5-1)*BK11,0) -> 1778.3722 | BV11: =IF(VALUE(MID(BV$5,6,1))<=$D$2,((1+$BD$3)^6-1)*BL11,0) -> 2231.6885 | BW11: =IF(VALUE(MID(BW$5,6,1))<=$D$2,((1+$BD$3)^7-1)*BM11,0) -> 0 | BX11: =IF(VALUE(MID(BX$5,6,1))<=$D$2,((1+$BD$3)^8-1)*BN11,0) -> 0 | BY11: =IF(VALUE(MID(BY$5,6,2))<=$D$2,((1+$BD$3)^9-1)*BO11,0) -> 0 | BZ11: =SUM(BP11:BY11) -> 7275.3361 | CA11: =SUM(BZ11,BF11:BO11) -> 81960.086 | CE11: =IF($CC11="Annual",1,IF($CC11="Monthly F",12,IF($CC11="Monthly V",CD11*12,IF($CC11="One-Time",1,CD11*12)))) -> 0 | CF11: {=IFERROR(_xlfn.IFS(VALUE(MID(CF$5,6,1))>$D$2,0,$CC11="Annual",1,CE11=12,12,$CC11="Monthly V",CE11*(1+$D$3),$CC11="Monthly F",12,$CC11="One-Time",0),CE11*(1+$D$3))} -> 0 | CG11: {=IFERROR(_xlfn.IFS(VALUE(MID(CG$5,6,1))>$D$2,0,$CC11="Annual",1,CF11=12,12,$CC11="Monthly V",CF11*(1+$D$3),$CC11="Monthly F",12,$CC11="One-Time",0),CF11*(1+$D$3))} -> 0 | CH11: {=IFERROR(_xlfn.IFS(VALUE(MID(CH$5,6,1))>$D$2,0,$CC11="Annual",1,CG11=12,12,$CC11="Monthly V",CG11*(1+$D$3),$CC11="Monthly F",12,$CC11="One-Time",0),CG11*(1+$D$3))} -> 0 | CI11: {=IFERROR(_xlfn.IFS(VALUE(MID(CI$5,6,1))>$D$2,0,$CC11="Annual",1,CH11=12,12,$CC11="Monthly V",CH11*(1+$D$3),$CC11="Monthly F",12,$CC11="One-Time",0),CH11*(1+$D$3))} -> 0 | CJ11: {=IFERROR(_xlfn.IFS(VALUE(MID(CJ$5,6,1))>$D$2,0,$CC11="Annual",1,CI11=12,12,$CC11="Monthly V",CI11*(1+$D$3),$CC11="Monthly F",12,$CC11="One-Time",0),CI11*(1+$D$3))} -> 0 | CK11: {=IFERROR(_xlfn.IFS(VALUE(MID(CK$5,6,1))>$D$2,0,$CC11="Annual",1,CJ11=12,12,$CC11="Monthly V",CJ11*(1+$D$3),$CC11="Monthly F",12,$CC11="One-Time",0),CJ11*(1+$D$3))} -> 0 | CL11: {=IFERROR(_xlfn.IFS(VALUE(MID(CL$5,6,1))>$D$2,0,$CC11="Annual",1,CK11=12,12,$CC11="Monthly V",CK11*(1+$D$3),$CC11="Monthly F",12,$CC11="One-Time",0),CK11*(1+$D$3))} -> 0 | CM11: {=IFERROR(_xlfn.IFS(VALUE(MID(CM$5,6,1))>$D$2,0,$CC11="Annual",1,CL11=12,12,$CC11="Monthly V",CL11*(1+$D$3),$CC11="Monthly F",12,$CC11="One-Time",0),CL11*(1+$D$3))} -> 0 | CN11: {=IFERROR(_xlfn.IFS(VALUE(MID(CN$5,6,2))>$D$2,0,$CC11="Annual",1,CM11=12,12,$CC11="Monthly V",CM11*(1+$D$3),$CC11="Monthly F",12,$CC11="One-Time",0),CM11*(1+$D$3))} -> 0 | CQ11: =CR11/12 -> 0 | CR11: =IFERROR(CE11*$CP11,0) -> 0 | CS11: =IFERROR(CF11*$CP11,0) -> 0 | CT11: =IFERROR(CG11*$CP11,0) -> 0 | CU11: =IFERROR(CH11*$CP11,0) -> 0 | CV11: =IFERROR(CI11*$CP11,0) -> 0 | CW11: =IFERROR(CJ11*$CP11,0) -> 0 | CX11: =IFERROR(CK11*$CP11,0) -> 0 | CY11: =IFERROR(CL11*$CP11,0) -> 0 | ... DA11: =IFERROR(CN11*$CP11,0) -> 0 | DC11: =IF(VALUE(MID(DC$5,6,1))<=$D$2,((1+$CP$3)^1-1)*CS11,0) -> 0 | DD11: =IF(VALUE(MID(DD$5,6,1))<=$D$2,((1+$CP$3)^2-1)*CT11,0) -> 0 | DE11: =IF(VALUE(MID(DE$5,6,1))<=$D$2,((1+$CP$3)^3-1)*CU11,0) -> 0 | DF11: =IF(VALUE(MID(DF$5,6,1))<=$D$2,((1+$CP$3)^4-1)*CV11,0) -> 0 | DG11: =IF(VALUE(MID(DG$5,6,1))<=$D$2,((1+$CP$3)^5-1)*CW11,0) -> 0 | DH11: =IF(VALUE(MID(DH$5,6,1))<=$D$2,((1+$CP$3)^6-1)*CX11,0) -> 0 | DI11: =IF(VALUE(MID(DI$5,6,1))<=$D$2,((1+$CP$3)^7-1)*CY11,0) -> 0 | DJ11: =IF(VALUE(MID(DJ$5,6,1))<=$D$2,((1+$CP$3)^8-1)*CZ11,0) -> 0 | DK11: =IF(VALUE(MID(DK$5,6,2))<=$D$2,((1+$CP$3)^9-1)*DA11,0) -> 0 | DL11: =SUM(DB11:DK11) -> 0 | DM11: =SUM(DL11,CR11:DA11) -> 0
B12: Monthly F | C12: 1 | D12: =IFERROR(AVERAGE(C12:C12),0) -> 1 | E12: 0 | F12: 0 | G12: 0 | H12: 0 | I12: 0 | J12: {=IFERROR(_xlfn.IFS(VALUE(MID(J$5,6,1))>$D$2,0,$B12="Annual",1,I12=12,12,$B12="Monthly V",I12*(1+$D$3),$B12="Monthly F",12,$B12="One-Time",0),I12*(1+$D$3))} -> 12 | K12: 0 | L12: 0 | M12: 0 | N12: 0 | O12: Year 6 CORE PROCESSING (Bundle) - CPI Increase Begins | P12: HORIZON CORE ACCOUNT PROCESSING | Q12: 35000 | R12: =S12/12 -> 0 | S12: =IFERROR($Q12*E12,0) -> 0 | T12: =IFERROR($Q12*F12,0) -> 0 | U12: =IFERROR($Q12*G12,0) -> 0 | V12: =IFERROR($Q12*H12,0) -> 0 | W12: =IFERROR($Q12*I12,0) -> 0 | X12: =IFERROR($Q12*J12,0) -> 420000 | Y12: =IFERROR($Q12*K12,0) -> 0 | Z12: =IFERROR($Q12*L12,0) -> 0 | ... AB12: =IFERROR($Q12*N12,0) -> 0 | AD12: =IF(VALUE(MID(AD$5,6,1))<=$D$2,((1+$Q$3)^1-1)*T12,0) -> 0 | AE12: =IF(VALUE(MID(AE$5,6,1))<=$D$2,((1+$Q$3)^2-1)*U12,0) -> 0 | AF12: =IF(VALUE(MID(AF$5,6,1))<=$D$2,((1+$Q$3)^3-1)*V12,0) -> 0 | AG12: =IF(VALUE(MID(AG$5,6,1))<=$D$2,((1+$Q$3)^4-1)*W12,0) -> 0 | AH12: =IF(VALUE(MID(AH$5,6,1))<=$D$2,((1+$Q$2)^1-1)*X12,0) -> 25200 | AI12: =IF(VALUE(MID(AI$5,6,1))<=$D$2,((1+$Q$3)^6-1)*Y12,0) -> 0 | AJ12: =IF(VALUE(MID(AJ$5,6,1))<=$D$2,((1+$Q$3)^7-1)*Z12,0) -> 0 | AK12: =IF(VALUE(MID(AK$5,6,1))<=$D$2,((1+$Q$3)^8-1)*AA12,0) -> 0 | AL12: =IF(VALUE(MID(AL$5,6,2))<=$D$2,((1+$Q$3)^9-1)*AB12,0) -> 0 | AM12: =SUM(AC12:AL12) -> 25200 | AN12: =SUM(AM12,S12:AB12) -> 445200 | AP12: Monthly V | AQ12: 5000 | AR12: =IF($AP12="Annual",1,IF($AP12="Monthly F",12,IF($AP12="Monthly V",AQ12*12,IF($AP12="One-Time",1,AQ12*12)))) -> 60000 | AS12: {=IFERROR(_xlfn.IFS(VALUE(MID(AS$5,6,1))>$D$2,0,$AP12="Annual",1,AR12=12,12,$AP12="Monthly V",AR12*(1+$BD$2),$AP12="Monthly F",12,$AP12="One-Time",0),AR12*(1+$BD$2))} -> 60000 | AT12: {=IFERROR(_xlfn.IFS(VALUE(MID(AT$5,6,1))>$D$2,0,$AP12="Annual",1,AS12=12,12,$AP12="Monthly V",AS12*(1+$BD$2),$AP12="Monthly F",12,$AP12="One-Time",0),AS12*(1+$BD$2))} -> 60000 | AU12: {=IFERROR(_xlfn.IFS(VALUE(MID(AU$5,6,1))>$D$2,0,$AP12="Annual",1,AT12=12,12,$AP12="Monthly V",AT12*(1+$BD$2),$AP12="Monthly F",12,$AP12="One-Time",0),AT12*(1+$BD$2))} -> 60000 | AV12: {=IFERROR(_xlfn.IFS(VALUE(MID(AV$5,6,1))>$D$2,0,$AP12="Annual",1,AU12=12,12,$AP12="Monthly V",AU12*(1+$BD$2),$AP12="Monthly F",12,$AP12="One-Time",0),AU12*(1+$BD$2))} -> 60000 | AW12: {=IFERROR(_xlfn.IFS(VALUE(MID(AW$5,6,1))>$D$2,0,$AP12="Annual",1,AV12=12,12,$AP12="Monthly V",AV12*(1+$BD$2),$AP12="Monthly F",12,$AP12="One-Time",0),AV12*(1+$BD$2))} -> 60000 | AX12: {=IFERROR(_xlfn.IFS(VALUE(MID(AX$5,6,1))>$D$2,0,$AP12="Annual",1,AW12=12,12,$AP12="Monthly V",AW12*(1+$BD$2),$AP12="Monthly F",12,$AP12="One-Time",0),AW12*(1+$BD$2))} -> 60000 | AY12: {=IFERROR(_xlfn.IFS(VALUE(MID(AY$5,6,1))>$D$2,0,$AP12="Annual",1,AX12=12,12,$AP12="Monthly V",AX12*(1+$D$3),$AP12="Monthly F",12,$AP12="One-Time",0),AX12*(1+$D$3))} -> 0 | AZ12: {=IFERROR(_xlfn.IFS(VALUE(MID(AZ$5,6,1))>$D$2,0,$AP12="Annual",1,AY12=12,12,$AP12="Monthly V",AY12*(1+$D$3),$AP12="Monthly F",12,$AP12="One-Time",0),AY12*(1+$D$3))} -> 0 | BA12: {=IFERROR(_xlfn.IFS(VALUE(MID(BA$5,6,2))>$D$2,0,$AP12="Annual",1,AZ12=12,12,$AP12="Monthly V",AZ12*(1+$D$3),$AP12="Monthly F",12,$AP12="One-Time",0),AZ12*(1+$D$3))} -> 0 | BB12: Teller Cash Recycler | BC12: Teller | BD12: 0.03 | BE12: =BF12/12 -> 150 | BF12: =IFERROR(AR12*$BD12,0) -> 1800 | BG12: =IFERROR(AS12*$BD12,0) -> 1800 | BH12: =IFERROR(AT12*$BD12,0) -> 1800 | BI12: =BH12*1.03 -> 1854 | BJ12: =BI12*1.03 -> 1909.62 | BK12: =BJ12*1.03 -> 1966.9086 | BL12: =BK12*1.03 -> 2025.9159 | BM12: =IFERROR(AY12*$BD12,0) -> 0 | BN12: =IFERROR(AZ12*$BD12,0) -> 0 | BO12: =IFERROR(BA12*$BD12,0) -> 0 | BQ12: =IF(VALUE(MID(BQ$5,6,1))<=$D$2,((1+$BD$3)^1-1)*BG12,0) -> 54 | BR12: =IF(VALUE(MID(BR$5,6,1))<=$D$2,((1+$BD$3)^2-1)*BH12,0) -> 109.62 | BS12: =IF(VALUE(MID(BS$5,6,1))<=$D$2,((1+$BD$3)^3-1)*BI12,0) -> 171.91586 | BT12: =IF(VALUE(MID(BT$5,6,1))<=$D$2,((1+$BD$3)^4-1)*BJ12,0) -> 239.67413 | BU12: =IF(VALUE(MID(BU$5,6,1))<=$D$2,((1+$BD$3)^5-1)*BK12,0) -> 313.27755 | BV12: =IF(VALUE(MID(BV$5,6,1))<=$D$2,((1+$BD$3)^6-1)*BL12,0) -> 393.13362 | BW12: =IF(VALUE(MID(BW$5,6,1))<=$D$2,((1+$BD$3)^7-1)*BM12,0) -> 0 | BX12: =IF(VALUE(MID(BX$5,6,1))<=$D$2,((1+$BD$3)^8-1)*BN12,0) -> 0 | BY12: =IF(VALUE(MID(BY$5,6,2))<=$D$2,((1+$BD$3)^9-1)*BO12,0) -> 0 | BZ12: =SUM(BP12:BY12) -> 1281.6212 | CA12: =SUM(BZ12,BF12:BO12) -> 14438.066 | CE12: =IF($CC12="Annual",1,IF($CC12="Monthly F",12,IF($CC12="Monthly V",CD12*12,IF($CC12="One-Time",1,CD12*12)))) -> 0 | CF12: {=IFERROR(_xlfn.IFS(VALUE(MID(CF$5,6,1))>$D$2,0,$CC12="Annual",1,CE12=12,12,$CC12="Monthly V",CE12*(1+$D$3),$CC12="Monthly F",12,$CC12="One-Time",0),CE12*(1+$D$3))} -> 0 | CG12: {=IFERROR(_xlfn.IFS(VALUE(MID(CG$5,6,1))>$D$2,0,$CC12="Annual",1,CF12=12,12,$CC12="Monthly V",CF12*(1+$D$3),$CC12="Monthly F",12,$CC12="One-Time",0),CF12*(1+$D$3))} -> 0 | CH12: {=IFERROR(_xlfn.IFS(VALUE(MID(CH$5,6,1))>$D$2,0,$CC12="Annual",1,CG12=12,12,$CC12="Monthly V",CG12*(1+$D$3),$CC12="Monthly F",12,$CC12="One-Time",0),CG12*(1+$D$3))} -> 0 | CI12: {=IFERROR(_xlfn.IFS(VALUE(MID(CI$5,6,1))>$D$2,0,$CC12="Annual",1,CH12=12,12,$CC12="Monthly V",CH12*(1+$D$3),$CC12="Monthly F",12,$CC12="One-Time",0),CH12*(1+$D$3))} -> 0 | CJ12: {=IFERROR(_xlfn.IFS(VALUE(MID(CJ$5,6,1))>$D$2,0,$CC12="Annual",1,CI12=12,12,$CC12="Monthly V",CI12*(1+$D$3),$CC12="Monthly F",12,$CC12="One-Time",0),CI12*(1+$D$3))} -> 0 | CK12: {=IFERROR(_xlfn.IFS(VALUE(MID(CK$5,6,1))>$D$2,0,$CC12="Annual",1,CJ12=12,12,$CC12="Monthly V",CJ12*(1+$D$3),$CC12="Monthly F",12,$CC12="One-Time",0),CJ12*(1+$D$3))} -> 0 | CL12: {=IFERROR(_xlfn.IFS(VALUE(MID(CL$5,6,1))>$D$2,0,$CC12="Annual",1,CK12=12,12,$CC12="Monthly V",CK12*(1+$D$3),$CC12="Monthly F",12,$CC12="One-Time",0),CK12*(1+$D$3))} -> 0 | CM12: {=IFERROR(_xlfn.IFS(VALUE(MID(CM$5,6,1))>$D$2,0,$CC12="Annual",1,CL12=12,12,$CC12="Monthly V",CL12*(1+$D$3),$CC12="Monthly F",12,$CC12="One-Time",0),CL12*(1+$D$3))} -> 0 | CN12: {=IFERROR(_xlfn.IFS(VALUE(MID(CN$5,6,2))>$D$2,0,$CC12="Annual",1,CM12=12,12,$CC12="Monthly V",CM12*(1+$D$3),$CC12="Monthly F",12,$CC12="One-Time",0),CM12*(1+$D$3))} -> 0 | CQ12: =CR12/12 -> 0 | CR12: =IFERROR(CE12*$CP12,0) -> 0 | CS12: =IFERROR(CF12*$CP12,0) -> 0 | CT12: =IFERROR(CG12*$CP12,0) -> 0 | CU12: =IFERROR(CH12*$CP12,0) -> 0 | CV12: =IFERROR(CI12*$CP12,0) -> 0 | CW12: =IFERROR(CJ12*$CP12,0) -> 0 | CX12: =IFERROR(CK12*$CP12,0) -> 0 | CY12: =IFERROR(CL12*$CP12,0) -> 0 | ... DA12: =IFERROR(CN12*$CP12,0) -> 0 | DC12: =IF(VALUE(MID(DC$5,6,1))<=$D$2,((1+$CP$3)^1-1)*CS12,0) -> 0 | DD12: =IF(VALUE(MID(DD$5,6,1))<=$D$2,((1+$CP$3)^2-1)*CT12,0) -> 0 | DE12: =IF(VALUE(MID(DE$5,6,1))<=$D$2,((1+$CP$3)^3-1)*CU12,0) -> 0 | DF12: =IF(VALUE(MID(DF$5,6,1))<=$D$2,((1+$CP$3)^4-1)*CV12,0) -> 0 | DG12: =IF(VALUE(MID(DG$5,6,1))<=$D$2,((1+$CP$3)^5-1)*CW12,0) -> 0 | DH12: =IF(VALUE(MID(DH$5,6,1))<=$D$2,((1+$CP$3)^6-1)*CX12,0) -> 0 | DI12: =IF(VALUE(MID(DI$5,6,1))<=$D$2,((1+$CP$3)^7-1)*CY12,0) -> 0 | DJ12: =IF(VALUE(MID(DJ$5,6,1))<=$D$2,((1+$CP$3)^8-1)*CZ12,0) -> 0 | DK12: =IF(VALUE(MID(DK$5,6,2))<=$D$2,((1+$CP$3)^9-1)*DA12,0) -> 0 | DL12: =SUM(DB12:DK12) -> 0 | DM12: =SUM(DL12,CR12:DA12) -> 0
B13: Monthly F | C13: 1 | D13: =IFERROR(AVERAGE(C13:C13),0) -> 1 | E13: 0 | F13: 0 | G13: 0 | H13: 0 | I13: 0 | J13: 0 | K13: {=IFERROR(_xlfn.IFS(VALUE(MID(K$5,6,1))>$D$2,0,$B13="Annual",1,J13=12,12,$B13="Monthly V",J13*(1+$D$3),$B13="Monthly F",12,$B13="One-Time",0),J13*(1+$D$3))} -> 12 | L13: 0 | M13: 0 | N13: 0 | O13: Year 7 CORE PROCESSING (Bundle) - CPI Increase | P13: HORIZON CORE ACCOUNT PROCESSING | Q13: =AN12/12 -> 37100 | R13: =S13/12 -> 0 | S13: =IFERROR($Q13*E13,0) -> 0 | T13: =IFERROR($Q13*F13,0) -> 0 | U13: =IFERROR($Q13*G13,0) -> 0 | V13: =IFERROR($Q13*H13,0) -> 0 | W13: =IFERROR($Q13*I13,0) -> 0 | X13: =IFERROR($Q13*J13,0) -> 0 | Y13: =IFERROR($Q13*K13,0) -> 445200 | Z13: =IFERROR($Q13*L13,0) -> 0 | ... AB13: =IFERROR($Q13*N13,0) -> 0 | AD13: =IF(VALUE(MID(AD$5,6,1))<=$D$2,((1+$Q$3)^1-1)*T13,0) -> 0 | AE13: =IF(VALUE(MID(AE$5,6,1))<=$D$2,((1+$Q$3)^2-1)*U13,0) -> 0 | AF13: =IF(VALUE(MID(AF$5,6,1))<=$D$2,((1+$Q$3)^3-1)*V13,0) -> 0 | AG13: =IF(VALUE(MID(AG$5,6,1))<=$D$2,((1+$Q$3)^4-1)*W13,0) -> 0 | AH13: =IF(VALUE(MID(AH$5,6,1))<=$D$2,((1+$Q$2)^1-1)*X13,0) -> 0 | AI13: =IF(VALUE(MID(AI$5,6,1))<=$D$2,((1+$Q$2)^1-1)*Y13,0) -> 26712 | AJ13: =IF(VALUE(MID(AJ$5,6,1))<=$D$2,((1+$Q$3)^7-1)*Z13,0) -> 0 | AK13: =IF(VALUE(MID(AK$5,6,1))<=$D$2,((1+$Q$3)^8-1)*AA13,0) -> 0 | AL13: =IF(VALUE(MID(AL$5,6,2))<=$D$2,((1+$Q$3)^9-1)*AB13,0) -> 0 | AM13: =SUM(AC13:AL13) -> 26712 | AN13: =SUM(AM13,S13:AB13) -> 471912 | AP13: Monthly V | AQ13: 5000 | AR13: =IF($AP13="Annual",1,IF($AP13="Monthly F",12,IF($AP13="Monthly V",AQ13*12,IF($AP13="One-Time",1,AQ13*12)))) -> 60000 | AS13: {=IFERROR(_xlfn.IFS(VALUE(MID(AS$5,6,1))>$D$2,0,$AP13="Annual",1,AR13=12,12,$AP13="Monthly V",AR13*(1+$BD$2),$AP13="Monthly F",12,$AP13="One-Time",0),AR13*(1+$BD$2))} -> 60000 | AT13: {=IFERROR(_xlfn.IFS(VALUE(MID(AT$5,6,1))>$D$2,0,$AP13="Annual",1,AS13=12,12,$AP13="Monthly V",AS13*(1+$BD$2),$AP13="Monthly F",12,$AP13="One-Time",0),AS13*(1+$BD$2))} -> 60000 | AU13: {=IFERROR(_xlfn.IFS(VALUE(MID(AU$5,6,1))>$D$2,0,$AP13="Annual",1,AT13=12,12,$AP13="Monthly V",AT13*(1+$BD$2),$AP13="Monthly F",12,$AP13="One-Time",0),AT13*(1+$BD$2))} -> 60000 | AV13: {=IFERROR(_xlfn.IFS(VALUE(MID(AV$5,6,1))>$D$2,0,$AP13="Annual",1,AU13=12,12,$AP13="Monthly V",AU13*(1+$BD$2),$AP13="Monthly F",12,$AP13="One-Time",0),AU13*(1+$BD$2))} -> 60000 | AW13: {=IFERROR(_xlfn.IFS(VALUE(MID(AW$5,6,1))>$D$2,0,$AP13="Annual",1,AV13=12,12,$AP13="Monthly V",AV13*(1+$BD$2),$AP13="Monthly F",12,$AP13="One-Time",0),AV13*(1+$BD$2))} -> 60000 | AX13: {=IFERROR(_xlfn.IFS(VALUE(MID(AX$5,6,1))>$D$2,0,$AP13="Annual",1,AW13=12,12,$AP13="Monthly V",AW13*(1+$BD$2),$AP13="Monthly F",12,$AP13="One-Time",0),AW13*(1+$BD$2))} -> 60000 | AY13: {=IFERROR(_xlfn.IFS(VALUE(MID(AY$5,6,1))>$D$2,0,$AP13="Annual",1,AX13=12,12,$AP13="Monthly V",AX13*(1+$D$3),$AP13="Monthly F",12,$AP13="One-Time",0),AX13*(1+$D$3))} -> 0 | AZ13: {=IFERROR(_xlfn.IFS(VALUE(MID(AZ$5,6,1))>$D$2,0,$AP13="Annual",1,AY13=12,12,$AP13="Monthly V",AY13*(1+$D$3),$AP13="Monthly F",12,$AP13="One-Time",0),AY13*(1+$D$3))} -> 0 | BA13: {=IFERROR(_xlfn.IFS(VALUE(MID(BA$5,6,2))>$D$2,0,$AP13="Annual",1,AZ13=12,12,$AP13="Monthly V",AZ13*(1+$D$3),$AP13="Monthly F",12,$AP13="One-Time",0),AZ13*(1+$D$3))} -> 0 | BB13: Teller CheckMaster Plus | BC13: Teller | BD13: 0.0135 | BE13: =BF13/12 -> 67.5 | BF13: =IFERROR(AR13*$BD13,0) -> 810 | BG13: =IFERROR(AS13*$BD13,0) -> 810 | BH13: =IFERROR(AT13*$BD13,0) -> 810 | BI13: =BH13*1.03 -> 834.3 | BJ13: =BI13*1.03 -> 859.329 | BK13: =BJ13*1.03 -> 885.10887 | BL13: =BK13*1.03 -> 911.66214 | BM13: =IFERROR(AY13*$BD13,0) -> 0 | BN13: =IFERROR(AZ13*$BD13,0) -> 0 | BO13: =IFERROR(BA13*$BD13,0) -> 0 | BQ13: =IF(VALUE(MID(BQ$5,6,1))<=$D$2,((1+$BD$3)^1-1)*BG13,0) -> 24.3 | BR13: =IF(VALUE(MID(BR$5,6,1))<=$D$2,((1+$BD$3)^2-1)*BH13,0) -> 49.329 | BS13: =IF(VALUE(MID(BS$5,6,1))<=$D$2,((1+$BD$3)^3-1)*BI13,0) -> 77.362136 | BT13: =IF(VALUE(MID(BT$5,6,1))<=$D$2,((1+$BD$3)^4-1)*BJ13,0) -> 107.85336 | BU13: =IF(VALUE(MID(BU$5,6,1))<=$D$2,((1+$BD$3)^5-1)*BK13,0) -> 140.9749 | BV13: =IF(VALUE(MID(BV$5,6,1))<=$D$2,((1+$BD$3)^6-1)*BL13,0) -> 176.91013 | BW13: =IF(VALUE(MID(BW$5,6,1))<=$D$2,((1+$BD$3)^7-1)*BM13,0) -> 0 | BX13: =IF(VALUE(MID(BX$5,6,1))<=$D$2,((1+$BD$3)^8-1)*BN13,0) -> 0 | BY13: =IF(VALUE(MID(BY$5,6,2))<=$D$2,((1+$BD$3)^9-1)*BO13,0) -> 0 | BZ13: =SUM(BP13:BY13) -> 576.72952 | CA13: =SUM(BZ13,BF13:BO13) -> 6497.1295 | CE13: =IF($CC13="Annual",1,IF($CC13="Monthly F",12,IF($CC13="Monthly V",CD13*12,IF($CC13="One-Time",1,CD13*12)))) -> 0 | CF13: {=IFERROR(_xlfn.IFS(VALUE(MID(CF$5,6,1))>$D$2,0,$CC13="Annual",1,CE13=12,12,$CC13="Monthly V",CE13*(1+$D$3),$CC13="Monthly F",12,$CC13="One-Time",0),CE13*(1+$D$3))} -> 0 | CG13: {=IFERROR(_xlfn.IFS(VALUE(MID(CG$5,6,1))>$D$2,0,$CC13="Annual",1,CF13=12,12,$CC13="Monthly V",CF13*(1+$D$3),$CC13="Monthly F",12,$CC13="One-Time",0),CF13*(1+$D$3))} -> 0 | CH13: {=IFERROR(_xlfn.IFS(VALUE(MID(CH$5,6,1))>$D$2,0,$CC13="Annual",1,CG13=12,12,$CC13="Monthly V",CG13*(1+$D$3),$CC13="Monthly F",12,$CC13="One-Time",0),CG13*(1+$D$3))} -> 0 | CI13: {=IFERROR(_xlfn.IFS(VALUE(MID(CI$5,6,1))>$D$2,0,$CC13="Annual",1,CH13=12,12,$CC13="Monthly V",CH13*(1+$D$3),$CC13="Monthly F",12,$CC13="One-Time",0),CH13*(1+$D$3))} -> 0 | CJ13: {=IFERROR(_xlfn.IFS(VALUE(MID(CJ$5,6,1))>$D$2,0,$CC13="Annual",1,CI13=12,12,$CC13="Monthly V",CI13*(1+$D$3),$CC13="Monthly F",12,$CC13="One-Time",0),CI13*(1+$D$3))} -> 0 | CK13: {=IFERROR(_xlfn.IFS(VALUE(MID(CK$5,6,1))>$D$2,0,$CC13="Annual",1,CJ13=12,12,$CC13="Monthly V",CJ13*(1+$D$3),$CC13="Monthly F",12,$CC13="One-Time",0),CJ13*(1+$D$3))} -> 0 | CL13: {=IFERROR(_xlfn.IFS(VALUE(MID(CL$5,6,1))>$D$2,0,$CC13="Annual",1,CK13=12,12,$CC13="Monthly V",CK13*(1+$D$3),$CC13="Monthly F",12,$CC13="One-Time",0),CK13*(1+$D$3))} -> 0 | CM13: {=IFERROR(_xlfn.IFS(VALUE(MID(CM$5,6,1))>$D$2,0,$CC13="Annual",1,CL13=12,12,$CC13="Monthly V",CL13*(1+$D$3),$CC13="Monthly F",12,$CC13="One-Time",0),CL13*(1+$D$3))} -> 0 | CN13: {=IFERROR(_xlfn.IFS(VALUE(MID(CN$5,6,2))>$D$2,0,$CC13="Annual",1,CM13=12,12,$CC13="Monthly V",CM13*(1+$D$3),$CC13="Monthly F",12,$CC13="One-Time",0),CM13*(1+$D$3))} -> 0 | CQ13: =CR13/12 -> 0 | CR13: =IFERROR(CE13*$CP13,0) -> 0 | CS13: =IFERROR(CF13*$CP13,0) -> 0 | CT13: =IFERROR(CG13*$CP13,0) -> 0 | CU13: =IFERROR(CH13*$CP13,0) -> 0 | CV13: =IFERROR(CI13*$CP13,0) -> 0 | CW13: =IFERROR(CJ13*$CP13,0) -> 0 | CX13: =IFERROR(CK13*$CP13,0) -> 0 | CY13: =IFERROR(CL13*$CP13,0) -> 0 | ... DA13: =IFERROR(CN13*$CP13,0) -> 0 | DC13: =IF(VALUE(MID(DC$5,6,1))<=$D$2,((1+$CP$3)^1-1)*CS13,0) -> 0 | DD13: =IF(VALUE(MID(DD$5,6,1))<=$D$2,((1+$CP$3)^2-1)*CT13,0) -> 0 | DE13: =IF(VALUE(MID(DE$5,6,1))<=$D$2,((1+$CP$3)^3-1)*CU13,0) -> 0 | DF13: =IF(VALUE(MID(DF$5,6,1))<=$D$2,((1+$CP$3)^4-1)*CV13,0) -> 0 | DG13: =IF(VALUE(MID(DG$5,6,1))<=$D$2,((1+$CP$3)^5-1)*CW13,0) -> 0 | DH13: =IF(VALUE(MID(DH$5,6,1))<=$D$2,((1+$CP$3)^6-1)*CX13,0) -> 0 | DI13: =IF(VALUE(MID(DI$5,6,1))<=$D$2,((1+$CP$3)^7-1)*CY13,0) -> 0 | DJ13: =IF(VALUE(MID(DJ$5,6,1))<=$D$2,((1+$CP$3)^8-1)*CZ13,0) -> 0 | DK13: =IF(VALUE(MID(DK$5,6,2))<=$D$2,((1+$CP$3)^9-1)*DA13,0) -> 0 | DL13: =SUM(DB13:DK13) -> 0 | DM13: =SUM(DL13,CR13:DA13) -> 0
D14: =IFERROR(AVERAGE(C14:C14),0) -> 0 | E14: =IF($B14="Annual",1,IF($B14="Monthly F",12,IF($B14="Monthly V",D14*12,IF($B14="One-Time",1,D14*12)))) -> 0 | F14: {=IFERROR(_xlfn.IFS(VALUE(MID(F$5,6,1))>$D$2,0,$B14="Annual",1,E14=12,12,$B14="Monthly V",E14*(1+$D$3),$B14="Monthly F",12,$B14="One-Time",0),E14*(1+$D$3))} -> 0 | G14: {=IFERROR(_xlfn.IFS(VALUE(MID(G$5,6,1))>$D$2,0,$B14="Annual",1,F14=12,12,$B14="Monthly V",F14*(1+$D$3),$B14="Monthly F",12,$B14="One-Time",0),F14*(1+$D$3))} -> 0 | H14: {=IFERROR(_xlfn.IFS(VALUE(MID(H$5,6,1))>$D$2,0,$B14="Annual",1,G14=12,12,$B14="Monthly V",G14*(1+$D$3),$B14="Monthly F",12,$B14="One-Time",0),G14*(1+$D$3))} -> 0 | I14: {=IFERROR(_xlfn.IFS(VALUE(MID(I$5,6,1))>$D$2,0,$B14="Annual",1,H14=12,12,$B14="Monthly V",H14*(1+$D$3),$B14="Monthly F",12,$B14="One-Time",0),H14*(1+$D$3))} -> 0 | J14: {=IFERROR(_xlfn.IFS(VALUE(MID(J$5,6,1))>$D$2,0,$B14="Annual",1,I14=12,12,$B14="Monthly V",I14*(1+$D$3),$B14="Monthly F",12,$B14="One-Time",0),I14*(1+$D$3))} -> 0 | K14: {=IFERROR(_xlfn.IFS(VALUE(MID(K$5,6,1))>$D$2,0,$B14="Annual",1,J14=12,12,$B14="Monthly V",J14*(1+$D$3),$B14="Monthly F",12,$B14="One-Time",0),J14*(1+$D$3))} -> 0 | L14: {=IFERROR(_xlfn.IFS(VALUE(MID(L$5,6,1))>$D$2,0,$B14="Annual",1,K14=12,12,$B14="Monthly V",K14*(1+$D$3),$B14="Monthly F",12,$B14="One-Time",0),K14*(1+$D$3))} -> 0 | M14: {=IFERROR(_xlfn.IFS(VALUE(MID(M$5,6,1))>$D$2,0,$B14="Annual",1,L14=12,12,$B14="Monthly V",L14*(1+$D$3),$B14="Monthly F",12,$B14="One-Time",0),L14*(1+$D$3))} -> 0 | N14: {=IFERROR(_xlfn.IFS(VALUE(MID(N$5,6,2))>$D$2,0,$B14="Annual",1,M14=12,12,$B14="Monthly V",M14*(1+$D$3),$B14="Monthly F",12,$B14="One-Time",0),M14*(1+$D$3))} -> 0 | R14: =S14/12 -> 0 | S14: =IFERROR($Q14*E14,0) -> 0 | T14: =IFERROR($Q14*F14,0) -> 0 | U14: =IFERROR($Q14*G14,0) -> 0 | V14: =IFERROR($Q14*H14,0) -> 0 | W14: =IFERROR($Q14*I14,0) -> 0 | X14: =IFERROR($Q14*J14,0) -> 0 | Y14: =IFERROR($Q14*K14,0) -> 0 | Z14: =IFERROR($Q14*L14,0) -> 0 | ... AB14: =IFERROR($Q14*N14,0) -> 0 | AD14: =IF(VALUE(MID(AD$5,6,1))<=$D$2,((1+$Q$3)^1-1)*T14,0) -> 0 | AE14: =IF(VALUE(MID(AE$5,6,1))<=$D$2,((1+$Q$3)^2-1)*U14,0) -> 0 | AF14: =IF(VALUE(MID(AF$5,6,1))<=$D$2,((1+$Q$3)^3-1)*V14,0) -> 0 | AG14: =IF(VALUE(MID(AG$5,6,1))<=$D$2,((1+$Q$3)^4-1)*W14,0) -> 0 | AH14: =IF(VALUE(MID(AH$5,6,1))<=$D$2,((1+$Q$3)^5-1)*X14,0) -> 0 | AI14: =IF(VALUE(MID(AI$5,6,1))<=$D$2,((1+$Q$3)^6-1)*Y14,0) -> 0 | AJ14: =IF(VALUE(MID(AJ$5,6,1))<=$D$2,((1+$Q$3)^7-1)*Z14,0) -> 0 | AK14: =IF(VALUE(MID(AK$5,6,1))<=$D$2,((1+$Q$3)^8-1)*AA14,0) -> 0 | AL14: =IF(VALUE(MID(AL$5,6,2))<=$D$2,((1+$Q$3)^9-1)*AB14,0) -> 0 | AM14: =SUM(AC14:AL14) -> 0 | AN14: =SUM(AM14,S14:AB14) -> 0 | AP14: Monthly V | AQ14: 5000 | AR14: =IF($AP14="Annual",1,IF($AP14="Monthly F",12,IF($AP14="Monthly V",AQ14*12,IF($AP14="One-Time",1,AQ14*12)))) -> 60000 | AS14: {=IFERROR(_xlfn.IFS(VALUE(MID(AS$5,6,1))>$D$2,0,$AP14="Annual",1,AR14=12,12,$AP14="Monthly V",AR14*(1+$BD$2),$AP14="Monthly F",12,$AP14="One-Time",0),AR14*(1+$BD$2))} -> 60000 | AT14: {=IFERROR(_xlfn.IFS(VALUE(MID(AT$5,6,1))>$D$2,0,$AP14="Annual",1,AS14=12,12,$AP14="Monthly V",AS14*(1+$BD$2),$AP14="Monthly F",12,$AP14="One-Time",0),AS14*(1+$BD$2))} -> 60000 | AU14: {=IFERROR(_xlfn.IFS(VALUE(MID(AU$5,6,1))>$D$2,0,$AP14="Annual",1,AT14=12,12,$AP14="Monthly V",AT14*(1+$BD$2),$AP14="Monthly F",12,$AP14="One-Time",0),AT14*(1+$BD$2))} -> 60000 | AV14: {=IFERROR(_xlfn.IFS(VALUE(MID(AV$5,6,1))>$D$2,0,$AP14="Annual",1,AU14=12,12,$AP14="Monthly V",AU14*(1+$BD$2),$AP14="Monthly F",12,$AP14="One-Time",0),AU14*(1+$BD$2))} -> 60000 | AW14: {=IFERROR(_xlfn.IFS(VALUE(MID(AW$5,6,1))>$D$2,0,$AP14="Annual",1,AV14=12,12,$AP14="Monthly V",AV14*(1+$BD$2),$AP14="Monthly F",12,$AP14="One-Time",0),AV14*(1+$BD$2))} -> 60000 | AX14: {=IFERROR(_xlfn.IFS(VALUE(MID(AX$5,6,1))>$D$2,0,$AP14="Annual",1,AW14=12,12,$AP14="Monthly V",AW14*(1+$BD$2),$AP14="Monthly F",12,$AP14="One-Time",0),AW14*(1+$BD$2))} -> 60000 | AY14: {=IFERROR(_xlfn.IFS(VALUE(MID(AY$5,6,1))>$D$2,0,$AP14="Annual",1,AX14=12,12,$AP14="Monthly V",AX14*(1+$D$3),$AP14="Monthly F",12,$AP14="One-Time",0),AX14*(1+$D$3))} -> 0 | AZ14: {=IFERROR(_xlfn.IFS(VALUE(MID(AZ$5,6,1))>$D$2,0,$AP14="Annual",1,AY14=12,12,$AP14="Monthly V",AY14*(1+$D$3),$AP14="Monthly F",12,$AP14="One-Time",0),AY14*(1+$D$3))} -> 0 | BA14: {=IFERROR(_xlfn.IFS(VALUE(MID(BA$5,6,2))>$D$2,0,$AP14="Annual",1,AZ14=12,12,$AP14="Monthly V",AZ14*(1+$D$3),$AP14="Monthly F",12,$AP14="One-Time",0),AZ14*(1+$D$3))} -> 0 | BB14: Synapsys CRM | BC14: Synapsys | BD14: 0.1643 | BE14: =BF14/12 -> 821.5 | BF14: =IFERROR(AR14*$BD14,0) -> 9858 | BG14: =IFERROR(AS14*$BD14,0) -> 9858 | BH14: =IFERROR(AT14*$BD14,0) -> 9858 | BI14: =BH14*1.03 -> 10153.74 | BJ14: =BI14*1.03 -> 10458.352 | BK14: =BJ14*1.03 -> 10772.103 | BL14: =BK14*1.03 -> 11095.266 | BM14: =IFERROR(AY14*$BD14,0) -> 0 | BN14: =IFERROR(AZ14*$BD14,0) -> 0 | BO14: =IFERROR(BA14*$BD14,0) -> 0 | BQ14: =IF(VALUE(MID(BQ$5,6,1))<=$D$2,((1+$BD$3)^1-1)*BG14,0) -> 295.74 | BR14: =IF(VALUE(MID(BR$5,6,1))<=$D$2,((1+$BD$3)^2-1)*BH14,0) -> 600.3522 | BS14: =IF(VALUE(MID(BS$5,6,1))<=$D$2,((1+$BD$3)^3-1)*BI14,0) -> 941.52585 | BT14: =IF(VALUE(MID(BT$5,6,1))<=$D$2,((1+$BD$3)^4-1)*BJ14,0) -> 1312.6153 | BU14: =IF(VALUE(MID(BU$5,6,1))<=$D$2,((1+$BD$3)^5-1)*BK14,0) -> 1715.7167 | BV14: =IF(VALUE(MID(BV$5,6,1))<=$D$2,((1+$BD$3)^6-1)*BL14,0) -> 2153.0618 | BW14: =IF(VALUE(MID(BW$5,6,1))<=$D$2,((1+$BD$3)^7-1)*BM14,0) -> 0 | BX14: =IF(VALUE(MID(BX$5,6,1))<=$D$2,((1+$BD$3)^8-1)*BN14,0) -> 0 | BY14: =IF(VALUE(MID(BY$5,6,2))<=$D$2,((1+$BD$3)^9-1)*BO14,0) -> 0 | BZ14: =SUM(BP14:BY14) -> 7019.0119 | CA14: =SUM(BZ14,BF14:BO14) -> 79072.473 | CE14: =IF($CC14="Annual",1,IF($CC14="Monthly F",12,IF($CC14="Monthly V",CD14*12,IF($CC14="One-Time",1,CD14*12)))) -> 0 | CF14: {=IFERROR(_xlfn.IFS(VALUE(MID(CF$5,6,1))>$D$2,0,$CC14="Annual",1,CE14=12,12,$CC14="Monthly V",CE14*(1+$D$3),$CC14="Monthly F",12,$CC14="One-Time",0),CE14*(1+$D$3))} -> 0 | CG14: {=IFERROR(_xlfn.IFS(VALUE(MID(CG$5,6,1))>$D$2,0,$CC14="Annual",1,CF14=12,12,$CC14="Monthly V",CF14*(1+$D$3),$CC14="Monthly F",12,$CC14="One-Time",0),CF14*(1+$D$3))} -> 0 | CH14: {=IFERROR(_xlfn.IFS(VALUE(MID(CH$5,6,1))>$D$2,0,$CC14="Annual",1,CG14=12,12,$CC14="Monthly V",CG14*(1+$D$3),$CC14="Monthly F",12,$CC14="One-Time",0),CG14*(1+$D$3))} -> 0 | CI14: {=IFERROR(_xlfn.IFS(VALUE(MID(CI$5,6,1))>$D$2,0,$CC14="Annual",1,CH14=12,12,$CC14="Monthly V",CH14*(1+$D$3),$CC14="Monthly F",12,$CC14="One-Time",0),CH14*(1+$D$3))} -> 0 | CJ14: {=IFERROR(_xlfn.IFS(VALUE(MID(CJ$5,6,1))>$D$2,0,$CC14="Annual",1,CI14=12,12,$CC14="Monthly V",CI14*(1+$D$3),$CC14="Monthly F",12,$CC14="One-Time",0),CI14*(1+$D$3))} -> 0 | CK14: {=IFERROR(_xlfn.IFS(VALUE(MID(CK$5,6,1))>$D$2,0,$CC14="Annual",1,CJ14=12,12,$CC14="Monthly V",CJ14*(1+$D$3),$CC14="Monthly F",12,$CC14="One-Time",0),CJ14*(1+$D$3))} -> 0 | CL14: {=IFERROR(_xlfn.IFS(VALUE(MID(CL$5,6,1))>$D$2,0,$CC14="Annual",1,CK14=12,12,$CC14="Monthly V",CK14*(1+$D$3),$CC14="Monthly F",12,$CC14="One-Time",0),CK14*(1+$D$3))} -> 0 | CM14: {=IFERROR(_xlfn.IFS(VALUE(MID(CM$5,6,1))>$D$2,0,$CC14="Annual",1,CL14=12,12,$CC14="Monthly V",CL14*(1+$D$3),$CC14="Monthly F",12,$CC14="One-Time",0),CL14*(1+$D$3))} -> 0 | CN14: {=IFERROR(_xlfn.IFS(VALUE(MID(CN$5,6,2))>$D$2,0,$CC14="Annual",1,CM14=12,12,$CC14="Monthly V",CM14*(1+$D$3),$CC14="Monthly F",12,$CC14="One-Time",0),CM14*(1+$D$3))} -> 0 | CQ14: =CR14/12 -> 0 | CR14: =IFERROR(CE14*$CP14,0) -> 0 | CS14: =IFERROR(CF14*$CP14,0) -> 0 | CT14: =IFERROR(CG14*$CP14,0) -> 0 | CU14: =IFERROR(CH14*$CP14,0) -> 0 | CV14: =IFERROR(CI14*$CP14,0) -> 0 | CW14: =IFERROR(CJ14*$CP14,0) -> 0 | CX14: =IFERROR(CK14*$CP14,0) -> 0 | CY14: =IFERROR(CL14*$CP14,0) -> 0 | ... DA14: =IFERROR(CN14*$CP14,0) -> 0 | DC14: =IF(VALUE(MID(DC$5,6,1))<=$D$2,((1+$CP$3)^1-1)*CS14,0) -> 0 | DD14: =IF(VALUE(MID(DD$5,6,1))<=$D$2,((1+$CP$3)^2-1)*CT14,0) -> 0 | DE14: =IF(VALUE(MID(DE$5,6,1))<=$D$2,((1+$CP$3)^3-1)*CU14,0) -> 0 | DF14: =IF(VALUE(MID(DF$5,6,1))<=$D$2,((1+$CP$3)^4-1)*CV14,0) -> 0 | DG14: =IF(VALUE(MID(DG$5,6,1))<=$D$2,((1+$CP$3)^5-1)*CW14,0) -> 0 | DH14: =IF(VALUE(MID(DH$5,6,1))<=$D$2,((1+$CP$3)^6-1)*CX14,0) -> 0 | DI14: =IF(VALUE(MID(DI$5,6,1))<=$D$2,((1+$CP$3)^7-1)*CY14,0) -> 0 | DJ14: =IF(VALUE(MID(DJ$5,6,1))<=$D$2,((1+$CP$3)^8-1)*CZ14,0) -> 0 | DK14: =IF(VALUE(MID(DK$5,6,2))<=$D$2,((1+$CP$3)^9-1)*DA14,0) -> 0 | DL14: =SUM(DB14:DK14) -> 0 | DM14: =SUM(DL14,CR14:DA14) -> 0
D15: =IFERROR(AVERAGE(C15:C15),0) -> 0 | E15: =IF($B15="Annual",1,IF($B15="Monthly F",12,IF($B15="Monthly V",D15*12,IF($B15="One-Time",1,D15*12)))) -> 0 | F15: {=IFERROR(_xlfn.IFS(VALUE(MID(F$5,6,1))>$D$2,0,$B15="Annual",1,E15=12,12,$B15="Monthly V",E15*(1+$D$3),$B15="Monthly F",12,$B15="One-Time",0),E15*(1+$D$3))} -> 0 | G15: {=IFERROR(_xlfn.IFS(VALUE(MID(G$5,6,1))>$D$2,0,$B15="Annual",1,F15=12,12,$B15="Monthly V",F15*(1+$D$3),$B15="Monthly F",12,$B15="One-Time",0),F15*(1+$D$3))} -> 0 | H15: {=IFERROR(_xlfn.IFS(VALUE(MID(H$5,6,1))>$D$2,0,$B15="Annual",1,G15=12,12,$B15="Monthly V",G15*(1+$D$3),$B15="Monthly F",12,$B15="One-Time",0),G15*(1+$D$3))} -> 0 | I15: {=IFERROR(_xlfn.IFS(VALUE(MID(I$5,6,1))>$D$2,0,$B15="Annual",1,H15=12,12,$B15="Monthly V",H15*(1+$D$3),$B15="Monthly F",12,$B15="One-Time",0),H15*(1+$D$3))} -> 0 | J15: {=IFERROR(_xlfn.IFS(VALUE(MID(J$5,6,1))>$D$2,0,$B15="Annual",1,I15=12,12,$B15="Monthly V",I15*(1+$D$3),$B15="Monthly F",12,$B15="One-Time",0),I15*(1+$D$3))} -> 0 | K15: {=IFERROR(_xlfn.IFS(VALUE(MID(K$5,6,1))>$D$2,0,$B15="Annual",1,J15=12,12,$B15="Monthly V",J15*(1+$D$3),$B15="Monthly F",12,$B15="One-Time",0),J15*(1+$D$3))} -> 0 | L15: {=IFERROR(_xlfn.IFS(VALUE(MID(L$5,6,1))>$D$2,0,$B15="Annual",1,K15=12,12,$B15="Monthly V",K15*(1+$D$3),$B15="Monthly F",12,$B15="One-Time",0),K15*(1+$D$3))} -> 0 | M15: {=IFERROR(_xlfn.IFS(VALUE(MID(M$5,6,1))>$D$2,0,$B15="Annual",1,L15=12,12,$B15="Monthly V",L15*(1+$D$3),$B15="Monthly F",12,$B15="One-Time",0),L15*(1+$D$3))} -> 0 | N15: {=IFERROR(_xlfn.IFS(VALUE(MID(N$5,6,2))>$D$2,0,$B15="Annual",1,M15=12,12,$B15="Monthly V",M15*(1+$D$3),$B15="Monthly F",12,$B15="One-Time",0),M15*(1+$D$3))} -> 0 | R15: =S15/12 -> 0 | S15: =IFERROR($Q15*E15,0) -> 0 | T15: =IFERROR($Q15*F15,0) -> 0 | U15: =IFERROR($Q15*G15,0) -> 0 | V15: =IFERROR($Q15*H15,0) -> 0 | W15: =IFERROR($Q15*I15,0) -> 0 | X15: =IFERROR($Q15*J15,0) -> 0 | Y15: =IFERROR($Q15*K15,0) -> 0 | Z15: =IFERROR($Q15*L15,0) -> 0 | ... AB15: =IFERROR($Q15*N15,0) -> 0 | AD15: =IF(VALUE(MID(AD$5,6,1))<=$D$2,((1+$Q$3)^1-1)*T15,0) -> 0 | AE15: =IF(VALUE(MID(AE$5,6,1))<=$D$2,((1+$Q$3)^2-1)*U15,0) -> 0 | AF15: =IF(VALUE(MID(AF$5,6,1))<=$D$2,((1+$Q$3)^3-1)*V15,0) -> 0 | AG15: =IF(VALUE(MID(AG$5,6,1))<=$D$2,((1+$Q$3)^4-1)*W15,0) -> 0 | AH15: =IF(VALUE(MID(AH$5,6,1))<=$D$2,((1+$Q$3)^5-1)*X15,0) -> 0 | AI15: =IF(VALUE(MID(AI$5,6,1))<=$D$2,((1+$Q$3)^6-1)*Y15,0) -> 0 | AJ15: =IF(VALUE(MID(AJ$5,6,1))<=$D$2,((1+$Q$3)^7-1)*Z15,0) -> 0 | AK15: =IF(VALUE(MID(AK$5,6,1))<=$D$2,((1+$Q$3)^8-1)*AA15,0) -> 0 | AL15: =IF(VALUE(MID(AL$5,6,2))<=$D$2,((1+$Q$3)^9-1)*AB15,0) -> 0 | AM15: =SUM(AC15:AL15) -> 0 | AN15: =SUM(AM15,S15:AB15) -> 0 | AP15: Monthly V | AQ15: 5000 | AR15: =IF($AP15="Annual",1,IF($AP15="Monthly F",12,IF($AP15="Monthly V",AQ15*12,IF($AP15="One-Time",1,AQ15*12)))) -> 60000 | AS15: {=IFERROR(_xlfn.IFS(VALUE(MID(AS$5,6,1))>$D$2,0,$AP15="Annual",1,AR15=12,12,$AP15="Monthly V",AR15*(1+$BD$2),$AP15="Monthly F",12,$AP15="One-Time",0),AR15*(1+$BD$2))} -> 60000 | AT15: {=IFERROR(_xlfn.IFS(VALUE(MID(AT$5,6,1))>$D$2,0,$AP15="Annual",1,AS15=12,12,$AP15="Monthly V",AS15*(1+$BD$2),$AP15="Monthly F",12,$AP15="One-Time",0),AS15*(1+$BD$2))} -> 60000 | AU15: {=IFERROR(_xlfn.IFS(VALUE(MID(AU$5,6,1))>$D$2,0,$AP15="Annual",1,AT15=12,12,$AP15="Monthly V",AT15*(1+$BD$2),$AP15="Monthly F",12,$AP15="One-Time",0),AT15*(1+$BD$2))} -> 60000 | AV15: {=IFERROR(_xlfn.IFS(VALUE(MID(AV$5,6,1))>$D$2,0,$AP15="Annual",1,AU15=12,12,$AP15="Monthly V",AU15*(1+$BD$2),$AP15="Monthly F",12,$AP15="One-Time",0),AU15*(1+$BD$2))} -> 60000 | AW15: {=IFERROR(_xlfn.IFS(VALUE(MID(AW$5,6,1))>$D$2,0,$AP15="Annual",1,AV15=12,12,$AP15="Monthly V",AV15*(1+$BD$2),$AP15="Monthly F",12,$AP15="One-Time",0),AV15*(1+$BD$2))} -> 60000 | AX15: {=IFERROR(_xlfn.IFS(VALUE(MID(AX$5,6,1))>$D$2,0,$AP15="Annual",1,AW15=12,12,$AP15="Monthly V",AW15*(1+$BD$2),$AP15="Monthly F",12,$AP15="One-Time",0),AW15*(1+$BD$2))} -> 60000 | AY15: {=IFERROR(_xlfn.IFS(VALUE(MID(AY$5,6,1))>$D$2,0,$AP15="Annual",1,AX15=12,12,$AP15="Monthly V",AX15*(1+$D$3),$AP15="Monthly F",12,$AP15="One-Time",0),AX15*(1+$D$3))} -> 0 | AZ15: {=IFERROR(_xlfn.IFS(VALUE(MID(AZ$5,6,1))>$D$2,0,$AP15="Annual",1,AY15=12,12,$AP15="Monthly V",AY15*(1+$D$3),$AP15="Monthly F",12,$AP15="One-Time",0),AY15*(1+$D$3))} -> 0 | BA15: {=IFERROR(_xlfn.IFS(VALUE(MID(BA$5,6,2))>$D$2,0,$AP15="Annual",1,AZ15=12,12,$AP15="Monthly V",AZ15*(1+$D$3),$AP15="Monthly F",12,$AP15="One-Time",0),AZ15*(1+$D$3))} -> 0 | BB15: JHA OpenAnywhere | BC15: JHA OpenAnywhere | BD15: 0.3323 | BE15: =BF15/12 -> 1661.5 | BF15: =IFERROR(AR15*$BD15,0) -> 19938 | BG15: =IFERROR(AS15*$BD15,0) -> 19938 | BH15: =IFERROR(AT15*$BD15,0) -> 19938 | BI15: =BH15*1.03 -> 20536.14 | BJ15: =BI15*1.03 -> 21152.224 | BK15: =BJ15*1.03 -> 21786.791 | BL15: =BK15*1.03 -> 22440.395 | BM15: =IFERROR(AY15*$BD15,0) -> 0 | BN15: =IFERROR(AZ15*$BD15,0) -> 0 | BO15: =IFERROR(BA15*$BD15,0) -> 0 | BQ15: =IF(VALUE(MID(BQ$5,6,1))<=$D$2,((1+$BD$3)^1-1)*BG15,0) -> 598.14 | BR15: =IF(VALUE(MID(BR$5,6,1))<=$D$2,((1+$BD$3)^2-1)*BH15,0) -> 1214.2242 | BS15: =IF(VALUE(MID(BS$5,6,1))<=$D$2,((1+$BD$3)^3-1)*BI15,0) -> 1904.2547 | BT15: =IF(VALUE(MID(BT$5,6,1))<=$D$2,((1+$BD$3)^4-1)*BJ15,0) -> 2654.7905 | BU15: =IF(VALUE(MID(BU$5,6,1))<=$D$2,((1+$BD$3)^5-1)*BK15,0) -> 3470.071 | BV15: =IF(VALUE(MID(BV$5,6,1))<=$D$2,((1+$BD$3)^6-1)*BL15,0) -> 4354.6101 | BW15: =IF(VALUE(MID(BW$5,6,1))<=$D$2,((1+$BD$3)^7-1)*BM15,0) -> 0 | BX15: =IF(VALUE(MID(BX$5,6,1))<=$D$2,((1+$BD$3)^8-1)*BN15,0) -> 0 | BY15: =IF(VALUE(MID(BY$5,6,2))<=$D$2,((1+$BD$3)^9-1)*BO15,0) -> 0 | BZ15: =SUM(BP15:BY15) -> 14196.09 | CA15: =SUM(BZ15,BF15:BO15) -> 159925.64 | CE15: =IF($CC15="Annual",1,IF($CC15="Monthly F",12,IF($CC15="Monthly V",CD15*12,IF($CC15="One-Time",1,CD15*12)))) -> 0 | CF15: {=IFERROR(_xlfn.IFS(VALUE(MID(CF$5,6,1))>$D$2,0,$CC15="Annual",1,CE15=12,12,$CC15="Monthly V",CE15*(1+$D$3),$CC15="Monthly F",12,$CC15="One-Time",0),CE15*(1+$D$3))} -> 0 | CG15: {=IFERROR(_xlfn.IFS(VALUE(MID(CG$5,6,1))>$D$2,0,$CC15="Annual",1,CF15=12,12,$CC15="Monthly V",CF15*(1+$D$3),$CC15="Monthly F",12,$CC15="One-Time",0),CF15*(1+$D$3))} -> 0 | CH15: {=IFERROR(_xlfn.IFS(VALUE(MID(CH$5,6,1))>$D$2,0,$CC15="Annual",1,CG15=12,12,$CC15="Monthly V",CG15*(1+$D$3),$CC15="Monthly F",12,$CC15="One-Time",0),CG15*(1+$D$3))} -> 0 | CI15: {=IFERROR(_xlfn.IFS(VALUE(MID(CI$5,6,1))>$D$2,0,$CC15="Annual",1,CH15=12,12,$CC15="Monthly V",CH15*(1+$D$3),$CC15="Monthly F",12,$CC15="One-Time",0),CH15*(1+$D$3))} -> 0 | CJ15: {=IFERROR(_xlfn.IFS(VALUE(MID(CJ$5,6,1))>$D$2,0,$CC15="Annual",1,CI15=12,12,$CC15="Monthly V",CI15*(1+$D$3),$CC15="Monthly F",12,$CC15="One-Time",0),CI15*(1+$D$3))} -> 0 | CK15: {=IFERROR(_xlfn.IFS(VALUE(MID(CK$5,6,1))>$D$2,0,$CC15="Annual",1,CJ15=12,12,$CC15="Monthly V",CJ15*(1+$D$3),$CC15="Monthly F",12,$CC15="One-Time",0),CJ15*(1+$D$3))} -> 0 | CL15: {=IFERROR(_xlfn.IFS(VALUE(MID(CL$5,6,1))>$D$2,0,$CC15="Annual",1,CK15=12,12,$CC15="Monthly V",CK15*(1+$D$3),$CC15="Monthly F",12,$CC15="One-Time",0),CK15*(1+$D$3))} -> 0 | CM15: {=IFERROR(_xlfn.IFS(VALUE(MID(CM$5,6,1))>$D$2,0,$CC15="Annual",1,CL15=12,12,$CC15="Monthly V",CL15*(1+$D$3),$CC15="Monthly F",12,$CC15="One-Time",0),CL15*(1+$D$3))} -> 0 | CN15: {=IFERROR(_xlfn.IFS(VALUE(MID(CN$5,6,2))>$D$2,0,$CC15="Annual",1,CM15=12,12,$CC15="Monthly V",CM15*(1+$D$3),$CC15="Monthly F",12,$CC15="One-Time",0),CM15*(1+$D$3))} -> 0 | CQ15: =CR15/12 -> 0 | CR15: =IFERROR(CE15*$CP15,0) -> 0 | CS15: =IFERROR(CF15*$CP15,0) -> 0 | CT15: =IFERROR(CG15*$CP15,0) -> 0 | CU15: =IFERROR(CH15*$CP15,0) -> 0 | CV15: =IFERROR(CI15*$CP15,0) -> 0 | CW15: =IFERROR(CJ15*$CP15,0) -> 0 | CX15: =IFERROR(CK15*$CP15,0) -> 0 | CY15: =IFERROR(CL15*$CP15,0) -> 0 | ... DA15: =IFERROR(CN15*$CP15,0) -> 0 | DC15: =IF(VALUE(MID(DC$5,6,1))<=$D$2,((1+$CP$3)^1-1)*CS15,0) -> 0 | DD15: =IF(VALUE(MID(DD$5,6,1))<=$D$2,((1+$CP$3)^2-1)*CT15,0) -> 0 | DE15: =IF(VALUE(MID(DE$5,6,1))<=$D$2,((1+$CP$3)^3-1)*CU15,0) -> 0 | DF15: =IF(VALUE(MID(DF$5,6,1))<=$D$2,((1+$CP$3)^4-1)*CV15,0) -> 0 | DG15: =IF(VALUE(MID(DG$5,6,1))<=$D$2,((1+$CP$3)^5-1)*CW15,0) -> 0 | DH15: =IF(VALUE(MID(DH$5,6,1))<=$D$2,((1+$CP$3)^6-1)*CX15,0) -> 0 | DI15: =IF(VALUE(MID(DI$5,6,1))<=$D$2,((1+$CP$3)^7-1)*CY15,0) -> 0 | DJ15: =IF(VALUE(MID(DJ$5,6,1))<=$D$2,((1+$CP$3)^8-1)*CZ15,0) -> 0 | DK15: =IF(VALUE(MID(DK$5,6,2))<=$D$2,((1+$CP$3)^9-1)*DA15,0) -> 0 | DL15: =SUM(DB15:DK15) -> 0 | DM15: =SUM(DL15,CR15:DA15) -> 0
D16: =IFERROR(AVERAGE(C16:C16),0) -> 0 | E16: =IF($B16="Annual",1,IF($B16="Monthly F",12,IF($B16="Monthly V",D16*12,IF($B16="One-Time",1,D16*12)))) -> 0 | F16: {=IFERROR(_xlfn.IFS(VALUE(MID(F$5,6,1))>$D$2,0,$B16="Annual",1,E16=12,12,$B16="Monthly V",E16*(1+$D$3),$B16="Monthly F",12,$B16="One-Time",0),E16*(1+$D$3))} -> 0 | G16: {=IFERROR(_xlfn.IFS(VALUE(MID(G$5,6,1))>$D$2,0,$B16="Annual",1,F16=12,12,$B16="Monthly V",F16*(1+$D$3),$B16="Monthly F",12,$B16="One-Time",0),F16*(1+$D$3))} -> 0 | H16: {=IFERROR(_xlfn.IFS(VALUE(MID(H$5,6,1))>$D$2,0,$B16="Annual",1,G16=12,12,$B16="Monthly V",G16*(1+$D$3),$B16="Monthly F",12,$B16="One-Time",0),G16*(1+$D$3))} -> 0 | I16: {=IFERROR(_xlfn.IFS(VALUE(MID(I$5,6,1))>$D$2,0,$B16="Annual",1,H16=12,12,$B16="Monthly V",H16*(1+$D$3),$B16="Monthly F",12,$B16="One-Time",0),H16*(1+$D$3))} -> 0 | J16: {=IFERROR(_xlfn.IFS(VALUE(MID(J$5,6,1))>$D$2,0,$B16="Annual",1,I16=12,12,$B16="Monthly V",I16*(1+$D$3),$B16="Monthly F",12,$B16="One-Time",0),I16*(1+$D$3))} -> 0 | K16: {=IFERROR(_xlfn.IFS(VALUE(MID(K$5,6,1))>$D$2,0,$B16="Annual",1,J16=12,12,$B16="Monthly V",J16*(1+$D$3),$B16="Monthly F",12,$B16="One-Time",0),J16*(1+$D$3))} -> 0 | L16: {=IFERROR(_xlfn.IFS(VALUE(MID(L$5,6,1))>$D$2,0,$B16="Annual",1,K16=12,12,$B16="Monthly V",K16*(1+$D$3),$B16="Monthly F",12,$B16="One-Time",0),K16*(1+$D$3))} -> 0 | M16: {=IFERROR(_xlfn.IFS(VALUE(MID(M$5,6,1))>$D$2,0,$B16="Annual",1,L16=12,12,$B16="Monthly V",L16*(1+$D$3),$B16="Monthly F",12,$B16="One-Time",0),L16*(1+$D$3))} -> 0 | N16: {=IFERROR(_xlfn.IFS(VALUE(MID(N$5,6,2))>$D$2,0,$B16="Annual",1,M16=12,12,$B16="Monthly V",M16*(1+$D$3),$B16="Monthly F",12,$B16="One-Time",0),M16*(1+$D$3))} -> 0 | R16: =S16/12 -> 0 | S16: =IFERROR($Q16*E16,0) -> 0 | T16: =IFERROR($Q16*F16,0) -> 0 | U16: =IFERROR($Q16*G16,0) -> 0 | V16: =IFERROR($Q16*H16,0) -> 0 | W16: =IFERROR($Q16*I16,0) -> 0 | X16: =IFERROR($Q16*J16,0) -> 0 | Y16: =IFERROR($Q16*K16,0) -> 0 | Z16: =IFERROR($Q16*L16,0) -> 0 | ... AB16: =IFERROR($Q16*N16,0) -> 0 | AD16: =IF(VALUE(MID(AD$5,6,1))<=$D$2,((1+$Q$3)^1-1)*T16,0) -> 0 | AE16: =IF(VALUE(MID(AE$5,6,1))<=$D$2,((1+$Q$3)^2-1)*U16,0) -> 0 | AF16: =IF(VALUE(MID(AF$5,6,1))<=$D$2,((1+$Q$3)^3-1)*V16,0) -> 0 | AG16: =IF(VALUE(MID(AG$5,6,1))<=$D$2,((1+$Q$3)^4-1)*W16,0) -> 0 | AH16: =IF(VALUE(MID(AH$5,6,1))<=$D$2,((1+$Q$3)^5-1)*X16,0) -> 0 | AI16: =IF(VALUE(MID(AI$5,6,1))<=$D$2,((1+$Q$3)^6-1)*Y16,0) -> 0 | AJ16: =IF(VALUE(MID(AJ$5,6,1))<=$D$2,((1+$Q$3)^7-1)*Z16,0) -> 0 | AK16: =IF(VALUE(MID(AK$5,6,1))<=$D$2,((1+$Q$3)^8-1)*AA16,0) -> 0 | AL16: =IF(VALUE(MID(AL$5,6,2))<=$D$2,((1+$Q$3)^9-1)*AB16,0) -> 0 | AM16: =SUM(AC16:AL16) -> 0 | AN16: =SUM(AM16,S16:AB16) -> 0 | AP16: Monthly F | AQ16: 1 | AR16: =IF($AP16="Annual",1,IF($AP16="Monthly F",12,IF($AP16="Monthly V",AQ16*12,IF($AP16="One-Time",1,AQ16*12)))) -> 12 | AS16: {=IFERROR(_xlfn.IFS(VALUE(MID(AS$5,6,1))>$D$2,0,$AP16="Annual",1,AR16=12,12,$AP16="Monthly V",AR16*(1+$BD$2),$AP16="Monthly F",12,$AP16="One-Time",0),AR16*(1+$BD$2))} -> 12 | AT16: {=IFERROR(_xlfn.IFS(VALUE(MID(AT$5,6,1))>$D$2,0,$AP16="Annual",1,AS16=12,12,$AP16="Monthly V",AS16*(1+$BD$2),$AP16="Monthly F",12,$AP16="One-Time",0),AS16*(1+$BD$2))} -> 12 | AU16: {=IFERROR(_xlfn.IFS(VALUE(MID(AU$5,6,1))>$D$2,0,$AP16="Annual",1,AT16=12,12,$AP16="Monthly V",AT16*(1+$BD$2),$AP16="Monthly F",12,$AP16="One-Time",0),AT16*(1+$BD$2))} -> 12 | AV16: {=IFERROR(_xlfn.IFS(VALUE(MID(AV$5,6,1))>$D$2,0,$AP16="Annual",1,AU16=12,12,$AP16="Monthly V",AU16*(1+$BD$2),$AP16="Monthly F",12,$AP16="One-Time",0),AU16*(1+$BD$2))} -> 12 | AW16: {=IFERROR(_xlfn.IFS(VALUE(MID(AW$5,6,1))>$D$2,0,$AP16="Annual",1,AV16=12,12,$AP16="Monthly V",AV16*(1+$BD$2),$AP16="Monthly F",12,$AP16="One-Time",0),AV16*(1+$BD$2))} -> 12 | AX16: {=IFERROR(_xlfn.IFS(VALUE(MID(AX$5,6,1))>$D$2,0,$AP16="Annual",1,AW16=12,12,$AP16="Monthly V",AW16*(1+$BD$2),$AP16="Monthly F",12,$AP16="One-Time",0),AW16*(1+$BD$2))} -> 12 | AY16: {=IFERROR(_xlfn.IFS(VALUE(MID(AY$5,6,1))>$D$2,0,$AP16="Annual",1,AX16=12,12,$AP16="Monthly V",AX16*(1+$D$3),$AP16="Monthly F",12,$AP16="One-Time",0),AX16*(1+$D$3))} -> 0 | AZ16: {=IFERROR(_xlfn.IFS(VALUE(MID(AZ$5,6,1))>$D$2,0,$AP16="Annual",1,AY16=12,12,$AP16="Monthly V",AY16*(1+$D$3),$AP16="Monthly F",12,$AP16="One-Time",0),AY16*(1+$D$3))} -> 0 | BA16: {=IFERROR(_xlfn.IFS(VALUE(MID(BA$5,6,2))>$D$2,0,$AP16="Annual",1,AZ16=12,12,$AP16="Monthly V",AZ16*(1+$D$3),$AP16="Monthly F",12,$AP16="One-Time",0),AZ16*(1+$D$3))} -> 0 | BB16: IDScan.net OCR | BC16: JHA OpenAnywhere | BD16: 400 | BE16: =BF16/12 -> 400 | BF16: =IFERROR(AR16*$BD16,0) -> 4800 | BG16: =IFERROR(AS16*$BD16,0) -> 4800 | BH16: =IFERROR(AT16*$BD16,0) -> 4800 | BI16: =BH16*1.03 -> 4944 | BJ16: =BI16*1.03 -> 5092.32 | BK16: =BJ16*1.03 -> 5245.0896 | BL16: =BK16*1.03 -> 5402.4423 | BM16: =IFERROR(AY16*$BD16,0) -> 0 | BN16: =IFERROR(AZ16*$BD16,0) -> 0 | BO16: =IFERROR(BA16*$BD16,0) -> 0 | BQ16: =IF(VALUE(MID(BQ$5,6,1))<=$D$2,((1+$BD$3)^1-1)*BG16,0) -> 144 | BR16: =IF(VALUE(MID(BR$5,6,1))<=$D$2,((1+$BD$3)^2-1)*BH16,0) -> 292.32 | BS16: =IF(VALUE(MID(BS$5,6,1))<=$D$2,((1+$BD$3)^3-1)*BI16,0) -> 458.44229 | BT16: =IF(VALUE(MID(BT$5,6,1))<=$D$2,((1+$BD$3)^4-1)*BJ16,0) -> 639.13102 | BU16: =IF(VALUE(MID(BU$5,6,1))<=$D$2,((1+$BD$3)^5-1)*BK16,0) -> 835.40679 | BV16: =IF(VALUE(MID(BV$5,6,1))<=$D$2,((1+$BD$3)^6-1)*BL16,0) -> 1048.3563 | BW16: =IF(VALUE(MID(BW$5,6,1))<=$D$2,((1+$BD$3)^7-1)*BM16,0) -> 0 | BX16: =IF(VALUE(MID(BX$5,6,1))<=$D$2,((1+$BD$3)^8-1)*BN16,0) -> 0 | BY16: =IF(VALUE(MID(BY$5,6,2))<=$D$2,((1+$BD$3)^9-1)*BO16,0) -> 0 | BZ16: =SUM(BP16:BY16) -> 3417.6564 | CA16: =SUM(BZ16,BF16:BO16) -> 38501.508 | CE16: =IF($CC16="Annual",1,IF($CC16="Monthly F",12,IF($CC16="Monthly V",CD16*12,IF($CC16="One-Time",1,CD16*12)))) -> 0 | CF16: {=IFERROR(_xlfn.IFS(VALUE(MID(CF$5,6,1))>$D$2,0,$CC16="Annual",1,CE16=12,12,$CC16="Monthly V",CE16*(1+$D$3),$CC16="Monthly F",12,$CC16="One-Time",0),CE16*(1+$D$3))} -> 0 | CG16: {=IFERROR(_xlfn.IFS(VALUE(MID(CG$5,6,1))>$D$2,0,$CC16="Annual",1,CF16=12,12,$CC16="Monthly V",CF16*(1+$D$3),$CC16="Monthly F",12,$CC16="One-Time",0),CF16*(1+$D$3))} -> 0 | CH16: {=IFERROR(_xlfn.IFS(VALUE(MID(CH$5,6,1))>$D$2,0,$CC16="Annual",1,CG16=12,12,$CC16="Monthly V",CG16*(1+$D$3),$CC16="Monthly F",12,$CC16="One-Time",0),CG16*(1+$D$3))} -> 0 | CI16: {=IFERROR(_xlfn.IFS(VALUE(MID(CI$5,6,1))>$D$2,0,$CC16="Annual",1,CH16=12,12,$CC16="Monthly V",CH16*(1+$D$3),$CC16="Monthly F",12,$CC16="One-Time",0),CH16*(1+$D$3))} -> 0 | CJ16: {=IFERROR(_xlfn.IFS(VALUE(MID(CJ$5,6,1))>$D$2,0,$CC16="Annual",1,CI16=12,12,$CC16="Monthly V",CI16*(1+$D$3),$CC16="Monthly F",12,$CC16="One-Time",0),CI16*(1+$D$3))} -> 0 | CK16: {=IFERROR(_xlfn.IFS(VALUE(MID(CK$5,6,1))>$D$2,0,$CC16="Annual",1,CJ16=12,12,$CC16="Monthly V",CJ16*(1+$D$3),$CC16="Monthly F",12,$CC16="One-Time",0),CJ16*(1+$D$3))} -> 0 | CL16: {=IFERROR(_xlfn.IFS(VALUE(MID(CL$5,6,1))>$D$2,0,$CC16="Annual",1,CK16=12,12,$CC16="Monthly V",CK16*(1+$D$3),$CC16="Monthly F",12,$CC16="One-Time",0),CK16*(1+$D$3))} -> 0 | CM16: {=IFERROR(_xlfn.IFS(VALUE(MID(CM$5,6,1))>$D$2,0,$CC16="Annual",1,CL16=12,12,$CC16="Monthly V",CL16*(1+$D$3),$CC16="Monthly F",12,$CC16="One-Time",0),CL16*(1+$D$3))} -> 0 | CN16: {=IFERROR(_xlfn.IFS(VALUE(MID(CN$5,6,2))>$D$2,0,$CC16="Annual",1,CM16=12,12,$CC16="Monthly V",CM16*(1+$D$3),$CC16="Monthly F",12,$CC16="One-Time",0),CM16*(1+$D$3))} -> 0 | CQ16: =CR16/12 -> 0 | CR16: =IFERROR(CE16*$CP16,0) -> 0 | CS16: =IFERROR(CF16*$CP16,0) -> 0 | CT16: =IFERROR(CG16*$CP16,0) -> 0 | CU16: =IFERROR(CH16*$CP16,0) -> 0 | CV16: =IFERROR(CI16*$CP16,0) -> 0 | CW16: =IFERROR(CJ16*$CP16,0) -> 0 | CX16: =IFERROR(CK16*$CP16,0) -> 0 | CY16: =IFERROR(CL16*$CP16,0) -> 0 | ... DA16: =IFERROR(CN16*$CP16,0) -> 0 | DC16: =IF(VALUE(MID(DC$5,6,1))<=$D$2,((1+$CP$3)^1-1)*CS16,0) -> 0 | DD16: =IF(VALUE(MID(DD$5,6,1))<=$D$2,((1+$CP$3)^2-1)*CT16,0) -> 0 | DE16: =IF(VALUE(MID(DE$5,6,1))<=$D$2,((1+$CP$3)^3-1)*CU16,0) -> 0 | DF16: =IF(VALUE(MID(DF$5,6,1))<=$D$2,((1+$CP$3)^4-1)*CV16,0) -> 0 | DG16: =IF(VALUE(MID(DG$5,6,1))<=$D$2,((1+$CP$3)^5-1)*CW16,0) -> 0 | DH16: =IF(VALUE(MID(DH$5,6,1))<=$D$2,((1+$CP$3)^6-1)*CX16,0) -> 0 | DI16: =IF(VALUE(MID(DI$5,6,1))<=$D$2,((1+$CP$3)^7-1)*CY16,0) -> 0 | DJ16: =IF(VALUE(MID(DJ$5,6,1))<=$D$2,((1+$CP$3)^8-1)*CZ16,0) -> 0 | DK16: =IF(VALUE(MID(DK$5,6,2))<=$D$2,((1+$CP$3)^9-1)*DA16,0) -> 0 | DL16: =SUM(DB16:DK16) -> 0 | DM16: =SUM(DL16,CR16:DA16) -> 0
D17: =IFERROR(AVERAGE(C17:C17),0) -> 0 | E17: =IF($B17="Annual",1,IF($B17="Monthly F",12,IF($B17="Monthly V",D17*12,IF($B17="One-Time",1,D17*12)))) -> 0 | F17: {=IFERROR(_xlfn.IFS(VALUE(MID(F$5,6,1))>$D$2,0,$B17="Annual",1,E17=12,12,$B17="Monthly V",E17*(1+$D$3),$B17="Monthly F",12,$B17="One-Time",0),E17*(1+$D$3))} -> 0 | G17: {=IFERROR(_xlfn.IFS(VALUE(MID(G$5,6,1))>$D$2,0,$B17="Annual",1,F17=12,12,$B17="Monthly V",F17*(1+$D$3),$B17="Monthly F",12,$B17="One-Time",0),F17*(1+$D$3))} -> 0 | H17: {=IFERROR(_xlfn.IFS(VALUE(MID(H$5,6,1))>$D$2,0,$B17="Annual",1,G17=12,12,$B17="Monthly V",G17*(1+$D$3),$B17="Monthly F",12,$B17="One-Time",0),G17*(1+$D$3))} -> 0 | I17: {=IFERROR(_xlfn.IFS(VALUE(MID(I$5,6,1))>$D$2,0,$B17="Annual",1,H17=12,12,$B17="Monthly V",H17*(1+$D$3),$B17="Monthly F",12,$B17="One-Time",0),H17*(1+$D$3))} -> 0 | J17: {=IFERROR(_xlfn.IFS(VALUE(MID(J$5,6,1))>$D$2,0,$B17="Annual",1,I17=12,12,$B17="Monthly V",I17*(1+$D$3),$B17="Monthly F",12,$B17="One-Time",0),I17*(1+$D$3))} -> 0 | K17: {=IFERROR(_xlfn.IFS(VALUE(MID(K$5,6,1))>$D$2,0,$B17="Annual",1,J17=12,12,$B17="Monthly V",J17*(1+$D$3),$B17="Monthly F",12,$B17="One-Time",0),J17*(1+$D$3))} -> 0 | L17: {=IFERROR(_xlfn.IFS(VALUE(MID(L$5,6,1))>$D$2,0,$B17="Annual",1,K17=12,12,$B17="Monthly V",K17*(1+$D$3),$B17="Monthly F",12,$B17="One-Time",0),K17*(1+$D$3))} -> 0 | M17: {=IFERROR(_xlfn.IFS(VALUE(MID(M$5,6,1))>$D$2,0,$B17="Annual",1,L17=12,12,$B17="Monthly V",L17*(1+$D$3),$B17="Monthly F",12,$B17="One-Time",0),L17*(1+$D$3))} -> 0 | N17: {=IFERROR(_xlfn.IFS(VALUE(MID(N$5,6,2))>$D$2,0,$B17="Annual",1,M17=12,12,$B17="Monthly V",M17*(1+$D$3),$B17="Monthly F",12,$B17="One-Time",0),M17*(1+$D$3))} -> 0 | R17: =S17/12 -> 0 | S17: =IFERROR($Q17*E17,0) -> 0 | T17: =IFERROR($Q17*F17,0) -> 0 | U17: =IFERROR($Q17*G17,0) -> 0 | V17: =IFERROR($Q17*H17,0) -> 0 | W17: =IFERROR($Q17*I17,0) -> 0 | X17: =IFERROR($Q17*J17,0) -> 0 | Y17: =IFERROR($Q17*K17,0) -> 0 | Z17: =IFERROR($Q17*L17,0) -> 0 | ... AB17: =IFERROR($Q17*N17,0) -> 0 | AD17: =IF(VALUE(MID(AD$5,6,1))<=$D$2,((1+$Q$3)^1-1)*T17,0) -> 0 | AE17: =IF(VALUE(MID(AE$5,6,1))<=$D$2,((1+$Q$3)^2-1)*U17,0) -> 0 | AF17: =IF(VALUE(MID(AF$5,6,1))<=$D$2,((1+$Q$3)^3-1)*V17,0) -> 0 | AG17: =IF(VALUE(MID(AG$5,6,1))<=$D$2,((1+$Q$3)^4-1)*W17,0) -> 0 | AH17: =IF(VALUE(MID(AH$5,6,1))<=$D$2,((1+$Q$3)^5-1)*X17,0) -> 0 | AI17: =IF(VALUE(MID(AI$5,6,1))<=$D$2,((1+$Q$3)^6-1)*Y17,0) -> 0 | AJ17: =IF(VALUE(MID(AJ$5,6,1))<=$D$2,((1+$Q$3)^7-1)*Z17,0) -> 0 | AK17: =IF(VALUE(MID(AK$5,6,1))<=$D$2,((1+$Q$3)^8-1)*AA17,0) -> 0 | AL17: =IF(VALUE(MID(AL$5,6,2))<=$D$2,((1+$Q$3)^9-1)*AB17,0) -> 0 | AM17: =SUM(AC17:AL17) -> 0 | AN17: =SUM(AM17,S17:AB17) -> 0 | AP17: Monthly F | AQ17: 1 | AR17: =IF($AP17="Annual",1,IF($AP17="Monthly F",12,IF($AP17="Monthly V",AQ17*12,IF($AP17="One-Time",1,AQ17*12)))) -> 12 | AS17: {=IFERROR(_xlfn.IFS(VALUE(MID(AS$5,6,1))>$D$2,0,$AP17="Annual",1,AR17=12,12,$AP17="Monthly V",AR17*(1+$BD$2),$AP17="Monthly F",12,$AP17="One-Time",0),AR17*(1+$BD$2))} -> 12 | AT17: {=IFERROR(_xlfn.IFS(VALUE(MID(AT$5,6,1))>$D$2,0,$AP17="Annual",1,AS17=12,12,$AP17="Monthly V",AS17*(1+$BD$2),$AP17="Monthly F",12,$AP17="One-Time",0),AS17*(1+$BD$2))} -> 12 | AU17: {=IFERROR(_xlfn.IFS(VALUE(MID(AU$5,6,1))>$D$2,0,$AP17="Annual",1,AT17=12,12,$AP17="Monthly V",AT17*(1+$BD$2),$AP17="Monthly F",12,$AP17="One-Time",0),AT17*(1+$BD$2))} -> 12 | AV17: {=IFERROR(_xlfn.IFS(VALUE(MID(AV$5,6,1))>$D$2,0,$AP17="Annual",1,AU17=12,12,$AP17="Monthly V",AU17*(1+$BD$2),$AP17="Monthly F",12,$AP17="One-Time",0),AU17*(1+$BD$2))} -> 12 | AW17: {=IFERROR(_xlfn.IFS(VALUE(MID(AW$5,6,1))>$D$2,0,$AP17="Annual",1,AV17=12,12,$AP17="Monthly V",AV17*(1+$BD$2),$AP17="Monthly F",12,$AP17="One-Time",0),AV17*(1+$BD$2))} -> 12 | AX17: {=IFERROR(_xlfn.IFS(VALUE(MID(AX$5,6,1))>$D$2,0,$AP17="Annual",1,AW17=12,12,$AP17="Monthly V",AW17*(1+$BD$2),$AP17="Monthly F",12,$AP17="One-Time",0),AW17*(1+$BD$2))} -> 12 | AY17: {=IFERROR(_xlfn.IFS(VALUE(MID(AY$5,6,1))>$D$2,0,$AP17="Annual",1,AX17=12,12,$AP17="Monthly V",AX17*(1+$D$3),$AP17="Monthly F",12,$AP17="One-Time",0),AX17*(1+$D$3))} -> 0 | AZ17: {=IFERROR(_xlfn.IFS(VALUE(MID(AZ$5,6,1))>$D$2,0,$AP17="Annual",1,AY17=12,12,$AP17="Monthly V",AY17*(1+$D$3),$AP17="Monthly F",12,$AP17="One-Time",0),AY17*(1+$D$3))} -> 0 | BA17: {=IFERROR(_xlfn.IFS(VALUE(MID(BA$5,6,2))>$D$2,0,$AP17="Annual",1,AZ17=12,12,$AP17="Monthly V",AZ17*(1+$D$3),$AP17="Monthly F",12,$AP17="One-Time",0),AZ17*(1+$D$3))} -> 0 | BB17: JHA OpenAnywhere Finicity | BC17: JHA OpenAnywhere | BD17: 200 | BE17: =BF17/12 -> 200 | BF17: =IFERROR(AR17*$BD17,0) -> 2400 | BG17: =IFERROR(AS17*$BD17,0) -> 2400 | BH17: =IFERROR(AT17*$BD17,0) -> 2400 | BI17: =BH17*1.03 -> 2472 | BJ17: =BI17*1.03 -> 2546.16 | BK17: =BJ17*1.03 -> 2622.5448 | BL17: =BK17*1.03 -> 2701.2211 | BM17: =IFERROR(AY17*$BD17,0) -> 0 | BN17: =IFERROR(AZ17*$BD17,0) -> 0 | BO17: =IFERROR(BA17*$BD17,0) -> 0 | BQ17: =IF(VALUE(MID(BQ$5,6,1))<=$D$2,((1+$BD$3)^1-1)*BG17,0) -> 72 | BR17: =IF(VALUE(MID(BR$5,6,1))<=$D$2,((1+$BD$3)^2-1)*BH17,0) -> 146.16 | BS17: =IF(VALUE(MID(BS$5,6,1))<=$D$2,((1+$BD$3)^3-1)*BI17,0) -> 229.22114 | BT17: =IF(VALUE(MID(BT$5,6,1))<=$D$2,((1+$BD$3)^4-1)*BJ17,0) -> 319.56551 | BU17: =IF(VALUE(MID(BU$5,6,1))<=$D$2,((1+$BD$3)^5-1)*BK17,0) -> 417.7034 | BV17: =IF(VALUE(MID(BV$5,6,1))<=$D$2,((1+$BD$3)^6-1)*BL17,0) -> 524.17817 | BW17: =IF(VALUE(MID(BW$5,6,1))<=$D$2,((1+$BD$3)^7-1)*BM17,0) -> 0 | BX17: =IF(VALUE(MID(BX$5,6,1))<=$D$2,((1+$BD$3)^8-1)*BN17,0) -> 0 | BY17: =IF(VALUE(MID(BY$5,6,2))<=$D$2,((1+$BD$3)^9-1)*BO17,0) -> 0 | BZ17: =SUM(BP17:BY17) -> 1708.8282 | CA17: =SUM(BZ17,BF17:BO17) -> 19250.754 | CE17: =IF($CC17="Annual",1,IF($CC17="Monthly F",12,IF($CC17="Monthly V",CD17*12,IF($CC17="One-Time",1,CD17*12)))) -> 0 | CF17: {=IFERROR(_xlfn.IFS(VALUE(MID(CF$5,6,1))>$D$2,0,$CC17="Annual",1,CE17=12,12,$CC17="Monthly V",CE17*(1+$D$3),$CC17="Monthly F",12,$CC17="One-Time",0),CE17*(1+$D$3))} -> 0 | CG17: {=IFERROR(_xlfn.IFS(VALUE(MID(CG$5,6,1))>$D$2,0,$CC17="Annual",1,CF17=12,12,$CC17="Monthly V",CF17*(1+$D$3),$CC17="Monthly F",12,$CC17="One-Time",0),CF17*(1+$D$3))} -> 0 | CH17: {=IFERROR(_xlfn.IFS(VALUE(MID(CH$5,6,1))>$D$2,0,$CC17="Annual",1,CG17=12,12,$CC17="Monthly V",CG17*(1+$D$3),$CC17="Monthly F",12,$CC17="One-Time",0),CG17*(1+$D$3))} -> 0 | CI17: {=IFERROR(_xlfn.IFS(VALUE(MID(CI$5,6,1))>$D$2,0,$CC17="Annual",1,CH17=12,12,$CC17="Monthly V",CH17*(1+$D$3),$CC17="Monthly F",12,$CC17="One-Time",0),CH17*(1+$D$3))} -> 0 | CJ17: {=IFERROR(_xlfn.IFS(VALUE(MID(CJ$5,6,1))>$D$2,0,$CC17="Annual",1,CI17=12,12,$CC17="Monthly V",CI17*(1+$D$3),$CC17="Monthly F",12,$CC17="One-Time",0),CI17*(1+$D$3))} -> 0 | CK17: {=IFERROR(_xlfn.IFS(VALUE(MID(CK$5,6,1))>$D$2,0,$CC17="Annual",1,CJ17=12,12,$CC17="Monthly V",CJ17*(1+$D$3),$CC17="Monthly F",12,$CC17="One-Time",0),CJ17*(1+$D$3))} -> 0 | CL17: {=IFERROR(_xlfn.IFS(VALUE(MID(CL$5,6,1))>$D$2,0,$CC17="Annual",1,CK17=12,12,$CC17="Monthly V",CK17*(1+$D$3),$CC17="Monthly F",12,$CC17="One-Time",0),CK17*(1+$D$3))} -> 0 | CM17: {=IFERROR(_xlfn.IFS(VALUE(MID(CM$5,6,1))>$D$2,0,$CC17="Annual",1,CL17=12,12,$CC17="Monthly V",CL17*(1+$D$3),$CC17="Monthly F",12,$CC17="One-Time",0),CL17*(1+$D$3))} -> 0 | CN17: {=IFERROR(_xlfn.IFS(VALUE(MID(CN$5,6,2))>$D$2,0,$CC17="Annual",1,CM17=12,12,$CC17="Monthly V",CM17*(1+$D$3),$CC17="Monthly F",12,$CC17="One-Time",0),CM17*(1+$D$3))} -> 0 | CQ17: =CR17/12 -> 0 | CR17: =IFERROR(CE17*$CP17,0) -> 0 | CS17: =IFERROR(CF17*$CP17,0) -> 0 | CT17: =IFERROR(CG17*$CP17,0) -> 0 | CU17: =IFERROR(CH17*$CP17,0) -> 0 | CV17: =IFERROR(CI17*$CP17,0) -> 0 | CW17: =IFERROR(CJ17*$CP17,0) -> 0 | CX17: =IFERROR(CK17*$CP17,0) -> 0 | CY17: =IFERROR(CL17*$CP17,0) -> 0 | ... DA17: =IFERROR(CN17*$CP17,0) -> 0 | DC17: =IF(VALUE(MID(DC$5,6,1))<=$D$2,((1+$CP$3)^1-1)*CS17,0) -> 0 | DD17: =IF(VALUE(MID(DD$5,6,1))<=$D$2,((1+$CP$3)^2-1)*CT17,0) -> 0 | DE17: =IF(VALUE(MID(DE$5,6,1))<=$D$2,((1+$CP$3)^3-1)*CU17,0) -> 0 | DF17: =IF(VALUE(MID(DF$5,6,1))<=$D$2,((1+$CP$3)^4-1)*CV17,0) -> 0 | DG17: =IF(VALUE(MID(DG$5,6,1))<=$D$2,((1+$CP$3)^5-1)*CW17,0) -> 0 | DH17: =IF(VALUE(MID(DH$5,6,1))<=$D$2,((1+$CP$3)^6-1)*CX17,0) -> 0 | DI17: =IF(VALUE(MID(DI$5,6,1))<=$D$2,((1+$CP$3)^7-1)*CY17,0) -> 0 | DJ17: =IF(VALUE(MID(DJ$5,6,1))<=$D$2,((1+$CP$3)^8-1)*CZ17,0) -> 0 | DK17: =IF(VALUE(MID(DK$5,6,2))<=$D$2,((1+$CP$3)^9-1)*DA17,0) -> 0 | DL17: =SUM(DB17:DK17) -> 0 | DM17: =SUM(DL17,CR17:DA17) -> 0
AP18: Monthly F | AQ18: 1 | AR18: =IF($AP18="Annual",1,IF($AP18="Monthly F",12,IF($AP18="Monthly V",AQ18*12,IF($AP18="One-Time",1,AQ18*12)))) -> 12 | AS18: {=IFERROR(_xlfn.IFS(VALUE(MID(AS$5,6,1))>$D$2,0,$AP18="Annual",1,AR18=12,12,$AP18="Monthly V",AR18*(1+$BD$2),$AP18="Monthly F",12,$AP18="One-Time",0),AR18*(1+$BD$2))} -> 12 | AT18: {=IFERROR(_xlfn.IFS(VALUE(MID(AT$5,6,1))>$D$2,0,$AP18="Annual",1,AS18=12,12,$AP18="Monthly V",AS18*(1+$BD$2),$AP18="Monthly F",12,$AP18="One-Time",0),AS18*(1+$BD$2))} -> 12 | AU18: {=IFERROR(_xlfn.IFS(VALUE(MID(AU$5,6,1))>$D$2,0,$AP18="Annual",1,AT18=12,12,$AP18="Monthly V",AT18*(1+$BD$2),$AP18="Monthly F",12,$AP18="One-Time",0),AT18*(1+$BD$2))} -> 12 | AV18: {=IFERROR(_xlfn.IFS(VALUE(MID(AV$5,6,1))>$D$2,0,$AP18="Annual",1,AU18=12,12,$AP18="Monthly V",AU18*(1+$BD$2),$AP18="Monthly F",12,$AP18="One-Time",0),AU18*(1+$BD$2))} -> 12 | AW18: {=IFERROR(_xlfn.IFS(VALUE(MID(AW$5,6,1))>$D$2,0,$AP18="Annual",1,AV18=12,12,$AP18="Monthly V",AV18*(1+$BD$2),$AP18="Monthly F",12,$AP18="One-Time",0),AV18*(1+$BD$2))} -> 12 | AX18: {=IFERROR(_xlfn.IFS(VALUE(MID(AX$5,6,1))>$D$2,0,$AP18="Annual",1,AW18=12,12,$AP18="Monthly V",AW18*(1+$BD$2),$AP18="Monthly F",12,$AP18="One-Time",0),AW18*(1+$BD$2))} -> 12 | AY18: {=IFERROR(_xlfn.IFS(VALUE(MID(AY$5,6,1))>$D$2,0,$AP18="Annual",1,AX18=12,12,$AP18="Monthly V",AX18*(1+$D$3),$AP18="Monthly F",12,$AP18="One-Time",0),AX18*(1+$D$3))} -> 0 | AZ18: {=IFERROR(_xlfn.IFS(VALUE(MID(AZ$5,6,1))>$D$2,0,$AP18="Annual",1,AY18=12,12,$AP18="Monthly V",AY18*(1+$D$3),$AP18="Monthly F",12,$AP18="One-Time",0),AY18*(1+$D$3))} -> 0 | BA18: {=IFERROR(_xlfn.IFS(VALUE(MID(BA$5,6,2))>$D$2,0,$AP18="Annual",1,AZ18=12,12,$AP18="Monthly V",AZ18*(1+$D$3),$AP18="Monthly F",12,$AP18="One-Time",0),AZ18*(1+$D$3))} -> 0 | BB18: Banno | BC18: Banno | BD18: 500 | BE18: =BF18/12 -> 500 | BF18: =IFERROR(AR18*$BD18,0) -> 6000 | BG18: =IFERROR(AS18*$BD18,0) -> 6000 | BH18: =IFERROR(AT18*$BD18,0) -> 6000 | BI18: =BH18*1.03 -> 6180 | BJ18: =BI18*1.03 -> 6365.4 | BK18: =BJ18*1.03 -> 6556.362 | BL18: =BK18*1.03 -> 6753.0529 | BM18: =IFERROR(AY18*$BD18,0) -> 0 | BN18: =IFERROR(AZ18*$BD18,0) -> 0 | BO18: =IFERROR(BA18*$BD18,0) -> 0 | BQ18: =IF(VALUE(MID(BQ$5,6,1))<=$D$2,((1+$BD$3)^1-1)*BG18,0) -> 180 | BR18: =IF(VALUE(MID(BR$5,6,1))<=$D$2,((1+$BD$3)^2-1)*BH18,0) -> 365.4 | BS18: =IF(VALUE(MID(BS$5,6,1))<=$D$2,((1+$BD$3)^3-1)*BI18,0) -> 573.05286 | BT18: =IF(VALUE(MID(BT$5,6,1))<=$D$2,((1+$BD$3)^4-1)*BJ18,0) -> 798.91378 | BU18: =IF(VALUE(MID(BU$5,6,1))<=$D$2,((1+$BD$3)^5-1)*BK18,0) -> 1044.2585 | BV18: =IF(VALUE(MID(BV$5,6,1))<=$D$2,((1+$BD$3)^6-1)*BL18,0) -> 1310.4454 | BW18: =IF(VALUE(MID(BW$5,6,1))<=$D$2,((1+$BD$3)^7-1)*BM18,0) -> 0 | BX18: =IF(VALUE(MID(BX$5,6,1))<=$D$2,((1+$BD$3)^8-1)*BN18,0) -> 0 | BY18: =IF(VALUE(MID(BY$5,6,2))<=$D$2,((1+$BD$3)^9-1)*BO18,0) -> 0 | BZ18: =SUM(BP18:BY18) -> 4272.0705 | CA18: =SUM(BZ18,BF18:BO18) -> 48126.885
D19: =IFERROR(AVERAGE(C19:C19),0) -> 0 | E19: =IF($B19="Annual",1,IF($B19="Monthly F",12,IF($B19="Monthly V",D19*12,IF($B19="One-Time",1,D19*12)))) -> 0 | F19: {=IFERROR(_xlfn.IFS(VALUE(MID(F$5,6,1))>$D$2,0,$B19="Annual",1,E19=12,12,$B19="Monthly V",E19*(1+$D$3),$B19="Monthly F",12,$B19="One-Time",0),E19*(1+$D$3))} -> 0 | G19: {=IFERROR(_xlfn.IFS(VALUE(MID(G$5,6,1))>$D$2,0,$B19="Annual",1,F19=12,12,$B19="Monthly V",F19*(1+$D$3),$B19="Monthly F",12,$B19="One-Time",0),F19*(1+$D$3))} -> 0 | H19: {=IFERROR(_xlfn.IFS(VALUE(MID(H$5,6,1))>$D$2,0,$B19="Annual",1,G19=12,12,$B19="Monthly V",G19*(1+$D$3),$B19="Monthly F",12,$B19="One-Time",0),G19*(1+$D$3))} -> 0 | I19: {=IFERROR(_xlfn.IFS(VALUE(MID(I$5,6,1))>$D$2,0,$B19="Annual",1,H19=12,12,$B19="Monthly V",H19*(1+$D$3),$B19="Monthly F",12,$B19="One-Time",0),H19*(1+$D$3))} -> 0 | J19: {=IFERROR(_xlfn.IFS(VALUE(MID(J$5,6,1))>$D$2,0,$B19="Annual",1,I19=12,12,$B19="Monthly V",I19*(1+$D$3),$B19="Monthly F",12,$B19="One-Time",0),I19*(1+$D$3))} -> 0 | K19: {=IFERROR(_xlfn.IFS(VALUE(MID(K$5,6,1))>$D$2,0,$B19="Annual",1,J19=12,12,$B19="Monthly V",J19*(1+$D$3),$B19="Monthly F",12,$B19="One-Time",0),J19*(1+$D$3))} -> 0 | L19: {=IFERROR(_xlfn.IFS(VALUE(MID(L$5,6,1))>$D$2,0,$B19="Annual",1,K19=12,12,$B19="Monthly V",K19*(1+$D$3),$B19="Monthly F",12,$B19="One-Time",0),K19*(1+$D$3))} -> 0 | M19: {=IFERROR(_xlfn.IFS(VALUE(MID(M$5,6,1))>$D$2,0,$B19="Annual",1,L19=12,12,$B19="Monthly V",L19*(1+$D$3),$B19="Monthly F",12,$B19="One-Time",0),L19*(1+$D$3))} -> 0 | N19: {=IFERROR(_xlfn.IFS(VALUE(MID(N$5,6,2))>$D$2,0,$B19="Annual",1,M19=12,12,$B19="Monthly V",M19*(1+$D$3),$B19="Monthly F",12,$B19="One-Time",0),M19*(1+$D$3))} -> 0 | R19: =S19/12 -> 0 | S19: =IFERROR($Q19*E19,0) -> 0 | T19: =IFERROR($Q19*F19,0) -> 0 | U19: =IFERROR($Q19*G19,0) -> 0 | V19: =IFERROR($Q19*H19,0) -> 0 | W19: =IFERROR($Q19*I19,0) -> 0 | X19: =IFERROR($Q19*J19,0) -> 0 | Y19: =IFERROR($Q19*K19,0) -> 0 | Z19: =IFERROR($Q19*L19,0) -> 0 | ... AB19: =IFERROR($Q19*N19,0) -> 0 | AD19: =IF(VALUE(MID(AD$5,6,1))<=$D$2,((1+$Q$3)^1-1)*T19,0) -> 0 | AE19: =IF(VALUE(MID(AE$5,6,1))<=$D$2,((1+$Q$3)^2-1)*U19,0) -> 0 | AF19: =IF(VALUE(MID(AF$5,6,1))<=$D$2,((1+$Q$3)^3-1)*V19,0) -> 0 | AG19: =IF(VALUE(MID(AG$5,6,1))<=$D$2,((1+$Q$3)^4-1)*W19,0) -> 0 | AH19: =IF(VALUE(MID(AH$5,6,1))<=$D$2,((1+$Q$3)^5-1)*X19,0) -> 0 | AI19: =IF(VALUE(MID(AI$5,6,1))<=$D$2,((1+$Q$3)^6-1)*Y19,0) -> 0 | AJ19: =IF(VALUE(MID(AJ$5,6,1))<=$D$2,((1+$Q$3)^7-1)*Z19,0) -> 0 | AK19: =IF(VALUE(MID(AK$5,6,1))<=$D$2,((1+$Q$3)^8-1)*AA19,0) -> 0 | AL19: =IF(VALUE(MID(AL$5,6,2))<=$D$2,((1+$Q$3)^9-1)*AB19,0) -> 0 | AM19: =SUM(AC19:AL19) -> 0 | AN19: =SUM(AM19,S19:AB19) -> 0 | AP19: Monthly F | AQ19: 1 | AR19: =IF($AP19="Annual",1,IF($AP19="Monthly F",12,IF($AP19="Monthly V",AQ19*12,IF($AP19="One-Time",1,AQ19*12)))) -> 12 | AS19: {=IFERROR(_xlfn.IFS(VALUE(MID(AS$5,6,1))>$D$2,0,$AP19="Annual",1,AR19=12,12,$AP19="Monthly V",AR19*(1+$BD$2),$AP19="Monthly F",12,$AP19="One-Time",0),AR19*(1+$BD$2))} -> 12 | AT19: {=IFERROR(_xlfn.IFS(VALUE(MID(AT$5,6,1))>$D$2,0,$AP19="Annual",1,AS19=12,12,$AP19="Monthly V",AS19*(1+$BD$2),$AP19="Monthly F",12,$AP19="One-Time",0),AS19*(1+$BD$2))} -> 12 | AU19: {=IFERROR(_xlfn.IFS(VALUE(MID(AU$5,6,1))>$D$2,0,$AP19="Annual",1,AT19=12,12,$AP19="Monthly V",AT19*(1+$BD$2),$AP19="Monthly F",12,$AP19="One-Time",0),AT19*(1+$BD$2))} -> 12 | AV19: {=IFERROR(_xlfn.IFS(VALUE(MID(AV$5,6,1))>$D$2,0,$AP19="Annual",1,AU19=12,12,$AP19="Monthly V",AU19*(1+$BD$2),$AP19="Monthly F",12,$AP19="One-Time",0),AU19*(1+$BD$2))} -> 12 | AW19: {=IFERROR(_xlfn.IFS(VALUE(MID(AW$5,6,1))>$D$2,0,$AP19="Annual",1,AV19=12,12,$AP19="Monthly V",AV19*(1+$BD$2),$AP19="Monthly F",12,$AP19="One-Time",0),AV19*(1+$BD$2))} -> 12 | AX19: {=IFERROR(_xlfn.IFS(VALUE(MID(AX$5,6,1))>$D$2,0,$AP19="Annual",1,AW19=12,12,$AP19="Monthly V",AW19*(1+$BD$2),$AP19="Monthly F",12,$AP19="One-Time",0),AW19*(1+$BD$2))} -> 12 | AY19: {=IFERROR(_xlfn.IFS(VALUE(MID(AY$5,6,1))>$D$2,0,$AP19="Annual",1,AX19=12,12,$AP19="Monthly V",AX19*(1+$D$3),$AP19="Monthly F",12,$AP19="One-Time",0),AX19*(1+$D$3))} -> 0 | AZ19: {=IFERROR(_xlfn.IFS(VALUE(MID(AZ$5,6,1))>$D$2,0,$AP19="Annual",1,AY19=12,12,$AP19="Monthly V",AY19*(1+$D$3),$AP19="Monthly F",12,$AP19="One-Time",0),AY19*(1+$D$3))} -> 0 | BA19: {=IFERROR(_xlfn.IFS(VALUE(MID(BA$5,6,2))>$D$2,0,$AP19="Annual",1,AZ19=12,12,$AP19="Monthly V",AZ19*(1+$D$3),$AP19="Monthly F",12,$AP19="One-Time",0),AZ19*(1+$D$3))} -> 0 | BB19: Jack Henry Digital Card Issuance and Provisioning - Mastercard | BC19: Banno | BD19: 50 | BE19: =BF19/12 -> 50 | BF19: =IFERROR(AR19*$BD19,0) -> 600 | BG19: =IFERROR(AS19*$BD19,0) -> 600 | BH19: =IFERROR(AT19*$BD19,0) -> 600 | BI19: =BH19*1.03 -> 618 | BJ19: =BI19*1.03 -> 636.54 | BK19: =BJ19*1.03 -> 655.6362 | BL19: =BK19*1.03 -> 675.30529 | BM19: =IFERROR(AY19*$BD19,0) -> 0 | BN19: =IFERROR(AZ19*$BD19,0) -> 0 | BO19: =IFERROR(BA19*$BD19,0) -> 0 | BQ19: =IF(VALUE(MID(BQ$5,6,1))<=$D$2,((1+$BD$3)^1-1)*BG19,0) -> 18 | BR19: =IF(VALUE(MID(BR$5,6,1))<=$D$2,((1+$BD$3)^2-1)*BH19,0) -> 36.54 | BS19: =IF(VALUE(MID(BS$5,6,1))<=$D$2,((1+$BD$3)^3-1)*BI19,0) -> 57.305286 | BT19: =IF(VALUE(MID(BT$5,6,1))<=$D$2,((1+$BD$3)^4-1)*BJ19,0) -> 79.891378 | BU19: =IF(VALUE(MID(BU$5,6,1))<=$D$2,((1+$BD$3)^5-1)*BK19,0) -> 104.42585 | BV19: =IF(VALUE(MID(BV$5,6,1))<=$D$2,((1+$BD$3)^6-1)*BL19,0) -> 131.04454 | BW19: =IF(VALUE(MID(BW$5,6,1))<=$D$2,((1+$BD$3)^7-1)*BM19,0) -> 0 | BX19: =IF(VALUE(MID(BX$5,6,1))<=$D$2,((1+$BD$3)^8-1)*BN19,0) -> 0 | BY19: =IF(VALUE(MID(BY$5,6,2))<=$D$2,((1+$BD$3)^9-1)*BO19,0) -> 0 | BZ19: =SUM(BP19:BY19) -> 427.20705 | CA19: =SUM(BZ19,BF19:BO19) -> 4812.6885 | CE19: =IF($CC19="Annual",1,IF($CC19="Monthly F",12,IF($CC19="Monthly V",CD19*12,IF($CC19="One-Time",1,CD19*12)))) -> 0 | CF19: {=IFERROR(_xlfn.IFS(VALUE(MID(CF$5,6,1))>$D$2,0,$CC19="Annual",1,CE19=12,12,$CC19="Monthly V",CE19*(1+$D$3),$CC19="Monthly F",12,$CC19="One-Time",0),CE19*(1+$D$3))} -> 0 | CG19: {=IFERROR(_xlfn.IFS(VALUE(MID(CG$5,6,1))>$D$2,0,$CC19="Annual",1,CF19=12,12,$CC19="Monthly V",CF19*(1+$D$3),$CC19="Monthly F",12,$CC19="One-Time",0),CF19*(1+$D$3))} -> 0 | CH19: {=IFERROR(_xlfn.IFS(VALUE(MID(CH$5,6,1))>$D$2,0,$CC19="Annual",1,CG19=12,12,$CC19="Monthly V",CG19*(1+$D$3),$CC19="Monthly F",12,$CC19="One-Time",0),CG19*(1+$D$3))} -> 0 | CI19: {=IFERROR(_xlfn.IFS(VALUE(MID(CI$5,6,1))>$D$2,0,$CC19="Annual",1,CH19=12,12,$CC19="Monthly V",CH19*(1+$D$3),$CC19="Monthly F",12,$CC19="One-Time",0),CH19*(1+$D$3))} -> 0 | CJ19: {=IFERROR(_xlfn.IFS(VALUE(MID(CJ$5,6,1))>$D$2,0,$CC19="Annual",1,CI19=12,12,$CC19="Monthly V",CI19*(1+$D$3),$CC19="Monthly F",12,$CC19="One-Time",0),CI19*(1+$D$3))} -> 0 | CK19: {=IFERROR(_xlfn.IFS(VALUE(MID(CK$5,6,1))>$D$2,0,$CC19="Annual",1,CJ19=12,12,$CC19="Monthly V",CJ19*(1+$D$3),$CC19="Monthly F",12,$CC19="One-Time",0),CJ19*(1+$D$3))} -> 0 | CL19: {=IFERROR(_xlfn.IFS(VALUE(MID(CL$5,6,1))>$D$2,0,$CC19="Annual",1,CK19=12,12,$CC19="Monthly V",CK19*(1+$D$3),$CC19="Monthly F",12,$CC19="One-Time",0),CK19*(1+$D$3))} -> 0 | CM19: {=IFERROR(_xlfn.IFS(VALUE(MID(CM$5,6,1))>$D$2,0,$CC19="Annual",1,CL19=12,12,$CC19="Monthly V",CL19*(1+$D$3),$CC19="Monthly F",12,$CC19="One-Time",0),CL19*(1+$D$3))} -> 0 | CN19: {=IFERROR(_xlfn.IFS(VALUE(MID(CN$5,6,2))>$D$2,0,$CC19="Annual",1,CM19=12,12,$CC19="Monthly V",CM19*(1+$D$3),$CC19="Monthly F",12,$CC19="One-Time",0),CM19*(1+$D$3))} -> 0 | CQ19: =CR19/12 -> 0 | CR19: =IFERROR(CE19*$CP19,0) -> 0 | CS19: =IFERROR(CF19*$CP19,0) -> 0 | CT19: =IFERROR(CG19*$CP19,0) -> 0 | CU19: =IFERROR(CH19*$CP19,0) -> 0 | CV19: =IFERROR(CI19*$CP19,0) -> 0 | CW19: =IFERROR(CJ19*$CP19,0) -> 0 | CX19: =IFERROR(CK19*$CP19,0) -> 0 | CY19: =IFERROR(CL19*$CP19,0) -> 0 | ... DA19: =IFERROR(CN19*$CP19,0) -> 0 | DC19: =IF(VALUE(MID(DC$5,6,1))<=$D$2,((1+$CP$3)^1-1)*CS19,0) -> 0 | DD19: =IF(VALUE(MID(DD$5,6,1))<=$D$2,((1+$CP$3)^2-1)*CT19,0) -> 0 | DE19: =IF(VALUE(MID(DE$5,6,1))<=$D$2,((1+$CP$3)^3-1)*CU19,0) -> 0 | DF19: =IF(VALUE(MID(DF$5,6,1))<=$D$2,((1+$CP$3)^4-1)*CV19,0) -> 0 | DG19: =IF(VALUE(MID(DG$5,6,1))<=$D$2,((1+$CP$3)^5-1)*CW19,0) -> 0 | DH19: =IF(VALUE(MID(DH$5,6,1))<=$D$2,((1+$CP$3)^6-1)*CX19,0) -> 0 | DI19: =IF(VALUE(MID(DI$5,6,1))<=$D$2,((1+$CP$3)^7-1)*CY19,0) -> 0 | DJ19: =IF(VALUE(MID(DJ$5,6,1))<=$D$2,((1+$CP$3)^8-1)*CZ19,0) -> 0 | DK19: =IF(VALUE(MID(DK$5,6,2))<=$D$2,((1+$CP$3)^9-1)*DA19,0) -> 0 | DL19: =SUM(DB19:DK19) -> 0 | DM19: =SUM(DL19,CR19:DA19) -> 0
D20: =IFERROR(AVERAGE(C20:C20),0) -> 0 | E20: =IF($B20="Annual",1,IF($B20="Monthly F",12,IF($B20="Monthly V",D20*12,IF($B20="One-Time",1,D20*12)))) -> 0 | F20: {=IFERROR(_xlfn.IFS(VALUE(MID(F$5,6,1))>$D$2,0,$B20="Annual",1,E20=12,12,$B20="Monthly V",E20*(1+$D$3),$B20="Monthly F",12,$B20="One-Time",0),E20*(1+$D$3))} -> 0 | G20: {=IFERROR(_xlfn.IFS(VALUE(MID(G$5,6,1))>$D$2,0,$B20="Annual",1,F20=12,12,$B20="Monthly V",F20*(1+$D$3),$B20="Monthly F",12,$B20="One-Time",0),F20*(1+$D$3))} -> 0 | H20: {=IFERROR(_xlfn.IFS(VALUE(MID(H$5,6,1))>$D$2,0,$B20="Annual",1,G20=12,12,$B20="Monthly V",G20*(1+$D$3),$B20="Monthly F",12,$B20="One-Time",0),G20*(1+$D$3))} -> 0 | I20: {=IFERROR(_xlfn.IFS(VALUE(MID(I$5,6,1))>$D$2,0,$B20="Annual",1,H20=12,12,$B20="Monthly V",H20*(1+$D$3),$B20="Monthly F",12,$B20="One-Time",0),H20*(1+$D$3))} -> 0 | J20: {=IFERROR(_xlfn.IFS(VALUE(MID(J$5,6,1))>$D$2,0,$B20="Annual",1,I20=12,12,$B20="Monthly V",I20*(1+$D$3),$B20="Monthly F",12,$B20="One-Time",0),I20*(1+$D$3))} -> 0 | K20: {=IFERROR(_xlfn.IFS(VALUE(MID(K$5,6,1))>$D$2,0,$B20="Annual",1,J20=12,12,$B20="Monthly V",J20*(1+$D$3),$B20="Monthly F",12,$B20="One-Time",0),J20*(1+$D$3))} -> 0 | L20: {=IFERROR(_xlfn.IFS(VALUE(MID(L$5,6,1))>$D$2,0,$B20="Annual",1,K20=12,12,$B20="Monthly V",K20*(1+$D$3),$B20="Monthly F",12,$B20="One-Time",0),K20*(1+$D$3))} -> 0 | M20: {=IFERROR(_xlfn.IFS(VALUE(MID(M$5,6,1))>$D$2,0,$B20="Annual",1,L20=12,12,$B20="Monthly V",L20*(1+$D$3),$B20="Monthly F",12,$B20="One-Time",0),L20*(1+$D$3))} -> 0 | N20: {=IFERROR(_xlfn.IFS(VALUE(MID(N$5,6,2))>$D$2,0,$B20="Annual",1,M20=12,12,$B20="Monthly V",M20*(1+$D$3),$B20="Monthly F",12,$B20="One-Time",0),M20*(1+$D$3))} -> 0 | R20: =S20/12 -> 0 | S20: =IFERROR($Q20*E20,0) -> 0 | T20: =IFERROR($Q20*F20,0) -> 0 | U20: =IFERROR($Q20*G20,0) -> 0 | V20: =IFERROR($Q20*H20,0) -> 0 | W20: =IFERROR($Q20*I20,0) -> 0 | X20: =IFERROR($Q20*J20,0) -> 0 | Y20: =IFERROR($Q20*K20,0) -> 0 | Z20: =IFERROR($Q20*L20,0) -> 0 | ... AB20: =IFERROR($Q20*N20,0) -> 0 | AD20: =IF(VALUE(MID(AD$5,6,1))<=$D$2,((1+$Q$3)^1-1)*T20,0) -> 0 | AE20: =IF(VALUE(MID(AE$5,6,1))<=$D$2,((1+$Q$3)^2-1)*U20,0) -> 0 | AF20: =IF(VALUE(MID(AF$5,6,1))<=$D$2,((1+$Q$3)^3-1)*V20,0) -> 0 | AG20: =IF(VALUE(MID(AG$5,6,1))<=$D$2,((1+$Q$3)^4-1)*W20,0) -> 0 | AH20: =IF(VALUE(MID(AH$5,6,1))<=$D$2,((1+$Q$3)^5-1)*X20,0) -> 0 | AI20: =IF(VALUE(MID(AI$5,6,1))<=$D$2,((1+$Q$3)^6-1)*Y20,0) -> 0 | AJ20: =IF(VALUE(MID(AJ$5,6,1))<=$D$2,((1+$Q$3)^7-1)*Z20,0) -> 0 | AK20: =IF(VALUE(MID(AK$5,6,1))<=$D$2,((1+$Q$3)^8-1)*AA20,0) -> 0 | AL20: =IF(VALUE(MID(AL$5,6,2))<=$D$2,((1+$Q$3)^9-1)*AB20,0) -> 0 | AM20: =SUM(AC20:AL20) -> 0 | AN20: =SUM(AM20,S20:AB20) -> 0 | AP20: Monthly V | AQ20: 5000 | AR20: =IF($AP20="Annual",1,IF($AP20="Monthly F",12,IF($AP20="Monthly V",AQ20*12,IF($AP20="One-Time",1,AQ20*12)))) -> 60000 | AS20: {=IFERROR(_xlfn.IFS(VALUE(MID(AS$5,6,1))>$D$2,0,$AP20="Annual",1,AR20=12,12,$AP20="Monthly V",AR20*(1+$BD$2),$AP20="Monthly F",12,$AP20="One-Time",0),AR20*(1+$BD$2))} -> 60000 | AT20: {=IFERROR(_xlfn.IFS(VALUE(MID(AT$5,6,1))>$D$2,0,$AP20="Annual",1,AS20=12,12,$AP20="Monthly V",AS20*(1+$BD$2),$AP20="Monthly F",12,$AP20="One-Time",0),AS20*(1+$BD$2))} -> 60000 | AU20: {=IFERROR(_xlfn.IFS(VALUE(MID(AU$5,6,1))>$D$2,0,$AP20="Annual",1,AT20=12,12,$AP20="Monthly V",AT20*(1+$BD$2),$AP20="Monthly F",12,$AP20="One-Time",0),AT20*(1+$BD$2))} -> 60000 | AV20: {=IFERROR(_xlfn.IFS(VALUE(MID(AV$5,6,1))>$D$2,0,$AP20="Annual",1,AU20=12,12,$AP20="Monthly V",AU20*(1+$BD$2),$AP20="Monthly F",12,$AP20="One-Time",0),AU20*(1+$BD$2))} -> 60000 | AW20: {=IFERROR(_xlfn.IFS(VALUE(MID(AW$5,6,1))>$D$2,0,$AP20="Annual",1,AV20=12,12,$AP20="Monthly V",AV20*(1+$BD$2),$AP20="Monthly F",12,$AP20="One-Time",0),AV20*(1+$BD$2))} -> 60000 | AX20: {=IFERROR(_xlfn.IFS(VALUE(MID(AX$5,6,1))>$D$2,0,$AP20="Annual",1,AW20=12,12,$AP20="Monthly V",AW20*(1+$BD$2),$AP20="Monthly F",12,$AP20="One-Time",0),AW20*(1+$BD$2))} -> 60000 | AY20: {=IFERROR(_xlfn.IFS(VALUE(MID(AY$5,6,1))>$D$2,0,$AP20="Annual",1,AX20=12,12,$AP20="Monthly V",AX20*(1+$D$3),$AP20="Monthly F",12,$AP20="One-Time",0),AX20*(1+$D$3))} -> 0 | AZ20: {=IFERROR(_xlfn.IFS(VALUE(MID(AZ$5,6,1))>$D$2,0,$AP20="Annual",1,AY20=12,12,$AP20="Monthly V",AY20*(1+$D$3),$AP20="Monthly F",12,$AP20="One-Time",0),AY20*(1+$D$3))} -> 0 | BA20: {=IFERROR(_xlfn.IFS(VALUE(MID(BA$5,6,2))>$D$2,0,$AP20="Annual",1,AZ20=12,12,$AP20="Monthly V",AZ20*(1+$D$3),$AP20="Monthly F",12,$AP20="One-Time",0),AZ20*(1+$D$3))} -> 0 | BB20: Electronic Statement Interactive (ESI) | BC20: Electronic Statements Interactive(ESI) | BD20: 0.021 | BE20: =BF20/12 -> 105 | BF20: =IFERROR(AR20*$BD20,0) -> 1260 | BG20: =IFERROR(AS20*$BD20,0) -> 1260 | BH20: =IFERROR(AT20*$BD20,0) -> 1260 | BI20: =BH20*1.03 -> 1297.8 | BJ20: =BI20*1.03 -> 1336.734 | BK20: =BJ20*1.03 -> 1376.836 | BL20: =BK20*1.03 -> 1418.1411 | BM20: =IFERROR(AY20*$BD20,0) -> 0 | BN20: =IFERROR(AZ20*$BD20,0) -> 0 | BO20: =IFERROR(BA20*$BD20,0) -> 0 | BQ20: =IF(VALUE(MID(BQ$5,6,1))<=$D$2,((1+$BD$3)^1-1)*BG20,0) -> 37.8 | BR20: =IF(VALUE(MID(BR$5,6,1))<=$D$2,((1+$BD$3)^2-1)*BH20,0) -> 76.734 | BS20: =IF(VALUE(MID(BS$5,6,1))<=$D$2,((1+$BD$3)^3-1)*BI20,0) -> 120.3411 | BT20: =IF(VALUE(MID(BT$5,6,1))<=$D$2,((1+$BD$3)^4-1)*BJ20,0) -> 167.77189 | BU20: =IF(VALUE(MID(BU$5,6,1))<=$D$2,((1+$BD$3)^5-1)*BK20,0) -> 219.29428 | BV20: =IF(VALUE(MID(BV$5,6,1))<=$D$2,((1+$BD$3)^6-1)*BL20,0) -> 275.19354 | BW20: =IF(VALUE(MID(BW$5,6,1))<=$D$2,((1+$BD$3)^7-1)*BM20,0) -> 0 | BX20: =IF(VALUE(MID(BX$5,6,1))<=$D$2,((1+$BD$3)^8-1)*BN20,0) -> 0 | BY20: =IF(VALUE(MID(BY$5,6,2))<=$D$2,((1+$BD$3)^9-1)*BO20,0) -> 0 | BZ20: =SUM(BP20:BY20) -> 897.13481 | CA20: =SUM(BZ20,BF20:BO20) -> 10106.646
B21: Recurring Monthly and Annual Fees - Non-Bundle REQUIRED FIS products | AP21: Monthly V | AQ21: 5000 | AR21: =IF($AP21="Annual",1,IF($AP21="Monthly F",12,IF($AP21="Monthly V",AQ21*12,IF($AP21="One-Time",1,AQ21*12)))) -> 60000 | AS21: {=IFERROR(_xlfn.IFS(VALUE(MID(AS$5,6,1))>$D$2,0,$AP21="Annual",1,AR21=12,12,$AP21="Monthly V",AR21*(1+$BD$2),$AP21="Monthly F",12,$AP21="One-Time",0),AR21*(1+$BD$2))} -> 60000 | AT21: {=IFERROR(_xlfn.IFS(VALUE(MID(AT$5,6,1))>$D$2,0,$AP21="Annual",1,AS21=12,12,$AP21="Monthly V",AS21*(1+$BD$2),$AP21="Monthly F",12,$AP21="One-Time",0),AS21*(1+$BD$2))} -> 60000 | AU21: {=IFERROR(_xlfn.IFS(VALUE(MID(AU$5,6,1))>$D$2,0,$AP21="Annual",1,AT21=12,12,$AP21="Monthly V",AT21*(1+$BD$2),$AP21="Monthly F",12,$AP21="One-Time",0),AT21*(1+$BD$2))} -> 60000 | AV21: {=IFERROR(_xlfn.IFS(VALUE(MID(AV$5,6,1))>$D$2,0,$AP21="Annual",1,AU21=12,12,$AP21="Monthly V",AU21*(1+$BD$2),$AP21="Monthly F",12,$AP21="One-Time",0),AU21*(1+$BD$2))} -> 60000 | AW21: {=IFERROR(_xlfn.IFS(VALUE(MID(AW$5,6,1))>$D$2,0,$AP21="Annual",1,AV21=12,12,$AP21="Monthly V",AV21*(1+$BD$2),$AP21="Monthly F",12,$AP21="One-Time",0),AV21*(1+$BD$2))} -> 60000 | AX21: {=IFERROR(_xlfn.IFS(VALUE(MID(AX$5,6,1))>$D$2,0,$AP21="Annual",1,AW21=12,12,$AP21="Monthly V",AW21*(1+$BD$2),$AP21="Monthly F",12,$AP21="One-Time",0),AW21*(1+$BD$2))} -> 60000 | AY21: {=IFERROR(_xlfn.IFS(VALUE(MID(AY$5,6,1))>$D$2,0,$AP21="Annual",1,AX21=12,12,$AP21="Monthly V",AX21*(1+$D$3),$AP21="Monthly F",12,$AP21="One-Time",0),AX21*(1+$D$3))} -> 0 | AZ21: {=IFERROR(_xlfn.IFS(VALUE(MID(AZ$5,6,1))>$D$2,0,$AP21="Annual",1,AY21=12,12,$AP21="Monthly V",AY21*(1+$D$3),$AP21="Monthly F",12,$AP21="One-Time",0),AY21*(1+$D$3))} -> 0 | BA21: {=IFERROR(_xlfn.IFS(VALUE(MID(BA$5,6,2))>$D$2,0,$AP21="Annual",1,AZ21=12,12,$AP21="Monthly V",AZ21*(1+$D$3),$AP21="Monthly F",12,$AP21="One-Time",0),AZ21*(1+$D$3))} -> 0 | BB21: OutLink Item Imaging | BC21: OutLink Item Processing | BD21: 0.3338 | BE21: =BF21/12 -> 1669 | BF21: =IFERROR(AR21*$BD21,0) -> 20028 | BG21: =IFERROR(AS21*$BD21,0) -> 20028 | BH21: =IFERROR(AT21*$BD21,0) -> 20028 | BI21: =BH21*1.03 -> 20628.84 | BJ21: =BI21*1.03 -> 21247.705 | BK21: =BJ21*1.03 -> 21885.136 | BL21: =BK21*1.03 -> 22541.69 | BM21: =IFERROR(AY21*$BD21,0) -> 0 | BN21: =IFERROR(AZ21*$BD21,0) -> 0 | BO21: =IFERROR(BA21*$BD21,0) -> 0 | BQ21: =IF(VALUE(MID(BQ$5,6,1))<=$D$2,((1+$BD$3)^1-1)*BG21,0) -> 600.84 | BR21: =IF(VALUE(MID(BR$5,6,1))<=$D$2,((1+$BD$3)^2-1)*BH21,0) -> 1219.7052 | BS21: =IF(VALUE(MID(BS$5,6,1))<=$D$2,((1+$BD$3)^3-1)*BI21,0) -> 1912.8504 | BT21: =IF(VALUE(MID(BT$5,6,1))<=$D$2,((1+$BD$3)^4-1)*BJ21,0) -> 2666.7742 | BU21: =IF(VALUE(MID(BU$5,6,1))<=$D$2,((1+$BD$3)^5-1)*BK21,0) -> 3485.7348 | BV21: =IF(VALUE(MID(BV$5,6,1))<=$D$2,((1+$BD$3)^6-1)*BL21,0) -> 4374.2668 | BW21: =IF(VALUE(MID(BW$5,6,1))<=$D$2,((1+$BD$3)^7-1)*BM21,0) -> 0 | BX21: =IF(VALUE(MID(BX$5,6,1))<=$D$2,((1+$BD$3)^8-1)*BN21,0) -> 0 | BY21: =IF(VALUE(MID(BY$5,6,2))<=$D$2,((1+$BD$3)^9-1)*BO21,0) -> 0 | BZ21: =SUM(BP21:BY21) -> 14260.171 | CA21: =SUM(BZ21,BF21:BO21) -> 160647.54 | CE21: =IF($CC21="Annual",1,IF($CC21="Monthly F",12,IF($CC21="Monthly V",CD21*12,IF($CC21="One-Time",1,CD21*12)))) -> 0 | CF21: {=IFERROR(_xlfn.IFS(VALUE(MID(CF$5,6,1))>$D$2,0,$CC21="Annual",1,CE21=12,12,$CC21="Monthly V",CE21*(1+$D$3),$CC21="Monthly F",12,$CC21="One-Time",0),CE21*(1+$D$3))} -> 0 | CG21: {=IFERROR(_xlfn.IFS(VALUE(MID(CG$5,6,1))>$D$2,0,$CC21="Annual",1,CF21=12,12,$CC21="Monthly V",CF21*(1+$D$3),$CC21="Monthly F",12,$CC21="One-Time",0),CF21*(1+$D$3))} -> 0 | CH21: {=IFERROR(_xlfn.IFS(VALUE(MID(CH$5,6,1))>$D$2,0,$CC21="Annual",1,CG21=12,12,$CC21="Monthly V",CG21*(1+$D$3),$CC21="Monthly F",12,$CC21="One-Time",0),CG21*(1+$D$3))} -> 0 | CI21: {=IFERROR(_xlfn.IFS(VALUE(MID(CI$5,6,1))>$D$2,0,$CC21="Annual",1,CH21=12,12,$CC21="Monthly V",CH21*(1+$D$3),$CC21="Monthly F",12,$CC21="One-Time",0),CH21*(1+$D$3))} -> 0 | CJ21: {=IFERROR(_xlfn.IFS(VALUE(MID(CJ$5,6,1))>$D$2,0,$CC21="Annual",1,CI21=12,12,$CC21="Monthly V",CI21*(1+$D$3),$CC21="Monthly F",12,$CC21="One-Time",0),CI21*(1+$D$3))} -> 0 | CK21: {=IFERROR(_xlfn.IFS(VALUE(MID(CK$5,6,1))>$D$2,0,$CC21="Annual",1,CJ21=12,12,$CC21="Monthly V",CJ21*(1+$D$3),$CC21="Monthly F",12,$CC21="One-Time",0),CJ21*(1+$D$3))} -> 0 | CL21: {=IFERROR(_xlfn.IFS(VALUE(MID(CL$5,6,1))>$D$2,0,$CC21="Annual",1,CK21=12,12,$CC21="Monthly V",CK21*(1+$D$3),$CC21="Monthly F",12,$CC21="One-Time",0),CK21*(1+$D$3))} -> 0 | CM21: {=IFERROR(_xlfn.IFS(VALUE(MID(CM$5,6,1))>$D$2,0,$CC21="Annual",1,CL21=12,12,$CC21="Monthly V",CL21*(1+$D$3),$CC21="Monthly F",12,$CC21="One-Time",0),CL21*(1+$D$3))} -> 0 | CN21: {=IFERROR(_xlfn.IFS(VALUE(MID(CN$5,6,2))>$D$2,0,$CC21="Annual",1,CM21=12,12,$CC21="Monthly V",CM21*(1+$D$3),$CC21="Monthly F",12,$CC21="One-Time",0),CM21*(1+$D$3))} -> 0 | CQ21: =CR21/12 -> 0 | CR21: =IFERROR(CE21*$CP21,0) -> 0 | CS21: =IFERROR(CF21*$CP21,0) -> 0 | CT21: =IFERROR(CG21*$CP21,0) -> 0 | CU21: =IFERROR(CH21*$CP21,0) -> 0 | CV21: =IFERROR(CI21*$CP21,0) -> 0 | CW21: =IFERROR(CJ21*$CP21,0) -> 0 | CX21: =IFERROR(CK21*$CP21,0) -> 0 | CY21: =IFERROR(CL21*$CP21,0) -> 0 | ... DA21: =IFERROR(CN21*$CP21,0) -> 0 | DC21: =IF(VALUE(MID(DC$5,6,1))<=$D$2,((1+$CP$3)^1-1)*CS21,0) -> 0 | DD21: =IF(VALUE(MID(DD$5,6,1))<=$D$2,((1+$CP$3)^2-1)*CT21,0) -> 0 | DE21: =IF(VALUE(MID(DE$5,6,1))<=$D$2,((1+$CP$3)^3-1)*CU21,0) -> 0 | DF21: =IF(VALUE(MID(DF$5,6,1))<=$D$2,((1+$CP$3)^4-1)*CV21,0) -> 0 | DG21: =IF(VALUE(MID(DG$5,6,1))<=$D$2,((1+$CP$3)^5-1)*CW21,0) -> 0 | DH21: =IF(VALUE(MID(DH$5,6,1))<=$D$2,((1+$CP$3)^6-1)*CX21,0) -> 0 | DI21: =IF(VALUE(MID(DI$5,6,1))<=$D$2,((1+$CP$3)^7-1)*CY21,0) -> 0 | DJ21: =IF(VALUE(MID(DJ$5,6,1))<=$D$2,((1+$CP$3)^8-1)*CZ21,0) -> 0 | DK21: =IF(VALUE(MID(DK$5,6,2))<=$D$2,((1+$CP$3)^9-1)*DA21,0) -> 0 | DL21: =SUM(DB21:DK21) -> 0 | DM21: =SUM(DL21,CR21:DA21) -> 0
O22: Paper and Envelopes | R22: =S22/12 -> 0 | S22: =IFERROR($Q22*E22,0) -> 0 | T22: =IFERROR($Q22*F22,0) -> 0 | U22: =IFERROR($Q22*G22,0) -> 0 | V22: =IFERROR($Q22*H22,0) -> 0 | W22: =IFERROR($Q22*I22,0) -> 0 | X22: =IFERROR($Q22*J22,0) -> 0 | Y22: =IFERROR($Q22*K22,0) -> 0 | Z22: =IFERROR($Q22*L22,0) -> 0 | ... AB22: =IFERROR($Q22*N22,0) -> 0 | AD22: =IF(VALUE(MID(AD$5,6,1))<=$D$2,((1+$Q$3)^1-1)*T22,0) -> 0 | AE22: =IF(VALUE(MID(AE$5,6,1))<=$D$2,((1+$Q$3)^2-1)*U22,0) -> 0 | AF22: =IF(VALUE(MID(AF$5,6,1))<=$D$2,((1+$Q$3)^3-1)*V22,0) -> 0 | AG22: =IF(VALUE(MID(AG$5,6,1))<=$D$2,((1+$Q$3)^4-1)*W22,0) -> 0 | AH22: =IF(VALUE(MID(AH$5,6,1))<=$D$2,((1+$Q$3)^5-1)*X22,0) -> 0 | AI22: =IF(VALUE(MID(AI$5,6,1))<=$D$2,((1+$Q$3)^6-1)*Y22,0) -> 0 | AJ22: =IF(VALUE(MID(AJ$5,6,1))<=$D$2,((1+$Q$3)^7-1)*Z22,0) -> 0 | AK22: =IF(VALUE(MID(AK$5,6,1))<=$D$2,((1+$Q$3)^8-1)*AA22,0) -> 0 | AL22: =IF(VALUE(MID(AL$5,6,2))<=$D$2,((1+$Q$3)^9-1)*AB22,0) -> 0 | AM22: =SUM(AC22:AL22) -> 0 | AN22: =SUM(AM22,S22:AB22) -> 0 | AP22: Monthly F | AQ22: 1 | AR22: =IF($AP22="Annual",1,IF($AP22="Monthly F",12,IF($AP22="Monthly V",AQ22*12,IF($AP22="One-Time",1,AQ22*12)))) -> 12 | AS22: {=IFERROR(_xlfn.IFS(VALUE(MID(AS$5,6,1))>$D$2,0,$AP22="Annual",1,AR22=12,12,$AP22="Monthly V",AR22*(1+$BD$2),$AP22="Monthly F",12,$AP22="One-Time",0),AR22*(1+$BD$2))} -> 12 | AT22: {=IFERROR(_xlfn.IFS(VALUE(MID(AT$5,6,1))>$D$2,0,$AP22="Annual",1,AS22=12,12,$AP22="Monthly V",AS22*(1+$BD$2),$AP22="Monthly F",12,$AP22="One-Time",0),AS22*(1+$BD$2))} -> 12 | AU22: {=IFERROR(_xlfn.IFS(VALUE(MID(AU$5,6,1))>$D$2,0,$AP22="Annual",1,AT22=12,12,$AP22="Monthly V",AT22*(1+$BD$2),$AP22="Monthly F",12,$AP22="One-Time",0),AT22*(1+$BD$2))} -> 12 | AV22: {=IFERROR(_xlfn.IFS(VALUE(MID(AV$5,6,1))>$D$2,0,$AP22="Annual",1,AU22=12,12,$AP22="Monthly V",AU22*(1+$BD$2),$AP22="Monthly F",12,$AP22="One-Time",0),AU22*(1+$BD$2))} -> 12 | AW22: {=IFERROR(_xlfn.IFS(VALUE(MID(AW$5,6,1))>$D$2,0,$AP22="Annual",1,AV22=12,12,$AP22="Monthly V",AV22*(1+$BD$2),$AP22="Monthly F",12,$AP22="One-Time",0),AV22*(1+$BD$2))} -> 12 | AX22: {=IFERROR(_xlfn.IFS(VALUE(MID(AX$5,6,1))>$D$2,0,$AP22="Annual",1,AW22=12,12,$AP22="Monthly V",AW22*(1+$BD$2),$AP22="Monthly F",12,$AP22="One-Time",0),AW22*(1+$BD$2))} -> 12 | AY22: {=IFERROR(_xlfn.IFS(VALUE(MID(AY$5,6,1))>$D$2,0,$AP22="Annual",1,AX22=12,12,$AP22="Monthly V",AX22*(1+$D$3),$AP22="Monthly F",12,$AP22="One-Time",0),AX22*(1+$D$3))} -> 0 | AZ22: {=IFERROR(_xlfn.IFS(VALUE(MID(AZ$5,6,1))>$D$2,0,$AP22="Annual",1,AY22=12,12,$AP22="Monthly V",AY22*(1+$D$3),$AP22="Monthly F",12,$AP22="One-Time",0),AY22*(1+$D$3))} -> 0 | BA22: {=IFERROR(_xlfn.IFS(VALUE(MID(BA$5,6,2))>$D$2,0,$AP22="Annual",1,AZ22=12,12,$AP22="Monthly V",AZ22*(1+$D$3),$AP22="Monthly F",12,$AP22="One-Time",0),AZ22*(1+$D$3))} -> 0 | BB22: Outlink Statement Printing | BC22: OutLink Item Processing | BD22: 900 | BE22: =BF22/12 -> 900 | BF22: =IFERROR(AR22*$BD22,0) -> 10800 | BG22: =IFERROR(AS22*$BD22,0) -> 10800 | BH22: =IFERROR(AT22*$BD22,0) -> 10800 | BI22: =BH22*1.03 -> 11124 | BJ22: =BI22*1.03 -> 11457.72 | BK22: =BJ22*1.03 -> 11801.452 | BL22: =BK22*1.03 -> 12155.495 | BM22: =IFERROR(AY22*$BD22,0) -> 0 | BN22: =IFERROR(AZ22*$BD22,0) -> 0 | BO22: =IFERROR(BA22*$BD22,0) -> 0 | BQ22: =IF(VALUE(MID(BQ$5,6,1))<=$D$2,((1+$BD$3)^1-1)*BG22,0) -> 324 | BR22: =IF(VALUE(MID(BR$5,6,1))<=$D$2,((1+$BD$3)^2-1)*BH22,0) -> 657.72 | BS22: =IF(VALUE(MID(BS$5,6,1))<=$D$2,((1+$BD$3)^3-1)*BI22,0) -> 1031.4951 | BT22: =IF(VALUE(MID(BT$5,6,1))<=$D$2,((1+$BD$3)^4-1)*BJ22,0) -> 1438.0448 | BU22: =IF(VALUE(MID(BU$5,6,1))<=$D$2,((1+$BD$3)^5-1)*BK22,0) -> 1879.6653 | BV22: =IF(VALUE(MID(BV$5,6,1))<=$D$2,((1+$BD$3)^6-1)*BL22,0) -> 2358.8017 | BW22: =IF(VALUE(MID(BW$5,6,1))<=$D$2,((1+$BD$3)^7-1)*BM22,0) -> 0 | BX22: =IF(VALUE(MID(BX$5,6,1))<=$D$2,((1+$BD$3)^8-1)*BN22,0) -> 0 | BY22: =IF(VALUE(MID(BY$5,6,2))<=$D$2,((1+$BD$3)^9-1)*BO22,0) -> 0 | BZ22: =SUM(BP22:BY22) -> 7689.727 | CA22: =SUM(BZ22,BF22:BO22) -> 86628.394 | CE22: =IF($CC22="Annual",1,IF($CC22="Monthly F",12,IF($CC22="Monthly V",CD22*12,IF($CC22="One-Time",1,CD22*12)))) -> 0 | CF22: {=IFERROR(_xlfn.IFS(VALUE(MID(CF$5,6,1))>$D$2,0,$CC22="Annual",1,CE22=12,12,$CC22="Monthly V",CE22*(1+$D$3),$CC22="Monthly F",12,$CC22="One-Time",0),CE22*(1+$D$3))} -> 0 | CG22: {=IFERROR(_xlfn.IFS(VALUE(MID(CG$5,6,1))>$D$2,0,$CC22="Annual",1,CF22=12,12,$CC22="Monthly V",CF22*(1+$D$3),$CC22="Monthly F",12,$CC22="One-Time",0),CF22*(1+$D$3))} -> 0 | CH22: {=IFERROR(_xlfn.IFS(VALUE(MID(CH$5,6,1))>$D$2,0,$CC22="Annual",1,CG22=12,12,$CC22="Monthly V",CG22*(1+$D$3),$CC22="Monthly F",12,$CC22="One-Time",0),CG22*(1+$D$3))} -> 0 | CI22: {=IFERROR(_xlfn.IFS(VALUE(MID(CI$5,6,1))>$D$2,0,$CC22="Annual",1,CH22=12,12,$CC22="Monthly V",CH22*(1+$D$3),$CC22="Monthly F",12,$CC22="One-Time",0),CH22*(1+$D$3))} -> 0 | CJ22: {=IFERROR(_xlfn.IFS(VALUE(MID(CJ$5,6,1))>$D$2,0,$CC22="Annual",1,CI22=12,12,$CC22="Monthly V",CI22*(1+$D$3),$CC22="Monthly F",12,$CC22="One-Time",0),CI22*(1+$D$3))} -> 0 | CK22: {=IFERROR(_xlfn.IFS(VALUE(MID(CK$5,6,1))>$D$2,0,$CC22="Annual",1,CJ22=12,12,$CC22="Monthly V",CJ22*(1+$D$3),$CC22="Monthly F",12,$CC22="One-Time",0),CJ22*(1+$D$3))} -> 0 | CL22: {=IFERROR(_xlfn.IFS(VALUE(MID(CL$5,6,1))>$D$2,0,$CC22="Annual",1,CK22=12,12,$CC22="Monthly V",CK22*(1+$D$3),$CC22="Monthly F",12,$CC22="One-Time",0),CK22*(1+$D$3))} -> 0 | CM22: {=IFERROR(_xlfn.IFS(VALUE(MID(CM$5,6,1))>$D$2,0,$CC22="Annual",1,CL22=12,12,$CC22="Monthly V",CL22*(1+$D$3),$CC22="Monthly F",12,$CC22="One-Time",0),CL22*(1+$D$3))} -> 0 | CN22: {=IFERROR(_xlfn.IFS(VALUE(MID(CN$5,6,2))>$D$2,0,$CC22="Annual",1,CM22=12,12,$CC22="Monthly V",CM22*(1+$D$3),$CC22="Monthly F",12,$CC22="One-Time",0),CM22*(1+$D$3))} -> 0 | CQ22: =CR22/12 -> 0 | CR22: =IFERROR(CE22*$CP22,0) -> 0 | CS22: =IFERROR(CF22*$CP22,0) -> 0 | CT22: =IFERROR(CG22*$CP22,0) -> 0 | CU22: =IFERROR(CH22*$CP22,0) -> 0 | CV22: =IFERROR(CI22*$CP22,0) -> 0 | CW22: =IFERROR(CJ22*$CP22,0) -> 0 | CX22: =IFERROR(CK22*$CP22,0) -> 0 | CY22: =IFERROR(CL22*$CP22,0) -> 0 | ... DA22: =IFERROR(CN22*$CP22,0) -> 0 | DC22: =IF(VALUE(MID(DC$5,6,1))<=$D$2,((1+$CP$3)^1-1)*CS22,0) -> 0 | DD22: =IF(VALUE(MID(DD$5,6,1))<=$D$2,((1+$CP$3)^2-1)*CT22,0) -> 0 | DE22: =IF(VALUE(MID(DE$5,6,1))<=$D$2,((1+$CP$3)^3-1)*CU22,0) -> 0 | DF22: =IF(VALUE(MID(DF$5,6,1))<=$D$2,((1+$CP$3)^4-1)*CV22,0) -> 0 | DG22: =IF(VALUE(MID(DG$5,6,1))<=$D$2,((1+$CP$3)^5-1)*CW22,0) -> 0 | DH22: =IF(VALUE(MID(DH$5,6,1))<=$D$2,((1+$CP$3)^6-1)*CX22,0) -> 0 | DI22: =IF(VALUE(MID(DI$5,6,1))<=$D$2,((1+$CP$3)^7-1)*CY22,0) -> 0 | DJ22: =IF(VALUE(MID(DJ$5,6,1))<=$D$2,((1+$CP$3)^8-1)*CZ22,0) -> 0 | DK22: =IF(VALUE(MID(DK$5,6,2))<=$D$2,((1+$CP$3)^9-1)*DA22,0) -> 0 | DL22: =SUM(DB22:DK22) -> 0 | DM22: =SUM(DL22,CR22:DA22) -> 0
B23: Monthly V | C23: 1000 | D23: =IFERROR(AVERAGE(C23:C23),0) -> 1000 | E23: =IF($B23="Annual",1,IF($B23="Monthly F",12,IF($B23="Monthly V",D23*12,IF($B23="One-Time",1,D23*12)))) -> 12000 | F23: {=IFERROR(_xlfn.IFS(VALUE(MID(F$5,6,1))>$D$2,0,$B23="Annual",1,E23=12,12,$B23="Monthly V",E23*(1+$D$3),$B23="Monthly F",12,$B23="One-Time",0),E23*(1+$D$3))} -> 14400 | G23: {=IFERROR(_xlfn.IFS(VALUE(MID(G$5,6,1))>$D$2,0,$B23="Annual",1,F23=12,12,$B23="Monthly V",F23*(1+$D$3),$B23="Monthly F",12,$B23="One-Time",0),F23*(1+$D$3))} -> 17280 | H23: {=IFERROR(_xlfn.IFS(VALUE(MID(H$5,6,1))>$D$2,0,$B23="Annual",1,G23=12,12,$B23="Monthly V",G23*(1+$D$3),$B23="Monthly F",12,$B23="One-Time",0),G23*(1+$D$3))} -> 20736 | I23: {=IFERROR(_xlfn.IFS(VALUE(MID(I$5,6,1))>$D$2,0,$B23="Annual",1,H23=12,12,$B23="Monthly V",H23*(1+$D$3),$B23="Monthly F",12,$B23="One-Time",0),H23*(1+$D$3))} -> 24883.2 | J23: {=IFERROR(_xlfn.IFS(VALUE(MID(J$5,6,1))>$D$2,0,$B23="Annual",1,I23=12,12,$B23="Monthly V",I23*(1+$D$3),$B23="Monthly F",12,$B23="One-Time",0),I23*(1+$D$3))} -> 29859.84 | K23: {=IFERROR(_xlfn.IFS(VALUE(MID(K$5,6,1))>$D$2,0,$B23="Annual",1,J23=12,12,$B23="Monthly V",J23*(1+$D$3),$B23="Monthly F",12,$B23="One-Time",0),J23*(1+$D$3))} -> 35831.808 | L23: {=IFERROR(_xlfn.IFS(VALUE(MID(L$5,6,1))>$D$2,0,$B23="Annual",1,K23=12,12,$B23="Monthly V",K23*(1+$D$3),$B23="Monthly F",12,$B23="One-Time",0),K23*(1+$D$3))} -> 0 | M23: {=IFERROR(_xlfn.IFS(VALUE(MID(M$5,6,1))>$D$2,0,$B23="Annual",1,L23=12,12,$B23="Monthly V",L23*(1+$D$3),$B23="Monthly F",12,$B23="One-Time",0),L23*(1+$D$3))} -> 0 | N23: {=IFERROR(_xlfn.IFS(VALUE(MID(N$5,6,2))>$D$2,0,$B23="Annual",1,M23=12,12,$B23="Monthly V",M23*(1+$D$3),$B23="Monthly F",12,$B23="One-Time",0),M23*(1+$D$3))} -> 0 | O23: Per piece of paper | P23: Output Solutions | Q23: 0.0136 | R23: =S23/12 -> 13.6 | S23: =IFERROR($Q23*E23,0) -> 163.2 | T23: =IFERROR($Q23*F23,0) -> 195.84 | U23: =IFERROR($Q23*G23,0) -> 235.008 | V23: =IFERROR($Q23*H23,0) -> 282.0096 | W23: =IFERROR($Q23*I23,0) -> 338.41152 | X23: =IFERROR($Q23*J23,0) -> 406.09382 | Y23: =IFERROR($Q23*K23,0) -> 487.31259 | Z23: =IFERROR($Q23*L23,0) -> 0 | ... AB23: =IFERROR($Q23*N23,0) -> 0 | AD23: =IF(VALUE(MID(AD$5,6,1))<=$D$2,((1+$Q$3)^1-1)*T23,0) -> 5.8752 | AE23: =IF(VALUE(MID(AE$5,6,1))<=$D$2,((1+$Q$3)^2-1)*U23,0) -> 14.311987 | AF23: =IF(VALUE(MID(AF$5,6,1))<=$D$2,((1+$Q$3)^3-1)*V23,0) -> 26.149904 | AG23: =IF(VALUE(MID(AG$5,6,1))<=$D$2,((1+$Q$3)^4-1)*W23,0) -> 42.473627 | AH23: =IF(VALUE(MID(AH$5,6,1))<=$D$2,((1+$Q$3)^5-1)*X23,0) -> 64.680218 | AI23: =IF(VALUE(MID(AI$5,6,1))<=$D$2,((1+$Q$3)^6-1)*Y23,0) -> 94.564127 | AJ23: =IF(VALUE(MID(AJ$5,6,1))<=$D$2,((1+$Q$3)^7-1)*Z23,0) -> 0 | AK23: =IF(VALUE(MID(AK$5,6,1))<=$D$2,((1+$Q$3)^8-1)*AA23,0) -> 0 | AL23: =IF(VALUE(MID(AL$5,6,2))<=$D$2,((1+$Q$3)^9-1)*AB23,0) -> 0 | AM23: =SUM(AC23:AL23) -> 248.05506 | AN23: =SUM(AM23,S23:AB23) -> 2355.9306 | AP23: Monthly V | AQ23: 5000 | AR23: =IF($AP23="Annual",1,IF($AP23="Monthly F",12,IF($AP23="Monthly V",AQ23*12,IF($AP23="One-Time",1,AQ23*12)))) -> 60000 | AS23: {=IFERROR(_xlfn.IFS(VALUE(MID(AS$5,6,1))>$D$2,0,$AP23="Annual",1,AR23=12,12,$AP23="Monthly V",AR23*(1+$BD$2),$AP23="Monthly F",12,$AP23="One-Time",0),AR23*(1+$BD$2))} -> 60000 | AT23: {=IFERROR(_xlfn.IFS(VALUE(MID(AT$5,6,1))>$D$2,0,$AP23="Annual",1,AS23=12,12,$AP23="Monthly V",AS23*(1+$BD$2),$AP23="Monthly F",12,$AP23="One-Time",0),AS23*(1+$BD$2))} -> 60000 | AU23: {=IFERROR(_xlfn.IFS(VALUE(MID(AU$5,6,1))>$D$2,0,$AP23="Annual",1,AT23=12,12,$AP23="Monthly V",AT23*(1+$BD$2),$AP23="Monthly F",12,$AP23="One-Time",0),AT23*(1+$BD$2))} -> 60000 | AV23: {=IFERROR(_xlfn.IFS(VALUE(MID(AV$5,6,1))>$D$2,0,$AP23="Annual",1,AU23=12,12,$AP23="Monthly V",AU23*(1+$BD$2),$AP23="Monthly F",12,$AP23="One-Time",0),AU23*(1+$BD$2))} -> 60000 | AW23: {=IFERROR(_xlfn.IFS(VALUE(MID(AW$5,6,1))>$D$2,0,$AP23="Annual",1,AV23=12,12,$AP23="Monthly V",AV23*(1+$BD$2),$AP23="Monthly F",12,$AP23="One-Time",0),AV23*(1+$BD$2))} -> 60000 | AX23: {=IFERROR(_xlfn.IFS(VALUE(MID(AX$5,6,1))>$D$2,0,$AP23="Annual",1,AW23=12,12,$AP23="Monthly V",AW23*(1+$BD$2),$AP23="Monthly F",12,$AP23="One-Time",0),AW23*(1+$BD$2))} -> 60000 | AY23: {=IFERROR(_xlfn.IFS(VALUE(MID(AY$5,6,1))>$D$2,0,$AP23="Annual",1,AX23=12,12,$AP23="Monthly V",AX23*(1+$D$3),$AP23="Monthly F",12,$AP23="One-Time",0),AX23*(1+$D$3))} -> 0 | AZ23: {=IFERROR(_xlfn.IFS(VALUE(MID(AZ$5,6,1))>$D$2,0,$AP23="Annual",1,AY23=12,12,$AP23="Monthly V",AY23*(1+$D$3),$AP23="Monthly F",12,$AP23="One-Time",0),AY23*(1+$D$3))} -> 0 | BA23: {=IFERROR(_xlfn.IFS(VALUE(MID(BA$5,6,2))>$D$2,0,$AP23="Annual",1,AZ23=12,12,$AP23="Monthly V",AZ23*(1+$D$3),$AP23="Monthly F",12,$AP23="One-Time",0),AZ23*(1+$D$3))} -> 0 | BB23: Synergy ECM | BC23: Synergy | BD23: 0.2055 | BE23: =BF23/12 -> 1027.5 | BF23: =IFERROR(AR23*$BD23,0) -> 12330 | BG23: =IFERROR(AS23*$BD23,0) -> 12330 | BH23: =IFERROR(AT23*$BD23,0) -> 12330 | BI23: =BH23*1.03 -> 12699.9 | BJ23: =BI23*1.03 -> 13080.897 | BK23: =BJ23*1.03 -> 13473.324 | BL23: =BK23*1.03 -> 13877.524 | BM23: =IFERROR(AY23*$BD23,0) -> 0 | BN23: =IFERROR(AZ23*$BD23,0) -> 0 | BO23: =IFERROR(BA23*$BD23,0) -> 0 | BQ23: =IF(VALUE(MID(BQ$5,6,1))<=$D$2,((1+$BD$3)^1-1)*BG23,0) -> 369.9 | BR23: =IF(VALUE(MID(BR$5,6,1))<=$D$2,((1+$BD$3)^2-1)*BH23,0) -> 750.897 | BS23: =IF(VALUE(MID(BS$5,6,1))<=$D$2,((1+$BD$3)^3-1)*BI23,0) -> 1177.6236 | BT23: =IF(VALUE(MID(BT$5,6,1))<=$D$2,((1+$BD$3)^4-1)*BJ23,0) -> 1641.7678 | BU23: =IF(VALUE(MID(BU$5,6,1))<=$D$2,((1+$BD$3)^5-1)*BK23,0) -> 2145.9512 | BV23: =IF(VALUE(MID(BV$5,6,1))<=$D$2,((1+$BD$3)^6-1)*BL23,0) -> 2692.9653 | BW23: =IF(VALUE(MID(BW$5,6,1))<=$D$2,((1+$BD$3)^7-1)*BM23,0) -> 0 | BX23: =IF(VALUE(MID(BX$5,6,1))<=$D$2,((1+$BD$3)^8-1)*BN23,0) -> 0 | BY23: =IF(VALUE(MID(BY$5,6,2))<=$D$2,((1+$BD$3)^9-1)*BO23,0) -> 0 | BZ23: =SUM(BP23:BY23) -> 8779.105 | CA23: =SUM(BZ23,BF23:BO23) -> 98900.75 | CE23: =IF($CC23="Annual",1,IF($CC23="Monthly F",12,IF($CC23="Monthly V",CD23*12,IF($CC23="One-Time",1,CD23*12)))) -> 0 | CF23: {=IFERROR(_xlfn.IFS(VALUE(MID(CF$5,6,1))>$D$2,0,$CC23="Annual",1,CE23=12,12,$CC23="Monthly V",CE23*(1+$D$3),$CC23="Monthly F",12,$CC23="One-Time",0),CE23*(1+$D$3))} -> 0 | CG23: {=IFERROR(_xlfn.IFS(VALUE(MID(CG$5,6,1))>$D$2,0,$CC23="Annual",1,CF23=12,12,$CC23="Monthly V",CF23*(1+$D$3),$CC23="Monthly F",12,$CC23="One-Time",0),CF23*(1+$D$3))} -> 0 | CH23: {=IFERROR(_xlfn.IFS(VALUE(MID(CH$5,6,1))>$D$2,0,$CC23="Annual",1,CG23=12,12,$CC23="Monthly V",CG23*(1+$D$3),$CC23="Monthly F",12,$CC23="One-Time",0),CG23*(1+$D$3))} -> 0 | CI23: {=IFERROR(_xlfn.IFS(VALUE(MID(CI$5,6,1))>$D$2,0,$CC23="Annual",1,CH23=12,12,$CC23="Monthly V",CH23*(1+$D$3),$CC23="Monthly F",12,$CC23="One-Time",0),CH23*(1+$D$3))} -> 0 | CJ23: {=IFERROR(_xlfn.IFS(VALUE(MID(CJ$5,6,1))>$D$2,0,$CC23="Annual",1,CI23=12,12,$CC23="Monthly V",CI23*(1+$D$3),$CC23="Monthly F",12,$CC23="One-Time",0),CI23*(1+$D$3))} -> 0 | CK23: {=IFERROR(_xlfn.IFS(VALUE(MID(CK$5,6,1))>$D$2,0,$CC23="Annual",1,CJ23=12,12,$CC23="Monthly V",CJ23*(1+$D$3),$CC23="Monthly F",12,$CC23="One-Time",0),CJ23*(1+$D$3))} -> 0 | CL23: {=IFERROR(_xlfn.IFS(VALUE(MID(CL$5,6,1))>$D$2,0,$CC23="Annual",1,CK23=12,12,$CC23="Monthly V",CK23*(1+$D$3),$CC23="Monthly F",12,$CC23="One-Time",0),CK23*(1+$D$3))} -> 0 | CM23: {=IFERROR(_xlfn.IFS(VALUE(MID(CM$5,6,1))>$D$2,0,$CC23="Annual",1,CL23=12,12,$CC23="Monthly V",CL23*(1+$D$3),$CC23="Monthly F",12,$CC23="One-Time",0),CL23*(1+$D$3))} -> 0 | CN23: {=IFERROR(_xlfn.IFS(VALUE(MID(CN$5,6,2))>$D$2,0,$CC23="Annual",1,CM23=12,12,$CC23="Monthly V",CM23*(1+$D$3),$CC23="Monthly F",12,$CC23="One-Time",0),CM23*(1+$D$3))} -> 0 | CQ23: =CR23/12 -> 0 | CR23: =IFERROR(CE23*$CP23,0) -> 0 | CS23: =IFERROR(CF23*$CP23,0) -> 0 | CT23: =IFERROR(CG23*$CP23,0) -> 0 | CU23: =IFERROR(CH23*$CP23,0) -> 0 | CV23: =IFERROR(CI23*$CP23,0) -> 0 | CW23: =IFERROR(CJ23*$CP23,0) -> 0 | CX23: =IFERROR(CK23*$CP23,0) -> 0 | CY23: =IFERROR(CL23*$CP23,0) -> 0 | ... DA23: =IFERROR(CN23*$CP23,0) -> 0 | DC23: =IF(VALUE(MID(DC$5,6,1))<=$D$2,((1+$CP$3)^1-1)*CS23,0) -> 0 | DD23: =IF(VALUE(MID(DD$5,6,1))<=$D$2,((1+$CP$3)^2-1)*CT23,0) -> 0 | DE23: =IF(VALUE(MID(DE$5,6,1))<=$D$2,((1+$CP$3)^3-1)*CU23,0) -> 0 | DF23: =IF(VALUE(MID(DF$5,6,1))<=$D$2,((1+$CP$3)^4-1)*CV23,0) -> 0 | DG23: =IF(VALUE(MID(DG$5,6,1))<=$D$2,((1+$CP$3)^5-1)*CW23,0) -> 0 | DH23: =IF(VALUE(MID(DH$5,6,1))<=$D$2,((1+$CP$3)^6-1)*CX23,0) -> 0 | DI23: =IF(VALUE(MID(DI$5,6,1))<=$D$2,((1+$CP$3)^7-1)*CY23,0) -> 0 | DJ23: =IF(VALUE(MID(DJ$5,6,1))<=$D$2,((1+$CP$3)^8-1)*CZ23,0) -> 0 | DK23: =IF(VALUE(MID(DK$5,6,2))<=$D$2,((1+$CP$3)^9-1)*DA23,0) -> 0 | DL23: =SUM(DB23:DK23) -> 0 | DM23: =SUM(DL23,CR23:DA23) -> 0
B24: Monthly V | C24: 5000 | D24: =IFERROR(AVERAGE(C24:C24),0) -> 5000 | E24: =IF($B24="Annual",1,IF($B24="Monthly F",12,IF($B24="Monthly V",D24*12,IF($B24="One-Time",1,D24*12)))) -> 60000 | F24: {=IFERROR(_xlfn.IFS(VALUE(MID(F$5,6,1))>$D$2,0,$B24="Annual",1,E24=12,12,$B24="Monthly V",E24*(1+$D$3),$B24="Monthly F",12,$B24="One-Time",0),E24*(1+$D$3))} -> 72000 | G24: {=IFERROR(_xlfn.IFS(VALUE(MID(G$5,6,1))>$D$2,0,$B24="Annual",1,F24=12,12,$B24="Monthly V",F24*(1+$D$3),$B24="Monthly F",12,$B24="One-Time",0),F24*(1+$D$3))} -> 86400 | H24: {=IFERROR(_xlfn.IFS(VALUE(MID(H$5,6,1))>$D$2,0,$B24="Annual",1,G24=12,12,$B24="Monthly V",G24*(1+$D$3),$B24="Monthly F",12,$B24="One-Time",0),G24*(1+$D$3))} -> 103680 | I24: {=IFERROR(_xlfn.IFS(VALUE(MID(I$5,6,1))>$D$2,0,$B24="Annual",1,H24=12,12,$B24="Monthly V",H24*(1+$D$3),$B24="Monthly F",12,$B24="One-Time",0),H24*(1+$D$3))} -> 124416 | J24: {=IFERROR(_xlfn.IFS(VALUE(MID(J$5,6,1))>$D$2,0,$B24="Annual",1,I24=12,12,$B24="Monthly V",I24*(1+$D$3),$B24="Monthly F",12,$B24="One-Time",0),I24*(1+$D$3))} -> 149299.2 | K24: {=IFERROR(_xlfn.IFS(VALUE(MID(K$5,6,1))>$D$2,0,$B24="Annual",1,J24=12,12,$B24="Monthly V",J24*(1+$D$3),$B24="Monthly F",12,$B24="One-Time",0),J24*(1+$D$3))} -> 179159.04 | L24: {=IFERROR(_xlfn.IFS(VALUE(MID(L$5,6,1))>$D$2,0,$B24="Annual",1,K24=12,12,$B24="Monthly V",K24*(1+$D$3),$B24="Monthly F",12,$B24="One-Time",0),K24*(1+$D$3))} -> 0 | M24: {=IFERROR(_xlfn.IFS(VALUE(MID(M$5,6,1))>$D$2,0,$B24="Annual",1,L24=12,12,$B24="Monthly V",L24*(1+$D$3),$B24="Monthly F",12,$B24="One-Time",0),L24*(1+$D$3))} -> 0 | N24: {=IFERROR(_xlfn.IFS(VALUE(MID(N$5,6,2))>$D$2,0,$B24="Annual",1,M24=12,12,$B24="Monthly V",M24*(1+$D$3),$B24="Monthly F",12,$B24="One-Time",0),M24*(1+$D$3))} -> 0 | O24: Per envelope x 500 | P24: Output Solutions | Q24: 0.0314 | R24: =S24/12 -> 157 | S24: =IFERROR($Q24*E24,0) -> 1884 | T24: =IFERROR($Q24*F24,0) -> 2260.8 | U24: =IFERROR($Q24*G24,0) -> 2712.96 | V24: =IFERROR($Q24*H24,0) -> 3255.552 | W24: =IFERROR($Q24*I24,0) -> 3906.6624 | X24: =IFERROR($Q24*J24,0) -> 4687.9949 | Y24: =IFERROR($Q24*K24,0) -> 5625.5939 | Z24: =IFERROR($Q24*L24,0) -> 0 | ... AB24: =IFERROR($Q24*N24,0) -> 0 | AD24: =IF(VALUE(MID(AD$5,6,1))<=$D$2,((1+$Q$3)^1-1)*T24,0) -> 67.824 | AE24: =IF(VALUE(MID(AE$5,6,1))<=$D$2,((1+$Q$3)^2-1)*U24,0) -> 165.21926 | AF24: =IF(VALUE(MID(AF$5,6,1))<=$D$2,((1+$Q$3)^3-1)*V24,0) -> 301.87757 | AG24: =IF(VALUE(MID(AG$5,6,1))<=$D$2,((1+$Q$3)^4-1)*W24,0) -> 490.32055 | AH24: =IF(VALUE(MID(AH$5,6,1))<=$D$2,((1+$Q$3)^5-1)*X24,0) -> 746.67604 | AI24: =IF(VALUE(MID(AI$5,6,1))<=$D$2,((1+$Q$3)^6-1)*Y24,0) -> 1091.6594 | AJ24: =IF(VALUE(MID(AJ$5,6,1))<=$D$2,((1+$Q$3)^7-1)*Z24,0) -> 0 | AK24: =IF(VALUE(MID(AK$5,6,1))<=$D$2,((1+$Q$3)^8-1)*AA24,0) -> 0 | AL24: =IF(VALUE(MID(AL$5,6,2))<=$D$2,((1+$Q$3)^9-1)*AB24,0) -> 0 | AM24: =SUM(AC24:AL24) -> 2863.5768 | AN24: =SUM(AM24,S24:AB24) -> 27197.14 | AP24: Monthly V | AQ24: 5000 | AR24: =IF($AP24="Annual",1,IF($AP24="Monthly F",12,IF($AP24="Monthly V",AQ24*12,IF($AP24="One-Time",1,AQ24*12)))) -> 60000 | AS24: {=IFERROR(_xlfn.IFS(VALUE(MID(AS$5,6,1))>$D$2,0,$AP24="Annual",1,AR24=12,12,$AP24="Monthly V",AR24*(1+$BD$2),$AP24="Monthly F",12,$AP24="One-Time",0),AR24*(1+$BD$2))} -> 60000 | AT24: {=IFERROR(_xlfn.IFS(VALUE(MID(AT$5,6,1))>$D$2,0,$AP24="Annual",1,AS24=12,12,$AP24="Monthly V",AS24*(1+$BD$2),$AP24="Monthly F",12,$AP24="One-Time",0),AS24*(1+$BD$2))} -> 60000 | AU24: {=IFERROR(_xlfn.IFS(VALUE(MID(AU$5,6,1))>$D$2,0,$AP24="Annual",1,AT24=12,12,$AP24="Monthly V",AT24*(1+$BD$2),$AP24="Monthly F",12,$AP24="One-Time",0),AT24*(1+$BD$2))} -> 60000 | AV24: {=IFERROR(_xlfn.IFS(VALUE(MID(AV$5,6,1))>$D$2,0,$AP24="Annual",1,AU24=12,12,$AP24="Monthly V",AU24*(1+$BD$2),$AP24="Monthly F",12,$AP24="One-Time",0),AU24*(1+$BD$2))} -> 60000 | AW24: {=IFERROR(_xlfn.IFS(VALUE(MID(AW$5,6,1))>$D$2,0,$AP24="Annual",1,AV24=12,12,$AP24="Monthly V",AV24*(1+$BD$2),$AP24="Monthly F",12,$AP24="One-Time",0),AV24*(1+$BD$2))} -> 60000 | AX24: {=IFERROR(_xlfn.IFS(VALUE(MID(AX$5,6,1))>$D$2,0,$AP24="Annual",1,AW24=12,12,$AP24="Monthly V",AW24*(1+$BD$2),$AP24="Monthly F",12,$AP24="One-Time",0),AW24*(1+$BD$2))} -> 60000 | AY24: {=IFERROR(_xlfn.IFS(VALUE(MID(AY$5,6,1))>$D$2,0,$AP24="Annual",1,AX24=12,12,$AP24="Monthly V",AX24*(1+$D$3),$AP24="Monthly F",12,$AP24="One-Time",0),AX24*(1+$D$3))} -> 0 | AZ24: {=IFERROR(_xlfn.IFS(VALUE(MID(AZ$5,6,1))>$D$2,0,$AP24="Annual",1,AY24=12,12,$AP24="Monthly V",AY24*(1+$D$3),$AP24="Monthly F",12,$AP24="One-Time",0),AY24*(1+$D$3))} -> 0 | BA24: {=IFERROR(_xlfn.IFS(VALUE(MID(BA$5,6,2))>$D$2,0,$AP24="Annual",1,AZ24=12,12,$AP24="Monthly V",AZ24*(1+$D$3),$AP24="Monthly F",12,$AP24="One-Time",0),AZ24*(1+$D$3))} -> 0 | BB24: Synergy Productivity | BC24: Synergy | BD24: 0.0765 | BE24: =BF24/12 -> 382.5 | BF24: =IFERROR(AR24*$BD24,0) -> 4590 | BG24: =IFERROR(AS24*$BD24,0) -> 4590 | BH24: =IFERROR(AT24*$BD24,0) -> 4590 | BI24: =BH24*1.03 -> 4727.7 | BJ24: =BI24*1.03 -> 4869.531 | BK24: =BJ24*1.03 -> 5015.6169 | BL24: =BK24*1.03 -> 5166.0854 | BM24: =IFERROR(AY24*$BD24,0) -> 0 | BN24: =IFERROR(AZ24*$BD24,0) -> 0 | BO24: =IFERROR(BA24*$BD24,0) -> 0 | BQ24: =IF(VALUE(MID(BQ$5,6,1))<=$D$2,((1+$BD$3)^1-1)*BG24,0) -> 137.7 | BR24: =IF(VALUE(MID(BR$5,6,1))<=$D$2,((1+$BD$3)^2-1)*BH24,0) -> 279.531 | BS24: =IF(VALUE(MID(BS$5,6,1))<=$D$2,((1+$BD$3)^3-1)*BI24,0) -> 438.38544 | BT24: =IF(VALUE(MID(BT$5,6,1))<=$D$2,((1+$BD$3)^4-1)*BJ24,0) -> 611.16904 | BU24: =IF(VALUE(MID(BU$5,6,1))<=$D$2,((1+$BD$3)^5-1)*BK24,0) -> 798.85774 | BV24: =IF(VALUE(MID(BV$5,6,1))<=$D$2,((1+$BD$3)^6-1)*BL24,0) -> 1002.4907 | BW24: =IF(VALUE(MID(BW$5,6,1))<=$D$2,((1+$BD$3)^7-1)*BM24,0) -> 0 | BX24: =IF(VALUE(MID(BX$5,6,1))<=$D$2,((1+$BD$3)^8-1)*BN24,0) -> 0 | BY24: =IF(VALUE(MID(BY$5,6,2))<=$D$2,((1+$BD$3)^9-1)*BO24,0) -> 0 | BZ24: =SUM(BP24:BY24) -> 3268.134 | CA24: =SUM(BZ24,BF24:BO24) -> 36817.067 | CE24: =IF($CC24="Annual",1,IF($CC24="Monthly F",12,IF($CC24="Monthly V",CD24*12,IF($CC24="One-Time",1,CD24*12)))) -> 0 | CF24: {=IFERROR(_xlfn.IFS(VALUE(MID(CF$5,6,1))>$D$2,0,$CC24="Annual",1,CE24=12,12,$CC24="Monthly V",CE24*(1+$D$3),$CC24="Monthly F",12,$CC24="One-Time",0),CE24*(1+$D$3))} -> 0 | CG24: {=IFERROR(_xlfn.IFS(VALUE(MID(CG$5,6,1))>$D$2,0,$CC24="Annual",1,CF24=12,12,$CC24="Monthly V",CF24*(1+$D$3),$CC24="Monthly F",12,$CC24="One-Time",0),CF24*(1+$D$3))} -> 0 | CH24: {=IFERROR(_xlfn.IFS(VALUE(MID(CH$5,6,1))>$D$2,0,$CC24="Annual",1,CG24=12,12,$CC24="Monthly V",CG24*(1+$D$3),$CC24="Monthly F",12,$CC24="One-Time",0),CG24*(1+$D$3))} -> 0 | CI24: {=IFERROR(_xlfn.IFS(VALUE(MID(CI$5,6,1))>$D$2,0,$CC24="Annual",1,CH24=12,12,$CC24="Monthly V",CH24*(1+$D$3),$CC24="Monthly F",12,$CC24="One-Time",0),CH24*(1+$D$3))} -> 0 | CJ24: {=IFERROR(_xlfn.IFS(VALUE(MID(CJ$5,6,1))>$D$2,0,$CC24="Annual",1,CI24=12,12,$CC24="Monthly V",CI24*(1+$D$3),$CC24="Monthly F",12,$CC24="One-Time",0),CI24*(1+$D$3))} -> 0 | CK24: {=IFERROR(_xlfn.IFS(VALUE(MID(CK$5,6,1))>$D$2,0,$CC24="Annual",1,CJ24=12,12,$CC24="Monthly V",CJ24*(1+$D$3),$CC24="Monthly F",12,$CC24="One-Time",0),CJ24*(1+$D$3))} -> 0 | CL24: {=IFERROR(_xlfn.IFS(VALUE(MID(CL$5,6,1))>$D$2,0,$CC24="Annual",1,CK24=12,12,$CC24="Monthly V",CK24*(1+$D$3),$CC24="Monthly F",12,$CC24="One-Time",0),CK24*(1+$D$3))} -> 0 | CM24: {=IFERROR(_xlfn.IFS(VALUE(MID(CM$5,6,1))>$D$2,0,$CC24="Annual",1,CL24=12,12,$CC24="Monthly V",CL24*(1+$D$3),$CC24="Monthly F",12,$CC24="One-Time",0),CL24*(1+$D$3))} -> 0 | CN24: {=IFERROR(_xlfn.IFS(VALUE(MID(CN$5,6,2))>$D$2,0,$CC24="Annual",1,CM24=12,12,$CC24="Monthly V",CM24*(1+$D$3),$CC24="Monthly F",12,$CC24="One-Time",0),CM24*(1+$D$3))} -> 0 | CQ24: =CR24/12 -> 0 | CR24: =IFERROR(CE24*$CP24,0) -> 0 | CS24: =IFERROR(CF24*$CP24,0) -> 0 | CT24: =IFERROR(CG24*$CP24,0) -> 0 | CU24: =IFERROR(CH24*$CP24,0) -> 0 | CV24: =IFERROR(CI24*$CP24,0) -> 0 | CW24: =IFERROR(CJ24*$CP24,0) -> 0 | CX24: =IFERROR(CK24*$CP24,0) -> 0 | CY24: =IFERROR(CL24*$CP24,0) -> 0 | ... DA24: =IFERROR(CN24*$CP24,0) -> 0 | DC24: =IF(VALUE(MID(DC$5,6,1))<=$D$2,((1+$CP$3)^1-1)*CS24,0) -> 0 | DD24: =IF(VALUE(MID(DD$5,6,1))<=$D$2,((1+$CP$3)^2-1)*CT24,0) -> 0 | DE24: =IF(VALUE(MID(DE$5,6,1))<=$D$2,((1+$CP$3)^3-1)*CU24,0) -> 0 | DF24: =IF(VALUE(MID(DF$5,6,1))<=$D$2,((1+$CP$3)^4-1)*CV24,0) -> 0 | DG24: =IF(VALUE(MID(DG$5,6,1))<=$D$2,((1+$CP$3)^5-1)*CW24,0) -> 0 | DH24: =IF(VALUE(MID(DH$5,6,1))<=$D$2,((1+$CP$3)^6-1)*CX24,0) -> 0 | DI24: =IF(VALUE(MID(DI$5,6,1))<=$D$2,((1+$CP$3)^7-1)*CY24,0) -> 0 | DJ24: =IF(VALUE(MID(DJ$5,6,1))<=$D$2,((1+$CP$3)^8-1)*CZ24,0) -> 0 | DK24: =IF(VALUE(MID(DK$5,6,2))<=$D$2,((1+$CP$3)^9-1)*DA24,0) -> 0 | DL24: =SUM(DB24:DK24) -> 0 | DM24: =SUM(DL24,CR24:DA24) -> 0
O25: Card Production | R25: =S25/12 -> 0 | S25: =IFERROR($Q25*E25,0) -> 0 | T25: =IFERROR($Q25*F25,0) -> 0 | U25: =IFERROR($Q25*G25,0) -> 0 | V25: =IFERROR($Q25*H25,0) -> 0 | W25: =IFERROR($Q25*I25,0) -> 0 | X25: =IFERROR($Q25*J25,0) -> 0 | Y25: =IFERROR($Q25*K25,0) -> 0 | Z25: =IFERROR($Q25*L25,0) -> 0 | ... AB25: =IFERROR($Q25*N25,0) -> 0 | AD25: =IF(VALUE(MID(AD$5,6,1))<=$D$2,((1+$Q$3)^1-1)*T25,0) -> 0 | AE25: =IF(VALUE(MID(AE$5,6,1))<=$D$2,((1+$Q$3)^2-1)*U25,0) -> 0 | AF25: =IF(VALUE(MID(AF$5,6,1))<=$D$2,((1+$Q$3)^3-1)*V25,0) -> 0 | AG25: =IF(VALUE(MID(AG$5,6,1))<=$D$2,((1+$Q$3)^4-1)*W25,0) -> 0 | AH25: =IF(VALUE(MID(AH$5,6,1))<=$D$2,((1+$Q$3)^5-1)*X25,0) -> 0 | AI25: =IF(VALUE(MID(AI$5,6,1))<=$D$2,((1+$Q$3)^6-1)*Y25,0) -> 0 | AJ25: =IF(VALUE(MID(AJ$5,6,1))<=$D$2,((1+$Q$3)^7-1)*Z25,0) -> 0 | AK25: =IF(VALUE(MID(AK$5,6,1))<=$D$2,((1+$Q$3)^8-1)*AA25,0) -> 0 | AL25: =IF(VALUE(MID(AL$5,6,2))<=$D$2,((1+$Q$3)^9-1)*AB25,0) -> 0 | AM25: =SUM(AC25:AL25) -> 0 | AN25: =SUM(AM25,S25:AB25) -> 0 | AP25: Monthly V | AQ25: 5000 | AR25: =IF($AP25="Annual",1,IF($AP25="Monthly F",12,IF($AP25="Monthly V",AQ25*12,IF($AP25="One-Time",1,AQ25*12)))) -> 60000 | AS25: {=IFERROR(_xlfn.IFS(VALUE(MID(AS$5,6,1))>$D$2,0,$AP25="Annual",1,AR25=12,12,$AP25="Monthly V",AR25*(1+$BD$2),$AP25="Monthly F",12,$AP25="One-Time",0),AR25*(1+$BD$2))} -> 60000 | AT25: {=IFERROR(_xlfn.IFS(VALUE(MID(AT$5,6,1))>$D$2,0,$AP25="Annual",1,AS25=12,12,$AP25="Monthly V",AS25*(1+$BD$2),$AP25="Monthly F",12,$AP25="One-Time",0),AS25*(1+$BD$2))} -> 60000 | AU25: {=IFERROR(_xlfn.IFS(VALUE(MID(AU$5,6,1))>$D$2,0,$AP25="Annual",1,AT25=12,12,$AP25="Monthly V",AT25*(1+$BD$2),$AP25="Monthly F",12,$AP25="One-Time",0),AT25*(1+$BD$2))} -> 60000 | AV25: {=IFERROR(_xlfn.IFS(VALUE(MID(AV$5,6,1))>$D$2,0,$AP25="Annual",1,AU25=12,12,$AP25="Monthly V",AU25*(1+$BD$2),$AP25="Monthly F",12,$AP25="One-Time",0),AU25*(1+$BD$2))} -> 60000 | AW25: {=IFERROR(_xlfn.IFS(VALUE(MID(AW$5,6,1))>$D$2,0,$AP25="Annual",1,AV25=12,12,$AP25="Monthly V",AV25*(1+$BD$2),$AP25="Monthly F",12,$AP25="One-Time",0),AV25*(1+$BD$2))} -> 60000 | AX25: {=IFERROR(_xlfn.IFS(VALUE(MID(AX$5,6,1))>$D$2,0,$AP25="Annual",1,AW25=12,12,$AP25="Monthly V",AW25*(1+$BD$2),$AP25="Monthly F",12,$AP25="One-Time",0),AW25*(1+$BD$2))} -> 60000 | AY25: {=IFERROR(_xlfn.IFS(VALUE(MID(AY$5,6,1))>$D$2,0,$AP25="Annual",1,AX25=12,12,$AP25="Monthly V",AX25*(1+$D$3),$AP25="Monthly F",12,$AP25="One-Time",0),AX25*(1+$D$3))} -> 0 | AZ25: {=IFERROR(_xlfn.IFS(VALUE(MID(AZ$5,6,1))>$D$2,0,$AP25="Annual",1,AY25=12,12,$AP25="Monthly V",AY25*(1+$D$3),$AP25="Monthly F",12,$AP25="One-Time",0),AY25*(1+$D$3))} -> 0 | BA25: {=IFERROR(_xlfn.IFS(VALUE(MID(BA$5,6,2))>$D$2,0,$AP25="Annual",1,AZ25=12,12,$AP25="Monthly V",AZ25*(1+$D$3),$AP25="Monthly F",12,$AP25="One-Time",0),AZ25*(1+$D$3))} -> 0 | BB25: Synergy eSign and eSignWeb Bundle | BC25: Synergy | BD25: 0.184 | BE25: =BF25/12 -> 920 | BF25: =IFERROR(AR25*$BD25,0) -> 11040 | BG25: =IFERROR(AS25*$BD25,0) -> 11040 | BH25: =IFERROR(AT25*$BD25,0) -> 11040 | BI25: =BH25*1.03 -> 11371.2 | BJ25: =BI25*1.03 -> 11712.336 | BK25: =BJ25*1.03 -> 12063.706 | BL25: =BK25*1.03 -> 12425.617 | BM25: =IFERROR(AY25*$BD25,0) -> 0 | BN25: =IFERROR(AZ25*$BD25,0) -> 0 | BO25: =IFERROR(BA25*$BD25,0) -> 0 | BQ25: =IF(VALUE(MID(BQ$5,6,1))<=$D$2,((1+$BD$3)^1-1)*BG25,0) -> 331.2 | BR25: =IF(VALUE(MID(BR$5,6,1))<=$D$2,((1+$BD$3)^2-1)*BH25,0) -> 672.336 | BS25: =IF(VALUE(MID(BS$5,6,1))<=$D$2,((1+$BD$3)^3-1)*BI25,0) -> 1054.4173 | BT25: =IF(VALUE(MID(BT$5,6,1))<=$D$2,((1+$BD$3)^4-1)*BJ25,0) -> 1470.0014 | BU25: =IF(VALUE(MID(BU$5,6,1))<=$D$2,((1+$BD$3)^5-1)*BK25,0) -> 1921.4356 | BV25: =IF(VALUE(MID(BV$5,6,1))<=$D$2,((1+$BD$3)^6-1)*BL25,0) -> 2411.2196 | BW25: =IF(VALUE(MID(BW$5,6,1))<=$D$2,((1+$BD$3)^7-1)*BM25,0) -> 0 | BX25: =IF(VALUE(MID(BX$5,6,1))<=$D$2,((1+$BD$3)^8-1)*BN25,0) -> 0 | BY25: =IF(VALUE(MID(BY$5,6,2))<=$D$2,((1+$BD$3)^9-1)*BO25,0) -> 0 | BZ25: =SUM(BP25:BY25) -> 7860.6098 | CA25: =SUM(BZ25,BF25:BO25) -> 88553.469 | CE25: =IF($CC25="Annual",1,IF($CC25="Monthly F",12,IF($CC25="Monthly V",CD25*12,IF($CC25="One-Time",1,CD25*12)))) -> 0 | CF25: {=IFERROR(_xlfn.IFS(VALUE(MID(CF$5,6,1))>$D$2,0,$CC25="Annual",1,CE25=12,12,$CC25="Monthly V",CE25*(1+$D$3),$CC25="Monthly F",12,$CC25="One-Time",0),CE25*(1+$D$3))} -> 0 | CG25: {=IFERROR(_xlfn.IFS(VALUE(MID(CG$5,6,1))>$D$2,0,$CC25="Annual",1,CF25=12,12,$CC25="Monthly V",CF25*(1+$D$3),$CC25="Monthly F",12,$CC25="One-Time",0),CF25*(1+$D$3))} -> 0 | CH25: {=IFERROR(_xlfn.IFS(VALUE(MID(CH$5,6,1))>$D$2,0,$CC25="Annual",1,CG25=12,12,$CC25="Monthly V",CG25*(1+$D$3),$CC25="Monthly F",12,$CC25="One-Time",0),CG25*(1+$D$3))} -> 0 | CI25: {=IFERROR(_xlfn.IFS(VALUE(MID(CI$5,6,1))>$D$2,0,$CC25="Annual",1,CH25=12,12,$CC25="Monthly V",CH25*(1+$D$3),$CC25="Monthly F",12,$CC25="One-Time",0),CH25*(1+$D$3))} -> 0 | CJ25: {=IFERROR(_xlfn.IFS(VALUE(MID(CJ$5,6,1))>$D$2,0,$CC25="Annual",1,CI25=12,12,$CC25="Monthly V",CI25*(1+$D$3),$CC25="Monthly F",12,$CC25="One-Time",0),CI25*(1+$D$3))} -> 0 | CK25: {=IFERROR(_xlfn.IFS(VALUE(MID(CK$5,6,1))>$D$2,0,$CC25="Annual",1,CJ25=12,12,$CC25="Monthly V",CJ25*(1+$D$3),$CC25="Monthly F",12,$CC25="One-Time",0),CJ25*(1+$D$3))} -> 0 | CL25: {=IFERROR(_xlfn.IFS(VALUE(MID(CL$5,6,1))>$D$2,0,$CC25="Annual",1,CK25=12,12,$CC25="Monthly V",CK25*(1+$D$3),$CC25="Monthly F",12,$CC25="One-Time",0),CK25*(1+$D$3))} -> 0 | CM25: {=IFERROR(_xlfn.IFS(VALUE(MID(CM$5,6,1))>$D$2,0,$CC25="Annual",1,CL25=12,12,$CC25="Monthly V",CL25*(1+$D$3),$CC25="Monthly F",12,$CC25="One-Time",0),CL25*(1+$D$3))} -> 0 | CN25: {=IFERROR(_xlfn.IFS(VALUE(MID(CN$5,6,2))>$D$2,0,$CC25="Annual",1,CM25=12,12,$CC25="Monthly V",CM25*(1+$D$3),$CC25="Monthly F",12,$CC25="One-Time",0),CM25*(1+$D$3))} -> 0 | CQ25: =CR25/12 -> 0 | CR25: =IFERROR(CE25*$CP25,0) -> 0 | CS25: =IFERROR(CF25*$CP25,0) -> 0 | CT25: =IFERROR(CG25*$CP25,0) -> 0 | CU25: =IFERROR(CH25*$CP25,0) -> 0 | CV25: =IFERROR(CI25*$CP25,0) -> 0 | CW25: =IFERROR(CJ25*$CP25,0) -> 0 | CX25: =IFERROR(CK25*$CP25,0) -> 0 | CY25: =IFERROR(CL25*$CP25,0) -> 0 | ... DA25: =IFERROR(CN25*$CP25,0) -> 0 | DC25: =IF(VALUE(MID(DC$5,6,1))<=$D$2,((1+$CP$3)^1-1)*CS25,0) -> 0 | DD25: =IF(VALUE(MID(DD$5,6,1))<=$D$2,((1+$CP$3)^2-1)*CT25,0) -> 0 | DE25: =IF(VALUE(MID(DE$5,6,1))<=$D$2,((1+$CP$3)^3-1)*CU25,0) -> 0 | DF25: =IF(VALUE(MID(DF$5,6,1))<=$D$2,((1+$CP$3)^4-1)*CV25,0) -> 0 | DG25: =IF(VALUE(MID(DG$5,6,1))<=$D$2,((1+$CP$3)^5-1)*CW25,0) -> 0 | DH25: =IF(VALUE(MID(DH$5,6,1))<=$D$2,((1+$CP$3)^6-1)*CX25,0) -> 0 | DI25: =IF(VALUE(MID(DI$5,6,1))<=$D$2,((1+$CP$3)^7-1)*CY25,0) -> 0 | DJ25: =IF(VALUE(MID(DJ$5,6,1))<=$D$2,((1+$CP$3)^8-1)*CZ25,0) -> 0 | DK25: =IF(VALUE(MID(DK$5,6,2))<=$D$2,((1+$CP$3)^9-1)*DA25,0) -> 0 | DL25: =SUM(DB25:DK25) -> 0 | DM25: =SUM(DL25,CR25:DA25) -> 0
B26: Monthly F | C26: 1 | D26: =IFERROR(AVERAGE(C26:C26),0) -> 1 | E26: =IF($B26="Annual",1,IF($B26="Monthly F",12,IF($B26="Monthly V",D26*12,IF($B26="One-Time",1,D26*12)))) -> 12 | F26: {=IFERROR(_xlfn.IFS(VALUE(MID(F$5,6,1))>$D$2,0,$B26="Annual",1,E26=12,12,$B26="Monthly V",E26*(1+$D$3),$B26="Monthly F",12,$B26="One-Time",0),E26*(1+$D$3))} -> 12 | G26: {=IFERROR(_xlfn.IFS(VALUE(MID(G$5,6,1))>$D$2,0,$B26="Annual",1,F26=12,12,$B26="Monthly V",F26*(1+$D$3),$B26="Monthly F",12,$B26="One-Time",0),F26*(1+$D$3))} -> 12 | H26: {=IFERROR(_xlfn.IFS(VALUE(MID(H$5,6,1))>$D$2,0,$B26="Annual",1,G26=12,12,$B26="Monthly V",G26*(1+$D$3),$B26="Monthly F",12,$B26="One-Time",0),G26*(1+$D$3))} -> 12 | I26: {=IFERROR(_xlfn.IFS(VALUE(MID(I$5,6,1))>$D$2,0,$B26="Annual",1,H26=12,12,$B26="Monthly V",H26*(1+$D$3),$B26="Monthly F",12,$B26="One-Time",0),H26*(1+$D$3))} -> 12 | J26: {=IFERROR(_xlfn.IFS(VALUE(MID(J$5,6,1))>$D$2,0,$B26="Annual",1,I26=12,12,$B26="Monthly V",I26*(1+$D$3),$B26="Monthly F",12,$B26="One-Time",0),I26*(1+$D$3))} -> 12 | K26: {=IFERROR(_xlfn.IFS(VALUE(MID(K$5,6,1))>$D$2,0,$B26="Annual",1,J26=12,12,$B26="Monthly V",J26*(1+$D$3),$B26="Monthly F",12,$B26="One-Time",0),J26*(1+$D$3))} -> 12 | L26: {=IFERROR(_xlfn.IFS(VALUE(MID(L$5,6,1))>$D$2,0,$B26="Annual",1,K26=12,12,$B26="Monthly V",K26*(1+$D$3),$B26="Monthly F",12,$B26="One-Time",0),K26*(1+$D$3))} -> 0 | M26: {=IFERROR(_xlfn.IFS(VALUE(MID(M$5,6,1))>$D$2,0,$B26="Annual",1,L26=12,12,$B26="Monthly V",L26*(1+$D$3),$B26="Monthly F",12,$B26="One-Time",0),L26*(1+$D$3))} -> 0 | N26: {=IFERROR(_xlfn.IFS(VALUE(MID(N$5,6,2))>$D$2,0,$B26="Annual",1,M26=12,12,$B26="Monthly V",M26*(1+$D$3),$B26="Monthly F",12,$B26="One-Time",0),M26*(1+$D$3))} -> 0 | O26: Card Pro Connect | P26: CardProd | Q26: 500 | R26: =S26/12 -> 500 | S26: =IFERROR($Q26*E26,0) -> 6000 | T26: =IFERROR($Q26*F26,0) -> 6000 | U26: =IFERROR($Q26*G26,0) -> 6000 | V26: =IFERROR($Q26*H26,0) -> 6000 | W26: =IFERROR($Q26*I26,0) -> 6000 | X26: =IFERROR($Q26*J26,0) -> 6000 | Y26: =IFERROR($Q26*K26,0) -> 6000 | Z26: =IFERROR($Q26*L26,0) -> 0 | ... AB26: =IFERROR($Q26*N26,0) -> 0 | AD26: =IF(VALUE(MID(AD$5,6,1))<=$D$2,((1+$Q$3)^1-1)*T26,0) -> 180 | AE26: =IF(VALUE(MID(AE$5,6,1))<=$D$2,((1+$Q$3)^2-1)*U26,0) -> 365.4 | AF26: =IF(VALUE(MID(AF$5,6,1))<=$D$2,((1+$Q$3)^3-1)*V26,0) -> 556.362 | AG26: =IF(VALUE(MID(AG$5,6,1))<=$D$2,((1+$Q$3)^4-1)*W26,0) -> 753.05286 | AH26: =IF(VALUE(MID(AH$5,6,1))<=$D$2,((1+$Q$3)^5-1)*X26,0) -> 955.64445 | AI26: =IF(VALUE(MID(AI$5,6,1))<=$D$2,((1+$Q$3)^6-1)*Y26,0) -> 1164.3138 | AJ26: =IF(VALUE(MID(AJ$5,6,1))<=$D$2,((1+$Q$3)^7-1)*Z26,0) -> 0 | AK26: =IF(VALUE(MID(AK$5,6,1))<=$D$2,((1+$Q$3)^8-1)*AA26,0) -> 0 | AL26: =IF(VALUE(MID(AL$5,6,2))<=$D$2,((1+$Q$3)^9-1)*AB26,0) -> 0 | AM26: =SUM(AC26:AL26) -> 3974.7731 | AN26: =SUM(AM26,S26:AB26) -> 45974.773 | AP26: Monthly F | AQ26: 1 | AR26: =IF($AP26="Annual",1,IF($AP26="Monthly F",12,IF($AP26="Monthly V",AQ26*12,IF($AP26="One-Time",1,AQ26*12)))) -> 12 | AS26: {=IFERROR(_xlfn.IFS(VALUE(MID(AS$5,6,1))>$D$2,0,$AP26="Annual",1,AR26=12,12,$AP26="Monthly V",AR26*(1+$BD$2),$AP26="Monthly F",12,$AP26="One-Time",0),AR26*(1+$BD$2))} -> 12 | AT26: {=IFERROR(_xlfn.IFS(VALUE(MID(AT$5,6,1))>$D$2,0,$AP26="Annual",1,AS26=12,12,$AP26="Monthly V",AS26*(1+$BD$2),$AP26="Monthly F",12,$AP26="One-Time",0),AS26*(1+$BD$2))} -> 12 | AU26: {=IFERROR(_xlfn.IFS(VALUE(MID(AU$5,6,1))>$D$2,0,$AP26="Annual",1,AT26=12,12,$AP26="Monthly V",AT26*(1+$BD$2),$AP26="Monthly F",12,$AP26="One-Time",0),AT26*(1+$BD$2))} -> 12 | AV26: {=IFERROR(_xlfn.IFS(VALUE(MID(AV$5,6,1))>$D$2,0,$AP26="Annual",1,AU26=12,12,$AP26="Monthly V",AU26*(1+$BD$2),$AP26="Monthly F",12,$AP26="One-Time",0),AU26*(1+$BD$2))} -> 12 | AW26: {=IFERROR(_xlfn.IFS(VALUE(MID(AW$5,6,1))>$D$2,0,$AP26="Annual",1,AV26=12,12,$AP26="Monthly V",AV26*(1+$BD$2),$AP26="Monthly F",12,$AP26="One-Time",0),AV26*(1+$BD$2))} -> 12 | AX26: {=IFERROR(_xlfn.IFS(VALUE(MID(AX$5,6,1))>$D$2,0,$AP26="Annual",1,AW26=12,12,$AP26="Monthly V",AW26*(1+$BD$2),$AP26="Monthly F",12,$AP26="One-Time",0),AW26*(1+$BD$2))} -> 12 | AY26: {=IFERROR(_xlfn.IFS(VALUE(MID(AY$5,6,1))>$D$2,0,$AP26="Annual",1,AX26=12,12,$AP26="Monthly V",AX26*(1+$D$3),$AP26="Monthly F",12,$AP26="One-Time",0),AX26*(1+$D$3))} -> 0 | AZ26: {=IFERROR(_xlfn.IFS(VALUE(MID(AZ$5,6,1))>$D$2,0,$AP26="Annual",1,AY26=12,12,$AP26="Monthly V",AY26*(1+$D$3),$AP26="Monthly F",12,$AP26="One-Time",0),AY26*(1+$D$3))} -> 0 | BA26: {=IFERROR(_xlfn.IFS(VALUE(MID(BA$5,6,2))>$D$2,0,$AP26="Annual",1,AZ26=12,12,$AP26="Monthly V",AZ26*(1+$D$3),$AP26="Monthly F",12,$AP26="One-Time",0),AZ26*(1+$D$3))} -> 0 | BB26: iPay Business BillPay Banno | BC26: iPay | BD26: 400 | BE26: =BF26/12 -> 400 | BF26: =IFERROR(AR26*$BD26,0) -> 4800 | BG26: =IFERROR(AS26*$BD26,0) -> 4800 | BH26: =IFERROR(AT26*$BD26,0) -> 4800 | BI26: =BH26*1.03 -> 4944 | BJ26: =BI26*1.03 -> 5092.32 | BK26: =BJ26*1.03 -> 5245.0896 | BL26: =BK26*1.03 -> 5402.4423 | BM26: =IFERROR(AY26*$BD26,0) -> 0 | BN26: =IFERROR(AZ26*$BD26,0) -> 0 | BO26: =IFERROR(BA26*$BD26,0) -> 0 | BQ26: =IF(VALUE(MID(BQ$5,6,1))<=$D$2,((1+$BD$3)^1-1)*BG26,0) -> 144 | BR26: =IF(VALUE(MID(BR$5,6,1))<=$D$2,((1+$BD$3)^2-1)*BH26,0) -> 292.32 | BS26: =IF(VALUE(MID(BS$5,6,1))<=$D$2,((1+$BD$3)^3-1)*BI26,0) -> 458.44229 | BT26: =IF(VALUE(MID(BT$5,6,1))<=$D$2,((1+$BD$3)^4-1)*BJ26,0) -> 639.13102 | BU26: =IF(VALUE(MID(BU$5,6,1))<=$D$2,((1+$BD$3)^5-1)*BK26,0) -> 835.40679 | BV26: =IF(VALUE(MID(BV$5,6,1))<=$D$2,((1+$BD$3)^6-1)*BL26,0) -> 1048.3563 | BW26: =IF(VALUE(MID(BW$5,6,1))<=$D$2,((1+$BD$3)^7-1)*BM26,0) -> 0 | BX26: =IF(VALUE(MID(BX$5,6,1))<=$D$2,((1+$BD$3)^8-1)*BN26,0) -> 0 | BY26: =IF(VALUE(MID(BY$5,6,2))<=$D$2,((1+$BD$3)^9-1)*BO26,0) -> 0 | BZ26: =SUM(BP26:BY26) -> 3417.6564 | CA26: =SUM(BZ26,BF26:BO26) -> 38501.508 | CE26: =IF($CC26="Annual",1,IF($CC26="Monthly F",12,IF($CC26="Monthly V",CD26*12,IF($CC26="One-Time",1,CD26*12)))) -> 0 | CF26: {=IFERROR(_xlfn.IFS(VALUE(MID(CF$5,6,1))>$D$2,0,$CC26="Annual",1,CE26=12,12,$CC26="Monthly V",CE26*(1+$D$3),$CC26="Monthly F",12,$CC26="One-Time",0),CE26*(1+$D$3))} -> 0 | CG26: {=IFERROR(_xlfn.IFS(VALUE(MID(CG$5,6,1))>$D$2,0,$CC26="Annual",1,CF26=12,12,$CC26="Monthly V",CF26*(1+$D$3),$CC26="Monthly F",12,$CC26="One-Time",0),CF26*(1+$D$3))} -> 0 | CH26: {=IFERROR(_xlfn.IFS(VALUE(MID(CH$5,6,1))>$D$2,0,$CC26="Annual",1,CG26=12,12,$CC26="Monthly V",CG26*(1+$D$3),$CC26="Monthly F",12,$CC26="One-Time",0),CG26*(1+$D$3))} -> 0 | CI26: {=IFERROR(_xlfn.IFS(VALUE(MID(CI$5,6,1))>$D$2,0,$CC26="Annual",1,CH26=12,12,$CC26="Monthly V",CH26*(1+$D$3),$CC26="Monthly F",12,$CC26="One-Time",0),CH26*(1+$D$3))} -> 0 | CJ26: {=IFERROR(_xlfn.IFS(VALUE(MID(CJ$5,6,1))>$D$2,0,$CC26="Annual",1,CI26=12,12,$CC26="Monthly V",CI26*(1+$D$3),$CC26="Monthly F",12,$CC26="One-Time",0),CI26*(1+$D$3))} -> 0 | CK26: {=IFERROR(_xlfn.IFS(VALUE(MID(CK$5,6,1))>$D$2,0,$CC26="Annual",1,CJ26=12,12,$CC26="Monthly V",CJ26*(1+$D$3),$CC26="Monthly F",12,$CC26="One-Time",0),CJ26*(1+$D$3))} -> 0 | CL26: {=IFERROR(_xlfn.IFS(VALUE(MID(CL$5,6,1))>$D$2,0,$CC26="Annual",1,CK26=12,12,$CC26="Monthly V",CK26*(1+$D$3),$CC26="Monthly F",12,$CC26="One-Time",0),CK26*(1+$D$3))} -> 0 | CM26: {=IFERROR(_xlfn.IFS(VALUE(MID(CM$5,6,1))>$D$2,0,$CC26="Annual",1,CL26=12,12,$CC26="Monthly V",CL26*(1+$D$3),$CC26="Monthly F",12,$CC26="One-Time",0),CL26*(1+$D$3))} -> 0 | CN26: {=IFERROR(_xlfn.IFS(VALUE(MID(CN$5,6,2))>$D$2,0,$CC26="Annual",1,CM26=12,12,$CC26="Monthly V",CM26*(1+$D$3),$CC26="Monthly F",12,$CC26="One-Time",0),CM26*(1+$D$3))} -> 0 | CQ26: =CR26/12 -> 0 | CR26: =IFERROR(CE26*$CP26,0) -> 0 | CS26: =IFERROR(CF26*$CP26,0) -> 0 | CT26: =IFERROR(CG26*$CP26,0) -> 0 | CU26: =IFERROR(CH26*$CP26,0) -> 0 | CV26: =IFERROR(CI26*$CP26,0) -> 0 | CW26: =IFERROR(CJ26*$CP26,0) -> 0 | CX26: =IFERROR(CK26*$CP26,0) -> 0 | CY26: =IFERROR(CL26*$CP26,0) -> 0 | ... DA26: =IFERROR(CN26*$CP26,0) -> 0 | DC26: =IF(VALUE(MID(DC$5,6,1))<=$D$2,((1+$CP$3)^1-1)*CS26,0) -> 0 | DD26: =IF(VALUE(MID(DD$5,6,1))<=$D$2,((1+$CP$3)^2-1)*CT26,0) -> 0 | DE26: =IF(VALUE(MID(DE$5,6,1))<=$D$2,((1+$CP$3)^3-1)*CU26,0) -> 0 | DF26: =IF(VALUE(MID(DF$5,6,1))<=$D$2,((1+$CP$3)^4-1)*CV26,0) -> 0 | DG26: =IF(VALUE(MID(DG$5,6,1))<=$D$2,((1+$CP$3)^5-1)*CW26,0) -> 0 | DH26: =IF(VALUE(MID(DH$5,6,1))<=$D$2,((1+$CP$3)^6-1)*CX26,0) -> 0 | DI26: =IF(VALUE(MID(DI$5,6,1))<=$D$2,((1+$CP$3)^7-1)*CY26,0) -> 0 | DJ26: =IF(VALUE(MID(DJ$5,6,1))<=$D$2,((1+$CP$3)^8-1)*CZ26,0) -> 0 | DK26: =IF(VALUE(MID(DK$5,6,2))<=$D$2,((1+$CP$3)^9-1)*DA26,0) -> 0 | DL26: =SUM(DB26:DK26) -> 0 | DM26: =SUM(DL26,CR26:DA26) -> 0
B27: Monthly V | C27: 29 | D27: =IFERROR(AVERAGE(C27:C27),0) -> 29 | E27: =IF($B27="Annual",1,IF($B27="Monthly F",12,IF($B27="Monthly V",D27*12,IF($B27="One-Time",1,D27*12)))) -> 348 | F27: {=IFERROR(_xlfn.IFS(VALUE(MID(F$5,6,1))>$D$2,0,$B27="Annual",1,E27=12,12,$B27="Monthly V",E27*(1+$D$3),$B27="Monthly F",12,$B27="One-Time",0),E27*(1+$D$3))} -> 417.6 | G27: {=IFERROR(_xlfn.IFS(VALUE(MID(G$5,6,1))>$D$2,0,$B27="Annual",1,F27=12,12,$B27="Monthly V",F27*(1+$D$3),$B27="Monthly F",12,$B27="One-Time",0),F27*(1+$D$3))} -> 501.12 | H27: {=IFERROR(_xlfn.IFS(VALUE(MID(H$5,6,1))>$D$2,0,$B27="Annual",1,G27=12,12,$B27="Monthly V",G27*(1+$D$3),$B27="Monthly F",12,$B27="One-Time",0),G27*(1+$D$3))} -> 601.344 | I27: {=IFERROR(_xlfn.IFS(VALUE(MID(I$5,6,1))>$D$2,0,$B27="Annual",1,H27=12,12,$B27="Monthly V",H27*(1+$D$3),$B27="Monthly F",12,$B27="One-Time",0),H27*(1+$D$3))} -> 721.6128 | J27: {=IFERROR(_xlfn.IFS(VALUE(MID(J$5,6,1))>$D$2,0,$B27="Annual",1,I27=12,12,$B27="Monthly V",I27*(1+$D$3),$B27="Monthly F",12,$B27="One-Time",0),I27*(1+$D$3))} -> 865.93536 | K27: {=IFERROR(_xlfn.IFS(VALUE(MID(K$5,6,1))>$D$2,0,$B27="Annual",1,J27=12,12,$B27="Monthly V",J27*(1+$D$3),$B27="Monthly F",12,$B27="One-Time",0),J27*(1+$D$3))} -> 1039.1224 | L27: {=IFERROR(_xlfn.IFS(VALUE(MID(L$5,6,1))>$D$2,0,$B27="Annual",1,K27=12,12,$B27="Monthly V",K27*(1+$D$3),$B27="Monthly F",12,$B27="One-Time",0),K27*(1+$D$3))} -> 0 | M27: {=IFERROR(_xlfn.IFS(VALUE(MID(M$5,6,1))>$D$2,0,$B27="Annual",1,L27=12,12,$B27="Monthly V",L27*(1+$D$3),$B27="Monthly F",12,$B27="One-Time",0),L27*(1+$D$3))} -> 0 | N27: {=IFERROR(_xlfn.IFS(VALUE(MID(N$5,6,2))>$D$2,0,$B27="Annual",1,M27=12,12,$B27="Monthly V",M27*(1+$D$3),$B27="Monthly F",12,$B27="One-Time",0),M27*(1+$D$3))} -> 0 | O27: Debit Card Production Files/Jobs per month | P27: CardProd | Q27: 12 | R27: =S27/12 -> 348 | S27: =IFERROR($Q27*E27,0) -> 4176 | T27: =IFERROR($Q27*F27,0) -> 5011.2 | U27: =IFERROR($Q27*G27,0) -> 6013.44 | V27: =IFERROR($Q27*H27,0) -> 7216.128 | W27: =IFERROR($Q27*I27,0) -> 8659.3536 | X27: =IFERROR($Q27*J27,0) -> 10391.224 | Y27: =IFERROR($Q27*K27,0) -> 12469.469 | Z27: =IFERROR($Q27*L27,0) -> 0 | ... AB27: =IFERROR($Q27*N27,0) -> 0 | AD27: =IF(VALUE(MID(AD$5,6,1))<=$D$2,((1+$Q$3)^1-1)*T27,0) -> 150.336 | AE27: =IF(VALUE(MID(AE$5,6,1))<=$D$2,((1+$Q$3)^2-1)*U27,0) -> 366.2185 | AF27: =IF(VALUE(MID(AF$5,6,1))<=$D$2,((1+$Q$3)^3-1)*V27,0) -> 669.1299 | AG27: =IF(VALUE(MID(AG$5,6,1))<=$D$2,((1+$Q$3)^4-1)*W27,0) -> 1086.8252 | AH27: =IF(VALUE(MID(AH$5,6,1))<=$D$2,((1+$Q$3)^5-1)*X27,0) -> 1655.0526 | AI27: =IF(VALUE(MID(AI$5,6,1))<=$D$2,((1+$Q$3)^6-1)*Y27,0) -> 2419.7291 | AJ27: =IF(VALUE(MID(AJ$5,6,1))<=$D$2,((1+$Q$3)^7-1)*Z27,0) -> 0 | AK27: =IF(VALUE(MID(AK$5,6,1))<=$D$2,((1+$Q$3)^8-1)*AA27,0) -> 0 | AL27: =IF(VALUE(MID(AL$5,6,2))<=$D$2,((1+$Q$3)^9-1)*AB27,0) -> 0 | AM27: =SUM(AC27:AL27) -> 6347.2913 | AN27: =SUM(AM27,S27:AB27) -> 60284.106 | AP27: Monthly F | AQ27: 1 | AR27: =IF($AP27="Annual",1,IF($AP27="Monthly F",12,IF($AP27="Monthly V",AQ27*12,IF($AP27="One-Time",1,AQ27*12)))) -> 12 | AS27: {=IFERROR(_xlfn.IFS(VALUE(MID(AS$5,6,1))>$D$2,0,$AP27="Annual",1,AR27=12,12,$AP27="Monthly V",AR27*(1+$BD$2),$AP27="Monthly F",12,$AP27="One-Time",0),AR27*(1+$BD$2))} -> 12 | AT27: {=IFERROR(_xlfn.IFS(VALUE(MID(AT$5,6,1))>$D$2,0,$AP27="Annual",1,AS27=12,12,$AP27="Monthly V",AS27*(1+$BD$2),$AP27="Monthly F",12,$AP27="One-Time",0),AS27*(1+$BD$2))} -> 12 | AU27: {=IFERROR(_xlfn.IFS(VALUE(MID(AU$5,6,1))>$D$2,0,$AP27="Annual",1,AT27=12,12,$AP27="Monthly V",AT27*(1+$BD$2),$AP27="Monthly F",12,$AP27="One-Time",0),AT27*(1+$BD$2))} -> 12 | AV27: {=IFERROR(_xlfn.IFS(VALUE(MID(AV$5,6,1))>$D$2,0,$AP27="Annual",1,AU27=12,12,$AP27="Monthly V",AU27*(1+$BD$2),$AP27="Monthly F",12,$AP27="One-Time",0),AU27*(1+$BD$2))} -> 12 | AW27: {=IFERROR(_xlfn.IFS(VALUE(MID(AW$5,6,1))>$D$2,0,$AP27="Annual",1,AV27=12,12,$AP27="Monthly V",AV27*(1+$BD$2),$AP27="Monthly F",12,$AP27="One-Time",0),AV27*(1+$BD$2))} -> 12 | AX27: {=IFERROR(_xlfn.IFS(VALUE(MID(AX$5,6,1))>$D$2,0,$AP27="Annual",1,AW27=12,12,$AP27="Monthly V",AW27*(1+$BD$2),$AP27="Monthly F",12,$AP27="One-Time",0),AW27*(1+$BD$2))} -> 12 | AY27: {=IFERROR(_xlfn.IFS(VALUE(MID(AY$5,6,1))>$D$2,0,$AP27="Annual",1,AX27=12,12,$AP27="Monthly V",AX27*(1+$D$3),$AP27="Monthly F",12,$AP27="One-Time",0),AX27*(1+$D$3))} -> 0 | AZ27: {=IFERROR(_xlfn.IFS(VALUE(MID(AZ$5,6,1))>$D$2,0,$AP27="Annual",1,AY27=12,12,$AP27="Monthly V",AY27*(1+$D$3),$AP27="Monthly F",12,$AP27="One-Time",0),AY27*(1+$D$3))} -> 0 | BA27: {=IFERROR(_xlfn.IFS(VALUE(MID(BA$5,6,2))>$D$2,0,$AP27="Annual",1,AZ27=12,12,$AP27="Monthly V",AZ27*(1+$D$3),$AP27="Monthly F",12,$AP27="One-Time",0),AZ27*(1+$D$3))} -> 0 | BB27: DirectLine Wires | BC27: DirectLine | BD27: 450 | BE27: =BF27/12 -> 450 | BF27: =IFERROR(AR27*$BD27,0) -> 5400 | BG27: =IFERROR(AS27*$BD27,0) -> 5400 | BH27: =IFERROR(AT27*$BD27,0) -> 5400 | BI27: =BH27*1.03 -> 5562 | BJ27: =BI27*1.03 -> 5728.86 | BK27: =BJ27*1.03 -> 5900.7258 | BL27: =BK27*1.03 -> 6077.7476 | BM27: =IFERROR(AY27*$BD27,0) -> 0 | BN27: =IFERROR(AZ27*$BD27,0) -> 0 | BO27: =IFERROR(BA27*$BD27,0) -> 0 | BQ27: =IF(VALUE(MID(BQ$5,6,1))<=$D$2,((1+$BD$3)^1-1)*BG27,0) -> 162 | BR27: =IF(VALUE(MID(BR$5,6,1))<=$D$2,((1+$BD$3)^2-1)*BH27,0) -> 328.86 | BS27: =IF(VALUE(MID(BS$5,6,1))<=$D$2,((1+$BD$3)^3-1)*BI27,0) -> 515.74757 | BT27: =IF(VALUE(MID(BT$5,6,1))<=$D$2,((1+$BD$3)^4-1)*BJ27,0) -> 719.0224 | BU27: =IF(VALUE(MID(BU$5,6,1))<=$D$2,((1+$BD$3)^5-1)*BK27,0) -> 939.83264 | BV27: =IF(VALUE(MID(BV$5,6,1))<=$D$2,((1+$BD$3)^6-1)*BL27,0) -> 1179.4009 | BW27: =IF(VALUE(MID(BW$5,6,1))<=$D$2,((1+$BD$3)^7-1)*BM27,0) -> 0 | BX27: =IF(VALUE(MID(BX$5,6,1))<=$D$2,((1+$BD$3)^8-1)*BN27,0) -> 0 | BY27: =IF(VALUE(MID(BY$5,6,2))<=$D$2,((1+$BD$3)^9-1)*BO27,0) -> 0 | BZ27: =SUM(BP27:BY27) -> 3844.8635 | CA27: =SUM(BZ27,BF27:BO27) -> 43314.197 | CE27: =IF($CC27="Annual",1,IF($CC27="Monthly F",12,IF($CC27="Monthly V",CD27*12,IF($CC27="One-Time",1,CD27*12)))) -> 0 | CF27: {=IFERROR(_xlfn.IFS(VALUE(MID(CF$5,6,1))>$D$2,0,$CC27="Annual",1,CE27=12,12,$CC27="Monthly V",CE27*(1+$D$3),$CC27="Monthly F",12,$CC27="One-Time",0),CE27*(1+$D$3))} -> 0 | CG27: {=IFERROR(_xlfn.IFS(VALUE(MID(CG$5,6,1))>$D$2,0,$CC27="Annual",1,CF27=12,12,$CC27="Monthly V",CF27*(1+$D$3),$CC27="Monthly F",12,$CC27="One-Time",0),CF27*(1+$D$3))} -> 0 | CH27: {=IFERROR(_xlfn.IFS(VALUE(MID(CH$5,6,1))>$D$2,0,$CC27="Annual",1,CG27=12,12,$CC27="Monthly V",CG27*(1+$D$3),$CC27="Monthly F",12,$CC27="One-Time",0),CG27*(1+$D$3))} -> 0 | CI27: {=IFERROR(_xlfn.IFS(VALUE(MID(CI$5,6,1))>$D$2,0,$CC27="Annual",1,CH27=12,12,$CC27="Monthly V",CH27*(1+$D$3),$CC27="Monthly F",12,$CC27="One-Time",0),CH27*(1+$D$3))} -> 0 | CJ27: {=IFERROR(_xlfn.IFS(VALUE(MID(CJ$5,6,1))>$D$2,0,$CC27="Annual",1,CI27=12,12,$CC27="Monthly V",CI27*(1+$D$3),$CC27="Monthly F",12,$CC27="One-Time",0),CI27*(1+$D$3))} -> 0 | CK27: {=IFERROR(_xlfn.IFS(VALUE(MID(CK$5,6,1))>$D$2,0,$CC27="Annual",1,CJ27=12,12,$CC27="Monthly V",CJ27*(1+$D$3),$CC27="Monthly F",12,$CC27="One-Time",0),CJ27*(1+$D$3))} -> 0 | CL27: {=IFERROR(_xlfn.IFS(VALUE(MID(CL$5,6,1))>$D$2,0,$CC27="Annual",1,CK27=12,12,$CC27="Monthly V",CK27*(1+$D$3),$CC27="Monthly F",12,$CC27="One-Time",0),CK27*(1+$D$3))} -> 0 | CM27: {=IFERROR(_xlfn.IFS(VALUE(MID(CM$5,6,1))>$D$2,0,$CC27="Annual",1,CL27=12,12,$CC27="Monthly V",CL27*(1+$D$3),$CC27="Monthly F",12,$CC27="One-Time",0),CL27*(1+$D$3))} -> 0 | CN27: {=IFERROR(_xlfn.IFS(VALUE(MID(CN$5,6,2))>$D$2,0,$CC27="Annual",1,CM27=12,12,$CC27="Monthly V",CM27*(1+$D$3),$CC27="Monthly F",12,$CC27="One-Time",0),CM27*(1+$D$3))} -> 0 | CQ27: =CR27/12 -> 0 | CR27: =IFERROR(CE27*$CP27,0) -> 0 | CS27: =IFERROR(CF27*$CP27,0) -> 0 | CT27: =IFERROR(CG27*$CP27,0) -> 0 | CU27: =IFERROR(CH27*$CP27,0) -> 0 | CV27: =IFERROR(CI27*$CP27,0) -> 0 | CW27: =IFERROR(CJ27*$CP27,0) -> 0 | CX27: =IFERROR(CK27*$CP27,0) -> 0 | CY27: =IFERROR(CL27*$CP27,0) -> 0 | ... DA27: =IFERROR(CN27*$CP27,0) -> 0 | DC27: =IF(VALUE(MID(DC$5,6,1))<=$D$2,((1+$CP$3)^1-1)*CS27,0) -> 0 | DD27: =IF(VALUE(MID(DD$5,6,1))<=$D$2,((1+$CP$3)^2-1)*CT27,0) -> 0 | DE27: =IF(VALUE(MID(DE$5,6,1))<=$D$2,((1+$CP$3)^3-1)*CU27,0) -> 0 | DF27: =IF(VALUE(MID(DF$5,6,1))<=$D$2,((1+$CP$3)^4-1)*CV27,0) -> 0 | DG27: =IF(VALUE(MID(DG$5,6,1))<=$D$2,((1+$CP$3)^5-1)*CW27,0) -> 0 | DH27: =IF(VALUE(MID(DH$5,6,1))<=$D$2,((1+$CP$3)^6-1)*CX27,0) -> 0 | DI27: =IF(VALUE(MID(DI$5,6,1))<=$D$2,((1+$CP$3)^7-1)*CY27,0) -> 0 | DJ27: =IF(VALUE(MID(DJ$5,6,1))<=$D$2,((1+$CP$3)^8-1)*CZ27,0) -> 0 | DK27: =IF(VALUE(MID(DK$5,6,2))<=$D$2,((1+$CP$3)^9-1)*DA27,0) -> 0 | DL27: =SUM(DB27:DK27) -> 0 | DM27: =SUM(DL27,CR27:DA27) -> 0
B28: Monthly V | C28: 25 | D28: =IFERROR(AVERAGE(C28:C28),0) -> 25 | E28: =IF($B28="Annual",1,IF($B28="Monthly F",12,IF($B28="Monthly V",D28*12,IF($B28="One-Time",1,D28*12)))) -> 300 | F28: {=IFERROR(_xlfn.IFS(VALUE(MID(F$5,6,1))>$D$2,0,$B28="Annual",1,E28=12,12,$B28="Monthly V",E28*(1+$D$3),$B28="Monthly F",12,$B28="One-Time",0),E28*(1+$D$3))} -> 360 | G28: {=IFERROR(_xlfn.IFS(VALUE(MID(G$5,6,1))>$D$2,0,$B28="Annual",1,F28=12,12,$B28="Monthly V",F28*(1+$D$3),$B28="Monthly F",12,$B28="One-Time",0),F28*(1+$D$3))} -> 432 | H28: {=IFERROR(_xlfn.IFS(VALUE(MID(H$5,6,1))>$D$2,0,$B28="Annual",1,G28=12,12,$B28="Monthly V",G28*(1+$D$3),$B28="Monthly F",12,$B28="One-Time",0),G28*(1+$D$3))} -> 518.4 | I28: {=IFERROR(_xlfn.IFS(VALUE(MID(I$5,6,1))>$D$2,0,$B28="Annual",1,H28=12,12,$B28="Monthly V",H28*(1+$D$3),$B28="Monthly F",12,$B28="One-Time",0),H28*(1+$D$3))} -> 622.08 | J28: {=IFERROR(_xlfn.IFS(VALUE(MID(J$5,6,1))>$D$2,0,$B28="Annual",1,I28=12,12,$B28="Monthly V",I28*(1+$D$3),$B28="Monthly F",12,$B28="One-Time",0),I28*(1+$D$3))} -> 746.496 | K28: {=IFERROR(_xlfn.IFS(VALUE(MID(K$5,6,1))>$D$2,0,$B28="Annual",1,J28=12,12,$B28="Monthly V",J28*(1+$D$3),$B28="Monthly F",12,$B28="One-Time",0),J28*(1+$D$3))} -> 895.7952 | L28: {=IFERROR(_xlfn.IFS(VALUE(MID(L$5,6,1))>$D$2,0,$B28="Annual",1,K28=12,12,$B28="Monthly V",K28*(1+$D$3),$B28="Monthly F",12,$B28="One-Time",0),K28*(1+$D$3))} -> 0 | M28: {=IFERROR(_xlfn.IFS(VALUE(MID(M$5,6,1))>$D$2,0,$B28="Annual",1,L28=12,12,$B28="Monthly V",L28*(1+$D$3),$B28="Monthly F",12,$B28="One-Time",0),L28*(1+$D$3))} -> 0 | N28: {=IFERROR(_xlfn.IFS(VALUE(MID(N$5,6,2))>$D$2,0,$B28="Annual",1,M28=12,12,$B28="Monthly V",M28*(1+$D$3),$B28="Monthly F",12,$B28="One-Time",0),M28*(1+$D$3))} -> 0 | O28: Debit Cards Produced per month | P28: CardProd | Q28: 6.82 | R28: =S28/12 -> 170.5 | S28: =IFERROR($Q28*E28,0) -> 2046 | T28: =IFERROR($Q28*F28,0) -> 2455.2 | U28: =IFERROR($Q28*G28,0) -> 2946.24 | V28: =IFERROR($Q28*H28,0) -> 3535.488 | W28: =IFERROR($Q28*I28,0) -> 4242.5856 | X28: =IFERROR($Q28*J28,0) -> 5091.1027 | Y28: =IFERROR($Q28*K28,0) -> 6109.3233 | Z28: =IFERROR($Q28*L28,0) -> 0 | ... AB28: =IFERROR($Q28*N28,0) -> 0 | AD28: =IF(VALUE(MID(AD$5,6,1))<=$D$2,((1+$Q$3)^1-1)*T28,0) -> 73.656 | AE28: =IF(VALUE(MID(AE$5,6,1))<=$D$2,((1+$Q$3)^2-1)*U28,0) -> 179.42602 | AF28: =IF(VALUE(MID(AF$5,6,1))<=$D$2,((1+$Q$3)^3-1)*V28,0) -> 327.8352 | AG28: =IF(VALUE(MID(AG$5,6,1))<=$D$2,((1+$Q$3)^4-1)*W28,0) -> 532.48187 | AH28: =IF(VALUE(MID(AH$5,6,1))<=$D$2,((1+$Q$3)^5-1)*X28,0) -> 810.88067 | AI28: =IF(VALUE(MID(AI$5,6,1))<=$D$2,((1+$Q$3)^6-1)*Y28,0) -> 1185.5282 | AJ28: =IF(VALUE(MID(AJ$5,6,1))<=$D$2,((1+$Q$3)^7-1)*Z28,0) -> 0 | AK28: =IF(VALUE(MID(AK$5,6,1))<=$D$2,((1+$Q$3)^8-1)*AA28,0) -> 0 | AL28: =IF(VALUE(MID(AL$5,6,2))<=$D$2,((1+$Q$3)^9-1)*AB28,0) -> 0 | AM28: =SUM(AC28:AL28) -> 3109.808 | AN28: =SUM(AM28,S28:AB28) -> 29535.748 | AP28: Monthly F | AQ28: 1 | AR28: =IF($AP28="Annual",1,IF($AP28="Monthly F",12,IF($AP28="Monthly V",AQ28*12,IF($AP28="One-Time",1,AQ28*12)))) -> 12 | AS28: {=IFERROR(_xlfn.IFS(VALUE(MID(AS$5,6,1))>$D$2,0,$AP28="Annual",1,AR28=12,12,$AP28="Monthly V",AR28*(1+$BD$2),$AP28="Monthly F",12,$AP28="One-Time",0),AR28*(1+$BD$2))} -> 12 | AT28: {=IFERROR(_xlfn.IFS(VALUE(MID(AT$5,6,1))>$D$2,0,$AP28="Annual",1,AS28=12,12,$AP28="Monthly V",AS28*(1+$BD$2),$AP28="Monthly F",12,$AP28="One-Time",0),AS28*(1+$BD$2))} -> 12 | AU28: {=IFERROR(_xlfn.IFS(VALUE(MID(AU$5,6,1))>$D$2,0,$AP28="Annual",1,AT28=12,12,$AP28="Monthly V",AT28*(1+$BD$2),$AP28="Monthly F",12,$AP28="One-Time",0),AT28*(1+$BD$2))} -> 12 | AV28: {=IFERROR(_xlfn.IFS(VALUE(MID(AV$5,6,1))>$D$2,0,$AP28="Annual",1,AU28=12,12,$AP28="Monthly V",AU28*(1+$BD$2),$AP28="Monthly F",12,$AP28="One-Time",0),AU28*(1+$BD$2))} -> 12 | AW28: {=IFERROR(_xlfn.IFS(VALUE(MID(AW$5,6,1))>$D$2,0,$AP28="Annual",1,AV28=12,12,$AP28="Monthly V",AV28*(1+$BD$2),$AP28="Monthly F",12,$AP28="One-Time",0),AV28*(1+$BD$2))} -> 12 | AX28: {=IFERROR(_xlfn.IFS(VALUE(MID(AX$5,6,1))>$D$2,0,$AP28="Annual",1,AW28=12,12,$AP28="Monthly V",AW28*(1+$BD$2),$AP28="Monthly F",12,$AP28="One-Time",0),AW28*(1+$BD$2))} -> 12 | AY28: {=IFERROR(_xlfn.IFS(VALUE(MID(AY$5,6,1))>$D$2,0,$AP28="Annual",1,AX28=12,12,$AP28="Monthly V",AX28*(1+$D$3),$AP28="Monthly F",12,$AP28="One-Time",0),AX28*(1+$D$3))} -> 0 | AZ28: {=IFERROR(_xlfn.IFS(VALUE(MID(AZ$5,6,1))>$D$2,0,$AP28="Annual",1,AY28=12,12,$AP28="Monthly V",AY28*(1+$D$3),$AP28="Monthly F",12,$AP28="One-Time",0),AY28*(1+$D$3))} -> 0 | BA28: {=IFERROR(_xlfn.IFS(VALUE(MID(BA$5,6,2))>$D$2,0,$AP28="Annual",1,AZ28=12,12,$AP28="Monthly V",AZ28*(1+$D$3),$AP28="Monthly F",12,$AP28="One-Time",0),AZ28*(1+$D$3))} -> 0 | BB28: CorPay Integration | BC28: DirectLine | BD28: 300 | BE28: =BF28/12 -> 300 | BF28: =IFERROR(AR28*$BD28,0) -> 3600 | BG28: =IFERROR(AS28*$BD28,0) -> 3600 | BH28: =IFERROR(AT28*$BD28,0) -> 3600 | BI28: =BH28*1.03 -> 3708 | BJ28: =BI28*1.03 -> 3819.24 | BK28: =BJ28*1.03 -> 3933.8172 | BL28: =BK28*1.03 -> 4051.8317 | BM28: =IFERROR(AY28*$BD28,0) -> 0 | BN28: =IFERROR(AZ28*$BD28,0) -> 0 | BO28: =IFERROR(BA28*$BD28,0) -> 0 | BQ28: =IF(VALUE(MID(BQ$5,6,1))<=$D$2,((1+$BD$3)^1-1)*BG28,0) -> 108 | BR28: =IF(VALUE(MID(BR$5,6,1))<=$D$2,((1+$BD$3)^2-1)*BH28,0) -> 219.24 | BS28: =IF(VALUE(MID(BS$5,6,1))<=$D$2,((1+$BD$3)^3-1)*BI28,0) -> 343.83172 | BT28: =IF(VALUE(MID(BT$5,6,1))<=$D$2,((1+$BD$3)^4-1)*BJ28,0) -> 479.34827 | BU28: =IF(VALUE(MID(BU$5,6,1))<=$D$2,((1+$BD$3)^5-1)*BK28,0) -> 626.55509 | BV28: =IF(VALUE(MID(BV$5,6,1))<=$D$2,((1+$BD$3)^6-1)*BL28,0) -> 786.26725 | BW28: =IF(VALUE(MID(BW$5,6,1))<=$D$2,((1+$BD$3)^7-1)*BM28,0) -> 0 | BX28: =IF(VALUE(MID(BX$5,6,1))<=$D$2,((1+$BD$3)^8-1)*BN28,0) -> 0 | BY28: =IF(VALUE(MID(BY$5,6,2))<=$D$2,((1+$BD$3)^9-1)*BO28,0) -> 0 | BZ28: =SUM(BP28:BY28) -> 2563.2423 | CA28: =SUM(BZ28,BF28:BO28) -> 28876.131 | CE28: =IF($CC28="Annual",1,IF($CC28="Monthly F",12,IF($CC28="Monthly V",CD28*12,IF($CC28="One-Time",1,CD28*12)))) -> 0 | CF28: {=IFERROR(_xlfn.IFS(VALUE(MID(CF$5,6,1))>$D$2,0,$CC28="Annual",1,CE28=12,12,$CC28="Monthly V",CE28*(1+$D$3),$CC28="Monthly F",12,$CC28="One-Time",0),CE28*(1+$D$3))} -> 0 | CG28: {=IFERROR(_xlfn.IFS(VALUE(MID(CG$5,6,1))>$D$2,0,$CC28="Annual",1,CF28=12,12,$CC28="Monthly V",CF28*(1+$D$3),$CC28="Monthly F",12,$CC28="One-Time",0),CF28*(1+$D$3))} -> 0 | CH28: {=IFERROR(_xlfn.IFS(VALUE(MID(CH$5,6,1))>$D$2,0,$CC28="Annual",1,CG28=12,12,$CC28="Monthly V",CG28*(1+$D$3),$CC28="Monthly F",12,$CC28="One-Time",0),CG28*(1+$D$3))} -> 0 | CI28: {=IFERROR(_xlfn.IFS(VALUE(MID(CI$5,6,1))>$D$2,0,$CC28="Annual",1,CH28=12,12,$CC28="Monthly V",CH28*(1+$D$3),$CC28="Monthly F",12,$CC28="One-Time",0),CH28*(1+$D$3))} -> 0 | CJ28: {=IFERROR(_xlfn.IFS(VALUE(MID(CJ$5,6,1))>$D$2,0,$CC28="Annual",1,CI28=12,12,$CC28="Monthly V",CI28*(1+$D$3),$CC28="Monthly F",12,$CC28="One-Time",0),CI28*(1+$D$3))} -> 0 | CK28: {=IFERROR(_xlfn.IFS(VALUE(MID(CK$5,6,1))>$D$2,0,$CC28="Annual",1,CJ28=12,12,$CC28="Monthly V",CJ28*(1+$D$3),$CC28="Monthly F",12,$CC28="One-Time",0),CJ28*(1+$D$3))} -> 0 | CL28: {=IFERROR(_xlfn.IFS(VALUE(MID(CL$5,6,1))>$D$2,0,$CC28="Annual",1,CK28=12,12,$CC28="Monthly V",CK28*(1+$D$3),$CC28="Monthly F",12,$CC28="One-Time",0),CK28*(1+$D$3))} -> 0 | CM28: {=IFERROR(_xlfn.IFS(VALUE(MID(CM$5,6,1))>$D$2,0,$CC28="Annual",1,CL28=12,12,$CC28="Monthly V",CL28*(1+$D$3),$CC28="Monthly F",12,$CC28="One-Time",0),CL28*(1+$D$3))} -> 0 | CN28: {=IFERROR(_xlfn.IFS(VALUE(MID(CN$5,6,2))>$D$2,0,$CC28="Annual",1,CM28=12,12,$CC28="Monthly V",CM28*(1+$D$3),$CC28="Monthly F",12,$CC28="One-Time",0),CM28*(1+$D$3))} -> 0 | CQ28: =CR28/12 -> 0 | CR28: =IFERROR(CE28*$CP28,0) -> 0 | CS28: =IFERROR(CF28*$CP28,0) -> 0 | CT28: =IFERROR(CG28*$CP28,0) -> 0 | CU28: =IFERROR(CH28*$CP28,0) -> 0 | CV28: =IFERROR(CI28*$CP28,0) -> 0 | CW28: =IFERROR(CJ28*$CP28,0) -> 0 | CX28: =IFERROR(CK28*$CP28,0) -> 0 | CY28: =IFERROR(CL28*$CP28,0) -> 0 | ... DA28: =IFERROR(CN28*$CP28,0) -> 0 | DC28: =IF(VALUE(MID(DC$5,6,1))<=$D$2,((1+$CP$3)^1-1)*CS28,0) -> 0 | DD28: =IF(VALUE(MID(DD$5,6,1))<=$D$2,((1+$CP$3)^2-1)*CT28,0) -> 0 | DE28: =IF(VALUE(MID(DE$5,6,1))<=$D$2,((1+$CP$3)^3-1)*CU28,0) -> 0 | DF28: =IF(VALUE(MID(DF$5,6,1))<=$D$2,((1+$CP$3)^4-1)*CV28,0) -> 0 | DG28: =IF(VALUE(MID(DG$5,6,1))<=$D$2,((1+$CP$3)^5-1)*CW28,0) -> 0 | DH28: =IF(VALUE(MID(DH$5,6,1))<=$D$2,((1+$CP$3)^6-1)*CX28,0) -> 0 | DI28: =IF(VALUE(MID(DI$5,6,1))<=$D$2,((1+$CP$3)^7-1)*CY28,0) -> 0 | DJ28: =IF(VALUE(MID(DJ$5,6,1))<=$D$2,((1+$CP$3)^8-1)*CZ28,0) -> 0 | DK28: =IF(VALUE(MID(DK$5,6,2))<=$D$2,((1+$CP$3)^9-1)*DA28,0) -> 0 | DL28: =SUM(DB28:DK28) -> 0 | DM28: =SUM(DL28,CR28:DA28) -> 0
O29: DirectLink Risk Review | R29: =S29/12 -> 0 | S29: =IFERROR($Q29*E29,0) -> 0 | T29: =IFERROR($Q29*F29,0) -> 0 | U29: =IFERROR($Q29*G29,0) -> 0 | V29: =IFERROR($Q29*H29,0) -> 0 | W29: =IFERROR($Q29*I29,0) -> 0 | X29: =IFERROR($Q29*J29,0) -> 0 | Y29: =IFERROR($Q29*K29,0) -> 0 | Z29: =IFERROR($Q29*L29,0) -> 0 | ... AB29: =IFERROR($Q29*N29,0) -> 0 | AD29: =IF(VALUE(MID(AD$5,6,1))<=$D$2,((1+$Q$3)^1-1)*T29,0) -> 0 | AE29: =IF(VALUE(MID(AE$5,6,1))<=$D$2,((1+$Q$3)^2-1)*U29,0) -> 0 | AF29: =IF(VALUE(MID(AF$5,6,1))<=$D$2,((1+$Q$3)^3-1)*V29,0) -> 0 | AG29: =IF(VALUE(MID(AG$5,6,1))<=$D$2,((1+$Q$3)^4-1)*W29,0) -> 0 | AH29: =IF(VALUE(MID(AH$5,6,1))<=$D$2,((1+$Q$3)^5-1)*X29,0) -> 0 | AI29: =IF(VALUE(MID(AI$5,6,1))<=$D$2,((1+$Q$3)^6-1)*Y29,0) -> 0 | AJ29: =IF(VALUE(MID(AJ$5,6,1))<=$D$2,((1+$Q$3)^7-1)*Z29,0) -> 0 | AK29: =IF(VALUE(MID(AK$5,6,1))<=$D$2,((1+$Q$3)^8-1)*AA29,0) -> 0 | AL29: =IF(VALUE(MID(AL$5,6,2))<=$D$2,((1+$Q$3)^9-1)*AB29,0) -> 0 | AM29: =SUM(AC29:AL29) -> 0 | AN29: =SUM(AM29,S29:AB29) -> 0 | AP29: Monthly F | AQ29: 1 | AR29: =IF($AP29="Annual",1,IF($AP29="Monthly F",12,IF($AP29="Monthly V",AQ29*12,IF($AP29="One-Time",1,AQ29*12)))) -> 12 | AS29: {=IFERROR(_xlfn.IFS(VALUE(MID(AS$5,6,1))>$D$2,0,$AP29="Annual",1,AR29=12,12,$AP29="Monthly V",AR29*(1+$BD$2),$AP29="Monthly F",12,$AP29="One-Time",0),AR29*(1+$BD$2))} -> 12 | AT29: {=IFERROR(_xlfn.IFS(VALUE(MID(AT$5,6,1))>$D$2,0,$AP29="Annual",1,AS29=12,12,$AP29="Monthly V",AS29*(1+$BD$2),$AP29="Monthly F",12,$AP29="One-Time",0),AS29*(1+$BD$2))} -> 12 | AU29: {=IFERROR(_xlfn.IFS(VALUE(MID(AU$5,6,1))>$D$2,0,$AP29="Annual",1,AT29=12,12,$AP29="Monthly V",AT29*(1+$BD$2),$AP29="Monthly F",12,$AP29="One-Time",0),AT29*(1+$BD$2))} -> 12 | AV29: {=IFERROR(_xlfn.IFS(VALUE(MID(AV$5,6,1))>$D$2,0,$AP29="Annual",1,AU29=12,12,$AP29="Monthly V",AU29*(1+$BD$2),$AP29="Monthly F",12,$AP29="One-Time",0),AU29*(1+$BD$2))} -> 12 | AW29: {=IFERROR(_xlfn.IFS(VALUE(MID(AW$5,6,1))>$D$2,0,$AP29="Annual",1,AV29=12,12,$AP29="Monthly V",AV29*(1+$BD$2),$AP29="Monthly F",12,$AP29="One-Time",0),AV29*(1+$BD$2))} -> 12 | AX29: {=IFERROR(_xlfn.IFS(VALUE(MID(AX$5,6,1))>$D$2,0,$AP29="Annual",1,AW29=12,12,$AP29="Monthly V",AW29*(1+$BD$2),$AP29="Monthly F",12,$AP29="One-Time",0),AW29*(1+$BD$2))} -> 12 | AY29: {=IFERROR(_xlfn.IFS(VALUE(MID(AY$5,6,1))>$D$2,0,$AP29="Annual",1,AX29=12,12,$AP29="Monthly V",AX29*(1+$D$3),$AP29="Monthly F",12,$AP29="One-Time",0),AX29*(1+$D$3))} -> 0 | AZ29: {=IFERROR(_xlfn.IFS(VALUE(MID(AZ$5,6,1))>$D$2,0,$AP29="Annual",1,AY29=12,12,$AP29="Monthly V",AY29*(1+$D$3),$AP29="Monthly F",12,$AP29="One-Time",0),AY29*(1+$D$3))} -> 0 | BA29: {=IFERROR(_xlfn.IFS(VALUE(MID(BA$5,6,2))>$D$2,0,$AP29="Annual",1,AZ29=12,12,$AP29="Monthly V",AZ29*(1+$D$3),$AP29="Monthly F",12,$AP29="One-Time",0),AZ29*(1+$D$3))} -> 0 | BB29: Zelle Implementation and Monthly Network | BC29: JHA Payment Center | BD29: 600 | BE29: =BF29/12 -> 600 | BF29: =IFERROR(AR29*$BD29,0) -> 7200 | BG29: =IFERROR(AS29*$BD29,0) -> 7200 | BH29: =IFERROR(AT29*$BD29,0) -> 7200 | BI29: =BH29*1.03 -> 7416 | BJ29: =BI29*1.03 -> 7638.48 | BK29: =BJ29*1.03 -> 7867.6344 | BL29: =BK29*1.03 -> 8103.6634 | BM29: =IFERROR(AY29*$BD29,0) -> 0 | BN29: =IFERROR(AZ29*$BD29,0) -> 0 | BO29: =IFERROR(BA29*$BD29,0) -> 0 | BQ29: =IF(VALUE(MID(BQ$5,6,1))<=$D$2,((1+$BD$3)^1-1)*BG29,0) -> 216 | BR29: =IF(VALUE(MID(BR$5,6,1))<=$D$2,((1+$BD$3)^2-1)*BH29,0) -> 438.48 | BS29: =IF(VALUE(MID(BS$5,6,1))<=$D$2,((1+$BD$3)^3-1)*BI29,0) -> 687.66343 | BT29: =IF(VALUE(MID(BT$5,6,1))<=$D$2,((1+$BD$3)^4-1)*BJ29,0) -> 958.69654 | BU29: =IF(VALUE(MID(BU$5,6,1))<=$D$2,((1+$BD$3)^5-1)*BK29,0) -> 1253.1102 | BV29: =IF(VALUE(MID(BV$5,6,1))<=$D$2,((1+$BD$3)^6-1)*BL29,0) -> 1572.5345 | BW29: =IF(VALUE(MID(BW$5,6,1))<=$D$2,((1+$BD$3)^7-1)*BM29,0) -> 0 | BX29: =IF(VALUE(MID(BX$5,6,1))<=$D$2,((1+$BD$3)^8-1)*BN29,0) -> 0 | BY29: =IF(VALUE(MID(BY$5,6,2))<=$D$2,((1+$BD$3)^9-1)*BO29,0) -> 0 | BZ29: =SUM(BP29:BY29) -> 5126.4847 | CA29: =SUM(BZ29,BF29:BO29) -> 57752.262 | CE29: =IF($CC29="Annual",1,IF($CC29="Monthly F",12,IF($CC29="Monthly V",CD29*12,IF($CC29="One-Time",1,CD29*12)))) -> 0 | CF29: {=IFERROR(_xlfn.IFS(VALUE(MID(CF$5,6,1))>$D$2,0,$CC29="Annual",1,CE29=12,12,$CC29="Monthly V",CE29*(1+$D$3),$CC29="Monthly F",12,$CC29="One-Time",0),CE29*(1+$D$3))} -> 0 | CG29: {=IFERROR(_xlfn.IFS(VALUE(MID(CG$5,6,1))>$D$2,0,$CC29="Annual",1,CF29=12,12,$CC29="Monthly V",CF29*(1+$D$3),$CC29="Monthly F",12,$CC29="One-Time",0),CF29*(1+$D$3))} -> 0 | CH29: {=IFERROR(_xlfn.IFS(VALUE(MID(CH$5,6,1))>$D$2,0,$CC29="Annual",1,CG29=12,12,$CC29="Monthly V",CG29*(1+$D$3),$CC29="Monthly F",12,$CC29="One-Time",0),CG29*(1+$D$3))} -> 0 | CI29: {=IFERROR(_xlfn.IFS(VALUE(MID(CI$5,6,1))>$D$2,0,$CC29="Annual",1,CH29=12,12,$CC29="Monthly V",CH29*(1+$D$3),$CC29="Monthly F",12,$CC29="One-Time",0),CH29*(1+$D$3))} -> 0 | CJ29: {=IFERROR(_xlfn.IFS(VALUE(MID(CJ$5,6,1))>$D$2,0,$CC29="Annual",1,CI29=12,12,$CC29="Monthly V",CI29*(1+$D$3),$CC29="Monthly F",12,$CC29="One-Time",0),CI29*(1+$D$3))} -> 0 | CK29: {=IFERROR(_xlfn.IFS(VALUE(MID(CK$5,6,1))>$D$2,0,$CC29="Annual",1,CJ29=12,12,$CC29="Monthly V",CJ29*(1+$D$3),$CC29="Monthly F",12,$CC29="One-Time",0),CJ29*(1+$D$3))} -> 0 | CL29: {=IFERROR(_xlfn.IFS(VALUE(MID(CL$5,6,1))>$D$2,0,$CC29="Annual",1,CK29=12,12,$CC29="Monthly V",CK29*(1+$D$3),$CC29="Monthly F",12,$CC29="One-Time",0),CK29*(1+$D$3))} -> 0 | CM29: {=IFERROR(_xlfn.IFS(VALUE(MID(CM$5,6,1))>$D$2,0,$CC29="Annual",1,CL29=12,12,$CC29="Monthly V",CL29*(1+$D$3),$CC29="Monthly F",12,$CC29="One-Time",0),CL29*(1+$D$3))} -> 0 | CN29: {=IFERROR(_xlfn.IFS(VALUE(MID(CN$5,6,2))>$D$2,0,$CC29="Annual",1,CM29=12,12,$CC29="Monthly V",CM29*(1+$D$3),$CC29="Monthly F",12,$CC29="One-Time",0),CM29*(1+$D$3))} -> 0 | CQ29: =CR29/12 -> 0 | CR29: =IFERROR(CE29*$CP29,0) -> 0 | CS29: =IFERROR(CF29*$CP29,0) -> 0 | CT29: =IFERROR(CG29*$CP29,0) -> 0 | CU29: =IFERROR(CH29*$CP29,0) -> 0 | CV29: =IFERROR(CI29*$CP29,0) -> 0 | CW29: =IFERROR(CJ29*$CP29,0) -> 0 | CX29: =IFERROR(CK29*$CP29,0) -> 0 | CY29: =IFERROR(CL29*$CP29,0) -> 0 | ... DA29: =IFERROR(CN29*$CP29,0) -> 0 | DC29: =IF(VALUE(MID(DC$5,6,1))<=$D$2,((1+$CP$3)^1-1)*CS29,0) -> 0 | DD29: =IF(VALUE(MID(DD$5,6,1))<=$D$2,((1+$CP$3)^2-1)*CT29,0) -> 0 | DE29: =IF(VALUE(MID(DE$5,6,1))<=$D$2,((1+$CP$3)^3-1)*CU29,0) -> 0 | DF29: =IF(VALUE(MID(DF$5,6,1))<=$D$2,((1+$CP$3)^4-1)*CV29,0) -> 0 | DG29: =IF(VALUE(MID(DG$5,6,1))<=$D$2,((1+$CP$3)^5-1)*CW29,0) -> 0 | DH29: =IF(VALUE(MID(DH$5,6,1))<=$D$2,((1+$CP$3)^6-1)*CX29,0) -> 0 | DI29: =IF(VALUE(MID(DI$5,6,1))<=$D$2,((1+$CP$3)^7-1)*CY29,0) -> 0 | DJ29: =IF(VALUE(MID(DJ$5,6,1))<=$D$2,((1+$CP$3)^8-1)*CZ29,0) -> 0 | DK29: =IF(VALUE(MID(DK$5,6,2))<=$D$2,((1+$CP$3)^9-1)*DA29,0) -> 0 | DL29: =SUM(DB29:DK29) -> 0 | DM29: =SUM(DL29,CR29:DA29) -> 0
B30: Monthly F | C30: 1 | D30: =IFERROR(AVERAGE(C30:C30),0) -> 1 | E30: =IF($B30="Annual",1,IF($B30="Monthly F",12,IF($B30="Monthly V",D30*12,IF($B30="One-Time",1,D30*12)))) -> 12 | F30: {=IFERROR(_xlfn.IFS(VALUE(MID(F$5,6,1))>$D$2,0,$B30="Annual",1,E30=12,12,$B30="Monthly V",E30*(1+$D$3),$B30="Monthly F",12,$B30="One-Time",0),E30*(1+$D$3))} -> 12 | G30: {=IFERROR(_xlfn.IFS(VALUE(MID(G$5,6,1))>$D$2,0,$B30="Annual",1,F30=12,12,$B30="Monthly V",F30*(1+$D$3),$B30="Monthly F",12,$B30="One-Time",0),F30*(1+$D$3))} -> 12 | H30: {=IFERROR(_xlfn.IFS(VALUE(MID(H$5,6,1))>$D$2,0,$B30="Annual",1,G30=12,12,$B30="Monthly V",G30*(1+$D$3),$B30="Monthly F",12,$B30="One-Time",0),G30*(1+$D$3))} -> 12 | I30: {=IFERROR(_xlfn.IFS(VALUE(MID(I$5,6,1))>$D$2,0,$B30="Annual",1,H30=12,12,$B30="Monthly V",H30*(1+$D$3),$B30="Monthly F",12,$B30="One-Time",0),H30*(1+$D$3))} -> 12 | J30: {=IFERROR(_xlfn.IFS(VALUE(MID(J$5,6,1))>$D$2,0,$B30="Annual",1,I30=12,12,$B30="Monthly V",I30*(1+$D$3),$B30="Monthly F",12,$B30="One-Time",0),I30*(1+$D$3))} -> 12 | K30: {=IFERROR(_xlfn.IFS(VALUE(MID(K$5,6,1))>$D$2,0,$B30="Annual",1,J30=12,12,$B30="Monthly V",J30*(1+$D$3),$B30="Monthly F",12,$B30="One-Time",0),J30*(1+$D$3))} -> 12 | L30: {=IFERROR(_xlfn.IFS(VALUE(MID(L$5,6,1))>$D$2,0,$B30="Annual",1,K30=12,12,$B30="Monthly V",K30*(1+$D$3),$B30="Monthly F",12,$B30="One-Time",0),K30*(1+$D$3))} -> 0 | M30: {=IFERROR(_xlfn.IFS(VALUE(MID(M$5,6,1))>$D$2,0,$B30="Annual",1,L30=12,12,$B30="Monthly V",L30*(1+$D$3),$B30="Monthly F",12,$B30="One-Time",0),L30*(1+$D$3))} -> 0 | N30: {=IFERROR(_xlfn.IFS(VALUE(MID(N$5,6,2))>$D$2,0,$B30="Annual",1,M30=12,12,$B30="Monthly V",M30*(1+$D$3),$B30="Monthly F",12,$B30="One-Time",0),M30*(1+$D$3))} -> 0 | O30: Monthly Minimum | P30: DirectLink | Q30: 200 | R30: =S30/12 -> 200 | S30: =IFERROR($Q30*E30,0) -> 2400 | T30: =IFERROR($Q30*F30,0) -> 2400 | U30: =IFERROR($Q30*G30,0) -> 2400 | V30: =IFERROR($Q30*H30,0) -> 2400 | W30: =IFERROR($Q30*I30,0) -> 2400 | X30: =IFERROR($Q30*J30,0) -> 2400 | Y30: =IFERROR($Q30*K30,0) -> 2400 | Z30: =IFERROR($Q30*L30,0) -> 0 | ... AB30: =IFERROR($Q30*N30,0) -> 0 | AD30: =IF(VALUE(MID(AD$5,6,1))<=$D$2,((1+$Q$3)^1-1)*T30,0) -> 72 | AE30: =IF(VALUE(MID(AE$5,6,1))<=$D$2,((1+$Q$3)^2-1)*U30,0) -> 146.16 | AF30: =IF(VALUE(MID(AF$5,6,1))<=$D$2,((1+$Q$3)^3-1)*V30,0) -> 222.5448 | AG30: =IF(VALUE(MID(AG$5,6,1))<=$D$2,((1+$Q$3)^4-1)*W30,0) -> 301.22114 | AH30: =IF(VALUE(MID(AH$5,6,1))<=$D$2,((1+$Q$3)^5-1)*X30,0) -> 382.25778 | AI30: =IF(VALUE(MID(AI$5,6,1))<=$D$2,((1+$Q$3)^6-1)*Y30,0) -> 465.72551 | AJ30: =IF(VALUE(MID(AJ$5,6,1))<=$D$2,((1+$Q$3)^7-1)*Z30,0) -> 0 | AK30: =IF(VALUE(MID(AK$5,6,1))<=$D$2,((1+$Q$3)^8-1)*AA30,0) -> 0 | AL30: =IF(VALUE(MID(AL$5,6,2))<=$D$2,((1+$Q$3)^9-1)*AB30,0) -> 0 | AM30: =SUM(AC30:AL30) -> 1589.9092 | AN30: =SUM(AM30,S30:AB30) -> 18389.909 | AP30: Monthly F | AQ30: 1 | AR30: =IF($AP30="Annual",1,IF($AP30="Monthly F",12,IF($AP30="Monthly V",AQ30*12,IF($AP30="One-Time",1,AQ30*12)))) -> 12 | AS30: {=IFERROR(_xlfn.IFS(VALUE(MID(AS$5,6,1))>$D$2,0,$AP30="Annual",1,AR30=12,12,$AP30="Monthly V",AR30*(1+$BD$2),$AP30="Monthly F",12,$AP30="One-Time",0),AR30*(1+$BD$2))} -> 12 | AT30: {=IFERROR(_xlfn.IFS(VALUE(MID(AT$5,6,1))>$D$2,0,$AP30="Annual",1,AS30=12,12,$AP30="Monthly V",AS30*(1+$BD$2),$AP30="Monthly F",12,$AP30="One-Time",0),AS30*(1+$BD$2))} -> 12 | AU30: {=IFERROR(_xlfn.IFS(VALUE(MID(AU$5,6,1))>$D$2,0,$AP30="Annual",1,AT30=12,12,$AP30="Monthly V",AT30*(1+$BD$2),$AP30="Monthly F",12,$AP30="One-Time",0),AT30*(1+$BD$2))} -> 12 | AV30: {=IFERROR(_xlfn.IFS(VALUE(MID(AV$5,6,1))>$D$2,0,$AP30="Annual",1,AU30=12,12,$AP30="Monthly V",AU30*(1+$BD$2),$AP30="Monthly F",12,$AP30="One-Time",0),AU30*(1+$BD$2))} -> 12 | AW30: {=IFERROR(_xlfn.IFS(VALUE(MID(AW$5,6,1))>$D$2,0,$AP30="Annual",1,AV30=12,12,$AP30="Monthly V",AV30*(1+$BD$2),$AP30="Monthly F",12,$AP30="One-Time",0),AV30*(1+$BD$2))} -> 12 | AX30: {=IFERROR(_xlfn.IFS(VALUE(MID(AX$5,6,1))>$D$2,0,$AP30="Annual",1,AW30=12,12,$AP30="Monthly V",AW30*(1+$BD$2),$AP30="Monthly F",12,$AP30="One-Time",0),AW30*(1+$BD$2))} -> 12 | AY30: {=IFERROR(_xlfn.IFS(VALUE(MID(AY$5,6,1))>$D$2,0,$AP30="Annual",1,AX30=12,12,$AP30="Monthly V",AX30*(1+$D$3),$AP30="Monthly F",12,$AP30="One-Time",0),AX30*(1+$D$3))} -> 0 | AZ30: {=IFERROR(_xlfn.IFS(VALUE(MID(AZ$5,6,1))>$D$2,0,$AP30="Annual",1,AY30=12,12,$AP30="Monthly V",AY30*(1+$D$3),$AP30="Monthly F",12,$AP30="One-Time",0),AY30*(1+$D$3))} -> 0 | BA30: {=IFERROR(_xlfn.IFS(VALUE(MID(BA$5,6,2))>$D$2,0,$AP30="Annual",1,AZ30=12,12,$AP30="Monthly V",AZ30*(1+$D$3),$AP30="Monthly F",12,$AP30="One-Time",0),AZ30*(1+$D$3))} -> 0 | BB30: RTP Implementation and Monthly Network Receive Only | BC30: JHA Payment Center | BD30: 400 | BE30: =BF30/12 -> 400 | BF30: =IFERROR(AR30*$BD30,0) -> 4800 | BG30: =IFERROR(AS30*$BD30,0) -> 4800 | BH30: =IFERROR(AT30*$BD30,0) -> 4800 | BI30: =BH30*1.03 -> 4944 | BJ30: =BI30*1.03 -> 5092.32 | BK30: =BJ30*1.03 -> 5245.0896 | BL30: =BK30*1.03 -> 5402.4423 | BM30: =IFERROR(AY30*$BD30,0) -> 0 | BN30: =IFERROR(AZ30*$BD30,0) -> 0 | BO30: =IFERROR(BA30*$BD30,0) -> 0 | BQ30: =IF(VALUE(MID(BQ$5,6,1))<=$D$2,((1+$BD$3)^1-1)*BG30,0) -> 144 | BR30: =IF(VALUE(MID(BR$5,6,1))<=$D$2,((1+$BD$3)^2-1)*BH30,0) -> 292.32 | BS30: =IF(VALUE(MID(BS$5,6,1))<=$D$2,((1+$BD$3)^3-1)*BI30,0) -> 458.44229 | BT30: =IF(VALUE(MID(BT$5,6,1))<=$D$2,((1+$BD$3)^4-1)*BJ30,0) -> 639.13102 | BU30: =IF(VALUE(MID(BU$5,6,1))<=$D$2,((1+$BD$3)^5-1)*BK30,0) -> 835.40679 | BV30: =IF(VALUE(MID(BV$5,6,1))<=$D$2,((1+$BD$3)^6-1)*BL30,0) -> 1048.3563 | BW30: =IF(VALUE(MID(BW$5,6,1))<=$D$2,((1+$BD$3)^7-1)*BM30,0) -> 0 | BX30: =IF(VALUE(MID(BX$5,6,1))<=$D$2,((1+$BD$3)^8-1)*BN30,0) -> 0 | BY30: =IF(VALUE(MID(BY$5,6,2))<=$D$2,((1+$BD$3)^9-1)*BO30,0) -> 0 | BZ30: =SUM(BP30:BY30) -> 3417.6564 | CA30: =SUM(BZ30,BF30:BO30) -> 38501.508 | CE30: =IF($CC30="Annual",1,IF($CC30="Monthly F",12,IF($CC30="Monthly V",CD30*12,IF($CC30="One-Time",1,CD30*12)))) -> 0 | CF30: {=IFERROR(_xlfn.IFS(VALUE(MID(CF$5,6,1))>$D$2,0,$CC30="Annual",1,CE30=12,12,$CC30="Monthly V",CE30*(1+$D$3),$CC30="Monthly F",12,$CC30="One-Time",0),CE30*(1+$D$3))} -> 0 | CG30: {=IFERROR(_xlfn.IFS(VALUE(MID(CG$5,6,1))>$D$2,0,$CC30="Annual",1,CF30=12,12,$CC30="Monthly V",CF30*(1+$D$3),$CC30="Monthly F",12,$CC30="One-Time",0),CF30*(1+$D$3))} -> 0 | CH30: {=IFERROR(_xlfn.IFS(VALUE(MID(CH$5,6,1))>$D$2,0,$CC30="Annual",1,CG30=12,12,$CC30="Monthly V",CG30*(1+$D$3),$CC30="Monthly F",12,$CC30="One-Time",0),CG30*(1+$D$3))} -> 0 | CI30: {=IFERROR(_xlfn.IFS(VALUE(MID(CI$5,6,1))>$D$2,0,$CC30="Annual",1,CH30=12,12,$CC30="Monthly V",CH30*(1+$D$3),$CC30="Monthly F",12,$CC30="One-Time",0),CH30*(1+$D$3))} -> 0 | CJ30: {=IFERROR(_xlfn.IFS(VALUE(MID(CJ$5,6,1))>$D$2,0,$CC30="Annual",1,CI30=12,12,$CC30="Monthly V",CI30*(1+$D$3),$CC30="Monthly F",12,$CC30="One-Time",0),CI30*(1+$D$3))} -> 0 | CK30: {=IFERROR(_xlfn.IFS(VALUE(MID(CK$5,6,1))>$D$2,0,$CC30="Annual",1,CJ30=12,12,$CC30="Monthly V",CJ30*(1+$D$3),$CC30="Monthly F",12,$CC30="One-Time",0),CJ30*(1+$D$3))} -> 0 | CL30: {=IFERROR(_xlfn.IFS(VALUE(MID(CL$5,6,1))>$D$2,0,$CC30="Annual",1,CK30=12,12,$CC30="Monthly V",CK30*(1+$D$3),$CC30="Monthly F",12,$CC30="One-Time",0),CK30*(1+$D$3))} -> 0 | CM30: {=IFERROR(_xlfn.IFS(VALUE(MID(CM$5,6,1))>$D$2,0,$CC30="Annual",1,CL30=12,12,$CC30="Monthly V",CL30*(1+$D$3),$CC30="Monthly F",12,$CC30="One-Time",0),CL30*(1+$D$3))} -> 0 | CN30: {=IFERROR(_xlfn.IFS(VALUE(MID(CN$5,6,2))>$D$2,0,$CC30="Annual",1,CM30=12,12,$CC30="Monthly V",CM30*(1+$D$3),$CC30="Monthly F",12,$CC30="One-Time",0),CM30*(1+$D$3))} -> 0 | CQ30: =CR30/12 -> 0 | CR30: =IFERROR(CE30*$CP30,0) -> 0 | CS30: =IFERROR(CF30*$CP30,0) -> 0 | CT30: =IFERROR(CG30*$CP30,0) -> 0 | CU30: =IFERROR(CH30*$CP30,0) -> 0 | CV30: =IFERROR(CI30*$CP30,0) -> 0 | CW30: =IFERROR(CJ30*$CP30,0) -> 0 | CX30: =IFERROR(CK30*$CP30,0) -> 0 | CY30: =IFERROR(CL30*$CP30,0) -> 0 | ... DA30: =IFERROR(CN30*$CP30,0) -> 0 | DC30: =IF(VALUE(MID(DC$5,6,1))<=$D$2,((1+$CP$3)^1-1)*CS30,0) -> 0 | DD30: =IF(VALUE(MID(DD$5,6,1))<=$D$2,((1+$CP$3)^2-1)*CT30,0) -> 0 | DE30: =IF(VALUE(MID(DE$5,6,1))<=$D$2,((1+$CP$3)^3-1)*CU30,0) -> 0 | DF30: =IF(VALUE(MID(DF$5,6,1))<=$D$2,((1+$CP$3)^4-1)*CV30,0) -> 0 | DG30: =IF(VALUE(MID(DG$5,6,1))<=$D$2,((1+$CP$3)^5-1)*CW30,0) -> 0 | DH30: =IF(VALUE(MID(DH$5,6,1))<=$D$2,((1+$CP$3)^6-1)*CX30,0) -> 0 | DI30: =IF(VALUE(MID(DI$5,6,1))<=$D$2,((1+$CP$3)^7-1)*CY30,0) -> 0 | DJ30: =IF(VALUE(MID(DJ$5,6,1))<=$D$2,((1+$CP$3)^8-1)*CZ30,0) -> 0 | DK30: =IF(VALUE(MID(DK$5,6,2))<=$D$2,((1+$CP$3)^9-1)*DA30,0) -> 0 | DL30: =SUM(DB30:DK30) -> 0 | DM30: =SUM(DL30,CR30:DA30) -> 0
B31: Monthly V | C31: 10000 | D31: =IFERROR(AVERAGE(C31:C31),0) -> 10000 | E31: =IF($B31="Annual",1,IF($B31="Monthly F",12,IF($B31="Monthly V",D31*12,IF($B31="One-Time",1,D31*12)))) -> 120000 | F31: {=IFERROR(_xlfn.IFS(VALUE(MID(F$5,6,1))>$D$2,0,$B31="Annual",1,E31=12,12,$B31="Monthly V",E31*(1+$D$3),$B31="Monthly F",12,$B31="One-Time",0),E31*(1+$D$3))} -> 144000 | G31: {=IFERROR(_xlfn.IFS(VALUE(MID(G$5,6,1))>$D$2,0,$B31="Annual",1,F31=12,12,$B31="Monthly V",F31*(1+$D$3),$B31="Monthly F",12,$B31="One-Time",0),F31*(1+$D$3))} -> 172800 | H31: {=IFERROR(_xlfn.IFS(VALUE(MID(H$5,6,1))>$D$2,0,$B31="Annual",1,G31=12,12,$B31="Monthly V",G31*(1+$D$3),$B31="Monthly F",12,$B31="One-Time",0),G31*(1+$D$3))} -> 207360 | I31: {=IFERROR(_xlfn.IFS(VALUE(MID(I$5,6,1))>$D$2,0,$B31="Annual",1,H31=12,12,$B31="Monthly V",H31*(1+$D$3),$B31="Monthly F",12,$B31="One-Time",0),H31*(1+$D$3))} -> 248832 | J31: {=IFERROR(_xlfn.IFS(VALUE(MID(J$5,6,1))>$D$2,0,$B31="Annual",1,I31=12,12,$B31="Monthly V",I31*(1+$D$3),$B31="Monthly F",12,$B31="One-Time",0),I31*(1+$D$3))} -> 298598.4 | K31: {=IFERROR(_xlfn.IFS(VALUE(MID(K$5,6,1))>$D$2,0,$B31="Annual",1,J31=12,12,$B31="Monthly V",J31*(1+$D$3),$B31="Monthly F",12,$B31="One-Time",0),J31*(1+$D$3))} -> 358318.08 | L31: {=IFERROR(_xlfn.IFS(VALUE(MID(L$5,6,1))>$D$2,0,$B31="Annual",1,K31=12,12,$B31="Monthly V",K31*(1+$D$3),$B31="Monthly F",12,$B31="One-Time",0),K31*(1+$D$3))} -> 0 | M31: {=IFERROR(_xlfn.IFS(VALUE(MID(M$5,6,1))>$D$2,0,$B31="Annual",1,L31=12,12,$B31="Monthly V",L31*(1+$D$3),$B31="Monthly F",12,$B31="One-Time",0),L31*(1+$D$3))} -> 0 | N31: {=IFERROR(_xlfn.IFS(VALUE(MID(N$5,6,2))>$D$2,0,$B31="Annual",1,M31=12,12,$B31="Monthly V",M31*(1+$D$3),$B31="Monthly F",12,$B31="One-Time",0),M31*(1+$D$3))} -> 0 | O31: DirectLink Risk Review (Transactions) | P31: DirectLink | Q31: 0.0033 | R31: =S31/12 -> 33 | S31: =IFERROR($Q31*E31,0) -> 396 | T31: =IFERROR($Q31*F31,0) -> 475.2 | U31: =IFERROR($Q31*G31,0) -> 570.24 | V31: =IFERROR($Q31*H31,0) -> 684.288 | W31: =IFERROR($Q31*I31,0) -> 821.1456 | X31: =IFERROR($Q31*J31,0) -> 985.37472 | Y31: =IFERROR($Q31*K31,0) -> 1182.4497 | Z31: =IFERROR($Q31*L31,0) -> 0 | ... AB31: =IFERROR($Q31*N31,0) -> 0 | AD31: =IF(VALUE(MID(AD$5,6,1))<=$D$2,((1+$Q$3)^1-1)*T31,0) -> 14.256 | AE31: =IF(VALUE(MID(AE$5,6,1))<=$D$2,((1+$Q$3)^2-1)*U31,0) -> 34.727616 | AF31: =IF(VALUE(MID(AF$5,6,1))<=$D$2,((1+$Q$3)^3-1)*V31,0) -> 63.451973 | AG31: =IF(VALUE(MID(AG$5,6,1))<=$D$2,((1+$Q$3)^4-1)*W31,0) -> 103.06101 | AH31: =IF(VALUE(MID(AH$5,6,1))<=$D$2,((1+$Q$3)^5-1)*X31,0) -> 156.94465 | AI31: =IF(VALUE(MID(AI$5,6,1))<=$D$2,((1+$Q$3)^6-1)*Y31,0) -> 229.45707 | AJ31: =IF(VALUE(MID(AJ$5,6,1))<=$D$2,((1+$Q$3)^7-1)*Z31,0) -> 0 | AK31: =IF(VALUE(MID(AK$5,6,1))<=$D$2,((1+$Q$3)^8-1)*AA31,0) -> 0 | AL31: =IF(VALUE(MID(AL$5,6,2))<=$D$2,((1+$Q$3)^9-1)*AB31,0) -> 0 | AM31: =SUM(AC31:AL31) -> 601.89832 | AN31: =SUM(AM31,S31:AB31) -> 5716.5963 | AP31: Monthly F | AQ31: 1 | AR31: =IF($AP31="Annual",1,IF($AP31="Monthly F",12,IF($AP31="Monthly V",AQ31*12,IF($AP31="One-Time",1,AQ31*12)))) -> 12 | AS31: {=IFERROR(_xlfn.IFS(VALUE(MID(AS$5,6,1))>$D$2,0,$AP31="Annual",1,AR31=12,12,$AP31="Monthly V",AR31*(1+$BD$2),$AP31="Monthly F",12,$AP31="One-Time",0),AR31*(1+$BD$2))} -> 12 | AT31: {=IFERROR(_xlfn.IFS(VALUE(MID(AT$5,6,1))>$D$2,0,$AP31="Annual",1,AS31=12,12,$AP31="Monthly V",AS31*(1+$BD$2),$AP31="Monthly F",12,$AP31="One-Time",0),AS31*(1+$BD$2))} -> 12 | AU31: {=IFERROR(_xlfn.IFS(VALUE(MID(AU$5,6,1))>$D$2,0,$AP31="Annual",1,AT31=12,12,$AP31="Monthly V",AT31*(1+$BD$2),$AP31="Monthly F",12,$AP31="One-Time",0),AT31*(1+$BD$2))} -> 12 | AV31: {=IFERROR(_xlfn.IFS(VALUE(MID(AV$5,6,1))>$D$2,0,$AP31="Annual",1,AU31=12,12,$AP31="Monthly V",AU31*(1+$BD$2),$AP31="Monthly F",12,$AP31="One-Time",0),AU31*(1+$BD$2))} -> 12 | AW31: {=IFERROR(_xlfn.IFS(VALUE(MID(AW$5,6,1))>$D$2,0,$AP31="Annual",1,AV31=12,12,$AP31="Monthly V",AV31*(1+$BD$2),$AP31="Monthly F",12,$AP31="One-Time",0),AV31*(1+$BD$2))} -> 12 | AX31: {=IFERROR(_xlfn.IFS(VALUE(MID(AX$5,6,1))>$D$2,0,$AP31="Annual",1,AW31=12,12,$AP31="Monthly V",AW31*(1+$BD$2),$AP31="Monthly F",12,$AP31="One-Time",0),AW31*(1+$BD$2))} -> 12 | AY31: {=IFERROR(_xlfn.IFS(VALUE(MID(AY$5,6,1))>$D$2,0,$AP31="Annual",1,AX31=12,12,$AP31="Monthly V",AX31*(1+$D$3),$AP31="Monthly F",12,$AP31="One-Time",0),AX31*(1+$D$3))} -> 0 | AZ31: {=IFERROR(_xlfn.IFS(VALUE(MID(AZ$5,6,1))>$D$2,0,$AP31="Annual",1,AY31=12,12,$AP31="Monthly V",AY31*(1+$D$3),$AP31="Monthly F",12,$AP31="One-Time",0),AY31*(1+$D$3))} -> 0 | BA31: {=IFERROR(_xlfn.IFS(VALUE(MID(BA$5,6,2))>$D$2,0,$AP31="Annual",1,AZ31=12,12,$AP31="Monthly V",AZ31*(1+$D$3),$AP31="Monthly F",12,$AP31="One-Time",0),AZ31*(1+$D$3))} -> 0 | BB31: FedNow Implementation and Monthly Network Receive Only | BC31: JHA Payment Center | BD31: 400 | BE31: =BF31/12 -> 400 | BF31: =IFERROR(AR31*$BD31,0) -> 4800 | BG31: =IFERROR(AS31*$BD31,0) -> 4800 | BH31: =IFERROR(AT31*$BD31,0) -> 4800 | BI31: =BH31*1.03 -> 4944 | BJ31: =BI31*1.03 -> 5092.32 | BK31: =BJ31*1.03 -> 5245.0896 | BL31: =BK31*1.03 -> 5402.4423 | BM31: =IFERROR(AY31*$BD31,0) -> 0 | BN31: =IFERROR(AZ31*$BD31,0) -> 0 | BO31: =IFERROR(BA31*$BD31,0) -> 0 | BQ31: =IF(VALUE(MID(BQ$5,6,1))<=$D$2,((1+$BD$3)^1-1)*BG31,0) -> 144 | BR31: =IF(VALUE(MID(BR$5,6,1))<=$D$2,((1+$BD$3)^2-1)*BH31,0) -> 292.32 | BS31: =IF(VALUE(MID(BS$5,6,1))<=$D$2,((1+$BD$3)^3-1)*BI31,0) -> 458.44229 | BT31: =IF(VALUE(MID(BT$5,6,1))<=$D$2,((1+$BD$3)^4-1)*BJ31,0) -> 639.13102 | BU31: =IF(VALUE(MID(BU$5,6,1))<=$D$2,((1+$BD$3)^5-1)*BK31,0) -> 835.40679 | BV31: =IF(VALUE(MID(BV$5,6,1))<=$D$2,((1+$BD$3)^6-1)*BL31,0) -> 1048.3563 | BW31: =IF(VALUE(MID(BW$5,6,1))<=$D$2,((1+$BD$3)^7-1)*BM31,0) -> 0 | BX31: =IF(VALUE(MID(BX$5,6,1))<=$D$2,((1+$BD$3)^8-1)*BN31,0) -> 0 | BY31: =IF(VALUE(MID(BY$5,6,2))<=$D$2,((1+$BD$3)^9-1)*BO31,0) -> 0 | BZ31: =SUM(BP31:BY31) -> 3417.6564 | CA31: =SUM(BZ31,BF31:BO31) -> 38501.508 | CE31: =IF($CC31="Annual",1,IF($CC31="Monthly F",12,IF($CC31="Monthly V",CD31*12,IF($CC31="One-Time",1,CD31*12)))) -> 0 | CF31: {=IFERROR(_xlfn.IFS(VALUE(MID(CF$5,6,1))>$D$2,0,$CC31="Annual",1,CE31=12,12,$CC31="Monthly V",CE31*(1+$D$3),$CC31="Monthly F",12,$CC31="One-Time",0),CE31*(1+$D$3))} -> 0 | CG31: {=IFERROR(_xlfn.IFS(VALUE(MID(CG$5,6,1))>$D$2,0,$CC31="Annual",1,CF31=12,12,$CC31="Monthly V",CF31*(1+$D$3),$CC31="Monthly F",12,$CC31="One-Time",0),CF31*(1+$D$3))} -> 0 | CH31: {=IFERROR(_xlfn.IFS(VALUE(MID(CH$5,6,1))>$D$2,0,$CC31="Annual",1,CG31=12,12,$CC31="Monthly V",CG31*(1+$D$3),$CC31="Monthly F",12,$CC31="One-Time",0),CG31*(1+$D$3))} -> 0 | CI31: {=IFERROR(_xlfn.IFS(VALUE(MID(CI$5,6,1))>$D$2,0,$CC31="Annual",1,CH31=12,12,$CC31="Monthly V",CH31*(1+$D$3),$CC31="Monthly F",12,$CC31="One-Time",0),CH31*(1+$D$3))} -> 0 | CJ31: {=IFERROR(_xlfn.IFS(VALUE(MID(CJ$5,6,1))>$D$2,0,$CC31="Annual",1,CI31=12,12,$CC31="Monthly V",CI31*(1+$D$3),$CC31="Monthly F",12,$CC31="One-Time",0),CI31*(1+$D$3))} -> 0 | CK31: {=IFERROR(_xlfn.IFS(VALUE(MID(CK$5,6,1))>$D$2,0,$CC31="Annual",1,CJ31=12,12,$CC31="Monthly V",CJ31*(1+$D$3),$CC31="Monthly F",12,$CC31="One-Time",0),CJ31*(1+$D$3))} -> 0 | CL31: {=IFERROR(_xlfn.IFS(VALUE(MID(CL$5,6,1))>$D$2,0,$CC31="Annual",1,CK31=12,12,$CC31="Monthly V",CK31*(1+$D$3),$CC31="Monthly F",12,$CC31="One-Time",0),CK31*(1+$D$3))} -> 0 | CM31: {=IFERROR(_xlfn.IFS(VALUE(MID(CM$5,6,1))>$D$2,0,$CC31="Annual",1,CL31=12,12,$CC31="Monthly V",CL31*(1+$D$3),$CC31="Monthly F",12,$CC31="One-Time",0),CL31*(1+$D$3))} -> 0 | CN31: {=IFERROR(_xlfn.IFS(VALUE(MID(CN$5,6,2))>$D$2,0,$CC31="Annual",1,CM31=12,12,$CC31="Monthly V",CM31*(1+$D$3),$CC31="Monthly F",12,$CC31="One-Time",0),CM31*(1+$D$3))} -> 0 | CQ31: =CR31/12 -> 0 | CR31: =IFERROR(CE31*$CP31,0) -> 0 | CS31: =IFERROR(CF31*$CP31,0) -> 0 | CT31: =IFERROR(CG31*$CP31,0) -> 0 | CU31: =IFERROR(CH31*$CP31,0) -> 0 | CV31: =IFERROR(CI31*$CP31,0) -> 0 | CW31: =IFERROR(CJ31*$CP31,0) -> 0 | CX31: =IFERROR(CK31*$CP31,0) -> 0 | CY31: =IFERROR(CL31*$CP31,0) -> 0 | ... DA31: =IFERROR(CN31*$CP31,0) -> 0 | DC31: =IF(VALUE(MID(DC$5,6,1))<=$D$2,((1+$CP$3)^1-1)*CS31,0) -> 0 | DD31: =IF(VALUE(MID(DD$5,6,1))<=$D$2,((1+$CP$3)^2-1)*CT31,0) -> 0 | DE31: =IF(VALUE(MID(DE$5,6,1))<=$D$2,((1+$CP$3)^3-1)*CU31,0) -> 0 | DF31: =IF(VALUE(MID(DF$5,6,1))<=$D$2,((1+$CP$3)^4-1)*CV31,0) -> 0 | DG31: =IF(VALUE(MID(DG$5,6,1))<=$D$2,((1+$CP$3)^5-1)*CW31,0) -> 0 | DH31: =IF(VALUE(MID(DH$5,6,1))<=$D$2,((1+$CP$3)^6-1)*CX31,0) -> 0 | DI31: =IF(VALUE(MID(DI$5,6,1))<=$D$2,((1+$CP$3)^7-1)*CY31,0) -> 0 | DJ31: =IF(VALUE(MID(DJ$5,6,1))<=$D$2,((1+$CP$3)^8-1)*CZ31,0) -> 0 | DK31: =IF(VALUE(MID(DK$5,6,2))<=$D$2,((1+$CP$3)^9-1)*DA31,0) -> 0 | DL31: =SUM(DB31:DK31) -> 0 | DM31: =SUM(DL31,CR31:DA31) -> 0
O32: Card Suite Pro (digital debit card controls) | R32: =S32/12 -> 0 | S32: =IFERROR($Q32*E32,0) -> 0 | T32: =IFERROR($Q32*F32,0) -> 0 | U32: =IFERROR($Q32*G32,0) -> 0 | V32: =IFERROR($Q32*H32,0) -> 0 | W32: =IFERROR($Q32*I32,0) -> 0 | X32: =IFERROR($Q32*J32,0) -> 0 | Y32: =IFERROR($Q32*K32,0) -> 0 | Z32: =IFERROR($Q32*L32,0) -> 0 | ... AB32: =IFERROR($Q32*N32,0) -> 0 | AD32: =IF(VALUE(MID(AD$5,6,1))<=$D$2,((1+$Q$3)^1-1)*T32,0) -> 0 | AE32: =IF(VALUE(MID(AE$5,6,1))<=$D$2,((1+$Q$3)^2-1)*U32,0) -> 0 | AF32: =IF(VALUE(MID(AF$5,6,1))<=$D$2,((1+$Q$3)^3-1)*V32,0) -> 0 | AG32: =IF(VALUE(MID(AG$5,6,1))<=$D$2,((1+$Q$3)^4-1)*W32,0) -> 0 | AH32: =IF(VALUE(MID(AH$5,6,1))<=$D$2,((1+$Q$3)^5-1)*X32,0) -> 0 | AI32: =IF(VALUE(MID(AI$5,6,1))<=$D$2,((1+$Q$3)^6-1)*Y32,0) -> 0 | AJ32: =IF(VALUE(MID(AJ$5,6,1))<=$D$2,((1+$Q$3)^7-1)*Z32,0) -> 0 | AK32: =IF(VALUE(MID(AK$5,6,1))<=$D$2,((1+$Q$3)^8-1)*AA32,0) -> 0 | AL32: =IF(VALUE(MID(AL$5,6,2))<=$D$2,((1+$Q$3)^9-1)*AB32,0) -> 0 | AM32: =SUM(AC32:AL32) -> 0 | AN32: =SUM(AM32,S32:AB32) -> 0 | AP32: Monthly F | AQ32: 1 | AR32: =IF($AP32="Annual",1,IF($AP32="Monthly F",12,IF($AP32="Monthly V",AQ32*12,IF($AP32="One-Time",1,AQ32*12)))) -> 12 | AS32: {=IFERROR(_xlfn.IFS(VALUE(MID(AS$5,6,1))>$D$2,0,$AP32="Annual",1,AR32=12,12,$AP32="Monthly V",AR32*(1+$BD$2),$AP32="Monthly F",12,$AP32="One-Time",0),AR32*(1+$BD$2))} -> 12 | AT32: {=IFERROR(_xlfn.IFS(VALUE(MID(AT$5,6,1))>$D$2,0,$AP32="Annual",1,AS32=12,12,$AP32="Monthly V",AS32*(1+$BD$2),$AP32="Monthly F",12,$AP32="One-Time",0),AS32*(1+$BD$2))} -> 12 | AU32: {=IFERROR(_xlfn.IFS(VALUE(MID(AU$5,6,1))>$D$2,0,$AP32="Annual",1,AT32=12,12,$AP32="Monthly V",AT32*(1+$BD$2),$AP32="Monthly F",12,$AP32="One-Time",0),AT32*(1+$BD$2))} -> 12 | AV32: {=IFERROR(_xlfn.IFS(VALUE(MID(AV$5,6,1))>$D$2,0,$AP32="Annual",1,AU32=12,12,$AP32="Monthly V",AU32*(1+$BD$2),$AP32="Monthly F",12,$AP32="One-Time",0),AU32*(1+$BD$2))} -> 12 | AW32: {=IFERROR(_xlfn.IFS(VALUE(MID(AW$5,6,1))>$D$2,0,$AP32="Annual",1,AV32=12,12,$AP32="Monthly V",AV32*(1+$BD$2),$AP32="Monthly F",12,$AP32="One-Time",0),AV32*(1+$BD$2))} -> 12 | AX32: {=IFERROR(_xlfn.IFS(VALUE(MID(AX$5,6,1))>$D$2,0,$AP32="Annual",1,AW32=12,12,$AP32="Monthly V",AW32*(1+$BD$2),$AP32="Monthly F",12,$AP32="One-Time",0),AW32*(1+$BD$2))} -> 12 | AY32: {=IFERROR(_xlfn.IFS(VALUE(MID(AY$5,6,1))>$D$2,0,$AP32="Annual",1,AX32=12,12,$AP32="Monthly V",AX32*(1+$D$3),$AP32="Monthly F",12,$AP32="One-Time",0),AX32*(1+$D$3))} -> 0 | AZ32: {=IFERROR(_xlfn.IFS(VALUE(MID(AZ$5,6,1))>$D$2,0,$AP32="Annual",1,AY32=12,12,$AP32="Monthly V",AY32*(1+$D$3),$AP32="Monthly F",12,$AP32="One-Time",0),AY32*(1+$D$3))} -> 0 | BA32: {=IFERROR(_xlfn.IFS(VALUE(MID(BA$5,6,2))>$D$2,0,$AP32="Annual",1,AZ32=12,12,$AP32="Monthly V",AZ32*(1+$D$3),$AP32="Monthly F",12,$AP32="One-Time",0),AZ32*(1+$D$3))} -> 0 | BB32: JHA SmartPay Remote Deposit Now (RDN) | BC32: Enterprise Payment Solutions (EPS) | BD32: 350 | BE32: =BF32/12 -> 350 | BF32: =IFERROR(AR32*$BD32,0) -> 4200 | BG32: =IFERROR(AS32*$BD32,0) -> 4200 | BH32: =IFERROR(AT32*$BD32,0) -> 4200 | BI32: =BH32*1.03 -> 4326 | BJ32: =BI32*1.03 -> 4455.78 | BK32: =BJ32*1.03 -> 4589.4534 | BL32: =BK32*1.03 -> 4727.137 | BM32: =IFERROR(AY32*$BD32,0) -> 0 | BN32: =IFERROR(AZ32*$BD32,0) -> 0 | BO32: =IFERROR(BA32*$BD32,0) -> 0 | BQ32: =IF(VALUE(MID(BQ$5,6,1))<=$D$2,((1+$BD$3)^1-1)*BG32,0) -> 126 | BR32: =IF(VALUE(MID(BR$5,6,1))<=$D$2,((1+$BD$3)^2-1)*BH32,0) -> 255.78 | BS32: =IF(VALUE(MID(BS$5,6,1))<=$D$2,((1+$BD$3)^3-1)*BI32,0) -> 401.137 | BT32: =IF(VALUE(MID(BT$5,6,1))<=$D$2,((1+$BD$3)^4-1)*BJ32,0) -> 559.23965 | BU32: =IF(VALUE(MID(BU$5,6,1))<=$D$2,((1+$BD$3)^5-1)*BK32,0) -> 730.98094 | BV32: =IF(VALUE(MID(BV$5,6,1))<=$D$2,((1+$BD$3)^6-1)*BL32,0) -> 917.31179 | BW32: =IF(VALUE(MID(BW$5,6,1))<=$D$2,((1+$BD$3)^7-1)*BM32,0) -> 0 | BX32: =IF(VALUE(MID(BX$5,6,1))<=$D$2,((1+$BD$3)^8-1)*BN32,0) -> 0 | BY32: =IF(VALUE(MID(BY$5,6,2))<=$D$2,((1+$BD$3)^9-1)*BO32,0) -> 0 | BZ32: =SUM(BP32:BY32) -> 2990.4494 | CA32: =SUM(BZ32,BF32:BO32) -> 33688.82 | CE32: =IF($CC32="Annual",1,IF($CC32="Monthly F",12,IF($CC32="Monthly V",CD32*12,IF($CC32="One-Time",1,CD32*12)))) -> 0 | CF32: {=IFERROR(_xlfn.IFS(VALUE(MID(CF$5,6,1))>$D$2,0,$CC32="Annual",1,CE32=12,12,$CC32="Monthly V",CE32*(1+$D$3),$CC32="Monthly F",12,$CC32="One-Time",0),CE32*(1+$D$3))} -> 0 | CG32: {=IFERROR(_xlfn.IFS(VALUE(MID(CG$5,6,1))>$D$2,0,$CC32="Annual",1,CF32=12,12,$CC32="Monthly V",CF32*(1+$D$3),$CC32="Monthly F",12,$CC32="One-Time",0),CF32*(1+$D$3))} -> 0 | CH32: {=IFERROR(_xlfn.IFS(VALUE(MID(CH$5,6,1))>$D$2,0,$CC32="Annual",1,CG32=12,12,$CC32="Monthly V",CG32*(1+$D$3),$CC32="Monthly F",12,$CC32="One-Time",0),CG32*(1+$D$3))} -> 0 | CI32: {=IFERROR(_xlfn.IFS(VALUE(MID(CI$5,6,1))>$D$2,0,$CC32="Annual",1,CH32=12,12,$CC32="Monthly V",CH32*(1+$D$3),$CC32="Monthly F",12,$CC32="One-Time",0),CH32*(1+$D$3))} -> 0 | CJ32: {=IFERROR(_xlfn.IFS(VALUE(MID(CJ$5,6,1))>$D$2,0,$CC32="Annual",1,CI32=12,12,$CC32="Monthly V",CI32*(1+$D$3),$CC32="Monthly F",12,$CC32="One-Time",0),CI32*(1+$D$3))} -> 0 | CK32: {=IFERROR(_xlfn.IFS(VALUE(MID(CK$5,6,1))>$D$2,0,$CC32="Annual",1,CJ32=12,12,$CC32="Monthly V",CJ32*(1+$D$3),$CC32="Monthly F",12,$CC32="One-Time",0),CJ32*(1+$D$3))} -> 0 | CL32: {=IFERROR(_xlfn.IFS(VALUE(MID(CL$5,6,1))>$D$2,0,$CC32="Annual",1,CK32=12,12,$CC32="Monthly V",CK32*(1+$D$3),$CC32="Monthly F",12,$CC32="One-Time",0),CK32*(1+$D$3))} -> 0 | CM32: {=IFERROR(_xlfn.IFS(VALUE(MID(CM$5,6,1))>$D$2,0,$CC32="Annual",1,CL32=12,12,$CC32="Monthly V",CL32*(1+$D$3),$CC32="Monthly F",12,$CC32="One-Time",0),CL32*(1+$D$3))} -> 0 | CN32: {=IFERROR(_xlfn.IFS(VALUE(MID(CN$5,6,2))>$D$2,0,$CC32="Annual",1,CM32=12,12,$CC32="Monthly V",CM32*(1+$D$3),$CC32="Monthly F",12,$CC32="One-Time",0),CM32*(1+$D$3))} -> 0 | CQ32: =CR32/12 -> 0 | CR32: =IFERROR(CE32*$CP32,0) -> 0 | CS32: =IFERROR(CF32*$CP32,0) -> 0 | CT32: =IFERROR(CG32*$CP32,0) -> 0 | CU32: =IFERROR(CH32*$CP32,0) -> 0 | CV32: =IFERROR(CI32*$CP32,0) -> 0 | CW32: =IFERROR(CJ32*$CP32,0) -> 0 | CX32: =IFERROR(CK32*$CP32,0) -> 0 | CY32: =IFERROR(CL32*$CP32,0) -> 0 | ... DA32: =IFERROR(CN32*$CP32,0) -> 0 | DC32: =IF(VALUE(MID(DC$5,6,1))<=$D$2,((1+$CP$3)^1-1)*CS32,0) -> 0 | DD32: =IF(VALUE(MID(DD$5,6,1))<=$D$2,((1+$CP$3)^2-1)*CT32,0) -> 0 | DE32: =IF(VALUE(MID(DE$5,6,1))<=$D$2,((1+$CP$3)^3-1)*CU32,0) -> 0 | DF32: =IF(VALUE(MID(DF$5,6,1))<=$D$2,((1+$CP$3)^4-1)*CV32,0) -> 0 | DG32: =IF(VALUE(MID(DG$5,6,1))<=$D$2,((1+$CP$3)^5-1)*CW32,0) -> 0 | DH32: =IF(VALUE(MID(DH$5,6,1))<=$D$2,((1+$CP$3)^6-1)*CX32,0) -> 0 | DI32: =IF(VALUE(MID(DI$5,6,1))<=$D$2,((1+$CP$3)^7-1)*CY32,0) -> 0 | DJ32: =IF(VALUE(MID(DJ$5,6,1))<=$D$2,((1+$CP$3)^8-1)*CZ32,0) -> 0 | DK32: =IF(VALUE(MID(DK$5,6,2))<=$D$2,((1+$CP$3)^9-1)*DA32,0) -> 0 | DL32: =SUM(DB32:DK32) -> 0 | DM32: =SUM(DL32,CR32:DA32) -> 0
