Workbook
Name ChgType: SF_Output!$L1048566:$L988
Name Delivery: SF_Output!$O1048566:$O988
Name Description: SF_Output!$M1048566:$M988
Name Disc: SF_Output!$T1048566:$T988
Name extid: SF_Output!$J1048566:$J988
Name Freq: SF_Output!$Q1048566:$Q988
Name List: SF_Output!$S1048566:$S988
Name OType: SF_Output!$N1048566:$N988

Sheet SF_Output
A1: Agreement: Last Activity Date | B1: Account | C1: Based On Assets | D1: Agreement: Owner Name | E1: Sales Support Owner | F1: PAP Val | G1: Optional PAP Val | H1: Agreement: Agreement Name | I1: Master Category Text | J1: Product External ID | K1: Product Family | L1: Charge Type | M1: Line Description | N1: Order Type | O1: Delivery | P1: Optional Product | Q1: Pricing Frequency | R1: Quantity | S1: Deal Sheet Base price for Override | T1: Deal Sheet Discount Amount | U1: JH Company ID | V1: Base Price (Override) | W1: Base Price | X1: PLI APTS ID | Y1: Based on Number of Open Accounts | Z1: Calculated List PAP | AA1: Sort1 | AB1: Sort2
A2: 45895 | B2: Echelon Bank (InOrg) | C2: 0 | D2: Christopher Darty | E2: Diane Jackson | F2: 0 | G2: 0 | H2: Clearwater, FL - Echelon Bank (InOrg) - New Core SilverLake OL PAP | I2: IS and Risk | J2: CTBK00039 | K2: Centurion | L2: Professional Service | M2: Centurion Remote Data Entry | N2: New | O2: Hosted by JHA | P2: 0 | Q2: Yearly | R2: 1 | S2: 1880 | T2: 0 | U2: 116592 | W2: 1880 | X2: a4p0R0000002bLDQAY | Y2: 5000 | Z2: =ROUND(IF((F2+G2)=0,0,S2/Y2),4) -> 0 | AA2: {=IFERROR(INDEX(H_Tables!E:E,MATCH(INDIRECT("I"&ROW()),H_Tables!F:F,0)),"")} -> 7 | AB2: {=IFERROR(INDEX(H_Tables!H:H,MATCH(INDIRECT("k"&ROW()),H_Tables!I:I,0)),"")} -> 1 | AC2: =_xlfn.TEXTJOIN(",",TRUE,M2:P2) -> Centurion Remote Data Entry,New,Hosted by JHA,0 | AD2: 1
A3: 45895 | B3: Echelon Bank (InOrg) | C3: 0 | D3: Christopher Darty | E3: Diane Jackson | F3: 0 | G3: 0 | H3: Clearwater, FL - Echelon Bank (InOrg) - New Core SilverLake OL PAP | I3: IS and Risk | J3: CTCT00101 | K3: Centurion | L3: Professional Service | M3: Centurion Connectivity for Jack Henry Hosted Services | N3: New | O3: Hosted by JHA | P3: 0 | Q3: Monthly | R3: 1 | S3: 200 | T3: 0 | U3: 116592 | W3: 200 | X3: a4pWB0000000DmrYAE | Y3: 5000 | Z3: =ROUND(IF((F3+G3)=0,0,S3/Y3),4) -> 0 | AA3: {=IFERROR(INDEX(H_Tables!E:E,MATCH(INDIRECT("I"&ROW()),H_Tables!F:F,0)),"")} -> 7 | AB3: {=IFERROR(INDEX(H_Tables!H:H,MATCH(INDIRECT("k"&ROW()),H_Tables!I:I,0)),"")} -> 1 | AC3: =_xlfn.TEXTJOIN(",",TRUE,M3:P3) -> Centurion Connectivity for Jack Henry Hosted Services,New,Hosted by JHA,0 | AD3: 2
A4: 45895 | B4: Echelon Bank (InOrg) | C4: 0 | D4: Christopher Darty | E4: Diane Jackson | F4: 0 | G4: 0 | H4: Clearwater, FL - Echelon Bank (InOrg) - New Core SilverLake OL PAP | I4: Payments | J4: IPNA00416 | K4: iPay | L4: Processing Service | M4: iPay Business BillPay Banno | N4: New | O4: Hosted by JHA | P4: 0 | Q4: Monthly | R4: 1 | S4: 400 | T4: 0 | U4: 116592 | W4: 400 | X4: a4g2a000000HBB5AAO | Y4: 5000 | Z4: =ROUND(IF((F4+G4)=0,0,S4/Y4),4) -> 0 | AA4: {=IFERROR(INDEX(H_Tables!E:E,MATCH(INDIRECT("I"&ROW()),H_Tables!F:F,0)),"")} -> 6 | AB4: {=IFERROR(INDEX(H_Tables!H:H,MATCH(INDIRECT("k"&ROW()),H_Tables!I:I,0)),"")} -> 3 | AC4: =_xlfn.TEXTJOIN(",",TRUE,M4:P4) -> iPay Business BillPay Banno,New,Hosted by JHA,0 | AD4: 3
A5: 45895 | B5: Echelon Bank (InOrg) | C5: 0 | D5: Christopher Darty | E5: Diane Jackson | F5: 0 | G5: 0 | H5: Clearwater, FL - Echelon Bank (InOrg) - New Core SilverLake OL PAP | I5: Payments | J5: IPNA00416 | K5: iPay | L5: Professional Service | M5: iPay Business BillPay Banno | N5: New | O5: Hosted by JHA | P5: 0 | Q5: One Time | R5: 1 | S5: 2500 | T5: -2500 | U5: 116592 | W5: 2500 | X5: a4g2a000000HA36AAG | Y5: 5000 | Z5: =ROUND(IF((F5+G5)=0,0,S5/Y5),4) -> 0 | AA5: {=IFERROR(INDEX(H_Tables!E:E,MATCH(INDIRECT("I"&ROW()),H_Tables!F:F,0)),"")} -> 6 | AB5: {=IFERROR(INDEX(H_Tables!H:H,MATCH(INDIRECT("k"&ROW()),H_Tables!I:I,0)),"")} -> 3 | AC5: =_xlfn.TEXTJOIN(",",TRUE,M5:P5) -> iPay Business BillPay Banno,New,Hosted by JHA,0 | AD5: 4
A6: 45895 | B6: Echelon Bank (InOrg) | C6: 0 | D6: Christopher Darty | E6: Diane Jackson | F6: 0 | G6: 0 | H6: Clearwater, FL - Echelon Bank (InOrg) - New Core SilverLake OL PAP | I6: Payments | J6: IPNA00415 | K6: iPay | L6: Processing Service | M6: iPay Electronic Bill Payment Annual Compliance Package Banno | N6: New | O6: Hosted by JHA | P6: 0 | Q6: Yearly | R6: 1 | S6: 630 | T6: 0 | U6: 116592 | V6: 630 | W6: 595 | X6: a4g2a000000HAPvAAO | Y6: 5000 | Z6: =ROUND(IF((F6+G6)=0,0,S6/Y6),4) -> 0 | AA6: {=IFERROR(INDEX(H_Tables!E:E,MATCH(INDIRECT("I"&ROW()),H_Tables!F:F,0)),"")} -> 6 | AB6: {=IFERROR(INDEX(H_Tables!H:H,MATCH(INDIRECT("k"&ROW()),H_Tables!I:I,0)),"")} -> 3 | AC6: =_xlfn.TEXTJOIN(",",TRUE,M6:P6) -> iPay Electronic Bill Payment Annual Compliance Package Banno,New,Hosted by JHA,0 | AD6: 5
A7: 45895 | B7: Echelon Bank (InOrg) | C7: 0 | D7: Christopher Darty | E7: Diane Jackson | F7: 0 | G7: 0 | H7: Clearwater, FL - Echelon Bank (InOrg) - New Core SilverLake OL PAP | I7: Payments | J7: IPNA00414 | K7: iPay | L7: Processing Service | M7: iPay eBill Detail | N7: New | O7: Hosted by JHA | P7: 0 | Q7: Monthly | R7: 1 | S7: 0 | T7: 0 | U7: 116592 | W7: 0 | X7: a4p3J0000013SezQAE | Y7: 5000 | Z7: =ROUND(IF((F7+G7)=0,0,S7/Y7),4) -> 0 | AA7: {=IFERROR(INDEX(H_Tables!E:E,MATCH(INDIRECT("I"&ROW()),H_Tables!F:F,0)),"")} -> 6 | AB7: {=IFERROR(INDEX(H_Tables!H:H,MATCH(INDIRECT("k"&ROW()),H_Tables!I:I,0)),"")} -> 3 | AC7: =_xlfn.TEXTJOIN(",",TRUE,M7:P7) -> iPay eBill Detail,New,Hosted by JHA,0 | AD7: 6
A8: 45895 | B8: Echelon Bank (InOrg) | C8: 0 | D8: Christopher Darty | E8: Diane Jackson | F8: 0 | G8: 0 | H8: Clearwater, FL - Echelon Bank (InOrg) - New Core SilverLake OL PAP | I8: Payments | J8: PYRZ00102 | K8: iPay | L8: Professional Service | M8: Payrailz/iPay Integration | N8: New | O8: Hosted by JHA | P8: 0 | Q8: One Time | R8: 1 | S8: 5000 | T8: -5000 | U8: 116592 | W8: 5000 | X8: a4p04000000DiGjAAK | Y8: 5000 | Z8: =ROUND(IF((F8+G8)=0,0,S8/Y8),4) -> 0 | AA8: {=IFERROR(INDEX(H_Tables!E:E,MATCH(INDIRECT("I"&ROW()),H_Tables!F:F,0)),"")} -> 6 | AB8: {=IFERROR(INDEX(H_Tables!H:H,MATCH(INDIRECT("k"&ROW()),H_Tables!I:I,0)),"")} -> 3 | AC8: =_xlfn.TEXTJOIN(",",TRUE,M8:P8) -> Payrailz/iPay Integration,New,Hosted by JHA,0 | AD8: 7
A9: 45895 | B9: Echelon Bank (InOrg) | C9: 0 | D9: Christopher Darty | E9: Diane Jackson | F9: 1.2181 | G9: 0 | H9: Clearwater, FL - Echelon Bank (InOrg) - New Core SilverLake OL PAP | I9: Core | J9: SLAKE00199 | K9: SilverLake | L9: Processing Service | M9: SilverLake System Bundle | N9: New | O9: Hosted by JHA | P9: 0 | Q9: Monthly | R9: 5000 | S9: 6921.15 | T9: -830.54 | U9: 116592 | W9: 1.38423 | X9: a4pWB0000008VmcYAE | Y9: 5000 | Z9: =ROUND(IF((F9+G9)=0,0,S9/Y9),4) -> 1.3842 | AA9: {=IFERROR(INDEX(H_Tables!E:E,MATCH(INDIRECT("I"&ROW()),H_Tables!F:F,0)),"")} -> 1 | AB9: {=IFERROR(INDEX(H_Tables!H:H,MATCH(INDIRECT("k"&ROW()),H_Tables!I:I,0)),"")} -> 1 | AC9: =_xlfn.TEXTJOIN(",",TRUE,M9:P9) -> SilverLake System Bundle,New,Hosted by JHA,0 | AD9: 8
A10: 45895 | B10: Echelon Bank (InOrg) | C10: 0 | D10: Christopher Darty | E10: Diane Jackson | F10: 0 | G10: 0 | H10: Clearwater, FL - Echelon Bank (InOrg) - New Core SilverLake OL PAP | I10: Core | J10: SLAKE00199 | K10: SilverLake | L10: Professional Service | M10: SilverLake System Bundle | N10: New | O10: Hosted by JHA | P10: 0 | Q10: One Time | R10: 1 | S10: 78700 | T10: -78700 | U10: 116592 | W10: 78700 | X10: a4pWB0000008VmbYAE | Y10: 5000 | Z10: =ROUND(IF((F10+G10)=0,0,S10/Y10),4) -> 0 | AA10: {=IFERROR(INDEX(H_Tables!E:E,MATCH(INDIRECT("I"&ROW()),H_Tables!F:F,0)),"")} -> 1 | AB10: {=IFERROR(INDEX(H_Tables!H:H,MATCH(INDIRECT("k"&ROW()),H_Tables!I:I,0)),"")} -> 1 | AC10: =_xlfn.TEXTJOIN(",",TRUE,M10:P10) -> SilverLake System Bundle,New,Hosted by JHA,0 | AD10: 9
A11: 45895 | B11: Echelon Bank (InOrg) | C11: 0 | D11: Christopher Darty | E11: Diane Jackson | F11: 0 | G11: 0 | H11: Clearwater, FL - Echelon Bank (InOrg) - New Core SilverLake OL PAP | I11: Core | J11: SLTC00100 | K11: SilverLake | L11: Professional Service | M11: SilverLake Technical Conversion/Installation | N11: New | O11: Hosted by JHA | P11: 0 | Q11: One Time | R11: 1 | S11: 125405 | T11: -125405 | U11: 116592 | W11: 125405 | X11: a4pWB000000CHWXYA4 | Y11: 5000 | Z11: =ROUND(IF((F11+G11)=0,0,S11/Y11),4) -> 0 | AA11: {=IFERROR(INDEX(H_Tables!E:E,MATCH(INDIRECT("I"&ROW()),H_Tables!F:F,0)),"")} -> 1 | AB11: {=IFERROR(INDEX(H_Tables!H:H,MATCH(INDIRECT("k"&ROW()),H_Tables!I:I,0)),"")} -> 1 | AC11: =_xlfn.TEXTJOIN(",",TRUE,M11:P11) -> SilverLake Technical Conversion/Installation,New,Hosted by JHA,0 | AD11: 10
A12: 45895 | B12: Echelon Bank (InOrg) | C12: 0 | D12: Christopher Darty | E12: Diane Jackson | F12: 0 | G12: 0 | H12: Clearwater, FL - Echelon Bank (InOrg) - New Core SilverLake OL PAP | I12: Training | J12: OLTF000117 | K12: SilverLake | L12: Professional Service | M12: Core Implementation Training | N12: New | O12: Hosted by JHA | P12: 0 | Q12: One Time | R12: 1 | S12: 30000 | T12: 0 | U12: 116592 | W12: 30000 | X12: a4p18000000GqnfAAC | Y12: 5000 | Z12: =ROUND(IF((F12+G12)=0,0,S12/Y12),4) -> 0 | AA12: {=IFERROR(INDEX(H_Tables!E:E,MATCH(INDIRECT("I"&ROW()),H_Tables!F:F,0)),"")} -> 9 | AB12: {=IFERROR(INDEX(H_Tables!H:H,MATCH(INDIRECT("k"&ROW()),H_Tables!I:I,0)),"")} -> 1 | AC12: =_xlfn.TEXTJOIN(",",TRUE,M12:P12) -> Core Implementation Training,New,Hosted by JHA,0 | AD12: 11
A13: 45895 | B13: Echelon Bank (InOrg) | C13: 0 | D13: Christopher Darty | E13: Diane Jackson | F13: 0 | G13: 0 | H13: Clearwater, FL - Echelon Bank (InOrg) - New Core SilverLake OL PAP | I13: Core | J13: CCORE00109 | K13: SilverLake | L13: Processing Service | M13: Closed Accounts (PAP) | N13: New | O13: Hosted by JHA | P13: 0 | Q13: Monthly | R13: 1 | S13: 0.25 | T13: 0 | U13: 116592 | W13: 0.25 | X13: a4p7h000000QZkzAAG | Y13: 5000 | Z13: =ROUND(IF((F13+G13)=0,0,S13/Y13),4) -> 0 | AA13: {=IFERROR(INDEX(H_Tables!E:E,MATCH(INDIRECT("I"&ROW()),H_Tables!F:F,0)),"")} -> 1 | AB13: {=IFERROR(INDEX(H_Tables!H:H,MATCH(INDIRECT("k"&ROW()),H_Tables!I:I,0)),"")} -> 1 | AC13: =_xlfn.TEXTJOIN(",",TRUE,M13:P13) -> Closed Accounts (PAP),New,Hosted by JHA,0 | AD13: 12
A14: 45895 | B14: Echelon Bank (InOrg) | C14: 0 | D14: Christopher Darty | E14: Diane Jackson | F14: 0 | G14: 0 | H14: Clearwater, FL - Echelon Bank (InOrg) - New Core SilverLake OL PAP | I14: Training | J14: OLTF000102 | K14: SilverLake | L14: Professional Service | M14: User and Device Administration Training | N14: New | O14: Hosted by JHA | P14: 0 | Q14: One Time | R14: 1 | S14: 5000 | T14: 0 | U14: 116592 | W14: 5000 | X14: a4p18000000GqlhAAC | Y14: 5000 | Z14: =ROUND(IF((F14+G14)=0,0,S14/Y14),4) -> 0 | AA14: {=IFERROR(INDEX(H_Tables!E:E,MATCH(INDIRECT("I"&ROW()),H_Tables!F:F,0)),"")} -> 9 | AB14: {=IFERROR(INDEX(H_Tables!H:H,MATCH(INDIRECT("k"&ROW()),H_Tables!I:I,0)),"")} -> 1 | AC14: =_xlfn.TEXTJOIN(",",TRUE,M14:P14) -> User and Device Administration Training,New,Hosted by JHA,0 | AD14: 13
A15: 45895 | B15: Echelon Bank (InOrg) | C15: 0 | D15: Christopher Darty | E15: Diane Jackson | F15: 0 | G15: 0 | H15: Clearwater, FL - Echelon Bank (InOrg) - New Core SilverLake OL PAP | I15: Core | J15: SLAKE000102 | K15: SilverLake | L15: Processing Service | M15: SilverLake Static Training Bank | N15: New | O15: Hosted by JHA | P15: 1 | Q15: Monthly | R15: 1 | S15: 530 | T15: -132.5 | U15: 116592 | W15: 530 | X15: a4p18000000GqkKAAS | Y15: 5000 | Z15: =ROUND(IF((F15+G15)=0,0,S15/Y15),4) -> 0 | AA15: {=IFERROR(INDEX(H_Tables!E:E,MATCH(INDIRECT("I"&ROW()),H_Tables!F:F,0)),"")} -> 1 | AB15: {=IFERROR(INDEX(H_Tables!H:H,MATCH(INDIRECT("k"&ROW()),H_Tables!I:I,0)),"")} -> 1 | AC15: =_xlfn.TEXTJOIN(",",TRUE,M15:P15) -> SilverLake Static Training Bank,New,Hosted by JHA,1 | AD15: 14
A16: 45895 | B16: Echelon Bank (InOrg) | C16: 0 | D16: Christopher Darty | E16: Diane Jackson | F16: 0 | G16: 0 | H16: Clearwater, FL - Echelon Bank (InOrg) - New Core SilverLake OL PAP | I16: Core | J16: SLAKE000102 | K16: SilverLake | L16: Professional Service | M16: SilverLake Static Training Bank | N16: New | O16: Hosted by JHA | P16: 1 | Q16: One Time | R16: 1 | S16: 6000 | T16: -6000 | U16: 116592 | W16: 6000 | X16: a4p18000000GqkPAAS | Y16: 5000 | Z16: =ROUND(IF((F16+G16)=0,0,S16/Y16),4) -> 0 | AA16: {=IFERROR(INDEX(H_Tables!E:E,MATCH(INDIRECT("I"&ROW()),H_Tables!F:F,0)),"")} -> 1 | AB16: {=IFERROR(INDEX(H_Tables!H:H,MATCH(INDIRECT("k"&ROW()),H_Tables!I:I,0)),"")} -> 1 | AC16: =_xlfn.TEXTJOIN(",",TRUE,M16:P16) -> SilverLake Static Training Bank,New,Hosted by JHA,1 | AD16: 15
A17: 45895 | B17: Echelon Bank (InOrg) | C17: 0 | D17: Christopher Darty | E17: Diane Jackson | F17: 0 | G17: 0 | H17: Clearwater, FL - Echelon Bank (InOrg) - New Core SilverLake OL PAP | I17: Retail | J17: STCT1001 | K17: SilverLake | L17: Processing Service | M17: Platform Static Training Bank | N17: New | O17: Hosted by JHA | P17: 1 | Q17: Monthly | R17: 1 | S17: 110 | T17: -27.5 | U17: 116592 | W17: 110 | X17: a4p0R000000AhCgQAK | Y17: 5000 | Z17: =ROUND(IF((F17+G17)=0,0,S17/Y17),4) -> 0 | AA17: {=IFERROR(INDEX(H_Tables!E:E,MATCH(INDIRECT("I"&ROW()),H_Tables!F:F,0)),"")} -> 2 | AB17: {=IFERROR(INDEX(H_Tables!H:H,MATCH(INDIRECT("k"&ROW()),H_Tables!I:I,0)),"")} -> 1 | AC17: =_xlfn.TEXTJOIN(",",TRUE,M17:P17) -> Platform Static Training Bank,New,Hosted by JHA,1 | AD17: 16
A18: 45895 | B18: Echelon Bank (InOrg) | C18: 0 | D18: Christopher Darty | E18: Diane Jackson | F18: 0 | G18: 0 | H18: Clearwater, FL - Echelon Bank (InOrg) - New Core SilverLake OL PAP | I18: Retail | J18: STCT1001 | K18: SilverLake | L18: Professional Service | M18: Platform Static Training Bank | N18: New | O18: Hosted by JHA | P18: 1 | Q18: One Time | R18: 1 | S18: 2500 | T18: -2500 | U18: 116592 | W18: 2500 | X18: a4p0R000000AhCbQAK | Y18: 5000 | Z18: =ROUND(IF((F18+G18)=0,0,S18/Y18),4) -> 0 | AA18: {=IFERROR(INDEX(H_Tables!E:E,MATCH(INDIRECT("I"&ROW()),H_Tables!F:F,0)),"")} -> 2 | AB18: {=IFERROR(INDEX(H_Tables!H:H,MATCH(INDIRECT("k"&ROW()),H_Tables!I:I,0)),"")} -> 1 | AC18: =_xlfn.TEXTJOIN(",",TRUE,M18:P18) -> Platform Static Training Bank,New,Hosted by JHA,1 | AD18: 17
... A163: 45895 | B163: Echelon Bank (InOrg) | C163: 0 | D163: Christopher Darty | E163: Diane Jackson | F163: 0 | G163: 0 | H163: Clearwater, FL - Echelon Bank (InOrg) - New Core SilverLake OL PAP | I163: Payments | J163: CPS000101 | K163: Card Processing Solutions (CPS) | L163: Professional Service | M163: JHA Debit Processing | N163: New | O163: Hosted by 3rd Party | P163: 0 | Q163: One Time | R163: 1 | S163: 12500 | T163: -12500 | U163: 116592 | W163: 12500 | X163: a4p18000000GxnuAAC | Y163: 5000 | Z163: =ROUND(IF((F163+G163)=0,0,S163/Y163),4) -> 0 | AA163: {=IFERROR(INDEX(H_Tables!E:E,MATCH(INDIRECT("I"&ROW()),H_Tables!F:F,0)),"")} -> 6 | AB163: {=IFERROR(INDEX(H_Tables!H:H,MATCH(INDIRECT("k"&ROW()),H_Tables!I:I,0)),"")} -> 1 | AC163: =_xlfn.TEXTJOIN(",",TRUE,M163:P163) -> JHA Debit Processing,New,Hosted by 3rd Party,0 | AD163: 160
A164: 45895 | B164: Echelon Bank (InOrg) | C164: 0 | D164: Christopher Darty | E164: Diane Jackson | F164: 0 | G164: 0 | H164: Clearwater, FL - Echelon Bank (InOrg) - New Core SilverLake OL PAP | I164: Payments | J164: CPS000104 | K164: Card Processing Solutions (CPS) | L164: Processing Service | M164: Debit Card Authorization subject to {$}250 minimum monthly | N164: New | O164: Hosted by 3rd Party | P164: 0 | Q164: Monthly | R164: 1 | S164: 250 | T164: 0 | U164: 116592 | V164: 250 | W164: 500 | X164: a3g4a000000WCwzAAG | Y164: 5000 | Z164: =ROUND(IF((F164+G164)=0,0,S164/Y164),4) -> 0 | AA164: {=IFERROR(INDEX(H_Tables!E:E,MATCH(INDIRECT("I"&ROW()),H_Tables!F:F,0)),"")} -> 6 | AB164: {=IFERROR(INDEX(H_Tables!H:H,MATCH(INDIRECT("k"&ROW()),H_Tables!I:I,0)),"")} -> 1 | AC164: =_xlfn.TEXTJOIN(",",TRUE,M164:P164) -> Debit Card Authorization subject to {$}250 minimum monthly,New,Hosted by 3rd Party,0 | AD164: 161
A165: 45895 | B165: Echelon Bank (InOrg) | C165: 0 | D165: Christopher Darty | E165: Diane Jackson | F165: 0 | G165: 0 | H165: Clearwater, FL - Echelon Bank (InOrg) - New Core SilverLake OL PAP | I165: Payments | J165: CPS000105 | K165: Card Processing Solutions (CPS) | L165: Processing Service | M165: Debit Card Settlement | N165: New | O165: Hosted by 3rd Party | P165: 0 | Q165: Monthly | R165: 0 | S165: 0 | T165: 0 | U165: 116592 | W165: 0.02 | X165: a4p18000000GxoiAAC | Y165: 5000 | Z165: =ROUND(IF((F165+G165)=0,0,S165/Y165),4) -> 0 | AA165: {=IFERROR(INDEX(H_Tables!E:E,MATCH(INDIRECT("I"&ROW()),H_Tables!F:F,0)),"")} -> 6 | AB165: {=IFERROR(INDEX(H_Tables!H:H,MATCH(INDIRECT("k"&ROW()),H_Tables!I:I,0)),"")} -> 1 | AC165: =_xlfn.TEXTJOIN(",",TRUE,M165:P165) -> Debit Card Settlement,New,Hosted by 3rd Party,0 | AD165: 162
A166: 45895 | B166: Echelon Bank (InOrg) | C166: 0 | D166: Christopher Darty | E166: Diane Jackson | F166: 0 | G166: 0 | H166: Clearwater, FL - Echelon Bank (InOrg) - New Core SilverLake OL PAP | I166: Payments | J166: CPS000106 | K166: Card Processing Solutions (CPS) | L166: Processing Service | M166: ATM/Debit Cards | N166: New | O166: Hosted by 3rd Party | P166: 0 | Q166: Monthly | R166: 0 | S166: 0 | T166: 0 | U166: 116592 | W166: 0.025 | X166: a4p18000000GxosAAC | Y166: 5000 | Z166: =ROUND(IF((F166+G166)=0,0,S166/Y166),4) -> 0 | AA166: {=IFERROR(INDEX(H_Tables!E:E,MATCH(INDIRECT("I"&ROW()),H_Tables!F:F,0)),"")} -> 6 | AB166: {=IFERROR(INDEX(H_Tables!H:H,MATCH(INDIRECT("k"&ROW()),H_Tables!I:I,0)),"")} -> 1 | AC166: =_xlfn.TEXTJOIN(",",TRUE,M166:P166) -> ATM/Debit Cards,New,Hosted by 3rd Party,0 | AD166: 163
A167: 45895 | B167: Echelon Bank (InOrg) | C167: 0 | D167: Christopher Darty | E167: Diane Jackson | F167: 0 | G167: 0 | H167: Clearwater, FL - Echelon Bank (InOrg) - New Core SilverLake OL PAP | I167: Payments | J167: CPS000200 | K167: Card Processing Solutions (CPS) | L167: Processing Service | M167: Administrative Fee | N167: New | O167: Hosted by 3rd Party | P167: 0 | Q167: Monthly | R167: 0 | S167: 0 | T167: 0 | U167: 116592 | W167: 0.015 | X167: a4p0R0000002bOqQAI | Y167: 5000 | Z167: =ROUND(IF((F167+G167)=0,0,S167/Y167),4) -> 0 | AA167: {=IFERROR(INDEX(H_Tables!E:E,MATCH(INDIRECT("I"&ROW()),H_Tables!F:F,0)),"")} -> 6 | AB167: {=IFERROR(INDEX(H_Tables!H:H,MATCH(INDIRECT("k"&ROW()),H_Tables!I:I,0)),"")} -> 1 | AC167: =_xlfn.TEXTJOIN(",",TRUE,M167:P167) -> Administrative Fee,New,Hosted by 3rd Party,0 | AD167: 164
A168: 45895 | B168: Echelon Bank (InOrg) | C168: 0 | D168: Christopher Darty | E168: Diane Jackson | F168: 0 | G168: 0 | H168: Clearwater, FL - Echelon Bank (InOrg) - New Core SilverLake OL PAP | I168: Payments | J168: CPS000109 | K168: Card Processing Solutions (CPS) | L168: Processing Service | M168: EMV Chip Card Authorization | N168: New | O168: Hosted by 3rd Party | P168: 0 | Q168: Monthly | R168: 0 | S168: 0 | T168: 0 | U168: 116592 | W168: 0.0075 | X168: a4p18000000GxpCAAS | Y168: 5000 | Z168: =ROUND(IF((F168+G168)=0,0,S168/Y168),4) -> 0 | AA168: {=IFERROR(INDEX(H_Tables!E:E,MATCH(INDIRECT("I"&ROW()),H_Tables!F:F,0)),"")} -> 6 | AB168: {=IFERROR(INDEX(H_Tables!H:H,MATCH(INDIRECT("k"&ROW()),H_Tables!I:I,0)),"")} -> 1 | AC168: =_xlfn.TEXTJOIN(",",TRUE,M168:P168) -> EMV Chip Card Authorization,New,Hosted by 3rd Party,0 | AD168: 165
A169: 45895 | B169: Echelon Bank (InOrg) | C169: 0 | D169: Christopher Darty | E169: Diane Jackson | F169: 0 | G169: 0 | H169: Clearwater, FL - Echelon Bank (InOrg) - New Core SilverLake OL PAP | I169: Payments | J169: CPS000930 | K169: Card Processing Solutions (CPS) | L169: Processing Service | M169: Authorization Track One Name Edit | N169: New | O169: Hosted by 3rd Party | P169: 0 | Q169: Monthly | R169: 0 | S169: 0 | T169: 0 | U169: 116592 | W169: 0.004 | X169: a4p2F0000006TvBQAU | Y169: 5000 | Z169: =ROUND(IF((F169+G169)=0,0,S169/Y169),4) -> 0 | AA169: {=IFERROR(INDEX(H_Tables!E:E,MATCH(INDIRECT("I"&ROW()),H_Tables!F:F,0)),"")} -> 6 | AB169: {=IFERROR(INDEX(H_Tables!H:H,MATCH(INDIRECT("k"&ROW()),H_Tables!I:I,0)),"")} -> 1 | AC169: =_xlfn.TEXTJOIN(",",TRUE,M169:P169) -> Authorization Track One Name Edit,New,Hosted by 3rd Party,0 | AD169: 166
A170: 45895 | B170: Echelon Bank (InOrg) | C170: 0 | D170: Christopher Darty | E170: Diane Jackson | F170: 0 | G170: 0 | H170: Clearwater, FL - Echelon Bank (InOrg) - New Core SilverLake OL PAP | I170: Payments | J170: CPS000190 | K170: Card Processing Solutions (CPS) | L170: Processing Service | M170: JHA ATM/POS Processing | N170: New | O170: Hosted by 3rd Party | P170: 0 | Q170: Monthly | R170: 1 | S170: 500 | T170: 0 | U170: 116592 | W170: 500 | X170: a4p0R0000002bP0QAI | Y170: 5000 | Z170: =ROUND(IF((F170+G170)=0,0,S170/Y170),4) -> 0 | AA170: {=IFERROR(INDEX(H_Tables!E:E,MATCH(INDIRECT("I"&ROW()),H_Tables!F:F,0)),"")} -> 6 | AB170: {=IFERROR(INDEX(H_Tables!H:H,MATCH(INDIRECT("k"&ROW()),H_Tables!I:I,0)),"")} -> 1 | AC170: =_xlfn.TEXTJOIN(",",TRUE,M170:P170) -> JHA ATM/POS Processing,New,Hosted by 3rd Party,0 | AD170: 167
A171: 45895 | B171: Echelon Bank (InOrg) | C171: 0 | D171: Christopher Darty | E171: Diane Jackson | F171: 0 | G171: 0 | H171: Clearwater, FL - Echelon Bank (InOrg) - New Core SilverLake OL PAP | I171: Payments | J171: CPS000190 | K171: Card Processing Solutions (CPS) | L171: Professional Service | M171: JHA ATM/POS Processing | N171: New | O171: Hosted by 3rd Party | P171: 0 | Q171: One Time | R171: 1 | S171: 3000 | T171: -3000 | U171: 116592 | W171: 3000 | X171: a4p0R0000002bOvQAI | Y171: 5000 | Z171: =ROUND(IF((F171+G171)=0,0,S171/Y171),4) -> 0 | AA171: {=IFERROR(INDEX(H_Tables!E:E,MATCH(INDIRECT("I"&ROW()),H_Tables!F:F,0)),"")} -> 6 | AB171: {=IFERROR(INDEX(H_Tables!H:H,MATCH(INDIRECT("k"&ROW()),H_Tables!I:I,0)),"")} -> 1 | AC171: =_xlfn.TEXTJOIN(",",TRUE,M171:P171) -> JHA ATM/POS Processing,New,Hosted by 3rd Party,0 | AD171: 168
A172: 45895 | B172: Echelon Bank (InOrg) | C172: 0 | D172: Christopher Darty | E172: Diane Jackson | F172: 0 | G172: 0 | H172: Clearwater, FL - Echelon Bank (InOrg) - New Core SilverLake OL PAP | I172: Payments | J172: CPS000103 | K172: Card Processing Solutions (CPS) | L172: Processing Service | M172: ATM/POS Transactions subject to {$}250 minimum monthly | N172: New | O172: Hosted by 3rd Party | P172: 0 | Q172: Monthly | R172: 1 | S172: 250 | T172: 0 | U172: 116592 | V172: 250 | W172: 500 | X172: a3g4a000000TCwzAAG | Y172: 5000 | Z172: =ROUND(IF((F172+G172)=0,0,S172/Y172),4) -> 0 | AA172: {=IFERROR(INDEX(H_Tables!E:E,MATCH(INDIRECT("I"&ROW()),H_Tables!F:F,0)),"")} -> 6 | AB172: {=IFERROR(INDEX(H_Tables!H:H,MATCH(INDIRECT("k"&ROW()),H_Tables!I:I,0)),"")} -> 1 | AC172: =_xlfn.TEXTJOIN(",",TRUE,M172:P172) -> ATM/POS Transactions subject to {$}250 minimum monthly,New,Hosted by 3rd Party,0 | AD172: 169
A173: 45895 | B173: Echelon Bank (InOrg) | C173: 0 | D173: Christopher Darty | E173: Diane Jackson | F173: 0 | G173: 0 | H173: Clearwater, FL - Echelon Bank (InOrg) - New Core SilverLake OL PAP | I173: Payments | J173: CPS000110 | K173: Card Processing Solutions (CPS) | L173: Processing Service | M173: ATM Transactions (on-us at-us) | N173: New | O173: Hosted by 3rd Party | P173: 0 | Q173: Monthly | R173: 0 | S173: 0 | T173: 0 | U173: 116592 | W173: 0.02 | X173: a4p18000000GxpWAAS | Y173: 5000 | Z173: =ROUND(IF((F173+G173)=0,0,S173/Y173),4) -> 0 | AA173: {=IFERROR(INDEX(H_Tables!E:E,MATCH(INDIRECT("I"&ROW()),H_Tables!F:F,0)),"")} -> 6 | AB173: {=IFERROR(INDEX(H_Tables!H:H,MATCH(INDIRECT("k"&ROW()),H_Tables!I:I,0)),"")} -> 1 | AC173: =_xlfn.TEXTJOIN(",",TRUE,M173:P173) -> ATM Transactions (on-us at-us),New,Hosted by 3rd Party,0 | AD173: 170
A174: 45895 | B174: Echelon Bank (InOrg) | C174: 0 | D174: Christopher Darty | E174: Diane Jackson | F174: 0 | G174: 0 | H174: Clearwater, FL - Echelon Bank (InOrg) - New Core SilverLake OL PAP | I174: Payments | J174: CPS000115 | K174: Card Processing Solutions (CPS) | L174: Professional Service | M174: ATM Setup | N174: New | O174: Hosted by 3rd Party | P174: 0 | Q174: One Time | R174: 1 | S174: 145 | T174: -145 | U174: 116592 | W174: 145 | X174: a4p18000000GxqFAAS | Y174: 5000 | Z174: =ROUND(IF((F174+G174)=0,0,S174/Y174),4) -> 0 | AA174: {=IFERROR(INDEX(H_Tables!E:E,MATCH(INDIRECT("I"&ROW()),H_Tables!F:F,0)),"")} -> 6 | AB174: {=IFERROR(INDEX(H_Tables!H:H,MATCH(INDIRECT("k"&ROW()),H_Tables!I:I,0)),"")} -> 1 | AC174: =_xlfn.TEXTJOIN(",",TRUE,M174:P174) -> ATM Setup,New,Hosted by 3rd Party,0 | AD174: 171
A175: 45895 | B175: Echelon Bank (InOrg) | C175: 0 | D175: Christopher Darty | E175: Diane Jackson | F175: 0 | G175: 0 | H175: Clearwater, FL - Echelon Bank (InOrg) - New Core SilverLake OL PAP | I175: Payments | J175: CPS000114 | K175: Card Processing Solutions (CPS) | L175: Processing Service | M175: ATM Driving VPN | N175: New | O175: Hosted by 3rd Party | P175: 0 | Q175: Monthly | R175: 1 | S175: 100 | T175: 0 | U175: 116592 | W175: 100 | X175: a4p18000000Gxq5AAC | Y175: 5000 | Z175: =ROUND(IF((F175+G175)=0,0,S175/Y175),4) -> 0 | AA175: {=IFERROR(INDEX(H_Tables!E:E,MATCH(INDIRECT("I"&ROW()),H_Tables!F:F,0)),"")} -> 6 | AB175: {=IFERROR(INDEX(H_Tables!H:H,MATCH(INDIRECT("k"&ROW()),H_Tables!I:I,0)),"")} -> 1 | AC175: =_xlfn.TEXTJOIN(",",TRUE,M175:P175) -> ATM Driving VPN,New,Hosted by 3rd Party,0 | AD175: 172
A176: 45895 | B176: Echelon Bank (InOrg) | C176: 0 | D176: Christopher Darty | E176: Diane Jackson | F176: 0 | G176: 0 | H176: Clearwater, FL - Echelon Bank (InOrg) - New Core SilverLake OL PAP | I176: Payments | J176: CPS000270 | K176: Card Processing Solutions (CPS) | L176: Processing Service | M176: Regional ATM/Debit Network | N176: New | O176: Hosted by 3rd Party | P176: 0 | Q176: Monthly | R176: 1 | S176: 75 | T176: 0 | U176: 116592 | W176: 75 | X176: a4p0R000000Cxg3QAC | Y176: 5000 | Z176: =ROUND(IF((F176+G176)=0,0,S176/Y176),4) -> 0 | AA176: {=IFERROR(INDEX(H_Tables!E:E,MATCH(INDIRECT("I"&ROW()),H_Tables!F:F,0)),"")} -> 6 | AB176: {=IFERROR(INDEX(H_Tables!H:H,MATCH(INDIRECT("k"&ROW()),H_Tables!I:I,0)),"")} -> 1 | AC176: =_xlfn.TEXTJOIN(",",TRUE,M176:P176) -> Regional ATM/Debit Network,New,Hosted by 3rd Party,0 | AD176: 173
A177: 45895 | B177: Echelon Bank (InOrg) | C177: 0 | D177: Christopher Darty | E177: Diane Jackson | F177: 0 | G177: 0 | H177: Clearwater, FL - Echelon Bank (InOrg) - New Core SilverLake OL PAP | I177: Payments | J177: CPS000270 | K177: Card Processing Solutions (CPS) | L177: Professional Service | M177: Regional ATM/Debit Network | N177: New | O177: Hosted by 3rd Party | P177: 0 | Q177: One Time | R177: 1 | S177: 500 | T177: -500 | U177: 116592 | W177: 500 | X177: a4p0R000000CxfyQAC | Y177: 5000 | Z177: =ROUND(IF((F177+G177)=0,0,S177/Y177),4) -> 0 | AA177: {=IFERROR(INDEX(H_Tables!E:E,MATCH(INDIRECT("I"&ROW()),H_Tables!F:F,0)),"")} -> 6 | AB177: {=IFERROR(INDEX(H_Tables!H:H,MATCH(INDIRECT("k"&ROW()),H_Tables!I:I,0)),"")} -> 1 | AC177: =_xlfn.TEXTJOIN(",",TRUE,M177:P177) -> Regional ATM/Debit Network,New,Hosted by 3rd Party,0 | AD177: 174
A178: 45895 | B178: Echelon Bank (InOrg) | C178: 0 | D178: Christopher Darty | E178: Diane Jackson | F178: 0 | G178: 0 | H178: Clearwater, FL - Echelon Bank (InOrg) - New Core SilverLake OL PAP | I178: Payments | J178: CPS000280 | K178: Card Processing Solutions (CPS) | L178: Processing Service | M178: National ATM/Debit Network | N178: New | O178: Hosted by 3rd Party | P178: 0 | Q178: Monthly | R178: 3 | S178: 225 | T178: 0 | U178: 116592 | W178: 75 | X178: a4p0R000000CxgDQAS | Y178: 5000 | Z178: =ROUND(IF((F178+G178)=0,0,S178/Y178),4) -> 0 | AA178: {=IFERROR(INDEX(H_Tables!E:E,MATCH(INDIRECT("I"&ROW()),H_Tables!F:F,0)),"")} -> 6 | AB178: {=IFERROR(INDEX(H_Tables!H:H,MATCH(INDIRECT("k"&ROW()),H_Tables!I:I,0)),"")} -> 1 | AC178: =_xlfn.TEXTJOIN(",",TRUE,M178:P178) -> National ATM/Debit Network,New,Hosted by 3rd Party,0 | AD178: 175
A179: 45895 | B179: Echelon Bank (InOrg) | C179: 0 | D179: Christopher Darty | E179: Diane Jackson | F179: 0 | G179: 0 | H179: Clearwater, FL - Echelon Bank (InOrg) - New Core SilverLake OL PAP | I179: Payments | J179: CPS000280 | K179: Card Processing Solutions (CPS) | L179: Professional Service | M179: National ATM/Debit Network | N179: New | O179: Hosted by 3rd Party | P179: 0 | Q179: One Time | R179: 3 | S179: 1500 | T179: -1500 | U179: 116592 | W179: 500 | X179: a4p0R000000Cxg8QAC | Y179: 5000 | Z179: =ROUND(IF((F179+G179)=0,0,S179/Y179),4) -> 0 | AA179: {=IFERROR(INDEX(H_Tables!E:E,MATCH(INDIRECT("I"&ROW()),H_Tables!F:F,0)),"")} -> 6 | AB179: {=IFERROR(INDEX(H_Tables!H:H,MATCH(INDIRECT("k"&ROW()),H_Tables!I:I,0)),"")} -> 1 | AC179: =_xlfn.TEXTJOIN(",",TRUE,M179:P179) -> National ATM/Debit Network,New,Hosted by 3rd Party,0 | AD179: 176
A180: 45895 | B180: Echelon Bank (InOrg) | C180: 0 | D180: Christopher Darty | E180: Diane Jackson | F180: 0 | G180: 0 | H180: Clearwater, FL - Echelon Bank (InOrg) - New Core SilverLake OL PAP | I180: Payments | J180: CPS000550 | K180: Card Processing Solutions (CPS) | L180: Processing Service | M180: VISA/MasterCard Account Update (Items Needing Review) | N180: New | O180: Hosted by 3rd Party | P180: 0 | Q180: Monthly | R180: 0 | S180: 0 | T180: 0 | U180: 116592 | W180: 0.0008 | X180: a4p0R000000AqN1QAK | Y180: 5000 | Z180: =ROUND(IF((F180+G180)=0,0,S180/Y180),4) -> 0 | AA180: {=IFERROR(INDEX(H_Tables!E:E,MATCH(INDIRECT("I"&ROW()),H_Tables!F:F,0)),"")} -> 6 | AB180: {=IFERROR(INDEX(H_Tables!H:H,MATCH(INDIRECT("k"&ROW()),H_Tables!I:I,0)),"")} -> 1 | AC180: =_xlfn.TEXTJOIN(",",TRUE,M180:P180) -> VISA/MasterCard Account Update (Items Needing Review),New,Hosted by 3rd Party,0 | AD180: 177
A181: 45895 | B181: Echelon Bank (InOrg) | C181: 0 | D181: Christopher Darty | E181: Diane Jackson | F181: 0 | G181: 0 | H181: Clearwater, FL - Echelon Bank (InOrg) - New Core SilverLake OL PAP | I181: Payments | J181: CPS000550 | K181: Card Processing Solutions (CPS) | L181: Professional Service | M181: VISA/MasterCard Account Update (Items Needing Review) | N181: New | O181: Hosted by 3rd Party | P181: 0 | Q181: One Time | R181: 0 | S181: 200 | T181: -200 | U181: 116592 | W181: 200 | X181: a4p0R000000AqMwQAK | Y181: 5000 | Z181: =ROUND(IF((F181+G181)=0,0,S181/Y181),4) -> 0 | AA181: {=IFERROR(INDEX(H_Tables!E:E,MATCH(INDIRECT("I"&ROW()),H_Tables!F:F,0)),"")} -> 6 | AB181: {=IFERROR(INDEX(H_Tables!H:H,MATCH(INDIRECT("k"&ROW()),H_Tables!I:I,0)),"")} -> 1 | AC181: =_xlfn.TEXTJOIN(",",TRUE,M181:P181) -> VISA/MasterCard Account Update (Items Needing Review),New,Hosted by 3rd Party,0 | AD181: 178
A182: 45895 | B182: Echelon Bank (InOrg) | C182: 0 | D182: Christopher Darty | E182: Diane Jackson | F182: 0 | G182: 0 | H182: Clearwater, FL - Echelon Bank (InOrg) - New Core SilverLake OL PAP | I182: Payments | J182: CPS000552 | K182: Card Processing Solutions (CPS) | L182: Processing Service | M182: VISA/MasterCard Add/Change/Delete | N182: New | O182: Hosted by 3rd Party | P182: 0 | Q182: Monthly | R182: 0 | S182: 0 | T182: 0 | U182: 116592 | W182: 0.04 | X182: 112020a2PLI000020 | Y182: 5000 | Z182: =ROUND(IF((F182+G182)=0,0,S182/Y182),4) -> 0 | AA182: {=IFERROR(INDEX(H_Tables!E:E,MATCH(INDIRECT("I"&ROW()),H_Tables!F:F,0)),"")} -> 6 | AB182: {=IFERROR(INDEX(H_Tables!H:H,MATCH(INDIRECT("k"&ROW()),H_Tables!I:I,0)),"")} -> 1 | AC182: =_xlfn.TEXTJOIN(",",TRUE,M182:P182) -> VISA/MasterCard Add/Change/Delete,New,Hosted by 3rd Party,0 | AD182: 179
A183: 45895 | B183: Echelon Bank (InOrg) | C183: 0 | D183: Christopher Darty | E183: Diane Jackson | F183: 0 | G183: 0 | H183: Clearwater, FL - Echelon Bank (InOrg) - New Core SilverLake OL PAP | I183: Payments | J183: CPS000121 | K183: Card Processing Solutions (CPS) | L183: Professional Service | M183: JHA Tokenization (Digital Wallet) JHA Debit Processing | N183: New | O183: Hosted by 3rd Party | P183: 0 | Q183: One Time | R183: 1 | S183: 4000 | T183: -4000 | U183: 116592 | W183: 4000 | X183: a4p18000000GxrSAAS | Y183: 5000 | Z183: =ROUND(IF((F183+G183)=0,0,S183/Y183),4) -> 0 | AA183: {=IFERROR(INDEX(H_Tables!E:E,MATCH(INDIRECT("I"&ROW()),H_Tables!F:F,0)),"")} -> 6 | AB183: {=IFERROR(INDEX(H_Tables!H:H,MATCH(INDIRECT("k"&ROW()),H_Tables!I:I,0)),"")} -> 1 | AC183: =_xlfn.TEXTJOIN(",",TRUE,M183:P183) -> JHA Tokenization (Digital Wallet) JHA Debit Processing,New,Hosted by 3rd Party,0 | AD183: 180
A184: 45895 | B184: Echelon Bank (InOrg) | C184: 0 | D184: Christopher Darty | E184: Diane Jackson | F184: 0 | G184: 0 | H184: Clearwater, FL - Echelon Bank (InOrg) - New Core SilverLake OL PAP | I184: Payments | J184: CPS01001 | K184: Card Processing Solutions (CPS) | L184: Professional Service | M184: JHA Tokenization (Digital Wallet) Additional Instance JHA Debit Processing | N184: New | O184: Hosted by 3rd Party | P184: 0 | Q184: One Time | R184: 1 | S184: 2000 | T184: -2000 | U184: 116592 | W184: 2000 | X184: a4p180000001AoSAAU | Y184: 5000 | Z184: =ROUND(IF((F184+G184)=0,0,S184/Y184),4) -> 0 | AA184: {=IFERROR(INDEX(H_Tables!E:E,MATCH(INDIRECT("I"&ROW()),H_Tables!F:F,0)),"")} -> 6 | AB184: {=IFERROR(INDEX(H_Tables!H:H,MATCH(INDIRECT("k"&ROW()),H_Tables!I:I,0)),"")} -> 1 | AC184: =_xlfn.TEXTJOIN(",",TRUE,M184:P184) -> JHA Tokenization (Digital Wallet) Additional Instance JHA Debit Processing,New,Hosted by 3rd Party,0 | AD184: 181
... A235: 45895 | B235: Echelon Bank (InOrg) | C235: 0 | D235: Christopher Darty | E235: Diane Jackson | F235: 0 | G235: 0 | H235: Clearwater, FL - Echelon Bank (InOrg) - New Core SilverLake OL PAP | I235: Payments | J235: CPS000149 | K235: Card Processing Solutions (CPS) | L235: Professional Service | M235: MyCardRules JHA Debit Processing | N235: New | O235: Hosted by 3rd Party | P235: 0 | Q235: One Time | R235: 0 | S235: 1500 | T235: -1500 | U235: 116592 | W235: 1500 | X235: a4p18000000GxwOAAS | Y235: 5000 | Z235: =ROUND(IF((F235+G235)=0,0,S235/Y235),4) -> 0 | AA235: {=IFERROR(INDEX(H_Tables!E:E,MATCH(INDIRECT("I"&ROW()),H_Tables!F:F,0)),"")} -> 6 | AB235: {=IFERROR(INDEX(H_Tables!H:H,MATCH(INDIRECT("k"&ROW()),H_Tables!I:I,0)),"")} -> 1 | AC235: =_xlfn.TEXTJOIN(",",TRUE,M235:P235) -> MyCardRules JHA Debit Processing,New,Hosted by 3rd Party,0 | AD235: 232
A236: 45895 | B236: Echelon Bank (InOrg) | C236: 0 | D236: Christopher Darty | E236: Diane Jackson | F236: 0 | G236: 0 | H236: Clearwater, FL - Echelon Bank (InOrg) - New Core SilverLake OL PAP | I236: Payments | J236: PYRZ00121 | K236: Payrailz | L236: Processing Service | M236: Payrailz Bundle | N236: New | O236: Hosted by JHA | P236: 0 | Q236: Monthly | R236: 1 | S236: 350 | T236: 0 | U236: 116592 | V236: 350 | W236: 500 | X236: a4p3J0000013A7FQAU | Y236: 5000 | Z236: =ROUND(IF((F236+G236)=0,0,S236/Y236),4) -> 0 | AA236: {=IFERROR(INDEX(H_Tables!E:E,MATCH(INDIRECT("I"&ROW()),H_Tables!F:F,0)),"")} -> 6 | AB236: {=IFERROR(INDEX(H_Tables!H:H,MATCH(INDIRECT("k"&ROW()),H_Tables!I:I,0)),"")} | AC236: =_xlfn.TEXTJOIN(",",TRUE,M236:P236) -> Payrailz Bundle,New,Hosted by JHA,0 | AD236: 233
A237: 45895 | B237: Echelon Bank (InOrg) | C237: 0 | D237: Christopher Darty | E237: Diane Jackson | F237: 0 | G237: 0 | H237: Clearwater, FL - Echelon Bank (InOrg) - New Core SilverLake OL PAP | I237: Payments | J237: PYRZ00121 | K237: Payrailz | L237: Professional Service | M237: Payrailz Bundle | N237: New | O237: Hosted by JHA | P237: 0 | Q237: One Time | R237: 1 | S237: 5000 | T237: -5000 | U237: 116592 | W237: 5000 | X237: a4p3J0000013A7AQAU | Y237: 5000 | Z237: =ROUND(IF((F237+G237)=0,0,S237/Y237),4) -> 0 | AA237: {=IFERROR(INDEX(H_Tables!E:E,MATCH(INDIRECT("I"&ROW()),H_Tables!F:F,0)),"")} -> 6 | AB237: {=IFERROR(INDEX(H_Tables!H:H,MATCH(INDIRECT("k"&ROW()),H_Tables!I:I,0)),"")} | AC237: =_xlfn.TEXTJOIN(",",TRUE,M237:P237) -> Payrailz Bundle,New,Hosted by JHA,0 | AD237: 234
A238: 45895 | B238: Echelon Bank (InOrg) | C238: 0 | D238: Christopher Darty | E238: Diane Jackson | F238: 0 | G238: 0 | H238: Clearwater, FL - Echelon Bank (InOrg) - New Core SilverLake OL PAP | I238: Payments | J238: PYRZ00122 | K238: Payrailz | L238: Processing Service | M238: Payrailz Bundle Transactions | N238: New | O238: Hosted by JHA | P238: 0 | Q238: Monthly | R238: 500 | S238: 310 | T238: 0 | U238: 116592 | V238: 0.62 | W238: 0.6 | X238: a4p3J0000013A75QAE | Y238: 5000 | Z238: =ROUND(IF((F238+G238)=0,0,S238/Y238),4) -> 0 | AA238: {=IFERROR(INDEX(H_Tables!E:E,MATCH(INDIRECT("I"&ROW()),H_Tables!F:F,0)),"")} -> 6 | AB238: {=IFERROR(INDEX(H_Tables!H:H,MATCH(INDIRECT("k"&ROW()),H_Tables!I:I,0)),"")} | AC238: =_xlfn.TEXTJOIN(",",TRUE,M238:P238) -> Payrailz Bundle Transactions,New,Hosted by JHA,0 | AD238: 235
A239: 45895 | B239: Echelon Bank (InOrg) | C239: 0 | D239: Christopher Darty | E239: Diane Jackson | F239: 0 | G239: 0 | H239: Clearwater, FL - Echelon Bank (InOrg) - New Core SilverLake OL PAP | I239: Payments | J239: PYRZ00102 | K239: Payrailz | L239: Professional Service | M239: Payrailz/iPay Integration | N239: New | O239: Hosted by JHA | P239: 0 | Q239: One Time | R239: 1 | S239: 5000 | T239: -5000 | U239: 116592 | W239: 5000 | X239: a4p04000000DiGoAAK | Y239: 5000 | Z239: =ROUND(IF((F239+G239)=0,0,S239/Y239),4) -> 0 | AA239: {=IFERROR(INDEX(H_Tables!E:E,MATCH(INDIRECT("I"&ROW()),H_Tables!F:F,0)),"")} -> 6 | AB239: {=IFERROR(INDEX(H_Tables!H:H,MATCH(INDIRECT("k"&ROW()),H_Tables!I:I,0)),"")} | AC239: =_xlfn.TEXTJOIN(",",TRUE,M239:P239) -> Payrailz/iPay Integration,New,Hosted by JHA,0 | AD239: 236
A240: 45895 | B240: Echelon Bank (InOrg) | C240: 0 | D240: Christopher Darty | E240: Diane Jackson | F240: 0 | G240: 0 | H240: Clearwater, FL - Echelon Bank (InOrg) - New Core SilverLake OL PAP | I240: Payments | J240: PYRZ00107 | K240: Payrailz | L240: Processing Service | M240: Payrailz Fraud Monitor | N240: New | O240: Hosted by JHA | P240: 0 | Q240: Monthly | R240: 1 | S240: 750 | T240: -750 | U240: 116592 | W240: 750 | X240: a4p04000000DiCcAAK | Y240: 5000 | Z240: =ROUND(IF((F240+G240)=0,0,S240/Y240),4) -> 0 | AA240: {=IFERROR(INDEX(H_Tables!E:E,MATCH(INDIRECT("I"&ROW()),H_Tables!F:F,0)),"")} -> 6 | AB240: {=IFERROR(INDEX(H_Tables!H:H,MATCH(INDIRECT("k"&ROW()),H_Tables!I:I,0)),"")} | AC240: =_xlfn.TEXTJOIN(",",TRUE,M240:P240) -> Payrailz Fraud Monitor,New,Hosted by JHA,0 | AD240: 237
A241: 45895 | B241: Echelon Bank (InOrg) | C241: 0 | D241: Christopher Darty | E241: Diane Jackson | F241: 0 | G241: 0 | H241: Clearwater, FL - Echelon Bank (InOrg) - New Core SilverLake OL PAP | I241: Payments | J241: PYRZ00107 | K241: Payrailz | L241: Professional Service | M241: Payrailz Fraud Monitor | N241: New | O241: Hosted by JHA | P241: 0 | Q241: One Time | R241: 1 | S241: 3000 | T241: -3000 | U241: 116592 | W241: 3000 | X241: a4p04000000DiCXAA0 | Y241: 5000 | Z241: =ROUND(IF((F241+G241)=0,0,S241/Y241),4) -> 0 | AA241: {=IFERROR(INDEX(H_Tables!E:E,MATCH(INDIRECT("I"&ROW()),H_Tables!F:F,0)),"")} -> 6 | AB241: {=IFERROR(INDEX(H_Tables!H:H,MATCH(INDIRECT("k"&ROW()),H_Tables!I:I,0)),"")} | AC241: =_xlfn.TEXTJOIN(",",TRUE,M241:P241) -> Payrailz Fraud Monitor,New,Hosted by JHA,0 | AD241: 238
A242: 45895 | B242: Echelon Bank (InOrg) | C242: 0 | D242: Christopher Darty | E242: Diane Jackson | F242: 0 | G242: 0 | H242: Clearwater, FL - Echelon Bank (InOrg) - New Core SilverLake OL PAP | I242: Payments | J242: PRRE00612 | K242: ProfitStars RemitPlus | L242: Processing Service | M242: RemitPlus Express - Financial Institution | N242: New | O242: Hosted by JHA | P242: 1 | Q242: Monthly | R242: 1 | S242: 100 | T242: 0 | U242: 116592 | W242: 100 | X242: a4pWB0000002CWZYA2 | Y242: 5000 | Z242: =ROUND(IF((F242+G242)=0,0,S242/Y242),4) -> 0 | AA242: {=IFERROR(INDEX(H_Tables!E:E,MATCH(INDIRECT("I"&ROW()),H_Tables!F:F,0)),"")} -> 6 | AB242: {=IFERROR(INDEX(H_Tables!H:H,MATCH(INDIRECT("k"&ROW()),H_Tables!I:I,0)),"")} -> 4 | AC242: =_xlfn.TEXTJOIN(",",TRUE,M242:P242) -> RemitPlus Express - Financial Institution,New,Hosted by JHA,1 | AD242: 239
A243: 45895 | B243: Echelon Bank (InOrg) | C243: 0 | D243: Christopher Darty | E243: Diane Jackson | F243: 0 | G243: 0 | H243: Clearwater, FL - Echelon Bank (InOrg) - New Core SilverLake OL PAP | I243: Payments | J243: PRRE00612 | K243: ProfitStars RemitPlus | L243: Professional Service | M243: RemitPlus Express - Financial Institution | N243: New | O243: Hosted by JHA | P243: 1 | Q243: One Time | R243: 1 | S243: 3000 | T243: 0 | U243: 116592 | W243: 3000 | X243: a4pWB0000002CWYYA2 | Y243: 5000 | Z243: =ROUND(IF((F243+G243)=0,0,S243/Y243),4) -> 0 | AA243: {=IFERROR(INDEX(H_Tables!E:E,MATCH(INDIRECT("I"&ROW()),H_Tables!F:F,0)),"")} -> 6 | AB243: {=IFERROR(INDEX(H_Tables!H:H,MATCH(INDIRECT("k"&ROW()),H_Tables!I:I,0)),"")} -> 4 | AC243: =_xlfn.TEXTJOIN(",",TRUE,M243:P243) -> RemitPlus Express - Financial Institution,New,Hosted by JHA,1 | AD243: 240
Z244: =ROUND(IF((F244+G244)=0,0,S244/Y244),4) -> 0 | AA244: {=IFERROR(INDEX(H_Tables!E:E,MATCH(INDIRECT("I"&ROW()),H_Tables!F:F,0)),"")} | AB244: {=IFERROR(INDEX(H_Tables!H:H,MATCH(INDIRECT("k"&ROW()),H_Tables!I:I,0)),"")} | AC244: =_xlfn.TEXTJOIN(",",TRUE,M244:P244) | AD244: 241
Z245: =ROUND(IF((F245+G245)=0,0,S245/Y245),4) -> 0 | AA245: {=IFERROR(INDEX(H_Tables!E:E,MATCH(INDIRECT("I"&ROW()),H_Tables!F:F,0)),"")} | AB245: {=IFERROR(INDEX(H_Tables!H:H,MATCH(INDIRECT("k"&ROW()),H_Tables!I:I,0)),"")} | AC245: =_xlfn.TEXTJOIN(",",TRUE,M245:P245) | AD245: 242
Z246: =ROUND(IF((F246+G246)=0,0,S246/Y246),4) -> 0 | AA246: {=IFERROR(INDEX(H_Tables!E:E,MATCH(INDIRECT("I"&ROW()),H_Tables!F:F,0)),"")} | AB246: {=IFERROR(INDEX(H_Tables!H:H,MATCH(INDIRECT("k"&ROW()),H_Tables!I:I,0)),"")} | AC246: =_xlfn.TEXTJOIN(",",TRUE,M246:P246) | AD246: 243
Z247: =ROUND(IF((F247+G247)=0,0,S247/Y247),4) -> 0 | AA247: {=IFERROR(INDEX(H_Tables!E:E,MATCH(INDIRECT("I"&ROW()),H_Tables!F:F,0)),"")} | AB247: {=IFERROR(INDEX(H_Tables!H:H,MATCH(INDIRECT("k"&ROW()),H_Tables!I:I,0)),"")} | AC247: =_xlfn.TEXTJOIN(",",TRUE,M247:P247) | AD247: 244
Z248: =ROUND(IF((F248+G248)=0,0,S248/Y248),4) -> 0 | AA248: {=IFERROR(INDEX(H_Tables!E:E,MATCH(INDIRECT("I"&ROW()),H_Tables!F:F,0)),"")} | AB248: {=IFERROR(INDEX(H_Tables!H:H,MATCH(INDIRECT("k"&ROW()),H_Tables!I:I,0)),"")} | AC248: =_xlfn.TEXTJOIN(",",TRUE,M248:P248) | AD248: 245
Z249: =ROUND(IF((F249+G249)=0,0,S249/Y249),4) -> 0 | AA249: {=IFERROR(INDEX(H_Tables!E:E,MATCH(INDIRECT("I"&ROW()),H_Tables!F:F,0)),"")} | AB249: {=IFERROR(INDEX(H_Tables!H:H,MATCH(INDIRECT("k"&ROW()),H_Tables!I:I,0)),"")} | AC249: =_xlfn.TEXTJOIN(",",TRUE,M249:P249) | AD249: 246
Z250: =ROUND(IF((F250+G250)=0,0,S250/Y250),4) -> 0 | AA250: {=IFERROR(INDEX(H_Tables!E:E,MATCH(INDIRECT("I"&ROW()),H_Tables!F:F,0)),"")} | AB250: {=IFERROR(INDEX(H_Tables!H:H,MATCH(INDIRECT("k"&ROW()),H_Tables!I:I,0)),"")} | AC250: =_xlfn.TEXTJOIN(",",TRUE,M250:P250) | AD250: 247
Z251: =ROUND(IF((F251+G251)=0,0,S251/Y251),4) -> 0 | AA251: {=IFERROR(INDEX(H_Tables!E:E,MATCH(INDIRECT("I"&ROW()),H_Tables!F:F,0)),"")} | AB251: {=IFERROR(INDEX(H_Tables!H:H,MATCH(INDIRECT("k"&ROW()),H_Tables!I:I,0)),"")} | AC251: =_xlfn.TEXTJOIN(",",TRUE,M251:P251) | AD251: 248
Z252: =ROUND(IF((F252+G252)=0,0,S252/Y252),4) -> 0 | AA252: {=IFERROR(INDEX(H_Tables!E:E,MATCH(INDIRECT("I"&ROW()),H_Tables!F:F,0)),"")} | AB252: {=IFERROR(INDEX(H_Tables!H:H,MATCH(INDIRECT("k"&ROW()),H_Tables!I:I,0)),"")} | AC252: =_xlfn.TEXTJOIN(",",TRUE,M252:P252) | AD252: 249
Z253: =ROUND(IF((F253+G253)=0,0,S253/Y253),4) -> 0 | AA253: {=IFERROR(INDEX(H_Tables!E:E,MATCH(INDIRECT("I"&ROW()),H_Tables!F:F,0)),"")} | AB253: {=IFERROR(INDEX(H_Tables!H:H,MATCH(INDIRECT("k"&ROW()),H_Tables!I:I,0)),"")} | AC253: =_xlfn.TEXTJOIN(",",TRUE,M253:P253) | AD253: 250
Z254: =ROUND(IF((F254+G254)=0,0,S254/Y254),4) -> 0 | AA254: {=IFERROR(INDEX(H_Tables!E:E,MATCH(INDIRECT("I"&ROW()),H_Tables!F:F,0)),"")} | AB254: {=IFERROR(INDEX(H_Tables!H:H,MATCH(INDIRECT("k"&ROW()),H_Tables!I:I,0)),"")} | AC254: =_xlfn.TEXTJOIN(",",TRUE,M254:P254) | AD254: 251
Z255: =ROUND(IF((F255+G255)=0,0,S255/Y255),4) -> 0 | AA255: {=IFERROR(INDEX(H_Tables!E:E,MATCH(INDIRECT("I"&ROW()),H_Tables!F:F,0)),"")} | AB255: {=IFERROR(INDEX(H_Tables!H:H,MATCH(INDIRECT("k"&ROW()),H_Tables!I:I,0)),"")} | AC255: =_xlfn.TEXTJOIN(",",TRUE,M255:P255) | AD255: 252
... Z1002: =ROUND(IF((F1002+G1002)=0,0,S1002/Y1002),4) -> 0 | AA1002: {=IFERROR(INDEX(H_Tables!E:E,MATCH(INDIRECT("I"&ROW()),H_Tables!F:F,0)),"")} | AB1002: {=IFERROR(INDEX(H_Tables!H:H,MATCH(INDIRECT("k"&ROW()),H_Tables!I:I,0)),"")} | AC1002: =_xlfn.TEXTJOIN(",",TRUE,M1002:P1002) | AD1002: 999
Z1003: =ROUND(IF((F1003+G1003)=0,0,S1003/Y1003),4) -> 0 | AA1003: {=IFERROR(INDEX(H_Tables!E:E,MATCH(INDIRECT("I"&ROW()),H_Tables!F:F,0)),"")} | AB1003: {=IFERROR(INDEX(H_Tables!H:H,MATCH(INDIRECT("k"&ROW()),H_Tables!I:I,0)),"")} | AC1003: =_xlfn.TEXTJOIN(",",TRUE,M1003:P1003)
Z1004: =ROUND(IF((F1004+G1004)=0,0,S1004/Y1004),4) -> 0 | AA1004: {=IFERROR(INDEX(H_Tables!E:E,MATCH(INDIRECT("I"&ROW()),H_Tables!F:F,0)),"")} | AB1004: {=IFERROR(INDEX(H_Tables!H:H,MATCH(INDIRECT("k"&ROW()),H_Tables!I:I,0)),"")} | AC1004: =_xlfn.TEXTJOIN(",",TRUE,M1004:P1004)

Sheet Balancing
B2: Product | D2: New License | E2: New Install | F2: New Annual | G2: New Monthly | I2: Old License | J2: Old Install | K2: Old Annual | L2: Old Monthly | N2: License Delta | O2: Install Delta | P2: Annual Delta | Q2: Monthly Delta | S2: BAF License | T2: BAF Install | U2: BAF Annual | V2: BAF Monthly
B3: SilverLake System Bundle,New,Hosted by JHA,0 | D3: 0 | E3: 0 | F3: 0 | G3: 6090.5 | I3: 0 | J3: 0 | K3: 0 | L3: 6090.5 | N3: 0 | O3: 0 | P3: 0 | Q3: 0
B4: SilverLake Technical Conversion/Installation,New,Hosted by JHA,0 | D4: 0 | E4: 0 | F4: 0 | G4: 0 | I4: 0 | J4: 0 | K4: 0 | L4: 0 | N4: 0 | O4: 0 | P4: 0 | Q4: 0
B5: Closed Accounts (PAP),New,Hosted by JHA,0 | D5: 0 | E5: 0 | F5: 0 | G5: 0.25 | I5: 0 | J5: 0 | K5: 0 | L5: 0.25 | N5: 0 | O5: 0 | P5: 0 | Q5: 0
B6: SilverLake Static Training Bank,New,Hosted by JHA,1 | D6: 0 | E6: 0 | F6: 0 | G6: 397.5 | I6: 0 | J6: 0 | K6: 0 | L6: 397.5 | N6: 0 | O6: 0 | P6: 0 | Q6: 0
B7: SilverLake Teller Static Training Bank,New,Hosted by JHA,1 | D7: 0 | E7: 0 | F7: 0 | G7: 165 | I7: 0 | J7: 0 | K7: 0 | L7: 165 | N7: 0 | O7: 0 | P7: 0 | Q7: 0
B8: JH Technology Architecture Services,New,Hosted by JHA,0 | D8: 0 | E8: 0 | F8: 0 | G8: 0 | I8: 0 | J8: 0 | K8: 0 | L8: 0 | N8: 0 | O8: 0 | P8: 0 | Q8: 0
B9: JHMenu Express,New,On Premise License,0 | D9: 9000 | E9: 0 | F9: 0 | G9: 0 | I9: 9000 | J9: 0 | K9: 0 | L9: 0 | N9: 0 | O9: 0 | P9: 0 | Q9: 0
B10: Daily File Transfer Integration IntraFi,New,Hosted by JHA,0 | D10: 0 | E10: 0 | F10: 0 | G10: 225 | I10: 0 | J10: 0 | K10: 0 | L10: 225 | N10: 0 | O10: 0 | P10: 0 | Q10: 0
B11: Hosted Xperience,New,Hosted by JHA,0 | D11: 0 | E11: 0 | F11: 0 | G11: 112.5 | I11: 0 | J11: 0 | K11: 0 | L11: 112.5 | N11: 0 | O11: 0 | P11: 0 | Q11: 0
B12: Platform Static Training Bank,New,Hosted by JHA,1 | D12: 0 | E12: 0 | F12: 0 | G12: 165 | I12: 0 | J12: 0 | K12: 0 | L12: 165 | N12: 0 | O12: 0 | P12: 0 | Q12: 0
B13: OnBoard Deposits,New,Hosted by JHA,0 | D13: 0 | E13: 0 | F13: 0 | G13: 851.5 | I13: 0 | J13: 0 | K13: 0 | L13: 851.5 | N13: 0 | O13: 0 | P13: 0 | Q13: 0
B14: OnBoard Lending,New,Hosted by JHA,1 | D14: 0 | E14: 0 | F14: 0 | G14: 1136.5 | I14: 0 | J14: 0 | K14: 0 | L14: 1136.5 | N14: 0 | O14: 0 | P14: 0 | Q14: 0
... B166: Know-It-All Now eLearning,New,Hosted by JHA,0 | D166: 0 | E166: 0 | F166: 3500 | G166: 0 | I166: 0 | J166: 0 | K166: 3500 | L166: 0 | N166: 0 | O166: 0 | P166: 0 | Q166: 0

Sheet DeleteThisPageThenSave
B2: OriginalFileName | C2: Updated_With_all_products__Deal_Sheet_Clearwater__FL_-_Echelon_Bank__InOrg__-_New_Core_SilverLake_OL_PAP_08_27_25

Sheet Proposal_1
H1: {=MID(CELL("filename",A1),FIND("]",CELL("filename",A1))+1,255)} -> Proposal_1
J2: License List | K2: Discount | L2: License Net | N2: Install List | O2: Discount | P2: Install Net | R2: Maintenance List | S2: Discount | T2: Maintenance Net | V2: New Monthly List | W2: Discount | X2: New Monthly Net | Z2: Current Monthly List | AA2: Discount | AB2: Current Monthly Net
B3: Date: | C3: 45896 | I3: Included Software | J3: =SUMIFS(J$14:J$350,$F$14:$F$350,"Included")+SUMIFS(J$14:J$350,$F$14:$F$350,"Add")-J6 -> 16545 | K3: =L3-J3 -> 0 | L3: =SUMIFS(L$14:L$350,$F$14:$F$350,"Included")+SUMIFS(L$14:L$350,$F$14:$F$350,"Add")-L6 -> 16545 | N3: =SUMIFS(N$14:N$350,$F$14:$F$350,"Included")+SUMIFS(N$14:N$350,$F$14:$F$350,"Add") -> 840215 | O3: =P3-N3 -> -589322.5 | P3: =SUMIFS(P$14:P$350,$F$14:$F$350,"Included")+SUMIFS(P$14:P$350,$F$14:$F$350,"Add") -> 250892.5 | R3: =SUMIFS(R$14:R$350,$F$14:$F$350,"Included")+SUMIFS(R$14:R$350,$F$14:$F$350,"Add") -> 34899 | S3: =T3-R3 -> 0 | T3: =SUMIFS(T$14:T$350,$F$14:$F$350,"Included")+SUMIFS(T$14:T$350,$F$14:$F$350,"Add") -> 34899 | V3: =SUMIFS(V$14:V$350,$F$14:$F$350,"Included")+SUMIFS(V$14:V$350,$F$14:$F$350,"Add") -> 44605.4 | W3: =X3-V3 -> -5529.9 | X3: =SUMIFS(X$14:X$350,$F$14:$F$350,"Included")+SUMIFS(X$14:X$350,$F$14:$F$350,"Add") -> 39075.5 | Z3: =SUMIFS(Z$14:Z$350,$F$14:$F$350,"Included")+SUMIFS(Z$14:Z$350,$F$14:$F$350,"Add") -> 0 | AA3: =AB3-Z3 -> 0 | AB3: =SUMIFS(AB$14:AB$350,$F$14:$F$350,"Included")+SUMIFS(AB$14:AB$350,$F$14:$F$350,"Add") -> 0
B4: Prepared for: | C4: Echelon Bank (InOrg) | I4: Optional Software | J4: =SUMIFS(J$14:J$350,$F$14:$F$350,"Optional")-J7 -> 0 | K4: =L4-J4 -> 0 | L4: =SUMIFS(L$14:L$350,$F$14:$F$350,"Optional")-L7 -> 0 | N4: =SUMIFS(N$14:N$350,$F$14:$F$350,"Optional") -> 279595 | O4: =P4-N4 -> -190745 | P4: =SUMIFS(P$14:P$350,$F$14:$F$350,"Optional") -> 88850 | R4: =SUMIFS(R$14:R$350,$F$14:$F$350,"Optional") -> 14095.7 | S4: =T4-R4 -> 0 | T4: =SUMIFS(T$14:T$350,$F$14:$F$350,"Optional") -> 14095.7 | V4: =SUMIFS(V$14:V$350,$F$14:$F$350,"Optional") -> 11380 | W4: =X4-V4 -> -1155.5 | X4: =SUMIFS(X$14:X$350,$F$14:$F$350,"Optional") -> 10224.5 | Z4: =SUMIFS(Z$14:Z$350,$F$14:$F$350,"Optional") -> 0 | AA4: =AB4-Z4 -> 0 | AB4: =SUMIFS(AB$14:AB$350,$F$14:$F$350,"Optional") -> 0
C5: Clearwater, FL - Echelon Bank (InOrg) - New Core SilverLake OL PAP | I5: Replaced Software | J5: =SUMIFS(J$14:J$350,$F$14:$F$350,"Replaced") -> 0 | K5: =L5-J5 -> 0 | L5: =SUMIFS(L$14:L$350,$F$14:$F$350,"Replaced") -> 0 | N5: =SUMIFS(N$14:N$350,$F$14:$F$350,"Replaced") -> 0 | O5: =P5-N5 -> 0 | P5: =SUMIFS(P$14:P$350,$F$14:$F$350,"Replaced") -> 0 | R5: =SUMIFS(R$14:R$350,$F$14:$F$350,"Replaced") -> 0 | S5: =T5-R5 -> 0 | T5: =SUMIFS(T$14:T$350,$F$14:$F$350,"Replaced") -> 0 | V5: =SUMIFS(V$14:V$350,$F$14:$F$350,"Replaced") -> 0 | W5: =X5-V5 -> 0 | X5: =SUMIFS(X$14:X$350,$F$14:$F$350,"Replaced") -> 0 | Z5: =SUMIFS(Z$14:Z$350,$F$14:$F$350,"Replaced") -> 0 | AA5: =AB5-Z5 -> 0 | AB5: =SUMIFS(AB$14:AB$350,$F$14:$F$350,"Replaced") -> 0
I6: Included Hardware | J6: =SUMIFS($J$14:$J$350,$C$14:$C$350,"",$F$14:$F$350,"Included") -> 0 | K6: =L6-J6 -> 0 | L6: =SUMIFS($L$14:$L$350,$C$14:$C$350,"",$F$14:$F$350,"Included") -> 0
B7: JHA Company ID | C7: 116592 | I7: Optional Hardware | J7: =SUMIFS($J$14:$J$350,$C$14:$C$350,"",$F$14:$F$350,"Optional") -> 0 | K7: =L7-J7 -> 0 | L7: =SUMIFS($L$14:$L$350,$C$14:$C$350,"",$F$14:$F$350,"Optional") -> 0 | V7: =IF(SUM(SF_Output!F:F)>0,"PAP Discount (%)","") -> PAP Discount (%) | W7: 0
B8: Asset Size: | C8: 0
B9: AE: | C9: Christopher Darty | J9: Global Discount | K9: 0 | N9: Global Discount | O9: 0 | R9: Global Discount | S9: 0 | V9: =IF(SUM(SF_Output!F:F)>0,"","Global Discount") | W9: 0
B10: PA: | C10: Diane Jackson
B11: Term in Months | C11: TBD | K11: License | O11: Install | S11: Maintenance | W11: New Monthly | AA11: Current Monthly
C12: 5000
B13: Product Description | C13: Order Type | D13: Delivery | E13: Optional from sf | F13: Category | G13: Product Family | H13: Quantity | I13: Avg Unit $ | J13: =J2 -> License List | K13: Discount | L13: =L2 -> License Net | N13: =N2 -> Install List | O13: Discount | P13: =P2 -> Install Net | R13: =R2 -> Maintenance List | S13: Discount | T13: =T2 -> Maintenance Net | V13: =V2 -> New Monthly List | W13: Discount | X13: =X2 -> New Monthly Net | Z13: Current Monthly List | AA13: Discount | AB13: Current Monthly Net | AD13: Difference | AF13: Exclusion | AH13: Freeform Comments to PA | AI13: AutoGenerated Comments to PA | AJ13: PA Sort | AK13: PAP
B14: SilverLake System Bundle | C14: New | D14: Hosted by JHA | E14: 0 | F14: =IF(B14="","",IF(E14*1=0,"Included","Optional")) -> Included | G14: =IF(B14="","",INDEX(SF_Output!$K$1:$K$400,MATCH(B14,SF_Output!$M$1:$M$400,0))) -> SilverLake | H14: {=_xlfn.IFS(B14="","",(SUMIFS(SF_Output!$F$1:$F$400,SF_Output!$AC$1:$AC$400,_xlfn.TEXTJOIN(",",TRUE,B14:E14))+SUMIFS(SF_Output!$G$1:$G$400,SF_Output!$AC$1:$AC$400,_xlfn.TEXTJOIN(",",TRUE,B14:E14)))<>0,SF_Output!$Y$2,INDEX(SF_Output!$F$1:$F$400,MATCH(_xlfn.TEXTJOIN(",",TRUE,B14:E14),SF_Output!$AC$1:$AC$400,0))=0,INDEX(SF_Output!$R$1:$R$400,MATCH(_xlfn.TEXTJOIN(",",TRUE,B14:E14),SF_Output!$AC$1:$AC$400,0)))} -> 5000 | I14: =IFERROR(IF(AND(H14>1,H14<>""),ROUND(SUMIFS(SF_Output!$S$1:$S$400,SF_Output!$AC$1:$AC$400,_xlfn.TEXTJOIN(",",TRUE,B14:E14),SF_Output!$Q$1:$Q$400,"monthly")*(1-W14)/H14,4),""),"") -> 1.2181 | J14: =IF(B14="","",SUMIFS(SF_Output!$S$1:$S$400,SF_Output!$AC$1:$AC$400,_xlfn.TEXTJOIN(",",TRUE,B14:E14),SF_Output!$Q$1:$Q$400,"One Time",SF_Output!$L$1:$L$400,"license fee")+SUMIFS(SF_Output!$S$1:$S$400,SF_Output!$AC$1:$AC$400,_xlfn.TEXTJOIN(",",TRUE,B14:E14),SF_Output!$Q$1:$Q$400,"One Time",SF_Output!$L$1:$L$400,"software license")+SUMIFS(SF_Output!$S$1:$S$400,SF_Output!$AC$1:$AC$400,_xlfn.TEXTJOIN(",",TRUE,B14:E14),SF_Output!$Q$1:$Q$400,"One Time",SF_Output!$L$1:$L$400,"hardware")) -> 0 | K14: =IF(OR(B14=0,B14="",G14="hardware",J14=0),"",IF(AF14<>"exclusion",MAX(K$9,-((SUMIFS(SF_Output!$T$1:$T$400,SF_Output!$AC$1:$AC$400,_xlfn.TEXTJOIN(",",TRUE,$B14:$E14),SF_Output!$Q$1:$Q$400,"One Time",SF_Output!$L$1:$L$400,"license fee")+SUMIFS(SF_Output!$T$1:$T$400,SF_Output!$AC$1:$AC$400,_xlfn.TEXTJOIN(",",TRUE,$B14:$E14),SF_Output!$Q$1:$Q$400,"One Time",SF_Output!$L$1:$L$400,"software license"))/J14)),-((SUMIFS(SF_Output!$T$1:$T$400,SF_Output!$AC$1:$AC$400,_xlfn.TEXTJOIN(",",TRUE,$B14:$E14),SF_Output!$Q$1:$Q$400,"One Time",SF_Output!$L$1:$L$400,"license fee")+SUMIFS(SF_Output!$T$1:$T$400,SF_Output!$AC$1:$AC$400,_xlfn.TEXTJOIN(",",TRUE,$B14:$E14),SF_Output!$Q$1:$Q$400,"One Time",SF_Output!$L$1:$L$400,"software license"))/J14))) | L14: =IF(K14="",J14,J14*(1-K14)) -> 0 | N14: =IF(B14="","",SUMIFS(SF_Output!$S$1:$S$400,SF_Output!$AC$1:$AC$400,_xlfn.TEXTJOIN(",",TRUE,B14:E14),SF_Output!$Q$1:$Q$400,"One Time",SF_Output!$L$1:$L$400,"professional service")) -> 78700 | O14: =IF(OR(B14=0,B14="",N14=0),"",IF(AF14<>"exclusion",MAX(O$9,-(SUMIFS(SF_Output!$T$1:$T$400,SF_Output!$AC$1:$AC$400,_xlfn.TEXTJOIN(",",TRUE,$B14:$E14),SF_Output!$Q$1:$Q$400,"One Time",SF_Output!$L$1:$L$400,"professional service"))/N14),-((SUMIFS(SF_Output!$T$1:$T$400,SF_Output!$AC$1:$AC$400,_xlfn.TEXTJOIN(",",TRUE,$B14:$E14),SF_Output!$Q$1:$Q$400,"One Time",SF_Output!$L$1:$L$400,"professional service")/N14)))) -> 1 | P14: =IF(O14="",N14,N14*(1-O14)) -> 0 | R14: =IF(B14="","",SUMIFS(SF_Output!$S$1:$S$400,SF_Output!$AC$1:$AC$400,_xlfn.TEXTJOIN(",",TRUE,B14:E14),SF_Output!$Q$1:$Q$400,"yearly")+SUMIFS(SF_Output!$S$1:$S$400,SF_Output!$AC$1:$AC$400,_xlfn.TEXTJOIN(",",TRUE,B14:E14),SF_Output!$Q$1:$Q$400,"quarterly")*4) -> 0 | S14: =IF(OR(B14=0,B14="",G14="hardware",R14=0),"",IF(AF14<>"exclusion",MAX(S$9,-(SUMIFS(SF_Output!$T$1:$T$400,SF_Output!$AC$1:$AC$400,_xlfn.TEXTJOIN(",",TRUE,$B14:$E14),SF_Output!$Q$1:$Q$400,"yearly"))/R14),-((SUMIFS(SF_Output!$T$1:$T$400,SF_Output!$AC$1:$AC$400,_xlfn.TEXTJOIN(",",TRUE,$B14:$E14),SF_Output!$Q$1:$Q$400,"yearly")/R14)))) | T14: =IF(S14="",R14,R14*(1-S14)) -> 0 | V14: {=_xlfn.IFS(B14="","",AND(B14<>"",H14=SF_Output!$Y$2,SUMIFS(SF_Output!$T$1:$T$400,SF_Output!$AC$1:$AC$400,_xlfn.TEXTJOIN(",",TRUE,B14:E14),SF_Output!$Q$1:$Q$400,"monthly")=0),(SUMIFS(SF_Output!$F$1:$F$400,SF_Output!$AC$1:$AC$400,_xlfn.TEXTJOIN(",",TRUE,B14:E14),SF_Output!$Q$1:$Q$400,"monthly")+SUMIFS(SF_Output!$G$1:$G$400,SF_Output!$AC$1:$AC$400,_xlfn.TEXTJOIN(",",TRUE,B14:E14),SF_Output!$Q$1:$Q$400,"monthly"))*H14,AND(B14<>"",H14=SF_Output!$Y$2,SUMIFS(SF_Output!$T$1:$T$400,SF_Output!$AC$1:$AC$400,_xlfn.TEXTJOIN(",",TRUE,B14:E14),SF_Output!$Q$1:$Q$400,"monthly")<>0),SUMIFS(SF_Output!$S$1:$S$400,SF_Output!$AC$1:$AC$400,_xlfn.TEXTJOIN(",",TRUE,B14:E14),SF_Output!$Q$1:$Q$400,"monthly"),AND(B14<>"",H14<>SF_Output!$Y$2),SUMIFS(SF_Output!$S$1:$S$400,SF_Output!$AC$1:$AC$400,_xlfn.TEXTJOIN(",",TRUE,B14:E14),SF_Output!$Q$1:$Q$400,"monthly"))} -> 6921.15 | W14: {=_xlfn.IFS(OR(B14=0,B14="",V14=0),"",AF14<>"exclusion",MAX($W$9,$W$7,(-(SUMIFS(SF_Output!$T$1:$T$400,SF_Output!$AC$1:$AC$400,_xlfn.TEXTJOIN(",",TRUE,$B14:$E14),SF_Output!$Q$1:$Q$400,"monthly"))/V14)),AF14="exclusion",-(SUMIFS(SF_Output!$T$1:$T$400,SF_Output!$AC$1:$AC$400,_xlfn.TEXTJOIN(",",TRUE,$B14:$E14),SF_Output!$Q$1:$Q$400,"monthly"))/V14)} -> 0.12000029 | X14: {=IFERROR(_xlfn.IFS(V14=0,0,V14="","",W14=0,V14,OR(V14<>0,V14<>""),H14*I14),V14*(1-W14))} -> 6090.5 | Z14: =IFERROR(IF(B14="","",SUMIFS(Billing_Fallout!H:H,Billing_Fallout!N:N,B14)),0) -> 0 | AA14: =IF(Z14="","",AB14-Z14) -> 0 | AB14: =IFERROR(IF(B14="","",SUMIFS(Billing_Fallout!J:J,Billing_Fallout!N:N,B14)),0) -> 0 | AD14: =IFERROR(X14-AB14,"") -> 6090.5 | AF14: =IFERROR(INDEX(H_Tables!$B$1:$B$1500,MATCH(INDEX(SF_Output!$J$1:$J$400,MATCH(B14,SF_Output!$M$1:$M$400,0)),H_Tables!$A$1:$A$1500,0)),"") -> Exclusion | AI14: =IF(B14="","",IF(F14="remove","Remove Product",IF(F14="add","Add Product",_xlfn.TEXTJOIN(", ",TRUE,AQ14,AR14,AS14,AT14,AU14,AV14,AW14,AX14,AY14,AZ14,BA14,BB14,BC14)))) | AJ14: =IFERROR(INDEX(SF_Output!AD:AD,MATCH(_xlfn.TEXTJOIN(",",TRUE,B14:E14),SF_Output!AC1:AC400,0)),0.05) -> 8 | AK14: =IF(SUMIFS(SF_Output!$F$1:$F$400,SF_Output!$AC$1:$AC$400,_xlfn.TEXTJOIN(",",TRUE,B14:E14))+SUMIFS(SF_Output!$G$1:$G$400,SF_Output!$AC$1:$AC$400,_xlfn.TEXTJOIN(",",TRUE,B14:E14))=0,"","PAP") -> PAP | AL14: =LEFT(_xlfn.TEXTJOIN(",",TRUE,B14:E14),80) -> SilverLake System Bundle,New,Hosted by JHA,0 | AR14: {=IFERROR(_xlfn.IFS(AND(E14*1=1,F14="Included"),"Change to Included",AND(E14*1=0,F14="Optional"),"Change to Optional",OR(B14="",F14="replaced"),""),"")} | AS14: =IF((OR(NOT(_xlfn.ISFORMULA(J14)),NOT(_xlfn.ISFORMULA(L14)))),"Check License Price Override","") | AT14: =IF(OR(AND(K14=$K$9,K14<>0),NOT(_xlfn.ISFORMULA(K14))),"License Discount "&K14*100&"%","") | AU14: =IF((OR(NOT(_xlfn.ISFORMULA(N14)),NOT(_xlfn.ISFORMULA(P14)))),"Check Install Price Override","") | AV14: =IF(OR(AND(O14=$O$9,O14<>0),NOT(_xlfn.ISFORMULA(O14))),"Install Discount "&O14*100&"%","") | AW14: =IF((OR(NOT(_xlfn.ISFORMULA(R14)),NOT(_xlfn.ISFORMULA(T14)))),"Check Maintenance Price Override","") | AX14: =IF(OR(AND(S14=$S$9,S14<>0),NOT(_xlfn.ISFORMULA(S14))),"Maintenance Discount "&S14*100&"%","") | AY14: =IF((OR(NOT(_xlfn.ISFORMULA(V14)),NOT(_xlfn.ISFORMULA(X14)))),"Check Monthly Price Override","") | AZ14: =IF(OR((AND(W14=$W$9,W14<>0)),(AND(W14=$W$7,W14<>0)),(NOT(_xlfn.ISFORMULA(W14))),AND($W$7+0.2=W14,$W$7<>0)),"Monthly Discount "&W14*100&"%","") | BA14: =IF(NOT(_xlfn.ISFORMULA(H14)),"Check Quantity","") | BB14: =IF(NOT(_xlfn.ISFORMULA(I14)),"Check Unit Price Override","") | BE14: =INDEX(SF_Output!$AA$2:$AA$400,MATCH($B14,SF_Output!$M$2:$M$400,0)) -> 1 | BF14: =INDEX(SF_Output!$AB$2:$AB$400,MATCH($B14,SF_Output!$M$2:$M$400,0)) -> 1
B15: SilverLake Technical Conversion/Installation | C15: New | D15: Hosted by JHA | E15: 0 | F15: =IF(B15="","",IF(E15*1=0,"Included","Optional")) -> Included | G15: =IF(B15="","",INDEX(SF_Output!$K$1:$K$400,MATCH(B15,SF_Output!$M$1:$M$400,0))) -> SilverLake | H15: {=_xlfn.IFS(B15="","",(SUMIFS(SF_Output!$F$1:$F$400,SF_Output!$AC$1:$AC$400,_xlfn.TEXTJOIN(",",TRUE,B15:E15))+SUMIFS(SF_Output!$G$1:$G$400,SF_Output!$AC$1:$AC$400,_xlfn.TEXTJOIN(",",TRUE,B15:E15)))<>0,SF_Output!$Y$2,INDEX(SF_Output!$F$1:$F$400,MATCH(_xlfn.TEXTJOIN(",",TRUE,B15:E15),SF_Output!$AC$1:$AC$400,0))=0,INDEX(SF_Output!$R$1:$R$400,MATCH(_xlfn.TEXTJOIN(",",TRUE,B15:E15),SF_Output!$AC$1:$AC$400,0)))} -> 1 | I15: =IFERROR(IF(AND(H15>1,H15<>""),ROUND(SUMIFS(SF_Output!$S$1:$S$400,SF_Output!$AC$1:$AC$400,_xlfn.TEXTJOIN(",",TRUE,B15:E15),SF_Output!$Q$1:$Q$400,"monthly")*(1-W15)/H15,4),""),"") | J15: =IF(B15="","",SUMIFS(SF_Output!$S$1:$S$400,SF_Output!$AC$1:$AC$400,_xlfn.TEXTJOIN(",",TRUE,B15:E15),SF_Output!$Q$1:$Q$400,"One Time",SF_Output!$L$1:$L$400,"license fee")+SUMIFS(SF_Output!$S$1:$S$400,SF_Output!$AC$1:$AC$400,_xlfn.TEXTJOIN(",",TRUE,B15:E15),SF_Output!$Q$1:$Q$400,"One Time",SF_Output!$L$1:$L$400,"software license")+SUMIFS(SF_Output!$S$1:$S$400,SF_Output!$AC$1:$AC$400,_xlfn.TEXTJOIN(",",TRUE,B15:E15),SF_Output!$Q$1:$Q$400,"One Time",SF_Output!$L$1:$L$400,"hardware")) -> 0 | K15: =IF(OR(B15=0,B15="",G15="hardware",J15=0),"",IF(AF15<>"exclusion",MAX(K$9,-((SUMIFS(SF_Output!$T$1:$T$400,SF_Output!$AC$1:$AC$400,_xlfn.TEXTJOIN(",",TRUE,$B15:$E15),SF_Output!$Q$1:$Q$400,"One Time",SF_Output!$L$1:$L$400,"license fee")+SUMIFS(SF_Output!$T$1:$T$400,SF_Output!$AC$1:$AC$400,_xlfn.TEXTJOIN(",",TRUE,$B15:$E15),SF_Output!$Q$1:$Q$400,"One Time",SF_Output!$L$1:$L$400,"software license"))/J15)),-((SUMIFS(SF_Output!$T$1:$T$400,SF_Output!$AC$1:$AC$400,_xlfn.TEXTJOIN(",",TRUE,$B15:$E15),SF_Output!$Q$1:$Q$400,"One Time",SF_Output!$L$1:$L$400,"license fee")+SUMIFS(SF_Output!$T$1:$T$400,SF_Output!$AC$1:$AC$400,_xlfn.TEXTJOIN(",",TRUE,$B15:$E15),SF_Output!$Q$1:$Q$400,"One Time",SF_Output!$L$1:$L$400,"software license"))/J15))) | L15: =IF(K15="",J15,J15*(1-K15)) -> 0 | N15: =IF(B15="","",SUMIFS(SF_Output!$S$1:$S$400,SF_Output!$AC$1:$AC$400,_xlfn.TEXTJOIN(",",TRUE,B15:E15),SF_Output!$Q$1:$Q$400,"One Time",SF_Output!$L$1:$L$400,"professional service")) -> 125405 | O15: =IF(OR(B15=0,B15="",N15=0),"",IF(AF15<>"exclusion",MAX(O$9,-(SUMIFS(SF_Output!$T$1:$T$400,SF_Output!$AC$1:$AC$400,_xlfn.TEXTJOIN(",",TRUE,$B15:$E15),SF_Output!$Q$1:$Q$400,"One Time",SF_Output!$L$1:$L$400,"professional service"))/N15),-((SUMIFS(SF_Output!$T$1:$T$400,SF_Output!$AC$1:$AC$400,_xlfn.TEXTJOIN(",",TRUE,$B15:$E15),SF_Output!$Q$1:$Q$400,"One Time",SF_Output!$L$1:$L$400,"professional service")/N15)))) -> 1 | P15: =IF(O15="",N15,N15*(1-O15)) -> 0 | R15: =IF(B15="","",SUMIFS(SF_Output!$S$1:$S$400,SF_Output!$AC$1:$AC$400,_xlfn.TEXTJOIN(",",TRUE,B15:E15),SF_Output!$Q$1:$Q$400,"yearly")+SUMIFS(SF_Output!$S$1:$S$400,SF_Output!$AC$1:$AC$400,_xlfn.TEXTJOIN(",",TRUE,B15:E15),SF_Output!$Q$1:$Q$400,"quarterly")*4) -> 0 | S15: =IF(OR(B15=0,B15="",G15="hardware",R15=0),"",IF(AF15<>"exclusion",MAX(S$9,-(SUMIFS(SF_Output!$T$1:$T$400,SF_Output!$AC$1:$AC$400,_xlfn.TEXTJOIN(",",TRUE,$B15:$E15),SF_Output!$Q$1:$Q$400,"yearly"))/R15),-((SUMIFS(SF_Output!$T$1:$T$400,SF_Output!$AC$1:$AC$400,_xlfn.TEXTJOIN(",",TRUE,$B15:$E15),SF_Output!$Q$1:$Q$400,"yearly")/R15)))) | T15: =IF(S15="",R15,R15*(1-S15)) -> 0 | V15: {=_xlfn.IFS(B15="","",AND(B15<>"",H15=SF_Output!$Y$2,SUMIFS(SF_Output!$T$1:$T$400,SF_Output!$AC$1:$AC$400,_xlfn.TEXTJOIN(",",TRUE,B15:E15),SF_Output!$Q$1:$Q$400,"monthly")=0),(SUMIFS(SF_Output!$F$1:$F$400,SF_Output!$AC$1:$AC$400,_xlfn.TEXTJOIN(",",TRUE,B15:E15),SF_Output!$Q$1:$Q$400,"monthly")+SUMIFS(SF_Output!$G$1:$G$400,SF_Output!$AC$1:$AC$400,_xlfn.TEXTJOIN(",",TRUE,B15:E15),SF_Output!$Q$1:$Q$400,"monthly"))*H15,AND(B15<>"",H15=SF_Output!$Y$2,SUMIFS(SF_Output!$T$1:$T$400,SF_Output!$AC$1:$AC$400,_xlfn.TEXTJOIN(",",TRUE,B15:E15),SF_Output!$Q$1:$Q$400,"monthly")<>0),SUMIFS(SF_Output!$S$1:$S$400,SF_Output!$AC$1:$AC$400,_xlfn.TEXTJOIN(",",TRUE,B15:E15),SF_Output!$Q$1:$Q$400,"monthly"),AND(B15<>"",H15<>SF_Output!$Y$2),SUMIFS(SF_Output!$S$1:$S$400,SF_Output!$AC$1:$AC$400,_xlfn.TEXTJOIN(",",TRUE,B15:E15),SF_Output!$Q$1:$Q$400,"monthly"))} -> 0 | W15: {=_xlfn.IFS(OR(B15=0,B15="",V15=0),"",AF15<>"exclusion",MAX($W$9,$W$7,(-(SUMIFS(SF_Output!$T$1:$T$400,SF_Output!$AC$1:$AC$400,_xlfn.TEXTJOIN(",",TRUE,$B15:$E15),SF_Output!$Q$1:$Q$400,"monthly"))/V15)),AF15="exclusion",-(SUMIFS(SF_Output!$T$1:$T$400,SF_Output!$AC$1:$AC$400,_xlfn.TEXTJOIN(",",TRUE,$B15:$E15),SF_Output!$Q$1:$Q$400,"monthly"))/V15)} | X15: {=IFERROR(_xlfn.IFS(V15=0,0,V15="","",W15=0,V15,OR(V15<>0,V15<>""),H15*I15),V15*(1-W15))} -> 0 | Z15: =IFERROR(IF(B15="","",SUMIFS(Billing_Fallout!H:H,Billing_Fallout!N:N,B15)),0) -> 0 | AA15: =IF(Z15="","",AB15-Z15) -> 0 | AB15: =IFERROR(IF(B15="","",SUMIFS(Billing_Fallout!J:J,Billing_Fallout!N:N,B15)),0) -> 0 | AD15: =IFERROR(X15-AB15,"") -> 0 | AF15: =IFERROR(INDEX(H_Tables!$B$1:$B$1500,MATCH(INDEX(SF_Output!$J$1:$J$400,MATCH(B15,SF_Output!$M$1:$M$400,0)),H_Tables!$A$1:$A$1500,0)),"") | AI15: =IF(B15="","",IF(F15="remove","Remove Product",IF(F15="add","Add Product",_xlfn.TEXTJOIN(", ",TRUE,AQ15,AR15,AS15,AT15,AU15,AV15,AW15,AX15,AY15,AZ15,BA15,BB15,BC15)))) | AJ15: =IFERROR(INDEX(SF_Output!AD:AD,MATCH(_xlfn.TEXTJOIN(",",TRUE,B15:E15),SF_Output!AC1:AC400,0)),0.05) -> 10 | AK15: =IF(SUMIFS(SF_Output!$F$1:$F$400,SF_Output!$AC$1:$AC$400,_xlfn.TEXTJOIN(",",TRUE,B15:E15))+SUMIFS(SF_Output!$G$1:$G$400,SF_Output!$AC$1:$AC$400,_xlfn.TEXTJOIN(",",TRUE,B15:E15))=0,"","PAP") | AL15: =LEFT(_xlfn.TEXTJOIN(",",TRUE,B15:E15),80) -> SilverLake Technical Conversion/Installation,New,Hosted by JHA,0 | AR15: {=IFERROR(_xlfn.IFS(AND(E15*1=1,F15="Included"),"Change to Included",AND(E15*1=0,F15="Optional"),"Change to Optional",OR(B15="",F15="replaced"),""),"")} | AS15: =IF((OR(NOT(_xlfn.ISFORMULA(J15)),NOT(_xlfn.ISFORMULA(L15)))),"Check License Price Override","") | AT15: =IF(OR(AND(K15=$K$9,K15<>0),NOT(_xlfn.ISFORMULA(K15))),"License Discount "&K15*100&"%","") | AU15: =IF((OR(NOT(_xlfn.ISFORMULA(N15)),NOT(_xlfn.ISFORMULA(P15)))),"Check Install Price Override","") | AV15: =IF(OR(AND(O15=$O$9,O15<>0),NOT(_xlfn.ISFORMULA(O15))),"Install Discount "&O15*100&"%","") | AW15: =IF((OR(NOT(_xlfn.ISFORMULA(R15)),NOT(_xlfn.ISFORMULA(T15)))),"Check Maintenance Price Override","") | AX15: =IF(OR(AND(S15=$S$9,S15<>0),NOT(_xlfn.ISFORMULA(S15))),"Maintenance Discount "&S15*100&"%","") | AY15: =IF((OR(NOT(_xlfn.ISFORMULA(V15)),NOT(_xlfn.ISFORMULA(X15)))),"Check Monthly Price Override","") | AZ15: =IF(OR((AND(W15=$W$9,W15<>0)),(AND(W15=$W$7,W15<>0)),(NOT(_xlfn.ISFORMULA(W15))),AND($W$7+0.2=W15,$W$7<>0)),"Monthly Discount "&W15*100&"%","") | BA15: =IF(NOT(_xlfn.ISFORMULA(H15)),"Check Quantity","") | BB15: =IF(NOT(_xlfn.ISFORMULA(I15)),"Check Unit Price Override","") | BE15: =INDEX(SF_Output!$AA$2:$AA$400,MATCH($B15,SF_Output!$M$2:$M$400,0)) -> 1 | BF15: =INDEX(SF_Output!$AB$2:$AB$400,MATCH($B15,SF_Output!$M$2:$M$400,0)) -> 1
B16: Closed Accounts (PAP) | C16: New | D16: Hosted by JHA | E16: 0 | F16: =IF(B16="","",IF(E16*1=0,"Included","Optional")) -> Included | G16: =IF(B16="","",INDEX(SF_Output!$K$1:$K$400,MATCH(B16,SF_Output!$M$1:$M$400,0))) -> SilverLake | H16: {=_xlfn.IFS(B16="","",(SUMIFS(SF_Output!$F$1:$F$400,SF_Output!$AC$1:$AC$400,_xlfn.TEXTJOIN(",",TRUE,B16:E16))+SUMIFS(SF_Output!$G$1:$G$400,SF_Output!$AC$1:$AC$400,_xlfn.TEXTJOIN(",",TRUE,B16:E16)))<>0,SF_Output!$Y$2,INDEX(SF_Output!$F$1:$F$400,MATCH(_xlfn.TEXTJOIN(",",TRUE,B16:E16),SF_Output!$AC$1:$AC$400,0))=0,INDEX(SF_Output!$R$1:$R$400,MATCH(_xlfn.TEXTJOIN(",",TRUE,B16:E16),SF_Output!$AC$1:$AC$400,0)))} -> 1 | I16: =IFERROR(IF(AND(H16>1,H16<>""),ROUND(SUMIFS(SF_Output!$S$1:$S$400,SF_Output!$AC$1:$AC$400,_xlfn.TEXTJOIN(",",TRUE,B16:E16),SF_Output!$Q$1:$Q$400,"monthly")*(1-W16)/H16,4),""),"") | J16: =IF(B16="","",SUMIFS(SF_Output!$S$1:$S$400,SF_Output!$AC$1:$AC$400,_xlfn.TEXTJOIN(",",TRUE,B16:E16),SF_Output!$Q$1:$Q$400,"One Time",SF_Output!$L$1:$L$400,"license fee")+SUMIFS(SF_Output!$S$1:$S$400,SF_Output!$AC$1:$AC$400,_xlfn.TEXTJOIN(",",TRUE,B16:E16),SF_Output!$Q$1:$Q$400,"One Time",SF_Output!$L$1:$L$400,"software license")+SUMIFS(SF_Output!$S$1:$S$400,SF_Output!$AC$1:$AC$400,_xlfn.TEXTJOIN(",",TRUE,B16:E16),SF_Output!$Q$1:$Q$400,"One Time",SF_Output!$L$1:$L$400,"hardware")) -> 0 | K16: =IF(OR(B16=0,B16="",G16="hardware",J16=0),"",IF(AF16<>"exclusion",MAX(K$9,-((SUMIFS(SF_Output!$T$1:$T$400,SF_Output!$AC$1:$AC$400,_xlfn.TEXTJOIN(",",TRUE,$B16:$E16),SF_Output!$Q$1:$Q$400,"One Time",SF_Output!$L$1:$L$400,"license fee")+SUMIFS(SF_Output!$T$1:$T$400,SF_Output!$AC$1:$AC$400,_xlfn.TEXTJOIN(",",TRUE,$B16:$E16),SF_Output!$Q$1:$Q$400,"One Time",SF_Output!$L$1:$L$400,"software license"))/J16)),-((SUMIFS(SF_Output!$T$1:$T$400,SF_Output!$AC$1:$AC$400,_xlfn.TEXTJOIN(",",TRUE,$B16:$E16),SF_Output!$Q$1:$Q$400,"One Time",SF_Output!$L$1:$L$400,"license fee")+SUMIFS(SF_Output!$T$1:$T$400,SF_Output!$AC$1:$AC$400,_xlfn.TEXTJOIN(",",TRUE,$B16:$E16),SF_Output!$Q$1:$Q$400,"One Time",SF_Output!$L$1:$L$400,"software license"))/J16))) | L16: =IF(K16="",J16,J16*(1-K16)) -> 0 | N16: =IF(B16="","",SUMIFS(SF_Output!$S$1:$S$400,SF_Output!$AC$1:$AC$400,_xlfn.TEXTJOIN(",",TRUE,B16:E16),SF_Output!$Q$1:$Q$400,"One Time",SF_Output!$L$1:$L$400,"professional service")) -> 0 | O16: =IF(OR(B16=0,B16="",N16=0),"",IF(AF16<>"exclusion",MAX(O$9,-(SUMIFS(SF_Output!$T$1:$T$400,SF_Output!$AC$1:$AC$400,_xlfn.TEXTJOIN(",",TRUE,$B16:$E16),SF_Output!$Q$1:$Q$400,"One Time",SF_Output!$L$1:$L$400,"professional service"))/N16),-((SUMIFS(SF_Output!$T$1:$T$400,SF_Output!$AC$1:$AC$400,_xlfn.TEXTJOIN(",",TRUE,$B16:$E16),SF_Output!$Q$1:$Q$400,"One Time",SF_Output!$L$1:$L$400,"professional service")/N16)))) | P16: =IF(O16="",N16,N16*(1-O16)) -> 0 | R16: =IF(B16="","",SUMIFS(SF_Output!$S$1:$S$400,SF_Output!$AC$1:$AC$400,_xlfn.TEXTJOIN(",",TRUE,B16:E16),SF_Output!$Q$1:$Q$400,"yearly")+SUMIFS(SF_Output!$S$1:$S$400,SF_Output!$AC$1:$AC$400,_xlfn.TEXTJOIN(",",TRUE,B16:E16),SF_Output!$Q$1:$Q$400,"quarterly")*4) -> 0 | S16: =IF(OR(B16=0,B16="",G16="hardware",R16=0),"",IF(AF16<>"exclusion",MAX(S$9,-(SUMIFS(SF_Output!$T$1:$T$400,SF_Output!$AC$1:$AC$400,_xlfn.TEXTJOIN(",",TRUE,$B16:$E16),SF_Output!$Q$1:$Q$400,"yearly"))/R16),-((SUMIFS(SF_Output!$T$1:$T$400,SF_Output!$AC$1:$AC$400,_xlfn.TEXTJOIN(",",TRUE,$B16:$E16),SF_Output!$Q$1:$Q$400,"yearly")/R16)))) | T16: =IF(S16="",R16,R16*(1-S16)) -> 0 | V16: {=_xlfn.IFS(B16="","",AND(B16<>"",H16=SF_Output!$Y$2,SUMIFS(SF_Output!$T$1:$T$400,SF_Output!$AC$1:$AC$400,_xlfn.TEXTJOIN(",",TRUE,B16:E16),SF_Output!$Q$1:$Q$400,"monthly")=0),(SUMIFS(SF_Output!$F$1:$F$400,SF_Output!$AC$1:$AC$400,_xlfn.TEXTJOIN(",",TRUE,B16:E16),SF_Output!$Q$1:$Q$400,"monthly")+SUMIFS(SF_Output!$G$1:$G$400,SF_Output!$AC$1:$AC$400,_xlfn.TEXTJOIN(",",TRUE,B16:E16),SF_Output!$Q$1:$Q$400,"monthly"))*H16,AND(B16<>"",H16=SF_Output!$Y$2,SUMIFS(SF_Output!$T$1:$T$400,SF_Output!$AC$1:$AC$400,_xlfn.TEXTJOIN(",",TRUE,B16:E16),SF_Output!$Q$1:$Q$400,"monthly")<>0),SUMIFS(SF_Output!$S$1:$S$400,SF_Output!$AC$1:$AC$400,_xlfn.TEXTJOIN(",",TRUE,B16:E16),SF_Output!$Q$1:$Q$400,"monthly"),AND(B16<>"",H16<>SF_Output!$Y$2),SUMIFS(SF_Output!$S$1:$S$400,SF_Output!$AC$1:$AC$400,_xlfn.TEXTJOIN(",",TRUE,B16:E16),SF_Output!$Q$1:$Q$400,"monthly"))} -> 0.25 | W16: {=_xlfn.IFS(OR(B16=0,B16="",V16=0),"",AF16<>"exclusion",MAX($W$9,$W$7,(-(SUMIFS(SF_Output!$T$1:$T$400,SF_Output!$AC$1:$AC$400,_xlfn.TEXTJOIN(",",TRUE,$B16:$E16),SF_Output!$Q$1:$Q$400,"monthly"))/V16)),AF16="exclusion",-(SUMIFS(SF_Output!$T$1:$T$400,SF_Output!$AC$1:$AC$400,_xlfn.TEXTJOIN(",",TRUE,$B16:$E16),SF_Output!$Q$1:$Q$400,"monthly"))/V16)} -> 0 | X16: {=IFERROR(_xlfn.IFS(V16=0,0,V16="","",W16=0,V16,OR(V16<>0,V16<>""),H16*I16),V16*(1-W16))} -> 0.25 | Z16: =IFERROR(IF(B16="","",SUMIFS(Billing_Fallout!H:H,Billing_Fallout!N:N,B16)),0) -> 0 | AA16: =IF(Z16="","",AB16-Z16) -> 0 | AB16: =IFERROR(IF(B16="","",SUMIFS(Billing_Fallout!J:J,Billing_Fallout!N:N,B16)),0) -> 0 | AD16: =IFERROR(X16-AB16,"") -> 0.25 | AF16: =IFERROR(INDEX(H_Tables!$B$1:$B$1500,MATCH(INDEX(SF_Output!$J$1:$J$400,MATCH(B16,SF_Output!$M$1:$M$400,0)),H_Tables!$A$1:$A$1500,0)),"") -> Exclusion | AI16: =IF(B16="","",IF(F16="remove","Remove Product",IF(F16="add","Add Product",_xlfn.TEXTJOIN(", ",TRUE,AQ16,AR16,AS16,AT16,AU16,AV16,AW16,AX16,AY16,AZ16,BA16,BB16,BC16)))) | AJ16: =IFERROR(INDEX(SF_Output!AD:AD,MATCH(_xlfn.TEXTJOIN(",",TRUE,B16:E16),SF_Output!AC1:AC400,0)),0.05) -> 12 | AK16: =IF(SUMIFS(SF_Output!$F$1:$F$400,SF_Output!$AC$1:$AC$400,_xlfn.TEXTJOIN(",",TRUE,B16:E16))+SUMIFS(SF_Output!$G$1:$G$400,SF_Output!$AC$1:$AC$400,_xlfn.TEXTJOIN(",",TRUE,B16:E16))=0,"","PAP") | AL16: =LEFT(_xlfn.TEXTJOIN(",",TRUE,B16:E16),80) -> Closed Accounts (PAP),New,Hosted by JHA,0 | AR16: {=IFERROR(_xlfn.IFS(AND(E16*1=1,F16="Included"),"Change to Included",AND(E16*1=0,F16="Optional"),"Change to Optional",OR(B16="",F16="replaced"),""),"")} | AS16: =IF((OR(NOT(_xlfn.ISFORMULA(J16)),NOT(_xlfn.ISFORMULA(L16)))),"Check License Price Override","") | AT16: =IF(OR(AND(K16=$K$9,K16<>0),NOT(_xlfn.ISFORMULA(K16))),"License Discount "&K16*100&"%","") | AU16: =IF((OR(NOT(_xlfn.ISFORMULA(N16)),NOT(_xlfn.ISFORMULA(P16)))),"Check Install Price Override","") | AV16: =IF(OR(AND(O16=$O$9,O16<>0),NOT(_xlfn.ISFORMULA(O16))),"Install Discount "&O16*100&"%","") | AW16: =IF((OR(NOT(_xlfn.ISFORMULA(R16)),NOT(_xlfn.ISFORMULA(T16)))),"Check Maintenance Price Override","") | AX16: =IF(OR(AND(S16=$S$9,S16<>0),NOT(_xlfn.ISFORMULA(S16))),"Maintenance Discount "&S16*100&"%","") | AY16: =IF((OR(NOT(_xlfn.ISFORMULA(V16)),NOT(_xlfn.ISFORMULA(X16)))),"Check Monthly Price Override","") | AZ16: =IF(OR((AND(W16=$W$9,W16<>0)),(AND(W16=$W$7,W16<>0)),(NOT(_xlfn.ISFORMULA(W16))),AND($W$7+0.2=W16,$W$7<>0)),"Monthly Discount "&W16*100&"%","") | BA16: =IF(NOT(_xlfn.ISFORMULA(H16)),"Check Quantity","") | BB16: =IF(NOT(_xlfn.ISFORMULA(I16)),"Check Unit Price Override","") | BE16: =INDEX(SF_Output!$AA$2:$AA$400,MATCH($B16,SF_Output!$M$2:$M$400,0)) -> 1 | BF16: =INDEX(SF_Output!$AB$2:$AB$400,MATCH($B16,SF_Output!$M$2:$M$400,0)) -> 1
B17: SilverLake Static Training Bank | C17: New | D17: Hosted by JHA | E17: 1 | F17: =IF(B17="","",IF(E17*1=0,"Included","Optional")) -> Optional | G17: =IF(B17="","",INDEX(SF_Output!$K$1:$K$400,MATCH(B17,SF_Output!$M$1:$M$400,0))) -> SilverLake | H17: {=_xlfn.IFS(B17="","",(SUMIFS(SF_Output!$F$1:$F$400,SF_Output!$AC$1:$AC$400,_xlfn.TEXTJOIN(",",TRUE,B17:E17))+SUMIFS(SF_Output!$G$1:$G$400,SF_Output!$AC$1:$AC$400,_xlfn.TEXTJOIN(",",TRUE,B17:E17)))<>0,SF_Output!$Y$2,INDEX(SF_Output!$F$1:$F$400,MATCH(_xlfn.TEXTJOIN(",",TRUE,B17:E17),SF_Output!$AC$1:$AC$400,0))=0,INDEX(SF_Output!$R$1:$R$400,MATCH(_xlfn.TEXTJOIN(",",TRUE,B17:E17),SF_Output!$AC$1:$AC$400,0)))} -> 1 | I17: =IFERROR(IF(AND(H17>1,H17<>""),ROUND(SUMIFS(SF_Output!$S$1:$S$400,SF_Output!$AC$1:$AC$400,_xlfn.TEXTJOIN(",",TRUE,B17:E17),SF_Output!$Q$1:$Q$400,"monthly")*(1-W17)/H17,4),""),"") | J17: =IF(B17="","",SUMIFS(SF_Output!$S$1:$S$400,SF_Output!$AC$1:$AC$400,_xlfn.TEXTJOIN(",",TRUE,B17:E17),SF_Output!$Q$1:$Q$400,"One Time",SF_Output!$L$1:$L$400,"license fee")+SUMIFS(SF_Output!$S$1:$S$400,SF_Output!$AC$1:$AC$400,_xlfn.TEXTJOIN(",",TRUE,B17:E17),SF_Output!$Q$1:$Q$400,"One Time",SF_Output!$L$1:$L$400,"software license")+SUMIFS(SF_Output!$S$1:$S$400,SF_Output!$AC$1:$AC$400,_xlfn.TEXTJOIN(",",TRUE,B17:E17),SF_Output!$Q$1:$Q$400,"One Time",SF_Output!$L$1:$L$400,"hardware")) -> 0 | K17: =IF(OR(B17=0,B17="",G17="hardware",J17=0),"",IF(AF17<>"exclusion",MAX(K$9,-((SUMIFS(SF_Output!$T$1:$T$400,SF_Output!$AC$1:$AC$400,_xlfn.TEXTJOIN(",",TRUE,$B17:$E17),SF_Output!$Q$1:$Q$400,"One Time",SF_Output!$L$1:$L$400,"license fee")+SUMIFS(SF_Output!$T$1:$T$400,SF_Output!$AC$1:$AC$400,_xlfn.TEXTJOIN(",",TRUE,$B17:$E17),SF_Output!$Q$1:$Q$400,"One Time",SF_Output!$L$1:$L$400,"software license"))/J17)),-((SUMIFS(SF_Output!$T$1:$T$400,SF_Output!$AC$1:$AC$400,_xlfn.TEXTJOIN(",",TRUE,$B17:$E17),SF_Output!$Q$1:$Q$400,"One Time",SF_Output!$L$1:$L$400,"license fee")+SUMIFS(SF_Output!$T$1:$T$400,SF_Output!$AC$1:$AC$400,_xlfn.TEXTJOIN(",",TRUE,$B17:$E17),SF_Output!$Q$1:$Q$400,"One Time",SF_Output!$L$1:$L$400,"software license"))/J17))) | L17: =IF(K17="",J17,J17*(1-K17)) -> 0 | N17: =IF(B17="","",SUMIFS(SF_Output!$S$1:$S$400,SF_Output!$AC$1:$AC$400,_xlfn.TEXTJOIN(",",TRUE,B17:E17),SF_Output!$Q$1:$Q$400,"One Time",SF_Output!$L$1:$L$400,"professional service")) -> 6000 | O17: =IF(OR(B17=0,B17="",N17=0),"",IF(AF17<>"exclusion",MAX(O$9,-(SUMIFS(SF_Output!$T$1:$T$400,SF_Output!$AC$1:$AC$400,_xlfn.TEXTJOIN(",",TRUE,$B17:$E17),SF_Output!$Q$1:$Q$400,"One Time",SF_Output!$L$1:$L$400,"professional service"))/N17),-((SUMIFS(SF_Output!$T$1:$T$400,SF_Output!$AC$1:$AC$400,_xlfn.TEXTJOIN(",",TRUE,$B17:$E17),SF_Output!$Q$1:$Q$400,"One Time",SF_Output!$L$1:$L$400,"professional service")/N17)))) -> 1 | P17: =IF(O17="",N17,N17*(1-O17)) -> 0 | R17: =IF(B17="","",SUMIFS(SF_Output!$S$1:$S$400,SF_Output!$AC$1:$AC$400,_xlfn.TEXTJOIN(",",TRUE,B17:E17),SF_Output!$Q$1:$Q$400,"yearly")+SUMIFS(SF_Output!$S$1:$S$400,SF_Output!$AC$1:$AC$400,_xlfn.TEXTJOIN(",",TRUE,B17:E17),SF_Output!$Q$1:$Q$400,"quarterly")*4) -> 0 | S17: =IF(OR(B17=0,B17="",G17="hardware",R17=0),"",IF(AF17<>"exclusion",MAX(S$9,-(SUMIFS(SF_Output!$T$1:$T$400,SF_Output!$AC$1:$AC$400,_xlfn.TEXTJOIN(",",TRUE,$B17:$E17),SF_Output!$Q$1:$Q$400,"yearly"))/R17),-((SUMIFS(SF_Output!$T$1:$T$400,SF_Output!$AC$1:$AC$400,_xlfn.TEXTJOIN(",",TRUE,$B17:$E17),SF_Output!$Q$1:$Q$400,"yearly")/R17)))) | T17: =IF(S17="",R17,R17*(1-S17)) -> 0 | V17: {=_xlfn.IFS(B17="","",AND(B17<>"",H17=SF_Output!$Y$2,SUMIFS(SF_Output!$T$1:$T$400,SF_Output!$AC$1:$AC$400,_xlfn.TEXTJOIN(",",TRUE,B17:E17),SF_Output!$Q$1:$Q$400,"monthly")=0),(SUMIFS(SF_Output!$F$1:$F$400,SF_Output!$AC$1:$AC$400,_xlfn.TEXTJOIN(",",TRUE,B17:E17),SF_Output!$Q$1:$Q$400,"monthly")+SUMIFS(SF_Output!$G$1:$G$400,SF_Output!$AC$1:$AC$400,_xlfn.TEXTJOIN(",",TRUE,B17:E17),SF_Output!$Q$1:$Q$400,"monthly"))*H17,AND(B17<>"",H17=SF_Output!$Y$2,SUMIFS(SF_Output!$T$1:$T$400,SF_Output!$AC$1:$AC$400,_xlfn.TEXTJOIN(",",TRUE,B17:E17),SF_Output!$Q$1:$Q$400,"monthly")<>0),SUMIFS(SF_Output!$S$1:$S$400,SF_Output!$AC$1:$AC$400,_xlfn.TEXTJOIN(",",TRUE,B17:E17),SF_Output!$Q$1:$Q$400,"monthly"),AND(B17<>"",H17<>SF_Output!$Y$2),SUMIFS(SF_Output!$S$1:$S$400,SF_Output!$AC$1:$AC$400,_xlfn.TEXTJOIN(",",TRUE,B17:E17),SF_Output!$Q$1:$Q$400,"monthly"))} -> 530 | W17: {=_xlfn.IFS(OR(B17=0,B17="",V17=0),"",AF17<>"exclusion",MAX($W$9,$W$7,(-(SUMIFS(SF_Output!$T$1:$T$400,SF_Output!$AC$1:$AC$400,_xlfn.TEXTJOIN(",",TRUE,$B17:$E17),SF_Output!$Q$1:$Q$400,"monthly"))/V17)),AF17="exclusion",-(SUMIFS(SF_Output!$T$1:$T$400,SF_Output!$AC$1:$AC$400,_xlfn.TEXTJOIN(",",TRUE,$B17:$E17),SF_Output!$Q$1:$Q$400,"monthly"))/V17)} -> 0.25 | X17: {=IFERROR(_xlfn.IFS(V17=0,0,V17="","",W17=0,V17,OR(V17<>0,V17<>""),H17*I17),V17*(1-W17))} -> 397.5 | Z17: =IFERROR(IF(B17="","",SUMIFS(Billing_Fallout!H:H,Billing_Fallout!N:N,B17)),0) -> 0 | AA17: =IF(Z17="","",AB17-Z17) -> 0 | AB17: =IFERROR(IF(B17="","",SUMIFS(Billing_Fallout!J:J,Billing_Fallout!N:N,B17)),0) -> 0 | AD17: =IFERROR(X17-AB17,"") -> 397.5 | AF17: =IFERROR(INDEX(H_Tables!$B$1:$B$1500,MATCH(INDEX(SF_Output!$J$1:$J$400,MATCH(B17,SF_Output!$M$1:$M$400,0)),H_Tables!$A$1:$A$1500,0)),"") | AI17: =IF(B17="","",IF(F17="remove","Remove Product",IF(F17="add","Add Product",_xlfn.TEXTJOIN(", ",TRUE,AQ17,AR17,AS17,AT17,AU17,AV17,AW17,AX17,AY17,AZ17,BA17,BB17,BC17)))) | AJ17: =IFERROR(INDEX(SF_Output!AD:AD,MATCH(_xlfn.TEXTJOIN(",",TRUE,B17:E17),SF_Output!AC1:AC400,0)),0.05) -> 14 | AK17: =IF(SUMIFS(SF_Output!$F$1:$F$400,SF_Output!$AC$1:$AC$400,_xlfn.TEXTJOIN(",",TRUE,B17:E17))+SUMIFS(SF_Output!$G$1:$G$400,SF_Output!$AC$1:$AC$400,_xlfn.TEXTJOIN(",",TRUE,B17:E17))=0,"","PAP") | AL17: =LEFT(_xlfn.TEXTJOIN(",",TRUE,B17:E17),80) -> SilverLake Static Training Bank,New,Hosted by JHA,1 | AR17: {=IFERROR(_xlfn.IFS(AND(E17*1=1,F17="Included"),"Change to Included",AND(E17*1=0,F17="Optional"),"Change to Optional",OR(B17="",F17="replaced"),""),"")} | AS17: =IF((OR(NOT(_xlfn.ISFORMULA(J17)),NOT(_xlfn.ISFORMULA(L17)))),"Check License Price Override","") | AT17: =IF(OR(AND(K17=$K$9,K17<>0),NOT(_xlfn.ISFORMULA(K17))),"License Discount "&K17*100&"%","") | AU17: =IF((OR(NOT(_xlfn.ISFORMULA(N17)),NOT(_xlfn.ISFORMULA(P17)))),"Check Install Price Override","") | AV17: =IF(OR(AND(O17=$O$9,O17<>0),NOT(_xlfn.ISFORMULA(O17))),"Install Discount "&O17*100&"%","") | AW17: =IF((OR(NOT(_xlfn.ISFORMULA(R17)),NOT(_xlfn.ISFORMULA(T17)))),"Check Maintenance Price Override","") | AX17: =IF(OR(AND(S17=$S$9,S17<>0),NOT(_xlfn.ISFORMULA(S17))),"Maintenance Discount "&S17*100&"%","") | AY17: =IF((OR(NOT(_xlfn.ISFORMULA(V17)),NOT(_xlfn.ISFORMULA(X17)))),"Check Monthly Price Override","") | AZ17: =IF(OR((AND(W17=$W$9,W17<>0)),(AND(W17=$W$7,W17<>0)),(NOT(_xlfn.ISFORMULA(W17))),AND($W$7+0.2=W17,$W$7<>0)),"Monthly Discount "&W17*100&"%","") | BA17: =IF(NOT(_xlfn.ISFORMULA(H17)),"Check Quantity","") | BB17: =IF(NOT(_xlfn.ISFORMULA(I17)),"Check Unit Price Override","") | BE17: =INDEX(SF_Output!$AA$2:$AA$400,MATCH($B17,SF_Output!$M$2:$M$400,0)) -> 1 | BF17: =INDEX(SF_Output!$AB$2:$AB$400,MATCH($B17,SF_Output!$M$2:$M$400,0)) -> 1
B18: SilverLake Teller Static Training Bank | C18: New | D18: Hosted by JHA | E18: 1 | F18: =IF(B18="","",IF(E18*1=0,"Included","Optional")) -> Optional | G18: =IF(B18="","",INDEX(SF_Output!$K$1:$K$400,MATCH(B18,SF_Output!$M$1:$M$400,0))) -> SilverLake | H18: {=_xlfn.IFS(B18="","",(SUMIFS(SF_Output!$F$1:$F$400,SF_Output!$AC$1:$AC$400,_xlfn.TEXTJOIN(",",TRUE,B18:E18))+SUMIFS(SF_Output!$G$1:$G$400,SF_Output!$AC$1:$AC$400,_xlfn.TEXTJOIN(",",TRUE,B18:E18)))<>0,SF_Output!$Y$2,INDEX(SF_Output!$F$1:$F$400,MATCH(_xlfn.TEXTJOIN(",",TRUE,B18:E18),SF_Output!$AC$1:$AC$400,0))=0,INDEX(SF_Output!$R$1:$R$400,MATCH(_xlfn.TEXTJOIN(",",TRUE,B18:E18),SF_Output!$AC$1:$AC$400,0)))} -> 1 | I18: =IFERROR(IF(AND(H18>1,H18<>""),ROUND(SUMIFS(SF_Output!$S$1:$S$400,SF_Output!$AC$1:$AC$400,_xlfn.TEXTJOIN(",",TRUE,B18:E18),SF_Output!$Q$1:$Q$400,"monthly")*(1-W18)/H18,4),""),"") | J18: =IF(B18="","",SUMIFS(SF_Output!$S$1:$S$400,SF_Output!$AC$1:$AC$400,_xlfn.TEXTJOIN(",",TRUE,B18:E18),SF_Output!$Q$1:$Q$400,"One Time",SF_Output!$L$1:$L$400,"license fee")+SUMIFS(SF_Output!$S$1:$S$400,SF_Output!$AC$1:$AC$400,_xlfn.TEXTJOIN(",",TRUE,B18:E18),SF_Output!$Q$1:$Q$400,"One Time",SF_Output!$L$1:$L$400,"software license")+SUMIFS(SF_Output!$S$1:$S$400,SF_Output!$AC$1:$AC$400,_xlfn.TEXTJOIN(",",TRUE,B18:E18),SF_Output!$Q$1:$Q$400,"One Time",SF_Output!$L$1:$L$400,"hardware")) -> 0 | K18: =IF(OR(B18=0,B18="",G18="hardware",J18=0),"",IF(AF18<>"exclusion",MAX(K$9,-((SUMIFS(SF_Output!$T$1:$T$400,SF_Output!$AC$1:$AC$400,_xlfn.TEXTJOIN(",",TRUE,$B18:$E18),SF_Output!$Q$1:$Q$400,"One Time",SF_Output!$L$1:$L$400,"license fee")+SUMIFS(SF_Output!$T$1:$T$400,SF_Output!$AC$1:$AC$400,_xlfn.TEXTJOIN(",",TRUE,$B18:$E18),SF_Output!$Q$1:$Q$400,"One Time",SF_Output!$L$1:$L$400,"software license"))/J18)),-((SUMIFS(SF_Output!$T$1:$T$400,SF_Output!$AC$1:$AC$400,_xlfn.TEXTJOIN(",",TRUE,$B18:$E18),SF_Output!$Q$1:$Q$400,"One Time",SF_Output!$L$1:$L$400,"license fee")+SUMIFS(SF_Output!$T$1:$T$400,SF_Output!$AC$1:$AC$400,_xlfn.TEXTJOIN(",",TRUE,$B18:$E18),SF_Output!$Q$1:$Q$400,"One Time",SF_Output!$L$1:$L$400,"software license"))/J18))) | L18: =IF(K18="",J18,J18*(1-K18)) -> 0 | N18: =IF(B18="","",SUMIFS(SF_Output!$S$1:$S$400,SF_Output!$AC$1:$AC$400,_xlfn.TEXTJOIN(",",TRUE,B18:E18),SF_Output!$Q$1:$Q$400,"One Time",SF_Output!$L$1:$L$400,"professional service")) -> 2340 | O18: =IF(OR(B18=0,B18="",N18=0),"",IF(AF18<>"exclusion",MAX(O$9,-(SUMIFS(SF_Output!$T$1:$T$400,SF_Output!$AC$1:$AC$400,_xlfn.TEXTJOIN(",",TRUE,$B18:$E18),SF_Output!$Q$1:$Q$400,"One Time",SF_Output!$L$1:$L$400,"professional service"))/N18),-((SUMIFS(SF_Output!$T$1:$T$400,SF_Output!$AC$1:$AC$400,_xlfn.TEXTJOIN(",",TRUE,$B18:$E18),SF_Output!$Q$1:$Q$400,"One Time",SF_Output!$L$1:$L$400,"professional service")/N18)))) -> 1 | P18: =IF(O18="",N18,N18*(1-O18)) -> 0 | R18: =IF(B18="","",SUMIFS(SF_Output!$S$1:$S$400,SF_Output!$AC$1:$AC$400,_xlfn.TEXTJOIN(",",TRUE,B18:E18),SF_Output!$Q$1:$Q$400,"yearly")+SUMIFS(SF_Output!$S$1:$S$400,SF_Output!$AC$1:$AC$400,_xlfn.TEXTJOIN(",",TRUE,B18:E18),SF_Output!$Q$1:$Q$400,"quarterly")*4) -> 0 | S18: =IF(OR(B18=0,B18="",G18="hardware",R18=0),"",IF(AF18<>"exclusion",MAX(S$9,-(SUMIFS(SF_Output!$T$1:$T$400,SF_Output!$AC$1:$AC$400,_xlfn.TEXTJOIN(",",TRUE,$B18:$E18),SF_Output!$Q$1:$Q$400,"yearly"))/R18),-((SUMIFS(SF_Output!$T$1:$T$400,SF_Output!$AC$1:$AC$400,_xlfn.TEXTJOIN(",",TRUE,$B18:$E18),SF_Output!$Q$1:$Q$400,"yearly")/R18)))) | T18: =IF(S18="",R18,R18*(1-S18)) -> 0 | V18: {=_xlfn.IFS(B18="","",AND(B18<>"",H18=SF_Output!$Y$2,SUMIFS(SF_Output!$T$1:$T$400,SF_Output!$AC$1:$AC$400,_xlfn.TEXTJOIN(",",TRUE,B18:E18),SF_Output!$Q$1:$Q$400,"monthly")=0),(SUMIFS(SF_Output!$F$1:$F$400,SF_Output!$AC$1:$AC$400,_xlfn.TEXTJOIN(",",TRUE,B18:E18),SF_Output!$Q$1:$Q$400,"monthly")+SUMIFS(SF_Output!$G$1:$G$400,SF_Output!$AC$1:$AC$400,_xlfn.TEXTJOIN(",",TRUE,B18:E18),SF_Output!$Q$1:$Q$400,"monthly"))*H18,AND(B18<>"",H18=SF_Output!$Y$2,SUMIFS(SF_Output!$T$1:$T$400,SF_Output!$AC$1:$AC$400,_xlfn.TEXTJOIN(",",TRUE,B18:E18),SF_Output!$Q$1:$Q$400,"monthly")<>0),SUMIFS(SF_Output!$S$1:$S$400,SF_Output!$AC$1:$AC$400,_xlfn.TEXTJOIN(",",TRUE,B18:E18),SF_Output!$Q$1:$Q$400,"monthly"),AND(B18<>"",H18<>SF_Output!$Y$2),SUMIFS(SF_Output!$S$1:$S$400,SF_Output!$AC$1:$AC$400,_xlfn.TEXTJOIN(",",TRUE,B18:E18),SF_Output!$Q$1:$Q$400,"monthly"))} -> 220 | W18: {=_xlfn.IFS(OR(B18=0,B18="",V18=0),"",AF18<>"exclusion",MAX($W$9,$W$7,(-(SUMIFS(SF_Output!$T$1:$T$400,SF_Output!$AC$1:$AC$400,_xlfn.TEXTJOIN(",",TRUE,$B18:$E18),SF_Output!$Q$1:$Q$400,"monthly"))/V18)),AF18="exclusion",-(SUMIFS(SF_Output!$T$1:$T$400,SF_Output!$AC$1:$AC$400,_xlfn.TEXTJOIN(",",TRUE,$B18:$E18),SF_Output!$Q$1:$Q$400,"monthly"))/V18)} -> 0.25 | X18: {=IFERROR(_xlfn.IFS(V18=0,0,V18="","",W18=0,V18,OR(V18<>0,V18<>""),H18*I18),V18*(1-W18))} -> 165 | Z18: =IFERROR(IF(B18="","",SUMIFS(Billing_Fallout!H:H,Billing_Fallout!N:N,B18)),0) -> 0 | AA18: =IF(Z18="","",AB18-Z18) -> 0 | AB18: =IFERROR(IF(B18="","",SUMIFS(Billing_Fallout!J:J,Billing_Fallout!N:N,B18)),0) -> 0 | AD18: =IFERROR(X18-AB18,"") -> 165 | AF18: =IFERROR(INDEX(H_Tables!$B$1:$B$1500,MATCH(INDEX(SF_Output!$J$1:$J$400,MATCH(B18,SF_Output!$M$1:$M$400,0)),H_Tables!$A$1:$A$1500,0)),"") | AI18: =IF(B18="","",IF(F18="remove","Remove Product",IF(F18="add","Add Product",_xlfn.TEXTJOIN(", ",TRUE,AQ18,AR18,AS18,AT18,AU18,AV18,AW18,AX18,AY18,AZ18,BA18,BB18,BC18)))) | AJ18: =IFERROR(INDEX(SF_Output!AD:AD,MATCH(_xlfn.TEXTJOIN(",",TRUE,B18:E18),SF_Output!AC1:AC400,0)),0.05) -> 20 | AK18: =IF(SUMIFS(SF_Output!$F$1:$F$400,SF_Output!$AC$1:$AC$400,_xlfn.TEXTJOIN(",",TRUE,B18:E18))+SUMIFS(SF_Output!$G$1:$G$400,SF_Output!$AC$1:$AC$400,_xlfn.TEXTJOIN(",",TRUE,B18:E18))=0,"","PAP") | AL18: =LEFT(_xlfn.TEXTJOIN(",",TRUE,B18:E18),80) -> SilverLake Teller Static Training Bank,New,Hosted by JHA,1 | AR18: {=IFERROR(_xlfn.IFS(AND(E18*1=1,F18="Included"),"Change to Included",AND(E18*1=0,F18="Optional"),"Change to Optional",OR(B18="",F18="replaced"),""),"")} | AS18: =IF((OR(NOT(_xlfn.ISFORMULA(J18)),NOT(_xlfn.ISFORMULA(L18)))),"Check License Price Override","") | AT18: =IF(OR(AND(K18=$K$9,K18<>0),NOT(_xlfn.ISFORMULA(K18))),"License Discount "&K18*100&"%","") | AU18: =IF((OR(NOT(_xlfn.ISFORMULA(N18)),NOT(_xlfn.ISFORMULA(P18)))),"Check Install Price Override","") | AV18: =IF(OR(AND(O18=$O$9,O18<>0),NOT(_xlfn.ISFORMULA(O18))),"Install Discount "&O18*100&"%","") | AW18: =IF((OR(NOT(_xlfn.ISFORMULA(R18)),NOT(_xlfn.ISFORMULA(T18)))),"Check Maintenance Price Override","") | AX18: =IF(OR(AND(S18=$S$9,S18<>0),NOT(_xlfn.ISFORMULA(S18))),"Maintenance Discount "&S18*100&"%","") | AY18: =IF((OR(NOT(_xlfn.ISFORMULA(V18)),NOT(_xlfn.ISFORMULA(X18)))),"Check Monthly Price Override","") | AZ18: =IF(OR((AND(W18=$W$9,W18<>0)),(AND(W18=$W$7,W18<>0)),(NOT(_xlfn.ISFORMULA(W18))),AND($W$7+0.2=W18,$W$7<>0)),"Monthly Discount "&W18*100&"%","") | BA18: =IF(NOT(_xlfn.ISFORMULA(H18)),"Check Quantity","") | BB18: =IF(NOT(_xlfn.ISFORMULA(I18)),"Check Unit Price Override","") | BE18: =INDEX(SF_Output!$AA$2:$AA$400,MATCH($B18,SF_Output!$M$2:$M$400,0)) -> 1 | BF18: =INDEX(SF_Output!$AB$2:$AB$400,MATCH($B18,SF_Output!$M$2:$M$400,0)) -> 1
B19: JH Technology Architecture Services | C19: New | D19: Hosted by JHA | E19: 0 | F19: =IF(B19="","",IF(E19*1=0,"Included","Optional")) -> Included | G19: =IF(B19="","",INDEX(SF_Output!$K$1:$K$400,MATCH(B19,SF_Output!$M$1:$M$400,0))) -> SilverLake | H19: {=_xlfn.IFS(B19="","",(SUMIFS(SF_Output!$F$1:$F$400,SF_Output!$AC$1:$AC$400,_xlfn.TEXTJOIN(",",TRUE,B19:E19))+SUMIFS(SF_Output!$G$1:$G$400,SF_Output!$AC$1:$AC$400,_xlfn.TEXTJOIN(",",TRUE,B19:E19)))<>0,SF_Output!$Y$2,INDEX(SF_Output!$F$1:$F$400,MATCH(_xlfn.TEXTJOIN(",",TRUE,B19:E19),SF_Output!$AC$1:$AC$400,0))=0,INDEX(SF_Output!$R$1:$R$400,MATCH(_xlfn.TEXTJOIN(",",TRUE,B19:E19),SF_Output!$AC$1:$AC$400,0)))} -> 1 | I19: =IFERROR(IF(AND(H19>1,H19<>""),ROUND(SUMIFS(SF_Output!$S$1:$S$400,SF_Output!$AC$1:$AC$400,_xlfn.TEXTJOIN(",",TRUE,B19:E19),SF_Output!$Q$1:$Q$400,"monthly")*(1-W19)/H19,4),""),"") | J19: =IF(B19="","",SUMIFS(SF_Output!$S$1:$S$400,SF_Output!$AC$1:$AC$400,_xlfn.TEXTJOIN(",",TRUE,B19:E19),SF_Output!$Q$1:$Q$400,"One Time",SF_Output!$L$1:$L$400,"license fee")+SUMIFS(SF_Output!$S$1:$S$400,SF_Output!$AC$1:$AC$400,_xlfn.TEXTJOIN(",",TRUE,B19:E19),SF_Output!$Q$1:$Q$400,"One Time",SF_Output!$L$1:$L$400,"software license")+SUMIFS(SF_Output!$S$1:$S$400,SF_Output!$AC$1:$AC$400,_xlfn.TEXTJOIN(",",TRUE,B19:E19),SF_Output!$Q$1:$Q$400,"One Time",SF_Output!$L$1:$L$400,"hardware")) -> 0 | K19: =IF(OR(B19=0,B19="",G19="hardware",J19=0),"",IF(AF19<>"exclusion",MAX(K$9,-((SUMIFS(SF_Output!$T$1:$T$400,SF_Output!$AC$1:$AC$400,_xlfn.TEXTJOIN(",",TRUE,$B19:$E19),SF_Output!$Q$1:$Q$400,"One Time",SF_Output!$L$1:$L$400,"license fee")+SUMIFS(SF_Output!$T$1:$T$400,SF_Output!$AC$1:$AC$400,_xlfn.TEXTJOIN(",",TRUE,$B19:$E19),SF_Output!$Q$1:$Q$400,"One Time",SF_Output!$L$1:$L$400,"software license"))/J19)),-((SUMIFS(SF_Output!$T$1:$T$400,SF_Output!$AC$1:$AC$400,_xlfn.TEXTJOIN(",",TRUE,$B19:$E19),SF_Output!$Q$1:$Q$400,"One Time",SF_Output!$L$1:$L$400,"license fee")+SUMIFS(SF_Output!$T$1:$T$400,SF_Output!$AC$1:$AC$400,_xlfn.TEXTJOIN(",",TRUE,$B19:$E19),SF_Output!$Q$1:$Q$400,"One Time",SF_Output!$L$1:$L$400,"software license"))/J19))) | L19: =IF(K19="",J19,J19*(1-K19)) -> 0 | N19: =IF(B19="","",SUMIFS(SF_Output!$S$1:$S$400,SF_Output!$AC$1:$AC$400,_xlfn.TEXTJOIN(",",TRUE,B19:E19),SF_Output!$Q$1:$Q$400,"One Time",SF_Output!$L$1:$L$400,"professional service")) -> 0 | O19: =IF(OR(B19=0,B19="",N19=0),"",IF(AF19<>"exclusion",MAX(O$9,-(SUMIFS(SF_Output!$T$1:$T$400,SF_Output!$AC$1:$AC$400,_xlfn.TEXTJOIN(",",TRUE,$B19:$E19),SF_Output!$Q$1:$Q$400,"One Time",SF_Output!$L$1:$L$400,"professional service"))/N19),-((SUMIFS(SF_Output!$T$1:$T$400,SF_Output!$AC$1:$AC$400,_xlfn.TEXTJOIN(",",TRUE,$B19:$E19),SF_Output!$Q$1:$Q$400,"One Time",SF_Output!$L$1:$L$400,"professional service")/N19)))) | P19: =IF(O19="",N19,N19*(1-O19)) -> 0 | R19: =IF(B19="","",SUMIFS(SF_Output!$S$1:$S$400,SF_Output!$AC$1:$AC$400,_xlfn.TEXTJOIN(",",TRUE,B19:E19),SF_Output!$Q$1:$Q$400,"yearly")+SUMIFS(SF_Output!$S$1:$S$400,SF_Output!$AC$1:$AC$400,_xlfn.TEXTJOIN(",",TRUE,B19:E19),SF_Output!$Q$1:$Q$400,"quarterly")*4) -> 0 | S19: =IF(OR(B19=0,B19="",G19="hardware",R19=0),"",IF(AF19<>"exclusion",MAX(S$9,-(SUMIFS(SF_Output!$T$1:$T$400,SF_Output!$AC$1:$AC$400,_xlfn.TEXTJOIN(",",TRUE,$B19:$E19),SF_Output!$Q$1:$Q$400,"yearly"))/R19),-((SUMIFS(SF_Output!$T$1:$T$400,SF_Output!$AC$1:$AC$400,_xlfn.TEXTJOIN(",",TRUE,$B19:$E19),SF_Output!$Q$1:$Q$400,"yearly")/R19)))) | T19: =IF(S19="",R19,R19*(1-S19)) -> 0 | V19: {=_xlfn.IFS(B19="","",AND(B19<>"",H19=SF_Output!$Y$2,SUMIFS(SF_Output!$T$1:$T$400,SF_Output!$AC$1:$AC$400,_xlfn.TEXTJOIN(",",TRUE,B19:E19),SF_Output!$Q$1:$Q$400,"monthly")=0),(SUMIFS(SF_Output!$F$1:$F$400,SF_Output!$AC$1:$AC$400,_xlfn.TEXTJOIN(",",TRUE,B19:E19),SF_Output!$Q$1:$Q$400,"monthly")+SUMIFS(SF_Output!$G$1:$G$400,SF_Output!$AC$1:$AC$400,_xlfn.TEXTJOIN(",",TRUE,B19:E19),SF_Output!$Q$1:$Q$400,"monthly"))*H19,AND(B19<>"",H19=SF_Output!$Y$2,SUMIFS(SF_Output!$T$1:$T$400,SF_Output!$AC$1:$AC$400,_xlfn.TEXTJOIN(",",TRUE,B19:E19),SF_Output!$Q$1:$Q$400,"monthly")<>0),SUMIFS(SF_Output!$S$1:$S$400,SF_Output!$AC$1:$AC$400,_xlfn.TEXTJOIN(",",TRUE,B19:E19),SF_Output!$Q$1:$Q$400,"monthly"),AND(B19<>"",H19<>SF_Output!$Y$2),SUMIFS(SF_Output!$S$1:$S$400,SF_Output!$AC$1:$AC$400,_xlfn.TEXTJOIN(",",TRUE,B19:E19),SF_Output!$Q$1:$Q$400,"monthly"))} -> 0 | W19: {=_xlfn.IFS(OR(B19=0,B19="",V19=0),"",AF19<>"exclusion",MAX($W$9,$W$7,(-(SUMIFS(SF_Output!$T$1:$T$400,SF_Output!$AC$1:$AC$400,_xlfn.TEXTJOIN(",",TRUE,$B19:$E19),SF_Output!$Q$1:$Q$400,"monthly"))/V19)),AF19="exclusion",-(SUMIFS(SF_Output!$T$1:$T$400,SF_Output!$AC$1:$AC$400,_xlfn.TEXTJOIN(",",TRUE,$B19:$E19),SF_Output!$Q$1:$Q$400,"monthly"))/V19)} | X19: {=IFERROR(_xlfn.IFS(V19=0,0,V19="","",W19=0,V19,OR(V19<>0,V19<>""),H19*I19),V19*(1-W19))} -> 0 | Z19: =IFERROR(IF(B19="","",SUMIFS(Billing_Fallout!H:H,Billing_Fallout!N:N,B19)),0) -> 0 | AA19: =IF(Z19="","",AB19-Z19) -> 0 | AB19: =IFERROR(IF(B19="","",SUMIFS(Billing_Fallout!J:J,Billing_Fallout!N:N,B19)),0) -> 0 | AD19: =IFERROR(X19-AB19,"") -> 0 | AF19: =IFERROR(INDEX(H_Tables!$B$1:$B$1500,MATCH(INDEX(SF_Output!$J$1:$J$400,MATCH(B19,SF_Output!$M$1:$M$400,0)),H_Tables!$A$1:$A$1500,0)),"") | AI19: =IF(B19="","",IF(F19="remove","Remove Product",IF(F19="add","Add Product",_xlfn.TEXTJOIN(", ",TRUE,AQ19,AR19,AS19,AT19,AU19,AV19,AW19,AX19,AY19,AZ19,BA19,BB19,BC19)))) | AJ19: =IFERROR(INDEX(SF_Output!AD:AD,MATCH(_xlfn.TEXTJOIN(",",TRUE,B19:E19),SF_Output!AC1:AC400,0)),0.05) -> 23 | AK19: =IF(SUMIFS(SF_Output!$F$1:$F$400,SF_Output!$AC$1:$AC$400,_xlfn.TEXTJOIN(",",TRUE,B19:E19))+SUMIFS(SF_Output!$G$1:$G$400,SF_Output!$AC$1:$AC$400,_xlfn.TEXTJOIN(",",TRUE,B19:E19))=0,"","PAP") | AL19: =LEFT(_xlfn.TEXTJOIN(",",TRUE,B19:E19),80) -> JH Technology Architecture Services,New,Hosted by JHA,0 | AR19: {=IFERROR(_xlfn.IFS(AND(E19*1=1,F19="Included"),"Change to Included",AND(E19*1=0,F19="Optional"),"Change to Optional",OR(B19="",F19="replaced"),""),"")} | AS19: =IF((OR(NOT(_xlfn.ISFORMULA(J19)),NOT(_xlfn.ISFORMULA(L19)))),"Check License Price Override","") | AT19: =IF(OR(AND(K19=$K$9,K19<>0),NOT(_xlfn.ISFORMULA(K19))),"License Discount "&K19*100&"%","") | AU19: =IF((OR(NOT(_xlfn.ISFORMULA(N19)),NOT(_xlfn.ISFORMULA(P19)))),"Check Install Price Override","") | AV19: =IF(OR(AND(O19=$O$9,O19<>0),NOT(_xlfn.ISFORMULA(O19))),"Install Discount "&O19*100&"%","") | AW19: =IF((OR(NOT(_xlfn.ISFORMULA(R19)),NOT(_xlfn.ISFORMULA(T19)))),"Check Maintenance Price Override","") | AX19: =IF(OR(AND(S19=$S$9,S19<>0),NOT(_xlfn.ISFORMULA(S19))),"Maintenance Discount "&S19*100&"%","") | AY19: =IF((OR(NOT(_xlfn.ISFORMULA(V19)),NOT(_xlfn.ISFORMULA(X19)))),"Check Monthly Price Override","") | AZ19: =IF(OR((AND(W19=$W$9,W19<>0)),(AND(W19=$W$7,W19<>0)),(NOT(_xlfn.ISFORMULA(W19))),AND($W$7+0.2=W19,$W$7<>0)),"Monthly Discount "&W19*100&"%","") | BA19: =IF(NOT(_xlfn.ISFORMULA(H19)),"Check Quantity","") | BB19: =IF(NOT(_xlfn.ISFORMULA(I19)),"Check Unit Price Override","") | BE19: =INDEX(SF_Output!$AA$2:$AA$400,MATCH($B19,SF_Output!$M$2:$M$400,0)) -> 1 | BF19: =INDEX(SF_Output!$AB$2:$AB$400,MATCH($B19,SF_Output!$M$2:$M$400,0)) -> 1
B20: JHMenu Express | C20: New | D20: On Premise License | E20: 0 | F20: =IF(B20="","",IF(E20*1=0,"Included","Optional")) -> Included | G20: =IF(B20="","",INDEX(SF_Output!$K$1:$K$400,MATCH(B20,SF_Output!$M$1:$M$400,0))) -> SilverLake | H20: {=_xlfn.IFS(B20="","",(SUMIFS(SF_Output!$F$1:$F$400,SF_Output!$AC$1:$AC$400,_xlfn.TEXTJOIN(",",TRUE,B20:E20))+SUMIFS(SF_Output!$G$1:$G$400,SF_Output!$AC$1:$AC$400,_xlfn.TEXTJOIN(",",TRUE,B20:E20)))<>0,SF_Output!$Y$2,INDEX(SF_Output!$F$1:$F$400,MATCH(_xlfn.TEXTJOIN(",",TRUE,B20:E20),SF_Output!$AC$1:$AC$400,0))=0,INDEX(SF_Output!$R$1:$R$400,MATCH(_xlfn.TEXTJOIN(",",TRUE,B20:E20),SF_Output!$AC$1:$AC$400,0)))} -> 1 | I20: =IFERROR(IF(AND(H20>1,H20<>""),ROUND(SUMIFS(SF_Output!$S$1:$S$400,SF_Output!$AC$1:$AC$400,_xlfn.TEXTJOIN(",",TRUE,B20:E20),SF_Output!$Q$1:$Q$400,"monthly")*(1-W20)/H20,4),""),"") | J20: =IF(B20="","",SUMIFS(SF_Output!$S$1:$S$400,SF_Output!$AC$1:$AC$400,_xlfn.TEXTJOIN(",",TRUE,B20:E20),SF_Output!$Q$1:$Q$400,"One Time",SF_Output!$L$1:$L$400,"license fee")+SUMIFS(SF_Output!$S$1:$S$400,SF_Output!$AC$1:$AC$400,_xlfn.TEXTJOIN(",",TRUE,B20:E20),SF_Output!$Q$1:$Q$400,"One Time",SF_Output!$L$1:$L$400,"software license")+SUMIFS(SF_Output!$S$1:$S$400,SF_Output!$AC$1:$AC$400,_xlfn.TEXTJOIN(",",TRUE,B20:E20),SF_Output!$Q$1:$Q$400,"One Time",SF_Output!$L$1:$L$400,"hardware")) -> 9000 | K20: =IF(OR(B20=0,B20="",G20="hardware",J20=0),"",IF(AF20<>"exclusion",MAX(K$9,-((SUMIFS(SF_Output!$T$1:$T$400,SF_Output!$AC$1:$AC$400,_xlfn.TEXTJOIN(",",TRUE,$B20:$E20),SF_Output!$Q$1:$Q$400,"One Time",SF_Output!$L$1:$L$400,"license fee")+SUMIFS(SF_Output!$T$1:$T$400,SF_Output!$AC$1:$AC$400,_xlfn.TEXTJOIN(",",TRUE,$B20:$E20),SF_Output!$Q$1:$Q$400,"One Time",SF_Output!$L$1:$L$400,"software license"))/J20)),-((SUMIFS(SF_Output!$T$1:$T$400,SF_Output!$AC$1:$AC$400,_xlfn.TEXTJOIN(",",TRUE,$B20:$E20),SF_Output!$Q$1:$Q$400,"One Time",SF_Output!$L$1:$L$400,"license fee")+SUMIFS(SF_Output!$T$1:$T$400,SF_Output!$AC$1:$AC$400,_xlfn.TEXTJOIN(",",TRUE,$B20:$E20),SF_Output!$Q$1:$Q$400,"One Time",SF_Output!$L$1:$L$400,"software license"))/J20))) -> 0 | L20: =IF(K20="",J20,J20*(1-K20)) -> 9000 | N20: =IF(B20="","",SUMIFS(SF_Output!$S$1:$S$400,SF_Output!$AC$1:$AC$400,_xlfn.TEXTJOIN(",",TRUE,B20:E20),SF_Output!$Q$1:$Q$400,"One Time",SF_Output!$L$1:$L$400,"professional service")) -> 0 | O20: =IF(OR(B20=0,B20="",N20=0),"",IF(AF20<>"exclusion",MAX(O$9,-(SUMIFS(SF_Output!$T$1:$T$400,SF_Output!$AC$1:$AC$400,_xlfn.TEXTJOIN(",",TRUE,$B20:$E20),SF_Output!$Q$1:$Q$400,"One Time",SF_Output!$L$1:$L$400,"professional service"))/N20),-((SUMIFS(SF_Output!$T$1:$T$400,SF_Output!$AC$1:$AC$400,_xlfn.TEXTJOIN(",",TRUE,$B20:$E20),SF_Output!$Q$1:$Q$400,"One Time",SF_Output!$L$1:$L$400,"professional service")/N20)))) | P20: =IF(O20="",N20,N20*(1-O20)) -> 0 | R20: =IF(B20="","",SUMIFS(SF_Output!$S$1:$S$400,SF_Output!$AC$1:$AC$400,_xlfn.TEXTJOIN(",",TRUE,B20:E20),SF_Output!$Q$1:$Q$400,"yearly")+SUMIFS(SF_Output!$S$1:$S$400,SF_Output!$AC$1:$AC$400,_xlfn.TEXTJOIN(",",TRUE,B20:E20),SF_Output!$Q$1:$Q$400,"quarterly")*4) -> 0 | S20: =IF(OR(B20=0,B20="",G20="hardware",R20=0),"",IF(AF20<>"exclusion",MAX(S$9,-(SUMIFS(SF_Output!$T$1:$T$400,SF_Output!$AC$1:$AC$400,_xlfn.TEXTJOIN(",",TRUE,$B20:$E20),SF_Output!$Q$1:$Q$400,"yearly"))/R20),-((SUMIFS(SF_Output!$T$1:$T$400,SF_Output!$AC$1:$AC$400,_xlfn.TEXTJOIN(",",TRUE,$B20:$E20),SF_Output!$Q$1:$Q$400,"yearly")/R20)))) | T20: =IF(S20="",R20,R20*(1-S20)) -> 0 | V20: {=_xlfn.IFS(B20="","",AND(B20<>"",H20=SF_Output!$Y$2,SUMIFS(SF_Output!$T$1:$T$400,SF_Output!$AC$1:$AC$400,_xlfn.TEXTJOIN(",",TRUE,B20:E20),SF_Output!$Q$1:$Q$400,"monthly")=0),(SUMIFS(SF_Output!$F$1:$F$400,SF_Output!$AC$1:$AC$400,_xlfn.TEXTJOIN(",",TRUE,B20:E20),SF_Output!$Q$1:$Q$400,"monthly")+SUMIFS(SF_Output!$G$1:$G$400,SF_Output!$AC$1:$AC$400,_xlfn.TEXTJOIN(",",TRUE,B20:E20),SF_Output!$Q$1:$Q$400,"monthly"))*H20,AND(B20<>"",H20=SF_Output!$Y$2,SUMIFS(SF_Output!$T$1:$T$400,SF_Output!$AC$1:$AC$400,_xlfn.TEXTJOIN(",",TRUE,B20:E20),SF_Output!$Q$1:$Q$400,"monthly")<>0),SUMIFS(SF_Output!$S$1:$S$400,SF_Output!$AC$1:$AC$400,_xlfn.TEXTJOIN(",",TRUE,B20:E20),SF_Output!$Q$1:$Q$400,"monthly"),AND(B20<>"",H20<>SF_Output!$Y$2),SUMIFS(SF_Output!$S$1:$S$400,SF_Output!$AC$1:$AC$400,_xlfn.TEXTJOIN(",",TRUE,B20:E20),SF_Output!$Q$1:$Q$400,"monthly"))} -> 0 | W20: {=_xlfn.IFS(OR(B20=0,B20="",V20=0),"",AF20<>"exclusion",MAX($W$9,$W$7,(-(SUMIFS(SF_Output!$T$1:$T$400,SF_Output!$AC$1:$AC$400,_xlfn.TEXTJOIN(",",TRUE,$B20:$E20),SF_Output!$Q$1:$Q$400,"monthly"))/V20)),AF20="exclusion",-(SUMIFS(SF_Output!$T$1:$T$400,SF_Output!$AC$1:$AC$400,_xlfn.TEXTJOIN(",",TRUE,$B20:$E20),SF_Output!$Q$1:$Q$400,"monthly"))/V20)} | X20: {=IFERROR(_xlfn.IFS(V20=0,0,V20="","",W20=0,V20,OR(V20<>0,V20<>""),H20*I20),V20*(1-W20))} -> 0 | Z20: =IFERROR(IF(B20="","",SUMIFS(Billing_Fallout!H:H,Billing_Fallout!N:N,B20)),0) -> 0 | AA20: =IF(Z20="","",AB20-Z20) -> 0 | AB20: =IFERROR(IF(B20="","",SUMIFS(Billing_Fallout!J:J,Billing_Fallout!N:N,B20)),0) -> 0 | AD20: =IFERROR(X20-AB20,"") -> 0 | AF20: =IFERROR(INDEX(H_Tables!$B$1:$B$1500,MATCH(INDEX(SF_Output!$J$1:$J$400,MATCH(B20,SF_Output!$M$1:$M$400,0)),H_Tables!$A$1:$A$1500,0)),"") | AI20: =IF(B20="","",IF(F20="remove","Remove Product",IF(F20="add","Add Product",_xlfn.TEXTJOIN(", ",TRUE,AQ20,AR20,AS20,AT20,AU20,AV20,AW20,AX20,AY20,AZ20,BA20,BB20,BC20)))) | AJ20: =IFERROR(INDEX(SF_Output!AD:AD,MATCH(_xlfn.TEXTJOIN(",",TRUE,B20:E20),SF_Output!AC1:AC400,0)),0.05) -> 24 | AK20: =IF(SUMIFS(SF_Output!$F$1:$F$400,SF_Output!$AC$1:$AC$400,_xlfn.TEXTJOIN(",",TRUE,B20:E20))+SUMIFS(SF_Output!$G$1:$G$400,SF_Output!$AC$1:$AC$400,_xlfn.TEXTJOIN(",",TRUE,B20:E20))=0,"","PAP") | AL20: =LEFT(_xlfn.TEXTJOIN(",",TRUE,B20:E20),80) -> JHMenu Express,New,On Premise License,0 | AR20: {=IFERROR(_xlfn.IFS(AND(E20*1=1,F20="Included"),"Change to Included",AND(E20*1=0,F20="Optional"),"Change to Optional",OR(B20="",F20="replaced"),""),"")} | AS20: =IF((OR(NOT(_xlfn.ISFORMULA(J20)),NOT(_xlfn.ISFORMULA(L20)))),"Check License Price Override","") | AT20: =IF(OR(AND(K20=$K$9,K20<>0),NOT(_xlfn.ISFORMULA(K20))),"License Discount "&K20*100&"%","") | AU20: =IF((OR(NOT(_xlfn.ISFORMULA(N20)),NOT(_xlfn.ISFORMULA(P20)))),"Check Install Price Override","") | AV20: =IF(OR(AND(O20=$O$9,O20<>0),NOT(_xlfn.ISFORMULA(O20))),"Install Discount "&O20*100&"%","") | AW20: =IF((OR(NOT(_xlfn.ISFORMULA(R20)),NOT(_xlfn.ISFORMULA(T20)))),"Check Maintenance Price Override","") | AX20: =IF(OR(AND(S20=$S$9,S20<>0),NOT(_xlfn.ISFORMULA(S20))),"Maintenance Discount "&S20*100&"%","") | AY20: =IF((OR(NOT(_xlfn.ISFORMULA(V20)),NOT(_xlfn.ISFORMULA(X20)))),"Check Monthly Price Override","") | AZ20: =IF(OR((AND(W20=$W$9,W20<>0)),(AND(W20=$W$7,W20<>0)),(NOT(_xlfn.ISFORMULA(W20))),AND($W$7+0.2=W20,$W$7<>0)),"Monthly Discount "&W20*100&"%","") | BA20: =IF(NOT(_xlfn.ISFORMULA(H20)),"Check Quantity","") | BB20: =IF(NOT(_xlfn.ISFORMULA(I20)),"Check Unit Price Override","") | BE20: =INDEX(SF_Output!$AA$2:$AA$400,MATCH($B20,SF_Output!$M$2:$M$400,0)) -> 1 | BF20: =INDEX(SF_Output!$AB$2:$AB$400,MATCH($B20,SF_Output!$M$2:$M$400,0)) -> 1
B21: Daily File Transfer Integration IntraFi | C21: New | D21: Hosted by JHA | E21: 0 | F21: =IF(B21="","",IF(E21*1=0,"Included","Optional")) -> Included | G21: =IF(B21="","",INDEX(SF_Output!$K$1:$K$400,MATCH(B21,SF_Output!$M$1:$M$400,0))) -> SilverLake | H21: {=_xlfn.IFS(B21="","",(SUMIFS(SF_Output!$F$1:$F$400,SF_Output!$AC$1:$AC$400,_xlfn.TEXTJOIN(",",TRUE,B21:E21))+SUMIFS(SF_Output!$G$1:$G$400,SF_Output!$AC$1:$AC$400,_xlfn.TEXTJOIN(",",TRUE,B21:E21)))<>0,SF_Output!$Y$2,INDEX(SF_Output!$F$1:$F$400,MATCH(_xlfn.TEXTJOIN(",",TRUE,B21:E21),SF_Output!$AC$1:$AC$400,0))=0,INDEX(SF_Output!$R$1:$R$400,MATCH(_xlfn.TEXTJOIN(",",TRUE,B21:E21),SF_Output!$AC$1:$AC$400,0)))} -> 1 | I21: =IFERROR(IF(AND(H21>1,H21<>""),ROUND(SUMIFS(SF_Output!$S$1:$S$400,SF_Output!$AC$1:$AC$400,_xlfn.TEXTJOIN(",",TRUE,B21:E21),SF_Output!$Q$1:$Q$400,"monthly")*(1-W21)/H21,4),""),"") | J21: =IF(B21="","",SUMIFS(SF_Output!$S$1:$S$400,SF_Output!$AC$1:$AC$400,_xlfn.TEXTJOIN(",",TRUE,B21:E21),SF_Output!$Q$1:$Q$400,"One Time",SF_Output!$L$1:$L$400,"license fee")+SUMIFS(SF_Output!$S$1:$S$400,SF_Output!$AC$1:$AC$400,_xlfn.TEXTJOIN(",",TRUE,B21:E21),SF_Output!$Q$1:$Q$400,"One Time",SF_Output!$L$1:$L$400,"software license")+SUMIFS(SF_Output!$S$1:$S$400,SF_Output!$AC$1:$AC$400,_xlfn.TEXTJOIN(",",TRUE,B21:E21),SF_Output!$Q$1:$Q$400,"One Time",SF_Output!$L$1:$L$400,"hardware")) -> 0 | K21: =IF(OR(B21=0,B21="",G21="hardware",J21=0),"",IF(AF21<>"exclusion",MAX(K$9,-((SUMIFS(SF_Output!$T$1:$T$400,SF_Output!$AC$1:$AC$400,_xlfn.TEXTJOIN(",",TRUE,$B21:$E21),SF_Output!$Q$1:$Q$400,"One Time",SF_Output!$L$1:$L$400,"license fee")+SUMIFS(SF_Output!$T$1:$T$400,SF_Output!$AC$1:$AC$400,_xlfn.TEXTJOIN(",",TRUE,$B21:$E21),SF_Output!$Q$1:$Q$400,"One Time",SF_Output!$L$1:$L$400,"software license"))/J21)),-((SUMIFS(SF_Output!$T$1:$T$400,SF_Output!$AC$1:$AC$400,_xlfn.TEXTJOIN(",",TRUE,$B21:$E21),SF_Output!$Q$1:$Q$400,"One Time",SF_Output!$L$1:$L$400,"license fee")+SUMIFS(SF_Output!$T$1:$T$400,SF_Output!$AC$1:$AC$400,_xlfn.TEXTJOIN(",",TRUE,$B21:$E21),SF_Output!$Q$1:$Q$400,"One Time",SF_Output!$L$1:$L$400,"software license"))/J21))) | L21: =IF(K21="",J21,J21*(1-K21)) -> 0 | N21: =IF(B21="","",SUMIFS(SF_Output!$S$1:$S$400,SF_Output!$AC$1:$AC$400,_xlfn.TEXTJOIN(",",TRUE,B21:E21),SF_Output!$Q$1:$Q$400,"One Time",SF_Output!$L$1:$L$400,"professional service")) -> 2500 | O21: =IF(OR(B21=0,B21="",N21=0),"",IF(AF21<>"exclusion",MAX(O$9,-(SUMIFS(SF_Output!$T$1:$T$400,SF_Output!$AC$1:$AC$400,_xlfn.TEXTJOIN(",",TRUE,$B21:$E21),SF_Output!$Q$1:$Q$400,"One Time",SF_Output!$L$1:$L$400,"professional service"))/N21),-((SUMIFS(SF_Output!$T$1:$T$400,SF_Output!$AC$1:$AC$400,_xlfn.TEXTJOIN(",",TRUE,$B21:$E21),SF_Output!$Q$1:$Q$400,"One Time",SF_Output!$L$1:$L$400,"professional service")/N21)))) -> 1 | P21: =IF(O21="",N21,N21*(1-O21)) -> 0 | R21: =IF(B21="","",SUMIFS(SF_Output!$S$1:$S$400,SF_Output!$AC$1:$AC$400,_xlfn.TEXTJOIN(",",TRUE,B21:E21),SF_Output!$Q$1:$Q$400,"yearly")+SUMIFS(SF_Output!$S$1:$S$400,SF_Output!$AC$1:$AC$400,_xlfn.TEXTJOIN(",",TRUE,B21:E21),SF_Output!$Q$1:$Q$400,"quarterly")*4) -> 0 | S21: =IF(OR(B21=0,B21="",G21="hardware",R21=0),"",IF(AF21<>"exclusion",MAX(S$9,-(SUMIFS(SF_Output!$T$1:$T$400,SF_Output!$AC$1:$AC$400,_xlfn.TEXTJOIN(",",TRUE,$B21:$E21),SF_Output!$Q$1:$Q$400,"yearly"))/R21),-((SUMIFS(SF_Output!$T$1:$T$400,SF_Output!$AC$1:$AC$400,_xlfn.TEXTJOIN(",",TRUE,$B21:$E21),SF_Output!$Q$1:$Q$400,"yearly")/R21)))) | T21: =IF(S21="",R21,R21*(1-S21)) -> 0 | V21: {=_xlfn.IFS(B21="","",AND(B21<>"",H21=SF_Output!$Y$2,SUMIFS(SF_Output!$T$1:$T$400,SF_Output!$AC$1:$AC$400,_xlfn.TEXTJOIN(",",TRUE,B21:E21),SF_Output!$Q$1:$Q$400,"monthly")=0),(SUMIFS(SF_Output!$F$1:$F$400,SF_Output!$AC$1:$AC$400,_xlfn.TEXTJOIN(",",TRUE,B21:E21),SF_Output!$Q$1:$Q$400,"monthly")+SUMIFS(SF_Output!$G$1:$G$400,SF_Output!$AC$1:$AC$400,_xlfn.TEXTJOIN(",",TRUE,B21:E21),SF_Output!$Q$1:$Q$400,"monthly"))*H21,AND(B21<>"",H21=SF_Output!$Y$2,SUMIFS(SF_Output!$T$1:$T$400,SF_Output!$AC$1:$AC$400,_xlfn.TEXTJOIN(",",TRUE,B21:E21),SF_Output!$Q$1:$Q$400,"monthly")<>0),SUMIFS(SF_Output!$S$1:$S$400,SF_Output!$AC$1:$AC$400,_xlfn.TEXTJOIN(",",TRUE,B21:E21),SF_Output!$Q$1:$Q$400,"monthly"),AND(B21<>"",H21<>SF_Output!$Y$2),SUMIFS(SF_Output!$S$1:$S$400,SF_Output!$AC$1:$AC$400,_xlfn.TEXTJOIN(",",TRUE,B21:E21),SF_Output!$Q$1:$Q$400,"monthly"))} -> 300 | W21: {=_xlfn.IFS(OR(B21=0,B21="",V21=0),"",AF21<>"exclusion",MAX($W$9,$W$7,(-(SUMIFS(SF_Output!$T$1:$T$400,SF_Output!$AC$1:$AC$400,_xlfn.TEXTJOIN(",",TRUE,$B21:$E21),SF_Output!$Q$1:$Q$400,"monthly"))/V21)),AF21="exclusion",-(SUMIFS(SF_Output!$T$1:$T$400,SF_Output!$AC$1:$AC$400,_xlfn.TEXTJOIN(",",TRUE,$B21:$E21),SF_Output!$Q$1:$Q$400,"monthly"))/V21)} -> 0.25 | X21: {=IFERROR(_xlfn.IFS(V21=0,0,V21="","",W21=0,V21,OR(V21<>0,V21<>""),H21*I21),V21*(1-W21))} -> 225 | Z21: =IFERROR(IF(B21="","",SUMIFS(Billing_Fallout!H:H,Billing_Fallout!N:N,B21)),0) -> 0 | AA21: =IF(Z21="","",AB21-Z21) -> 0 | AB21: =IFERROR(IF(B21="","",SUMIFS(Billing_Fallout!J:J,Billing_Fallout!N:N,B21)),0) -> 0 | AD21: =IFERROR(X21-AB21,"") -> 225 | AF21: =IFERROR(INDEX(H_Tables!$B$1:$B$1500,MATCH(INDEX(SF_Output!$J$1:$J$400,MATCH(B21,SF_Output!$M$1:$M$400,0)),H_Tables!$A$1:$A$1500,0)),"") -> Exclusion | AI21: =IF(B21="","",IF(F21="remove","Remove Product",IF(F21="add","Add Product",_xlfn.TEXTJOIN(", ",TRUE,AQ21,AR21,AS21,AT21,AU21,AV21,AW21,AX21,AY21,AZ21,BA21,BB21,BC21)))) | AJ21: =IFERROR(INDEX(SF_Output!AD:AD,MATCH(_xlfn.TEXTJOIN(",",TRUE,B21:E21),SF_Output!AC1:AC400,0)),0.05) -> 27 | AK21: =IF(SUMIFS(SF_Output!$F$1:$F$400,SF_Output!$AC$1:$AC$400,_xlfn.TEXTJOIN(",",TRUE,B21:E21))+SUMIFS(SF_Output!$G$1:$G$400,SF_Output!$AC$1:$AC$400,_xlfn.TEXTJOIN(",",TRUE,B21:E21))=0,"","PAP") | AL21: =LEFT(_xlfn.TEXTJOIN(",",TRUE,B21:E21),80) -> Daily File Transfer Integration IntraFi,New,Hosted by JHA,0 | AR21: {=IFERROR(_xlfn.IFS(AND(E21*1=1,F21="Included"),"Change to Included",AND(E21*1=0,F21="Optional"),"Change to Optional",OR(B21="",F21="replaced"),""),"")} | AS21: =IF((OR(NOT(_xlfn.ISFORMULA(J21)),NOT(_xlfn.ISFORMULA(L21)))),"Check License Price Override","") | AT21: =IF(OR(AND(K21=$K$9,K21<>0),NOT(_xlfn.ISFORMULA(K21))),"License Discount "&K21*100&"%","") | AU21: =IF((OR(NOT(_xlfn.ISFORMULA(N21)),NOT(_xlfn.ISFORMULA(P21)))),"Check Install Price Override","") | AV21: =IF(OR(AND(O21=$O$9,O21<>0),NOT(_xlfn.ISFORMULA(O21))),"Install Discount "&O21*100&"%","") | AW21: =IF((OR(NOT(_xlfn.ISFORMULA(R21)),NOT(_xlfn.ISFORMULA(T21)))),"Check Maintenance Price Override","") | AX21: =IF(OR(AND(S21=$S$9,S21<>0),NOT(_xlfn.ISFORMULA(S21))),"Maintenance Discount "&S21*100&"%","") | AY21: =IF((OR(NOT(_xlfn.ISFORMULA(V21)),NOT(_xlfn.ISFORMULA(X21)))),"Check Monthly Price Override","") | AZ21: =IF(OR((AND(W21=$W$9,W21<>0)),(AND(W21=$W$7,W21<>0)),(NOT(_xlfn.ISFORMULA(W21))),AND($W$7+0.2=W21,$W$7<>0)),"Monthly Discount "&W21*100&"%","") | BA21: =IF(NOT(_xlfn.ISFORMULA(H21)),"Check Quantity","") | BB21: =IF(NOT(_xlfn.ISFORMULA(I21)),"Check Unit Price Override","") | BE21: =INDEX(SF_Output!$AA$2:$AA$400,MATCH($B21,SF_Output!$M$2:$M$400,0)) -> 1 | BF21: =INDEX(SF_Output!$AB$2:$AB$400,MATCH($B21,SF_Output!$M$2:$M$400,0)) -> 1
B22: Hosted Xperience | C22: New | D22: Hosted by JHA | E22: 0 | F22: =IF(B22="","",IF(E22*1=0,"Included","Optional")) -> Included | G22: =IF(B22="","",INDEX(SF_Output!$K$1:$K$400,MATCH(B22,SF_Output!$M$1:$M$400,0))) -> Xperience | H22: {=_xlfn.IFS(B22="","",(SUMIFS(SF_Output!$F$1:$F$400,SF_Output!$AC$1:$AC$400,_xlfn.TEXTJOIN(",",TRUE,B22:E22))+SUMIFS(SF_Output!$G$1:$G$400,SF_Output!$AC$1:$AC$400,_xlfn.TEXTJOIN(",",TRUE,B22:E22)))<>0,SF_Output!$Y$2,INDEX(SF_Output!$F$1:$F$400,MATCH(_xlfn.TEXTJOIN(",",TRUE,B22:E22),SF_Output!$AC$1:$AC$400,0))=0,INDEX(SF_Output!$R$1:$R$400,MATCH(_xlfn.TEXTJOIN(",",TRUE,B22:E22),SF_Output!$AC$1:$AC$400,0)))} -> 5000 | I22: =IFERROR(IF(AND(H22>1,H22<>""),ROUND(SUMIFS(SF_Output!$S$1:$S$400,SF_Output!$AC$1:$AC$400,_xlfn.TEXTJOIN(",",TRUE,B22:E22),SF_Output!$Q$1:$Q$400,"monthly")*(1-W22)/H22,4),""),"") -> 0.0225 | J22: =IF(B22="","",SUMIFS(SF_Output!$S$1:$S$400,SF_Output!$AC$1:$AC$400,_xlfn.TEXTJOIN(",",TRUE,B22:E22),SF_Output!$Q$1:$Q$400,"One Time",SF_Output!$L$1:$L$400,"license fee")+SUMIFS(SF_Output!$S$1:$S$400,SF_Output!$AC$1:$AC$400,_xlfn.TEXTJOIN(",",TRUE,B22:E22),SF_Output!$Q$1:$Q$400,"One Time",SF_Output!$L$1:$L$400,"software license")+SUMIFS(SF_Output!$S$1:$S$400,SF_Output!$AC$1:$AC$400,_xlfn.TEXTJOIN(",",TRUE,B22:E22),SF_Output!$Q$1:$Q$400,"One Time",SF_Output!$L$1:$L$400,"hardware")) -> 0 | K22: =IF(OR(B22=0,B22="",G22="hardware",J22=0),"",IF(AF22<>"exclusion",MAX(K$9,-((SUMIFS(SF_Output!$T$1:$T$400,SF_Output!$AC$1:$AC$400,_xlfn.TEXTJOIN(",",TRUE,$B22:$E22),SF_Output!$Q$1:$Q$400,"One Time",SF_Output!$L$1:$L$400,"license fee")+SUMIFS(SF_Output!$T$1:$T$400,SF_Output!$AC$1:$AC$400,_xlfn.TEXTJOIN(",",TRUE,$B22:$E22),SF_Output!$Q$1:$Q$400,"One Time",SF_Output!$L$1:$L$400,"software license"))/J22)),-((SUMIFS(SF_Output!$T$1:$T$400,SF_Output!$AC$1:$AC$400,_xlfn.TEXTJOIN(",",TRUE,$B22:$E22),SF_Output!$Q$1:$Q$400,"One Time",SF_Output!$L$1:$L$400,"license fee")+SUMIFS(SF_Output!$T$1:$T$400,SF_Output!$AC$1:$AC$400,_xlfn.TEXTJOIN(",",TRUE,$B22:$E22),SF_Output!$Q$1:$Q$400,"One Time",SF_Output!$L$1:$L$400,"software license"))/J22))) | L22: =IF(K22="",J22,J22*(1-K22)) -> 0 | N22: =IF(B22="","",SUMIFS(SF_Output!$S$1:$S$400,SF_Output!$AC$1:$AC$400,_xlfn.TEXTJOIN(",",TRUE,B22:E22),SF_Output!$Q$1:$Q$400,"One Time",SF_Output!$L$1:$L$400,"professional service")) -> 0 | O22: =IF(OR(B22=0,B22="",N22=0),"",IF(AF22<>"exclusion",MAX(O$9,-(SUMIFS(SF_Output!$T$1:$T$400,SF_Output!$AC$1:$AC$400,_xlfn.TEXTJOIN(",",TRUE,$B22:$E22),SF_Output!$Q$1:$Q$400,"One Time",SF_Output!$L$1:$L$400,"professional service"))/N22),-((SUMIFS(SF_Output!$T$1:$T$400,SF_Output!$AC$1:$AC$400,_xlfn.TEXTJOIN(",",TRUE,$B22:$E22),SF_Output!$Q$1:$Q$400,"One Time",SF_Output!$L$1:$L$400,"professional service")/N22)))) | P22: =IF(O22="",N22,N22*(1-O22)) -> 0 | R22: =IF(B22="","",SUMIFS(SF_Output!$S$1:$S$400,SF_Output!$AC$1:$AC$400,_xlfn.TEXTJOIN(",",TRUE,B22:E22),SF_Output!$Q$1:$Q$400,"yearly")+SUMIFS(SF_Output!$S$1:$S$400,SF_Output!$AC$1:$AC$400,_xlfn.TEXTJOIN(",",TRUE,B22:E22),SF_Output!$Q$1:$Q$400,"quarterly")*4) -> 0 | S22: =IF(OR(B22=0,B22="",G22="hardware",R22=0),"",IF(AF22<>"exclusion",MAX(S$9,-(SUMIFS(SF_Output!$T$1:$T$400,SF_Output!$AC$1:$AC$400,_xlfn.TEXTJOIN(",",TRUE,$B22:$E22),SF_Output!$Q$1:$Q$400,"yearly"))/R22),-((SUMIFS(SF_Output!$T$1:$T$400,SF_Output!$AC$1:$AC$400,_xlfn.TEXTJOIN(",",TRUE,$B22:$E22),SF_Output!$Q$1:$Q$400,"yearly")/R22)))) | T22: =IF(S22="",R22,R22*(1-S22)) -> 0 | V22: {=_xlfn.IFS(B22="","",AND(B22<>"",H22=SF_Output!$Y$2,SUMIFS(SF_Output!$T$1:$T$400,SF_Output!$AC$1:$AC$400,_xlfn.TEXTJOIN(",",TRUE,B22:E22),SF_Output!$Q$1:$Q$400,"monthly")=0),(SUMIFS(SF_Output!$F$1:$F$400,SF_Output!$AC$1:$AC$400,_xlfn.TEXTJOIN(",",TRUE,B22:E22),SF_Output!$Q$1:$Q$400,"monthly")+SUMIFS(SF_Output!$G$1:$G$400,SF_Output!$AC$1:$AC$400,_xlfn.TEXTJOIN(",",TRUE,B22:E22),SF_Output!$Q$1:$Q$400,"monthly"))*H22,AND(B22<>"",H22=SF_Output!$Y$2,SUMIFS(SF_Output!$T$1:$T$400,SF_Output!$AC$1:$AC$400,_xlfn.TEXTJOIN(",",TRUE,B22:E22),SF_Output!$Q$1:$Q$400,"monthly")<>0),SUMIFS(SF_Output!$S$1:$S$400,SF_Output!$AC$1:$AC$400,_xlfn.TEXTJOIN(",",TRUE,B22:E22),SF_Output!$Q$1:$Q$400,"monthly"),AND(B22<>"",H22<>SF_Output!$Y$2),SUMIFS(SF_Output!$S$1:$S$400,SF_Output!$AC$1:$AC$400,_xlfn.TEXTJOIN(",",TRUE,B22:E22),SF_Output!$Q$1:$Q$400,"monthly"))} -> 150 | W22: {=_xlfn.IFS(OR(B22=0,B22="",V22=0),"",AF22<>"exclusion",MAX($W$9,$W$7,(-(SUMIFS(SF_Output!$T$1:$T$400,SF_Output!$AC$1:$AC$400,_xlfn.TEXTJOIN(",",TRUE,$B22:$E22),SF_Output!$Q$1:$Q$400,"monthly"))/V22)),AF22="exclusion",-(SUMIFS(SF_Output!$T$1:$T$400,SF_Output!$AC$1:$AC$400,_xlfn.TEXTJOIN(",",TRUE,$B22:$E22),SF_Output!$Q$1:$Q$400,"monthly"))/V22)} -> 0.25 | X22: {=IFERROR(_xlfn.IFS(V22=0,0,V22="","",W22=0,V22,OR(V22<>0,V22<>""),H22*I22),V22*(1-W22))} -> 112.5 | Z22: =IFERROR(IF(B22="","",SUMIFS(Billing_Fallout!H:H,Billing_Fallout!N:N,B22)),0) -> 0 | AA22: =IF(Z22="","",AB22-Z22) -> 0 | AB22: =IFERROR(IF(B22="","",SUMIFS(Billing_Fallout!J:J,Billing_Fallout!N:N,B22)),0) -> 0 | AD22: =IFERROR(X22-AB22,"") -> 112.5 | AF22: =IFERROR(INDEX(H_Tables!$B$1:$B$1500,MATCH(INDEX(SF_Output!$J$1:$J$400,MATCH(B22,SF_Output!$M$1:$M$400,0)),H_Tables!$A$1:$A$1500,0)),"") | AI22: =IF(B22="","",IF(F22="remove","Remove Product",IF(F22="add","Add Product",_xlfn.TEXTJOIN(", ",TRUE,AQ22,AR22,AS22,AT22,AU22,AV22,AW22,AX22,AY22,AZ22,BA22,BB22,BC22)))) | AJ22: =IFERROR(INDEX(SF_Output!AD:AD,MATCH(_xlfn.TEXTJOIN(",",TRUE,B22:E22),SF_Output!AC1:AC400,0)),0.05) -> 143 | AK22: =IF(SUMIFS(SF_Output!$F$1:$F$400,SF_Output!$AC$1:$AC$400,_xlfn.TEXTJOIN(",",TRUE,B22:E22))+SUMIFS(SF_Output!$G$1:$G$400,SF_Output!$AC$1:$AC$400,_xlfn.TEXTJOIN(",",TRUE,B22:E22))=0,"","PAP") -> PAP | AL22: =LEFT(_xlfn.TEXTJOIN(",",TRUE,B22:E22),80) -> Hosted Xperience,New,Hosted by JHA,0 | AR22: {=IFERROR(_xlfn.IFS(AND(E22*1=1,F22="Included"),"Change to Included",AND(E22*1=0,F22="Optional"),"Change to Optional",OR(B22="",F22="replaced"),""),"")} | AS22: =IF((OR(NOT(_xlfn.ISFORMULA(J22)),NOT(_xlfn.ISFORMULA(L22)))),"Check License Price Override","") | AT22: =IF(OR(AND(K22=$K$9,K22<>0),NOT(_xlfn.ISFORMULA(K22))),"License Discount "&K22*100&"%","") | AU22: =IF((OR(NOT(_xlfn.ISFORMULA(N22)),NOT(_xlfn.ISFORMULA(P22)))),"Check Install Price Override","") | AV22: =IF(OR(AND(O22=$O$9,O22<>0),NOT(_xlfn.ISFORMULA(O22))),"Install Discount "&O22*100&"%","") | AW22: =IF((OR(NOT(_xlfn.ISFORMULA(R22)),NOT(_xlfn.ISFORMULA(T22)))),"Check Maintenance Price Override","") | AX22: =IF(OR(AND(S22=$S$9,S22<>0),NOT(_xlfn.ISFORMULA(S22))),"Maintenance Discount "&S22*100&"%","") | AY22: =IF((OR(NOT(_xlfn.ISFORMULA(V22)),NOT(_xlfn.ISFORMULA(X22)))),"Check Monthly Price Override","") | AZ22: =IF(OR((AND(W22=$W$9,W22<>0)),(AND(W22=$W$7,W22<>0)),(NOT(_xlfn.ISFORMULA(W22))),AND($W$7+0.2=W22,$W$7<>0)),"Monthly Discount "&W22*100&"%","") | BA22: =IF(NOT(_xlfn.ISFORMULA(H22)),"Check Quantity","") | BB22: =IF(NOT(_xlfn.ISFORMULA(I22)),"Check Unit Price Override","") | BE22: =INDEX(SF_Output!$AA$2:$AA$400,MATCH($B22,SF_Output!$M$2:$M$400,0)) -> 1 | BF22: =INDEX(SF_Output!$AB$2:$AB$400,MATCH($B22,SF_Output!$M$2:$M$400,0)) -> 4
B23: Platform Static Training Bank | C23: New | D23: Hosted by JHA | E23: 1 | F23: =IF(B23="","",IF(E23*1=0,"Included","Optional")) -> Optional | G23: =IF(B23="","",INDEX(SF_Output!$K$1:$K$400,MATCH(B23,SF_Output!$M$1:$M$400,0))) -> SilverLake | H23: {=_xlfn.IFS(B23="","",(SUMIFS(SF_Output!$F$1:$F$400,SF_Output!$AC$1:$AC$400,_xlfn.TEXTJOIN(",",TRUE,B23:E23))+SUMIFS(SF_Output!$G$1:$G$400,SF_Output!$AC$1:$AC$400,_xlfn.TEXTJOIN(",",TRUE,B23:E23)))<>0,SF_Output!$Y$2,INDEX(SF_Output!$F$1:$F$400,MATCH(_xlfn.TEXTJOIN(",",TRUE,B23:E23),SF_Output!$AC$1:$AC$400,0))=0,INDEX(SF_Output!$R$1:$R$400,MATCH(_xlfn.TEXTJOIN(",",TRUE,B23:E23),SF_Output!$AC$1:$AC$400,0)))} -> 1 | I23: =IFERROR(IF(AND(H23>1,H23<>""),ROUND(SUMIFS(SF_Output!$S$1:$S$400,SF_Output!$AC$1:$AC$400,_xlfn.TEXTJOIN(",",TRUE,B23:E23),SF_Output!$Q$1:$Q$400,"monthly")*(1-W23)/H23,4),""),"") | J23: =IF(B23="","",SUMIFS(SF_Output!$S$1:$S$400,SF_Output!$AC$1:$AC$400,_xlfn.TEXTJOIN(",",TRUE,B23:E23),SF_Output!$Q$1:$Q$400,"One Time",SF_Output!$L$1:$L$400,"license fee")+SUMIFS(SF_Output!$S$1:$S$400,SF_Output!$AC$1:$AC$400,_xlfn.TEXTJOIN(",",TRUE,B23:E23),SF_Output!$Q$1:$Q$400,"One Time",SF_Output!$L$1:$L$400,"software license")+SUMIFS(SF_Output!$S$1:$S$400,SF_Output!$AC$1:$AC$400,_xlfn.TEXTJOIN(",",TRUE,B23:E23),SF_Output!$Q$1:$Q$400,"One Time",SF_Output!$L$1:$L$400,"hardware")) -> 0 | K23: =IF(OR(B23=0,B23="",G23="hardware",J23=0),"",IF(AF23<>"exclusion",MAX(K$9,-((SUMIFS(SF_Output!$T$1:$T$400,SF_Output!$AC$1:$AC$400,_xlfn.TEXTJOIN(",",TRUE,$B23:$E23),SF_Output!$Q$1:$Q$400,"One Time",SF_Output!$L$1:$L$400,"license fee")+SUMIFS(SF_Output!$T$1:$T$400,SF_Output!$AC$1:$AC$400,_xlfn.TEXTJOIN(",",TRUE,$B23:$E23),SF_Output!$Q$1:$Q$400,"One Time",SF_Output!$L$1:$L$400,"software license"))/J23)),-((SUMIFS(SF_Output!$T$1:$T$400,SF_Output!$AC$1:$AC$400,_xlfn.TEXTJOIN(",",TRUE,$B23:$E23),SF_Output!$Q$1:$Q$400,"One Time",SF_Output!$L$1:$L$400,"license fee")+SUMIFS(SF_Output!$T$1:$T$400,SF_Output!$AC$1:$AC$400,_xlfn.TEXTJOIN(",",TRUE,$B23:$E23),SF_Output!$Q$1:$Q$400,"One Time",SF_Output!$L$1:$L$400,"software license"))/J23))) | L23: =IF(K23="",J23,J23*(1-K23)) -> 0 | N23: =IF(B23="","",SUMIFS(SF_Output!$S$1:$S$400,SF_Output!$AC$1:$AC$400,_xlfn.TEXTJOIN(",",TRUE,B23:E23),SF_Output!$Q$1:$Q$400,"One Time",SF_Output!$L$1:$L$400,"professional service")) -> 5000 | O23: =IF(OR(B23=0,B23="",N23=0),"",IF(AF23<>"exclusion",MAX(O$9,-(SUMIFS(SF_Output!$T$1:$T$400,SF_Output!$AC$1:$AC$400,_xlfn.TEXTJOIN(",",TRUE,$B23:$E23),SF_Output!$Q$1:$Q$400,"One Time",SF_Output!$L$1:$L$400,"professional service"))/N23),-((SUMIFS(SF_Output!$T$1:$T$400,SF_Output!$AC$1:$AC$400,_xlfn.TEXTJOIN(",",TRUE,$B23:$E23),SF_Output!$Q$1:$Q$400,"One Time",SF_Output!$L$1:$L$400,"professional service")/N23)))) -> 1 | P23: =IF(O23="",N23,N23*(1-O23)) -> 0 | R23: =IF(B23="","",SUMIFS(SF_Output!$S$1:$S$400,SF_Output!$AC$1:$AC$400,_xlfn.TEXTJOIN(",",TRUE,B23:E23),SF_Output!$Q$1:$Q$400,"yearly")+SUMIFS(SF_Output!$S$1:$S$400,SF_Output!$AC$1:$AC$400,_xlfn.TEXTJOIN(",",TRUE,B23:E23),SF_Output!$Q$1:$Q$400,"quarterly")*4) -> 0 | S23: =IF(OR(B23=0,B23="",G23="hardware",R23=0),"",IF(AF23<>"exclusion",MAX(S$9,-(SUMIFS(SF_Output!$T$1:$T$400,SF_Output!$AC$1:$AC$400,_xlfn.TEXTJOIN(",",TRUE,$B23:$E23),SF_Output!$Q$1:$Q$400,"yearly"))/R23),-((SUMIFS(SF_Output!$T$1:$T$400,SF_Output!$AC$1:$AC$400,_xlfn.TEXTJOIN(",",TRUE,$B23:$E23),SF_Output!$Q$1:$Q$400,"yearly")/R23)))) | T23: =IF(S23="",R23,R23*(1-S23)) -> 0 | V23: {=_xlfn.IFS(B23="","",AND(B23<>"",H23=SF_Output!$Y$2,SUMIFS(SF_Output!$T$1:$T$400,SF_Output!$AC$1:$AC$400,_xlfn.TEXTJOIN(",",TRUE,B23:E23),SF_Output!$Q$1:$Q$400,"monthly")=0),(SUMIFS(SF_Output!$F$1:$F$400,SF_Output!$AC$1:$AC$400,_xlfn.TEXTJOIN(",",TRUE,B23:E23),SF_Output!$Q$1:$Q$400,"monthly")+SUMIFS(SF_Output!$G$1:$G$400,SF_Output!$AC$1:$AC$400,_xlfn.TEXTJOIN(",",TRUE,B23:E23),SF_Output!$Q$1:$Q$400,"monthly"))*H23,AND(B23<>"",H23=SF_Output!$Y$2,SUMIFS(SF_Output!$T$1:$T$400,SF_Output!$AC$1:$AC$400,_xlfn.TEXTJOIN(",",TRUE,B23:E23),SF_Output!$Q$1:$Q$400,"monthly")<>0),SUMIFS(SF_Output!$S$1:$S$400,SF_Output!$AC$1:$AC$400,_xlfn.TEXTJOIN(",",TRUE,B23:E23),SF_Output!$Q$1:$Q$400,"monthly"),AND(B23<>"",H23<>SF_Output!$Y$2),SUMIFS(SF_Output!$S$1:$S$400,SF_Output!$AC$1:$AC$400,_xlfn.TEXTJOIN(",",TRUE,B23:E23),SF_Output!$Q$1:$Q$400,"monthly"))} -> 220 | W23: {=_xlfn.IFS(OR(B23=0,B23="",V23=0),"",AF23<>"exclusion",MAX($W$9,$W$7,(-(SUMIFS(SF_Output!$T$1:$T$400,SF_Output!$AC$1:$AC$400,_xlfn.TEXTJOIN(",",TRUE,$B23:$E23),SF_Output!$Q$1:$Q$400,"monthly"))/V23)),AF23="exclusion",-(SUMIFS(SF_Output!$T$1:$T$400,SF_Output!$AC$1:$AC$400,_xlfn.TEXTJOIN(",",TRUE,$B23:$E23),SF_Output!$Q$1:$Q$400,"monthly"))/V23)} -> 0.25 | X23: {=IFERROR(_xlfn.IFS(V23=0,0,V23="","",W23=0,V23,OR(V23<>0,V23<>""),H23*I23),V23*(1-W23))} -> 165 | Z23: =IFERROR(IF(B23="","",SUMIFS(Billing_Fallout!H:H,Billing_Fallout!N:N,B23)),0) -> 0 | AA23: =IF(Z23="","",AB23-Z23) -> 0 | AB23: =IFERROR(IF(B23="","",SUMIFS(Billing_Fallout!J:J,Billing_Fallout!N:N,B23)),0) -> 0 | AD23: =IFERROR(X23-AB23,"") -> 165 | AF23: =IFERROR(INDEX(H_Tables!$B$1:$B$1500,MATCH(INDEX(SF_Output!$J$1:$J$400,MATCH(B23,SF_Output!$M$1:$M$400,0)),H_Tables!$A$1:$A$1500,0)),"") | AI23: =IF(B23="","",IF(F23="remove","Remove Product",IF(F23="add","Add Product",_xlfn.TEXTJOIN(", ",TRUE,AQ23,AR23,AS23,AT23,AU23,AV23,AW23,AX23,AY23,AZ23,BA23,BB23,BC23)))) | AJ23: =IFERROR(INDEX(SF_Output!AD:AD,MATCH(_xlfn.TEXTJOIN(",",TRUE,B23:E23),SF_Output!AC1:AC400,0)),0.05) -> 16 | AK23: =IF(SUMIFS(SF_Output!$F$1:$F$400,SF_Output!$AC$1:$AC$400,_xlfn.TEXTJOIN(",",TRUE,B23:E23))+SUMIFS(SF_Output!$G$1:$G$400,SF_Output!$AC$1:$AC$400,_xlfn.TEXTJOIN(",",TRUE,B23:E23))=0,"","PAP") | AL23: =LEFT(_xlfn.TEXTJOIN(",",TRUE,B23:E23),80) -> Platform Static Training Bank,New,Hosted by JHA,1 | AR23: {=IFERROR(_xlfn.IFS(AND(E23*1=1,F23="Included"),"Change to Included",AND(E23*1=0,F23="Optional"),"Change to Optional",OR(B23="",F23="replaced"),""),"")} | AS23: =IF((OR(NOT(_xlfn.ISFORMULA(J23)),NOT(_xlfn.ISFORMULA(L23)))),"Check License Price Override","") | AT23: =IF(OR(AND(K23=$K$9,K23<>0),NOT(_xlfn.ISFORMULA(K23))),"License Discount "&K23*100&"%","") | AU23: =IF((OR(NOT(_xlfn.ISFORMULA(N23)),NOT(_xlfn.ISFORMULA(P23)))),"Check Install Price Override","") | AV23: =IF(OR(AND(O23=$O$9,O23<>0),NOT(_xlfn.ISFORMULA(O23))),"Install Discount "&O23*100&"%","") | AW23: =IF((OR(NOT(_xlfn.ISFORMULA(R23)),NOT(_xlfn.ISFORMULA(T23)))),"Check Maintenance Price Override","") | AX23: =IF(OR(AND(S23=$S$9,S23<>0),NOT(_xlfn.ISFORMULA(S23))),"Maintenance Discount "&S23*100&"%","") | AY23: =IF((OR(NOT(_xlfn.ISFORMULA(V23)),NOT(_xlfn.ISFORMULA(X23)))),"Check Monthly Price Override","") | AZ23: =IF(OR((AND(W23=$W$9,W23<>0)),(AND(W23=$W$7,W23<>0)),(NOT(_xlfn.ISFORMULA(W23))),AND($W$7+0.2=W23,$W$7<>0)),"Monthly Discount "&W23*100&"%","") | BA23: =IF(NOT(_xlfn.ISFORMULA(H23)),"Check Quantity","") | BB23: =IF(NOT(_xlfn.ISFORMULA(I23)),"Check Unit Price Override","") | BE23: =INDEX(SF_Output!$AA$2:$AA$400,MATCH($B23,SF_Output!$M$2:$M$400,0)) -> 2 | BF23: =INDEX(SF_Output!$AB$2:$AB$400,MATCH($B23,SF_Output!$M$2:$M$400,0)) -> 1
B24: OnBoard Deposits | C24: New | D24: Hosted by JHA | E24: 0 | F24: =IF(B24="","",IF(E24*1=0,"Included","Optional")) -> Included | G24: =IF(B24="","",INDEX(SF_Output!$K$1:$K$400,MATCH(B24,SF_Output!$M$1:$M$400,0))) -> OnBoard | H24: {=_xlfn.IFS(B24="","",(SUMIFS(SF_Output!$F$1:$F$400,SF_Output!$AC$1:$AC$400,_xlfn.TEXTJOIN(",",TRUE,B24:E24))+SUMIFS(SF_Output!$G$1:$G$400,SF_Output!$AC$1:$AC$400,_xlfn.TEXTJOIN(",",TRUE,B24:E24)))<>0,SF_Output!$Y$2,INDEX(SF_Output!$F$1:$F$400,MATCH(_xlfn.TEXTJOIN(",",TRUE,B24:E24),SF_Output!$AC$1:$AC$400,0))=0,INDEX(SF_Output!$R$1:$R$400,MATCH(_xlfn.TEXTJOIN(",",TRUE,B24:E24),SF_Output!$AC$1:$AC$400,0)))} -> 5000 | I24: =IFERROR(IF(AND(H24>1,H24<>""),ROUND(SUMIFS(SF_Output!$S$1:$S$400,SF_Output!$AC$1:$AC$400,_xlfn.TEXTJOIN(",",TRUE,B24:E24),SF_Output!$Q$1:$Q$400,"monthly")*(1-W24)/H24,4),""),"") -> 0.1703 | J24: =IF(B24="","",SUMIFS(SF_Output!$S$1:$S$400,SF_Output!$AC$1:$AC$400,_xlfn.TEXTJOIN(",",TRUE,B24:E24),SF_Output!$Q$1:$Q$400,"One Time",SF_Output!$L$1:$L$400,"license fee")+SUMIFS(SF_Output!$S$1:$S$400,SF_Output!$AC$1:$AC$400,_xlfn.TEXTJOIN(",",TRUE,B24:E24),SF_Output!$Q$1:$Q$400,"One Time",SF_Output!$L$1:$L$400,"software license")+SUMIFS(SF_Output!$S$1:$S$400,SF_Output!$AC$1:$AC$400,_xlfn.TEXTJOIN(",",TRUE,B24:E24),SF_Output!$Q$1:$Q$400,"One Time",SF_Output!$L$1:$L$400,"hardware")) -> 0 | K24: =IF(OR(B24=0,B24="",G24="hardware",J24=0),"",IF(AF24<>"exclusion",MAX(K$9,-((SUMIFS(SF_Output!$T$1:$T$400,SF_Output!$AC$1:$AC$400,_xlfn.TEXTJOIN(",",TRUE,$B24:$E24),SF_Output!$Q$1:$Q$400,"One Time",SF_Output!$L$1:$L$400,"license fee")+SUMIFS(SF_Output!$T$1:$T$400,SF_Output!$AC$1:$AC$400,_xlfn.TEXTJOIN(",",TRUE,$B24:$E24),SF_Output!$Q$1:$Q$400,"One Time",SF_Output!$L$1:$L$400,"software license"))/J24)),-((SUMIFS(SF_Output!$T$1:$T$400,SF_Output!$AC$1:$AC$400,_xlfn.TEXTJOIN(",",TRUE,$B24:$E24),SF_Output!$Q$1:$Q$400,"One Time",SF_Output!$L$1:$L$400,"license fee")+SUMIFS(SF_Output!$T$1:$T$400,SF_Output!$AC$1:$AC$400,_xlfn.TEXTJOIN(",",TRUE,$B24:$E24),SF_Output!$Q$1:$Q$400,"One Time",SF_Output!$L$1:$L$400,"software license"))/J24))) | L24: =IF(K24="",J24,J24*(1-K24)) -> 0 | N24: =IF(B24="","",SUMIFS(SF_Output!$S$1:$S$400,SF_Output!$AC$1:$AC$400,_xlfn.TEXTJOIN(",",TRUE,B24:E24),SF_Output!$Q$1:$Q$400,"One Time",SF_Output!$L$1:$L$400,"professional service")) -> 23180 | O24: =IF(OR(B24=0,B24="",N24=0),"",IF(AF24<>"exclusion",MAX(O$9,-(SUMIFS(SF_Output!$T$1:$T$400,SF_Output!$AC$1:$AC$400,_xlfn.TEXTJOIN(",",TRUE,$B24:$E24),SF_Output!$Q$1:$Q$400,"One Time",SF_Output!$L$1:$L$400,"professional service"))/N24),-((SUMIFS(SF_Output!$T$1:$T$400,SF_Output!$AC$1:$AC$400,_xlfn.TEXTJOIN(",",TRUE,$B24:$E24),SF_Output!$Q$1:$Q$400,"One Time",SF_Output!$L$1:$L$400,"professional service")/N24)))) -> 1 | P24: =IF(O24="",N24,N24*(1-O24)) -> 0 | R24: =IF(B24="","",SUMIFS(SF_Output!$S$1:$S$400,SF_Output!$AC$1:$AC$400,_xlfn.TEXTJOIN(",",TRUE,B24:E24),SF_Output!$Q$1:$Q$400,"yearly")+SUMIFS(SF_Output!$S$1:$S$400,SF_Output!$AC$1:$AC$400,_xlfn.TEXTJOIN(",",TRUE,B24:E24),SF_Output!$Q$1:$Q$400,"quarterly")*4) -> 0 | S24: =IF(OR(B24=0,B24="",G24="hardware",R24=0),"",IF(AF24<>"exclusion",MAX(S$9,-(SUMIFS(SF_Output!$T$1:$T$400,SF_Output!$AC$1:$AC$400,_xlfn.TEXTJOIN(",",TRUE,$B24:$E24),SF_Output!$Q$1:$Q$400,"yearly"))/R24),-((SUMIFS(SF_Output!$T$1:$T$400,SF_Output!$AC$1:$AC$400,_xlfn.TEXTJOIN(",",TRUE,$B24:$E24),SF_Output!$Q$1:$Q$400,"yearly")/R24)))) | T24: =IF(S24="",R24,R24*(1-S24)) -> 0 | V24: {=_xlfn.IFS(B24="","",AND(B24<>"",H24=SF_Output!$Y$2,SUMIFS(SF_Output!$T$1:$T$400,SF_Output!$AC$1:$AC$400,_xlfn.TEXTJOIN(",",TRUE,B24:E24),SF_Output!$Q$1:$Q$400,"monthly")=0),(SUMIFS(SF_Output!$F$1:$F$400,SF_Output!$AC$1:$AC$400,_xlfn.TEXTJOIN(",",TRUE,B24:E24),SF_Output!$Q$1:$Q$400,"monthly")+SUMIFS(SF_Output!$G$1:$G$400,SF_Output!$AC$1:$AC$400,_xlfn.TEXTJOIN(",",TRUE,B24:E24),SF_Output!$Q$1:$Q$400,"monthly"))*H24,AND(B24<>"",H24=SF_Output!$Y$2,SUMIFS(SF_Output!$T$1:$T$400,SF_Output!$AC$1:$AC$400,_xlfn.TEXTJOIN(",",TRUE,B24:E24),SF_Output!$Q$1:$Q$400,"monthly")<>0),SUMIFS(SF_Output!$S$1:$S$400,SF_Output!$AC$1:$AC$400,_xlfn.TEXTJOIN(",",TRUE,B24:E24),SF_Output!$Q$1:$Q$400,"monthly"),AND(B24<>"",H24<>SF_Output!$Y$2),SUMIFS(SF_Output!$S$1:$S$400,SF_Output!$AC$1:$AC$400,_xlfn.TEXTJOIN(",",TRUE,B24:E24),SF_Output!$Q$1:$Q$400,"monthly"))} -> 1135 | W24: {=_xlfn.IFS(OR(B24=0,B24="",V24=0),"",AF24<>"exclusion",MAX($W$9,$W$7,(-(SUMIFS(SF_Output!$T$1:$T$400,SF_Output!$AC$1:$AC$400,_xlfn.TEXTJOIN(",",TRUE,$B24:$E24),SF_Output!$Q$1:$Q$400,"monthly"))/V24)),AF24="exclusion",-(SUMIFS(SF_Output!$T$1:$T$400,SF_Output!$AC$1:$AC$400,_xlfn.TEXTJOIN(",",TRUE,$B24:$E24),SF_Output!$Q$1:$Q$400,"monthly"))/V24)} -> 0.25 | X24: {=IFERROR(_xlfn.IFS(V24=0,0,V24="","",W24=0,V24,OR(V24<>0,V24<>""),H24*I24),V24*(1-W24))} -> 851.5 | Z24: =IFERROR(IF(B24="","",SUMIFS(Billing_Fallout!H:H,Billing_Fallout!N:N,B24)),0) -> 0 | AA24: =IF(Z24="","",AB24-Z24) -> 0 | AB24: =IFERROR(IF(B24="","",SUMIFS(Billing_Fallout!J:J,Billing_Fallout!N:N,B24)),0) -> 0 | AD24: =IFERROR(X24-AB24,"") -> 851.5 | AF24: =IFERROR(INDEX(H_Tables!$B$1:$B$1500,MATCH(INDEX(SF_Output!$J$1:$J$400,MATCH(B24,SF_Output!$M$1:$M$400,0)),H_Tables!$A$1:$A$1500,0)),"") | AI24: =IF(B24="","",IF(F24="remove","Remove Product",IF(F24="add","Add Product",_xlfn.TEXTJOIN(", ",TRUE,AQ24,AR24,AS24,AT24,AU24,AV24,AW24,AX24,AY24,AZ24,BA24,BB24,BC24)))) | AJ24: =IFERROR(INDEX(SF_Output!AD:AD,MATCH(_xlfn.TEXTJOIN(",",TRUE,B24:E24),SF_Output!AC1:AC400,0)),0.05) -> 33 | AK24: =IF(SUMIFS(SF_Output!$F$1:$F$400,SF_Output!$AC$1:$AC$400,_xlfn.TEXTJOIN(",",TRUE,B24:E24))+SUMIFS(SF_Output!$G$1:$G$400,SF_Output!$AC$1:$AC$400,_xlfn.TEXTJOIN(",",TRUE,B24:E24))=0,"","PAP") -> PAP | AL24: =LEFT(_xlfn.TEXTJOIN(",",TRUE,B24:E24),80) -> OnBoard Deposits,New,Hosted by JHA,0 | AR24: {=IFERROR(_xlfn.IFS(AND(E24*1=1,F24="Included"),"Change to Included",AND(E24*1=0,F24="Optional"),"Change to Optional",OR(B24="",F24="replaced"),""),"")} | AS24: =IF((OR(NOT(_xlfn.ISFORMULA(J24)),NOT(_xlfn.ISFORMULA(L24)))),"Check License Price Override","") | AT24: =IF(OR(AND(K24=$K$9,K24<>0),NOT(_xlfn.ISFORMULA(K24))),"License Discount "&K24*100&"%","") | AU24: =IF((OR(NOT(_xlfn.ISFORMULA(N24)),NOT(_xlfn.ISFORMULA(P24)))),"Check Install Price Override","") | AV24: =IF(OR(AND(O24=$O$9,O24<>0),NOT(_xlfn.ISFORMULA(O24))),"Install Discount "&O24*100&"%","") | AW24: =IF((OR(NOT(_xlfn.ISFORMULA(R24)),NOT(_xlfn.ISFORMULA(T24)))),"Check Maintenance Price Override","") | AX24: =IF(OR(AND(S24=$S$9,S24<>0),NOT(_xlfn.ISFORMULA(S24))),"Maintenance Discount "&S24*100&"%","") | AY24: =IF((OR(NOT(_xlfn.ISFORMULA(V24)),NOT(_xlfn.ISFORMULA(X24)))),"Check Monthly Price Override","") | AZ24: =IF(OR((AND(W24=$W$9,W24<>0)),(AND(W24=$W$7,W24<>0)),(NOT(_xlfn.ISFORMULA(W24))),AND($W$7+0.2=W24,$W$7<>0)),"Monthly Discount "&W24*100&"%","") | BA24: =IF(NOT(_xlfn.ISFORMULA(H24)),"Check Quantity","") | BB24: =IF(NOT(_xlfn.ISFORMULA(I24)),"Check Unit Price Override","") | BE24: =INDEX(SF_Output!$AA$2:$AA$400,MATCH($B24,SF_Output!$M$2:$M$400,0)) -> 2 | BF24: =INDEX(SF_Output!$AB$2:$AB$400,MATCH($B24,SF_Output!$M$2:$M$400,0)) -> 1
B25: OnBoard Lending | C25: New | D25: Hosted by JHA | E25: 1 | F25: =IF(B25="","",IF(E25*1=0,"Included","Optional")) -> Optional | G25: =IF(B25="","",INDEX(SF_Output!$K$1:$K$400,MATCH(B25,SF_Output!$M$1:$M$400,0))) -> OnBoard | H25: {=_xlfn.IFS(B25="","",(SUMIFS(SF_Output!$F$1:$F$400,SF_Output!$AC$1:$AC$400,_xlfn.TEXTJOIN(",",TRUE,B25:E25))+SUMIFS(SF_Output!$G$1:$G$400,SF_Output!$AC$1:$AC$400,_xlfn.TEXTJOIN(",",TRUE,B25:E25)))<>0,SF_Output!$Y$2,INDEX(SF_Output!$F$1:$F$400,MATCH(_xlfn.TEXTJOIN(",",TRUE,B25:E25),SF_Output!$AC$1:$AC$400,0))=0,INDEX(SF_Output!$R$1:$R$400,MATCH(_xlfn.TEXTJOIN(",",TRUE,B25:E25),SF_Output!$AC$1:$AC$400,0)))} -> 5000 | I25: =IFERROR(IF(AND(H25>1,H25<>""),ROUND(SUMIFS(SF_Output!$S$1:$S$400,SF_Output!$AC$1:$AC$400,_xlfn.TEXTJOIN(",",TRUE,B25:E25),SF_Output!$Q$1:$Q$400,"monthly")*(1-W25)/H25,4),""),"") -> 0.2273 | J25: =IF(B25="","",SUMIFS(SF_Output!$S$1:$S$400,SF_Output!$AC$1:$AC$400,_xlfn.TEXTJOIN(",",TRUE,B25:E25),SF_Output!$Q$1:$Q$400,"One Time",SF_Output!$L$1:$L$400,"license fee")+SUMIFS(SF_Output!$S$1:$S$400,SF_Output!$AC$1:$AC$400,_xlfn.TEXTJOIN(",",TRUE,B25:E25),SF_Output!$Q$1:$Q$400,"One Time",SF_Output!$L$1:$L$400,"software license")+SUMIFS(SF_Output!$S$1:$S$400,SF_Output!$AC$1:$AC$400,_xlfn.TEXTJOIN(",",TRUE,B25:E25),SF_Output!$Q$1:$Q$400,"One Time",SF_Output!$L$1:$L$400,"hardware")) -> 0 | K25: =IF(OR(B25=0,B25="",G25="hardware",J25=0),"",IF(AF25<>"exclusion",MAX(K$9,-((SUMIFS(SF_Output!$T$1:$T$400,SF_Output!$AC$1:$AC$400,_xlfn.TEXTJOIN(",",TRUE,$B25:$E25),SF_Output!$Q$1:$Q$400,"One Time",SF_Output!$L$1:$L$400,"license fee")+SUMIFS(SF_Output!$T$1:$T$400,SF_Output!$AC$1:$AC$400,_xlfn.TEXTJOIN(",",TRUE,$B25:$E25),SF_Output!$Q$1:$Q$400,"One Time",SF_Output!$L$1:$L$400,"software license"))/J25)),-((SUMIFS(SF_Output!$T$1:$T$400,SF_Output!$AC$1:$AC$400,_xlfn.TEXTJOIN(",",TRUE,$B25:$E25),SF_Output!$Q$1:$Q$400,"One Time",SF_Output!$L$1:$L$400,"license fee")+SUMIFS(SF_Output!$T$1:$T$400,SF_Output!$AC$1:$AC$400,_xlfn.TEXTJOIN(",",TRUE,$B25:$E25),SF_Output!$Q$1:$Q$400,"One Time",SF_Output!$L$1:$L$400,"software license"))/J25))) | L25: =IF(K25="",J25,J25*(1-K25)) -> 0 | N25: =IF(B25="","",SUMIFS(SF_Output!$S$1:$S$400,SF_Output!$AC$1:$AC$400,_xlfn.TEXTJOIN(",",TRUE,B25:E25),SF_Output!$Q$1:$Q$400,"One Time",SF_Output!$L$1:$L$400,"professional service")) -> 42480 | O25: =IF(OR(B25=0,B25="",N25=0),"",IF(AF25<>"exclusion",MAX(O$9,-(SUMIFS(SF_Output!$T$1:$T$400,SF_Output!$AC$1:$AC$400,_xlfn.TEXTJOIN(",",TRUE,$B25:$E25),SF_Output!$Q$1:$Q$400,"One Time",SF_Output!$L$1:$L$400,"professional service"))/N25),-((SUMIFS(SF_Output!$T$1:$T$400,SF_Output!$AC$1:$AC$400,_xlfn.TEXTJOIN(",",TRUE,$B25:$E25),SF_Output!$Q$1:$Q$400,"One Time",SF_Output!$L$1:$L$400,"professional service")/N25)))) -> 1 | P25: =IF(O25="",N25,N25*(1-O25)) -> 0 | R25: =IF(B25="","",SUMIFS(SF_Output!$S$1:$S$400,SF_Output!$AC$1:$AC$400,_xlfn.TEXTJOIN(",",TRUE,B25:E25),SF_Output!$Q$1:$Q$400,"yearly")+SUMIFS(SF_Output!$S$1:$S$400,SF_Output!$AC$1:$AC$400,_xlfn.TEXTJOIN(",",TRUE,B25:E25),SF_Output!$Q$1:$Q$400,"quarterly")*4) -> 0 | S25: =IF(OR(B25=0,B25="",G25="hardware",R25=0),"",IF(AF25<>"exclusion",MAX(S$9,-(SUMIFS(SF_Output!$T$1:$T$400,SF_Output!$AC$1:$AC$400,_xlfn.TEXTJOIN(",",TRUE,$B25:$E25),SF_Output!$Q$1:$Q$400,"yearly"))/R25),-((SUMIFS(SF_Output!$T$1:$T$400,SF_Output!$AC$1:$AC$400,_xlfn.TEXTJOIN(",",TRUE,$B25:$E25),SF_Output!$Q$1:$Q$400,"yearly")/R25)))) | T25: =IF(S25="",R25,R25*(1-S25)) -> 0 | V25: {=_xlfn.IFS(B25="","",AND(B25<>"",H25=SF_Output!$Y$2,SUMIFS(SF_Output!$T$1:$T$400,SF_Output!$AC$1:$AC$400,_xlfn.TEXTJOIN(",",TRUE,B25:E25),SF_Output!$Q$1:$Q$400,"monthly")=0),(SUMIFS(SF_Output!$F$1:$F$400,SF_Output!$AC$1:$AC$400,_xlfn.TEXTJOIN(",",TRUE,B25:E25),SF_Output!$Q$1:$Q$400,"monthly")+SUMIFS(SF_Output!$G$1:$G$400,SF_Output!$AC$1:$AC$400,_xlfn.TEXTJOIN(",",TRUE,B25:E25),SF_Output!$Q$1:$Q$400,"monthly"))*H25,AND(B25<>"",H25=SF_Output!$Y$2,SUMIFS(SF_Output!$T$1:$T$400,SF_Output!$AC$1:$AC$400,_xlfn.TEXTJOIN(",",TRUE,B25:E25),SF_Output!$Q$1:$Q$400,"monthly")<>0),SUMIFS(SF_Output!$S$1:$S$400,SF_Output!$AC$1:$AC$400,_xlfn.TEXTJOIN(",",TRUE,B25:E25),SF_Output!$Q$1:$Q$400,"monthly"),AND(B25<>"",H25<>SF_Output!$Y$2),SUMIFS(SF_Output!$S$1:$S$400,SF_Output!$AC$1:$AC$400,_xlfn.TEXTJOIN(",",TRUE,B25:E25),SF_Output!$Q$1:$Q$400,"monthly"))} -> 1515 | W25: {=_xlfn.IFS(OR(B25=0,B25="",V25=0),"",AF25<>"exclusion",MAX($W$9,$W$7,(-(SUMIFS(SF_Output!$T$1:$T$400,SF_Output!$AC$1:$AC$400,_xlfn.TEXTJOIN(",",TRUE,$B25:$E25),SF_Output!$Q$1:$Q$400,"monthly"))/V25)),AF25="exclusion",-(SUMIFS(SF_Output!$T$1:$T$400,SF_Output!$AC$1:$AC$400,_xlfn.TEXTJOIN(",",TRUE,$B25:$E25),SF_Output!$Q$1:$Q$400,"monthly"))/V25)} -> 0.25 | X25: {=IFERROR(_xlfn.IFS(V25=0,0,V25="","",W25=0,V25,OR(V25<>0,V25<>""),H25*I25),V25*(1-W25))} -> 1136.5 | Z25: =IFERROR(IF(B25="","",SUMIFS(Billing_Fallout!H:H,Billing_Fallout!N:N,B25)),0) -> 0 | AA25: =IF(Z25="","",AB25-Z25) -> 0 | AB25: =IFERROR(IF(B25="","",SUMIFS(Billing_Fallout!J:J,Billing_Fallout!N:N,B25)),0) -> 0 | AD25: =IFERROR(X25-AB25,"") -> 1136.5 | AF25: =IFERROR(INDEX(H_Tables!$B$1:$B$1500,MATCH(INDEX(SF_Output!$J$1:$J$400,MATCH(B25,SF_Output!$M$1:$M$400,0)),H_Tables!$A$1:$A$1500,0)),"") | AI25: =IF(B25="","",IF(F25="remove","Remove Product",IF(F25="add","Add Product",_xlfn.TEXTJOIN(", ",TRUE,AQ25,AR25,AS25,AT25,AU25,AV25,AW25,AX25,AY25,AZ25,BA25,BB25,BC25)))) | AJ25: =IFERROR(INDEX(SF_Output!AD:AD,MATCH(_xlfn.TEXTJOIN(",",TRUE,B25:E25),SF_Output!AC1:AC400,0)),0.05) -> 35 | AK25: =IF(SUMIFS(SF_Output!$F$1:$F$400,SF_Output!$AC$1:$AC$400,_xlfn.TEXTJOIN(",",TRUE,B25:E25))+SUMIFS(SF_Output!$G$1:$G$400,SF_Output!$AC$1:$AC$400,_xlfn.TEXTJOIN(",",TRUE,B25:E25))=0,"","PAP") -> PAP | AL25: =LEFT(_xlfn.TEXTJOIN(",",TRUE,B25:E25),80) -> OnBoard Lending,New,Hosted by JHA,1 | AR25: {=IFERROR(_xlfn.IFS(AND(E25*1=1,F25="Included"),"Change to Included",AND(E25*1=0,F25="Optional"),"Change to Optional",OR(B25="",F25="replaced"),""),"")} | AS25: =IF((OR(NOT(_xlfn.ISFORMULA(J25)),NOT(_xlfn.ISFORMULA(L25)))),"Check License Price Override","") | AT25: =IF(OR(AND(K25=$K$9,K25<>0),NOT(_xlfn.ISFORMULA(K25))),"License Discount "&K25*100&"%","") | AU25: =IF((OR(NOT(_xlfn.ISFORMULA(N25)),NOT(_xlfn.ISFORMULA(P25)))),"Check Install Price Override","") | AV25: =IF(OR(AND(O25=$O$9,O25<>0),NOT(_xlfn.ISFORMULA(O25))),"Install Discount "&O25*100&"%","") | AW25: =IF((OR(NOT(_xlfn.ISFORMULA(R25)),NOT(_xlfn.ISFORMULA(T25)))),"Check Maintenance Price Override","") | AX25: =IF(OR(AND(S25=$S$9,S25<>0),NOT(_xlfn.ISFORMULA(S25))),"Maintenance Discount "&S25*100&"%","") | AY25: =IF((OR(NOT(_xlfn.ISFORMULA(V25)),NOT(_xlfn.ISFORMULA(X25)))),"Check Monthly Price Override","") | AZ25: =IF(OR((AND(W25=$W$9,W25<>0)),(AND(W25=$W$7,W25<>0)),(NOT(_xlfn.ISFORMULA(W25))),AND($W$7+0.2=W25,$W$7<>0)),"Monthly Discount "&W25*100&"%","") | BA25: =IF(NOT(_xlfn.ISFORMULA(H25)),"Check Quantity","") | BB25: =IF(NOT(_xlfn.ISFORMULA(I25)),"Check Unit Price Override","") | BE25: =INDEX(SF_Output!$AA$2:$AA$400,MATCH($B25,SF_Output!$M$2:$M$400,0)) -> 2 | BF25: =INDEX(SF_Output!$AB$2:$AB$400,MATCH($B25,SF_Output!$M$2:$M$400,0)) -> 1
B26: Carleton SmartCalcs Lending | C26: New | D26: Hosted by JHA | E26: 1 | F26: =IF(B26="","",IF(E26*1=0,"Included","Optional")) -> Optional | G26: =IF(B26="","",INDEX(SF_Output!$K$1:$K$400,MATCH(B26,SF_Output!$M$1:$M$400,0))) -> OnBoard | H26: {=_xlfn.IFS(B26="","",(SUMIFS(SF_Output!$F$1:$F$400,SF_Output!$AC$1:$AC$400,_xlfn.TEXTJOIN(",",TRUE,B26:E26))+SUMIFS(SF_Output!$G$1:$G$400,SF_Output!$AC$1:$AC$400,_xlfn.TEXTJOIN(",",TRUE,B26:E26)))<>0,SF_Output!$Y$2,INDEX(SF_Output!$F$1:$F$400,MATCH(_xlfn.TEXTJOIN(",",TRUE,B26:E26),SF_Output!$AC$1:$AC$400,0))=0,INDEX(SF_Output!$R$1:$R$400,MATCH(_xlfn.TEXTJOIN(",",TRUE,B26:E26),SF_Output!$AC$1:$AC$400,0)))} -> 1 | I26: =IFERROR(IF(AND(H26>1,H26<>""),ROUND(SUMIFS(SF_Output!$S$1:$S$400,SF_Output!$AC$1:$AC$400,_xlfn.TEXTJOIN(",",TRUE,B26:E26),SF_Output!$Q$1:$Q$400,"monthly")*(1-W26)/H26,4),""),"") | J26: =IF(B26="","",SUMIFS(SF_Output!$S$1:$S$400,SF_Output!$AC$1:$AC$400,_xlfn.TEXTJOIN(",",TRUE,B26:E26),SF_Output!$Q$1:$Q$400,"One Time",SF_Output!$L$1:$L$400,"license fee")+SUMIFS(SF_Output!$S$1:$S$400,SF_Output!$AC$1:$AC$400,_xlfn.TEXTJOIN(",",TRUE,B26:E26),SF_Output!$Q$1:$Q$400,"One Time",SF_Output!$L$1:$L$400,"software license")+SUMIFS(SF_Output!$S$1:$S$400,SF_Output!$AC$1:$AC$400,_xlfn.TEXTJOIN(",",TRUE,B26:E26),SF_Output!$Q$1:$Q$400,"One Time",SF_Output!$L$1:$L$400,"hardware")) -> 0 | K26: =IF(OR(B26=0,B26="",G26="hardware",J26=0),"",IF(AF26<>"exclusion",MAX(K$9,-((SUMIFS(SF_Output!$T$1:$T$400,SF_Output!$AC$1:$AC$400,_xlfn.TEXTJOIN(",",TRUE,$B26:$E26),SF_Output!$Q$1:$Q$400,"One Time",SF_Output!$L$1:$L$400,"license fee")+SUMIFS(SF_Output!$T$1:$T$400,SF_Output!$AC$1:$AC$400,_xlfn.TEXTJOIN(",",TRUE,$B26:$E26),SF_Output!$Q$1:$Q$400,"One Time",SF_Output!$L$1:$L$400,"software license"))/J26)),-((SUMIFS(SF_Output!$T$1:$T$400,SF_Output!$AC$1:$AC$400,_xlfn.TEXTJOIN(",",TRUE,$B26:$E26),SF_Output!$Q$1:$Q$400,"One Time",SF_Output!$L$1:$L$400,"license fee")+SUMIFS(SF_Output!$T$1:$T$400,SF_Output!$AC$1:$AC$400,_xlfn.TEXTJOIN(",",TRUE,$B26:$E26),SF_Output!$Q$1:$Q$400,"One Time",SF_Output!$L$1:$L$400,"software license"))/J26))) | L26: =IF(K26="",J26,J26*(1-K26)) -> 0 | N26: =IF(B26="","",SUMIFS(SF_Output!$S$1:$S$400,SF_Output!$AC$1:$AC$400,_xlfn.TEXTJOIN(",",TRUE,B26:E26),SF_Output!$Q$1:$Q$400,"One Time",SF_Output!$L$1:$L$400,"professional service")) -> 1500 | O26: =IF(OR(B26=0,B26="",N26=0),"",IF(AF26<>"exclusion",MAX(O$9,-(SUMIFS(SF_Output!$T$1:$T$400,SF_Output!$AC$1:$AC$400,_xlfn.TEXTJOIN(",",TRUE,$B26:$E26),SF_Output!$Q$1:$Q$400,"One Time",SF_Output!$L$1:$L$400,"professional service"))/N26),-((SUMIFS(SF_Output!$T$1:$T$400,SF_Output!$AC$1:$AC$400,_xlfn.TEXTJOIN(",",TRUE,$B26:$E26),SF_Output!$Q$1:$Q$400,"One Time",SF_Output!$L$1:$L$400,"professional service")/N26)))) -> 0 | P26: =IF(O26="",N26,N26*(1-O26)) -> 1500 | R26: =IF(B26="","",SUMIFS(SF_Output!$S$1:$S$400,SF_Output!$AC$1:$AC$400,_xlfn.TEXTJOIN(",",TRUE,B26:E26),SF_Output!$Q$1:$Q$400,"yearly")+SUMIFS(SF_Output!$S$1:$S$400,SF_Output!$AC$1:$AC$400,_xlfn.TEXTJOIN(",",TRUE,B26:E26),SF_Output!$Q$1:$Q$400,"quarterly")*4) -> 0 | S26: =IF(OR(B26=0,B26="",G26="hardware",R26=0),"",IF(AF26<>"exclusion",MAX(S$9,-(SUMIFS(SF_Output!$T$1:$T$400,SF_Output!$AC$1:$AC$400,_xlfn.TEXTJOIN(",",TRUE,$B26:$E26),SF_Output!$Q$1:$Q$400,"yearly"))/R26),-((SUMIFS(SF_Output!$T$1:$T$400,SF_Output!$AC$1:$AC$400,_xlfn.TEXTJOIN(",",TRUE,$B26:$E26),SF_Output!$Q$1:$Q$400,"yearly")/R26)))) | T26: =IF(S26="",R26,R26*(1-S26)) -> 0 | V26: {=_xlfn.IFS(B26="","",AND(B26<>"",H26=SF_Output!$Y$2,SUMIFS(SF_Output!$T$1:$T$400,SF_Output!$AC$1:$AC$400,_xlfn.TEXTJOIN(",",TRUE,B26:E26),SF_Output!$Q$1:$Q$400,"monthly")=0),(SUMIFS(SF_Output!$F$1:$F$400,SF_Output!$AC$1:$AC$400,_xlfn.TEXTJOIN(",",TRUE,B26:E26),SF_Output!$Q$1:$Q$400,"monthly")+SUMIFS(SF_Output!$G$1:$G$400,SF_Output!$AC$1:$AC$400,_xlfn.TEXTJOIN(",",TRUE,B26:E26),SF_Output!$Q$1:$Q$400,"monthly"))*H26,AND(B26<>"",H26=SF_Output!$Y$2,SUMIFS(SF_Output!$T$1:$T$400,SF_Output!$AC$1:$AC$400,_xlfn.TEXTJOIN(",",TRUE,B26:E26),SF_Output!$Q$1:$Q$400,"monthly")<>0),SUMIFS(SF_Output!$S$1:$S$400,SF_Output!$AC$1:$AC$400,_xlfn.TEXTJOIN(",",TRUE,B26:E26),SF_Output!$Q$1:$Q$400,"monthly"),AND(B26<>"",H26<>SF_Output!$Y$2),SUMIFS(SF_Output!$S$1:$S$400,SF_Output!$AC$1:$AC$400,_xlfn.TEXTJOIN(",",TRUE,B26:E26),SF_Output!$Q$1:$Q$400,"monthly"))} -> 0 | W26: {=_xlfn.IFS(OR(B26=0,B26="",V26=0),"",AF26<>"exclusion",MAX($W$9,$W$7,(-(SUMIFS(SF_Output!$T$1:$T$400,SF_Output!$AC$1:$AC$400,_xlfn.TEXTJOIN(",",TRUE,$B26:$E26),SF_Output!$Q$1:$Q$400,"monthly"))/V26)),AF26="exclusion",-(SUMIFS(SF_Output!$T$1:$T$400,SF_Output!$AC$1:$AC$400,_xlfn.TEXTJOIN(",",TRUE,$B26:$E26),SF_Output!$Q$1:$Q$400,"monthly"))/V26)} | X26: {=IFERROR(_xlfn.IFS(V26=0,0,V26="","",W26=0,V26,OR(V26<>0,V26<>""),H26*I26),V26*(1-W26))} -> 0 | Z26: =IFERROR(IF(B26="","",SUMIFS(Billing_Fallout!H:H,Billing_Fallout!N:N,B26)),0) -> 0 | AA26: =IF(Z26="","",AB26-Z26) -> 0 | AB26: =IFERROR(IF(B26="","",SUMIFS(Billing_Fallout!J:J,Billing_Fallout!N:N,B26)),0) -> 0 | AD26: =IFERROR(X26-AB26,"") -> 0 | AF26: =IFERROR(INDEX(H_Tables!$B$1:$B$1500,MATCH(INDEX(SF_Output!$J$1:$J$400,MATCH(B26,SF_Output!$M$1:$M$400,0)),H_Tables!$A$1:$A$1500,0)),"") -> Exclusion | AI26: =IF(B26="","",IF(F26="remove","Remove Product",IF(F26="add","Add Product",_xlfn.TEXTJOIN(", ",TRUE,AQ26,AR26,AS26,AT26,AU26,AV26,AW26,AX26,AY26,AZ26,BA26,BB26,BC26)))) | AJ26: =IFERROR(INDEX(SF_Output!AD:AD,MATCH(_xlfn.TEXTJOIN(",",TRUE,B26:E26),SF_Output!AC1:AC400,0)),0.05) -> 37 | AK26: =IF(SUMIFS(SF_Output!$F$1:$F$400,SF_Output!$AC$1:$AC$400,_xlfn.TEXTJOIN(",",TRUE,B26:E26))+SUMIFS(SF_Output!$G$1:$G$400,SF_Output!$AC$1:$AC$400,_xlfn.TEXTJOIN(",",TRUE,B26:E26))=0,"","PAP") | AL26: =LEFT(_xlfn.TEXTJOIN(",",TRUE,B26:E26),80) -> Carleton SmartCalcs Lending,New,Hosted by JHA,1 | AR26: {=IFERROR(_xlfn.IFS(AND(E26*1=1,F26="Included"),"Change to Included",AND(E26*1=0,F26="Optional"),"Change to Optional",OR(B26="",F26="replaced"),""),"")} | AS26: =IF((OR(NOT(_xlfn.ISFORMULA(J26)),NOT(_xlfn.ISFORMULA(L26)))),"Check License Price Override","") | AT26: =IF(OR(AND(K26=$K$9,K26<>0),NOT(_xlfn.ISFORMULA(K26))),"License Discount "&K26*100&"%","") | AU26: =IF((OR(NOT(_xlfn.ISFORMULA(N26)),NOT(_xlfn.ISFORMULA(P26)))),"Check Install Price Override","") | AV26: =IF(OR(AND(O26=$O$9,O26<>0),NOT(_xlfn.ISFORMULA(O26))),"Install Discount "&O26*100&"%","") | AW26: =IF((OR(NOT(_xlfn.ISFORMULA(R26)),NOT(_xlfn.ISFORMULA(T26)))),"Check Maintenance Price Override","") | AX26: =IF(OR(AND(S26=$S$9,S26<>0),NOT(_xlfn.ISFORMULA(S26))),"Maintenance Discount "&S26*100&"%","") | AY26: =IF((OR(NOT(_xlfn.ISFORMULA(V26)),NOT(_xlfn.ISFORMULA(X26)))),"Check Monthly Price Override","") | AZ26: =IF(OR((AND(W26=$W$9,W26<>0)),(AND(W26=$W$7,W26<>0)),(NOT(_xlfn.ISFORMULA(W26))),AND($W$7+0.2=W26,$W$7<>0)),"Monthly Discount "&W26*100&"%","") | BA26: =IF(NOT(_xlfn.ISFORMULA(H26)),"Check Quantity","") | BB26: =IF(NOT(_xlfn.ISFORMULA(I26)),"Check Unit Price Override","") | BE26: =INDEX(SF_Output!$AA$2:$AA$400,MATCH($B26,SF_Output!$M$2:$M$400,0)) -> 2 | BF26: =INDEX(SF_Output!$AB$2:$AB$400,MATCH($B26,SF_Output!$M$2:$M$400,0)) -> 1
B27: Teller Cash Recycler | C27: New | D27: Hosted by JHA | E27: 0 | F27: =IF(B27="","",IF(E27*1=0,"Included","Optional")) -> Included | G27: =IF(B27="","",INDEX(SF_Output!$K$1:$K$400,MATCH(B27,SF_Output!$M$1:$M$400,0))) -> Teller | H27: {=_xlfn.IFS(B27="","",(SUMIFS(SF_Output!$F$1:$F$400,SF_Output!$AC$1:$AC$400,_xlfn.TEXTJOIN(",",TRUE,B27:E27))+SUMIFS(SF_Output!$G$1:$G$400,SF_Output!$AC$1:$AC$400,_xlfn.TEXTJOIN(",",TRUE,B27:E27)))<>0,SF_Output!$Y$2,INDEX(SF_Output!$F$1:$F$400,MATCH(_xlfn.TEXTJOIN(",",TRUE,B27:E27),SF_Output!$AC$1:$AC$400,0))=0,INDEX(SF_Output!$R$1:$R$400,MATCH(_xlfn.TEXTJOIN(",",TRUE,B27:E27),SF_Output!$AC$1:$AC$400,0)))} -> 5000 | I27: =IFERROR(IF(AND(H27>1,H27<>""),ROUND(SUMIFS(SF_Output!$S$1:$S$400,SF_Output!$AC$1:$AC$400,_xlfn.TEXTJOIN(",",TRUE,B27:E27),SF_Output!$Q$1:$Q$400,"monthly")*(1-W27)/H27,4),""),"") -> 0.03 | J27: =IF(B27="","",SUMIFS(SF_Output!$S$1:$S$400,SF_Output!$AC$1:$AC$400,_xlfn.TEXTJOIN(",",TRUE,B27:E27),SF_Output!$Q$1:$Q$400,"One Time",SF_Output!$L$1:$L$400,"license fee")+SUMIFS(SF_Output!$S$1:$S$400,SF_Output!$AC$1:$AC$400,_xlfn.TEXTJOIN(",",TRUE,B27:E27),SF_Output!$Q$1:$Q$400,"One Time",SF_Output!$L$1:$L$400,"software license")+SUMIFS(SF_Output!$S$1:$S$400,SF_Output!$AC$1:$AC$400,_xlfn.TEXTJOIN(",",TRUE,B27:E27),SF_Output!$Q$1:$Q$400,"One Time",SF_Output!$L$1:$L$400,"hardware")) -> 0 | K27: =IF(OR(B27=0,B27="",G27="hardware",J27=0),"",IF(AF27<>"exclusion",MAX(K$9,-((SUMIFS(SF_Output!$T$1:$T$400,SF_Output!$AC$1:$AC$400,_xlfn.TEXTJOIN(",",TRUE,$B27:$E27),SF_Output!$Q$1:$Q$400,"One Time",SF_Output!$L$1:$L$400,"license fee")+SUMIFS(SF_Output!$T$1:$T$400,SF_Output!$AC$1:$AC$400,_xlfn.TEXTJOIN(",",TRUE,$B27:$E27),SF_Output!$Q$1:$Q$400,"One Time",SF_Output!$L$1:$L$400,"software license"))/J27)),-((SUMIFS(SF_Output!$T$1:$T$400,SF_Output!$AC$1:$AC$400,_xlfn.TEXTJOIN(",",TRUE,$B27:$E27),SF_Output!$Q$1:$Q$400,"One Time",SF_Output!$L$1:$L$400,"license fee")+SUMIFS(SF_Output!$T$1:$T$400,SF_Output!$AC$1:$AC$400,_xlfn.TEXTJOIN(",",TRUE,$B27:$E27),SF_Output!$Q$1:$Q$400,"One Time",SF_Output!$L$1:$L$400,"software license"))/J27))) | L27: =IF(K27="",J27,J27*(1-K27)) -> 0 | N27: =IF(B27="","",SUMIFS(SF_Output!$S$1:$S$400,SF_Output!$AC$1:$AC$400,_xlfn.TEXTJOIN(",",TRUE,B27:E27),SF_Output!$Q$1:$Q$400,"One Time",SF_Output!$L$1:$L$400,"professional service")) -> 855 | O27: =IF(OR(B27=0,B27="",N27=0),"",IF(AF27<>"exclusion",MAX(O$9,-(SUMIFS(SF_Output!$T$1:$T$400,SF_Output!$AC$1:$AC$400,_xlfn.TEXTJOIN(",",TRUE,$B27:$E27),SF_Output!$Q$1:$Q$400,"One Time",SF_Output!$L$1:$L$400,"professional service"))/N27),-((SUMIFS(SF_Output!$T$1:$T$400,SF_Output!$AC$1:$AC$400,_xlfn.TEXTJOIN(",",TRUE,$B27:$E27),SF_Output!$Q$1:$Q$400,"One Time",SF_Output!$L$1:$L$400,"professional service")/N27)))) -> 1 | P27: =IF(O27="",N27,N27*(1-O27)) -> 0 | R27: =IF(B27="","",SUMIFS(SF_Output!$S$1:$S$400,SF_Output!$AC$1:$AC$400,_xlfn.TEXTJOIN(",",TRUE,B27:E27),SF_Output!$Q$1:$Q$400,"yearly")+SUMIFS(SF_Output!$S$1:$S$400,SF_Output!$AC$1:$AC$400,_xlfn.TEXTJOIN(",",TRUE,B27:E27),SF_Output!$Q$1:$Q$400,"quarterly")*4) -> 0 | S27: =IF(OR(B27=0,B27="",G27="hardware",R27=0),"",IF(AF27<>"exclusion",MAX(S$9,-(SUMIFS(SF_Output!$T$1:$T$400,SF_Output!$AC$1:$AC$400,_xlfn.TEXTJOIN(",",TRUE,$B27:$E27),SF_Output!$Q$1:$Q$400,"yearly"))/R27),-((SUMIFS(SF_Output!$T$1:$T$400,SF_Output!$AC$1:$AC$400,_xlfn.TEXTJOIN(",",TRUE,$B27:$E27),SF_Output!$Q$1:$Q$400,"yearly")/R27)))) | T27: =IF(S27="",R27,R27*(1-S27)) -> 0 | V27: {=_xlfn.IFS(B27="","",AND(B27<>"",H27=SF_Output!$Y$2,SUMIFS(SF_Output!$T$1:$T$400,SF_Output!$AC$1:$AC$400,_xlfn.TEXTJOIN(",",TRUE,B27:E27),SF_Output!$Q$1:$Q$400,"monthly")=0),(SUMIFS(SF_Output!$F$1:$F$400,SF_Output!$AC$1:$AC$400,_xlfn.TEXTJOIN(",",TRUE,B27:E27),SF_Output!$Q$1:$Q$400,"monthly")+SUMIFS(SF_Output!$G$1:$G$400,SF_Output!$AC$1:$AC$400,_xlfn.TEXTJOIN(",",TRUE,B27:E27),SF_Output!$Q$1:$Q$400,"monthly"))*H27,AND(B27<>"",H27=SF_Output!$Y$2,SUMIFS(SF_Output!$T$1:$T$400,SF_Output!$AC$1:$AC$400,_xlfn.TEXTJOIN(",",TRUE,B27:E27),SF_Output!$Q$1:$Q$400,"monthly")<>0),SUMIFS(SF_Output!$S$1:$S$400,SF_Output!$AC$1:$AC$400,_xlfn.TEXTJOIN(",",TRUE,B27:E27),SF_Output!$Q$1:$Q$400,"monthly"),AND(B27<>"",H27<>SF_Output!$Y$2),SUMIFS(SF_Output!$S$1:$S$400,SF_Output!$AC$1:$AC$400,_xlfn.TEXTJOIN(",",TRUE,B27:E27),SF_Output!$Q$1:$Q$400,"monthly"))} -> 200 | W27: {=_xlfn.IFS(OR(B27=0,B27="",V27=0),"",AF27<>"exclusion",MAX($W$9,$W$7,(-(SUMIFS(SF_Output!$T$1:$T$400,SF_Output!$AC$1:$AC$400,_xlfn.TEXTJOIN(",",TRUE,$B27:$E27),SF_Output!$Q$1:$Q$400,"monthly"))/V27)),AF27="exclusion",-(SUMIFS(SF_Output!$T$1:$T$400,SF_Output!$AC$1:$AC$400,_xlfn.TEXTJOIN(",",TRUE,$B27:$E27),SF_Output!$Q$1:$Q$400,"monthly"))/V27)} -> 0.25 | X27: {=IFERROR(_xlfn.IFS(V27=0,0,V27="","",W27=0,V27,OR(V27<>0,V27<>""),H27*I27),V27*(1-W27))} -> 150 | Z27: =IFERROR(IF(B27="","",SUMIFS(Billing_Fallout!H:H,Billing_Fallout!N:N,B27)),0) -> 0 | AA27: =IF(Z27="","",AB27-Z27) -> 0 | AB27: =IFERROR(IF(B27="","",SUMIFS(Billing_Fallout!J:J,Billing_Fallout!N:N,B27)),0) -> 0 | AD27: =IFERROR(X27-AB27,"") -> 150 | AF27: =IFERROR(INDEX(H_Tables!$B$1:$B$1500,MATCH(INDEX(SF_Output!$J$1:$J$400,MATCH(B27,SF_Output!$M$1:$M$400,0)),H_Tables!$A$1:$A$1500,0)),"") | AI27: =IF(B27="","",IF(F27="remove","Remove Product",IF(F27="add","Add Product",_xlfn.TEXTJOIN(", ",TRUE,AQ27,AR27,AS27,AT27,AU27,AV27,AW27,AX27,AY27,AZ27,BA27,BB27,BC27)))) | AJ27: =IFERROR(INDEX(SF_Output!AD:AD,MATCH(_xlfn.TEXTJOIN(",",TRUE,B27:E27),SF_Output!AC1:AC400,0)),0.05) -> 46 | AK27: =IF(SUMIFS(SF_Output!$F$1:$F$400,SF_Output!$AC$1:$AC$400,_xlfn.TEXTJOIN(",",TRUE,B27:E27))+SUMIFS(SF_Output!$G$1:$G$400,SF_Output!$AC$1:$AC$400,_xlfn.TEXTJOIN(",",TRUE,B27:E27))=0,"","PAP") -> PAP | AL27: =LEFT(_xlfn.TEXTJOIN(",",TRUE,B27:E27),80) -> Teller Cash Recycler,New,Hosted by JHA,0 | AR27: {=IFERROR(_xlfn.IFS(AND(E27*1=1,F27="Included"),"Change to Included",AND(E27*1=0,F27="Optional"),"Change to Optional",OR(B27="",F27="replaced"),""),"")} | AS27: =IF((OR(NOT(_xlfn.ISFORMULA(J27)),NOT(_xlfn.ISFORMULA(L27)))),"Check License Price Override","") | AT27: =IF(OR(AND(K27=$K$9,K27<>0),NOT(_xlfn.ISFORMULA(K27))),"License Discount "&K27*100&"%","") | AU27: =IF((OR(NOT(_xlfn.ISFORMULA(N27)),NOT(_xlfn.ISFORMULA(P27)))),"Check Install Price Override","") | AV27: =IF(OR(AND(O27=$O$9,O27<>0),NOT(_xlfn.ISFORMULA(O27))),"Install Discount "&O27*100&"%","") | AW27: =IF((OR(NOT(_xlfn.ISFORMULA(R27)),NOT(_xlfn.ISFORMULA(T27)))),"Check Maintenance Price Override","") | AX27: =IF(OR(AND(S27=$S$9,S27<>0),NOT(_xlfn.ISFORMULA(S27))),"Maintenance Discount "&S27*100&"%","") | AY27: =IF((OR(NOT(_xlfn.ISFORMULA(V27)),NOT(_xlfn.ISFORMULA(X27)))),"Check Monthly Price Override","") | AZ27: =IF(OR((AND(W27=$W$9,W27<>0)),(AND(W27=$W$7,W27<>0)),(NOT(_xlfn.ISFORMULA(W27))),AND($W$7+0.2=W27,$W$7<>0)),"Monthly Discount "&W27*100&"%","") | BA27: =IF(NOT(_xlfn.ISFORMULA(H27)),"Check Quantity","") | BB27: =IF(NOT(_xlfn.ISFORMULA(I27)),"Check Unit Price Override","") | BE27: =INDEX(SF_Output!$AA$2:$AA$400,MATCH($B27,SF_Output!$M$2:$M$400,0)) -> 2 | BF27: =INDEX(SF_Output!$AB$2:$AB$400,MATCH($B27,SF_Output!$M$2:$M$400,0)) -> 2
B28: Teller CheckMaster Plus | C28: New | D28: Hosted by JHA | E28: 0 | F28: =IF(B28="","",IF(E28*1=0,"Included","Optional")) -> Included | G28: =IF(B28="","",INDEX(SF_Output!$K$1:$K$400,MATCH(B28,SF_Output!$M$1:$M$400,0))) -> Teller | H28: {=_xlfn.IFS(B28="","",(SUMIFS(SF_Output!$F$1:$F$400,SF_Output!$AC$1:$AC$400,_xlfn.TEXTJOIN(",",TRUE,B28:E28))+SUMIFS(SF_Output!$G$1:$G$400,SF_Output!$AC$1:$AC$400,_xlfn.TEXTJOIN(",",TRUE,B28:E28)))<>0,SF_Output!$Y$2,INDEX(SF_Output!$F$1:$F$400,MATCH(_xlfn.TEXTJOIN(",",TRUE,B28:E28),SF_Output!$AC$1:$AC$400,0))=0,INDEX(SF_Output!$R$1:$R$400,MATCH(_xlfn.TEXTJOIN(",",TRUE,B28:E28),SF_Output!$AC$1:$AC$400,0)))} -> 5000 | I28: =IFERROR(IF(AND(H28>1,H28<>""),ROUND(SUMIFS(SF_Output!$S$1:$S$400,SF_Output!$AC$1:$AC$400,_xlfn.TEXTJOIN(",",TRUE,B28:E28),SF_Output!$Q$1:$Q$400,"monthly")*(1-W28)/H28,4),""),"") -> 0.0135 | J28: =IF(B28="","",SUMIFS(SF_Output!$S$1:$S$400,SF_Output!$AC$1:$AC$400,_xlfn.TEXTJOIN(",",TRUE,B28:E28),SF_Output!$Q$1:$Q$400,"One Time",SF_Output!$L$1:$L$400,"license fee")+SUMIFS(SF_Output!$S$1:$S$400,SF_Output!$AC$1:$AC$400,_xlfn.TEXTJOIN(",",TRUE,B28:E28),SF_Output!$Q$1:$Q$400,"One Time",SF_Output!$L$1:$L$400,"software license")+SUMIFS(SF_Output!$S$1:$S$400,SF_Output!$AC$1:$AC$400,_xlfn.TEXTJOIN(",",TRUE,B28:E28),SF_Output!$Q$1:$Q$400,"One Time",SF_Output!$L$1:$L$400,"hardware")) -> 0 | K28: =IF(OR(B28=0,B28="",G28="hardware",J28=0),"",IF(AF28<>"exclusion",MAX(K$9,-((SUMIFS(SF_Output!$T$1:$T$400,SF_Output!$AC$1:$AC$400,_xlfn.TEXTJOIN(",",TRUE,$B28:$E28),SF_Output!$Q$1:$Q$400,"One Time",SF_Output!$L$1:$L$400,"license fee")+SUMIFS(SF_Output!$T$1:$T$400,SF_Output!$AC$1:$AC$400,_xlfn.TEXTJOIN(",",TRUE,$B28:$E28),SF_Output!$Q$1:$Q$400,"One Time",SF_Output!$L$1:$L$400,"software license"))/J28)),-((SUMIFS(SF_Output!$T$1:$T$400,SF_Output!$AC$1:$AC$400,_xlfn.TEXTJOIN(",",TRUE,$B28:$E28),SF_Output!$Q$1:$Q$400,"One Time",SF_Output!$L$1:$L$400,"license fee")+SUMIFS(SF_Output!$T$1:$T$400,SF_Output!$AC$1:$AC$400,_xlfn.TEXTJOIN(",",TRUE,$B28:$E28),SF_Output!$Q$1:$Q$400,"One Time",SF_Output!$L$1:$L$400,"software license"))/J28))) | L28: =IF(K28="",J28,J28*(1-K28)) -> 0 | N28: =IF(B28="","",SUMIFS(SF_Output!$S$1:$S$400,SF_Output!$AC$1:$AC$400,_xlfn.TEXTJOIN(",",TRUE,B28:E28),SF_Output!$Q$1:$Q$400,"One Time",SF_Output!$L$1:$L$400,"professional service")) -> 390 | O28: =IF(OR(B28=0,B28="",N28=0),"",IF(AF28<>"exclusion",MAX(O$9,-(SUMIFS(SF_Output!$T$1:$T$400,SF_Output!$AC$1:$AC$400,_xlfn.TEXTJOIN(",",TRUE,$B28:$E28),SF_Output!$Q$1:$Q$400,"One Time",SF_Output!$L$1:$L$400,"professional service"))/N28),-((SUMIFS(SF_Output!$T$1:$T$400,SF_Output!$AC$1:$AC$400,_xlfn.TEXTJOIN(",",TRUE,$B28:$E28),SF_Output!$Q$1:$Q$400,"One Time",SF_Output!$L$1:$L$400,"professional service")/N28)))) -> 1 | P28: =IF(O28="",N28,N28*(1-O28)) -> 0 | R28: =IF(B28="","",SUMIFS(SF_Output!$S$1:$S$400,SF_Output!$AC$1:$AC$400,_xlfn.TEXTJOIN(",",TRUE,B28:E28),SF_Output!$Q$1:$Q$400,"yearly")+SUMIFS(SF_Output!$S$1:$S$400,SF_Output!$AC$1:$AC$400,_xlfn.TEXTJOIN(",",TRUE,B28:E28),SF_Output!$Q$1:$Q$400,"quarterly")*4) -> 0 | S28: =IF(OR(B28=0,B28="",G28="hardware",R28=0),"",IF(AF28<>"exclusion",MAX(S$9,-(SUMIFS(SF_Output!$T$1:$T$400,SF_Output!$AC$1:$AC$400,_xlfn.TEXTJOIN(",",TRUE,$B28:$E28),SF_Output!$Q$1:$Q$400,"yearly"))/R28),-((SUMIFS(SF_Output!$T$1:$T$400,SF_Output!$AC$1:$AC$400,_xlfn.TEXTJOIN(",",TRUE,$B28:$E28),SF_Output!$Q$1:$Q$400,"yearly")/R28)))) | T28: =IF(S28="",R28,R28*(1-S28)) -> 0 | V28: {=_xlfn.IFS(B28="","",AND(B28<>"",H28=SF_Output!$Y$2,SUMIFS(SF_Output!$T$1:$T$400,SF_Output!$AC$1:$AC$400,_xlfn.TEXTJOIN(",",TRUE,B28:E28),SF_Output!$Q$1:$Q$400,"monthly")=0),(SUMIFS(SF_Output!$F$1:$F$400,SF_Output!$AC$1:$AC$400,_xlfn.TEXTJOIN(",",TRUE,B28:E28),SF_Output!$Q$1:$Q$400,"monthly")+SUMIFS(SF_Output!$G$1:$G$400,SF_Output!$AC$1:$AC$400,_xlfn.TEXTJOIN(",",TRUE,B28:E28),SF_Output!$Q$1:$Q$400,"monthly"))*H28,AND(B28<>"",H28=SF_Output!$Y$2,SUMIFS(SF_Output!$T$1:$T$400,SF_Output!$AC$1:$AC$400,_xlfn.TEXTJOIN(",",TRUE,B28:E28),SF_Output!$Q$1:$Q$400,"monthly")<>0),SUMIFS(SF_Output!$S$1:$S$400,SF_Output!$AC$1:$AC$400,_xlfn.TEXTJOIN(",",TRUE,B28:E28),SF_Output!$Q$1:$Q$400,"monthly"),AND(B28<>"",H28<>SF_Output!$Y$2),SUMIFS(SF_Output!$S$1:$S$400,SF_Output!$AC$1:$AC$400,_xlfn.TEXTJOIN(",",TRUE,B28:E28),SF_Output!$Q$1:$Q$400,"monthly"))} -> 90 | W28: {=_xlfn.IFS(OR(B28=0,B28="",V28=0),"",AF28<>"exclusion",MAX($W$9,$W$7,(-(SUMIFS(SF_Output!$T$1:$T$400,SF_Output!$AC$1:$AC$400,_xlfn.TEXTJOIN(",",TRUE,$B28:$E28),SF_Output!$Q$1:$Q$400,"monthly"))/V28)),AF28="exclusion",-(SUMIFS(SF_Output!$T$1:$T$400,SF_Output!$AC$1:$AC$400,_xlfn.TEXTJOIN(",",TRUE,$B28:$E28),SF_Output!$Q$1:$Q$400,"monthly"))/V28)} -> 0.25 | X28: {=IFERROR(_xlfn.IFS(V28=0,0,V28="","",W28=0,V28,OR(V28<>0,V28<>""),H28*I28),V28*(1-W28))} -> 67.5 | Z28: =IFERROR(IF(B28="","",SUMIFS(Billing_Fallout!H:H,Billing_Fallout!N:N,B28)),0) -> 0 | AA28: =IF(Z28="","",AB28-Z28) -> 0 | AB28: =IFERROR(IF(B28="","",SUMIFS(Billing_Fallout!J:J,Billing_Fallout!N:N,B28)),0) -> 0 | AD28: =IFERROR(X28-AB28,"") -> 67.5 | AF28: =IFERROR(INDEX(H_Tables!$B$1:$B$1500,MATCH(INDEX(SF_Output!$J$1:$J$400,MATCH(B28,SF_Output!$M$1:$M$400,0)),H_Tables!$A$1:$A$1500,0)),"") | AI28: =IF(B28="","",IF(F28="remove","Remove Product",IF(F28="add","Add Product",_xlfn.TEXTJOIN(", ",TRUE,AQ28,AR28,AS28,AT28,AU28,AV28,AW28,AX28,AY28,AZ28,BA28,BB28,BC28)))) | AJ28: =IFERROR(INDEX(SF_Output!AD:AD,MATCH(_xlfn.TEXTJOIN(",",TRUE,B28:E28),SF_Output!AC1:AC400,0)),0.05) -> 48 | AK28: =IF(SUMIFS(SF_Output!$F$1:$F$400,SF_Output!$AC$1:$AC$400,_xlfn.TEXTJOIN(",",TRUE,B28:E28))+SUMIFS(SF_Output!$G$1:$G$400,SF_Output!$AC$1:$AC$400,_xlfn.TEXTJOIN(",",TRUE,B28:E28))=0,"","PAP") -> PAP | AL28: =LEFT(_xlfn.TEXTJOIN(",",TRUE,B28:E28),80) -> Teller CheckMaster Plus,New,Hosted by JHA,0 | AR28: {=IFERROR(_xlfn.IFS(AND(E28*1=1,F28="Included"),"Change to Included",AND(E28*1=0,F28="Optional"),"Change to Optional",OR(B28="",F28="replaced"),""),"")} | AS28: =IF((OR(NOT(_xlfn.ISFORMULA(J28)),NOT(_xlfn.ISFORMULA(L28)))),"Check License Price Override","") | AT28: =IF(OR(AND(K28=$K$9,K28<>0),NOT(_xlfn.ISFORMULA(K28))),"License Discount "&K28*100&"%","") | AU28: =IF((OR(NOT(_xlfn.ISFORMULA(N28)),NOT(_xlfn.ISFORMULA(P28)))),"Check Install Price Override","") | AV28: =IF(OR(AND(O28=$O$9,O28<>0),NOT(_xlfn.ISFORMULA(O28))),"Install Discount "&O28*100&"%","") | AW28: =IF((OR(NOT(_xlfn.ISFORMULA(R28)),NOT(_xlfn.ISFORMULA(T28)))),"Check Maintenance Price Override","") | AX28: =IF(OR(AND(S28=$S$9,S28<>0),NOT(_xlfn.ISFORMULA(S28))),"Maintenance Discount "&S28*100&"%","") | AY28: =IF((OR(NOT(_xlfn.ISFORMULA(V28)),NOT(_xlfn.ISFORMULA(X28)))),"Check Monthly Price Override","") | AZ28: =IF(OR((AND(W28=$W$9,W28<>0)),(AND(W28=$W$7,W28<>0)),(NOT(_xlfn.ISFORMULA(W28))),AND($W$7+0.2=W28,$W$7<>0)),"Monthly Discount "&W28*100&"%","") | BA28: =IF(NOT(_xlfn.ISFORMULA(H28)),"Check Quantity","") | BB28: =IF(NOT(_xlfn.ISFORMULA(I28)),"Check Unit Price Override","") | BE28: =INDEX(SF_Output!$AA$2:$AA$400,MATCH($B28,SF_Output!$M$2:$M$400,0)) -> 2 | BF28: =INDEX(SF_Output!$AB$2:$AB$400,MATCH($B28,SF_Output!$M$2:$M$400,0)) -> 2
B29: Teller Email Receipts | C29: New | D29: Hosted by JHA | E29: 0 | F29: =IF(B29="","",IF(E29*1=0,"Included","Optional")) -> Included | G29: =IF(B29="","",INDEX(SF_Output!$K$1:$K$400,MATCH(B29,SF_Output!$M$1:$M$400,0))) -> Teller | H29: {=_xlfn.IFS(B29="","",(SUMIFS(SF_Output!$F$1:$F$400,SF_Output!$AC$1:$AC$400,_xlfn.TEXTJOIN(",",TRUE,B29:E29))+SUMIFS(SF_Output!$G$1:$G$400,SF_Output!$AC$1:$AC$400,_xlfn.TEXTJOIN(",",TRUE,B29:E29)))<>0,SF_Output!$Y$2,INDEX(SF_Output!$F$1:$F$400,MATCH(_xlfn.TEXTJOIN(",",TRUE,B29:E29),SF_Output!$AC$1:$AC$400,0))=0,INDEX(SF_Output!$R$1:$R$400,MATCH(_xlfn.TEXTJOIN(",",TRUE,B29:E29),SF_Output!$AC$1:$AC$400,0)))} -> 1 | I29: =IFERROR(IF(AND(H29>1,H29<>""),ROUND(SUMIFS(SF_Output!$S$1:$S$400,SF_Output!$AC$1:$AC$400,_xlfn.TEXTJOIN(",",TRUE,B29:E29),SF_Output!$Q$1:$Q$400,"monthly")*(1-W29)/H29,4),""),"") | J29: =IF(B29="","",SUMIFS(SF_Output!$S$1:$S$400,SF_Output!$AC$1:$AC$400,_xlfn.TEXTJOIN(",",TRUE,B29:E29),SF_Output!$Q$1:$Q$400,"One Time",SF_Output!$L$1:$L$400,"license fee")+SUMIFS(SF_Output!$S$1:$S$400,SF_Output!$AC$1:$AC$400,_xlfn.TEXTJOIN(",",TRUE,B29:E29),SF_Output!$Q$1:$Q$400,"One Time",SF_Output!$L$1:$L$400,"software license")+SUMIFS(SF_Output!$S$1:$S$400,SF_Output!$AC$1:$AC$400,_xlfn.TEXTJOIN(",",TRUE,B29:E29),SF_Output!$Q$1:$Q$400,"One Time",SF_Output!$L$1:$L$400,"hardware")) -> 0 | K29: =IF(OR(B29=0,B29="",G29="hardware",J29=0),"",IF(AF29<>"exclusion",MAX(K$9,-((SUMIFS(SF_Output!$T$1:$T$400,SF_Output!$AC$1:$AC$400,_xlfn.TEXTJOIN(",",TRUE,$B29:$E29),SF_Output!$Q$1:$Q$400,"One Time",SF_Output!$L$1:$L$400,"license fee")+SUMIFS(SF_Output!$T$1:$T$400,SF_Output!$AC$1:$AC$400,_xlfn.TEXTJOIN(",",TRUE,$B29:$E29),SF_Output!$Q$1:$Q$400,"One Time",SF_Output!$L$1:$L$400,"software license"))/J29)),-((SUMIFS(SF_Output!$T$1:$T$400,SF_Output!$AC$1:$AC$400,_xlfn.TEXTJOIN(",",TRUE,$B29:$E29),SF_Output!$Q$1:$Q$400,"One Time",SF_Output!$L$1:$L$400,"license fee")+SUMIFS(SF_Output!$T$1:$T$400,SF_Output!$AC$1:$AC$400,_xlfn.TEXTJOIN(",",TRUE,$B29:$E29),SF_Output!$Q$1:$Q$400,"One Time",SF_Output!$L$1:$L$400,"software license"))/J29))) | L29: =IF(K29="",J29,J29*(1-K29)) -> 0 | N29: =IF(B29="","",SUMIFS(SF_Output!$S$1:$S$400,SF_Output!$AC$1:$AC$400,_xlfn.TEXTJOIN(",",TRUE,B29:E29),SF_Output!$Q$1:$Q$400,"One Time",SF_Output!$L$1:$L$400,"professional service")) -> 3750 | O29: =IF(OR(B29=0,B29="",N29=0),"",IF(AF29<>"exclusion",MAX(O$9,-(SUMIFS(SF_Output!$T$1:$T$400,SF_Output!$AC$1:$AC$400,_xlfn.TEXTJOIN(",",TRUE,$B29:$E29),SF_Output!$Q$1:$Q$400,"One Time",SF_Output!$L$1:$L$400,"professional service"))/N29),-((SUMIFS(SF_Output!$T$1:$T$400,SF_Output!$AC$1:$AC$400,_xlfn.TEXTJOIN(",",TRUE,$B29:$E29),SF_Output!$Q$1:$Q$400,"One Time",SF_Output!$L$1:$L$400,"professional service")/N29)))) -> 1 | P29: =IF(O29="",N29,N29*(1-O29)) -> 0 | R29: =IF(B29="","",SUMIFS(SF_Output!$S$1:$S$400,SF_Output!$AC$1:$AC$400,_xlfn.TEXTJOIN(",",TRUE,B29:E29),SF_Output!$Q$1:$Q$400,"yearly")+SUMIFS(SF_Output!$S$1:$S$400,SF_Output!$AC$1:$AC$400,_xlfn.TEXTJOIN(",",TRUE,B29:E29),SF_Output!$Q$1:$Q$400,"quarterly")*4) -> 0 | S29: =IF(OR(B29=0,B29="",G29="hardware",R29=0),"",IF(AF29<>"exclusion",MAX(S$9,-(SUMIFS(SF_Output!$T$1:$T$400,SF_Output!$AC$1:$AC$400,_xlfn.TEXTJOIN(",",TRUE,$B29:$E29),SF_Output!$Q$1:$Q$400,"yearly"))/R29),-((SUMIFS(SF_Output!$T$1:$T$400,SF_Output!$AC$1:$AC$400,_xlfn.TEXTJOIN(",",TRUE,$B29:$E29),SF_Output!$Q$1:$Q$400,"yearly")/R29)))) | T29: =IF(S29="",R29,R29*(1-S29)) -> 0 | V29: {=_xlfn.IFS(B29="","",AND(B29<>"",H29=SF_Output!$Y$2,SUMIFS(SF_Output!$T$1:$T$400,SF_Output!$AC$1:$AC$400,_xlfn.TEXTJOIN(",",TRUE,B29:E29),SF_Output!$Q$1:$Q$400,"monthly")=0),(SUMIFS(SF_Output!$F$1:$F$400,SF_Output!$AC$1:$AC$400,_xlfn.TEXTJOIN(",",TRUE,B29:E29),SF_Output!$Q$1:$Q$400,"monthly")+SUMIFS(SF_Output!$G$1:$G$400,SF_Output!$AC$1:$AC$400,_xlfn.TEXTJOIN(",",TRUE,B29:E29),SF_Output!$Q$1:$Q$400,"monthly"))*H29,AND(B29<>"",H29=SF_Output!$Y$2,SUMIFS(SF_Output!$T$1:$T$400,SF_Output!$AC$1:$AC$400,_xlfn.TEXTJOIN(",",TRUE,B29:E29),SF_Output!$Q$1:$Q$400,"monthly")<>0),SUMIFS(SF_Output!$S$1:$S$400,SF_Output!$AC$1:$AC$400,_xlfn.TEXTJOIN(",",TRUE,B29:E29),SF_Output!$Q$1:$Q$400,"monthly"),AND(B29<>"",H29<>SF_Output!$Y$2),SUMIFS(SF_Output!$S$1:$S$400,SF_Output!$AC$1:$AC$400,_xlfn.TEXTJOIN(",",TRUE,B29:E29),SF_Output!$Q$1:$Q$400,"monthly"))} -> 0 | W29: {=_xlfn.IFS(OR(B29=0,B29="",V29=0),"",AF29<>"exclusion",MAX($W$9,$W$7,(-(SUMIFS(SF_Output!$T$1:$T$400,SF_Output!$AC$1:$AC$400,_xlfn.TEXTJOIN(",",TRUE,$B29:$E29),SF_Output!$Q$1:$Q$400,"monthly"))/V29)),AF29="exclusion",-(SUMIFS(SF_Output!$T$1:$T$400,SF_Output!$AC$1:$AC$400,_xlfn.TEXTJOIN(",",TRUE,$B29:$E29),SF_Output!$Q$1:$Q$400,"monthly"))/V29)} | X29: {=IFERROR(_xlfn.IFS(V29=0,0,V29="","",W29=0,V29,OR(V29<>0,V29<>""),H29*I29),V29*(1-W29))} -> 0 | Z29: =IFERROR(IF(B29="","",SUMIFS(Billing_Fallout!H:H,Billing_Fallout!N:N,B29)),0) -> 0 | AA29: =IF(Z29="","",AB29-Z29) -> 0 | AB29: =IFERROR(IF(B29="","",SUMIFS(Billing_Fallout!J:J,Billing_Fallout!N:N,B29)),0) -> 0 | AD29: =IFERROR(X29-AB29,"") -> 0 | AF29: =IFERROR(INDEX(H_Tables!$B$1:$B$1500,MATCH(INDEX(SF_Output!$J$1:$J$400,MATCH(B29,SF_Output!$M$1:$M$400,0)),H_Tables!$A$1:$A$1500,0)),"") | AI29: =IF(B29="","",IF(F29="remove","Remove Product",IF(F29="add","Add Product",_xlfn.TEXTJOIN(", ",TRUE,AQ29,AR29,AS29,AT29,AU29,AV29,AW29,AX29,AY29,AZ29,BA29,BB29,BC29)))) | AJ29: =IFERROR(INDEX(SF_Output!AD:AD,MATCH(_xlfn.TEXTJOIN(",",TRUE,B29:E29),SF_Output!AC1:AC400,0)),0.05) -> 50 | AK29: =IF(SUMIFS(SF_Output!$F$1:$F$400,SF_Output!$AC$1:$AC$400,_xlfn.TEXTJOIN(",",TRUE,B29:E29))+SUMIFS(SF_Output!$G$1:$G$400,SF_Output!$AC$1:$AC$400,_xlfn.TEXTJOIN(",",TRUE,B29:E29))=0,"","PAP") | AL29: =LEFT(_xlfn.TEXTJOIN(",",TRUE,B29:E29),80) -> Teller Email Receipts,New,Hosted by JHA,0 | AR29: {=IFERROR(_xlfn.IFS(AND(E29*1=1,F29="Included"),"Change to Included",AND(E29*1=0,F29="Optional"),"Change to Optional",OR(B29="",F29="replaced"),""),"")} | AS29: =IF((OR(NOT(_xlfn.ISFORMULA(J29)),NOT(_xlfn.ISFORMULA(L29)))),"Check License Price Override","") | AT29: =IF(OR(AND(K29=$K$9,K29<>0),NOT(_xlfn.ISFORMULA(K29))),"License Discount "&K29*100&"%","") | AU29: =IF((OR(NOT(_xlfn.ISFORMULA(N29)),NOT(_xlfn.ISFORMULA(P29)))),"Check Install Price Override","") | AV29: =IF(OR(AND(O29=$O$9,O29<>0),NOT(_xlfn.ISFORMULA(O29))),"Install Discount "&O29*100&"%","") | AW29: =IF((OR(NOT(_xlfn.ISFORMULA(R29)),NOT(_xlfn.ISFORMULA(T29)))),"Check Maintenance Price Override","") | AX29: =IF(OR(AND(S29=$S$9,S29<>0),NOT(_xlfn.ISFORMULA(S29))),"Maintenance Discount "&S29*100&"%","") | AY29: =IF((OR(NOT(_xlfn.ISFORMULA(V29)),NOT(_xlfn.ISFORMULA(X29)))),"Check Monthly Price Override","") | AZ29: =IF(OR((AND(W29=$W$9,W29<>0)),(AND(W29=$W$7,W29<>0)),(NOT(_xlfn.ISFORMULA(W29))),AND($W$7+0.2=W29,$W$7<>0)),"Monthly Discount "&W29*100&"%","") | BA29: =IF(NOT(_xlfn.ISFORMULA(H29)),"Check Quantity","") | BB29: =IF(NOT(_xlfn.ISFORMULA(I29)),"Check Unit Price Override","") | BE29: =INDEX(SF_Output!$AA$2:$AA$400,MATCH($B29,SF_Output!$M$2:$M$400,0)) -> 2 | BF29: =INDEX(SF_Output!$AB$2:$AB$400,MATCH($B29,SF_Output!$M$2:$M$400,0)) -> 2
B30: Teller OrboAnywhere AI Recognition | C30: New | D30: On Premise License | E30: 0 | F30: =IF(B30="","",IF(E30*1=0,"Included","Optional")) -> Included | G30: =IF(B30="","",INDEX(SF_Output!$K$1:$K$400,MATCH(B30,SF_Output!$M$1:$M$400,0))) -> Teller | H30: {=_xlfn.IFS(B30="","",(SUMIFS(SF_Output!$F$1:$F$400,SF_Output!$AC$1:$AC$400,_xlfn.TEXTJOIN(",",TRUE,B30:E30))+SUMIFS(SF_Output!$G$1:$G$400,SF_Output!$AC$1:$AC$400,_xlfn.TEXTJOIN(",",TRUE,B30:E30)))<>0,SF_Output!$Y$2,INDEX(SF_Output!$F$1:$F$400,MATCH(_xlfn.TEXTJOIN(",",TRUE,B30:E30),SF_Output!$AC$1:$AC$400,0))=0,INDEX(SF_Output!$R$1:$R$400,MATCH(_xlfn.TEXTJOIN(",",TRUE,B30:E30),SF_Output!$AC$1:$AC$400,0)))} -> 1 | I30: =IFERROR(IF(AND(H30>1,H30<>""),ROUND(SUMIFS(SF_Output!$S$1:$S$400,SF_Output!$AC$1:$AC$400,_xlfn.TEXTJOIN(",",TRUE,B30:E30),SF_Output!$Q$1:$Q$400,"monthly")*(1-W30)/H30,4),""),"") | J30: =IF(B30="","",SUMIFS(SF_Output!$S$1:$S$400,SF_Output!$AC$1:$AC$400,_xlfn.TEXTJOIN(",",TRUE,B30:E30),SF_Output!$Q$1:$Q$400,"One Time",SF_Output!$L$1:$L$400,"license fee")+SUMIFS(SF_Output!$S$1:$S$400,SF_Output!$AC$1:$AC$400,_xlfn.TEXTJOIN(",",TRUE,B30:E30),SF_Output!$Q$1:$Q$400,"One Time",SF_Output!$L$1:$L$400,"software license")+SUMIFS(SF_Output!$S$1:$S$400,SF_Output!$AC$1:$AC$400,_xlfn.TEXTJOIN(",",TRUE,B30:E30),SF_Output!$Q$1:$Q$400,"One Time",SF_Output!$L$1:$L$400,"hardware")) -> 4909 | K30: =IF(OR(B30=0,B30="",G30="hardware",J30=0),"",IF(AF30<>"exclusion",MAX(K$9,-((SUMIFS(SF_Output!$T$1:$T$400,SF_Output!$AC$1:$AC$400,_xlfn.TEXTJOIN(",",TRUE,$B30:$E30),SF_Output!$Q$1:$Q$400,"One Time",SF_Output!$L$1:$L$400,"license fee")+SUMIFS(SF_Output!$T$1:$T$400,SF_Output!$AC$1:$AC$400,_xlfn.TEXTJOIN(",",TRUE,$B30:$E30),SF_Output!$Q$1:$Q$400,"One Time",SF_Output!$L$1:$L$400,"software license"))/J30)),-((SUMIFS(SF_Output!$T$1:$T$400,SF_Output!$AC$1:$AC$400,_xlfn.TEXTJOIN(",",TRUE,$B30:$E30),SF_Output!$Q$1:$Q$400,"One Time",SF_Output!$L$1:$L$400,"license fee")+SUMIFS(SF_Output!$T$1:$T$400,SF_Output!$AC$1:$AC$400,_xlfn.TEXTJOIN(",",TRUE,$B30:$E30),SF_Output!$Q$1:$Q$400,"One Time",SF_Output!$L$1:$L$400,"software license"))/J30))) -> 0 | L30: =IF(K30="",J30,J30*(1-K30)) -> 4909 | N30: =IF(B30="","",SUMIFS(SF_Output!$S$1:$S$400,SF_Output!$AC$1:$AC$400,_xlfn.TEXTJOIN(",",TRUE,B30:E30),SF_Output!$Q$1:$Q$400,"One Time",SF_Output!$L$1:$L$400,"professional service")) -> 0 | O30: =IF(OR(B30=0,B30="",N30=0),"",IF(AF30<>"exclusion",MAX(O$9,-(SUMIFS(SF_Output!$T$1:$T$400,SF_Output!$AC$1:$AC$400,_xlfn.TEXTJOIN(",",TRUE,$B30:$E30),SF_Output!$Q$1:$Q$400,"One Time",SF_Output!$L$1:$L$400,"professional service"))/N30),-((SUMIFS(SF_Output!$T$1:$T$400,SF_Output!$AC$1:$AC$400,_xlfn.TEXTJOIN(",",TRUE,$B30:$E30),SF_Output!$Q$1:$Q$400,"One Time",SF_Output!$L$1:$L$400,"professional service")/N30)))) | P30: =IF(O30="",N30,N30*(1-O30)) -> 0 | R30: =IF(B30="","",SUMIFS(SF_Output!$S$1:$S$400,SF_Output!$AC$1:$AC$400,_xlfn.TEXTJOIN(",",TRUE,B30:E30),SF_Output!$Q$1:$Q$400,"yearly")+SUMIFS(SF_Output!$S$1:$S$400,SF_Output!$AC$1:$AC$400,_xlfn.TEXTJOIN(",",TRUE,B30:E30),SF_Output!$Q$1:$Q$400,"quarterly")*4) -> 982 | S30: =IF(OR(B30=0,B30="",G30="hardware",R30=0),"",IF(AF30<>"exclusion",MAX(S$9,-(SUMIFS(SF_Output!$T$1:$T$400,SF_Output!$AC$1:$AC$400,_xlfn.TEXTJOIN(",",TRUE,$B30:$E30),SF_Output!$Q$1:$Q$400,"yearly"))/R30),-((SUMIFS(SF_Output!$T$1:$T$400,SF_Output!$AC$1:$AC$400,_xlfn.TEXTJOIN(",",TRUE,$B30:$E30),SF_Output!$Q$1:$Q$400,"yearly")/R30)))) -> 0 | T30: =IF(S30="",R30,R30*(1-S30)) -> 982 | V30: {=_xlfn.IFS(B30="","",AND(B30<>"",H30=SF_Output!$Y$2,SUMIFS(SF_Output!$T$1:$T$400,SF_Output!$AC$1:$AC$400,_xlfn.TEXTJOIN(",",TRUE,B30:E30),SF_Output!$Q$1:$Q$400,"monthly")=0),(SUMIFS(SF_Output!$F$1:$F$400,SF_Output!$AC$1:$AC$400,_xlfn.TEXTJOIN(",",TRUE,B30:E30),SF_Output!$Q$1:$Q$400,"monthly")+SUMIFS(SF_Output!$G$1:$G$400,SF_Output!$AC$1:$AC$400,_xlfn.TEXTJOIN(",",TRUE,B30:E30),SF_Output!$Q$1:$Q$400,"monthly"))*H30,AND(B30<>"",H30=SF_Output!$Y$2,SUMIFS(SF_Output!$T$1:$T$400,SF_Output!$AC$1:$AC$400,_xlfn.TEXTJOIN(",",TRUE,B30:E30),SF_Output!$Q$1:$Q$400,"monthly")<>0),SUMIFS(SF_Output!$S$1:$S$400,SF_Output!$AC$1:$AC$400,_xlfn.TEXTJOIN(",",TRUE,B30:E30),SF_Output!$Q$1:$Q$400,"monthly"),AND(B30<>"",H30<>SF_Output!$Y$2),SUMIFS(SF_Output!$S$1:$S$400,SF_Output!$AC$1:$AC$400,_xlfn.TEXTJOIN(",",TRUE,B30:E30),SF_Output!$Q$1:$Q$400,"monthly"))} -> 0 | W30: {=_xlfn.IFS(OR(B30=0,B30="",V30=0),"",AF30<>"exclusion",MAX($W$9,$W$7,(-(SUMIFS(SF_Output!$T$1:$T$400,SF_Output!$AC$1:$AC$400,_xlfn.TEXTJOIN(",",TRUE,$B30:$E30),SF_Output!$Q$1:$Q$400,"monthly"))/V30)),AF30="exclusion",-(SUMIFS(SF_Output!$T$1:$T$400,SF_Output!$AC$1:$AC$400,_xlfn.TEXTJOIN(",",TRUE,$B30:$E30),SF_Output!$Q$1:$Q$400,"monthly"))/V30)} | X30: {=IFERROR(_xlfn.IFS(V30=0,0,V30="","",W30=0,V30,OR(V30<>0,V30<>""),H30*I30),V30*(1-W30))} -> 0 | Z30: =IFERROR(IF(B30="","",SUMIFS(Billing_Fallout!H:H,Billing_Fallout!N:N,B30)),0) -> 0 | AA30: =IF(Z30="","",AB30-Z30) -> 0 | AB30: =IFERROR(IF(B30="","",SUMIFS(Billing_Fallout!J:J,Billing_Fallout!N:N,B30)),0) -> 0 | AD30: =IFERROR(X30-AB30,"") -> 0 | AF30: =IFERROR(INDEX(H_Tables!$B$1:$B$1500,MATCH(INDEX(SF_Output!$J$1:$J$400,MATCH(B30,SF_Output!$M$1:$M$400,0)),H_Tables!$A$1:$A$1500,0)),"") -> Exclusion | AI30: =IF(B30="","",IF(F30="remove","Remove Product",IF(F30="add","Add Product",_xlfn.TEXTJOIN(", ",TRUE,AQ30,AR30,AS30,AT30,AU30,AV30,AW30,AX30,AY30,AZ30,BA30,BB30,BC30)))) | AJ30: =IFERROR(INDEX(SF_Output!AD:AD,MATCH(_xlfn.TEXTJOIN(",",TRUE,B30:E30),SF_Output!AC1:AC400,0)),0.05) -> 51 | AK30: =IF(SUMIFS(SF_Output!$F$1:$F$400,SF_Output!$AC$1:$AC$400,_xlfn.TEXTJOIN(",",TRUE,B30:E30))+SUMIFS(SF_Output!$G$1:$G$400,SF_Output!$AC$1:$AC$400,_xlfn.TEXTJOIN(",",TRUE,B30:E30))=0,"","PAP") | AL30: =LEFT(_xlfn.TEXTJOIN(",",TRUE,B30:E30),80) -> Teller OrboAnywhere AI Recognition,New,On Premise License,0 | AR30: {=IFERROR(_xlfn.IFS(AND(E30*1=1,F30="Included"),"Change to Included",AND(E30*1=0,F30="Optional"),"Change to Optional",OR(B30="",F30="replaced"),""),"")} | AS30: =IF((OR(NOT(_xlfn.ISFORMULA(J30)),NOT(_xlfn.ISFORMULA(L30)))),"Check License Price Override","") | AT30: =IF(OR(AND(K30=$K$9,K30<>0),NOT(_xlfn.ISFORMULA(K30))),"License Discount "&K30*100&"%","") | AU30: =IF((OR(NOT(_xlfn.ISFORMULA(N30)),NOT(_xlfn.ISFORMULA(P30)))),"Check Install Price Override","") | AV30: =IF(OR(AND(O30=$O$9,O30<>0),NOT(_xlfn.ISFORMULA(O30))),"Install Discount "&O30*100&"%","") | AW30: =IF((OR(NOT(_xlfn.ISFORMULA(R30)),NOT(_xlfn.ISFORMULA(T30)))),"Check Maintenance Price Override","") | AX30: =IF(OR(AND(S30=$S$9,S30<>0),NOT(_xlfn.ISFORMULA(S30))),"Maintenance Discount "&S30*100&"%","") | AY30: =IF((OR(NOT(_xlfn.ISFORMULA(V30)),NOT(_xlfn.ISFORMULA(X30)))),"Check Monthly Price Override","") | AZ30: =IF(OR((AND(W30=$W$9,W30<>0)),(AND(W30=$W$7,W30<>0)),(NOT(_xlfn.ISFORMULA(W30))),AND($W$7+0.2=W30,$W$7<>0)),"Monthly Discount "&W30*100&"%","") | BA30: =IF(NOT(_xlfn.ISFORMULA(H30)),"Check Quantity","") | BB30: =IF(NOT(_xlfn.ISFORMULA(I30)),"Check Unit Price Override","") | BE30: =INDEX(SF_Output!$AA$2:$AA$400,MATCH($B30,SF_Output!$M$2:$M$400,0)) -> 2 | BF30: =INDEX(SF_Output!$AB$2:$AB$400,MATCH($B30,SF_Output!$M$2:$M$400,0)) -> 2
B31: Teller OrboAnywhere AI Validate | C31: New | D31: On Premise License | E31: 0 | F31: =IF(B31="","",IF(E31*1=0,"Included","Optional")) -> Included | G31: =IF(B31="","",INDEX(SF_Output!$K$1:$K$400,MATCH(B31,SF_Output!$M$1:$M$400,0))) -> Teller | H31: {=_xlfn.IFS(B31="","",(SUMIFS(SF_Output!$F$1:$F$400,SF_Output!$AC$1:$AC$400,_xlfn.TEXTJOIN(",",TRUE,B31:E31))+SUMIFS(SF_Output!$G$1:$G$400,SF_Output!$AC$1:$AC$400,_xlfn.TEXTJOIN(",",TRUE,B31:E31)))<>0,SF_Output!$Y$2,INDEX(SF_Output!$F$1:$F$400,MATCH(_xlfn.TEXTJOIN(",",TRUE,B31:E31),SF_Output!$AC$1:$AC$400,0))=0,INDEX(SF_Output!$R$1:$R$400,MATCH(_xlfn.TEXTJOIN(",",TRUE,B31:E31),SF_Output!$AC$1:$AC$400,0)))} -> 1 | I31: =IFERROR(IF(AND(H31>1,H31<>""),ROUND(SUMIFS(SF_Output!$S$1:$S$400,SF_Output!$AC$1:$AC$400,_xlfn.TEXTJOIN(",",TRUE,B31:E31),SF_Output!$Q$1:$Q$400,"monthly")*(1-W31)/H31,4),""),"") | J31: =IF(B31="","",SUMIFS(SF_Output!$S$1:$S$400,SF_Output!$AC$1:$AC$400,_xlfn.TEXTJOIN(",",TRUE,B31:E31),SF_Output!$Q$1:$Q$400,"One Time",SF_Output!$L$1:$L$400,"license fee")+SUMIFS(SF_Output!$S$1:$S$400,SF_Output!$AC$1:$AC$400,_xlfn.TEXTJOIN(",",TRUE,B31:E31),SF_Output!$Q$1:$Q$400,"One Time",SF_Output!$L$1:$L$400,"software license")+SUMIFS(SF_Output!$S$1:$S$400,SF_Output!$AC$1:$AC$400,_xlfn.TEXTJOIN(",",TRUE,B31:E31),SF_Output!$Q$1:$Q$400,"One Time",SF_Output!$L$1:$L$400,"hardware")) -> 1636 | K31: =IF(OR(B31=0,B31="",G31="hardware",J31=0),"",IF(AF31<>"exclusion",MAX(K$9,-((SUMIFS(SF_Output!$T$1:$T$400,SF_Output!$AC$1:$AC$400,_xlfn.TEXTJOIN(",",TRUE,$B31:$E31),SF_Output!$Q$1:$Q$400,"One Time",SF_Output!$L$1:$L$400,"license fee")+SUMIFS(SF_Output!$T$1:$T$400,SF_Output!$AC$1:$AC$400,_xlfn.TEXTJOIN(",",TRUE,$B31:$E31),SF_Output!$Q$1:$Q$400,"One Time",SF_Output!$L$1:$L$400,"software license"))/J31)),-((SUMIFS(SF_Output!$T$1:$T$400,SF_Output!$AC$1:$AC$400,_xlfn.TEXTJOIN(",",TRUE,$B31:$E31),SF_Output!$Q$1:$Q$400,"One Time",SF_Output!$L$1:$L$400,"license fee")+SUMIFS(SF_Output!$T$1:$T$400,SF_Output!$AC$1:$AC$400,_xlfn.TEXTJOIN(",",TRUE,$B31:$E31),SF_Output!$Q$1:$Q$400,"One Time",SF_Output!$L$1:$L$400,"software license"))/J31))) -> 0 | L31: =IF(K31="",J31,J31*(1-K31)) -> 1636 | N31: =IF(B31="","",SUMIFS(SF_Output!$S$1:$S$400,SF_Output!$AC$1:$AC$400,_xlfn.TEXTJOIN(",",TRUE,B31:E31),SF_Output!$Q$1:$Q$400,"One Time",SF_Output!$L$1:$L$400,"professional service")) -> 0 | O31: =IF(OR(B31=0,B31="",N31=0),"",IF(AF31<>"exclusion",MAX(O$9,-(SUMIFS(SF_Output!$T$1:$T$400,SF_Output!$AC$1:$AC$400,_xlfn.TEXTJOIN(",",TRUE,$B31:$E31),SF_Output!$Q$1:$Q$400,"One Time",SF_Output!$L$1:$L$400,"professional service"))/N31),-((SUMIFS(SF_Output!$T$1:$T$400,SF_Output!$AC$1:$AC$400,_xlfn.TEXTJOIN(",",TRUE,$B31:$E31),SF_Output!$Q$1:$Q$400,"One Time",SF_Output!$L$1:$L$400,"professional service")/N31)))) | P31: =IF(O31="",N31,N31*(1-O31)) -> 0 | R31: =IF(B31="","",SUMIFS(SF_Output!$S$1:$S$400,SF_Output!$AC$1:$AC$400,_xlfn.TEXTJOIN(",",TRUE,B31:E31),SF_Output!$Q$1:$Q$400,"yearly")+SUMIFS(SF_Output!$S$1:$S$400,SF_Output!$AC$1:$AC$400,_xlfn.TEXTJOIN(",",TRUE,B31:E31),SF_Output!$Q$1:$Q$400,"quarterly")*4) -> 327 | S31: =IF(OR(B31=0,B31="",G31="hardware",R31=0),"",IF(AF31<>"exclusion",MAX(S$9,-(SUMIFS(SF_Output!$T$1:$T$400,SF_Output!$AC$1:$AC$400,_xlfn.TEXTJOIN(",",TRUE,$B31:$E31),SF_Output!$Q$1:$Q$400,"yearly"))/R31),-((SUMIFS(SF_Output!$T$1:$T$400,SF_Output!$AC$1:$AC$400,_xlfn.TEXTJOIN(",",TRUE,$B31:$E31),SF_Output!$Q$1:$Q$400,"yearly")/R31)))) -> 0 | T31: =IF(S31="",R31,R31*(1-S31)) -> 327 | V31: {=_xlfn.IFS(B31="","",AND(B31<>"",H31=SF_Output!$Y$2,SUMIFS(SF_Output!$T$1:$T$400,SF_Output!$AC$1:$AC$400,_xlfn.TEXTJOIN(",",TRUE,B31:E31),SF_Output!$Q$1:$Q$400,"monthly")=0),(SUMIFS(SF_Output!$F$1:$F$400,SF_Output!$AC$1:$AC$400,_xlfn.TEXTJOIN(",",TRUE,B31:E31),SF_Output!$Q$1:$Q$400,"monthly")+SUMIFS(SF_Output!$G$1:$G$400,SF_Output!$AC$1:$AC$400,_xlfn.TEXTJOIN(",",TRUE,B31:E31),SF_Output!$Q$1:$Q$400,"monthly"))*H31,AND(B31<>"",H31=SF_Output!$Y$2,SUMIFS(SF_Output!$T$1:$T$400,SF_Output!$AC$1:$AC$400,_xlfn.TEXTJOIN(",",TRUE,B31:E31),SF_Output!$Q$1:$Q$400,"monthly")<>0),SUMIFS(SF_Output!$S$1:$S$400,SF_Output!$AC$1:$AC$400,_xlfn.TEXTJOIN(",",TRUE,B31:E31),SF_Output!$Q$1:$Q$400,"monthly"),AND(B31<>"",H31<>SF_Output!$Y$2),SUMIFS(SF_Output!$S$1:$S$400,SF_Output!$AC$1:$AC$400,_xlfn.TEXTJOIN(",",TRUE,B31:E31),SF_Output!$Q$1:$Q$400,"monthly"))} -> 0 | W31: {=_xlfn.IFS(OR(B31=0,B31="",V31=0),"",AF31<>"exclusion",MAX($W$9,$W$7,(-(SUMIFS(SF_Output!$T$1:$T$400,SF_Output!$AC$1:$AC$400,_xlfn.TEXTJOIN(",",TRUE,$B31:$E31),SF_Output!$Q$1:$Q$400,"monthly"))/V31)),AF31="exclusion",-(SUMIFS(SF_Output!$T$1:$T$400,SF_Output!$AC$1:$AC$400,_xlfn.TEXTJOIN(",",TRUE,$B31:$E31),SF_Output!$Q$1:$Q$400,"monthly"))/V31)} | X31: {=IFERROR(_xlfn.IFS(V31=0,0,V31="","",W31=0,V31,OR(V31<>0,V31<>""),H31*I31),V31*(1-W31))} -> 0 | Z31: =IFERROR(IF(B31="","",SUMIFS(Billing_Fallout!H:H,Billing_Fallout!N:N,B31)),0) -> 0 | AA31: =IF(Z31="","",AB31-Z31) -> 0 | AB31: =IFERROR(IF(B31="","",SUMIFS(Billing_Fallout!J:J,Billing_Fallout!N:N,B31)),0) -> 0 | AD31: =IFERROR(X31-AB31,"") -> 0 | AF31: =IFERROR(INDEX(H_Tables!$B$1:$B$1500,MATCH(INDEX(SF_Output!$J$1:$J$400,MATCH(B31,SF_Output!$M$1:$M$400,0)),H_Tables!$A$1:$A$1500,0)),"") -> Exclusion | AI31: =IF(B31="","",IF(F31="remove","Remove Product",IF(F31="add","Add Product",_xlfn.TEXTJOIN(", ",TRUE,AQ31,AR31,AS31,AT31,AU31,AV31,AW31,AX31,AY31,AZ31,BA31,BB31,BC31)))) | AJ31: =IFERROR(INDEX(SF_Output!AD:AD,MATCH(_xlfn.TEXTJOIN(",",TRUE,B31:E31),SF_Output!AC1:AC400,0)),0.05) -> 53 | AK31: =IF(SUMIFS(SF_Output!$F$1:$F$400,SF_Output!$AC$1:$AC$400,_xlfn.TEXTJOIN(",",TRUE,B31:E31))+SUMIFS(SF_Output!$G$1:$G$400,SF_Output!$AC$1:$AC$400,_xlfn.TEXTJOIN(",",TRUE,B31:E31))=0,"","PAP") | AL31: =LEFT(_xlfn.TEXTJOIN(",",TRUE,B31:E31),80) -> Teller OrboAnywhere AI Validate,New,On Premise License,0 | AR31: {=IFERROR(_xlfn.IFS(AND(E31*1=1,F31="Included"),"Change to Included",AND(E31*1=0,F31="Optional"),"Change to Optional",OR(B31="",F31="replaced"),""),"")} | AS31: =IF((OR(NOT(_xlfn.ISFORMULA(J31)),NOT(_xlfn.ISFORMULA(L31)))),"Check License Price Override","") | AT31: =IF(OR(AND(K31=$K$9,K31<>0),NOT(_xlfn.ISFORMULA(K31))),"License Discount "&K31*100&"%","") | AU31: =IF((OR(NOT(_xlfn.ISFORMULA(N31)),NOT(_xlfn.ISFORMULA(P31)))),"Check Install Price Override","") | AV31: =IF(OR(AND(O31=$O$9,O31<>0),NOT(_xlfn.ISFORMULA(O31))),"Install Discount "&O31*100&"%","") | AW31: =IF((OR(NOT(_xlfn.ISFORMULA(R31)),NOT(_xlfn.ISFORMULA(T31)))),"Check Maintenance Price Override","") | AX31: =IF(OR(AND(S31=$S$9,S31<>0),NOT(_xlfn.ISFORMULA(S31))),"Maintenance Discount "&S31*100&"%","") | AY31: =IF((OR(NOT(_xlfn.ISFORMULA(V31)),NOT(_xlfn.ISFORMULA(X31)))),"Check Monthly Price Override","") | AZ31: =IF(OR((AND(W31=$W$9,W31<>0)),(AND(W31=$W$7,W31<>0)),(NOT(_xlfn.ISFORMULA(W31))),AND($W$7+0.2=W31,$W$7<>0)),"Monthly Discount "&W31*100&"%","") | BA31: =IF(NOT(_xlfn.ISFORMULA(H31)),"Check Quantity","") | BB31: =IF(NOT(_xlfn.ISFORMULA(I31)),"Check Unit Price Override","") | BE31: =INDEX(SF_Output!$AA$2:$AA$400,MATCH($B31,SF_Output!$M$2:$M$400,0)) -> 2 | BF31: =INDEX(SF_Output!$AB$2:$AB$400,MATCH($B31,SF_Output!$M$2:$M$400,0)) -> 2
B32: Teller Integration to AlertCenter | C32: New | D32: Hosted by JHA | E32: 1 | F32: =IF(B32="","",IF(E32*1=0,"Included","Optional")) -> Optional | G32: =IF(B32="","",INDEX(SF_Output!$K$1:$K$400,MATCH(B32,SF_Output!$M$1:$M$400,0))) -> AlertCenter | H32: {=_xlfn.IFS(B32="","",(SUMIFS(SF_Output!$F$1:$F$400,SF_Output!$AC$1:$AC$400,_xlfn.TEXTJOIN(",",TRUE,B32:E32))+SUMIFS(SF_Output!$G$1:$G$400,SF_Output!$AC$1:$AC$400,_xlfn.TEXTJOIN(",",TRUE,B32:E32)))<>0,SF_Output!$Y$2,INDEX(SF_Output!$F$1:$F$400,MATCH(_xlfn.TEXTJOIN(",",TRUE,B32:E32),SF_Output!$AC$1:$AC$400,0))=0,INDEX(SF_Output!$R$1:$R$400,MATCH(_xlfn.TEXTJOIN(",",TRUE,B32:E32),SF_Output!$AC$1:$AC$400,0)))} -> 1 | I32: =IFERROR(IF(AND(H32>1,H32<>""),ROUND(SUMIFS(SF_Output!$S$1:$S$400,SF_Output!$AC$1:$AC$400,_xlfn.TEXTJOIN(",",TRUE,B32:E32),SF_Output!$Q$1:$Q$400,"monthly")*(1-W32)/H32,4),""),"") | J32: =IF(B32="","",SUMIFS(SF_Output!$S$1:$S$400,SF_Output!$AC$1:$AC$400,_xlfn.TEXTJOIN(",",TRUE,B32:E32),SF_Output!$Q$1:$Q$400,"One Time",SF_Output!$L$1:$L$400,"license fee")+SUMIFS(SF_Output!$S$1:$S$400,SF_Output!$AC$1:$AC$400,_xlfn.TEXTJOIN(",",TRUE,B32:E32),SF_Output!$Q$1:$Q$400,"One Time",SF_Output!$L$1:$L$400,"software license")+SUMIFS(SF_Output!$S$1:$S$400,SF_Output!$AC$1:$AC$400,_xlfn.TEXTJOIN(",",TRUE,B32:E32),SF_Output!$Q$1:$Q$400,"One Time",SF_Output!$L$1:$L$400,"hardware")) -> 0 | K32: =IF(OR(B32=0,B32="",G32="hardware",J32=0),"",IF(AF32<>"exclusion",MAX(K$9,-((SUMIFS(SF_Output!$T$1:$T$400,SF_Output!$AC$1:$AC$400,_xlfn.TEXTJOIN(",",TRUE,$B32:$E32),SF_Output!$Q$1:$Q$400,"One Time",SF_Output!$L$1:$L$400,"license fee")+SUMIFS(SF_Output!$T$1:$T$400,SF_Output!$AC$1:$AC$400,_xlfn.TEXTJOIN(",",TRUE,$B32:$E32),SF_Output!$Q$1:$Q$400,"One Time",SF_Output!$L$1:$L$400,"software license"))/J32)),-((SUMIFS(SF_Output!$T$1:$T$400,SF_Output!$AC$1:$AC$400,_xlfn.TEXTJOIN(",",TRUE,$B32:$E32),SF_Output!$Q$1:$Q$400,"One Time",SF_Output!$L$1:$L$400,"license fee")+SUMIFS(SF_Output!$T$1:$T$400,SF_Output!$AC$1:$AC$400,_xlfn.TEXTJOIN(",",TRUE,$B32:$E32),SF_Output!$Q$1:$Q$400,"One Time",SF_Output!$L$1:$L$400,"software license"))/J32))) | L32: =IF(K32="",J32,J32*(1-K32)) -> 0 | N32: =IF(B32="","",SUMIFS(SF_Output!$S$1:$S$400,SF_Output!$AC$1:$AC$400,_xlfn.TEXTJOIN(",",TRUE,B32:E32),SF_Output!$Q$1:$Q$400,"One Time",SF_Output!$L$1:$L$400,"professional service")) -> 3750 | O32: =IF(OR(B32=0,B32="",N32=0),"",IF(AF32<>"exclusion",MAX(O$9,-(SUMIFS(SF_Output!$T$1:$T$400,SF_Output!$AC$1:$AC$400,_xlfn.TEXTJOIN(",",TRUE,$B32:$E32),SF_Output!$Q$1:$Q$400,"One Time",SF_Output!$L$1:$L$400,"professional service"))/N32),-((SUMIFS(SF_Output!$T$1:$T$400,SF_Output!$AC$1:$AC$400,_xlfn.TEXTJOIN(",",TRUE,$B32:$E32),SF_Output!$Q$1:$Q$400,"One Time",SF_Output!$L$1:$L$400,"professional service")/N32)))) -> 1 | P32: =IF(O32="",N32,N32*(1-O32)) -> 0 | R32: =IF(B32="","",SUMIFS(SF_Output!$S$1:$S$400,SF_Output!$AC$1:$AC$400,_xlfn.TEXTJOIN(",",TRUE,B32:E32),SF_Output!$Q$1:$Q$400,"yearly")+SUMIFS(SF_Output!$S$1:$S$400,SF_Output!$AC$1:$AC$400,_xlfn.TEXTJOIN(",",TRUE,B32:E32),SF_Output!$Q$1:$Q$400,"quarterly")*4) -> 0 | S32: =IF(OR(B32=0,B32="",G32="hardware",R32=0),"",IF(AF32<>"exclusion",MAX(S$9,-(SUMIFS(SF_Output!$T$1:$T$400,SF_Output!$AC$1:$AC$400,_xlfn.TEXTJOIN(",",TRUE,$B32:$E32),SF_Output!$Q$1:$Q$400,"yearly"))/R32),-((SUMIFS(SF_Output!$T$1:$T$400,SF_Output!$AC$1:$AC$400,_xlfn.TEXTJOIN(",",TRUE,$B32:$E32),SF_Output!$Q$1:$Q$400,"yearly")/R32)))) | T32: =IF(S32="",R32,R32*(1-S32)) -> 0 | V32: {=_xlfn.IFS(B32="","",AND(B32<>"",H32=SF_Output!$Y$2,SUMIFS(SF_Output!$T$1:$T$400,SF_Output!$AC$1:$AC$400,_xlfn.TEXTJOIN(",",TRUE,B32:E32),SF_Output!$Q$1:$Q$400,"monthly")=0),(SUMIFS(SF_Output!$F$1:$F$400,SF_Output!$AC$1:$AC$400,_xlfn.TEXTJOIN(",",TRUE,B32:E32),SF_Output!$Q$1:$Q$400,"monthly")+SUMIFS(SF_Output!$G$1:$G$400,SF_Output!$AC$1:$AC$400,_xlfn.TEXTJOIN(",",TRUE,B32:E32),SF_Output!$Q$1:$Q$400,"monthly"))*H32,AND(B32<>"",H32=SF_Output!$Y$2,SUMIFS(SF_Output!$T$1:$T$400,SF_Output!$AC$1:$AC$400,_xlfn.TEXTJOIN(",",TRUE,B32:E32),SF_Output!$Q$1:$Q$400,"monthly")<>0),SUMIFS(SF_Output!$S$1:$S$400,SF_Output!$AC$1:$AC$400,_xlfn.TEXTJOIN(",",TRUE,B32:E32),SF_Output!$Q$1:$Q$400,"monthly"),AND(B32<>"",H32<>SF_Output!$Y$2),SUMIFS(SF_Output!$S$1:$S$400,SF_Output!$AC$1:$AC$400,_xlfn.TEXTJOIN(",",TRUE,B32:E32),SF_Output!$Q$1:$Q$400,"monthly"))} -> 0 | W32: {=_xlfn.IFS(OR(B32=0,B32="",V32=0),"",AF32<>"exclusion",MAX($W$9,$W$7,(-(SUMIFS(SF_Output!$T$1:$T$400,SF_Output!$AC$1:$AC$400,_xlfn.TEXTJOIN(",",TRUE,$B32:$E32),SF_Output!$Q$1:$Q$400,"monthly"))/V32)),AF32="exclusion",-(SUMIFS(SF_Output!$T$1:$T$400,SF_Output!$AC$1:$AC$400,_xlfn.TEXTJOIN(",",TRUE,$B32:$E32),SF_Output!$Q$1:$Q$400,"monthly"))/V32)} | X32: {=IFERROR(_xlfn.IFS(V32=0,0,V32="","",W32=0,V32,OR(V32<>0,V32<>""),H32*I32),V32*(1-W32))} -> 0 | Z32: =IFERROR(IF(B32="","",SUMIFS(Billing_Fallout!H:H,Billing_Fallout!N:N,B32)),0) -> 0 | AA32: =IF(Z32="","",AB32-Z32) -> 0 | AB32: =IFERROR(IF(B32="","",SUMIFS(Billing_Fallout!J:J,Billing_Fallout!N:N,B32)),0) -> 0 | AD32: =IFERROR(X32-AB32,"") -> 0 | AF32: =IFERROR(INDEX(H_Tables!$B$1:$B$1500,MATCH(INDEX(SF_Output!$J$1:$J$400,MATCH(B32,SF_Output!$M$1:$M$400,0)),H_Tables!$A$1:$A$1500,0)),"") -> Exclusion | AI32: =IF(B32="","",IF(F32="remove","Remove Product",IF(F32="add","Add Product",_xlfn.TEXTJOIN(", ",TRUE,AQ32,AR32,AS32,AT32,AU32,AV32,AW32,AX32,AY32,AZ32,BA32,BB32,BC32)))) | AJ32: =IFERROR(INDEX(SF_Output!AD:AD,MATCH(_xlfn.TEXTJOIN(",",TRUE,B32:E32),SF_Output!AC1:AC400,0)),0.05) -> 97 | AK32: =IF(SUMIFS(SF_Output!$F$1:$F$400,SF_Output!$AC$1:$AC$400,_xlfn.TEXTJOIN(",",TRUE,B32:E32))+SUMIFS(SF_Output!$G$1:$G$400,SF_Output!$AC$1:$AC$400,_xlfn.TEXTJOIN(",",TRUE,B32:E32))=0,"","PAP") | AL32: =LEFT(_xlfn.TEXTJOIN(",",TRUE,B32:E32),80) -> Teller Integration to AlertCenter,New,Hosted by JHA,1 | AR32: {=IFERROR(_xlfn.IFS(AND(E32*1=1,F32="Included"),"Change to Included",AND(E32*1=0,F32="Optional"),"Change to Optional",OR(B32="",F32="replaced"),""),"")} | AS32: =IF((OR(NOT(_xlfn.ISFORMULA(J32)),NOT(_xlfn.ISFORMULA(L32)))),"Check License Price Override","") | AT32: =IF(OR(AND(K32=$K$9,K32<>0),NOT(_xlfn.ISFORMULA(K32))),"License Discount "&K32*100&"%","") | AU32: =IF((OR(NOT(_xlfn.ISFORMULA(N32)),NOT(_xlfn.ISFORMULA(P32)))),"Check Install Price Override","") | AV32: =IF(OR(AND(O32=$O$9,O32<>0),NOT(_xlfn.ISFORMULA(O32))),"Install Discount "&O32*100&"%","") | AW32: =IF((OR(NOT(_xlfn.ISFORMULA(R32)),NOT(_xlfn.ISFORMULA(T32)))),"Check Maintenance Price Override","") | AX32: =IF(OR(AND(S32=$S$9,S32<>0),NOT(_xlfn.ISFORMULA(S32))),"Maintenance Discount "&S32*100&"%","") | AY32: =IF((OR(NOT(_xlfn.ISFORMULA(V32)),NOT(_xlfn.ISFORMULA(X32)))),"Check Monthly Price Override","") | AZ32: =IF(OR((AND(W32=$W$9,W32<>0)),(AND(W32=$W$7,W32<>0)),(NOT(_xlfn.ISFORMULA(W32))),AND($W$7+0.2=W32,$W$7<>0)),"Monthly Discount "&W32*100&"%","") | BA32: =IF(NOT(_xlfn.ISFORMULA(H32)),"Check Quantity","") | BB32: =IF(NOT(_xlfn.ISFORMULA(I32)),"Check Unit Price Override","") | BE32: =INDEX(SF_Output!$AA$2:$AA$400,MATCH($B32,SF_Output!$M$2:$M$400,0)) -> 2 | BF32: =INDEX(SF_Output!$AB$2:$AB$400,MATCH($B32,SF_Output!$M$2:$M$400,0)) -> 4
B33: Synapsys CRM | C33: New | D33: Hosted by JHA | E33: 0 | F33: =IF(B33="","",IF(E33*1=0,"Included","Optional")) -> Included | G33: =IF(B33="","",INDEX(SF_Output!$K$1:$K$400,MATCH(B33,SF_Output!$M$1:$M$400,0))) -> Synapsys | H33: {=_xlfn.IFS(B33="","",(SUMIFS(SF_Output!$F$1:$F$400,SF_Output!$AC$1:$AC$400,_xlfn.TEXTJOIN(",",TRUE,B33:E33))+SUMIFS(SF_Output!$G$1:$G$400,SF_Output!$AC$1:$AC$400,_xlfn.TEXTJOIN(",",TRUE,B33:E33)))<>0,SF_Output!$Y$2,INDEX(SF_Output!$F$1:$F$400,MATCH(_xlfn.TEXTJOIN(",",TRUE,B33:E33),SF_Output!$AC$1:$AC$400,0))=0,INDEX(SF_Output!$R$1:$R$400,MATCH(_xlfn.TEXTJOIN(",",TRUE,B33:E33),SF_Output!$AC$1:$AC$400,0)))} -> 5000 | I33: =IFERROR(IF(AND(H33>1,H33<>""),ROUND(SUMIFS(SF_Output!$S$1:$S$400,SF_Output!$AC$1:$AC$400,_xlfn.TEXTJOIN(",",TRUE,B33:E33),SF_Output!$Q$1:$Q$400,"monthly")*(1-W33)/H33,4),""),"") -> 0.1643 | J33: =IF(B33="","",SUMIFS(SF_Output!$S$1:$S$400,SF_Output!$AC$1:$AC$400,_xlfn.TEXTJOIN(",",TRUE,B33:E33),SF_Output!$Q$1:$Q$400,"One Time",SF_Output!$L$1:$L$400,"license fee")+SUMIFS(SF_Output!$S$1:$S$400,SF_Output!$AC$1:$AC$400,_xlfn.TEXTJOIN(",",TRUE,B33:E33),SF_Output!$Q$1:$Q$400,"One Time",SF_Output!$L$1:$L$400,"software license")+SUMIFS(SF_Output!$S$1:$S$400,SF_Output!$AC$1:$AC$400,_xlfn.TEXTJOIN(",",TRUE,B33:E33),SF_Output!$Q$1:$Q$400,"One Time",SF_Output!$L$1:$L$400,"hardware")) -> 0 | K33: =IF(OR(B33=0,B33="",G33="hardware",J33=0),"",IF(AF33<>"exclusion",MAX(K$9,-((SUMIFS(SF_Output!$T$1:$T$400,SF_Output!$AC$1:$AC$400,_xlfn.TEXTJOIN(",",TRUE,$B33:$E33),SF_Output!$Q$1:$Q$400,"One Time",SF_Output!$L$1:$L$400,"license fee")+SUMIFS(SF_Output!$T$1:$T$400,SF_Output!$AC$1:$AC$400,_xlfn.TEXTJOIN(",",TRUE,$B33:$E33),SF_Output!$Q$1:$Q$400,"One Time",SF_Output!$L$1:$L$400,"software license"))/J33)),-((SUMIFS(SF_Output!$T$1:$T$400,SF_Output!$AC$1:$AC$400,_xlfn.TEXTJOIN(",",TRUE,$B33:$E33),SF_Output!$Q$1:$Q$400,"One Time",SF_Output!$L$1:$L$400,"license fee")+SUMIFS(SF_Output!$T$1:$T$400,SF_Output!$AC$1:$AC$400,_xlfn.TEXTJOIN(",",TRUE,$B33:$E33),SF_Output!$Q$1:$Q$400,"One Time",SF_Output!$L$1:$L$400,"software license"))/J33))) | L33: =IF(K33="",J33,J33*(1-K33)) -> 0 | N33: =IF(B33="","",SUMIFS(SF_Output!$S$1:$S$400,SF_Output!$AC$1:$AC$400,_xlfn.TEXTJOIN(",",TRUE,B33:E33),SF_Output!$Q$1:$Q$400,"One Time",SF_Output!$L$1:$L$400,"professional service")) -> 8500 | O33: =IF(OR(B33=0,B33="",N33=0),"",IF(AF33<>"exclusion",MAX(O$9,-(SUMIFS(SF_Output!$T$1:$T$400,SF_Output!$AC$1:$AC$400,_xlfn.TEXTJOIN(",",TRUE,$B33:$E33),SF_Output!$Q$1:$Q$400,"One Time",SF_Output!$L$1:$L$400,"professional service"))/N33),-((SUMIFS(SF_Output!$T$1:$T$400,SF_Output!$AC$1:$AC$400,_xlfn.TEXTJOIN(",",TRUE,$B33:$E33),SF_Output!$Q$1:$Q$400,"One Time",SF_Output!$L$1:$L$400,"professional service")/N33)))) -> 1 | P33: =IF(O33="",N33,N33*(1-O33)) -> 0 | R33: =IF(B33="","",SUMIFS(SF_Output!$S$1:$S$400,SF_Output!$AC$1:$AC$400,_xlfn.TEXTJOIN(",",TRUE,B33:E33),SF_Output!$Q$1:$Q$400,"yearly")+SUMIFS(SF_Output!$S$1:$S$400,SF_Output!$AC$1:$AC$400,_xlfn.TEXTJOIN(",",TRUE,B33:E33),SF_Output!$Q$1:$Q$400,"quarterly")*4) -> 0 | S33: =IF(OR(B33=0,B33="",G33="hardware",R33=0),"",IF(AF33<>"exclusion",MAX(S$9,-(SUMIFS(SF_Output!$T$1:$T$400,SF_Output!$AC$1:$AC$400,_xlfn.TEXTJOIN(",",TRUE,$B33:$E33),SF_Output!$Q$1:$Q$400,"yearly"))/R33),-((SUMIFS(SF_Output!$T$1:$T$400,SF_Output!$AC$1:$AC$400,_xlfn.TEXTJOIN(",",TRUE,$B33:$E33),SF_Output!$Q$1:$Q$400,"yearly")/R33)))) | T33: =IF(S33="",R33,R33*(1-S33)) -> 0 | V33: {=_xlfn.IFS(B33="","",AND(B33<>"",H33=SF_Output!$Y$2,SUMIFS(SF_Output!$T$1:$T$400,SF_Output!$AC$1:$AC$400,_xlfn.TEXTJOIN(",",TRUE,B33:E33),SF_Output!$Q$1:$Q$400,"monthly")=0),(SUMIFS(SF_Output!$F$1:$F$400,SF_Output!$AC$1:$AC$400,_xlfn.TEXTJOIN(",",TRUE,B33:E33),SF_Output!$Q$1:$Q$400,"monthly")+SUMIFS(SF_Output!$G$1:$G$400,SF_Output!$AC$1:$AC$400,_xlfn.TEXTJOIN(",",TRUE,B33:E33),SF_Output!$Q$1:$Q$400,"monthly"))*H33,AND(B33<>"",H33=SF_Output!$Y$2,SUMIFS(SF_Output!$T$1:$T$400,SF_Output!$AC$1:$AC$400,_xlfn.TEXTJOIN(",",TRUE,B33:E33),SF_Output!$Q$1:$Q$400,"monthly")<>0),SUMIFS(SF_Output!$S$1:$S$400,SF_Output!$AC$1:$AC$400,_xlfn.TEXTJOIN(",",TRUE,B33:E33),SF_Output!$Q$1:$Q$400,"monthly"),AND(B33<>"",H33<>SF_Output!$Y$2),SUMIFS(SF_Output!$S$1:$S$400,SF_Output!$AC$1:$AC$400,_xlfn.TEXTJOIN(",",TRUE,B33:E33),SF_Output!$Q$1:$Q$400,"monthly"))} -> 1095 | W33: {=_xlfn.IFS(OR(B33=0,B33="",V33=0),"",AF33<>"exclusion",MAX($W$9,$W$7,(-(SUMIFS(SF_Output!$T$1:$T$400,SF_Output!$AC$1:$AC$400,_xlfn.TEXTJOIN(",",TRUE,$B33:$E33),SF_Output!$Q$1:$Q$400,"monthly"))/V33)),AF33="exclusion",-(SUMIFS(SF_Output!$T$1:$T$400,SF_Output!$AC$1:$AC$400,_xlfn.TEXTJOIN(",",TRUE,$B33:$E33),SF_Output!$Q$1:$Q$400,"monthly"))/V33)} -> 0.25 | X33: {=IFERROR(_xlfn.IFS(V33=0,0,V33="","",W33=0,V33,OR(V33<>0,V33<>""),H33*I33),V33*(1-W33))} -> 821.5 | Z33: =IFERROR(IF(B33="","",SUMIFS(Billing_Fallout!H:H,Billing_Fallout!N:N,B33)),0) -> 0 | AA33: =IF(Z33="","",AB33-Z33) -> 0 | AB33: =IFERROR(IF(B33="","",SUMIFS(Billing_Fallout!J:J,Billing_Fallout!N:N,B33)),0) -> 0 | AD33: =IFERROR(X33-AB33,"") -> 821.5 | AF33: =IFERROR(INDEX(H_Tables!$B$1:$B$1500,MATCH(INDEX(SF_Output!$J$1:$J$400,MATCH(B33,SF_Output!$M$1:$M$400,0)),H_Tables!$A$1:$A$1500,0)),"") | AI33: =IF(B33="","",IF(F33="remove","Remove Product",IF(F33="add","Add Product",_xlfn.TEXTJOIN(", ",TRUE,AQ33,AR33,AS33,AT33,AU33,AV33,AW33,AX33,AY33,AZ33,BA33,BB33,BC33)))) | AJ33: =IFERROR(INDEX(SF_Output!AD:AD,MATCH(_xlfn.TEXTJOIN(",",TRUE,B33:E33),SF_Output!AC1:AC400,0)),0.05) -> 113 | AK33: =IF(SUMIFS(SF_Output!$F$1:$F$400,SF_Output!$AC$1:$AC$400,_xlfn.TEXTJOIN(",",TRUE,B33:E33))+SUMIFS(SF_Output!$G$1:$G$400,SF_Output!$AC$1:$AC$400,_xlfn.TEXTJOIN(",",TRUE,B33:E33))=0,"","PAP") -> PAP | AL33: =LEFT(_xlfn.TEXTJOIN(",",TRUE,B33:E33),80) -> Synapsys CRM,New,Hosted by JHA,0 | AR33: {=IFERROR(_xlfn.IFS(AND(E33*1=1,F33="Included"),"Change to Included",AND(E33*1=0,F33="Optional"),"Change to Optional",OR(B33="",F33="replaced"),""),"")} | AS33: =IF((OR(NOT(_xlfn.ISFORMULA(J33)),NOT(_xlfn.ISFORMULA(L33)))),"Check License Price Override","") | AT33: =IF(OR(AND(K33=$K$9,K33<>0),NOT(_xlfn.ISFORMULA(K33))),"License Discount "&K33*100&"%","") | AU33: =IF((OR(NOT(_xlfn.ISFORMULA(N33)),NOT(_xlfn.ISFORMULA(P33)))),"Check Install Price Override","") | AV33: =IF(OR(AND(O33=$O$9,O33<>0),NOT(_xlfn.ISFORMULA(O33))),"Install Discount "&O33*100&"%","") | AW33: =IF((OR(NOT(_xlfn.ISFORMULA(R33)),NOT(_xlfn.ISFORMULA(T33)))),"Check Maintenance Price Override","") | AX33: =IF(OR(AND(S33=$S$9,S33<>0),NOT(_xlfn.ISFORMULA(S33))),"Maintenance Discount "&S33*100&"%","") | AY33: =IF((OR(NOT(_xlfn.ISFORMULA(V33)),NOT(_xlfn.ISFORMULA(X33)))),"Check Monthly Price Override","") | AZ33: =IF(OR((AND(W33=$W$9,W33<>0)),(AND(W33=$W$7,W33<>0)),(NOT(_xlfn.ISFORMULA(W33))),AND($W$7+0.2=W33,$W$7<>0)),"Monthly Discount "&W33*100&"%","") | BA33: =IF(NOT(_xlfn.ISFORMULA(H33)),"Check Quantity","") | BB33: =IF(NOT(_xlfn.ISFORMULA(I33)),"Check Unit Price Override","") | BE33: =INDEX(SF_Output!$AA$2:$AA$400,MATCH($B33,SF_Output!$M$2:$M$400,0)) -> 2 | BF33: =INDEX(SF_Output!$AB$2:$AB$400,MATCH($B33,SF_Output!$M$2:$M$400,0)) -> 3
