Workbook

Sheet Metadata
A1: TCO Analysis - Proposal Metadata
A2: Primary Vendor: | B2: FIS
A3: Client Name: | B3: Liberty Capital Bank
A4: Proposal Type: | B4: Renewal with Acquisition
A5: Proposal Date: | B5: December 2024
A6: Contract Term (Years): | B6: 7
A7: Annual Growth Rate: | B7: 0.02
A8: Annual CPI Rate: | B8: 0.02
A10: Data Extraction Date: | B10: 2025-12-08 17:04:41
A11: AI Model Used: | B11: claude-sonnet-4-20250514
A12: Source Proposal File: | B12: N/A

Sheet Enums
A1: Fee Types | B1: Categories | C1: Boolean
A2: Monthly F | B2: Core | C2: TRUE
A3: Monthly V | B3: Digital | C3: FALSE
A4: Annual | B4: EFT
A5: One-Time | B5: Risk, Fraud & Compliance
B6: Treasury
B7: Image Solutions
B8: Item Processing
B9: FOS
B10: Lending
B11: ACH
B12: Accounts Payable
B13: Security Plus
B14: Network
B15: Other

Sheet Line_Items
A1: Row ID | B1: Fee Type | C1: Solution Name | D1: Category | E1: Third Party | F1: Optional | G1: Per Unit Rate | H1: Unit Description | I1: Avg Monthly Qty | J1: Year 1 Monthly | K1: Year 1 Annual | L1: Year 2 | M1: Year 3 | N1: Year 4 | O1: Year 5 | P1: Year 6 | Q1: Year 7 | R1: Total 7-Year Cost | S1: Confidence | T1: Notes
A2: 1 | B2: Monthly F | C2: Core: HORIZON | D2: Core | E2: FALSE | F2: FALSE | G2: 16792 | H2: per month | J2: =IF(B2="Monthly F",G2,IF(B2="Monthly V",G2*I2,IF(B2="Annual",G2/12,0))) -> 16792 | K2: =IF(B2="One-Time",G2,J2*12) -> 201504 | L2: =IF(B2="One-Time",0,K2*(1+Metadata!$B$8)) -> 205534.08 | M2: =IF(B2="One-Time",0,L2*(1+Metadata!$B$8)) -> 209644.76 | N2: =IF(B2="One-Time",0,M2*(1+Metadata!$B$8)) -> 213837.66 | O2: =IF(B2="One-Time",0,N2*(1+Metadata!$B$8)) -> 218114.41 | P2: =IF(B2="One-Time",0,O2*(1+Metadata!$B$8)) -> 222476.7 | Q2: =IF(B2="One-Time",0,P2*(1+Metadata!$B$8)) -> 226926.23 | R2: =SUM(K2:Q2) -> 1498037.8 | S2: 0.98 | T2: Core banking system pricing clearly defined
A3: 2 | B3: Monthly F | C3: Digital: D1 Flex, D1 Business, Mobile, Bill Pay | D3: Digital | E3: FALSE | F3: FALSE | G3: 35253 | H3: per month | J3: =IF(B3="Monthly F",G3,IF(B3="Monthly V",G3*I3,IF(B3="Annual",G3/12,0))) -> 35253 | K3: =IF(B3="One-Time",G3,J3*12) -> 423036 | L3: =IF(B3="One-Time",0,K3*(1+Metadata!$B$8)) -> 431496.72 | M3: =IF(B3="One-Time",0,L3*(1+Metadata!$B$8)) -> 440126.65 | N3: =IF(B3="One-Time",0,M3*(1+Metadata!$B$8)) -> 448929.19 | O3: =IF(B3="One-Time",0,N3*(1+Metadata!$B$8)) -> 457907.77 | P3: =IF(B3="One-Time",0,O3*(1+Metadata!$B$8)) -> 467065.93 | Q3: =IF(B3="One-Time",0,P3*(1+Metadata!$B$8)) -> 476407.25 | R3: =SUM(K3:Q3) -> 3144969.5 | S3: 0.98 | T3: Digital banking suite pricing clearly defined
A4: 3 | B4: Monthly F | C4: Digital: Website Services | D4: Digital | E4: FALSE | F4: FALSE | G4: 568 | H4: per month | J4: =IF(B4="Monthly F",G4,IF(B4="Monthly V",G4*I4,IF(B4="Annual",G4/12,0))) -> 568 | K4: =IF(B4="One-Time",G4,J4*12) -> 6816 | L4: =IF(B4="One-Time",0,K4*(1+Metadata!$B$8)) -> 6952.32 | M4: =IF(B4="One-Time",0,L4*(1+Metadata!$B$8)) -> 7091.3664 | N4: =IF(B4="One-Time",0,M4*(1+Metadata!$B$8)) -> 7233.1937 | O4: =IF(B4="One-Time",0,N4*(1+Metadata!$B$8)) -> 7377.8576 | P4: =IF(B4="One-Time",0,O4*(1+Metadata!$B$8)) -> 7525.4148 | Q4: =IF(B4="One-Time",0,P4*(1+Metadata!$B$8)) -> 7675.923 | R4: =SUM(K4:Q4) -> 50672.076 | S4: 0.98 | T4: Website services pricing unchanged
A5: 4 | B5: Monthly F | C5: Digital: Zelle | D5: Digital | E5: FALSE | F5: FALSE | G5: 641 | H5: per month | J5: =IF(B5="Monthly F",G5,IF(B5="Monthly V",G5*I5,IF(B5="Annual",G5/12,0))) -> 641 | K5: =IF(B5="One-Time",G5,J5*12) -> 7692 | L5: =IF(B5="One-Time",0,K5*(1+Metadata!$B$8)) -> 7845.84 | M5: =IF(B5="One-Time",0,L5*(1+Metadata!$B$8)) -> 8002.7568 | N5: =IF(B5="One-Time",0,M5*(1+Metadata!$B$8)) -> 8162.8119 | O5: =IF(B5="One-Time",0,N5*(1+Metadata!$B$8)) -> 8326.0682 | P5: =IF(B5="One-Time",0,O5*(1+Metadata!$B$8)) -> 8492.5895 | Q5: =IF(B5="One-Time",0,P5*(1+Metadata!$B$8)) -> 8662.4413 | R5: =SUM(K5:Q5) -> 57184.508 | S5: 0.98 | T5: Zelle pricing unchanged
A6: 18 | B6: Monthly F | C6: EFT: Debit Card Production | D6: EFT | E6: FALSE | F6: FALSE | G6: 512 | H6: per month | J6: =IF(B6="Monthly F",G6,IF(B6="Monthly V",G6*I6,IF(B6="Annual",G6/12,0))) -> 512 | K6: =IF(B6="One-Time",G6,J6*12) -> 6144 | L6: =IF(B6="One-Time",0,K6*(1+Metadata!$B$8)) -> 6266.88 | M6: =IF(B6="One-Time",0,L6*(1+Metadata!$B$8)) -> 6392.2176 | N6: =IF(B6="One-Time",0,M6*(1+Metadata!$B$8)) -> 6520.062 | O6: =IF(B6="One-Time",0,N6*(1+Metadata!$B$8)) -> 6650.4632 | P6: =IF(B6="One-Time",0,O6*(1+Metadata!$B$8)) -> 6783.4725 | Q6: =IF(B6="One-Time",0,P6*(1+Metadata!$B$8)) -> 6919.1419 | R6: =SUM(K6:Q6) -> 45676.237 | S6: 0.98 | T6: Debit card production pricing unchanged
A7: 5 | B7: Monthly F | C7: EFT: EFT Norcross, 3D Secure, Tokenization, SecurLOCK | D7: EFT | E7: FALSE | F7: FALSE | G7: 6675 | H7: per month | J7: =IF(B7="Monthly F",G7,IF(B7="Monthly V",G7*I7,IF(B7="Annual",G7/12,0))) -> 6675 | K7: =IF(B7="One-Time",G7,J7*12) -> 80100 | L7: =IF(B7="One-Time",0,K7*(1+Metadata!$B$8)) -> 81702 | M7: =IF(B7="One-Time",0,L7*(1+Metadata!$B$8)) -> 83336.04 | N7: =IF(B7="One-Time",0,M7*(1+Metadata!$B$8)) -> 85002.761 | O7: =IF(B7="One-Time",0,N7*(1+Metadata!$B$8)) -> 86702.816 | P7: =IF(B7="One-Time",0,O7*(1+Metadata!$B$8)) -> 88436.872 | Q7: =IF(B7="One-Time",0,P7*(1+Metadata!$B$8)) -> 90205.61 | R7: =SUM(K7:Q7) -> 595486.1 | S7: 0.98 | T7: EFT services bundle pricing clearly defined
A8: 19 | B8: Monthly F | C8: EFT: NYCE Debit Card Network | D8: EFT | E8: FALSE | F8: FALSE | G8: 171 | H8: per month | J8: =IF(B8="Monthly F",G8,IF(B8="Monthly V",G8*I8,IF(B8="Annual",G8/12,0))) -> 171 | K8: =IF(B8="One-Time",G8,J8*12) -> 2052 | L8: =IF(B8="One-Time",0,K8*(1+Metadata!$B$8)) -> 2093.04 | M8: =IF(B8="One-Time",0,L8*(1+Metadata!$B$8)) -> 2134.9008 | N8: =IF(B8="One-Time",0,M8*(1+Metadata!$B$8)) -> 2177.5988 | O8: =IF(B8="One-Time",0,N8*(1+Metadata!$B$8)) -> 2221.1508 | P8: =IF(B8="One-Time",0,O8*(1+Metadata!$B$8)) -> 2265.5738 | Q8: =IF(B8="One-Time",0,P8*(1+Metadata!$B$8)) -> 2310.8853 | R8: =SUM(K8:Q8) -> 15255.15 | S8: 0.98 | T8: NYCE network pricing unchanged
A9: 10 | B9: Monthly F | C9: FOS: eDelivery, Print/Render, Forms & Envelopes | D9: Other | E9: FALSE | F9: FALSE | G9: 2168 | H9: per month | J9: =IF(B9="Monthly F",G9,IF(B9="Monthly V",G9*I9,IF(B9="Annual",G9/12,0))) -> 2168 | K9: =IF(B9="One-Time",G9,J9*12) -> 26016 | L9: =IF(B9="One-Time",0,K9*(1+Metadata!$B$8)) -> 26536.32 | M9: =IF(B9="One-Time",0,L9*(1+Metadata!$B$8)) -> 27067.046 | N9: =IF(B9="One-Time",0,M9*(1+Metadata!$B$8)) -> 27608.387 | O9: =IF(B9="One-Time",0,N9*(1+Metadata!$B$8)) -> 28160.555 | P9: =IF(B9="One-Time",0,O9*(1+Metadata!$B$8)) -> 28723.766 | Q9: =IF(B9="One-Time",0,P9*(1+Metadata!$B$8)) -> 29298.241 | R9: =SUM(K9:Q9) -> 193410.32 | S9: 0.98 | T9: Forms and output services pricing clearly defined
A10: 25 | B10: Monthly F | C10: HORIZON: Conditional Processing | D10: Other | E10: FALSE | F10: FALSE | G10: 1076.8 | H10: per month | J10: =IF(B10="Monthly F",G10,IF(B10="Monthly V",G10*I10,IF(B10="Annual",G10/12,0))) -> 1076.8 | K10: =IF(B10="One-Time",G10,J10*12) -> 12921.6 | L10: =IF(B10="One-Time",0,K10*(1+Metadata!$B$8)) -> 13180.032 | M10: =IF(B10="One-Time",0,L10*(1+Metadata!$B$8)) -> 13443.633 | N10: =IF(B10="One-Time",0,M10*(1+Metadata!$B$8)) -> 13712.505 | O10: =IF(B10="One-Time",0,N10*(1+Metadata!$B$8)) -> 13986.755 | P10: =IF(B10="One-Time",0,O10*(1+Metadata!$B$8)) -> 14266.491 | Q10: =IF(B10="One-Time",0,P10*(1+Metadata!$B$8)) -> 14551.82 | R10: =SUM(K10:Q10) -> 96062.836 | S10: 0.98 | T10: New HORIZON conditional processing module
A11: 23 | B11: Monthly F | C11: IP: DirectLink Consumer (via FXD) | D11: Other | E11: FALSE | F11: FALSE | G11: 1170.19 | H11: per month | J11: =IF(B11="Monthly F",G11,IF(B11="Monthly V",G11*I11,IF(B11="Annual",G11/12,0))) -> 1170.19 | K11: =IF(B11="One-Time",G11,J11*12) -> 14042.28 | L11: =IF(B11="One-Time",0,K11*(1+Metadata!$B$8)) -> 14323.126 | M11: =IF(B11="One-Time",0,L11*(1+Metadata!$B$8)) -> 14609.588 | N11: =IF(B11="One-Time",0,M11*(1+Metadata!$B$8)) -> 14901.78 | O11: =IF(B11="One-Time",0,N11*(1+Metadata!$B$8)) -> 15199.815 | P11: =IF(B11="One-Time",0,O11*(1+Metadata!$B$8)) -> 15503.812 | Q11: =IF(B11="One-Time",0,P11*(1+Metadata!$B$8)) -> 15813.888 | R11: =SUM(K11:Q11) -> 104394.29 | S11: 0.98 | T11: New DirectLink Consumer solution
A12: 21 | B12: Monthly F | C12: IP: DirectLink Merchant (via RDC) | D12: Other | E12: FALSE | F12: FALSE | G12: 3402.14 | H12: per month | J12: =IF(B12="Monthly F",G12,IF(B12="Monthly V",G12*I12,IF(B12="Annual",G12/12,0))) -> 3402.14 | K12: =IF(B12="One-Time",G12,J12*12) -> 40825.68 | L12: =IF(B12="One-Time",0,K12*(1+Metadata!$B$8)) -> 41642.194 | M12: =IF(B12="One-Time",0,L12*(1+Metadata!$B$8)) -> 42475.037 | N12: =IF(B12="One-Time",0,M12*(1+Metadata!$B$8)) -> 43324.538 | O12: =IF(B12="One-Time",0,N12*(1+Metadata!$B$8)) -> 44191.029 | P12: =IF(B12="One-Time",0,O12*(1+Metadata!$B$8)) -> 45074.85 | Q12: =IF(B12="One-Time",0,P12*(1+Metadata!$B$8)) -> 45976.347 | R12: =SUM(K12:Q12) -> 303509.67 | S12: 0.98 | T12: New DirectLink Merchant solution
A13: 34 | B13: Monthly F | C13: Image Solutions: Chargeback Manager | D13: Other | E13: FALSE | F13: FALSE | G13: 250 | H13: per month | J13: =IF(B13="Monthly F",G13,IF(B13="Monthly V",G13*I13,IF(B13="Annual",G13/12,0))) -> 250 | K13: =IF(B13="One-Time",G13,J13*12) -> 3000 | L13: =IF(B13="One-Time",0,K13*(1+Metadata!$B$8)) -> 3060 | M13: =IF(B13="One-Time",0,L13*(1+Metadata!$B$8)) -> 3121.2 | N13: =IF(B13="One-Time",0,M13*(1+Metadata!$B$8)) -> 3183.624 | O13: =IF(B13="One-Time",0,N13*(1+Metadata!$B$8)) -> 3247.2965 | P13: =IF(B13="One-Time",0,O13*(1+Metadata!$B$8)) -> 3312.2424 | Q13: =IF(B13="One-Time",0,P13*(1+Metadata!$B$8)) -> 3378.4873 | R13: =SUM(K13:Q13) -> 22302.85 | S13: 0.98 | T13: New chargeback management solution
... A38: 13 | B38: Monthly F | C38: Accounts Payable: Avid Ascend | D38: Other | E38: TRUE | F38: FALSE | G38: 807 | H38: per month | J38: =IF(B38="Monthly F",G38,IF(B38="Monthly V",G38*I38,IF(B38="Annual",G38/12,0))) -> 807 | K38: =IF(B38="One-Time",G38,J38*12) -> 9684 | L38: =IF(B38="One-Time",0,K38*(1+Metadata!$B$8)) -> 9877.68 | M38: =IF(B38="One-Time",0,L38*(1+Metadata!$B$8)) -> 10075.234 | N38: =IF(B38="One-Time",0,M38*(1+Metadata!$B$8)) -> 10276.738 | O38: =IF(B38="One-Time",0,N38*(1+Metadata!$B$8)) -> 10482.273 | P38: =IF(B38="One-Time",0,O38*(1+Metadata!$B$8)) -> 10691.918 | Q38: =IF(B38="One-Time",0,P38*(1+Metadata!$B$8)) -> 10905.757 | R38: =SUM(K38:Q38) -> 71993.6 | S38: 0.98 | T38: Third-party accounts payable solution

Sheet Year_Summary
A1: Annual Cost Breakdown (7-Year Projection)
A2: Category | B2: Year 1 | C2: Year 2 | D2: Year 3 | E2: Year 4 | F2: Year 5 | G2: Year 6 | H2: Year 7
A3: Required Annual Fees | B3: 399533 | C3: 376753.4 | D3: 440017.88 | E3: 510294.94 | F3: 599967.73 | G3: 607547.29 | H3: 642270.55
A4: Optional Annual Fees | B4: 421958 | C4: 436416 | D4: 299616 | E4: 351456 | F4: 413664 | G4: 488313.6 | H4: 577893.12
A5: One-Time Fees | B5: -159156.14 | C5: -159156.14 | D5: -159156.14 | E5: -159156.14 | F5: -159156.14 | G5: -159156.14 | H5: -159156.14
A6: Total Annual Cost | B6: =SUM(B3:B5) -> 662334.86 | C6: =SUM(C3:C5) -> 654013.26 | D6: =SUM(D3:D5) -> 580477.74 | E6: =SUM(E3:E5) -> 702594.8 | F6: =SUM(F3:F5) -> 854475.59 | G6: =SUM(G3:G5) -> 936704.75 | H6: =SUM(H3:H5) -> 1061007.5

Sheet Summary
A1: Total Cost of Ownership (TCO) Summary
A2: Vendor: | B2: =Metadata!B2 -> FIS
A4: Category | B4: 7-Year Total | C4: Monthly Average
A5: Core | B5: =Line_Items!R2 -> 1498037.8
A6: Digital | B6: =SUM(Line_Items!R3:R37) -> 8173546.4
A7: EFT | B7: =SUM(Line_Items!R6:R8) -> 656417.49
A8: One-Time Fees | B8: =SUM(Line_Items!R26:R27) -> 377096.59
A10: Total Required TCO | B10: =SUM(B5:B8) -> 10705098
A12: Optional Solutions | B12: =SUM(Line_Items!R9:R38) -> 4336296.4
A14: Grand Total (Required + Optional) | B14: =SUM(B10,B12) -> 15041395
