Workbook

Sheet Line Items
O1: FIS
B2: Years-> | D2: 7
B3: Growth-> | D3: 0.2
B4: Type (Monthly/Annual) | D4: Average Monthly QTY | E4: Quantity Per Year with Growth | O4: FIS | Q4: Per Unit Rate
C5: Proposal (12/2025) | E5: Year 1 Quantity | F5: Year 2 Quantity | G5: Year 3 Quantity | H5: Year 4 Quantity | I5: Year 5 Quantity | J5: Year 6 Quantity | K5: Year 7 Quantity | O5: Solution Name/Description | P5: Category | R5: Year 1 Monthly Cost | S5: Year 1 Cost | T5: Year 2 Cost | U5: Year 3 Cost | V5: Year 4 Cost | W5: Year 5 Cost | X5: Year 6 Cost | Y5: Year 7 Cost | AM5: CPI | AN5: Total Term Cost
B6: Recurring Monthly and Annual Fees
B7: Monthly F | C7: 1 | D7: =IFERROR(AVERAGE(C7:C7),0) | E7: 12 | F7: 0 | G7: 0 | H7: 0 | I7: 0 | J7: 0 | K7: 0 | O7: Year 1 CORE PROCESSING (Bundle) | P7: HORIZON CORE ACCOUNT PROCESSING | Q7: 15000 | R7: =S7/12 | S7: =IFERROR($Q7*E7,0) | T7: =IFERROR($Q7*F7,0) | U7: =IFERROR($Q7*G7,0) | V7: =IFERROR($Q7*H7,0) | W7: =IFERROR($Q7*I7,0) | X7: =IFERROR($Q7*J7,0) | Y7: =IFERROR($Q7*K7,0) | AM7: 0 | AN7: =SUM(AM7,S7:Y7)
B8: Monthly F | C8: 1 | D8: =IFERROR(AVERAGE(C8:C8),0) | E8: 0 | F8: 12 | G8: 0 | H8: 0 | I8: 0 | J8: 0 | K8: 0 | O8: Year 2 CORE PROCESSING (Bundle) | P8: HORIZON CORE ACCOUNT PROCESSING | Q8: 17500 | R8: =S8/12 | S8: =IFERROR($Q8*E8,0) | T8: =IFERROR($Q8*F8,0) | U8: =IFERROR($Q8*G8,0) | V8: =IFERROR($Q8*H8,0) | W8: =IFERROR($Q8*I8,0) | X8: =IFERROR($Q8*J8,0) | Y8: =IFERROR($Q8*K8,0) | AM8: 0 | AN8: =SUM(AM8,S8:Y8)
B9: Monthly F | C9: 1 | D9: =IFERROR(AVERAGE(C9:C9),0) | E9: 0 | F9: 0 | G9: 12 | H9: 0 | I9: 0 | J9: 0 | K9: 0 | O9: Year 3 CORE PROCESSING (Bundle) | P9: HORIZON CORE ACCOUNT PROCESSING | Q9: 22500 | R9: =S9/12 | S9: =IFERROR($Q9*E9,0) | T9: =IFERROR($Q9*F9,0) | U9: =IFERROR($Q9*G9,0) | V9: =IFERROR($Q9*H9,0) | W9: =IFERROR($Q9*I9,0) | X9: =IFERROR($Q9*J9,0) | Y9: =IFERROR($Q9*K9,0) | AM9: 0 | AN9: =SUM(AM9,S9:Y9)
B10: Monthly F | C10: 1 | D10: =IFERROR(AVERAGE(C10:C10),0) | E10: 0 | F10: 0 | G10: 0 | H10: 12 | I10: 0 | J10: 0 | K10: 0 | O10: Year 4 CORE PROCESSING (Bundle) | P10: HORIZON CORE ACCOUNT PROCESSING | Q10: 28000 | R10: =S10/12 | S10: =IFERROR($Q10*E10,0) | T10: =IFERROR($Q10*F10,0) | U10: =IFERROR($Q10*G10,0) | V10: =IFERROR($Q10*H10,0) | W10: =IFERROR($Q10*I10,0) | X10: =IFERROR($Q10*J10,0) | Y10: =IFERROR($Q10*K10,0) | AM10: 0 | AN10: =SUM(AM10,S10:Y10)
B11: Monthly F | C11: 1 | D11: =IFERROR(AVERAGE(C11:C11),0) | E11: 0 | F11: 0 | G11: 0 | H11: 0 | I11: 12 | J11: 0 | K11: 0 | O11: Year 5 CORE PROCESSING (Bundle) | P11: HORIZON CORE ACCOUNT PROCESSING | Q11: 35000 | R11: =S11/12 | S11: =IFERROR($Q11*E11,0) | T11: =IFERROR($Q11*F11,0) | U11: =IFERROR($Q11*G11,0) | V11: =IFERROR($Q11*H11,0) | W11: =IFERROR($Q11*I11,0) | X11: =IFERROR($Q11*J11,0) | Y11: =IFERROR($Q11*K11,0) | AM11: 0 | AN11: =SUM(AM11,S11:Y11)
B12: Monthly F | C12: 1 | D12: =IFERROR(AVERAGE(C12:C12),0) | E12: 0 | F12: 0 | G12: 0 | H12: 0 | I12: 0 | J12: 12 | K12: 0 | O12: Year 6 CORE PROCESSING (Bundle) - CPI Increase | P12: HORIZON CORE ACCOUNT PROCESSING | Q12: 37275 | R12: =S12/12 | S12: =IFERROR($Q12*E12,0) | T12: =IFERROR($Q12*F12,0) | U12: =IFERROR($Q12*G12,0) | V12: =IFERROR($Q12*H12,0) | W12: =IFERROR($Q12*I12,0) | X12: =IFERROR($Q12*J12,0) | Y12: =IFERROR($Q12*K12,0) | AM12: 0 | AN12: =SUM(AM12,S12:Y12)
B13: Monthly F | C13: 1 | D13: =IFERROR(AVERAGE(C13:C13),0) | E13: 0 | F13: 0 | G13: 0 | H13: 0 | I13: 0 | J13: 0 | K13: 12 | O13: Year 7 CORE PROCESSING (Bundle) - CPI Increase | P13: HORIZON CORE ACCOUNT PROCESSING | Q13: 39697.875 | R13: =S13/12 | S13: =IFERROR($Q13*E13,0) | T13: =IFERROR($Q13*F13,0) | U13: =IFERROR($Q13*G13,0) | V13: =IFERROR($Q13*H13,0) | W13: =IFERROR($Q13*I13,0) | X13: =IFERROR($Q13*J13,0) | Y13: =IFERROR($Q13*K13,0) | AM13: 0 | AN13: =SUM(AM13,S13:Y13)
O21: Non-Bundle FIS Required Products
B22: Monthly F | C22: 1 | D22: =IFERROR(AVERAGE(C22:C22),0) | E22: =IF($B22="Annual",1,IF($B22="Monthly F",12,IF($B22="Monthly V",D22*12,IF($B22="One-Time",1,D22*12)))) | F22: =IF($B22="Monthly V",E22*(1+$D$3),E22) | G22: =IF($B22="Monthly V",F22*(1+$D$3),F22) | H22: =IF($B22="Monthly V",G22*(1+$D$3),G22) | I22: =IF($B22="Monthly V",H22*(1+$D$3),H22) | J22: =IF($B22="Monthly V",I22*(1+$D$3),I22) | K22: =IF($B22="Monthly V",J22*(1+$D$3),J22) | O22: Paper and Envelopes (statements and notices) | P22: Non-Bundle Required | Q22: 29 | R22: =S22/12 | S22: =IFERROR($Q22*E22,0) | T22: =IFERROR($Q22*F22,0) | U22: =IFERROR($Q22*G22,0) | V22: =IFERROR($Q22*H22,0) | W22: =IFERROR($Q22*I22,0) | X22: =IFERROR($Q22*J22,0) | Y22: =IFERROR($Q22*K22,0) | AM22: 0 | AN22: =SUM(AM22,S22:Y22)
B23: Monthly F | C23: 1 | D23: =IFERROR(AVERAGE(C23:C23),0) | E23: =IF($B23="Annual",1,IF($B23="Monthly F",12,IF($B23="Monthly V",D23*12,IF($B23="One-Time",1,D23*12)))) | F23: =IF($B23="Monthly V",E23*(1+$D$3),E23) | G23: =IF($B23="Monthly V",F23*(1+$D$3),F23) | H23: =IF($B23="Monthly V",G23*(1+$D$3),G23) | I23: =IF($B23="Monthly V",H23*(1+$D$3),H23) | J23: =IF($B23="Monthly V",I23*(1+$D$3),I23) | K23: =IF($B23="Monthly V",J23*(1+$D$3),J23) | O23: Debit Card Production | P23: Non-Bundle Required | Q23: 1018 | R23: =S23/12 | S23: =IFERROR($Q23*E23,0) | T23: =IFERROR($Q23*F23,0) | U23: =IFERROR($Q23*G23,0) | V23: =IFERROR($Q23*H23,0) | W23: =IFERROR($Q23*I23,0) | X23: =IFERROR($Q23*J23,0) | Y23: =IFERROR($Q23*K23,0) | AM23: 0 | AN23: =SUM(AM23,S23:Y23)
B24: Monthly F | C24: 1 | D24: =IFERROR(AVERAGE(C24:C24),0) | E24: =IF($B24="Annual",1,IF($B24="Monthly F",12,IF($B24="Monthly V",D24*12,IF($B24="One-Time",1,D24*12)))) | F24: =IF($B24="Monthly V",E24*(1+$D$3),E24) | G24: =IF($B24="Monthly V",F24*(1+$D$3),F24) | H24: =IF($B24="Monthly V",G24*(1+$D$3),G24) | I24: =IF($B24="Monthly V",H24*(1+$D$3),H24) | J24: =IF($B24="Monthly V",I24*(1+$D$3),I24) | K24: =IF($B24="Monthly V",J24*(1+$D$3),J24) | O24: DirectLink Risk Review (DLRR) | P24: Non-Bundle Required | Q24: 233 | R24: =S24/12 | S24: =IFERROR($Q24*E24,0) | T24: =IFERROR($Q24*F24,0) | U24: =IFERROR($Q24*G24,0) | V24: =IFERROR($Q24*H24,0) | W24: =IFERROR($Q24*I24,0) | X24: =IFERROR($Q24*J24,0) | Y24: =IFERROR($Q24*K24,0) | AM24: 0 | AN24: =SUM(AM24,S24:Y24)
B25: Monthly F | C25: 1 | D25: =IFERROR(AVERAGE(C25:C25),0) | E25: =IF($B25="Annual",1,IF($B25="Monthly F",12,IF($B25="Monthly V",D25*12,IF($B25="One-Time",1,D25*12)))) | F25: =IF($B25="Monthly V",E25*(1+$D$3),E25) | G25: =IF($B25="Monthly V",F25*(1+$D$3),F25) | H25: =IF($B25="Monthly V",G25*(1+$D$3),G25) | I25: =IF($B25="Monthly V",H25*(1+$D$3),H25) | J25: =IF($B25="Monthly V",I25*(1+$D$3),I25) | K25: =IF($B25="Monthly V",J25*(1+$D$3),J25) | O25: Card Suite Pro (digital debit card controls) | P25: Non-Bundle Required | Q25: 425 | R25: =S25/12 | S25: =IFERROR($Q25*E25,0) | T25: =IFERROR($Q25*F25,0) | U25: =IFERROR($Q25*G25,0) | V25: =IFERROR($Q25*H25,0) | W25: =IFERROR($Q25*I25,0) | X25: =IFERROR($Q25*J25,0) | Y25: =IFERROR($Q25*K25,0) | AM25: 0 | AN25: =SUM(AM25,S25:Y25)
B26: Monthly F | C26: 1 | D26: =IFERROR(AVERAGE(C26:C26),0) | E26: =IF($B26="Annual",1,IF($B26="Monthly F",12,IF($B26="Monthly V",D26*12,IF($B26="One-Time",1,D26*12)))) | F26: =IF($B26="Monthly V",E26*(1+$D$3),E26) | G26: =IF($B26="Monthly V",F26*(1+$D$3),F26) | H26: =IF($B26="Monthly V",G26*(1+$D$3),G26) | I26: =IF($B26="Monthly V",H26*(1+$D$3),H26) | J26: =IF($B26="Monthly V",I26*(1+$D$3),I26) | K26: =IF($B26="Monthly V",J26*(1+$D$3),J26) | O26: Payments One Debit Card Fraud Case Investigation Sheets | P26: Non-Bundle Required | Q26: 500 | R26: =S26/12 | S26: =IFERROR($Q26*E26,0) | T26: =IFERROR($Q26*F26,0) | U26: =IFERROR($Q26*G26,0) | V26: =IFERROR($Q26*H26,0) | W26: =IFERROR($Q26*I26,0) | X26: =IFERROR($Q26*J26,0) | Y26: =IFERROR($Q26*K26,0) | AM26: 0 | AN26: =SUM(AM26,S26:Y26)
B27: Monthly F | C27: 1 | D27: =IFERROR(AVERAGE(C27:C27),0) | E27: =IF($B27="Annual",1,IF($B27="Monthly F",12,IF($B27="Monthly V",D27*12,IF($B27="One-Time",1,D27*12)))) | F27: =IF($B27="Monthly V",E27*(1+$D$3),E27) | G27: =IF($B27="Monthly V",F27*(1+$D$3),F27) | H27: =IF($B27="Monthly V",G27*(1+$D$3),G27) | I27: =IF($B27="Monthly V",H27*(1+$D$3),H27) | J27: =IF($B27="Monthly V",I27*(1+$D$3),I27) | K27: =IF($B27="Monthly V",J27*(1+$D$3),J27) | O27: Payments One Full-Service Debit Card Fraud Disputes | P27: Non-Bundle Required | Q27: 175 | R27: =S27/12 | S27: =IFERROR($Q27*E27,0) | T27: =IFERROR($Q27*F27,0) | U27: =IFERROR($Q27*G27,0) | V27: =IFERROR($Q27*H27,0) | W27: =IFERROR($Q27*I27,0) | X27: =IFERROR($Q27*J27,0) | Y27: =IFERROR($Q27*K27,0) | AM27: 0 | AN27: =SUM(AM27,S27:Y27)
B28: Monthly F | C28: 1 | D28: =IFERROR(AVERAGE(C28:C28),0) | E28: =IF($B28="Annual",1,IF($B28="Monthly F",12,IF($B28="Monthly V",D28*12,IF($B28="One-Time",1,D28*12)))) | F28: =IF($B28="Monthly V",E28*(1+$D$3),E28) | G28: =IF($B28="Monthly V",F28*(1+$D$3),F28) | H28: =IF($B28="Monthly V",G28*(1+$D$3),G28) | I28: =IF($B28="Monthly V",H28*(1+$D$3),H28) | J28: =IF($B28="Monthly V",I28*(1+$D$3),I28) | K28: =IF($B28="Monthly V",J28*(1+$D$3),J28) | O28: Tokenization (ApplePay, Additional Pays) | P28: Non-Bundle Required | Q28: 337 | R28: =S28/12 | S28: =IFERROR($Q28*E28,0) | T28: =IFERROR($Q28*F28,0) | U28: =IFERROR($Q28*G28,0) | V28: =IFERROR($Q28*H28,0) | W28: =IFERROR($Q28*I28,0) | X28: =IFERROR($Q28*J28,0) | Y28: =IFERROR($Q28*K28,0) | AM28: 0 | AN28: =SUM(AM28,S28:Y28)
B29: Monthly F | C29: 1 | D29: =IFERROR(AVERAGE(C29:C29),0) | E29: =IF($B29="Annual",1,IF($B29="Monthly F",12,IF($B29="Monthly V",D29*12,IF($B29="One-Time",1,D29*12)))) | F29: =IF($B29="Monthly V",E29*(1+$D$3),E29) | G29: =IF($B29="Monthly V",F29*(1+$D$3),F29) | H29: =IF($B29="Monthly V",G29*(1+$D$3),G29) | I29: =IF($B29="Monthly V",H29*(1+$D$3),H29) | J29: =IF($B29="Monthly V",I29*(1+$D$3),I29) | K29: =IF($B29="Monthly V",J29*(1+$D$3),J29) | O29: NYCE Preferred Debit Card Network | P29: Non-Bundle Required | Q29: 152 | R29: =S29/12 | S29: =IFERROR($Q29*E29,0) | T29: =IFERROR($Q29*F29,0) | U29: =IFERROR($Q29*G29,0) | V29: =IFERROR($Q29*H29,0) | W29: =IFERROR($Q29*I29,0) | X29: =IFERROR($Q29*J29,0) | Y29: =IFERROR($Q29*K29,0) | AM29: 0 | AN29: =SUM(AM29,S29:Y29)
B30: Monthly F | C30: 1 | D30: =IFERROR(AVERAGE(C30:C30),0) | E30: =IF($B30="Annual",1,IF($B30="Monthly F",12,IF($B30="Monthly V",D30*12,IF($B30="One-Time",1,D30*12)))) | F30: =IF($B30="Monthly V",E30*(1+$D$3),E30) | G30: =IF($B30="Monthly V",F30*(1+$D$3),F30) | H30: =IF($B30="Monthly V",G30*(1+$D$3),G30) | I30: =IF($B30="Monthly V",H30*(1+$D$3),H30) | J30: =IF($B30="Monthly V",I30*(1+$D$3),I30) | K30: =IF($B30="Monthly V",J30*(1+$D$3),J30) | O30: Subpoena Centre | P30: Non-Bundle Required | Q30: 382 | R30: =S30/12 | S30: =IFERROR($Q30*E30,0) | T30: =IFERROR($Q30*F30,0) | U30: =IFERROR($Q30*G30,0) | V30: =IFERROR($Q30*H30,0) | W30: =IFERROR($Q30*I30,0) | X30: =IFERROR($Q30*J30,0) | Y30: =IFERROR($Q30*K30,0) | AM30: 0 | AN30: =SUM(AM30,S30:Y30)
B31: Monthly F | C31: 1 | D31: =IFERROR(AVERAGE(C31:C31),0) | E31: =IF($B31="Annual",1,IF($B31="Monthly F",12,IF($B31="Monthly V",D31*12,IF($B31="One-Time",1,D31*12)))) | F31: =IF($B31="Monthly V",E31*(1+$D$3),E31) | G31: =IF($B31="Monthly V",F31*(1+$D$3),F31) | H31: =IF($B31="Monthly V",G31*(1+$D$3),G31) | I31: =IF($B31="Monthly V",H31*(1+$D$3),H31) | J31: =IF($B31="Monthly V",I31*(1+$D$3),I31) | K31: =IF($B31="Monthly V",J31*(1+$D$3),J31) | O31: Start Card (Temporary Debit Card) | P31: Non-Bundle Required | Q31: 150 | R31: =S31/12 | S31: =IFERROR($Q31*E31,0) | T31: =IFERROR($Q31*F31,0) | U31: =IFERROR($Q31*G31,0) | V31: =IFERROR($Q31*H31,0) | W31: =IFERROR($Q31*I31,0) | X31: =IFERROR($Q31*J31,0) | Y31: =IFERROR($Q31*K31,0) | AM31: 0 | AN31: =SUM(AM31,S31:Y31)
B32: Monthly F | C32: 1 | D32: =IFERROR(AVERAGE(C32:C32),0) | E32: =IF($B32="Annual",1,IF($B32="Monthly F",12,IF($B32="Monthly V",D32*12,IF($B32="One-Time",1,D32*12)))) | F32: =IF($B32="Monthly V",E32*(1+$D$3),E32) | G32: =IF($B32="Monthly V",F32*(1+$D$3),F32) | H32: =IF($B32="Monthly V",G32*(1+$D$3),G32) | I32: =IF($B32="Monthly V",H32*(1+$D$3),H32) | J32: =IF($B32="Monthly V",I32*(1+$D$3),I32) | K32: =IF($B32="Monthly V",J32*(1+$D$3),J32) | O32: FedNOW (Receive Only) | P32: Non-Bundle Required | Q32: 1500 | R32: =S32/12 | S32: =IFERROR($Q32*E32,0) | T32: =IFERROR($Q32*F32,0) | U32: =IFERROR($Q32*G32,0) | V32: =IFERROR($Q32*H32,0) | W32: =IFERROR($Q32*I32,0) | X32: =IFERROR($Q32*J32,0) | Y32: =IFERROR($Q32*K32,0) | AM32: 0 | AN32: =SUM(AM32,S32:Y32)
B33: Monthly F | C33: 1 | D33: =IFERROR(AVERAGE(C33:C33),0) | E33: =IF($B33="Annual",1,IF($B33="Monthly F",12,IF($B33="Monthly V",D33*12,IF($B33="One-Time",1,D33*12)))) | F33: =IF($B33="Monthly V",E33*(1+$D$3),E33) | G33: =IF($B33="Monthly V",F33*(1+$D$3),F33) | H33: =IF($B33="Monthly V",G33*(1+$D$3),G33) | I33: =IF($B33="Monthly V",H33*(1+$D$3),H33) | J33: =IF($B33="Monthly V",I33*(1+$D$3),I33) | K33: =IF($B33="Monthly V",J33*(1+$D$3),J33) | O33: Real-Time Payments (RTP) (Receive Only) | P33: Non-Bundle Required | Q33: 1500 | R33: =S33/12 | S33: =IFERROR($Q33*E33,0) | T33: =IFERROR($Q33*F33,0) | U33: =IFERROR($Q33*G33,0) | V33: =IFERROR($Q33*H33,0) | W33: =IFERROR($Q33*I33,0) | X33: =IFERROR($Q33*J33,0) | Y33: =IFERROR($Q33*K33,0) | AM33: 0 | AN33: =SUM(AM33,S33:Y33)
... B37: Monthly F | C37: 1 | D37: =IFERROR(AVERAGE(C37:C37),0) | E37: =IF($B37="Annual",1,IF($B37="Monthly F",12,IF($B37="Monthly V",D37*12,IF($B37="One-Time",1,D37*12)))) | F37: =IF($B37="Monthly V",E37*(1+$D$3),E37) | G37: =IF($B37="Monthly V",F37*(1+$D$3),F37) | H37: =IF($B37="Monthly V",G37*(1+$D$3),G37) | I37: =IF($B37="Monthly V",H37*(1+$D$3),H37) | J37: =IF($B37="Monthly V",I37*(1+$D$3),I37) | K37: =IF($B37="Monthly V",J37*(1+$D$3),J37) | O37: Collaboration Hub | P37: Non-Bundle Required | Q37: 3300 | R37: =S37/12 | S37: =IFERROR($Q37*E37,0) | T37: =IFERROR($Q37*F37,0) | U37: =IFERROR($Q37*G37,0) | V37: =IFERROR($Q37*H37,0) | W37: =IFERROR($Q37*I37,0) | X37: =IFERROR($Q37*J37,0) | Y37: =IFERROR($Q37*K37,0) | AM37: 0 | AN37: =SUM(AM37,S37:Y37)
O57: Non-Bundle Required Third Parties
B58: Monthly F | C58: 1 | D58: =IFERROR(AVERAGE(C58:C58),0) | E58: =IF($B58="Annual",1,IF($B58="Monthly F",12,IF($B58="Monthly V",D58*12,IF($B58="One-Time",1,D58*12)))) | F58: =IF($B58="Monthly V",E58*(1+$D$3),E58) | G58: =IF($B58="Monthly V",F58*(1+$D$3),F58) | H58: =IF($B58="Monthly V",G58*(1+$D$3),G58) | I58: =IF($B58="Monthly V",H58*(1+$D$3),H58) | J58: =IF($B58="Monthly V",I58*(1+$D$3),I58) | K58: =IF($B58="Monthly V",J58*(1+$D$3),J58) | O58: Network Services (connectivity to data center) | P58: Third-Party Required | Q58: 2088 | R58: =S58/12 | S58: =IFERROR($Q58*E58,0) | T58: =IFERROR($Q58*F58,0) | U58: =IFERROR($Q58*G58,0) | V58: =IFERROR($Q58*H58,0) | W58: =IFERROR($Q58*I58,0) | X58: =IFERROR($Q58*J58,0) | Y58: =IFERROR($Q58*K58,0) | AM58: 0 | AN58: =SUM(AM58,S58:Y58)
B59: Monthly F | C59: 1 | D59: =IFERROR(AVERAGE(C59:C59),0) | E59: =IF($B59="Annual",1,IF($B59="Monthly F",12,IF($B59="Monthly V",D59*12,IF($B59="One-Time",1,D59*12)))) | F59: =IF($B59="Monthly V",E59*(1+$D$3),E59) | G59: =IF($B59="Monthly V",F59*(1+$D$3),F59) | H59: =IF($B59="Monthly V",G59*(1+$D$3),G59) | I59: =IF($B59="Monthly V",H59*(1+$D$3),H59) | J59: =IF($B59="Monthly V",I59*(1+$D$3),I59) | K59: =IF($B59="Monthly V",J59*(1+$D$3),J59) | O59: SmartSign (eSignature) | P59: Third-Party Required | Q59: 478 | R59: =S59/12 | S59: =IFERROR($Q59*E59,0) | T59: =IFERROR($Q59*F59,0) | U59: =IFERROR($Q59*G59,0) | V59: =IFERROR($Q59*H59,0) | W59: =IFERROR($Q59*I59,0) | X59: =IFERROR($Q59*J59,0) | Y59: =IFERROR($Q59*K59,0) | AM59: 0 | AN59: =SUM(AM59,S59:Y59)
B60: Monthly F | C60: 1 | D60: =IFERROR(AVERAGE(C60:C60),0) | E60: =IF($B60="Annual",1,IF($B60="Monthly F",12,IF($B60="Monthly V",D60*12,IF($B60="One-Time",1,D60*12)))) | F60: =IF($B60="Monthly V",E60*(1+$D$3),E60) | G60: =IF($B60="Monthly V",F60*(1+$D$3),F60) | H60: =IF($B60="Monthly V",G60*(1+$D$3),G60) | I60: =IF($B60="Monthly V",H60*(1+$D$3),H60) | J60: =IF($B60="Monthly V",I60*(1+$D$3),I60) | K60: =IF($B60="Monthly V",J60*(1+$D$3),J60) | O60: TruStage (new deposit account documents) | P60: Third-Party Required | Q60: 1158 | R60: =S60/12 | S60: =IFERROR($Q60*E60,0) | T60: =IFERROR($Q60*F60,0) | U60: =IFERROR($Q60*G60,0) | V60: =IFERROR($Q60*H60,0) | W60: =IFERROR($Q60*I60,0) | X60: =IFERROR($Q60*J60,0) | Y60: =IFERROR($Q60*K60,0) | AM60: 0 | AN60: =SUM(AM60,S60:Y60)
B61: Monthly F | C61: 1 | D61: =IFERROR(AVERAGE(C61:C61),0) | E61: =IF($B61="Annual",1,IF($B61="Monthly F",12,IF($B61="Monthly V",D61*12,IF($B61="One-Time",1,D61*12)))) | F61: =IF($B61="Monthly V",E61*(1+$D$3),E61) | G61: =IF($B61="Monthly V",F61*(1+$D$3),F61) | H61: =IF($B61="Monthly V",G61*(1+$D$3),G61) | I61: =IF($B61="Monthly V",H61*(1+$D$3),H61) | J61: =IF($B61="Monthly V",I61*(1+$D$3),I61) | K61: =IF($B61="Monthly V",J61*(1+$D$3),J61) | O61: IBM Cognos (HORIZON 360) | P61: Third-Party Required | Q61: 1172 | R61: =S61/12 | S61: =IFERROR($Q61*E61,0) | T61: =IFERROR($Q61*F61,0) | U61: =IFERROR($Q61*G61,0) | V61: =IFERROR($Q61*H61,0) | W61: =IFERROR($Q61*I61,0) | X61: =IFERROR($Q61*J61,0) | Y61: =IFERROR($Q61*K61,0) | AM61: 0 | AN61: =SUM(AM61,S61:Y61)
B62: Monthly F | C62: 1 | D62: =IFERROR(AVERAGE(C62:C62),0) | E62: =IF($B62="Annual",1,IF($B62="Monthly F",12,IF($B62="Monthly V",D62*12,IF($B62="One-Time",1,D62*12)))) | F62: =IF($B62="Monthly V",E62*(1+$D$3),E62) | G62: =IF($B62="Monthly V",F62*(1+$D$3),F62) | H62: =IF($B62="Monthly V",G62*(1+$D$3),G62) | I62: =IF($B62="Monthly V",H62*(1+$D$3),H62) | J62: =IF($B62="Monthly V",I62*(1+$D$3),I62) | K62: =IF($B62="Monthly V",J62*(1+$D$3),J62) | O62: AvidAscend (Accounts Payable, Fixed Assets, and Prepaids) | P62: Third-Party Required | Q62: 1127 | R62: =S62/12 | S62: =IFERROR($Q62*E62,0) | T62: =IFERROR($Q62*F62,0) | U62: =IFERROR($Q62*G62,0) | V62: =IFERROR($Q62*H62,0) | W62: =IFERROR($Q62*I62,0) | X62: =IFERROR($Q62*J62,0) | Y62: =IFERROR($Q62*K62,0) | AM62: 0 | AN62: =SUM(AM62,S62:Y62)
O92: Implementation Credits and Fees
B93: One-Time | C93: 1 | D93: =IFERROR(AVERAGE(C93:C93),0) | E93: 1 | F93: 0 | G93: 0 | H93: 0 | I93: 0 | J93: 0 | K93: 0 | O93: Signing Bonus | P93: Implementation Credit | Q93: -75000 | R93: =S93/12 | S93: =IFERROR($Q93*E93,0) | T93: 0 | U93: 0 | V93: 0 | W93: 0 | X93: 0 | Y93: 0 | AM93: 0 | AN93: =SUM(AM93,S93:Y93)
B94: One-Time | C94: 1 | D94: =IFERROR(AVERAGE(C94:C94),0) | E94: 1 | F94: 0 | G94: 0 | H94: 0 | I94: 0 | J94: 0 | K94: 0 | O94: First-Year Free FIS Processing | P94: Implementation Credit | Q94: -180000 | R94: =S94/12 | S94: =IFERROR($Q94*E94,0) | T94: 0 | U94: 0 | V94: 0 | W94: 0 | X94: 0 | Y94: 0 | AM94: 0 | AN94: =SUM(AM94,S94:Y94)
B95: One-Time | C95: 1 | D95: =IFERROR(AVERAGE(C95:C95),0) | E95: 1 | F95: 0 | G95: 0 | H95: 0 | I95: 0 | J95: 0 | K95: 0 | O95: FIS Conversion / Implementation Fees | P95: Implementation Fee | Q95: 844093 | R95: =S95/12 | S95: =IFERROR($Q95*E95,0) | T95: 0 | U95: 0 | V95: 0 | W95: 0 | X95: 0 | Y95: 0 | AM95: 0 | AN95: =SUM(AM95,S95:Y95)
B96: One-Time | C96: 1 | D96: =IFERROR(AVERAGE(C96:C96),0) | E96: 1 | F96: 0 | G96: 0 | H96: 0 | I96: 0 | J96: 0 | K96: 0 | O96: Third-Party Conversion / Implementation Fees | P96: Implementation Fee | Q96: 137070 | R96: =S96/12 | S96: =IFERROR($Q96*E96,0) | T96: 0 | U96: 0 | V96: 0 | W96: 0 | X96: 0 | Y96: 0 | AM96: 0 | AN96: =SUM(AM96,S96:Y96)
B97: One-Time | C97: 1 | D97: =IFERROR(AVERAGE(C97:C97),0) | E97: 1 | F97: 0 | G97: 0 | H97: 0 | I97: 0 | J97: 0 | K97: 0 | O97: Special Credit to Hire Industry Consultant | P97: Implementation Credit | Q97: -50000 | R97: =S97/12 | S97: =IFERROR($Q97*E97,0) | T97: 0 | U97: 0 | V97: 0 | W97: 0 | X97: 0 | Y97: 0 | AM97: 0 | AN97: =SUM(AM97,S97:Y97)
B98: One-Time | C98: 1 | D98: =IFERROR(AVERAGE(C98:C98),0) | E98: 1 | F98: 0 | G98: 0 | H98: 0 | I98: 0 | J98: 0 | K98: 0 | O98: Conversion-Related Professional Service Fees | P98: Implementation Fee | Q98: 290000 | R98: =S98/12 | S98: =IFERROR($Q98*E98,0) | T98: 0 | U98: 0 | V98: 0 | W98: 0 | X98: 0 | Y98: 0 | AM98: 0 | AN98: =SUM(AM98,S98:Y98)

Sheet Summary
B1: FIS
B2: Required Items | C2: Total 7 Year | D2: Monthly Avg.
B3: Bundle FIS Products | C3: =SUM('Line Items'!AN7:AN13) | D3: =C3/84
B4: Non-Bundle FIS Required Products | C4: =SUM('Line Items'!AN22:AN54) | D4: =C4/84
B5: Non-Bundle Required Third Parties | C5: =SUM('Line Items'!AN58:AN84) | D5: =C5/84
B6: Sub-Total: Required/Included Products | C6: =SUM(C3:C5) | D6: =C6/84
B8: Implementation Credits | C8: =SUM('Line Items'!AN93:AN97)
B10: TOTAL REQUIRED (minus credits) | C10: =C6+C8 | D10: =C10/84
B13: Yearly Breakdown
B14: Year 1 | C14: =SUM('Line Items'!S7:S97)
B15: Year 2 | C15: =SUM('Line Items'!T7:T97)
B16: Year 3 | C16: =SUM('Line Items'!U7:U97)
B17: Year 4 | C17: =SUM('Line Items'!V7:V97)
B18: Year 5 | C18: =SUM('Line Items'!W7:W97)
B19: Year 6 | C19: =SUM('Line Items'!X7:X97)
B20: Year 7 | C20: =SUM('Line Items'!Y7:Y97)
