Workbook

Sheet Line Items
A1: Row ID | B1: Fee Type | C1: Solution Name | D1: Category | E1: Third Party | F1: Optional | G1: Per Unit Rate | H1: Unit Description | I1: Avg Monthly Qty | J1: Year 1 Monthly | K1: Year 1 Annual | L1: Year 2 | M1: Year 3 | N1: Year 4 | O1: Year 5 | P1: Year 6 | Q1: Year 7 | R1: Total 7-Year Cost | S1: Confidence | T1: Notes
A2: 8 | B2: Annual | C2: CSI Annual Forms & Statements | D2: Other | E2: FALSE | F2: FALSE | G2: 170.33 | H2: per year | J2: =IF(B2="Monthly F",G2,IF(B2="Monthly V",G2*I2,IF(B2="Annual",G2/12,0))) | K2: =IF(B2="One-Time",G2,J2*12) | L2: =IF(B2="One-Time",0,K2*(1+Metadata!$B$8)) | M2: =IF(B2="One-Time",0,L2*(1+Metadata!$B$8)) | N2: =IF(B2="One-Time",0,M2*(1+Metadata!$B$8)) | O2: =IF(B2="One-Time",0,N2*(1+Metadata!$B$8)) | P2: =IF(B2="One-Time",0,O2*(1+Metadata!$B$8)) | Q2: =IF(B2="One-Time",0,P2*(1+Metadata!$B$8)) | R2: =SUM(K2:Q2) | S2: 0.95 | T2: Annual fee of $2,044 converted to monthly
A3: 5 | B3: Monthly F | C3: CSI Fees Included in Organic Growth Based Pricing | D3: Core | E3: FALSE | F3: FALSE | G3: 38663 | H3: per month | J3: =IF(B3="Monthly F",G3,IF(B3="Monthly V",G3*I3,IF(B3="Annual",G3/12,0))) | K3: =IF(B3="One-Time",G3,J3*12) | L3: =IF(B3="One-Time",0,K3*(1+Metadata!$B$8)) | M3: =IF(B3="One-Time",0,L3*(1+Metadata!$B$8)) | N3: =IF(B3="One-Time",0,M3*(1+Metadata!$B$8)) | O3: =IF(B3="One-Time",0,N3*(1+Metadata!$B$8)) | P3: =IF(B3="One-Time",0,O3*(1+Metadata!$B$8)) | Q3: =IF(B3="One-Time",0,P3*(1+Metadata!$B$8)) | R3: =SUM(K3:Q3) | S3: 0.95 | T3: Core processing fees
A4: 7 | B4: Monthly F | C4: Monthly Equipment Fees | D4: Item Processing | E4: FALSE | F4: FALSE | G4: 250 | H4: per month | J4: =IF(B4="Monthly F",G4,IF(B4="Monthly V",G4*I4,IF(B4="Annual",G4/12,0))) | K4: =IF(B4="One-Time",G4,J4*12) | L4: =IF(B4="One-Time",0,K4*(1+Metadata!$B$8)) | M4: =IF(B4="One-Time",0,L4*(1+Metadata!$B$8)) | N4: =IF(B4="One-Time",0,M4*(1+Metadata!$B$8)) | O4: =IF(B4="One-Time",0,N4*(1+Metadata!$B$8)) | P4: =IF(B4="One-Time",0,O4*(1+Metadata!$B$8)) | Q4: =IF(B4="One-Time",0,P4*(1+Metadata!$B$8)) | R4: =SUM(K4:Q4) | S4: 0.95 | T4: Monthly equipment rental/maintenance
A5: 6 | B5: Monthly F | C5: Other Processing Fees | D5: Other | E5: FALSE | F5: FALSE | G5: 12734 | H5: per month | J5: =IF(B5="Monthly F",G5,IF(B5="Monthly V",G5*I5,IF(B5="Annual",G5/12,0))) | K5: =IF(B5="One-Time",G5,J5*12) | L5: =IF(B5="One-Time",0,K5*(1+Metadata!$B$8)) | M5: =IF(B5="One-Time",0,L5*(1+Metadata!$B$8)) | N5: =IF(B5="One-Time",0,M5*(1+Metadata!$B$8)) | O5: =IF(B5="One-Time",0,N5*(1+Metadata!$B$8)) | P5: =IF(B5="One-Time",0,O5*(1+Metadata!$B$8)) | Q5: =IF(B5="One-Time",0,P5*(1+Metadata!$B$8)) | R5: =SUM(K5:Q5) | S5: 0.95 | T5: Additional processing fees
A6: 2 | B6: One-Time | C6: Equipment Fees - Implementation Fee | D6: Item Processing | E6: FALSE | F6: FALSE | G6: 76933 | H6: one-time | J6: =IF(B6="Monthly F",G6,IF(B6="Monthly V",G6*I6,IF(B6="Annual",G6/12,0))) | K6: =IF(B6="One-Time",G6,J6*12) | L6: =IF(B6="One-Time",0,K6*(1+Metadata!$B$8)) | M6: =IF(B6="One-Time",0,L6*(1+Metadata!$B$8)) | N6: =IF(B6="One-Time",0,M6*(1+Metadata!$B$8)) | O6: =IF(B6="One-Time",0,N6*(1+Metadata!$B$8)) | P6: =IF(B6="One-Time",0,O6*(1+Metadata!$B$8)) | Q6: =IF(B6="One-Time",0,P6*(1+Metadata!$B$8)) | R6: =SUM(K6:Q6) | S6: 0.95 | T6: Hardware and equipment costs
A7: 1 | B7: One-Time | C7: CSI One-Time Fee - Implementation Fee | D7: Other | E7: FALSE | F7: FALSE | G7: 261102 | H7: one-time | J7: =IF(B7="Monthly F",G7,IF(B7="Monthly V",G7*I7,IF(B7="Annual",G7/12,0))) | K7: =IF(B7="One-Time",G7,J7*12) | L7: =IF(B7="One-Time",0,K7*(1+Metadata!$B$8)) | M7: =IF(B7="One-Time",0,L7*(1+Metadata!$B$8)) | N7: =IF(B7="One-Time",0,M7*(1+Metadata!$B$8)) | O7: =IF(B7="One-Time",0,N7*(1+Metadata!$B$8)) | P7: =IF(B7="One-Time",0,O7*(1+Metadata!$B$8)) | Q7: =IF(B7="One-Time",0,P7*(1+Metadata!$B$8)) | R7: =SUM(K7:Q7) | S7: 0.95 | T7: Base implementation fee
A8: 3 | B8: One-Time | C8: Credit for One-Time Fees - Implementation Fee | D8: Other | E8: FALSE | F8: FALSE | G8: -338034 | H8: one-time | J8: =IF(B8="Monthly F",G8,IF(B8="Monthly V",G8*I8,IF(B8="Annual",G8/12,0))) | K8: =IF(B8="One-Time",G8,J8*12) | L8: =IF(B8="One-Time",0,K8*(1+Metadata!$B$8)) | M8: =IF(B8="One-Time",0,L8*(1+Metadata!$B$8)) | N8: =IF(B8="One-Time",0,M8*(1+Metadata!$B$8)) | O8: =IF(B8="One-Time",0,N8*(1+Metadata!$B$8)) | P8: =IF(B8="One-Time",0,O8*(1+Metadata!$B$8)) | Q8: =IF(B8="One-Time",0,P8*(1+Metadata!$B$8)) | R8: =SUM(K8:Q8) | S8: 0.95 | T8: Credit applied to implementation fees
A9: 4 | B9: One-Time | C9: Special Incentive Billing Credit - Implementation Fee | D9: Other | E9: FALSE | F9: FALSE | G9: -375000 | H9: one-time | J9: =IF(B9="Monthly F",G9,IF(B9="Monthly V",G9*I9,IF(B9="Annual",G9/12,0))) | K9: =IF(B9="One-Time",G9,J9*12) | L9: =IF(B9="One-Time",0,K9*(1+Metadata!$B$8)) | M9: =IF(B9="One-Time",0,L9*(1+Metadata!$B$8)) | N9: =IF(B9="One-Time",0,M9*(1+Metadata!$B$8)) | O9: =IF(B9="One-Time",0,N9*(1+Metadata!$B$8)) | P9: =IF(B9="One-Time",0,O9*(1+Metadata!$B$8)) | Q9: =IF(B9="One-Time",0,P9*(1+Metadata!$B$8)) | R9: =SUM(K9:Q9) | S9: 0.95 | T9: Special incentive credit
A10: 17 | B10: Monthly F | C10: PLUS Network Sponsorship | D10: EFT | E10: FALSE | F10: TRUE | G10: 50 | H10: per month | J10: =IF(B10="Monthly F",G10,IF(B10="Monthly V",G10*I10,IF(B10="Annual",G10/12,0))) | K10: =IF(B10="One-Time",G10,J10*12) | L10: =IF(B10="One-Time",0,K10*(1+Metadata!$B$8)) | M10: =IF(B10="One-Time",0,L10*(1+Metadata!$B$8)) | N10: =IF(B10="One-Time",0,M10*(1+Metadata!$B$8)) | O10: =IF(B10="One-Time",0,N10*(1+Metadata!$B$8)) | P10: =IF(B10="One-Time",0,O10*(1+Metadata!$B$8)) | Q10: =IF(B10="One-Time",0,P10*(1+Metadata!$B$8)) | R10: =SUM(K10:Q10) | S10: 0.9 | T10: Network sponsorship fee
A11: 36 | B11: Monthly F | C11: Call Report File Download (SmartCall) | D11: Other | E11: FALSE | F11: TRUE | G11: 100 | H11: per month | J11: =IF(B11="Monthly F",G11,IF(B11="Monthly V",G11*I11,IF(B11="Annual",G11/12,0))) | K11: =IF(B11="One-Time",G11,J11*12) | L11: =IF(B11="One-Time",0,K11*(1+Metadata!$B$8)) | M11: =IF(B11="One-Time",0,L11*(1+Metadata!$B$8)) | N11: =IF(B11="One-Time",0,M11*(1+Metadata!$B$8)) | O11: =IF(B11="One-Time",0,N11*(1+Metadata!$B$8)) | P11: =IF(B11="One-Time",0,O11*(1+Metadata!$B$8)) | Q11: =IF(B11="One-Time",0,P11*(1+Metadata!$B$8)) | R11: =SUM(K11:Q11) | S11: 0.9 | T11: Fixed monthly fee
A12: 40 | B12: Monthly F | C12: WatchDog CIP | D12: Risk, Fraud & Compliance | E12: FALSE | F12: TRUE | G12: 249.58 | H12: per month | J12: =IF(B12="Monthly F",G12,IF(B12="Monthly V",G12*I12,IF(B12="Annual",G12/12,0))) | K12: =IF(B12="One-Time",G12,J12*12) | L12: =IF(B12="One-Time",0,K12*(1+Metadata!$B$8)) | M12: =IF(B12="One-Time",0,L12*(1+Metadata!$B$8)) | N12: =IF(B12="One-Time",0,M12*(1+Metadata!$B$8)) | O12: =IF(B12="One-Time",0,N12*(1+Metadata!$B$8)) | P12: =IF(B12="One-Time",0,O12*(1+Metadata!$B$8)) | Q12: =IF(B12="One-Time",0,P12*(1+Metadata!$B$8)) | R12: =SUM(K12:Q12) | S12: 0.9 | T12: Annual license fee shown monthly
A13: 31 | B13: Monthly V | C13: Card Alerts | D13: Digital | E13: FALSE | F13: TRUE | G13: 778 | H13: per alert | I13: 1 | J13: =IF(B13="Monthly F",G13,IF(B13="Monthly V",G13*I13,IF(B13="Annual",G13/12,0))) | K13: =IF(B13="One-Time",G13,J13*12) | L13: =IF(B13="One-Time",0,K13*(1+Metadata!$B$8)) | M13: =IF(B13="One-Time",0,L13*(1+Metadata!$B$8)) | N13: =IF(B13="One-Time",0,M13*(1+Metadata!$B$8)) | O13: =IF(B13="One-Time",0,N13*(1+Metadata!$B$8)) | P13: =IF(B13="One-Time",0,O13*(1+Metadata!$B$8)) | Q13: =IF(B13="One-Time",0,P13*(1+Metadata!$B$8)) | R13: =SUM(K13:Q13) | S13: 0.85 | T13: 1,416 alerts at $0.55 per alert
A14: 35 | B14: Monthly V | C14: Digital Chat | D14: Digital | E14: FALSE | F14: TRUE | G14: 12 | H14: per chat | I14: 1 | J14: =IF(B14="Monthly F",G14,IF(B14="Monthly V",G14*I14,IF(B14="Annual",G14/12,0))) | K14: =IF(B14="One-Time",G14,J14*12) | L14: =IF(B14="One-Time",0,K14*(1+Metadata!$B$8)) | M14: =IF(B14="One-Time",0,L14*(1+Metadata!$B$8)) | N14: =IF(B14="One-Time",0,M14*(1+Metadata!$B$8)) | O14: =IF(B14="One-Time",0,N14*(1+Metadata!$B$8)) | P14: =IF(B14="One-Time",0,O14*(1+Metadata!$B$8)) | Q14: =IF(B14="One-Time",0,P14*(1+Metadata!$B$8)) | R14: =SUM(K14:Q14) | S14: 0.85 | T14: 121 chats at $0.10 per chat
A15: 32 | B15: Monthly V | C15: Digital Wallet - Push Provisioning | D15: Digital | E15: FALSE | F15: TRUE | G15: 120 | H15: per provisioning | I15: 1 | J15: =IF(B15="Monthly F",G15,IF(B15="Monthly V",G15*I15,IF(B15="Annual",G15/12,0))) | K15: =IF(B15="One-Time",G15,J15*12) | L15: =IF(B15="One-Time",0,K15*(1+Metadata!$B$8)) | M15: =IF(B15="One-Time",0,L15*(1+Metadata!$B$8)) | N15: =IF(B15="One-Time",0,M15*(1+Metadata!$B$8)) | O15: =IF(B15="One-Time",0,N15*(1+Metadata!$B$8)) | P15: =IF(B15="One-Time",0,O15*(1+Metadata!$B$8)) | Q15: =IF(B15="One-Time",0,P15*(1+Metadata!$B$8)) | R15: =SUM(K15:Q15) | S15: 0.85 | T15: 600 provisionings at $0.20 per provisioning
A16: 27 | B16: Monthly V | C16: Mobile Banking Push Notifications | D16: Digital | E16: FALSE | F16: TRUE | G16: 161 | H16: per notification | I16: 1 | J16: =IF(B16="Monthly F",G16,IF(B16="Monthly V",G16*I16,IF(B16="Annual",G16/12,0))) | K16: =IF(B16="One-Time",G16,J16*12) | L16: =IF(B16="One-Time",0,K16*(1+Metadata!$B$8)) | M16: =IF(B16="One-Time",0,L16*(1+Metadata!$B$8)) | N16: =IF(B16="One-Time",0,M16*(1+Metadata!$B$8)) | O16: =IF(B16="One-Time",0,N16*(1+Metadata!$B$8)) | P16: =IF(B16="One-Time",0,O16*(1+Metadata!$B$8)) | Q16: =IF(B16="One-Time",0,P16*(1+Metadata!$B$8)) | R16: =SUM(K16:Q16) | S16: 0.85 | T16: 3,223 notifications at $0.05 + $100 base fee
A17: 29 | B17: Monthly V | C17: Mobile Deposit | D17: Digital | E17: FALSE | F17: TRUE | G17: 525 | H17: per transaction | I17: 1 | J17: =IF(B17="Monthly F",G17,IF(B17="Monthly V",G17*I17,IF(B17="Annual",G17/12,0))) | K17: =IF(B17="One-Time",G17,J17*12) | L17: =IF(B17="One-Time",0,K17*(1+Metadata!$B$8)) | M17: =IF(B17="One-Time",0,L17*(1+Metadata!$B$8)) | N17: =IF(B17="One-Time",0,M17*(1+Metadata!$B$8)) | O17: =IF(B17="One-Time",0,N17*(1+Metadata!$B$8)) | P17: =IF(B17="One-Time",0,O17*(1+Metadata!$B$8)) | Q17: =IF(B17="One-Time",0,P17*(1+Metadata!$B$8)) | R17: =SUM(K17:Q17) | S17: 0.85 | T17: 500 transactions at $0.01 + $525 base fee
A18: 23 | B18: Monthly V | C18: Out of Band Authentication (OOBA) | D18: Digital | E18: FALSE | F18: TRUE | G18: 101 | H18: per authentication | I18: 1 | J18: =IF(B18="Monthly F",G18,IF(B18="Monthly V",G18*I18,IF(B18="Annual",G18/12,0))) | K18: =IF(B18="One-Time",G18,J18*12) | L18: =IF(B18="One-Time",0,K18*(1+Metadata!$B$8)) | M18: =IF(B18="One-Time",0,L18*(1+Metadata!$B$8)) | N18: =IF(B18="One-Time",0,M18*(1+Metadata!$B$8)) | O18: =IF(B18="One-Time",0,N18*(1+Metadata!$B$8)) | P18: =IF(B18="One-Time",0,O18*(1+Metadata!$B$8)) | Q18: =IF(B18="One-Time",0,P18*(1+Metadata!$B$8)) | R18: =SUM(K18:Q18) | S18: 0.85 | T18: 2,027 authentications at $0.05 + $300 base fee
A19: 25 | B19: Monthly V | C19: Text Messages | D19: Digital | E19: FALSE | F19: TRUE | G19: 107 | H19: per message | I19: 1 | J19: =IF(B19="Monthly F",G19,IF(B19="Monthly V",G19*I19,IF(B19="Annual",G19/12,0))) | K19: =IF(B19="One-Time",G19,J19*12) | L19: =IF(B19="One-Time",0,K19*(1+Metadata!$B$8)) | M19: =IF(B19="One-Time",0,L19*(1+Metadata!$B$8)) | N19: =IF(B19="One-Time",0,M19*(1+Metadata!$B$8)) | O19: =IF(B19="One-Time",0,N19*(1+Metadata!$B$8)) | P19: =IF(B19="One-Time",0,O19*(1+Metadata!$B$8)) | Q19: =IF(B19="One-Time",0,P19*(1+Metadata!$B$8)) | R19: =SUM(K19:Q19) | S19: 0.85 | T19: 10,730 messages at $0.01 per message
A20: 26 | B20: Monthly V | C20: Voice Authentication | D20: Digital | E20: FALSE | F20: TRUE | G20: 1 | H20: per call | I20: 1 | J20: =IF(B20="Monthly F",G20,IF(B20="Monthly V",G20*I20,IF(B20="Annual",G20/12,0))) | K20: =IF(B20="One-Time",G20,J20*12) | L20: =IF(B20="One-Time",0,K20*(1+Metadata!$B$8)) | M20: =IF(B20="One-Time",0,L20*(1+Metadata!$B$8)) | N20: =IF(B20="One-Time",0,M20*(1+Metadata!$B$8)) | O20: =IF(B20="One-Time",0,N20*(1+Metadata!$B$8)) | P20: =IF(B20="One-Time",0,O20*(1+Metadata!$B$8)) | Q20: =IF(B20="One-Time",0,P20*(1+Metadata!$B$8)) | R20: =SUM(K20:Q20) | S20: 0.85 | T20: 51 calls at $0.02 per call
A21: 13 | B21: Monthly V | C21: Card Production - Instant Issue | D21: EFT | E21: FALSE | F21: TRUE | G21: 81 | H21: per card | I21: 1 | J21: =IF(B21="Monthly F",G21,IF(B21="Monthly V",G21*I21,IF(B21="Annual",G21/12,0))) | K21: =IF(B21="One-Time",G21,J21*12) | L21: =IF(B21="One-Time",0,K21*(1+Metadata!$B$8)) | M21: =IF(B21="One-Time",0,L21*(1+Metadata!$B$8)) | N21: =IF(B21="One-Time",0,M21*(1+Metadata!$B$8)) | O21: =IF(B21="One-Time",0,N21*(1+Metadata!$B$8)) | P21: =IF(B21="One-Time",0,O21*(1+Metadata!$B$8)) | Q21: =IF(B21="One-Time",0,P21*(1+Metadata!$B$8)) | R21: =SUM(K21:Q21) | S21: 0.9 | T21: 108 cards at $0.75 per card
A22: 16 | B22: Monthly V | C22: Contactless EMV Card Production Fee | D22: EFT | E22: FALSE | F22: TRUE | G22: 68 | H22: per card | I22: 1 | J22: =IF(B22="Monthly F",G22,IF(B22="Monthly V",G22*I22,IF(B22="Annual",G22/12,0))) | K22: =IF(B22="One-Time",G22,J22*12) | L22: =IF(B22="One-Time",0,K22*(1+Metadata!$B$8)) | M22: =IF(B22="One-Time",0,L22*(1+Metadata!$B$8)) | N22: =IF(B22="One-Time",0,M22*(1+Metadata!$B$8)) | O22: =IF(B22="One-Time",0,N22*(1+Metadata!$B$8)) | P22: =IF(B22="One-Time",0,O22*(1+Metadata!$B$8)) | Q22: =IF(B22="One-Time",0,P22*(1+Metadata!$B$8)) | R22: =SUM(K22:Q22) | S22: 0.9 | T22: 22,710 cards at $0.00 per card
A23: 15 | B23: Monthly V | C23: EFT Processing Fees - Primary Network | D23: EFT | E23: FALSE | F23: TRUE | G23: 514 | H23: per transaction | I23: 1 | J23: =IF(B23="Monthly F",G23,IF(B23="Monthly V",G23*I23,IF(B23="Annual",G23/12,0))) | K23: =IF(B23="One-Time",G23,J23*12) | L23: =IF(B23="One-Time",0,K23*(1+Metadata!$B$8)) | M23: =IF(B23="One-Time",0,L23*(1+Metadata!$B$8)) | N23: =IF(B23="One-Time",0,M23*(1+Metadata!$B$8)) | O23: =IF(B23="One-Time",0,N23*(1+Metadata!$B$8)) | P23: =IF(B23="One-Time",0,O23*(1+Metadata!$B$8)) | Q23: =IF(B23="One-Time",0,P23*(1+Metadata!$B$8)) | R23: =SUM(K23:Q23) | S23: 0.9 | T23: 41,101 transactions at $0.01 per transaction
A24: 14 | B24: Monthly V | C24: EMV Card Production Fee | D24: EFT | E24: FALSE | F24: TRUE | G24: 73 | H24: per card | I24: 1 | J24: =IF(B24="Monthly F",G24,IF(B24="Monthly V",G24*I24,IF(B24="Annual",G24/12,0))) | K24: =IF(B24="One-Time",G24,J24*12) | L24: =IF(B24="One-Time",0,K24*(1+Metadata!$B$8)) | M24: =IF(B24="One-Time",0,L24*(1+Metadata!$B$8)) | N24: =IF(B24="One-Time",0,M24*(1+Metadata!$B$8)) | O24: =IF(B24="One-Time",0,N24*(1+Metadata!$B$8)) | P24: =IF(B24="One-Time",0,O24*(1+Metadata!$B$8)) | Q24: =IF(B24="One-Time",0,P24*(1+Metadata!$B$8)) | R24: =SUM(K24:Q24) | S24: 0.9 | T24: 3,672 cards at $0.02 per card
... A35: 42 | B35: Monthly V | C35: Out of Wallet Transactions | D35: Risk, Fraud & Compliance | E35: FALSE | F35: TRUE | G35: 98 | H35: per transaction | I35: 1 | J35: =IF(B35="Monthly F",G35,IF(B35="Monthly V",G35*I35,IF(B35="Annual",G35/12,0))) | K35: =IF(B35="One-Time",G35,J35*12) | L35: =IF(B35="One-Time",0,K35*(1+Metadata!$B$8)) | M35: =IF(B35="One-Time",0,L35*(1+Metadata!$B$8)) | N35: =IF(B35="One-Time",0,M35*(1+Metadata!$B$8)) | O35: =IF(B35="One-Time",0,N35*(1+Metadata!$B$8)) | P35: =IF(B35="One-Time",0,O35*(1+Metadata!$B$8)) | Q35: =IF(B35="One-Time",0,P35*(1+Metadata!$B$8)) | R35: =SUM(K35:Q35) | S35: 0.9 | T35: 39 transactions at $2.50 per transaction
A36: 28 | B36: One-Time | C36: Mobile Banking Push Notifications - Implementation Fee | D36: Digital | E36: FALSE | F36: TRUE | G36: 100 | H36: per notification | J36: =IF(B36="Monthly F",G36,IF(B36="Monthly V",G36*I36,IF(B36="Annual",G36/12,0))) | K36: =IF(B36="One-Time",G36,J36*12) | L36: =IF(B36="One-Time",0,K36*(1+Metadata!$B$8)) | M36: =IF(B36="One-Time",0,L36*(1+Metadata!$B$8)) | N36: =IF(B36="One-Time",0,M36*(1+Metadata!$B$8)) | O36: =IF(B36="One-Time",0,N36*(1+Metadata!$B$8)) | P36: =IF(B36="One-Time",0,O36*(1+Metadata!$B$8)) | Q36: =IF(B36="One-Time",0,P36*(1+Metadata!$B$8)) | R36: =SUM(K36:Q36) | S36: 0.85 | T36: 3,223 notifications at $0.05 + $100 base fee
A37: 30 | B37: One-Time | C37: Mobile Deposit - Implementation Fee | D37: Digital | E37: FALSE | F37: TRUE | G37: 525 | H37: per transaction | J37: =IF(B37="Monthly F",G37,IF(B37="Monthly V",G37*I37,IF(B37="Annual",G37/12,0))) | K37: =IF(B37="One-Time",G37,J37*12) | L37: =IF(B37="One-Time",0,K37*(1+Metadata!$B$8)) | M37: =IF(B37="One-Time",0,L37*(1+Metadata!$B$8)) | N37: =IF(B37="One-Time",0,M37*(1+Metadata!$B$8)) | O37: =IF(B37="One-Time",0,N37*(1+Metadata!$B$8)) | P37: =IF(B37="One-Time",0,O37*(1+Metadata!$B$8)) | Q37: =IF(B37="One-Time",0,P37*(1+Metadata!$B$8)) | R37: =SUM(K37:Q37) | S37: 0.85 | T37: 500 transactions at $0.01 + $525 base fee
A38: 24 | B38: One-Time | C38: Out of Band Authentication (OOBA) - Implementation Fee | D38: Digital | E38: FALSE | F38: TRUE | G38: 300 | H38: per authentication | J38: =IF(B38="Monthly F",G38,IF(B38="Monthly V",G38*I38,IF(B38="Annual",G38/12,0))) | K38: =IF(B38="One-Time",G38,J38*12) | L38: =IF(B38="One-Time",0,K38*(1+Metadata!$B$8)) | M38: =IF(B38="One-Time",0,L38*(1+Metadata!$B$8)) | N38: =IF(B38="One-Time",0,M38*(1+Metadata!$B$8)) | O38: =IF(B38="One-Time",0,N38*(1+Metadata!$B$8)) | P38: =IF(B38="One-Time",0,O38*(1+Metadata!$B$8)) | Q38: =IF(B38="One-Time",0,P38*(1+Metadata!$B$8)) | R38: =SUM(K38:Q38) | S38: 0.85 | T38: 2,027 authentications at $0.05 + $300 base fee
A39: 34 | B39: One-Time | C39: 800 Number - Implementation Fee | D39: Other | E39: FALSE | F39: TRUE | G39: 100 | H39: per call | J39: =IF(B39="Monthly F",G39,IF(B39="Monthly V",G39*I39,IF(B39="Annual",G39/12,0))) | K39: =IF(B39="One-Time",G39,J39*12) | L39: =IF(B39="One-Time",0,K39*(1+Metadata!$B$8)) | M39: =IF(B39="One-Time",0,L39*(1+Metadata!$B$8)) | N39: =IF(B39="One-Time",0,M39*(1+Metadata!$B$8)) | O39: =IF(B39="One-Time",0,N39*(1+Metadata!$B$8)) | P39: =IF(B39="One-Time",0,O39*(1+Metadata!$B$8)) | Q39: =IF(B39="One-Time",0,P39*(1+Metadata!$B$8)) | R39: =SUM(K39:Q39) | S39: 0.85 | T39: 20 calls at $1.00 + $100 base fee
A40: 22 | B40: Monthly F | C40: Quicken & QuickBooks | D40: Digital | E40: TRUE | F40: TRUE | G40: 736.67 | H40: per month | J40: =IF(B40="Monthly F",G40,IF(B40="Monthly V",G40*I40,IF(B40="Annual",G40/12,0))) | K40: =IF(B40="One-Time",G40,J40*12) | L40: =IF(B40="One-Time",0,K40*(1+Metadata!$B$8)) | M40: =IF(B40="One-Time",0,L40*(1+Metadata!$B$8)) | N40: =IF(B40="One-Time",0,M40*(1+Metadata!$B$8)) | O40: =IF(B40="One-Time",0,N40*(1+Metadata!$B$8)) | P40: =IF(B40="One-Time",0,O40*(1+Metadata!$B$8)) | Q40: =IF(B40="One-Time",0,P40*(1+Metadata!$B$8)) | R40: =SUM(K40:Q40) | S40: 0.85 | T40: Fixed monthly fee for integration
A41: 20 | B41: Monthly V | C41: Integrated (PFM) | D41: Digital | E41: TRUE | F41: TRUE | G41: 353 | H41: per user | I41: 1 | J41: =IF(B41="Monthly F",G41,IF(B41="Monthly V",G41*I41,IF(B41="Annual",G41/12,0))) | K41: =IF(B41="One-Time",G41,J41*12) | L41: =IF(B41="One-Time",0,K41*(1+Metadata!$B$8)) | M41: =IF(B41="One-Time",0,L41*(1+Metadata!$B$8)) | N41: =IF(B41="One-Time",0,M41*(1+Metadata!$B$8)) | O41: =IF(B41="One-Time",0,N41*(1+Metadata!$B$8)) | P41: =IF(B41="One-Time",0,O41*(1+Metadata!$B$8)) | Q41: =IF(B41="One-Time",0,P41*(1+Metadata!$B$8)) | R41: =SUM(K41:Q41) | S41: 0.85 | T41: 470 users at $0.75 per user
A42: 21 | B42: Monthly V | C42: Integrated (PFM) + Aggregation | D42: Digital | E42: TRUE | F42: TRUE | G42: 94 | H42: per user | I42: 1 | J42: =IF(B42="Monthly F",G42,IF(B42="Monthly V",G42*I42,IF(B42="Annual",G42/12,0))) | K42: =IF(B42="One-Time",G42,J42*12) | L42: =IF(B42="One-Time",0,K42*(1+Metadata!$B$8)) | M42: =IF(B42="One-Time",0,L42*(1+Metadata!$B$8)) | N42: =IF(B42="One-Time",0,M42*(1+Metadata!$B$8)) | O42: =IF(B42="One-Time",0,N42*(1+Metadata!$B$8)) | P42: =IF(B42="One-Time",0,O42*(1+Metadata!$B$8)) | Q42: =IF(B42="One-Time",0,P42*(1+Metadata!$B$8)) | R42: =SUM(K42:Q42) | S42: 0.85 | T42: 94 users at $1.00 per user
A43: 19 | B43: Monthly V | C43: iPay Business Bill Pay Program | D43: Digital | E43: TRUE | F43: TRUE | G43: 737 | H43: per user + $0.45 per payment | I43: 1 | J43: =IF(B43="Monthly F",G43,IF(B43="Monthly V",G43*I43,IF(B43="Annual",G43/12,0))) | K43: =IF(B43="One-Time",G43,J43*12) | L43: =IF(B43="One-Time",0,K43*(1+Metadata!$B$8)) | M43: =IF(B43="One-Time",0,L43*(1+Metadata!$B$8)) | N43: =IF(B43="One-Time",0,M43*(1+Metadata!$B$8)) | O43: =IF(B43="One-Time",0,N43*(1+Metadata!$B$8)) | P43: =IF(B43="One-Time",0,O43*(1+Metadata!$B$8)) | Q43: =IF(B43="One-Time",0,P43*(1+Metadata!$B$8)) | R43: =SUM(K43:Q43) | S43: 0.85 | T43: 102 users at $5.95/user + 290 payments at $0.45/payment
A44: 18 | B44: Monthly V | C44: iPay Online Bill Pay | D44: Digital | E44: TRUE | F44: TRUE | G44: 1328 | H44: per user | I44: 1 | J44: =IF(B44="Monthly F",G44,IF(B44="Monthly V",G44*I44,IF(B44="Annual",G44/12,0))) | K44: =IF(B44="One-Time",G44,J44*12) | L44: =IF(B44="One-Time",0,K44*(1+Metadata!$B$8)) | M44: =IF(B44="One-Time",0,L44*(1+Metadata!$B$8)) | N44: =IF(B44="One-Time",0,M44*(1+Metadata!$B$8)) | O44: =IF(B44="One-Time",0,N44*(1+Metadata!$B$8)) | P44: =IF(B44="One-Time",0,O44*(1+Metadata!$B$8)) | Q44: =IF(B44="One-Time",0,P44*(1+Metadata!$B$8)) | R44: =SUM(K44:Q44) | S44: 0.85 | T44: 1,398 users at $0.95 per user

Sheet Years 1-7
A1: Annual Cost Breakdown (7-Year Projection)
A2: Category | B2: Year 1 | C2: Year 2 | D2: Year 3 | E2: Year 4 | F2: Year 5 | G2: Year 6 | H2: Year 7
A3: Required Annual Fees | B3: =SUMIFS('Line Items'!$K:$K,'Line Items'!$F:$F,FALSE) | C3: =SUMIFS('Line Items'!$L:$L,'Line Items'!$F:$F,FALSE) | D3: =SUMIFS('Line Items'!$M:$M,'Line Items'!$F:$F,FALSE) | E3: =SUMIFS('Line Items'!$N:$N,'Line Items'!$F:$F,FALSE) | F3: =SUMIFS('Line Items'!$O:$O,'Line Items'!$F:$F,FALSE) | G3: =SUMIFS('Line Items'!$P:$P,'Line Items'!$F:$F,FALSE) | H3: =SUMIFS('Line Items'!$Q:$Q,'Line Items'!$F:$F,FALSE)
A4: Optional Annual Fees | B4: =SUMIFS('Line Items'!$K:$K,'Line Items'!$F:$F,TRUE) | C4: =SUMIFS('Line Items'!$L:$L,'Line Items'!$F:$F,TRUE) | D4: =SUMIFS('Line Items'!$M:$M,'Line Items'!$F:$F,TRUE) | E4: =SUMIFS('Line Items'!$N:$N,'Line Items'!$F:$F,TRUE) | F4: =SUMIFS('Line Items'!$O:$O,'Line Items'!$F:$F,TRUE) | G4: =SUMIFS('Line Items'!$P:$P,'Line Items'!$F:$F,TRUE) | H4: =SUMIFS('Line Items'!$Q:$Q,'Line Items'!$F:$F,TRUE)
A5: Total Annual Cost | B5: =B3+B4 | C5: =C3+C4 | D5: =D3+D4 | E5: =E3+E4 | F5: =F3+F4 | G5: =G3+G4 | H5: =H3+H4

Sheet Summary
A1: Total Cost of Ownership (TCO) Summary
A2: Vendor: | B2: =Metadata!B2
A4: Category | B4: 7-Year Total | C4: Monthly Average
A5: Core | B5: =SUMIFS('Line Items'!$R:$R,'Line Items'!$D:$D,A5) | C5: =B5/84
A6: Digital | B6: =SUMIFS('Line Items'!$R:$R,'Line Items'!$D:$D,A6) | C6: =B6/84
A7: EFT | B7: =SUMIFS('Line Items'!$R:$R,'Line Items'!$D:$D,A7) | C7: =B7/84
A8: Image Solutions | B8: =SUMIFS('Line Items'!$R:$R,'Line Items'!$D:$D,A8) | C8: =B8/84
A9: Item Processing | B9: =SUMIFS('Line Items'!$R:$R,'Line Items'!$D:$D,A9) | C9: =B9/84
A10: Other | B10: =SUMIFS('Line Items'!$R:$R,'Line Items'!$D:$D,A10) | C10: =B10/84
A11: Risk, Fraud & Compliance | B11: =SUMIFS('Line Items'!$R:$R,'Line Items'!$D:$D,A11) | C11: =B11/84
A12: Optional Solutions
A13: Total Required TCO | B13: =SUM(B5:B11) | C13: =B13/84
A14: Grand Total (Required + Optional)
A15: Optional Items Total | B15: =SUMIFS('Line Items'!$R:$R,'Line Items'!$F:$F,TRUE) | C15: =B15/84

Sheet Metadata
A1: TCO Analysis - Proposal Metadata
A2: Primary Vendor: | B2: LIBERTY_CAPITAL_BANK_CSI
A3: Client Name: | B3: Liberty Capital & Texas Heritage (COMBINED)
A4: Proposal Type: | B4: CSI Pricing Proposal (Organic Growth 7-yr)
A5: Proposal Date: | B5: 2024-12-16
A6: Contract Term (Years): | B6: 7
A7: Annual Growth Rate: | B7: 0.02
A8: Annual CPI Rate: | B8: 0.02
A10: Data Extraction Date: | B10: 2025-12-14 15:03:03
A12: Source Proposal File: | B12: N/A
