Workbook
Name HighlightActiveRow: 23

Sheet (INTERNAL) Basic Entry 
B2: INTERNAL USE ONLY
B4: Arriba Advisors Data Entry Required in Blue Fields
E6: Additional Boxes for Custom Cell Linking:
B7: Client's Name | C7: First State Bank of Waynesboro | E7: Current Contract Effective Date
B9: Project Type (ex: Digital, CORE, etc.) | C9: CORE & DIGITAL | E9: (Custom Entry)
B11: Current Contract End Date | E11: Early Term Savings (# of Months)
B13: What is our baseline?
A14: A) | B14: Baseline from Current Invoices
B17: Incumbent Vendor's Name | C17: Current (FIS Bankway)
B19: Prospective Vendor #1's Name | C19: FIS Horizon with D1 Flex | E19: Vendor #1 Proposal Date or Round | F19: Proposal Dated 12/13/2023
B21: Prospective Vendor #2's Name | C21: FIS Horizon WITHOUT D1 Flex | E21: Vendor #2 Proposal Date or Round | F21: Proposal Dated 12/13/2023
B23: Prospective Vendor #3's Name | C23: Vendor #3 | E23: Vendor #3 Proposal Date or Round | F23: Month Year

Sheet CORE Recurring Items
C3: CORE: Monthly & Annual Fees | H3: QTY YOY Growth % | J3: CPI Rates
C4: ='(INTERNAL) Basic Entry '!$C$7 -> First State Bank of Waynesboro | J4: Current | K4: Vendor #1 Proposed | L4: Vendor #2 Proposed | M4: Vendor #3 Proposed | N4: ='(INTERNAL) Basic Entry '!$C$17 -> Current (FIS Bankway) | X4: ='(INTERNAL) Basic Entry '!$C$19 -> FIS Horizon with D1 Flex | AI4: ='(INTERNAL) Basic Entry '!C21 -> FIS Horizon WITHOUT D1 Flex | AT4: ='(INTERNAL) Basic Entry '!C23 -> Vendor #3
C5: ='(INTERNAL) Basic Entry '!$C$9&" Pricing Analysis" -> CORE & DIGITAL Pricing Analysis | H5: 0.05 | J5: 0.0467 | K5: 0.0467 | L5: 0.0467 | M5: 0 | N5: ='(INTERNAL) Basic Entry '!$B$14 -> Baseline from Current Invoices | X5: ='(INTERNAL) Basic Entry '!F19 -> Proposal Dated 12/13/2023 | AI5: ='(INTERNAL) Basic Entry '!F21 -> Proposal Dated 12/13/2023 | AT5: ='(INTERNAL) Basic Entry '!F23 -> Month Year
B6: Billing Category | C6: MONTHLY PROCESSING ITEMS | D6: Invoice #1 (Sep/2023) | E6: Invoice #2 (Aug/2023) | F6: Invoice #3 (Jul/2023) | G6: Invoice #4 (Jun/2023) | H6: Average Monthly QTY | I6: Year 1 Quantity | J6: Year 2 Quantity | K6: Year 3 Quantity | L6: Year 4 Quantity | M6: Year 5 Quantity | N6: Item Name | O6: Per Unit Rate | Q6: Year 1 Cost | R6: Year 2 Cost | S6: Year 3 Cost | T6: Year 4 Cost | U6: Year 5 Cost | V6: Total Term Cost | W6: Line Item Note | X6: Product Name | Y6: Per Unit Rate | AA6: Year 1 Cost (7/31/2025) | AB6: Year 2 Cost | AC6: Year 3 Cost | AD6: Year 4 Cost | AE6: Year 5 Cost (7/31/2030) | AF6: Term Total Cost | AG6: P/S Fee (if any) | AH6: Line Item Note | AI6: Product Name | AJ6: Per Unit Rate | AK6: Year 1 by Month | AL6: Year 1 Cost | AM6: Year 2 Cost | AN6: Year 3 Cost | AO6: Year 4 Cost | AP6: Year 5 Cost | AQ6: Term Total Cost | AR6: P/S Fee (if any) | AS6: Line Item Note | AT6: Product Name | AU6: Per Unit Rate | AV6: Year 1 Cost | AW6: Year 2 Cost | AX6: Year 3 Cost | AY6: Year 4 Cost | AZ6: Year 5 Cost | BA6: Term Total Cost | BB6: Line Item Note
B8: =C8 -> Core Banking Service: | C8: Core Banking Service: | N8: =C8 -> Core Banking Service: | X8: =C8 -> Core Banking Service: | AI8: =C8 -> Core Banking Service: | AT8: =C8 -> Core Banking Service:
C9: Bankway Core Banking System (Enterprise License) | D9: 1 | E9: 1 | F9: 1 | G9: 1 | H9: =IFERROR(AVERAGE(D9:G9),0) -> 1 | I9: =H9*12 -> 12 | J9: =((I9)*$H$5)+I9 -> 12.6 | K9: =((J9)*$H$5)+J9 -> 13.23 | L9: =((K9)*$H$5)+K9 -> 13.8915 | M9: =((L9)*$H$5)+L9 -> 14.586075 | N9: =IF(C9="","",C9) -> Bankway Core Banking System (Enterprise License) | O9: 25697.928 | P9: =Q9/12 -> 25697.928 | Q9: =IF(O9>0,PRODUCT(I9,$O9),0) -> 308375.14 | R9: =IF(Q9>0,PRODUCT(J9,$O9),0) -> 323793.9 | S9: =IF(R9>0,PRODUCT(K9,$O9),0) -> 339983.59 | T9: =IF(S9>0,PRODUCT(L9,$O9),0) -> 356982.77 | U9: =IF(T9>0,PRODUCT(M9,$O9),0) -> 374831.91 | V9: =SUM(Q9:U9) -> 1703967.3 | W9: Cost Based on Asset Size increasing 5% Annually | Z9: =AA9/12 -> 0 | AA9: =IF(Y9>0,PRODUCT(I9,$Y9),0) -> 0 | AB9: =IF(AA9>0,PRODUCT(J9,$Y9),0) -> 0 | AC9: =IF(AB9>0,PRODUCT(K9,$Y9),0) -> 0 | AD9: =IF(AC9>0,PRODUCT(L9,$Y9),0) -> 0 | AE9: =IF(AD9>0,PRODUCT(M9,$Y9),0) -> 0 | AF9: =SUM(AA9:AE9) -> 0 | AK9: =AL9/12 -> 0 | AL9: {=_xlfn.IFS(AJ9="NO CHARGE",0,AJ9=0,0,AJ9>0,PRODUCT(I9,$AJ9))} -> 0 | AM9: {=_xlfn.IFS(AK9="NO CHARGE",0,AK9=0,0,AK9>0,PRODUCT(J9,$AJ9))} -> 0 | AN9: {=_xlfn.IFS(AL9="NO CHARGE",0,AL9=0,0,AL9>0,PRODUCT(K9,$AJ9))} -> 0 | AO9: {=_xlfn.IFS(AM9="NO CHARGE",0,AM9=0,0,AM9>0,PRODUCT(L9,$AJ9))} -> 0 | AP9: {=_xlfn.IFS(AN9="NO CHARGE",0,AN9=0,0,AN9>0,PRODUCT(M9,$AJ9))} -> 0 | AQ9: =SUM(AL9:AP9) -> 0 | AV9: =IF(AU9>0,PRODUCT(I9,$AU9),0) -> 0 | AW9: =IF(AV9>0,PRODUCT(J9,$AU9),0) -> 0 | AX9: =IF(AW9>0,PRODUCT(K9,$AU9),0) -> 0 | AY9: =IF(AX9>0,PRODUCT(L9,$AU9),0) -> 0 | AZ9: =IF(AY9>0,PRODUCT(M9,$AU9),0) -> 0 | BA9: =SUM(AV9:AZ9) -> 0
C10: Bankway Core Banking System New Account Desk | D10: 1 | E10: 1 | F10: 1 | G10: 1 | H10: =IFERROR(AVERAGE(D10:G10),0) -> 1 | I10: =H10*12 -> 12 | J10: =IF(I10>12,(((I10)*$H$5)+I10),(I10*1)) -> 12 | K10: =IF(J10>12,(((J10)*$H$5)+J10),(J10*1)) -> 12 | L10: =IF(K10>12,(((K10)*$H$5)+K10),(K10*1)) -> 12 | M10: =IF(L10>12,(((L10)*$H$5)+L10),(L10*1)) -> 12 | N10: =IF(C10="","",C10) -> Bankway Core Banking System New Account Desk | O10: 817.53583 | P10: =Q10/12 -> 817.53583 | Q10: =IF(O10>0,PRODUCT(I10,$O10),0) -> 9810.43 | R10: =IF(Q10>0,PRODUCT(J10,$O10),0) -> 9810.43 | S10: =IF(R10>0,PRODUCT(K10,$O10),0) -> 9810.43 | T10: =IF(S10>0,PRODUCT(L10,$O10),0) -> 9810.43 | U10: =IF(T10>0,PRODUCT(M10,$O10),0) -> 9810.43 | V10: =SUM(Q10:U10) -> 49052.15 | Z10: =AA10/12 -> 0 | AA10: =IF(Y10>0,PRODUCT(I10,$Y10),0) -> 0 | AB10: =IF(AA10>0,PRODUCT(J10,$Y10),0) -> 0 | AC10: =IF(AB10>0,PRODUCT(K10,$Y10),0) -> 0 | AD10: =IF(AC10>0,PRODUCT(L10,$Y10),0) -> 0 | AE10: =IF(AD10>0,PRODUCT(M10,$Y10),0) -> 0 | AF10: =SUM(AA10:AE10) -> 0 | AK10: =AL10/12 -> 0 | AL10: {=_xlfn.IFS(AJ10="NO CHARGE",0,AJ10=0,0,AJ10>0,PRODUCT(I10,$AJ10))} -> 0 | AM10: {=_xlfn.IFS(AK10="NO CHARGE",0,AK10=0,0,AK10>0,PRODUCT(J10,$AJ10))} -> 0 | AN10: {=_xlfn.IFS(AL10="NO CHARGE",0,AL10=0,0,AL10>0,PRODUCT(K10,$AJ10))} -> 0 | AO10: {=_xlfn.IFS(AM10="NO CHARGE",0,AM10=0,0,AM10>0,PRODUCT(L10,$AJ10))} -> 0 | AP10: {=_xlfn.IFS(AN10="NO CHARGE",0,AN10=0,0,AN10>0,PRODUCT(M10,$AJ10))} -> 0 | AQ10: =SUM(AL10:AP10) -> 0 | AV10: =IF(AU10>0,PRODUCT(I10,$AU10),0) -> 0 | AW10: =IF(AV10>0,PRODUCT(J10,$AU10),0) -> 0 | AX10: =IF(AW10>0,PRODUCT(K10,$AU10),0) -> 0 | AY10: =IF(AX10>0,PRODUCT(L10,$AU10),0) -> 0 | AZ10: =IF(AY10>0,PRODUCT(M10,$AU10),0) -> 0 | BA10: =SUM(AV10:AZ10) -> 0
C11: EFT Card Management | D11: 1 | E11: 1 | F11: 1 | G11: 1 | H11: =IFERROR(AVERAGE(D11:G11),0) -> 1 | I11: =H11*12 -> 12 | J11: =IF(I11>12,(((I11)*$H$5)+I11),(I11*1)) -> 12 | K11: =IF(J11>12,(((J11)*$H$5)+J11),(J11*1)) -> 12 | L11: =IF(K11>12,(((K11)*$H$5)+K11),(K11*1)) -> 12 | M11: =IF(L11>12,(((L11)*$H$5)+L11),(L11*1)) -> 12 | N11: =IF(C11="","",C11) -> EFT Card Management | O11: 1502.9425 | P11: =Q11/12 -> 1502.9425 | Q11: =IF(O11>0,PRODUCT(I11,$O11),0) -> 18035.31 | R11: =IF(Q11>0,PRODUCT(J11,$O11),0) -> 18035.31 | S11: =IF(R11>0,PRODUCT(K11,$O11),0) -> 18035.31 | T11: =IF(S11>0,PRODUCT(L11,$O11),0) -> 18035.31 | U11: =IF(T11>0,PRODUCT(M11,$O11),0) -> 18035.31 | V11: =SUM(Q11:U11) -> 90176.55 | Z11: =AA11/12 -> 0 | AA11: =IF(Y11>0,PRODUCT(I11,$Y11),0) -> 0 | AB11: =IF(AA11>0,PRODUCT(J11,$Y11),0) -> 0 | AC11: =IF(AB11>0,PRODUCT(K11,$Y11),0) -> 0 | AD11: =IF(AC11>0,PRODUCT(L11,$Y11),0) -> 0 | AE11: =IF(AD11>0,PRODUCT(M11,$Y11),0) -> 0 | AF11: =SUM(AA11:AE11) -> 0 | AK11: =AL11/12 -> 0 | AL11: {=_xlfn.IFS(AJ11="NO CHARGE",0,AJ11=0,0,AJ11>0,PRODUCT(I11,$AJ11))} -> 0 | AM11: {=_xlfn.IFS(AK11="NO CHARGE",0,AK11=0,0,AK11>0,PRODUCT(J11,$AJ11))} -> 0 | AN11: {=_xlfn.IFS(AL11="NO CHARGE",0,AL11=0,0,AL11>0,PRODUCT(K11,$AJ11))} -> 0 | AO11: {=_xlfn.IFS(AM11="NO CHARGE",0,AM11=0,0,AM11>0,PRODUCT(L11,$AJ11))} -> 0 | AP11: {=_xlfn.IFS(AN11="NO CHARGE",0,AN11=0,0,AN11>0,PRODUCT(M11,$AJ11))} -> 0 | AQ11: =SUM(AL11:AP11) -> 0 | AV11: =IF(AU11>0,PRODUCT(I11,$AU11),0) -> 0 | AW11: =IF(AV11>0,PRODUCT(J11,$AU11),0) -> 0 | AX11: =IF(AW11>0,PRODUCT(K11,$AU11),0) -> 0 | AY11: =IF(AX11>0,PRODUCT(L11,$AU11),0) -> 0 | AZ11: =IF(AY11>0,PRODUCT(M11,$AU11),0) -> 0 | BA11: =SUM(AV11:AZ11) -> 0
B12: Horizon Core Account Processing | C12: =B12&" [QTY CALCULATIONS YOY]" -> Horizon Core Account Processing [QTY CALCULATIONS YOY] | H12: 54437 | I12: =H12*12 -> 653244 | J12: =IF(I12>12,(((I12)*$H$5)+I12),(I12*1)) -> 685906.2 | K12: =IF(J12>12,(((J12)*$H$5)+J12),(J12*1)) -> 720201.51 | L12: =IF(K12>12,(((K12)*$H$5)+K12),(K12*1)) -> 756211.59 | M12: =IF(L12>12,(((L12)*$H$5)+L12),(L12*1)) -> 794022.16 | P12: =Q12/12 -> 0 | Q12: =IF(O12>0,PRODUCT(I12,$O12),0) -> 0 | R12: =IF(Q12>0,PRODUCT(J12,$O12),0) -> 0 | S12: =IF(R12>0,PRODUCT(K12,$O12),0) -> 0 | T12: =IF(S12>0,PRODUCT(L12,$O12),0) -> 0 | U12: =IF(T12>0,PRODUCT(M12,$O12),0) -> 0 | V12: =SUM(Q12:U12) -> 0 | X12: =B12&" [TIERED]" -> Horizon Core Account Processing [TIERED] | Z12: =AA12/12 -> 0 | AA12: =IF(Y12>0,PRODUCT(I12,$Y12),0) -> 0 | AB12: =IF(AA12>0,PRODUCT(J12,$Y12),0) -> 0 | AC12: =IF(AB12>0,PRODUCT(K12,$Y12),0) -> 0 | AD12: =IF(AC12>0,PRODUCT(L12,$Y12),0) -> 0 | AE12: =IF(AD12>0,PRODUCT(M12,$Y12),0) -> 0 | AF12: =SUM(AA12:AE12) -> 0 | AI12: =X12 -> Horizon Core Account Processing [TIERED] | AK12: =AL12/12 -> 0 | AL12: {=_xlfn.IFS(AJ12="NO CHARGE",0,AJ12=0,0,AJ12>0,PRODUCT(I12,$AJ12))} -> 0 | AM12: {=_xlfn.IFS(AK12="NO CHARGE",0,AK12=0,0,AK12>0,PRODUCT(J12,$AJ12))} -> 0 | AN12: {=_xlfn.IFS(AL12="NO CHARGE",0,AL12=0,0,AL12>0,PRODUCT(K12,$AJ12))} -> 0 | AO12: {=_xlfn.IFS(AM12="NO CHARGE",0,AM12=0,0,AM12>0,PRODUCT(L12,$AJ12))} -> 0 | AP12: {=_xlfn.IFS(AN12="NO CHARGE",0,AN12=0,0,AN12>0,PRODUCT(M12,$AJ12))} -> 0 | AQ12: =SUM(AL12:AP12) -> 0 | AV12: =IF(AU12>0,PRODUCT(I12,$AU12),0) -> 0 | AW12: =IF(AV12>0,PRODUCT(J12,$AU12),0) -> 0 | AX12: =IF(AW12>0,PRODUCT(K12,$AU12),0) -> 0 | AY12: =IF(AX12>0,PRODUCT(L12,$AU12),0) -> 0 | AZ12: =IF(AY12>0,PRODUCT(M12,$AU12),0) -> 0 | BA12: =SUM(AV12:AZ12) -> 0
B13: Horizon Core Account Processing | C13: [Tiered] Base Monthly Processing 0 - 54,437 Accounts | H13: 54437 | I13: =IF(I12>($H13*12),$H13*12,I12) -> 653244 | J13: =IF(J12>($H13*12),$H13*12,J12) -> 653244 | K13: =IF(K12>($H13*12),$H13*12,K12) -> 653244 | L13: =IF(L12>($H13*12),$H13*12,L12) -> 653244 | M13: =IF(M12>($H13*12),$H13*12,M12) -> 653244 | P13: =Q13/12 -> 0 | Q13: =IF(O13>0,PRODUCT(I13,$O13),0) -> 0 | R13: =IF(Q13>0,PRODUCT(J13,$O13),0) -> 0 | S13: =IF(R13>0,PRODUCT(K13,$O13),0) -> 0 | T13: =IF(S13>0,PRODUCT(L13,$O13),0) -> 0 | U13: =IF(T13>0,PRODUCT(M13,$O13),0) -> 0 | V13: =SUM(Q13:U13) -> 0 | X13: =C13 -> [Tiered] Base Monthly Processing 0 - 54,437 Accounts | Y13: =28853.62/54437 -> 0.53003692 | Z13: =AA13/12 -> 28853.62 | AA13: =IF(Y13>0,PRODUCT(I13,$Y13),0) -> 346243.44 | AB13: =IF(AA13>0,PRODUCT(J13,$Y13),0) -> 346243.44 | AC13: =IF(AB13>0,PRODUCT(K13,$Y13),0) -> 346243.44 | AD13: =IF(AC13>0,PRODUCT(L13,$Y13),0) -> 346243.44 | AE13: =IF(AD13>0,PRODUCT(M13,$Y13),0) -> 346243.44 | AF13: =SUM(AA13:AE13) -> 1731217.2 | AG13: WAIVED | AH13: FIS PROPOSAL MISSING PER UNIT RATE | AI13: =C13 -> [Tiered] Base Monthly Processing 0 - 54,437 Accounts | AJ13: =28853.62/54437 -> 0.53003692 | AK13: =AL13/12 -> 28853.62 | AL13: {=_xlfn.IFS($AJ13="NO CHARGE",0,$AJ13=0,0,$AJ13>0,PRODUCT(I13,$AJ13))} -> 346243.44 | AM13: {=_xlfn.IFS($AJ13="NO CHARGE",0,$AJ13=0,0,$AJ13>0,PRODUCT(J13,$AJ13))} -> 346243.44 | AN13: {=_xlfn.IFS($AJ13="NO CHARGE",0,$AJ13=0,0,$AJ13>0,PRODUCT(K13,$AJ13))} -> 346243.44 | AO13: {=_xlfn.IFS($AJ13="NO CHARGE",0,$AJ13=0,0,$AJ13>0,PRODUCT(L13,$AJ13))} -> 346243.44 | AP13: {=_xlfn.IFS($AJ13="NO CHARGE",0,$AJ13=0,0,$AJ13>0,PRODUCT(M13,$AJ13))} -> 346243.44 | AQ13: =SUM(AL13:AP13) -> 1731217.2 | AR13: Waived | AS13: FIS PROPOSAL MISSING PER UNIT RATE | AV13: =IF(AU13>0,PRODUCT(I13,$AU13),0) -> 0 | AW13: =IF(AV13>0,PRODUCT(J13,$AU13),0) -> 0 | AX13: =IF(AW13>0,PRODUCT(K13,$AU13),0) -> 0 | AY13: =IF(AX13>0,PRODUCT(L13,$AU13),0) -> 0 | AZ13: =IF(AY13>0,PRODUCT(M13,$AU13),0) -> 0 | BA13: =SUM(AV13:AZ13) -> 0
B14: Horizon Core Account Processing | C14: [Tiered] Base Monthly Processing 54,438 - 100k Accounts | H14: =100000-54438 -> 45562 | I14: {=_xlfn.IFS(I12>(($H13*12)+($H14*12)),$H14*12, I12<(($H13*12)+($H14*12)),I12-I13, I12=(($H13*12)+($H14*12)),I12-I13)} -> 0 | J14: {=_xlfn.IFS(J12>(($H13*12)+($H14*12)),$H14*12, J12<(($H13*12)+($H14*12)),J12-J13, J12=(($H13*12)+($H14*12)),J12-J13)} -> 32662.2 | K14: {=_xlfn.IFS(K12>(($H13*12)+($H14*12)),$H14*12, K12<(($H13*12)+($H14*12)),K12-K13, K12=(($H13*12)+($H14*12)),K12-K13)} -> 66957.51 | L14: {=_xlfn.IFS(L12>(($H13*12)+($H14*12)),$H14*12, L12<(($H13*12)+($H14*12)),L12-L13, L12=(($H13*12)+($H14*12)),L12-L13)} -> 102967.59 | M14: {=_xlfn.IFS(M12>(($H13*12)+($H14*12)),$H14*12, M12<(($H13*12)+($H14*12)),M12-M13, M12=(($H13*12)+($H14*12)),M12-M13)} -> 140778.16 | P14: =Q14/12 -> 0 | Q14: =IF(O14>0,PRODUCT(I14,$O14),0) -> 0 | R14: =IF(Q14>0,PRODUCT(J14,$O14),0) -> 0 | S14: =IF(R14>0,PRODUCT(K14,$O14),0) -> 0 | T14: =IF(S14>0,PRODUCT(L14,$O14),0) -> 0 | U14: =IF(T14>0,PRODUCT(M14,$O14),0) -> 0 | V14: =SUM(Q14:U14) -> 0 | X14: =C14 -> [Tiered] Base Monthly Processing 54,438 - 100k Accounts | Y14: 0.5 | Z14: =AA14/12 -> 0 | AA14: =IF(Y14>0,PRODUCT(I14,$Y14),0) -> 0 | AB14: {=_xlfn.IFS($AJ14="NO CHARGE",0,$AJ14=0,0,$AJ14>0,PRODUCT(J14,$AJ14))} -> 16331.1 | AC14: =IF(AB14>0,PRODUCT(K14,$Y14),0) -> 33478.755 | AD14: =IF(AC14>0,PRODUCT(L14,$Y14),0) -> 51483.793 | AE14: =IF(AD14>0,PRODUCT(M14,$Y14),0) -> 70389.082 | AF14: =SUM(AA14:AE14) -> 171682.73 | AI14: =C14 -> [Tiered] Base Monthly Processing 54,438 - 100k Accounts | AJ14: 0.5 | AK14: =AL14/12 -> 0 | AL14: {=_xlfn.IFS($AJ14="NO CHARGE",0,$AJ14=0,0,$AJ14>0,PRODUCT(I14,$AJ14))} -> 0 | AM14: {=_xlfn.IFS($AJ14="NO CHARGE",0,$AJ14=0,0,$AJ14>0,PRODUCT(J14,$AJ14))} -> 16331.1 | AN14: {=_xlfn.IFS($AJ14="NO CHARGE",0,$AJ14=0,0,$AJ14>0,PRODUCT(K14,$AJ14))} -> 33478.755 | AO14: {=_xlfn.IFS($AJ14="NO CHARGE",0,$AJ14=0,0,$AJ14>0,PRODUCT(L14,$AJ14))} -> 51483.793 | AP14: {=_xlfn.IFS($AJ14="NO CHARGE",0,$AJ14=0,0,$AJ14>0,PRODUCT(M14,$AJ14))} -> 70389.082 | AQ14: =SUM(AL14:AP14) -> 171682.73 | AV14: =IF(AU14>0,PRODUCT(I14,$AU14),0) -> 0 | AW14: =IF(AV14>0,PRODUCT(J14,$AU14),0) -> 0 | AX14: =IF(AW14>0,PRODUCT(K14,$AU14),0) -> 0 | AY14: =IF(AX14>0,PRODUCT(L14,$AU14),0) -> 0 | AZ14: =IF(AY14>0,PRODUCT(M14,$AU14),0) -> 0 | BA14: =SUM(AV14:AZ14) -> 0
B15: Horizon Core Account Processing | C15: [Tiered] Base Monthly Processing beyond 100k Accounts | I15: {=_xlfn.IFS(I12>(($H13+$H14)*12),I12-I13-I14, I12<(($H13+$H14)*12),0, I12=(($H13+$H14)*12),0)} -> 0 | J15: {=_xlfn.IFS(J12>(($H13+$H14)*12),J12-J13-J14, J12<(($H13+$H14)*12),0, J12=(($H13+$H14)*12),0)} -> 0 | K15: {=_xlfn.IFS(K12>(($H13+$H14)*12),K12-K13-K14, K12<(($H13+$H14)*12),0, K12=(($H13+$H14)*12),0)} -> 0 | L15: {=_xlfn.IFS(L12>(($H13+$H14)*12),L12-L13-L14, L12<(($H13+$H14)*12),0, L12=(($H13+$H14)*12),0)} -> 0 | M15: {=_xlfn.IFS(M12>(($H13+$H14)*12),M12-M13-M14, M12<(($H13+$H14)*12),0, M12=(($H13+$H14)*12),0)} -> 0 | P15: =Q15/12 -> 0 | Q15: =IF(O15>0,PRODUCT(I15,$O15),0) -> 0 | R15: =IF(Q15>0,PRODUCT(J15,$O15),0) -> 0 | S15: =IF(R15>0,PRODUCT(K15,$O15),0) -> 0 | T15: =IF(S15>0,PRODUCT(L15,$O15),0) -> 0 | U15: =IF(T15>0,PRODUCT(M15,$O15),0) -> 0 | V15: =SUM(Q15:U15) -> 0 | X15: =C15 -> [Tiered] Base Monthly Processing beyond 100k Accounts | Y15: 0.48 | Z15: =AA15/12 -> 0 | AA15: =IF(Y15>0,PRODUCT(I15,$Y15),0) -> 0 | AB15: =IF(AA15>0,PRODUCT(J15,$Y15),0) -> 0 | AC15: =IF(AB15>0,PRODUCT(K15,$Y15),0) -> 0 | AD15: =IF(AC15>0,PRODUCT(L15,$Y15),0) -> 0 | AE15: =IF(AD15>0,PRODUCT(M15,$Y15),0) -> 0 | AF15: =SUM(AA15:AE15) -> 0 | AI15: =C15 -> [Tiered] Base Monthly Processing beyond 100k Accounts | AJ15: 0.48 | AK15: =AL15/12 -> 0 | AL15: {=_xlfn.IFS($AJ15="NO CHARGE",0,$AJ15=0,0,$AJ15>0,PRODUCT(I15,$AJ15))} -> 0 | AM15: {=_xlfn.IFS($AJ15="NO CHARGE",0,$AJ15=0,0,$AJ15>0,PRODUCT(J15,$AJ15))} -> 0 | AN15: {=_xlfn.IFS($AJ15="NO CHARGE",0,$AJ15=0,0,$AJ15>0,PRODUCT(K15,$AJ15))} -> 0 | AO15: {=_xlfn.IFS($AJ15="NO CHARGE",0,$AJ15=0,0,$AJ15>0,PRODUCT(L15,$AJ15))} -> 0 | AP15: {=_xlfn.IFS($AJ15="NO CHARGE",0,$AJ15=0,0,$AJ15>0,PRODUCT(M15,$AJ15))} -> 0 | AQ15: =SUM(AL15:AP15) -> 0 | AV15: =IF(AU15>0,PRODUCT(I15,$AU15),0) -> 0 | AW15: =IF(AV15>0,PRODUCT(J15,$AU15),0) -> 0 | AX15: =IF(AW15>0,PRODUCT(K15,$AU15),0) -> 0 | AY15: =IF(AX15>0,PRODUCT(L15,$AU15),0) -> 0 | AZ15: =IF(AY15>0,PRODUCT(M15,$AU15),0) -> 0 | BA15: =SUM(AV15:AZ15) -> 0
B16: Horizon Core Account Processing | C16: =B16&" Monthly Minimum" -> Horizon Core Account Processing Monthly Minimum | H16: 0 | I16: =H16*12 -> 0 | J16: =IF(I16>12,(((I16)*$H$5)+I16),(I16*1)) -> 0 | K16: =IF(J16>12,(((J16)*$H$5)+J16),(J16*1)) -> 0 | L16: =IF(K16>12,(((K16)*$H$5)+K16),(K16*1)) -> 0 | M16: =IF(L16>12,(((L16)*$H$5)+L16),(L16*1)) -> 0 | P16: =Q16/12 -> 0 | Q16: =IF(O16>0,PRODUCT(I16,$O16),0) -> 0 | R16: =IF(Q16>0,PRODUCT(J16,$O16),0) -> 0 | S16: =IF(R16>0,PRODUCT(K16,$O16),0) -> 0 | T16: =IF(S16>0,PRODUCT(L16,$O16),0) -> 0 | U16: =IF(T16>0,PRODUCT(M16,$O16),0) -> 0 | V16: =SUM(Q16:U16) -> 0 | X16: =C16 -> Horizon Core Account Processing Monthly Minimum | Y16: 26000 | Z16: =AA16/12 -> 0 | AA16: =IF(Y16>0,PRODUCT(I16,$Y16),0) -> 0 | AB16: =IF(AA16>0,PRODUCT(J16,$Y16),0) -> 0 | AC16: =IF(AB16>0,PRODUCT(K16,$Y16),0) -> 0 | AD16: =IF(AC16>0,PRODUCT(L16,$Y16),0) -> 0 | AE16: =IF(AD16>0,PRODUCT(M16,$Y16),0) -> 0 | AF16: =SUM(AA16:AE16) -> 0 | AH16: Monthly Minimum Item | AI16: =C16 -> Horizon Core Account Processing Monthly Minimum | AJ16: 26000 | AK16: =AL16/12 -> 0 | AL16: {=_xlfn.IFS($AJ16="NO CHARGE",0,$AJ16=0,0,$AJ16>0,PRODUCT(I16,$AJ16))} -> 0 | AM16: {=_xlfn.IFS($AJ16="NO CHARGE",0,$AJ16=0,0,$AJ16>0,PRODUCT(J16,$AJ16))} -> 0 | AN16: {=_xlfn.IFS($AJ16="NO CHARGE",0,$AJ16=0,0,$AJ16>0,PRODUCT(K16,$AJ16))} -> 0 | AO16: {=_xlfn.IFS($AJ16="NO CHARGE",0,$AJ16=0,0,$AJ16>0,PRODUCT(L16,$AJ16))} -> 0 | AP16: {=_xlfn.IFS($AJ16="NO CHARGE",0,$AJ16=0,0,$AJ16>0,PRODUCT(M16,$AJ16))} -> 0 | AQ16: =SUM(AL16:AP16) -> 0 | AS16: Monthly Minimum Item | AV16: =IF(AU16>0,PRODUCT(I16,$AU16),0) -> 0 | AW16: =IF(AV16>0,PRODUCT(J16,$AU16),0) -> 0 | AX16: =IF(AW16>0,PRODUCT(K16,$AU16),0) -> 0 | AY16: =IF(AX16>0,PRODUCT(L16,$AU16),0) -> 0 | AZ16: =IF(AY16>0,PRODUCT(M16,$AU16),0) -> 0 | BA16: =SUM(AV16:AZ16) -> 0
H17: =IFERROR(AVERAGE(D17:G17),0) -> 0 | I17: =H17*12 -> 0 | J17: =IF(I17>12,(((I17)*$H$5)+I17),(I17*1)) -> 0 | K17: =IF(J17>12,(((J17)*$H$5)+J17),(J17*1)) -> 0 | L17: =IF(K17>12,(((K17)*$H$5)+K17),(K17*1)) -> 0 | M17: =IF(L17>12,(((L17)*$H$5)+L17),(L17*1)) -> 0 | N17: =IF(C17="","",C17) | P17: =Q17/12 -> 0 | Q17: =IF(O17>0,PRODUCT(I17,$O17),0) -> 0 | R17: =IF(Q17>0,PRODUCT(J17,$O17),0) -> 0 | S17: =IF(R17>0,PRODUCT(K17,$O17),0) -> 0 | T17: =IF(S17>0,PRODUCT(L17,$O17),0) -> 0 | U17: =IF(T17>0,PRODUCT(M17,$O17),0) -> 0 | V17: =SUM(Q17:U17) -> 0 | Z17: =AA17/12 -> 0 | AA17: =IF(Y17>0,PRODUCT(I17,$Y17),0) -> 0 | AB17: =IF(AA17>0,PRODUCT(J17,$Y17),0) -> 0 | AC17: =IF(AB17>0,PRODUCT(K17,$Y17),0) -> 0 | AD17: =IF(AC17>0,PRODUCT(L17,$Y17),0) -> 0 | AE17: =IF(AD17>0,PRODUCT(M17,$Y17),0) -> 0 | AF17: =SUM(AA17:AE17) -> 0 | AK17: =AL17/12 -> 0 | AL17: {=_xlfn.IFS($AJ17="NO CHARGE",0,$AJ17=0,0,$AJ17>0,PRODUCT(I17,$AJ17))} -> 0 | AM17: {=_xlfn.IFS($AJ17="NO CHARGE",0,$AJ17=0,0,$AJ17>0,PRODUCT(J17,$AJ17))} -> 0 | AN17: {=_xlfn.IFS($AJ17="NO CHARGE",0,$AJ17=0,0,$AJ17>0,PRODUCT(K17,$AJ17))} -> 0 | AO17: {=_xlfn.IFS($AJ17="NO CHARGE",0,$AJ17=0,0,$AJ17>0,PRODUCT(L17,$AJ17))} -> 0 | AP17: {=_xlfn.IFS($AJ17="NO CHARGE",0,$AJ17=0,0,$AJ17>0,PRODUCT(M17,$AJ17))} -> 0 | AQ17: =SUM(AL17:AP17) -> 0 | AV17: =IF(AU17>0,PRODUCT(I17,$AU17),0) -> 0 | AW17: =IF(AV17>0,PRODUCT(J17,$AU17),0) -> 0 | AX17: =IF(AW17>0,PRODUCT(K17,$AU17),0) -> 0 | AY17: =IF(AX17>0,PRODUCT(L17,$AU17),0) -> 0 | AZ17: =IF(AY17>0,PRODUCT(M17,$AU17),0) -> 0 | BA17: =SUM(AV17:AZ17) -> 0
C18: Core Module Per Account Fee Inclusions: | H18: =IFERROR(AVERAGE(D18:G18),0) -> 0 | I18: =H18*12 -> 0 | J18: =IF(I18>12,(((I18)*$H$5)+I18),(I18*1)) -> 0 | K18: =IF(J18>12,(((J18)*$H$5)+J18),(J18*1)) -> 0 | L18: =IF(K18>12,(((K18)*$H$5)+K18),(K18*1)) -> 0 | M18: =IF(L18>12,(((L18)*$H$5)+L18),(L18*1)) -> 0 | P18: =Q18/12 -> 0 | Q18: =IF(O18>0,PRODUCT(I18,$O18),0) -> 0 | R18: =IF(Q18>0,PRODUCT(J18,$O18),0) -> 0 | S18: =IF(R18>0,PRODUCT(K18,$O18),0) -> 0 | T18: =IF(S18>0,PRODUCT(L18,$O18),0) -> 0 | U18: =IF(T18>0,PRODUCT(M18,$O18),0) -> 0 | V18: =SUM(Q18:U18) -> 0 | X18: =C18 -> Core Module Per Account Fee Inclusions: | Z18: =AA18/12 -> 0 | AA18: =IF(Y18>0,PRODUCT(I18,$Y18),0) -> 0 | AB18: =IF(AA18>0,PRODUCT(J18,$Y18),0) -> 0 | AC18: =IF(AB18>0,PRODUCT(K18,$Y18),0) -> 0 | AD18: =IF(AC18>0,PRODUCT(L18,$Y18),0) -> 0 | AE18: =IF(AD18>0,PRODUCT(M18,$Y18),0) -> 0 | AF18: =SUM(AA18:AE18) -> 0 | AI18: Core Module Per Account Fee Inclusions: | AK18: =AL18/12 -> 0 | AL18: {=_xlfn.IFS($AJ18="NO CHARGE",0,$AJ18=0,0,$AJ18>0,PRODUCT(I18,$AJ18))} -> 0 | AM18: {=_xlfn.IFS($AJ18="NO CHARGE",0,$AJ18=0,0,$AJ18>0,PRODUCT(J18,$AJ18))} -> 0 | AN18: {=_xlfn.IFS($AJ18="NO CHARGE",0,$AJ18=0,0,$AJ18>0,PRODUCT(K18,$AJ18))} -> 0 | AO18: {=_xlfn.IFS($AJ18="NO CHARGE",0,$AJ18=0,0,$AJ18>0,PRODUCT(L18,$AJ18))} -> 0 | AP18: {=_xlfn.IFS($AJ18="NO CHARGE",0,$AJ18=0,0,$AJ18>0,PRODUCT(M18,$AJ18))} -> 0 | AQ18: =SUM(AL18:AP18) -> 0 | AV18: =IF(AU18>0,PRODUCT(I18,$AU18),0) -> 0 | AW18: =IF(AV18>0,PRODUCT(J18,$AU18),0) -> 0 | AX18: =IF(AW18>0,PRODUCT(K18,$AU18),0) -> 0 | AY18: =IF(AX18>0,PRODUCT(L18,$AU18),0) -> 0 | AZ18: =IF(AY18>0,PRODUCT(M18,$AU18),0) -> 0 | BA18: =SUM(AV18:AZ18) -> 0
C19: Archived Accounts | H19: =IFERROR(AVERAGE(D19:G19),0) -> 0 | I19: =H19*12 -> 0 | J19: =IF(I19>12,(((I19)*$H$5)+I19),(I19*1)) -> 0 | K19: =IF(J19>12,(((J19)*$H$5)+J19),(J19*1)) -> 0 | L19: =IF(K19>12,(((K19)*$H$5)+K19),(K19*1)) -> 0 | M19: =IF(L19>12,(((L19)*$H$5)+L19),(L19*1)) -> 0 | P19: =Q19/12 -> 0 | Q19: =IF(O19>0,PRODUCT(I19,$O19),0) -> 0 | R19: =IF(Q19>0,PRODUCT(J19,$O19),0) -> 0 | S19: =IF(R19>0,PRODUCT(K19,$O19),0) -> 0 | T19: =IF(S19>0,PRODUCT(L19,$O19),0) -> 0 | U19: =IF(T19>0,PRODUCT(M19,$O19),0) -> 0 | V19: =SUM(Q19:U19) -> 0 | X19: =C19 -> Archived Accounts | Y19: INCLUDED | Z19: =AA19/12 -> 0 | AA19: =IF(Y19>0,PRODUCT(I19,$Y19),0) -> 0 | AB19: =IF(AA19>0,PRODUCT(J19,$Y19),0) -> 0 | AC19: =IF(AB19>0,PRODUCT(K19,$Y19),0) -> 0 | AD19: =IF(AC19>0,PRODUCT(L19,$Y19),0) -> 0 | AE19: =IF(AD19>0,PRODUCT(M19,$Y19),0) -> 0 | AF19: =SUM(AA19:AE19) -> 0 | AI19: Archived Accounts | AK19: =AL19/12 -> 0 | AL19: {=_xlfn.IFS($AJ19="NO CHARGE",0,$AJ19=0,0,$AJ19>0,PRODUCT(I19,$AJ19))} -> 0 | AM19: {=_xlfn.IFS($AJ19="NO CHARGE",0,$AJ19=0,0,$AJ19>0,PRODUCT(J19,$AJ19))} -> 0 | AN19: {=_xlfn.IFS($AJ19="NO CHARGE",0,$AJ19=0,0,$AJ19>0,PRODUCT(K19,$AJ19))} -> 0 | AO19: {=_xlfn.IFS($AJ19="NO CHARGE",0,$AJ19=0,0,$AJ19>0,PRODUCT(L19,$AJ19))} -> 0 | AP19: {=_xlfn.IFS($AJ19="NO CHARGE",0,$AJ19=0,0,$AJ19>0,PRODUCT(M19,$AJ19))} -> 0 | AQ19: =SUM(AL19:AP19) -> 0 | AV19: =IF(AU19>0,PRODUCT(I19,$AU19),0) -> 0 | AW19: =IF(AV19>0,PRODUCT(J19,$AU19),0) -> 0 | AX19: =IF(AW19>0,PRODUCT(K19,$AU19),0) -> 0 | AY19: =IF(AX19>0,PRODUCT(L19,$AU19),0) -> 0 | AZ19: =IF(AY19>0,PRODUCT(M19,$AU19),0) -> 0 | BA19: =SUM(AV19:AZ19) -> 0
C20: Credit Bureau Reporting (3 included) | H20: =IFERROR(AVERAGE(D20:G20),0) -> 0 | I20: =H20*12 -> 0 | J20: =IF(I20>12,(((I20)*$H$5)+I20),(I20*1)) -> 0 | K20: =IF(J20>12,(((J20)*$H$5)+J20),(J20*1)) -> 0 | L20: =IF(K20>12,(((K20)*$H$5)+K20),(K20*1)) -> 0 | M20: =IF(L20>12,(((L20)*$H$5)+L20),(L20*1)) -> 0 | P20: =Q20/12 -> 0 | Q20: =IF(O20>0,PRODUCT(I20,$O20),0) -> 0 | R20: =IF(Q20>0,PRODUCT(J20,$O20),0) -> 0 | S20: =IF(R20>0,PRODUCT(K20,$O20),0) -> 0 | T20: =IF(S20>0,PRODUCT(L20,$O20),0) -> 0 | U20: =IF(T20>0,PRODUCT(M20,$O20),0) -> 0 | V20: =SUM(Q20:U20) -> 0 | X20: =C20 -> Credit Bureau Reporting (3 included) | Y20: INCLUDED | Z20: =AA20/12 -> 0 | AA20: =IF(Y20>0,PRODUCT(I20,$Y20),0) -> 0 | AB20: =IF(AA20>0,PRODUCT(J20,$Y20),0) -> 0 | AC20: =IF(AB20>0,PRODUCT(K20,$Y20),0) -> 0 | AD20: =IF(AC20>0,PRODUCT(L20,$Y20),0) -> 0 | AE20: =IF(AD20>0,PRODUCT(M20,$Y20),0) -> 0 | AF20: =SUM(AA20:AE20) -> 0 | AI20: Credit Bureau Reporting (3 included) | AK20: =AL20/12 -> 0 | AL20: {=_xlfn.IFS($AJ20="NO CHARGE",0,$AJ20=0,0,$AJ20>0,PRODUCT(I20,$AJ20))} -> 0 | AM20: {=_xlfn.IFS($AJ20="NO CHARGE",0,$AJ20=0,0,$AJ20>0,PRODUCT(J20,$AJ20))} -> 0 | AN20: {=_xlfn.IFS($AJ20="NO CHARGE",0,$AJ20=0,0,$AJ20>0,PRODUCT(K20,$AJ20))} -> 0 | AO20: {=_xlfn.IFS($AJ20="NO CHARGE",0,$AJ20=0,0,$AJ20>0,PRODUCT(L20,$AJ20))} -> 0 | AP20: {=_xlfn.IFS($AJ20="NO CHARGE",0,$AJ20=0,0,$AJ20>0,PRODUCT(M20,$AJ20))} -> 0 | AQ20: =SUM(AL20:AP20) -> 0 | AV20: =IF(AU20>0,PRODUCT(I20,$AU20),0) -> 0 | AW20: =IF(AV20>0,PRODUCT(J20,$AU20),0) -> 0 | AX20: =IF(AW20>0,PRODUCT(K20,$AU20),0) -> 0 | AY20: =IF(AX20>0,PRODUCT(L20,$AU20),0) -> 0 | AZ20: =IF(AY20>0,PRODUCT(M20,$AU20),0) -> 0 | BA20: =SUM(AV20:AZ20) -> 0
C21: DDA/Savings History Retention | H21: =IFERROR(AVERAGE(D21:G21),0) -> 0 | I21: =H21*12 -> 0 | J21: =IF(I21>12,(((I21)*$H$5)+I21),(I21*1)) -> 0 | K21: =IF(J21>12,(((J21)*$H$5)+J21),(J21*1)) -> 0 | L21: =IF(K21>12,(((K21)*$H$5)+K21),(K21*1)) -> 0 | M21: =IF(L21>12,(((L21)*$H$5)+L21),(L21*1)) -> 0 | P21: =Q21/12 -> 0 | Q21: =IF(O21>0,PRODUCT(I21,$O21),0) -> 0 | R21: =IF(Q21>0,PRODUCT(J21,$O21),0) -> 0 | S21: =IF(R21>0,PRODUCT(K21,$O21),0) -> 0 | T21: =IF(S21>0,PRODUCT(L21,$O21),0) -> 0 | U21: =IF(T21>0,PRODUCT(M21,$O21),0) -> 0 | V21: =SUM(Q21:U21) -> 0 | X21: =C21 -> DDA/Savings History Retention | Y21: INCLUDED | Z21: =AA21/12 -> 0 | AA21: =IF(Y21>0,PRODUCT(I21,$Y21),0) -> 0 | AB21: =IF(AA21>0,PRODUCT(J21,$Y21),0) -> 0 | AC21: =IF(AB21>0,PRODUCT(K21,$Y21),0) -> 0 | AD21: =IF(AC21>0,PRODUCT(L21,$Y21),0) -> 0 | AE21: =IF(AD21>0,PRODUCT(M21,$Y21),0) -> 0 | AF21: =SUM(AA21:AE21) -> 0 | AI21: DDA/Savings History Retention | AK21: =AL21/12 -> 0 | AL21: {=_xlfn.IFS($AJ21="NO CHARGE",0,$AJ21=0,0,$AJ21>0,PRODUCT(I21,$AJ21))} -> 0 | AM21: {=_xlfn.IFS($AJ21="NO CHARGE",0,$AJ21=0,0,$AJ21>0,PRODUCT(J21,$AJ21))} -> 0 | AN21: {=_xlfn.IFS($AJ21="NO CHARGE",0,$AJ21=0,0,$AJ21>0,PRODUCT(K21,$AJ21))} -> 0 | AO21: {=_xlfn.IFS($AJ21="NO CHARGE",0,$AJ21=0,0,$AJ21>0,PRODUCT(L21,$AJ21))} -> 0 | AP21: {=_xlfn.IFS($AJ21="NO CHARGE",0,$AJ21=0,0,$AJ21>0,PRODUCT(M21,$AJ21))} -> 0 | AQ21: =SUM(AL21:AP21) -> 0 | AV21: =IF(AU21>0,PRODUCT(I21,$AU21),0) -> 0 | AW21: =IF(AV21>0,PRODUCT(J21,$AU21),0) -> 0 | AX21: =IF(AW21>0,PRODUCT(K21,$AU21),0) -> 0 | AY21: =IF(AX21>0,PRODUCT(L21,$AU21),0) -> 0 | AZ21: =IF(AY21>0,PRODUCT(M21,$AU21),0) -> 0 | BA21: =SUM(AV21:AZ21) -> 0
C22: Deposit Origination (DO) | H22: =IFERROR(AVERAGE(D22:G22),0) -> 0 | I22: =H22*12 -> 0 | J22: =IF(I22>12,(((I22)*$H$5)+I22),(I22*1)) -> 0 | K22: =IF(J22>12,(((J22)*$H$5)+J22),(J22*1)) -> 0 | L22: =IF(K22>12,(((K22)*$H$5)+K22),(K22*1)) -> 0 | M22: =IF(L22>12,(((L22)*$H$5)+L22),(L22*1)) -> 0 | P22: =Q22/12 -> 0 | Q22: =IF(O22>0,PRODUCT(I22,$O22),0) -> 0 | R22: =IF(Q22>0,PRODUCT(J22,$O22),0) -> 0 | S22: =IF(R22>0,PRODUCT(K22,$O22),0) -> 0 | T22: =IF(S22>0,PRODUCT(L22,$O22),0) -> 0 | U22: =IF(T22>0,PRODUCT(M22,$O22),0) -> 0 | V22: =SUM(Q22:U22) -> 0 | X22: =C22 -> Deposit Origination (DO) | Y22: INCLUDED | Z22: =AA22/12 -> 0 | AA22: =IF(Y22>0,PRODUCT(I22,$Y22),0) -> 0 | AB22: =IF(AA22>0,PRODUCT(J22,$Y22),0) -> 0 | AC22: =IF(AB22>0,PRODUCT(K22,$Y22),0) -> 0 | AD22: =IF(AC22>0,PRODUCT(L22,$Y22),0) -> 0 | AE22: =IF(AD22>0,PRODUCT(M22,$Y22),0) -> 0 | AF22: =SUM(AA22:AE22) -> 0 | AI22: Deposit Origination (DO) | AK22: =AL22/12 -> 0 | AL22: {=_xlfn.IFS($AJ22="NO CHARGE",0,$AJ22=0,0,$AJ22>0,PRODUCT(I22,$AJ22))} -> 0 | AM22: {=_xlfn.IFS($AJ22="NO CHARGE",0,$AJ22=0,0,$AJ22>0,PRODUCT(J22,$AJ22))} -> 0 | AN22: {=_xlfn.IFS($AJ22="NO CHARGE",0,$AJ22=0,0,$AJ22>0,PRODUCT(K22,$AJ22))} -> 0 | AO22: {=_xlfn.IFS($AJ22="NO CHARGE",0,$AJ22=0,0,$AJ22>0,PRODUCT(L22,$AJ22))} -> 0 | AP22: {=_xlfn.IFS($AJ22="NO CHARGE",0,$AJ22=0,0,$AJ22>0,PRODUCT(M22,$AJ22))} -> 0 | AQ22: =SUM(AL22:AP22) -> 0 | AV22: =IF(AU22>0,PRODUCT(I22,$AU22),0) -> 0 | AW22: =IF(AV22>0,PRODUCT(J22,$AU22),0) -> 0 | AX22: =IF(AW22>0,PRODUCT(K22,$AU22),0) -> 0 | AY22: =IF(AX22>0,PRODUCT(L22,$AU22),0) -> 0 | AZ22: =IF(AY22>0,PRODUCT(M22,$AU22),0) -> 0 | BA22: =SUM(AV22:AZ22) -> 0
C23: eSignature for Teller Capture | H23: =IFERROR(AVERAGE(D23:G23),0) -> 0 | I23: =H23*12 -> 0 | J23: =IF(I23>12,(((I23)*$H$5)+I23),(I23*1)) -> 0 | K23: =IF(J23>12,(((J23)*$H$5)+J23),(J23*1)) -> 0 | L23: =IF(K23>12,(((K23)*$H$5)+K23),(K23*1)) -> 0 | M23: =IF(L23>12,(((L23)*$H$5)+L23),(L23*1)) -> 0 | P23: =Q23/12 -> 0 | Q23: =IF(O23>0,PRODUCT(I23,$O23),0) -> 0 | R23: =IF(Q23>0,PRODUCT(J23,$O23),0) -> 0 | S23: =IF(R23>0,PRODUCT(K23,$O23),0) -> 0 | T23: =IF(S23>0,PRODUCT(L23,$O23),0) -> 0 | U23: =IF(T23>0,PRODUCT(M23,$O23),0) -> 0 | V23: =SUM(Q23:U23) -> 0 | X23: =C23 -> eSignature for Teller Capture | Y23: INCLUDED | Z23: =AA23/12 -> 0 | AA23: =IF(Y23>0,PRODUCT(I23,$Y23),0) -> 0 | AB23: =IF(AA23>0,PRODUCT(J23,$Y23),0) -> 0 | AC23: =IF(AB23>0,PRODUCT(K23,$Y23),0) -> 0 | AD23: =IF(AC23>0,PRODUCT(L23,$Y23),0) -> 0 | AE23: =IF(AD23>0,PRODUCT(M23,$Y23),0) -> 0 | AF23: =SUM(AA23:AE23) -> 0 | AI23: eSignature for Teller Capture | AK23: =AL23/12 -> 0 | AL23: {=_xlfn.IFS($AJ23="NO CHARGE",0,$AJ23=0,0,$AJ23>0,PRODUCT(I23,$AJ23))} -> 0 | AM23: {=_xlfn.IFS($AJ23="NO CHARGE",0,$AJ23=0,0,$AJ23>0,PRODUCT(J23,$AJ23))} -> 0 | AN23: {=_xlfn.IFS($AJ23="NO CHARGE",0,$AJ23=0,0,$AJ23>0,PRODUCT(K23,$AJ23))} -> 0 | AO23: {=_xlfn.IFS($AJ23="NO CHARGE",0,$AJ23=0,0,$AJ23>0,PRODUCT(L23,$AJ23))} -> 0 | AP23: {=_xlfn.IFS($AJ23="NO CHARGE",0,$AJ23=0,0,$AJ23>0,PRODUCT(M23,$AJ23))} -> 0 | AQ23: =SUM(AL23:AP23) -> 0 | AV23: =IF(AU23>0,PRODUCT(I23,$AU23),0) -> 0 | AW23: =IF(AV23>0,PRODUCT(J23,$AU23),0) -> 0 | AX23: =IF(AW23>0,PRODUCT(K23,$AU23),0) -> 0 | AY23: =IF(AX23>0,PRODUCT(L23,$AU23),0) -> 0 | AZ23: =IF(AY23>0,PRODUCT(M23,$AU23),0) -> 0 | BA23: =SUM(AV23:AZ23) -> 0
C24: General Ledger History Retention | H24: =IFERROR(AVERAGE(D24:G24),0) -> 0 | I24: =H24*12 -> 0 | J24: =IF(I24>12,(((I24)*$H$5)+I24),(I24*1)) -> 0 | K24: =IF(J24>12,(((J24)*$H$5)+J24),(J24*1)) -> 0 | L24: =IF(K24>12,(((K24)*$H$5)+K24),(K24*1)) -> 0 | M24: =IF(L24>12,(((L24)*$H$5)+L24),(L24*1)) -> 0 | P24: =Q24/12 -> 0 | Q24: =IF(O24>0,PRODUCT(I24,$O24),0) -> 0 | R24: =IF(Q24>0,PRODUCT(J24,$O24),0) -> 0 | S24: =IF(R24>0,PRODUCT(K24,$O24),0) -> 0 | T24: =IF(S24>0,PRODUCT(L24,$O24),0) -> 0 | U24: =IF(T24>0,PRODUCT(M24,$O24),0) -> 0 | V24: =SUM(Q24:U24) -> 0 | X24: =C24 -> General Ledger History Retention | Y24: INCLUDED | Z24: =AA24/12 -> 0 | AA24: =IF(Y24>0,PRODUCT(I24,$Y24),0) -> 0 | AB24: =IF(AA24>0,PRODUCT(J24,$Y24),0) -> 0 | AC24: =IF(AB24>0,PRODUCT(K24,$Y24),0) -> 0 | AD24: =IF(AC24>0,PRODUCT(L24,$Y24),0) -> 0 | AE24: =IF(AD24>0,PRODUCT(M24,$Y24),0) -> 0 | AF24: =SUM(AA24:AE24) -> 0 | AI24: General Ledger History Retention | AK24: =AL24/12 -> 0 | AL24: {=_xlfn.IFS($AJ24="NO CHARGE",0,$AJ24=0,0,$AJ24>0,PRODUCT(I24,$AJ24))} -> 0 | AM24: {=_xlfn.IFS($AJ24="NO CHARGE",0,$AJ24=0,0,$AJ24>0,PRODUCT(J24,$AJ24))} -> 0 | AN24: {=_xlfn.IFS($AJ24="NO CHARGE",0,$AJ24=0,0,$AJ24>0,PRODUCT(K24,$AJ24))} -> 0 | AO24: {=_xlfn.IFS($AJ24="NO CHARGE",0,$AJ24=0,0,$AJ24>0,PRODUCT(L24,$AJ24))} -> 0 | AP24: {=_xlfn.IFS($AJ24="NO CHARGE",0,$AJ24=0,0,$AJ24>0,PRODUCT(M24,$AJ24))} -> 0 | AQ24: =SUM(AL24:AP24) -> 0 | AV24: =IF(AU24>0,PRODUCT(I24,$AU24),0) -> 0 | AW24: =IF(AV24>0,PRODUCT(J24,$AU24),0) -> 0 | AX24: =IF(AW24>0,PRODUCT(K24,$AU24),0) -> 0 | AY24: =IF(AX24>0,PRODUCT(L24,$AU24),0) -> 0 | AZ24: =IF(AY24>0,PRODUCT(M24,$AU24),0) -> 0 | BA24: =SUM(AV24:AZ24) -> 0
C25: GL Posting Account/Branch/Center Processing | H25: =IFERROR(AVERAGE(D25:G25),0) -> 0 | I25: =H25*12 -> 0 | J25: =IF(I25>12,(((I25)*$H$5)+I25),(I25*1)) -> 0 | K25: =IF(J25>12,(((J25)*$H$5)+J25),(J25*1)) -> 0 | L25: =IF(K25>12,(((K25)*$H$5)+K25),(K25*1)) -> 0 | M25: =IF(L25>12,(((L25)*$H$5)+L25),(L25*1)) -> 0 | P25: =Q25/12 -> 0 | Q25: =IF(O25>0,PRODUCT(I25,$O25),0) -> 0 | R25: =IF(Q25>0,PRODUCT(J25,$O25),0) -> 0 | S25: =IF(R25>0,PRODUCT(K25,$O25),0) -> 0 | T25: =IF(S25>0,PRODUCT(L25,$O25),0) -> 0 | U25: =IF(T25>0,PRODUCT(M25,$O25),0) -> 0 | V25: =SUM(Q25:U25) -> 0 | X25: =C25 -> GL Posting Account/Branch/Center Processing | Y25: INCLUDED | Z25: =AA25/12 -> 0 | AA25: =IF(Y25>0,PRODUCT(I25,$Y25),0) -> 0 | AB25: =IF(AA25>0,PRODUCT(J25,$Y25),0) -> 0 | AC25: =IF(AB25>0,PRODUCT(K25,$Y25),0) -> 0 | AD25: =IF(AC25>0,PRODUCT(L25,$Y25),0) -> 0 | AE25: =IF(AD25>0,PRODUCT(M25,$Y25),0) -> 0 | AF25: =SUM(AA25:AE25) -> 0 | AI25: GL Posting Account/Branch/Center Processing | AK25: =AL25/12 -> 0 | AL25: {=_xlfn.IFS($AJ25="NO CHARGE",0,$AJ25=0,0,$AJ25>0,PRODUCT(I25,$AJ25))} -> 0 | AM25: {=_xlfn.IFS($AJ25="NO CHARGE",0,$AJ25=0,0,$AJ25>0,PRODUCT(J25,$AJ25))} -> 0 | AN25: {=_xlfn.IFS($AJ25="NO CHARGE",0,$AJ25=0,0,$AJ25>0,PRODUCT(K25,$AJ25))} -> 0 | AO25: {=_xlfn.IFS($AJ25="NO CHARGE",0,$AJ25=0,0,$AJ25>0,PRODUCT(L25,$AJ25))} -> 0 | AP25: {=_xlfn.IFS($AJ25="NO CHARGE",0,$AJ25=0,0,$AJ25>0,PRODUCT(M25,$AJ25))} -> 0 | AQ25: =SUM(AL25:AP25) -> 0 | AV25: =IF(AU25>0,PRODUCT(I25,$AU25),0) -> 0 | AW25: =IF(AV25>0,PRODUCT(J25,$AU25),0) -> 0 | AX25: =IF(AW25>0,PRODUCT(K25,$AU25),0) -> 0 | AY25: =IF(AX25>0,PRODUCT(L25,$AU25),0) -> 0 | AZ25: =IF(AY25>0,PRODUCT(M25,$AU25),0) -> 0 | BA25: =SUM(AV25:AZ25) -> 0
C26: HORIZON eAlert (email only) | H26: =IFERROR(AVERAGE(D26:G26),0) -> 0 | I26: =H26*12 -> 0 | J26: =IF(I26>12,(((I26)*$H$5)+I26),(I26*1)) -> 0 | K26: =IF(J26>12,(((J26)*$H$5)+J26),(J26*1)) -> 0 | L26: =IF(K26>12,(((K26)*$H$5)+K26),(K26*1)) -> 0 | M26: =IF(L26>12,(((L26)*$H$5)+L26),(L26*1)) -> 0 | P26: =Q26/12 -> 0 | Q26: =IF(O26>0,PRODUCT(I26,$O26),0) -> 0 | R26: =IF(Q26>0,PRODUCT(J26,$O26),0) -> 0 | S26: =IF(R26>0,PRODUCT(K26,$O26),0) -> 0 | T26: =IF(S26>0,PRODUCT(L26,$O26),0) -> 0 | U26: =IF(T26>0,PRODUCT(M26,$O26),0) -> 0 | V26: =SUM(Q26:U26) -> 0 | X26: =C26 -> HORIZON eAlert (email only) | Y26: INCLUDED | Z26: =AA26/12 -> 0 | AA26: =IF(Y26>0,PRODUCT(I26,$Y26),0) -> 0 | AB26: =IF(AA26>0,PRODUCT(J26,$Y26),0) -> 0 | AC26: =IF(AB26>0,PRODUCT(K26,$Y26),0) -> 0 | AD26: =IF(AC26>0,PRODUCT(L26,$Y26),0) -> 0 | AE26: =IF(AD26>0,PRODUCT(M26,$Y26),0) -> 0 | AF26: =SUM(AA26:AE26) -> 0 | AI26: HORIZON eAlert (email only) | AK26: =AL26/12 -> 0 | AL26: {=_xlfn.IFS($AJ26="NO CHARGE",0,$AJ26=0,0,$AJ26>0,PRODUCT(I26,$AJ26))} -> 0 | AM26: {=_xlfn.IFS($AJ26="NO CHARGE",0,$AJ26=0,0,$AJ26>0,PRODUCT(J26,$AJ26))} -> 0 | AN26: {=_xlfn.IFS($AJ26="NO CHARGE",0,$AJ26=0,0,$AJ26>0,PRODUCT(K26,$AJ26))} -> 0 | AO26: {=_xlfn.IFS($AJ26="NO CHARGE",0,$AJ26=0,0,$AJ26>0,PRODUCT(L26,$AJ26))} -> 0 | AP26: {=_xlfn.IFS($AJ26="NO CHARGE",0,$AJ26=0,0,$AJ26>0,PRODUCT(M26,$AJ26))} -> 0 | AQ26: =SUM(AL26:AP26) -> 0 | AV26: =IF(AU26>0,PRODUCT(I26,$AU26),0) -> 0 | AW26: =IF(AV26>0,PRODUCT(J26,$AU26),0) -> 0 | AX26: =IF(AW26>0,PRODUCT(K26,$AU26),0) -> 0 | AY26: =IF(AX26>0,PRODUCT(L26,$AU26),0) -> 0 | AZ26: =IF(AY26>0,PRODUCT(M26,$AU26),0) -> 0 | BA26: =SUM(AV26:AZ26) -> 0
C27: HORIZON Teller | H27: =IFERROR(AVERAGE(D27:G27),0) -> 0 | I27: =H27*12 -> 0 | J27: =IF(I27>12,(((I27)*$H$5)+I27),(I27*1)) -> 0 | K27: =IF(J27>12,(((J27)*$H$5)+J27),(J27*1)) -> 0 | L27: =IF(K27>12,(((K27)*$H$5)+K27),(K27*1)) -> 0 | M27: =IF(L27>12,(((L27)*$H$5)+L27),(L27*1)) -> 0 | P27: =Q27/12 -> 0 | Q27: =IF(O27>0,PRODUCT(I27,$O27),0) -> 0 | R27: =IF(Q27>0,PRODUCT(J27,$O27),0) -> 0 | S27: =IF(R27>0,PRODUCT(K27,$O27),0) -> 0 | T27: =IF(S27>0,PRODUCT(L27,$O27),0) -> 0 | U27: =IF(T27>0,PRODUCT(M27,$O27),0) -> 0 | V27: =SUM(Q27:U27) -> 0 | X27: =C27 -> HORIZON Teller | Y27: INCLUDED | Z27: =AA27/12 -> 0 | AA27: =IF(Y27>0,PRODUCT(I27,$Y27),0) -> 0 | AB27: =IF(AA27>0,PRODUCT(J27,$Y27),0) -> 0 | AC27: =IF(AB27>0,PRODUCT(K27,$Y27),0) -> 0 | AD27: =IF(AC27>0,PRODUCT(L27,$Y27),0) -> 0 | AE27: =IF(AD27>0,PRODUCT(M27,$Y27),0) -> 0 | AF27: =SUM(AA27:AE27) -> 0 | AI27: HORIZON Teller | AK27: =AL27/12 -> 0 | AL27: {=_xlfn.IFS($AJ27="NO CHARGE",0,$AJ27=0,0,$AJ27>0,PRODUCT(I27,$AJ27))} -> 0 | AM27: {=_xlfn.IFS($AJ27="NO CHARGE",0,$AJ27=0,0,$AJ27>0,PRODUCT(J27,$AJ27))} -> 0 | AN27: {=_xlfn.IFS($AJ27="NO CHARGE",0,$AJ27=0,0,$AJ27>0,PRODUCT(K27,$AJ27))} -> 0 | AO27: {=_xlfn.IFS($AJ27="NO CHARGE",0,$AJ27=0,0,$AJ27>0,PRODUCT(L27,$AJ27))} -> 0 | AP27: {=_xlfn.IFS($AJ27="NO CHARGE",0,$AJ27=0,0,$AJ27>0,PRODUCT(M27,$AJ27))} -> 0 | AQ27: =SUM(AL27:AP27) -> 0 | AV27: =IF(AU27>0,PRODUCT(I27,$AU27),0) -> 0 | AW27: =IF(AV27>0,PRODUCT(J27,$AU27),0) -> 0 | AX27: =IF(AW27>0,PRODUCT(K27,$AU27),0) -> 0 | AY27: =IF(AX27>0,PRODUCT(L27,$AU27),0) -> 0 | AZ27: =IF(AY27>0,PRODUCT(M27,$AU27),0) -> 0 | BA27: =SUM(AV27:AZ27) -> 0
C28: Multi-Tabbing | H28: =IFERROR(AVERAGE(D28:G28),0) -> 0 | I28: =H28*12 -> 0 | J28: =IF(I28>12,(((I28)*$H$5)+I28),(I28*1)) -> 0 | K28: =IF(J28>12,(((J28)*$H$5)+J28),(J28*1)) -> 0 | L28: =IF(K28>12,(((K28)*$H$5)+K28),(K28*1)) -> 0 | M28: =IF(L28>12,(((L28)*$H$5)+L28),(L28*1)) -> 0 | P28: =Q28/12 -> 0 | Q28: =IF(O28>0,PRODUCT(I28,$O28),0) -> 0 | R28: =IF(Q28>0,PRODUCT(J28,$O28),0) -> 0 | S28: =IF(R28>0,PRODUCT(K28,$O28),0) -> 0 | T28: =IF(S28>0,PRODUCT(L28,$O28),0) -> 0 | U28: =IF(T28>0,PRODUCT(M28,$O28),0) -> 0 | V28: =SUM(Q28:U28) -> 0 | X28: =C28 -> Multi-Tabbing | Y28: INCLUDED | Z28: =AA28/12 -> 0 | AA28: =IF(Y28>0,PRODUCT(I28,$Y28),0) -> 0 | AB28: =IF(AA28>0,PRODUCT(J28,$Y28),0) -> 0 | AC28: =IF(AB28>0,PRODUCT(K28,$Y28),0) -> 0 | AD28: =IF(AC28>0,PRODUCT(L28,$Y28),0) -> 0 | AE28: =IF(AD28>0,PRODUCT(M28,$Y28),0) -> 0 | AF28: =SUM(AA28:AE28) -> 0 | AI28: Multi-Tabbing | AK28: =AL28/12 -> 0 | AL28: {=_xlfn.IFS($AJ28="NO CHARGE",0,$AJ28=0,0,$AJ28>0,PRODUCT(I28,$AJ28))} -> 0 | AM28: {=_xlfn.IFS($AJ28="NO CHARGE",0,$AJ28=0,0,$AJ28>0,PRODUCT(J28,$AJ28))} -> 0 | AN28: {=_xlfn.IFS($AJ28="NO CHARGE",0,$AJ28=0,0,$AJ28>0,PRODUCT(K28,$AJ28))} -> 0 | AO28: {=_xlfn.IFS($AJ28="NO CHARGE",0,$AJ28=0,0,$AJ28>0,PRODUCT(L28,$AJ28))} -> 0 | AP28: {=_xlfn.IFS($AJ28="NO CHARGE",0,$AJ28=0,0,$AJ28>0,PRODUCT(M28,$AJ28))} -> 0 | AQ28: =SUM(AL28:AP28) -> 0 | AV28: =IF(AU28>0,PRODUCT(I28,$AU28),0) -> 0 | AW28: =IF(AV28>0,PRODUCT(J28,$AU28),0) -> 0 | AX28: =IF(AW28>0,PRODUCT(K28,$AU28),0) -> 0 | AY28: =IF(AX28>0,PRODUCT(L28,$AU28),0) -> 0 | AZ28: =IF(AY28>0,PRODUCT(M28,$AU28),0) -> 0 | BA28: =SUM(AV28:AZ28) -> 0
C29: Origination eSignature | H29: =IFERROR(AVERAGE(D29:G29),0) -> 0 | I29: =H29*12 -> 0 | J29: =IF(I29>12,(((I29)*$H$5)+I29),(I29*1)) -> 0 | K29: =IF(J29>12,(((J29)*$H$5)+J29),(J29*1)) -> 0 | L29: =IF(K29>12,(((K29)*$H$5)+K29),(K29*1)) -> 0 | M29: =IF(L29>12,(((L29)*$H$5)+L29),(L29*1)) -> 0 | P29: =Q29/12 -> 0 | Q29: =IF(O29>0,PRODUCT(I29,$O29),0) -> 0 | R29: =IF(Q29>0,PRODUCT(J29,$O29),0) -> 0 | S29: =IF(R29>0,PRODUCT(K29,$O29),0) -> 0 | T29: =IF(S29>0,PRODUCT(L29,$O29),0) -> 0 | U29: =IF(T29>0,PRODUCT(M29,$O29),0) -> 0 | V29: =SUM(Q29:U29) -> 0 | X29: =C29 -> Origination eSignature | Y29: INCLUDED | Z29: =AA29/12 -> 0 | AA29: =IF(Y29>0,PRODUCT(I29,$Y29),0) -> 0 | AB29: =IF(AA29>0,PRODUCT(J29,$Y29),0) -> 0 | AC29: =IF(AB29>0,PRODUCT(K29,$Y29),0) -> 0 | AD29: =IF(AC29>0,PRODUCT(L29,$Y29),0) -> 0 | AE29: =IF(AD29>0,PRODUCT(M29,$Y29),0) -> 0 | AF29: =SUM(AA29:AE29) -> 0 | AI29: Origination eSignature | AK29: =AL29/12 -> 0 | AL29: {=_xlfn.IFS($AJ29="NO CHARGE",0,$AJ29=0,0,$AJ29>0,PRODUCT(I29,$AJ29))} -> 0 | AM29: {=_xlfn.IFS($AJ29="NO CHARGE",0,$AJ29=0,0,$AJ29>0,PRODUCT(J29,$AJ29))} -> 0 | AN29: {=_xlfn.IFS($AJ29="NO CHARGE",0,$AJ29=0,0,$AJ29>0,PRODUCT(K29,$AJ29))} -> 0 | AO29: {=_xlfn.IFS($AJ29="NO CHARGE",0,$AJ29=0,0,$AJ29>0,PRODUCT(L29,$AJ29))} -> 0 | AP29: {=_xlfn.IFS($AJ29="NO CHARGE",0,$AJ29=0,0,$AJ29>0,PRODUCT(M29,$AJ29))} -> 0 | AQ29: =SUM(AL29:AP29) -> 0 | AV29: =IF(AU29>0,PRODUCT(I29,$AU29),0) -> 0 | AW29: =IF(AV29>0,PRODUCT(J29,$AU29),0) -> 0 | AX29: =IF(AW29>0,PRODUCT(K29,$AU29),0) -> 0 | AY29: =IF(AX29>0,PRODUCT(L29,$AU29),0) -> 0 | AZ29: =IF(AY29>0,PRODUCT(M29,$AU29),0) -> 0 | BA29: =SUM(AV29:AZ29) -> 0
C30: Relationship Management Accounts | H30: =IFERROR(AVERAGE(D30:G30),0) -> 0 | I30: =H30*12 -> 0 | J30: =IF(I30>12,(((I30)*$H$5)+I30),(I30*1)) -> 0 | K30: =IF(J30>12,(((J30)*$H$5)+J30),(J30*1)) -> 0 | L30: =IF(K30>12,(((K30)*$H$5)+K30),(K30*1)) -> 0 | M30: =IF(L30>12,(((L30)*$H$5)+L30),(L30*1)) -> 0 | P30: =Q30/12 -> 0 | Q30: =IF(O30>0,PRODUCT(I30,$O30),0) -> 0 | R30: =IF(Q30>0,PRODUCT(J30,$O30),0) -> 0 | S30: =IF(R30>0,PRODUCT(K30,$O30),0) -> 0 | T30: =IF(S30>0,PRODUCT(L30,$O30),0) -> 0 | U30: =IF(T30>0,PRODUCT(M30,$O30),0) -> 0 | V30: =SUM(Q30:U30) -> 0 | X30: =C30 -> Relationship Management Accounts | Y30: INCLUDED | Z30: =AA30/12 -> 0 | AA30: =IF(Y30>0,PRODUCT(I30,$Y30),0) -> 0 | AB30: =IF(AA30>0,PRODUCT(J30,$Y30),0) -> 0 | AC30: =IF(AB30>0,PRODUCT(K30,$Y30),0) -> 0 | AD30: =IF(AC30>0,PRODUCT(L30,$Y30),0) -> 0 | AE30: =IF(AD30>0,PRODUCT(M30,$Y30),0) -> 0 | AF30: =SUM(AA30:AE30) -> 0 | AI30: Relationship Management Accounts | AK30: =AL30/12 -> 0 | AL30: {=_xlfn.IFS($AJ30="NO CHARGE",0,$AJ30=0,0,$AJ30>0,PRODUCT(I30,$AJ30))} -> 0 | AM30: {=_xlfn.IFS($AJ30="NO CHARGE",0,$AJ30=0,0,$AJ30>0,PRODUCT(J30,$AJ30))} -> 0 | AN30: {=_xlfn.IFS($AJ30="NO CHARGE",0,$AJ30=0,0,$AJ30>0,PRODUCT(K30,$AJ30))} -> 0 | AO30: {=_xlfn.IFS($AJ30="NO CHARGE",0,$AJ30=0,0,$AJ30>0,PRODUCT(L30,$AJ30))} -> 0 | AP30: {=_xlfn.IFS($AJ30="NO CHARGE",0,$AJ30=0,0,$AJ30>0,PRODUCT(M30,$AJ30))} -> 0 | AQ30: =SUM(AL30:AP30) -> 0 | AV30: =IF(AU30>0,PRODUCT(I30,$AU30),0) -> 0 | AW30: =IF(AV30>0,PRODUCT(J30,$AU30),0) -> 0 | AX30: =IF(AW30>0,PRODUCT(K30,$AU30),0) -> 0 | AY30: =IF(AX30>0,PRODUCT(L30,$AU30),0) -> 0 | AZ30: =IF(AY30>0,PRODUCT(M30,$AU30),0) -> 0 | BA30: =SUM(AV30:AZ30) -> 0
... C33: XChange Messaging Middleware Base Fee | H33: =IFERROR(AVERAGE(D33:G33),0) -> 0 | I33: =H33*12 -> 0 | J33: =IF(I33>12,(((I33)*$H$5)+I33),(I33*1)) -> 0 | K33: =IF(J33>12,(((J33)*$H$5)+J33),(J33*1)) -> 0 | L33: =IF(K33>12,(((K33)*$H$5)+K33),(K33*1)) -> 0 | M33: =IF(L33>12,(((L33)*$H$5)+L33),(L33*1)) -> 0 | P33: =Q33/12 -> 0 | Q33: =IF(O33>0,PRODUCT(I33,$O33),0) -> 0 | R33: =IF(Q33>0,PRODUCT(J33,$O33),0) -> 0 | S33: =IF(R33>0,PRODUCT(K33,$O33),0) -> 0 | T33: =IF(S33>0,PRODUCT(L33,$O33),0) -> 0 | U33: =IF(T33>0,PRODUCT(M33,$O33),0) -> 0 | V33: =SUM(Q33:U33) -> 0 | X33: =C33 -> XChange Messaging Middleware Base Fee | Y33: INCLUDED | Z33: =AA33/12 -> 0 | AA33: =IF(Y33>0,PRODUCT(I33,$Y33),0) -> 0 | AB33: =IF(AA33>0,PRODUCT(J33,$Y33),0) -> 0 | AC33: =IF(AB33>0,PRODUCT(K33,$Y33),0) -> 0 | AD33: =IF(AC33>0,PRODUCT(L33,$Y33),0) -> 0 | AE33: =IF(AD33>0,PRODUCT(M33,$Y33),0) -> 0 | AF33: =SUM(AA33:AE33) -> 0 | AI33: XChange Messaging Middleware Base Fee | AK33: =AL33/12 -> 0 | AL33: {=_xlfn.IFS($AJ33="NO CHARGE",0,$AJ33=0,0,$AJ33>0,PRODUCT(I33,$AJ33))} -> 0 | AM33: {=_xlfn.IFS($AJ33="NO CHARGE",0,$AJ33=0,0,$AJ33>0,PRODUCT(J33,$AJ33))} -> 0 | AN33: {=_xlfn.IFS($AJ33="NO CHARGE",0,$AJ33=0,0,$AJ33>0,PRODUCT(K33,$AJ33))} -> 0 | AO33: {=_xlfn.IFS($AJ33="NO CHARGE",0,$AJ33=0,0,$AJ33>0,PRODUCT(L33,$AJ33))} -> 0 | AP33: {=_xlfn.IFS($AJ33="NO CHARGE",0,$AJ33=0,0,$AJ33>0,PRODUCT(M33,$AJ33))} -> 0 | AQ33: =SUM(AL33:AP33) -> 0 | AV33: =IF(AU33>0,PRODUCT(I33,$AU33),0) -> 0 | AW33: =IF(AV33>0,PRODUCT(J33,$AU33),0) -> 0 | AX33: =IF(AW33>0,PRODUCT(K33,$AU33),0) -> 0 | AY33: =IF(AX33>0,PRODUCT(L33,$AU33),0) -> 0 | AZ33: =IF(AY33>0,PRODUCT(M33,$AU33),0) -> 0 | BA33: =SUM(AV33:AZ33) -> 0
H34: =IFERROR(AVERAGE(D34:G34),0) -> 0 | I34: =H34*12 -> 0 | J34: =IF(I34>12,(((I34)*$H$5)+I34),(I34*1)) -> 0 | K34: =IF(J34>12,(((J34)*$H$5)+J34),(J34*1)) -> 0 | L34: =IF(K34>12,(((K34)*$H$5)+K34),(K34*1)) -> 0 | M34: =IF(L34>12,(((L34)*$H$5)+L34),(L34*1)) -> 0 | N34: =IF(C34="","",C34) | P34: =Q34/12 -> 0 | Q34: =IF(O34>0,PRODUCT(I34,$O34),0) -> 0 | R34: =IF(Q34>0,PRODUCT(J34,$O34),0) -> 0 | S34: =IF(R34>0,PRODUCT(K34,$O34),0) -> 0 | T34: =IF(S34>0,PRODUCT(L34,$O34),0) -> 0 | U34: =IF(T34>0,PRODUCT(M34,$O34),0) -> 0 | V34: =SUM(Q34:U34) -> 0 | Z34: =AA34/12 -> 0 | AA34: =IF(Y34>0,PRODUCT(I34,$Y34),0) -> 0 | AB34: =IF(AA34>0,PRODUCT(J34,$Y34),0) -> 0 | AC34: =IF(AB34>0,PRODUCT(K34,$Y34),0) -> 0 | AD34: =IF(AC34>0,PRODUCT(L34,$Y34),0) -> 0 | AE34: =IF(AD34>0,PRODUCT(M34,$Y34),0) -> 0 | AF34: =SUM(AA34:AE34) -> 0 | AK34: =AL34/12 -> 0 | AL34: {=_xlfn.IFS($AJ34="NO CHARGE",0,$AJ34=0,0,$AJ34>0,PRODUCT(I34,$AJ34))} -> 0 | AM34: {=_xlfn.IFS($AJ34="NO CHARGE",0,$AJ34=0,0,$AJ34>0,PRODUCT(J34,$AJ34))} -> 0 | AN34: {=_xlfn.IFS($AJ34="NO CHARGE",0,$AJ34=0,0,$AJ34>0,PRODUCT(K34,$AJ34))} -> 0 | AO34: {=_xlfn.IFS($AJ34="NO CHARGE",0,$AJ34=0,0,$AJ34>0,PRODUCT(L34,$AJ34))} -> 0 | AP34: {=_xlfn.IFS($AJ34="NO CHARGE",0,$AJ34=0,0,$AJ34>0,PRODUCT(M34,$AJ34))} -> 0 | AQ34: =SUM(AL34:AP34) -> 0 | AV34: =IF(AU34>0,PRODUCT(I34,$AU34),0) -> 0 | AW34: =IF(AV34>0,PRODUCT(J34,$AU34),0) -> 0 | AX34: =IF(AW34>0,PRODUCT(K34,$AU34),0) -> 0 | AY34: =IF(AX34>0,PRODUCT(L34,$AU34),0) -> 0 | AZ34: =IF(AY34>0,PRODUCT(M34,$AU34),0) -> 0 | BA34: =SUM(AV34:AZ34) -> 0
B35: Horizon Aggregated Products and Services | C35: =B35&" [QTY CALCULATIONS YOY]" -> Horizon Aggregated Products and Services [QTY CALCULATIONS YOY] | H35: 54437 | I35: =H35*12 -> 653244 | J35: =IF(I35>12,(((I35)*$H$5)+I35),(I35*1)) -> 685906.2 | K35: =IF(J35>12,(((J35)*$H$5)+J35),(J35*1)) -> 720201.51 | L35: =IF(K35>12,(((K35)*$H$5)+K35),(K35*1)) -> 756211.59 | M35: =IF(L35>12,(((L35)*$H$5)+L35),(L35*1)) -> 794022.16 | P35: =Q35/12 -> 0 | Q35: =IF(O35>0,PRODUCT(I35,$O35),0) -> 0 | R35: =IF(Q35>0,PRODUCT(J35,$O35),0) -> 0 | S35: =IF(R35>0,PRODUCT(K35,$O35),0) -> 0 | T35: =IF(S35>0,PRODUCT(L35,$O35),0) -> 0 | U35: =IF(T35>0,PRODUCT(M35,$O35),0) -> 0 | V35: =SUM(Q35:U35) -> 0 | X35: =B35&" [TIERED]" -> Horizon Aggregated Products and Services [TIERED] | Z35: =AA35/12 -> 0 | AA35: =IF(Y35>0,PRODUCT(I35,$Y35),0) -> 0 | AB35: =IF(AA35>0,PRODUCT(J35,$Y35),0) -> 0 | AC35: =IF(AB35>0,PRODUCT(K35,$Y35),0) -> 0 | AD35: =IF(AC35>0,PRODUCT(L35,$Y35),0) -> 0 | AE35: =IF(AD35>0,PRODUCT(M35,$Y35),0) -> 0 | AF35: =SUM(AA35:AE35) -> 0 | AI35: =X35 -> Horizon Aggregated Products and Services [TIERED] | AK35: =AL35/12 -> 0 | AL35: {=_xlfn.IFS($AJ35="NO CHARGE",0,$AJ35=0,0,$AJ35>0,PRODUCT(I35,$AJ35))} -> 0 | AM35: {=_xlfn.IFS($AJ35="NO CHARGE",0,$AJ35=0,0,$AJ35>0,PRODUCT(J35,$AJ35))} -> 0 | AN35: {=_xlfn.IFS($AJ35="NO CHARGE",0,$AJ35=0,0,$AJ35>0,PRODUCT(K35,$AJ35))} -> 0 | AO35: {=_xlfn.IFS($AJ35="NO CHARGE",0,$AJ35=0,0,$AJ35>0,PRODUCT(L35,$AJ35))} -> 0 | AP35: {=_xlfn.IFS($AJ35="NO CHARGE",0,$AJ35=0,0,$AJ35>0,PRODUCT(M35,$AJ35))} -> 0 | AQ35: =SUM(AL35:AP35) -> 0 | AV35: =IF(AU35>0,PRODUCT(I35,$AU35),0) -> 0 | AW35: =IF(AV35>0,PRODUCT(J35,$AU35),0) -> 0 | AX35: =IF(AW35>0,PRODUCT(K35,$AU35),0) -> 0 | AY35: =IF(AX35>0,PRODUCT(L35,$AU35),0) -> 0 | AZ35: =IF(AY35>0,PRODUCT(M35,$AU35),0) -> 0 | BA35: =SUM(AV35:AZ35) -> 0
B36: Horizon Aggregated Products and Services | C36: [Tiered] Base Monthly Processing 0 - 54,437 Accounts | H36: 54437 | I36: =IF(I35>($H36*12),$H36*12,I35) -> 653244 | J36: =IF(J35>($H36*12),$H36*12,J35) -> 653244 | K36: =IF(K35>($H36*12),$H36*12,K35) -> 653244 | L36: =IF(L35>($H36*12),$H36*12,L35) -> 653244 | M36: =IF(M35>($H36*12),$H36*12,M35) -> 653244 | P36: =Q36/12 -> 0 | Q36: =IF(O36>0,PRODUCT(I36,$O36),0) -> 0 | R36: =IF(Q36>0,PRODUCT(J36,$O36),0) -> 0 | S36: =IF(R36>0,PRODUCT(K36,$O36),0) -> 0 | T36: =IF(S36>0,PRODUCT(L36,$O36),0) -> 0 | U36: =IF(T36>0,PRODUCT(M36,$O36),0) -> 0 | V36: =SUM(Q36:U36) -> 0 | X36: =C36 -> [Tiered] Base Monthly Processing 0 - 54,437 Accounts | Y36: =2775.26/54437 -> 0.050981134 | Z36: =AA36/12 -> 2775.26 | AA36: =IF(Y36>0,PRODUCT(I36,$Y36),0) -> 33303.12 | AB36: =IF(AA36>0,PRODUCT(J36,$Y36),0) -> 33303.12 | AC36: =IF(AB36>0,PRODUCT(K36,$Y36),0) -> 33303.12 | AD36: =IF(AC36>0,PRODUCT(L36,$Y36),0) -> 33303.12 | AE36: =IF(AD36>0,PRODUCT(M36,$Y36),0) -> 33303.12 | AF36: =SUM(AA36:AE36) -> 166515.6 | AG36: WAIVED | AH36: FIS PROPOSAL MISSING PER UNIT RATE | AI36: =C36 -> [Tiered] Base Monthly Processing 0 - 54,437 Accounts | AJ36: =2775.26/54437 -> 0.050981134 | AK36: =AL36/12 -> 2775.26 | AL36: {=_xlfn.IFS($AJ36="NO CHARGE",0,$AJ36=0,0,$AJ36>0,PRODUCT(I36,$AJ36))} -> 33303.12 | AM36: {=_xlfn.IFS($AJ36="NO CHARGE",0,$AJ36=0,0,$AJ36>0,PRODUCT(J36,$AJ36))} -> 33303.12 | AN36: {=_xlfn.IFS($AJ36="NO CHARGE",0,$AJ36=0,0,$AJ36>0,PRODUCT(K36,$AJ36))} -> 33303.12 | AO36: {=_xlfn.IFS($AJ36="NO CHARGE",0,$AJ36=0,0,$AJ36>0,PRODUCT(L36,$AJ36))} -> 33303.12 | AP36: {=_xlfn.IFS($AJ36="NO CHARGE",0,$AJ36=0,0,$AJ36>0,PRODUCT(M36,$AJ36))} -> 33303.12 | AQ36: =SUM(AL36:AP36) -> 166515.6 | AR36: Waived | AS36: FIS PROPOSAL MISSING PER UNIT RATE | AV36: =IF(AU36>0,PRODUCT(I36,$AU36),0) -> 0 | AW36: =IF(AV36>0,PRODUCT(J36,$AU36),0) -> 0 | AX36: =IF(AW36>0,PRODUCT(K36,$AU36),0) -> 0 | AY36: =IF(AX36>0,PRODUCT(L36,$AU36),0) -> 0 | AZ36: =IF(AY36>0,PRODUCT(M36,$AU36),0) -> 0 | BA36: =SUM(AV36:AZ36) -> 0
B37: Horizon Aggregated Products and Services | C37: [Tiered] Base Monthly Processing 54,438 - 100k Accounts | H37: =100000-54438 -> 45562 | I37: {=_xlfn.IFS(I35>(($H36*12)+($H37*12)),$H37*12, I35<(($H36*12)+($H37*12)),I35-I36, I35=(($H36*12)+($H37*12)),I35-I36)} -> 0 | J37: {=_xlfn.IFS(J35>(($H36*12)+($H37*12)),$H37*12, J35<(($H36*12)+($H37*12)),J35-J36, J35=(($H36*12)+($H37*12)),J35-J36)} -> 32662.2 | K37: {=_xlfn.IFS(K35>(($H36*12)+($H37*12)),$H37*12, K35<(($H36*12)+($H37*12)),K35-K36, K35=(($H36*12)+($H37*12)),K35-K36)} -> 66957.51 | L37: {=_xlfn.IFS(L35>(($H36*12)+($H37*12)),$H37*12, L35<(($H36*12)+($H37*12)),L35-L36, L35=(($H36*12)+($H37*12)),L35-L36)} -> 102967.59 | M37: {=_xlfn.IFS(M35>(($H36*12)+($H37*12)),$H37*12, M35<(($H36*12)+($H37*12)),M35-M36, M35=(($H36*12)+($H37*12)),M35-M36)} -> 140778.16 | P37: =Q37/12 -> 0 | Q37: =IF(O37>0,PRODUCT(I37,$O37),0) -> 0 | R37: =IF(Q37>0,PRODUCT(J37,$O37),0) -> 0 | S37: =IF(R37>0,PRODUCT(K37,$O37),0) -> 0 | T37: =IF(S37>0,PRODUCT(L37,$O37),0) -> 0 | U37: =IF(T37>0,PRODUCT(M37,$O37),0) -> 0 | V37: =SUM(Q37:U37) -> 0 | X37: =C37 -> [Tiered] Base Monthly Processing 54,438 - 100k Accounts | Y37: 0.048 | Z37: =AA37/12 -> 0 | AA37: =IF(Y37>0,PRODUCT(I37,$Y37),0) -> 0 | AB37: {=_xlfn.IFS($AJ37="NO CHARGE",0,$AJ37=0,0,$AJ37>0,PRODUCT(J37,$AJ37))} -> 1567.7856 | AC37: =IF(AB37>0,PRODUCT(K37,$Y37),0) -> 3213.9605 | AD37: =IF(AC37>0,PRODUCT(L37,$Y37),0) -> 4942.4441 | AE37: =IF(AD37>0,PRODUCT(M37,$Y37),0) -> 6757.3519 | AF37: =SUM(AA37:AE37) -> 16481.542 | AI37: =C37 -> [Tiered] Base Monthly Processing 54,438 - 100k Accounts | AJ37: 0.048 | AK37: =AL37/12 -> 0 | AL37: {=_xlfn.IFS($AJ37="NO CHARGE",0,$AJ37=0,0,$AJ37>0,PRODUCT(I37,$AJ37))} -> 0 | AM37: {=_xlfn.IFS($AJ37="NO CHARGE",0,$AJ37=0,0,$AJ37>0,PRODUCT(J37,$AJ37))} -> 1567.7856 | AN37: {=_xlfn.IFS($AJ37="NO CHARGE",0,$AJ37=0,0,$AJ37>0,PRODUCT(K37,$AJ37))} -> 3213.9605 | AO37: {=_xlfn.IFS($AJ37="NO CHARGE",0,$AJ37=0,0,$AJ37>0,PRODUCT(L37,$AJ37))} -> 4942.4441 | AP37: {=_xlfn.IFS($AJ37="NO CHARGE",0,$AJ37=0,0,$AJ37>0,PRODUCT(M37,$AJ37))} -> 6757.3519 | AQ37: =SUM(AL37:AP37) -> 16481.542 | AV37: =IF(AU37>0,PRODUCT(I37,$AU37),0) -> 0 | AW37: =IF(AV37>0,PRODUCT(J37,$AU37),0) -> 0 | AX37: =IF(AW37>0,PRODUCT(K37,$AU37),0) -> 0 | AY37: =IF(AX37>0,PRODUCT(L37,$AU37),0) -> 0 | AZ37: =IF(AY37>0,PRODUCT(M37,$AU37),0) -> 0 | BA37: =SUM(AV37:AZ37) -> 0
B38: Horizon Aggregated Products and Services | C38: [Tiered] Base Monthly Processing beyond 100k Accounts | I38: {=_xlfn.IFS(I35>(($H36+$H37)*12),I35-I36-I37, I35<(($H36+$H37)*12),0, I35=(($H36+$H37)*12),0)} -> 0 | J38: {=_xlfn.IFS(J35>(($H36+$H37)*12),J35-J36-J37, J35<(($H36+$H37)*12),0, J35=(($H36+$H37)*12),0)} -> 0 | K38: {=_xlfn.IFS(K35>(($H36+$H37)*12),K35-K36-K37, K35<(($H36+$H37)*12),0, K35=(($H36+$H37)*12),0)} -> 0 | L38: {=_xlfn.IFS(L35>(($H36+$H37)*12),L35-L36-L37, L35<(($H36+$H37)*12),0, L35=(($H36+$H37)*12),0)} -> 0 | M38: {=_xlfn.IFS(M35>(($H36+$H37)*12),M35-M36-M37, M35<(($H36+$H37)*12),0, M35=(($H36+$H37)*12),0)} -> 0 | P38: =Q38/12 -> 0 | Q38: =IF(O38>0,PRODUCT(I38,$O38),0) -> 0 | R38: =IF(Q38>0,PRODUCT(J38,$O38),0) -> 0 | S38: =IF(R38>0,PRODUCT(K38,$O38),0) -> 0 | T38: =IF(S38>0,PRODUCT(L38,$O38),0) -> 0 | U38: =IF(T38>0,PRODUCT(M38,$O38),0) -> 0 | V38: =SUM(Q38:U38) -> 0 | X38: =C38 -> [Tiered] Base Monthly Processing beyond 100k Accounts | Y38: 0.046 | Z38: =AA38/12 -> 0 | AA38: =IF(Y38>0,PRODUCT(I38,$Y38),0) -> 0 | AB38: =IF(AA38>0,PRODUCT(J38,$Y38),0) -> 0 | AC38: =IF(AB38>0,PRODUCT(K38,$Y38),0) -> 0 | AD38: =IF(AC38>0,PRODUCT(L38,$Y38),0) -> 0 | AE38: =IF(AD38>0,PRODUCT(M38,$Y38),0) -> 0 | AF38: =SUM(AA38:AE38) -> 0 | AI38: =C38 -> [Tiered] Base Monthly Processing beyond 100k Accounts | AJ38: 0.046 | AK38: =AL38/12 -> 0 | AL38: {=_xlfn.IFS($AJ38="NO CHARGE",0,$AJ38=0,0,$AJ38>0,PRODUCT(I38,$AJ38))} -> 0 | AM38: {=_xlfn.IFS($AJ38="NO CHARGE",0,$AJ38=0,0,$AJ38>0,PRODUCT(J38,$AJ38))} -> 0 | AN38: {=_xlfn.IFS($AJ38="NO CHARGE",0,$AJ38=0,0,$AJ38>0,PRODUCT(K38,$AJ38))} -> 0 | AO38: {=_xlfn.IFS($AJ38="NO CHARGE",0,$AJ38=0,0,$AJ38>0,PRODUCT(L38,$AJ38))} -> 0 | AP38: {=_xlfn.IFS($AJ38="NO CHARGE",0,$AJ38=0,0,$AJ38>0,PRODUCT(M38,$AJ38))} -> 0 | AQ38: =SUM(AL38:AP38) -> 0 | AV38: =IF(AU38>0,PRODUCT(I38,$AU38),0) -> 0 | AW38: =IF(AV38>0,PRODUCT(J38,$AU38),0) -> 0 | AX38: =IF(AW38>0,PRODUCT(K38,$AU38),0) -> 0 | AY38: =IF(AX38>0,PRODUCT(L38,$AU38),0) -> 0 | AZ38: =IF(AY38>0,PRODUCT(M38,$AU38),0) -> 0 | BA38: =SUM(AV38:AZ38) -> 0
H39: =IFERROR(AVERAGE(D39:G39),0) -> 0 | I39: =H39*12 -> 0 | J39: =IF(I39>12,(((I39)*$H$5)+I39),(I39*1)) -> 0 | K39: =IF(J39>12,(((J39)*$H$5)+J39),(J39*1)) -> 0 | L39: =IF(K39>12,(((K39)*$H$5)+K39),(K39*1)) -> 0 | M39: =IF(L39>12,(((L39)*$H$5)+L39),(L39*1)) -> 0 | P39: =Q39/12 -> 0 | Q39: =IF(O39>0,PRODUCT(I39,$O39),0) -> 0 | R39: =IF(Q39>0,PRODUCT(J39,$O39),0) -> 0 | S39: =IF(R39>0,PRODUCT(K39,$O39),0) -> 0 | T39: =IF(S39>0,PRODUCT(L39,$O39),0) -> 0 | U39: =IF(T39>0,PRODUCT(M39,$O39),0) -> 0 | V39: =SUM(Q39:U39) -> 0 | Z39: =AA39/12 -> 0 | AA39: =IF(Y39>0,PRODUCT(I39,$Y39),0) -> 0 | AB39: =IF(AA39>0,PRODUCT(J39,$Y39),0) -> 0 | AC39: =IF(AB39>0,PRODUCT(K39,$Y39),0) -> 0 | AD39: =IF(AC39>0,PRODUCT(L39,$Y39),0) -> 0 | AE39: =IF(AD39>0,PRODUCT(M39,$Y39),0) -> 0 | AF39: =SUM(AA39:AE39) -> 0 | AK39: =AL39/12 -> 0 | AL39: {=_xlfn.IFS($AJ39="NO CHARGE",0,$AJ39=0,0,$AJ39>0,PRODUCT(I39,$AJ39))} -> 0 | AM39: {=_xlfn.IFS($AJ39="NO CHARGE",0,$AJ39=0,0,$AJ39>0,PRODUCT(J39,$AJ39))} -> 0 | AN39: {=_xlfn.IFS($AJ39="NO CHARGE",0,$AJ39=0,0,$AJ39>0,PRODUCT(K39,$AJ39))} -> 0 | AO39: {=_xlfn.IFS($AJ39="NO CHARGE",0,$AJ39=0,0,$AJ39>0,PRODUCT(L39,$AJ39))} -> 0 | AP39: {=_xlfn.IFS($AJ39="NO CHARGE",0,$AJ39=0,0,$AJ39>0,PRODUCT(M39,$AJ39))} -> 0 | AQ39: =SUM(AL39:AP39) -> 0 | AV39: =IF(AU39>0,PRODUCT(I39,$AU39),0) -> 0 | AW39: =IF(AV39>0,PRODUCT(J39,$AU39),0) -> 0 | AX39: =IF(AW39>0,PRODUCT(K39,$AU39),0) -> 0 | AY39: =IF(AX39>0,PRODUCT(L39,$AU39),0) -> 0 | AZ39: =IF(AY39>0,PRODUCT(M39,$AU39),0) -> 0 | BA39: =SUM(AV39:AZ39) -> 0
B40: Horizon Aggregated Products and Services | C40: ACH Activity | H40: 10611 | I40: =H40*12 -> 127332 | J40: =IF(I40>12,(((I40)*$H$5)+I40),(I40*1)) -> 133698.6 | K40: =IF(J40>12,(((J40)*$H$5)+J40),(J40*1)) -> 140383.53 | L40: =IF(K40>12,(((K40)*$H$5)+K40),(K40*1)) -> 147402.71 | M40: =IF(L40>12,(((L40)*$H$5)+L40),(L40*1)) -> 154772.84 | P40: =Q40/12 -> 0 | Q40: =IF(O40>0,PRODUCT(I40,$O40),0) -> 0 | R40: =IF(Q40>0,PRODUCT(J40,$O40),0) -> 0 | S40: =IF(R40>0,PRODUCT(K40,$O40),0) -> 0 | T40: =IF(S40>0,PRODUCT(L40,$O40),0) -> 0 | U40: =IF(T40>0,PRODUCT(M40,$O40),0) -> 0 | V40: =SUM(Q40:U40) -> 0 | X40: =C40 -> ACH Activity | Y40: 0.005 | Z40: =AA40/12 -> 53.055 | AA40: =IF(Y40>0,PRODUCT(I40,$Y40),0) -> 636.66 | AB40: =IF(AA40>0,PRODUCT(J40,$Y40),0) -> 668.493 | AC40: =IF(AB40>0,PRODUCT(K40,$Y40),0) -> 701.91765 | AD40: =IF(AC40>0,PRODUCT(L40,$Y40),0) -> 737.01353 | AE40: =IF(AD40>0,PRODUCT(M40,$Y40),0) -> 773.86421 | AF40: =SUM(AA40:AE40) -> 3517.9484 | AI40: =C40 -> ACH Activity | AJ40: 0.005 | AK40: =AL40/12 -> 53.055 | AL40: {=_xlfn.IFS($AJ40="NO CHARGE",0,$AJ40=0,0,$AJ40>0,PRODUCT(I40,$AJ40))} -> 636.66 | AM40: {=_xlfn.IFS($AJ40="NO CHARGE",0,$AJ40=0,0,$AJ40>0,PRODUCT(J40,$AJ40))} -> 668.493 | AN40: {=_xlfn.IFS($AJ40="NO CHARGE",0,$AJ40=0,0,$AJ40>0,PRODUCT(K40,$AJ40))} -> 701.91765 | AO40: {=_xlfn.IFS($AJ40="NO CHARGE",0,$AJ40=0,0,$AJ40>0,PRODUCT(L40,$AJ40))} -> 737.01353 | AP40: {=_xlfn.IFS($AJ40="NO CHARGE",0,$AJ40=0,0,$AJ40>0,PRODUCT(M40,$AJ40))} -> 773.86421 | AQ40: =SUM(AL40:AP40) -> 3517.9484 | AV40: =IF(AU40>0,PRODUCT(I40,$AU40),0) -> 0 | AW40: =IF(AV40>0,PRODUCT(J40,$AU40),0) -> 0 | AX40: =IF(AW40>0,PRODUCT(K40,$AU40),0) -> 0 | AY40: =IF(AX40>0,PRODUCT(L40,$AU40),0) -> 0 | AZ40: =IF(AY40>0,PRODUCT(M40,$AU40),0) -> 0 | BA40: =SUM(AV40:AZ40) -> 0
B41: Horizon Aggregated Products and Services | C41: Same Day ACH Settlement | H41: 1 | I41: =H41*12 -> 12 | J41: =IF(I41>12,(((I41)*$H$5)+I41),(I41*1)) -> 12 | K41: =IF(J41>12,(((J41)*$H$5)+J41),(J41*1)) -> 12 | L41: =IF(K41>12,(((K41)*$H$5)+K41),(K41*1)) -> 12 | M41: =IF(L41>12,(((L41)*$H$5)+L41),(L41*1)) -> 12 | P41: =Q41/12 -> 0 | Q41: =IF(O41>0,PRODUCT(I41,$O41),0) -> 0 | R41: =IF(Q41>0,PRODUCT(J41,$O41),0) -> 0 | S41: =IF(R41>0,PRODUCT(K41,$O41),0) -> 0 | T41: =IF(S41>0,PRODUCT(L41,$O41),0) -> 0 | U41: =IF(T41>0,PRODUCT(M41,$O41),0) -> 0 | V41: =SUM(Q41:U41) -> 0 | X41: =C41 -> Same Day ACH Settlement | Y41: 0.01 | Z41: =AA41/12 -> 0.01 | AA41: =IF(Y41>0,PRODUCT(I41,$Y41),0) -> 0.12 | AB41: =IF(AA41>0,PRODUCT(J41,$Y41),0) -> 0.12 | AC41: =IF(AB41>0,PRODUCT(K41,$Y41),0) -> 0.12 | AD41: =IF(AC41>0,PRODUCT(L41,$Y41),0) -> 0.12 | AE41: =IF(AD41>0,PRODUCT(M41,$Y41),0) -> 0.12 | AF41: =IF((SUM(AA41:AE41))<(Y42*60),0,(SUM(AA41:AE41))) -> 0 | AG41: WAIVED | AI41: =C41 -> Same Day ACH Settlement | AJ41: 0.01 | AK41: =AL41/12 -> 0.01 | AL41: {=_xlfn.IFS($AJ41="NO CHARGE",0,$AJ41=0,0,$AJ41>0,PRODUCT(I41,$AJ41))} -> 0.12 | AM41: {=_xlfn.IFS($AJ41="NO CHARGE",0,$AJ41=0,0,$AJ41>0,PRODUCT(J41,$AJ41))} -> 0.12 | AN41: {=_xlfn.IFS($AJ41="NO CHARGE",0,$AJ41=0,0,$AJ41>0,PRODUCT(K41,$AJ41))} -> 0.12 | AO41: {=_xlfn.IFS($AJ41="NO CHARGE",0,$AJ41=0,0,$AJ41>0,PRODUCT(L41,$AJ41))} -> 0.12 | AP41: {=_xlfn.IFS($AJ41="NO CHARGE",0,$AJ41=0,0,$AJ41>0,PRODUCT(M41,$AJ41))} -> 0.12 | AQ41: =IF((SUM(AL41:AP41))<(AJ42*60),0,(SUM(AL41:AP41))) -> 0 | AR41: Waived | AV41: =IF(AU41>0,PRODUCT(I41,$AU41),0) -> 0 | AW41: =IF(AV41>0,PRODUCT(J41,$AU41),0) -> 0 | AX41: =IF(AW41>0,PRODUCT(K41,$AU41),0) -> 0 | AY41: =IF(AX41>0,PRODUCT(L41,$AU41),0) -> 0 | AZ41: =IF(AY41>0,PRODUCT(M41,$AU41),0) -> 0 | BA41: =SUM(AV41:AZ41) -> 0
B42: Horizon Aggregated Products and Services | C42: Same Day ACH Settlement Monthly Minimum | H42: 1 | I42: =H42*12 -> 12 | J42: =IF(I42>12,(((I42)*$H$5)+I42),(I42*1)) -> 12 | K42: =IF(J42>12,(((J42)*$H$5)+J42),(J42*1)) -> 12 | L42: =IF(K42>12,(((K42)*$H$5)+K42),(K42*1)) -> 12 | M42: =IF(L42>12,(((L42)*$H$5)+L42),(L42*1)) -> 12 | P42: =Q42/12 -> 0 | Q42: =IF(O42>0,PRODUCT(I42,$O42),0) -> 0 | R42: =IF(Q42>0,PRODUCT(J42,$O42),0) -> 0 | S42: =IF(R42>0,PRODUCT(K42,$O42),0) -> 0 | T42: =IF(S42>0,PRODUCT(L42,$O42),0) -> 0 | U42: =IF(T42>0,PRODUCT(M42,$O42),0) -> 0 | V42: =SUM(Q42:U42) -> 0 | X42: =C42 -> Same Day ACH Settlement Monthly Minimum | Y42: 250 | Z42: =AA42/12 -> 250 | AA42: =IF(Y42>0,PRODUCT(I42,$Y42),0) -> 3000 | AB42: =IF(AA42>0,PRODUCT(J42,$Y42),0) -> 3000 | AC42: =IF(AB42>0,PRODUCT(K42,$Y42),0) -> 3000 | AD42: =IF(AC42>0,PRODUCT(L42,$Y42),0) -> 3000 | AE42: =IF(AD42>0,PRODUCT(M42,$Y42),0) -> 3000 | AF42: =IF((SUM(AA42:AE42))<(SUM(AA41:AE41)), 0, SUM(AA42:AE42)) -> 15000 | AH42: Monthly Minimum Item | AI42: =C42 -> Same Day ACH Settlement Monthly Minimum | AJ42: 250 | AK42: =AL42/12 -> 250 | AL42: {=_xlfn.IFS($AJ42="NO CHARGE",0,$AJ42=0,0,$AJ42>0,PRODUCT(I42,$AJ42))} -> 3000 | AM42: {=_xlfn.IFS($AJ42="NO CHARGE",0,$AJ42=0,0,$AJ42>0,PRODUCT(J42,$AJ42))} -> 3000 | AN42: {=_xlfn.IFS($AJ42="NO CHARGE",0,$AJ42=0,0,$AJ42>0,PRODUCT(K42,$AJ42))} -> 3000 | AO42: {=_xlfn.IFS($AJ42="NO CHARGE",0,$AJ42=0,0,$AJ42>0,PRODUCT(L42,$AJ42))} -> 3000 | AP42: {=_xlfn.IFS($AJ42="NO CHARGE",0,$AJ42=0,0,$AJ42>0,PRODUCT(M42,$AJ42))} -> 3000 | AQ42: =IF((SUM(AL42:AP42))<(SUM(AL41:AP41)), 0, SUM(AL42:AP42)) -> 15000 | AS42: Monthly Minimum Item | AV42: =IF(AU42>0,PRODUCT(I42,$AU42),0) -> 0 | AW42: =IF(AV42>0,PRODUCT(J42,$AU42),0) -> 0 | AX42: =IF(AW42>0,PRODUCT(K42,$AU42),0) -> 0 | AY42: =IF(AX42>0,PRODUCT(L42,$AU42),0) -> 0 | AZ42: =IF(AY42>0,PRODUCT(M42,$AU42),0) -> 0 | BA42: =SUM(AV42:AZ42) -> 0
B43: Horizon Aggregated Products and Services | C43: Deposit Origination (DO) CSi Simplicity Hosting | H43: 1 | I43: =H43*12 -> 12 | J43: =IF(I43>12,(((I43)*$H$5)+I43),(I43*1)) -> 12 | K43: =IF(J43>12,(((J43)*$H$5)+J43),(J43*1)) -> 12 | L43: =IF(K43>12,(((K43)*$H$5)+K43),(K43*1)) -> 12 | M43: =IF(L43>12,(((L43)*$H$5)+L43),(L43*1)) -> 12 | P43: =Q43/12 -> 0 | Q43: =IF(O43>0,PRODUCT(I43,$O43),0) -> 0 | R43: =IF(Q43>0,PRODUCT(J43,$O43),0) -> 0 | S43: =IF(R43>0,PRODUCT(K43,$O43),0) -> 0 | T43: =IF(S43>0,PRODUCT(L43,$O43),0) -> 0 | U43: =IF(T43>0,PRODUCT(M43,$O43),0) -> 0 | V43: =SUM(Q43:U43) -> 0 | X43: =C43 -> Deposit Origination (DO) CSi Simplicity Hosting | Y43: 120 | Z43: =AA43/12 -> 120 | AA43: =IF(Y43>0,PRODUCT(I43,$Y43),0) -> 1440 | AB43: =IF(AA43>0,PRODUCT(J43,$Y43),0) -> 1440 | AC43: =IF(AB43>0,PRODUCT(K43,$Y43),0) -> 1440 | AD43: =IF(AC43>0,PRODUCT(L43,$Y43),0) -> 1440 | AE43: =IF(AD43>0,PRODUCT(M43,$Y43),0) -> 1440 | AF43: =SUM(AA43:AE43) -> 7200 | AG43: WAIVED | AI43: =C43 -> Deposit Origination (DO) CSi Simplicity Hosting | AJ43: 120 | AK43: =AL43/12 -> 120 | AL43: {=_xlfn.IFS($AJ43="NO CHARGE",0,$AJ43=0,0,$AJ43>0,PRODUCT(I43,$AJ43))} -> 1440 | AM43: {=_xlfn.IFS($AJ43="NO CHARGE",0,$AJ43=0,0,$AJ43>0,PRODUCT(J43,$AJ43))} -> 1440 | AN43: {=_xlfn.IFS($AJ43="NO CHARGE",0,$AJ43=0,0,$AJ43>0,PRODUCT(K43,$AJ43))} -> 1440 | AO43: {=_xlfn.IFS($AJ43="NO CHARGE",0,$AJ43=0,0,$AJ43>0,PRODUCT(L43,$AJ43))} -> 1440 | AP43: {=_xlfn.IFS($AJ43="NO CHARGE",0,$AJ43=0,0,$AJ43>0,PRODUCT(M43,$AJ43))} -> 1440 | AQ43: =SUM(AL43:AP43) -> 7200 | AR43: Waived | AV43: =IF(AU43>0,PRODUCT(I43,$AU43),0) -> 0 | AW43: =IF(AV43>0,PRODUCT(J43,$AU43),0) -> 0 | AX43: =IF(AW43>0,PRODUCT(K43,$AU43),0) -> 0 | AY43: =IF(AX43>0,PRODUCT(L43,$AU43),0) -> 0 | AZ43: =IF(AY43>0,PRODUCT(M43,$AU43),0) -> 0 | BA43: =SUM(AV43:AZ43) -> 0
B44: Horizon Aggregated Products and Services | C44: Deposit Origination (DO) SmartSign | H44: 1 | I44: =H44*12 -> 12 | J44: =IF(I44>12,(((I44)*$H$5)+I44),(I44*1)) -> 12 | K44: =IF(J44>12,(((J44)*$H$5)+J44),(J44*1)) -> 12 | L44: =IF(K44>12,(((K44)*$H$5)+K44),(K44*1)) -> 12 | M44: =IF(L44>12,(((L44)*$H$5)+L44),(L44*1)) -> 12 | P44: =Q44/12 -> 0 | Q44: =IF(O44>0,PRODUCT(I44,$O44),0) -> 0 | R44: =IF(Q44>0,PRODUCT(J44,$O44),0) -> 0 | S44: =IF(R44>0,PRODUCT(K44,$O44),0) -> 0 | T44: =IF(S44>0,PRODUCT(L44,$O44),0) -> 0 | U44: =IF(T44>0,PRODUCT(M44,$O44),0) -> 0 | V44: =SUM(Q44:U44) -> 0 | X44: =C44 -> Deposit Origination (DO) SmartSign | Y44: 1531.2 | Z44: =AA44/12 -> 1531.2 | AA44: =IF(Y44>0,PRODUCT(I44,$Y44),0) -> 18374.4 | AB44: =IF(AA44>0,PRODUCT(J44,$Y44),0) -> 18374.4 | AC44: =IF(AB44>0,PRODUCT(K44,$Y44),0) -> 18374.4 | AD44: =IF(AC44>0,PRODUCT(L44,$Y44),0) -> 18374.4 | AE44: =IF(AD44>0,PRODUCT(M44,$Y44),0) -> 18374.4 | AF44: =SUM(AA44:AE44) -> 91872 | AG44: 9000 | AI44: =C44 -> Deposit Origination (DO) SmartSign | AJ44: 1531.2 | AK44: =AL44/12 -> 1531.2 | AL44: {=_xlfn.IFS($AJ44="NO CHARGE",0,$AJ44=0,0,$AJ44>0,PRODUCT(I44,$AJ44))} -> 18374.4 | AM44: {=_xlfn.IFS($AJ44="NO CHARGE",0,$AJ44=0,0,$AJ44>0,PRODUCT(J44,$AJ44))} -> 18374.4 | AN44: {=_xlfn.IFS($AJ44="NO CHARGE",0,$AJ44=0,0,$AJ44>0,PRODUCT(K44,$AJ44))} -> 18374.4 | AO44: {=_xlfn.IFS($AJ44="NO CHARGE",0,$AJ44=0,0,$AJ44>0,PRODUCT(L44,$AJ44))} -> 18374.4 | AP44: {=_xlfn.IFS($AJ44="NO CHARGE",0,$AJ44=0,0,$AJ44>0,PRODUCT(M44,$AJ44))} -> 18374.4 | AQ44: =SUM(AL44:AP44) -> 91872 | AR44: 9000 | AV44: =IF(AU44>0,PRODUCT(I44,$AU44),0) -> 0 | AW44: =IF(AV44>0,PRODUCT(J44,$AU44),0) -> 0 | AX44: =IF(AW44>0,PRODUCT(K44,$AU44),0) -> 0 | AY44: =IF(AX44>0,PRODUCT(L44,$AU44),0) -> 0 | AZ44: =IF(AY44>0,PRODUCT(M44,$AU44),0) -> 0 | BA44: =SUM(AV44:AZ44) -> 0
B45: Horizon Aggregated Products and Services | C45: Horizon 360 BI Enterprise License | H45: 1 | I45: =H45*12 -> 12 | J45: =IF(I45>12,(((I45)*$H$5)+I45),(I45*1)) -> 12 | K45: =IF(J45>12,(((J45)*$H$5)+J45),(J45*1)) -> 12 | L45: =IF(K45>12,(((K45)*$H$5)+K45),(K45*1)) -> 12 | M45: =IF(L45>12,(((L45)*$H$5)+L45),(L45*1)) -> 12 | N45: =IF(C45="","",C45) -> Horizon 360 BI Enterprise License | P45: =Q45/12 -> 0 | Q45: =IF(O45>0,PRODUCT(I45,$O45),0) -> 0 | R45: =IF(Q45>0,PRODUCT(J45,$O45),0) -> 0 | S45: =IF(R45>0,PRODUCT(K45,$O45),0) -> 0 | T45: =IF(S45>0,PRODUCT(L45,$O45),0) -> 0 | U45: =IF(T45>0,PRODUCT(M45,$O45),0) -> 0 | V45: =SUM(Q45:U45) -> 0 | X45: =C45 -> Horizon 360 BI Enterprise License | Y45: 1350 | Z45: =AA45/12 -> 1350 | AA45: =IF(Y45>0,PRODUCT(I45,$Y45),0) -> 16200 | AB45: =IF(AA45>0,PRODUCT(J45,$Y45),0) -> 16200 | AC45: =IF(AB45>0,PRODUCT(K45,$Y45),0) -> 16200 | AD45: =IF(AC45>0,PRODUCT(L45,$Y45),0) -> 16200 | AE45: =IF(AD45>0,PRODUCT(M45,$Y45),0) -> 16200 | AF45: =SUM(AA45:AE45) -> 81000 | AG45: 19159 | AI45: =C45 -> Horizon 360 BI Enterprise License | AJ45: 1350 | AK45: =AL45/12 -> 1350 | AL45: {=_xlfn.IFS($AJ45="NO CHARGE",0,$AJ45=0,0,$AJ45>0,PRODUCT(I45,$AJ45))} -> 16200 | AM45: {=_xlfn.IFS($AJ45="NO CHARGE",0,$AJ45=0,0,$AJ45>0,PRODUCT(J45,$AJ45))} -> 16200 | AN45: {=_xlfn.IFS($AJ45="NO CHARGE",0,$AJ45=0,0,$AJ45>0,PRODUCT(K45,$AJ45))} -> 16200 | AO45: {=_xlfn.IFS($AJ45="NO CHARGE",0,$AJ45=0,0,$AJ45>0,PRODUCT(L45,$AJ45))} -> 16200 | AP45: {=_xlfn.IFS($AJ45="NO CHARGE",0,$AJ45=0,0,$AJ45>0,PRODUCT(M45,$AJ45))} -> 16200 | AQ45: =SUM(AL45:AP45) -> 81000 | AR45: 19159 | AV45: =IF(AU45>0,PRODUCT(I45,$AU45),0) -> 0 | AW45: =IF(AV45>0,PRODUCT(J45,$AU45),0) -> 0 | AX45: =IF(AW45>0,PRODUCT(K45,$AU45),0) -> 0 | AY45: =IF(AX45>0,PRODUCT(L45,$AU45),0) -> 0 | AZ45: =IF(AY45>0,PRODUCT(M45,$AU45),0) -> 0 | BA45: =SUM(AV45:AZ45) -> 0
B46: Horizon Aggregated Products and Services | C46: Horizon 360 BI Web Administrator | H46: 1 | I46: =H46*12 -> 12 | J46: =IF(I46>12,(((I46)*$H$5)+I46),(I46*1)) -> 12 | K46: =IF(J46>12,(((J46)*$H$5)+J46),(J46*1)) -> 12 | L46: =IF(K46>12,(((K46)*$H$5)+K46),(K46*1)) -> 12 | M46: =IF(L46>12,(((L46)*$H$5)+L46),(L46*1)) -> 12 | N46: =IF(C46="","",C46) -> Horizon 360 BI Web Administrator | P46: =Q46/12 -> 0 | Q46: =IF(O46>0,PRODUCT(I46,$O46),0) -> 0 | R46: =IF(Q46>0,PRODUCT(J46,$O46),0) -> 0 | S46: =IF(R46>0,PRODUCT(K46,$O46),0) -> 0 | T46: =IF(S46>0,PRODUCT(L46,$O46),0) -> 0 | U46: =IF(T46>0,PRODUCT(M46,$O46),0) -> 0 | V46: =SUM(Q46:U46) -> 0 | X46: =C46 -> Horizon 360 BI Web Administrator | Y46: 469 | Z46: =AA46/12 -> 469 | AA46: =IF(Y46>0,PRODUCT(I46,$Y46),0) -> 5628 | AB46: =IF(AA46>0,PRODUCT(J46,$Y46),0) -> 5628 | AC46: =IF(AB46>0,PRODUCT(K46,$Y46),0) -> 5628 | AD46: =IF(AC46>0,PRODUCT(L46,$Y46),0) -> 5628 | AE46: =IF(AD46>0,PRODUCT(M46,$Y46),0) -> 5628 | AF46: =SUM(AA46:AE46) -> 28140 | AG46: 11250 | AI46: =C46 -> Horizon 360 BI Web Administrator | AJ46: 469 | AK46: =AL46/12 -> 469 | AL46: {=_xlfn.IFS($AJ46="NO CHARGE",0,$AJ46=0,0,$AJ46>0,PRODUCT(I46,$AJ46))} -> 5628 | AM46: {=_xlfn.IFS($AJ46="NO CHARGE",0,$AJ46=0,0,$AJ46>0,PRODUCT(J46,$AJ46))} -> 5628 | AN46: {=_xlfn.IFS($AJ46="NO CHARGE",0,$AJ46=0,0,$AJ46>0,PRODUCT(K46,$AJ46))} -> 5628 | AO46: {=_xlfn.IFS($AJ46="NO CHARGE",0,$AJ46=0,0,$AJ46>0,PRODUCT(L46,$AJ46))} -> 5628 | AP46: {=_xlfn.IFS($AJ46="NO CHARGE",0,$AJ46=0,0,$AJ46>0,PRODUCT(M46,$AJ46))} -> 5628 | AQ46: =SUM(AL46:AP46) -> 28140 | AR46: 11250 | AV46: =IF(AU46>0,PRODUCT(I46,$AU46),0) -> 0 | AW46: =IF(AV46>0,PRODUCT(J46,$AU46),0) -> 0 | AX46: =IF(AW46>0,PRODUCT(K46,$AU46),0) -> 0 | AY46: =IF(AX46>0,PRODUCT(L46,$AU46),0) -> 0 | AZ46: =IF(AY46>0,PRODUCT(M46,$AU46),0) -> 0 | BA46: =SUM(AV46:AZ46) -> 0
H47: =IFERROR(AVERAGE(D47:G47),0) -> 0 | I47: =H47*12 -> 0 | J47: =IF(I47>12,(((I47)*$H$5)+I47),(I47*1)) -> 0 | K47: =IF(J47>12,(((J47)*$H$5)+J47),(J47*1)) -> 0 | L47: =IF(K47>12,(((K47)*$H$5)+K47),(K47*1)) -> 0 | M47: =IF(L47>12,(((L47)*$H$5)+L47),(L47*1)) -> 0 | N47: =IF(C47="","",C47) | P47: =Q47/12 -> 0 | Q47: =IF(O47>0,PRODUCT(I47,$O47),0) -> 0 | R47: =IF(Q47>0,PRODUCT(J47,$O47),0) -> 0 | S47: =IF(R47>0,PRODUCT(K47,$O47),0) -> 0 | T47: =IF(S47>0,PRODUCT(L47,$O47),0) -> 0 | U47: =IF(T47>0,PRODUCT(M47,$O47),0) -> 0 | V47: =SUM(Q47:U47) -> 0 | Z47: =AA47/12 -> 0 | AA47: =IF(Y47>0,PRODUCT(I47,$Y47),0) -> 0 | AB47: =IF(AA47>0,PRODUCT(J47,$Y47),0) -> 0 | AC47: =IF(AB47>0,PRODUCT(K47,$Y47),0) -> 0 | AD47: =IF(AC47>0,PRODUCT(L47,$Y47),0) -> 0 | AE47: =IF(AD47>0,PRODUCT(M47,$Y47),0) -> 0 | AF47: =SUM(AA47:AE47) -> 0 | AK47: =AL47/12 -> 0 | AL47: {=_xlfn.IFS($AJ47="NO CHARGE",0,$AJ47=0,0,$AJ47>0,PRODUCT(I47,$AJ47))} -> 0 | AM47: {=_xlfn.IFS($AJ47="NO CHARGE",0,$AJ47=0,0,$AJ47>0,PRODUCT(J47,$AJ47))} -> 0 | AN47: {=_xlfn.IFS($AJ47="NO CHARGE",0,$AJ47=0,0,$AJ47>0,PRODUCT(K47,$AJ47))} -> 0 | AO47: {=_xlfn.IFS($AJ47="NO CHARGE",0,$AJ47=0,0,$AJ47>0,PRODUCT(L47,$AJ47))} -> 0 | AP47: {=_xlfn.IFS($AJ47="NO CHARGE",0,$AJ47=0,0,$AJ47>0,PRODUCT(M47,$AJ47))} -> 0 | AQ47: =SUM(AL47:AP47) -> 0 | AV47: =IF(AU47>0,PRODUCT(I47,$AU47),0) -> 0 | AW47: =IF(AV47>0,PRODUCT(J47,$AU47),0) -> 0 | AX47: =IF(AW47>0,PRODUCT(K47,$AU47),0) -> 0 | AY47: =IF(AX47>0,PRODUCT(L47,$AU47),0) -> 0 | AZ47: =IF(AY47>0,PRODUCT(M47,$AU47),0) -> 0 | BA47: =SUM(AV47:AZ47) -> 0
H48: =IFERROR(AVERAGE(D48:G48),0) -> 0 | I48: =H48*12 -> 0 | J48: =IF(I48>12,(((I48)*$H$5)+I48),(I48*1)) -> 0 | K48: =IF(J48>12,(((J48)*$H$5)+J48),(J48*1)) -> 0 | L48: =IF(K48>12,(((K48)*$H$5)+K48),(K48*1)) -> 0 | M48: =IF(L48>12,(((L48)*$H$5)+L48),(L48*1)) -> 0 | N48: =IF(C48="","",C48) | P48: =Q48/12 -> 0 | Q48: =IF(O48>0,PRODUCT(I48,$O48),0) -> 0 | R48: =IF(Q48>0,PRODUCT(J48,$O48),0) -> 0 | S48: =IF(R48>0,PRODUCT(K48,$O48),0) -> 0 | T48: =IF(S48>0,PRODUCT(L48,$O48),0) -> 0 | U48: =IF(T48>0,PRODUCT(M48,$O48),0) -> 0 | V48: =SUM(Q48:U48) -> 0 | Z48: =AA48/12 -> 0 | AA48: =IF(Y48>0,PRODUCT(I48,$Y48),0) -> 0 | AB48: =IF(AA48>0,PRODUCT(J48,$Y48),0) -> 0 | AC48: =IF(AB48>0,PRODUCT(K48,$Y48),0) -> 0 | AD48: =IF(AC48>0,PRODUCT(L48,$Y48),0) -> 0 | AE48: =IF(AD48>0,PRODUCT(M48,$Y48),0) -> 0 | AF48: =SUM(AA48:AE48) -> 0 | AK48: =AL48/12 -> 0 | AL48: {=_xlfn.IFS($AJ48="NO CHARGE",0,$AJ48=0,0,$AJ48>0,PRODUCT(I48,$AJ48))} -> 0 | AM48: {=_xlfn.IFS($AJ48="NO CHARGE",0,$AJ48=0,0,$AJ48>0,PRODUCT(J48,$AJ48))} -> 0 | AN48: {=_xlfn.IFS($AJ48="NO CHARGE",0,$AJ48=0,0,$AJ48>0,PRODUCT(K48,$AJ48))} -> 0 | AO48: {=_xlfn.IFS($AJ48="NO CHARGE",0,$AJ48=0,0,$AJ48>0,PRODUCT(L48,$AJ48))} -> 0 | AP48: {=_xlfn.IFS($AJ48="NO CHARGE",0,$AJ48=0,0,$AJ48>0,PRODUCT(M48,$AJ48))} -> 0 | AQ48: =SUM(AL48:AP48) -> 0 | AV48: =IF(AU48>0,PRODUCT(I48,$AU48),0) -> 0 | AW48: =IF(AV48>0,PRODUCT(J48,$AU48),0) -> 0 | AX48: =IF(AW48>0,PRODUCT(K48,$AU48),0) -> 0 | AY48: =IF(AX48>0,PRODUCT(L48,$AU48),0) -> 0 | AZ48: =IF(AY48>0,PRODUCT(M48,$AU48),0) -> 0 | BA48: =SUM(AV48:AZ48) -> 0
B49: =C49 -> Third Party Interfaces: | C49: Third Party Interfaces: | N49: =C49 -> Third Party Interfaces: | X49: =C49 -> Third Party Interfaces: | AI49: =C49 -> Third Party Interfaces: | AQ49: =SUM(AL49:AP49) -> 0 | AT49: =C49 -> Third Party Interfaces:
C50: Equifax Cash Management | D50: 1 | E50: 1 | F50: 1 | G50: 1 | H50: =IFERROR(AVERAGE(D50:G50),0) -> 1 | I50: =H50*12 -> 12 | J50: =IF(I50>12,(((I50)*$H$5)+I50),(I50*1)) -> 12 | K50: =IF(J50>12,(((J50)*$H$5)+J50),(J50*1)) -> 12 | L50: =IF(K50>12,(((K50)*$H$5)+K50),(K50*1)) -> 12 | M50: =IF(L50>12,(((L50)*$H$5)+L50),(L50*1)) -> 12 | N50: =IF(C50="","",C50) -> Equifax Cash Management | O50: 45.833333 | P50: =Q50/12 -> 45.833333 | Q50: =IF(O50>0,PRODUCT(I50,$O50),0) -> 550 | R50: =IF(Q50>0,PRODUCT(J50,$O50),0) -> 550 | S50: =IF(R50>0,PRODUCT(K50,$O50),0) -> 550 | T50: =IF(S50>0,PRODUCT(L50,$O50),0) -> 550 | U50: =IF(T50>0,PRODUCT(M50,$O50),0) -> 550 | V50: =SUM(Q50:U50) -> 2750 | Z50: =AA50/12 -> 0 | AA50: =IF(Y50>0,PRODUCT(I50,$Y50),0) -> 0 | AB50: =IF(AA50>0,PRODUCT(J50,$Y50),0) -> 0 | AC50: =IF(AB50>0,PRODUCT(K50,$Y50),0) -> 0 | AD50: =IF(AC50>0,PRODUCT(L50,$Y50),0) -> 0 | AE50: =IF(AD50>0,PRODUCT(M50,$Y50),0) -> 0 | AF50: =SUM(AA50:AE50) -> 0 | AK50: =AL50/12 -> 0 | AL50: {=_xlfn.IFS($AJ50="NO CHARGE",0,$AJ50=0,0,$AJ50>0,PRODUCT(I50,$AJ50))} -> 0 | AM50: {=_xlfn.IFS($AJ50="NO CHARGE",0,$AJ50=0,0,$AJ50>0,PRODUCT(J50,$AJ50))} -> 0 | AN50: {=_xlfn.IFS($AJ50="NO CHARGE",0,$AJ50=0,0,$AJ50>0,PRODUCT(K50,$AJ50))} -> 0 | AO50: {=_xlfn.IFS($AJ50="NO CHARGE",0,$AJ50=0,0,$AJ50>0,PRODUCT(L50,$AJ50))} -> 0 | AP50: {=_xlfn.IFS($AJ50="NO CHARGE",0,$AJ50=0,0,$AJ50>0,PRODUCT(M50,$AJ50))} -> 0 | AQ50: =SUM(AL50:AP50) -> 0 | AV50: =IF(AU50>0,PRODUCT(I50,$AU50),0) -> 0 | AW50: =IF(AV50>0,PRODUCT(J50,$AU50),0) -> 0 | AX50: =IF(AW50>0,PRODUCT(K50,$AU50),0) -> 0 | AY50: =IF(AX50>0,PRODUCT(L50,$AU50),0) -> 0 | AZ50: =IF(AY50>0,PRODUCT(M50,$AU50),0) -> 0 | BA50: =SUM(AV50:AZ50) -> 0
C51: Cornerstone for DR Host | D51: 1 | E51: 1 | F51: 1 | G51: 1 | H51: =IFERROR(AVERAGE(D51:G51),0) -> 1 | I51: =H51*12 -> 12 | J51: =IF(I51>12,(((I51)*$H$5)+I51),(I51*1)) -> 12 | K51: =IF(J51>12,(((J51)*$H$5)+J51),(J51*1)) -> 12 | L51: =IF(K51>12,(((K51)*$H$5)+K51),(K51*1)) -> 12 | M51: =IF(L51>12,(((L51)*$H$5)+L51),(L51*1)) -> 12 | N51: =IF(C51="","",C51) -> Cornerstone for DR Host | O51: 838.43167 | P51: =Q51/12 -> 838.43167 | Q51: =IF(O51>0,PRODUCT(I51,$O51),0) -> 10061.18 | R51: =IF(Q51>0,PRODUCT(J51,$O51),0) -> 10061.18 | S51: =IF(R51>0,PRODUCT(K51,$O51),0) -> 10061.18 | T51: =IF(S51>0,PRODUCT(L51,$O51),0) -> 10061.18 | U51: =IF(T51>0,PRODUCT(M51,$O51),0) -> 10061.18 | V51: =SUM(Q51:U51) -> 50305.9 | Z51: =AA51/12 -> 0 | AA51: =IF(Y51>0,PRODUCT(I51,$Y51),0) -> 0 | AB51: =IF(AA51>0,PRODUCT(J51,$Y51),0) -> 0 | AC51: =IF(AB51>0,PRODUCT(K51,$Y51),0) -> 0 | AD51: =IF(AC51>0,PRODUCT(L51,$Y51),0) -> 0 | AE51: =IF(AD51>0,PRODUCT(M51,$Y51),0) -> 0 | AF51: =SUM(AA51:AE51) -> 0 | AK51: =AL51/12 -> 0 | AL51: {=_xlfn.IFS($AJ51="NO CHARGE",0,$AJ51=0,0,$AJ51>0,PRODUCT(I51,$AJ51))} -> 0 | AM51: {=_xlfn.IFS($AJ51="NO CHARGE",0,$AJ51=0,0,$AJ51>0,PRODUCT(J51,$AJ51))} -> 0 | AN51: {=_xlfn.IFS($AJ51="NO CHARGE",0,$AJ51=0,0,$AJ51>0,PRODUCT(K51,$AJ51))} -> 0 | AO51: {=_xlfn.IFS($AJ51="NO CHARGE",0,$AJ51=0,0,$AJ51>0,PRODUCT(L51,$AJ51))} -> 0 | AP51: {=_xlfn.IFS($AJ51="NO CHARGE",0,$AJ51=0,0,$AJ51>0,PRODUCT(M51,$AJ51))} -> 0 | AQ51: =SUM(AL51:AP51) -> 0 | AV51: =IF(AU51>0,PRODUCT(I51,$AU51),0) -> 0 | AW51: =IF(AV51>0,PRODUCT(J51,$AU51),0) -> 0 | AX51: =IF(AW51>0,PRODUCT(K51,$AU51),0) -> 0 | AY51: =IF(AX51>0,PRODUCT(L51,$AU51),0) -> 0 | AZ51: =IF(AY51>0,PRODUCT(M51,$AU51),0) -> 0 | BA51: =SUM(AV51:AZ51) -> 0
C52: CASS Certification - WorksRight | H52: 1 | I52: =H52*12 -> 12 | J52: =IF(I52>12,(((I52)*$H$5)+I52),(I52*1)) -> 12 | K52: =IF(J52>12,(((J52)*$H$5)+J52),(J52*1)) -> 12 | L52: =IF(K52>12,(((K52)*$H$5)+K52),(K52*1)) -> 12 | M52: =IF(L52>12,(((L52)*$H$5)+L52),(L52*1)) -> 12 | P52: =Q52/12 -> 0 | Q52: =IF(O52>0,PRODUCT(I52,$O52),0) -> 0 | R52: =IF(Q52>0,PRODUCT(J52,$O52),0) -> 0 | S52: =IF(R52>0,PRODUCT(K52,$O52),0) -> 0 | T52: =IF(S52>0,PRODUCT(L52,$O52),0) -> 0 | U52: =IF(T52>0,PRODUCT(M52,$O52),0) -> 0 | V52: =SUM(Q52:U52) -> 0 | X52: =C52 -> CASS Certification - WorksRight | Y52: 416.46 | Z52: =AA52/12 -> 416.46 | AA52: =IF(Y52>0,PRODUCT(I52,$Y52),0) -> 4997.52 | AB52: =IF(AA52>0,PRODUCT(J52,$Y52),0) -> 4997.52 | AC52: =IF(AB52>0,PRODUCT(K52,$Y52),0) -> 4997.52 | AD52: =IF(AC52>0,PRODUCT(L52,$Y52),0) -> 4997.52 | AE52: =IF(AD52>0,PRODUCT(M52,$Y52),0) -> 4997.52 | AF52: =SUM(AA52:AE52) -> 24987.6 | AG52: 2500 | AK52: =AL52/12 -> 0 | AL52: {=_xlfn.IFS($AJ52="NO CHARGE",0,$AJ52=0,0,$AJ52>0,PRODUCT(I52,$AJ52))} -> 0 | AM52: {=_xlfn.IFS($AJ52="NO CHARGE",0,$AJ52=0,0,$AJ52>0,PRODUCT(J52,$AJ52))} -> 0 | AN52: {=_xlfn.IFS($AJ52="NO CHARGE",0,$AJ52=0,0,$AJ52>0,PRODUCT(K52,$AJ52))} -> 0 | AO52: {=_xlfn.IFS($AJ52="NO CHARGE",0,$AJ52=0,0,$AJ52>0,PRODUCT(L52,$AJ52))} -> 0 | AP52: {=_xlfn.IFS($AJ52="NO CHARGE",0,$AJ52=0,0,$AJ52>0,PRODUCT(M52,$AJ52))} -> 0 | AQ52: =SUM(AL52:AP52) -> 0 | AV52: =IF(AU52>0,PRODUCT(I52,$AU52),0) -> 0 | AW52: =IF(AV52>0,PRODUCT(J52,$AU52),0) -> 0 | AX52: =IF(AW52>0,PRODUCT(K52,$AU52),0) -> 0 | AY52: =IF(AX52>0,PRODUCT(L52,$AU52),0) -> 0 | AZ52: =IF(AY52>0,PRODUCT(M52,$AU52),0) -> 0 | BA52: =SUM(AV52:AZ52) -> 0
C53: CASS Certification - WorksRight | H53: 1 | I53: =H53*12 -> 12 | J53: =IF(I53>12,(((I53)*$H$5)+I53),(I53*1)) -> 12 | K53: =IF(J53>12,(((J53)*$H$5)+J53),(J53*1)) -> 12 | L53: =IF(K53>12,(((K53)*$H$5)+K53),(K53*1)) -> 12 | M53: =IF(L53>12,(((L53)*$H$5)+L53),(L53*1)) -> 12 | P53: =Q53/12 -> 0 | Q53: =IF(O53>0,PRODUCT(I53,$O53),0) -> 0 | R53: =IF(Q53>0,PRODUCT(J53,$O53),0) -> 0 | S53: =IF(R53>0,PRODUCT(K53,$O53),0) -> 0 | T53: =IF(S53>0,PRODUCT(L53,$O53),0) -> 0 | U53: =IF(T53>0,PRODUCT(M53,$O53),0) -> 0 | V53: =SUM(Q53:U53) -> 0 | Z53: =AA53/12 -> 0 | AA53: =IF(Y53>0,PRODUCT(I53,$Y53),0) -> 0 | AB53: =IF(AA53>0,PRODUCT(J53,$Y53),0) -> 0 | AC53: =IF(AB53>0,PRODUCT(K53,$Y53),0) -> 0 | AD53: =IF(AC53>0,PRODUCT(L53,$Y53),0) -> 0 | AE53: =IF(AD53>0,PRODUCT(M53,$Y53),0) -> 0 | AF53: =SUM(AA53:AE53) -> 0 | AI53: =C53 -> CASS Certification - WorksRight | AJ53: 416.46 | AK53: =AL53/12 -> 416.46 | AL53: {=_xlfn.IFS($AJ53="NO CHARGE",0,$AJ53=0,0,$AJ53>0,PRODUCT(I53,$AJ53))} -> 4997.52 | AM53: {=_xlfn.IFS($AJ53="NO CHARGE",0,$AJ53=0,0,$AJ53>0,PRODUCT(J53,$AJ53))} -> 4997.52 | AN53: {=_xlfn.IFS($AJ53="NO CHARGE",0,$AJ53=0,0,$AJ53>0,PRODUCT(K53,$AJ53))} -> 4997.52 | AO53: {=_xlfn.IFS($AJ53="NO CHARGE",0,$AJ53=0,0,$AJ53>0,PRODUCT(L53,$AJ53))} -> 4997.52 | AP53: {=_xlfn.IFS($AJ53="NO CHARGE",0,$AJ53=0,0,$AJ53>0,PRODUCT(M53,$AJ53))} -> 4997.52 | AQ53: =SUM(AL53:AP53) -> 24987.6 | AR53: Waived | AV53: =IF(AU53>0,PRODUCT(I53,$AU53),0) -> 0 | AW53: =IF(AV53>0,PRODUCT(J53,$AU53),0) -> 0 | AX53: =IF(AW53>0,PRODUCT(K53,$AU53),0) -> 0 | AY53: =IF(AX53>0,PRODUCT(L53,$AU53),0) -> 0 | AZ53: =IF(AY53>0,PRODUCT(M53,$AU53),0) -> 0 | BA53: =SUM(AV53:AZ53) -> 0
C54: Internet Banking - Q2 eBanking | H54: 1 | I54: =H54*12 -> 12 | J54: =IF(I54>12,(((I54)*$H$5)+I54),(I54*1)) -> 12 | K54: =IF(J54>12,(((J54)*$H$5)+J54),(J54*1)) -> 12 | L54: =IF(K54>12,(((K54)*$H$5)+K54),(K54*1)) -> 12 | M54: =IF(L54>12,(((L54)*$H$5)+L54),(L54*1)) -> 12 | P54: =Q54/12 -> 0 | Q54: =IF(O54>0,PRODUCT(I54,$O54),0) -> 0 | R54: =IF(Q54>0,PRODUCT(J54,$O54),0) -> 0 | S54: =IF(R54>0,PRODUCT(K54,$O54),0) -> 0 | T54: =IF(S54>0,PRODUCT(L54,$O54),0) -> 0 | U54: =IF(T54>0,PRODUCT(M54,$O54),0) -> 0 | V54: =SUM(Q54:U54) -> 0 | Z54: =AA54/12 -> 0 | AA54: =IF(Y54>0,PRODUCT(I54,$Y54),0) -> 0 | AB54: =IF(AA54>0,PRODUCT(J54,$Y54),0) -> 0 | AC54: =IF(AB54>0,PRODUCT(K54,$Y54),0) -> 0 | AD54: =IF(AC54>0,PRODUCT(L54,$Y54),0) -> 0 | AE54: =IF(AD54>0,PRODUCT(M54,$Y54),0) -> 0 | AF54: =SUM(AA54:AE54) -> 0 | AI54: =C54 -> Internet Banking - Q2 eBanking | AJ54: 1194 | AK54: =AL54/12 -> 1194 | AL54: {=_xlfn.IFS($AJ54="NO CHARGE",0,$AJ54=0,0,$AJ54>0,PRODUCT(I54,$AJ54))} -> 14328 | AM54: {=_xlfn.IFS($AJ54="NO CHARGE",0,$AJ54=0,0,$AJ54>0,PRODUCT(J54,$AJ54))} -> 14328 | AN54: {=_xlfn.IFS($AJ54="NO CHARGE",0,$AJ54=0,0,$AJ54>0,PRODUCT(K54,$AJ54))} -> 14328 | AO54: {=_xlfn.IFS($AJ54="NO CHARGE",0,$AJ54=0,0,$AJ54>0,PRODUCT(L54,$AJ54))} -> 14328 | AP54: {=_xlfn.IFS($AJ54="NO CHARGE",0,$AJ54=0,0,$AJ54>0,PRODUCT(M54,$AJ54))} -> 14328 | AQ54: =SUM(AL54:AP54) -> 71640 | AR54: 22500 | AV54: =IF(AU54>0,PRODUCT(I54,$AU54),0) -> 0 | AW54: =IF(AV54>0,PRODUCT(J54,$AU54),0) -> 0 | AX54: =IF(AW54>0,PRODUCT(K54,$AU54),0) -> 0 | AY54: =IF(AX54>0,PRODUCT(L54,$AU54),0) -> 0 | AZ54: =IF(AY54>0,PRODUCT(M54,$AU54),0) -> 0 | BA54: =SUM(AV54:AZ54) -> 0
H55: =IFERROR(AVERAGE(D55:G55),0) -> 0 | I55: =H55*12 -> 0 | J55: =IF(I55>12,(((I55)*$H$5)+I55),(I55*1)) -> 0 | K55: =IF(J55>12,(((J55)*$H$5)+J55),(J55*1)) -> 0 | L55: =IF(K55>12,(((K55)*$H$5)+K55),(K55*1)) -> 0 | M55: =IF(L55>12,(((L55)*$H$5)+L55),(L55*1)) -> 0 | P55: =Q55/12 -> 0 | Q55: =IF(O55>0,PRODUCT(I55,$O55),0) -> 0 | R55: =IF(Q55>0,PRODUCT(J55,$O55),0) -> 0 | S55: =IF(R55>0,PRODUCT(K55,$O55),0) -> 0 | T55: =IF(S55>0,PRODUCT(L55,$O55),0) -> 0 | U55: =IF(T55>0,PRODUCT(M55,$O55),0) -> 0 | V55: =SUM(Q55:U55) -> 0 | Z55: =AA55/12 -> 0 | AA55: =IF(Y55>0,PRODUCT(I55,$Y55),0) -> 0 | AB55: =IF(AA55>0,PRODUCT(J55,$Y55),0) -> 0 | AC55: =IF(AB55>0,PRODUCT(K55,$Y55),0) -> 0 | AD55: =IF(AC55>0,PRODUCT(L55,$Y55),0) -> 0 | AE55: =IF(AD55>0,PRODUCT(M55,$Y55),0) -> 0 | AF55: =SUM(AA55:AE55) -> 0 | AK55: =AL55/12 -> 0 | AL55: {=_xlfn.IFS($AJ55="NO CHARGE",0,$AJ55=0,0,$AJ55>0,PRODUCT(I55,$AJ55))} -> 0 | AM55: {=_xlfn.IFS($AJ55="NO CHARGE",0,$AJ55=0,0,$AJ55>0,PRODUCT(J55,$AJ55))} -> 0 | AN55: {=_xlfn.IFS($AJ55="NO CHARGE",0,$AJ55=0,0,$AJ55>0,PRODUCT(K55,$AJ55))} -> 0 | AO55: {=_xlfn.IFS($AJ55="NO CHARGE",0,$AJ55=0,0,$AJ55>0,PRODUCT(L55,$AJ55))} -> 0 | AP55: {=_xlfn.IFS($AJ55="NO CHARGE",0,$AJ55=0,0,$AJ55>0,PRODUCT(M55,$AJ55))} -> 0 | AQ55: =SUM(AL55:AP55) -> 0 | AV55: =IF(AU55>0,PRODUCT(I55,$AU55),0) -> 0 | AW55: =IF(AV55>0,PRODUCT(J55,$AU55),0) -> 0 | AX55: =IF(AW55>0,PRODUCT(K55,$AU55),0) -> 0 | AY55: =IF(AX55>0,PRODUCT(L55,$AU55),0) -> 0 | AZ55: =IF(AY55>0,PRODUCT(M55,$AU55),0) -> 0 | BA55: =SUM(AV55:AZ55) -> 0
B56: =C56 -> ATM / EFT Services: | C56: ATM / EFT Services: | N56: =C56 -> ATM / EFT Services: | X56: =C56 -> ATM / EFT Services: | AI56: =C56 -> ATM / EFT Services: | AQ56: =SUM(AL56:AP56) -> 0 | AT56: =C56 -> ATM / EFT Services:
B57: PaymentsOne | C57: ATM/EFT Network Services (Debit Card Processing) | H57: 1 | I57: =H57*12 -> 12 | J57: =IF(I57>12,(((I57)*$H$5)+I57),(I57*1)) -> 12 | K57: =IF(J57>12,(((J57)*$H$5)+J57),(J57*1)) -> 12 | L57: =IF(K57>12,(((K57)*$H$5)+K57),(K57*1)) -> 12 | M57: =IF(L57>12,(((L57)*$H$5)+L57),(L57*1)) -> 12 | N57: =IF(C57="","",C57) -> ATM/EFT Network Services (Debit Card Processing) | O57: 269.42 | P57: =Q57/12 -> 269.42 | Q57: =IF(O57>0,PRODUCT(I57,$O57),0) -> 3233.04 | R57: =IF(Q57>0,PRODUCT(J57,$O57),0) -> 3233.04 | S57: =IF(R57>0,PRODUCT(K57,$O57),0) -> 3233.04 | T57: =IF(S57>0,PRODUCT(L57,$O57),0) -> 3233.04 | U57: =IF(T57>0,PRODUCT(M57,$O57),0) -> 3233.04 | V57: =SUM(Q57:U57) -> 16165.2 | X57: =C57 -> ATM/EFT Network Services (Debit Card Processing) | Y57: 350 | Z57: =AA57/12 -> 350 | AA57: =IF(Y57>0,PRODUCT(I57,$Y57),0) -> 4200 | AB57: =IF(AA57>0,PRODUCT(J57,$Y57),0) -> 4200 | AC57: =IF(AB57>0,PRODUCT(K57,$Y57),0) -> 4200 | AD57: =IF(AC57>0,PRODUCT(L57,$Y57),0) -> 4200 | AE57: =IF(AD57>0,PRODUCT(M57,$Y57),0) -> 4200 | AF57: =SUM(AA57:AE57) -> 21000 | AI57: =C57 -> ATM/EFT Network Services (Debit Card Processing) | AJ57: 450 | AK57: =AL57/12 -> 450 | AL57: {=_xlfn.IFS($AJ57="NO CHARGE",0,$AJ57=0,0,$AJ57>0,PRODUCT(I57,$AJ57))} -> 5400 | AM57: {=_xlfn.IFS($AJ57="NO CHARGE",0,$AJ57=0,0,$AJ57>0,PRODUCT(J57,$AJ57))} -> 5400 | AN57: {=_xlfn.IFS($AJ57="NO CHARGE",0,$AJ57=0,0,$AJ57>0,PRODUCT(K57,$AJ57))} -> 5400 | AO57: {=_xlfn.IFS($AJ57="NO CHARGE",0,$AJ57=0,0,$AJ57>0,PRODUCT(L57,$AJ57))} -> 5400 | AP57: {=_xlfn.IFS($AJ57="NO CHARGE",0,$AJ57=0,0,$AJ57>0,PRODUCT(M57,$AJ57))} -> 5400 | AQ57: =SUM(AL57:AP57) -> 27000 | AV57: =IF(AU57>0,PRODUCT(I57,$AU57),0) -> 0 | AW57: =IF(AV57>0,PRODUCT(J57,$AU57),0) -> 0 | AX57: =IF(AW57>0,PRODUCT(K57,$AU57),0) -> 0 | AY57: =IF(AX57>0,PRODUCT(L57,$AU57),0) -> 0 | AZ57: =IF(AY57>0,PRODUCT(M57,$AU57),0) -> 0 | BA57: =SUM(AV57:AZ57) -> 0
B58: PaymentsOne | C58: Signature Based Authorizations | E58: 203292 | F58: 195453 | G58: 197668 | H58: =AVERAGE(E58:G58) -> 198804.33 | I58: =H58*12 -> 2385652 | J58: =IF(I58>12,(((I58)*$H$5)+I58),(I58*1)) -> 2504934.6 | K58: =IF(J58>12,(((J58)*$H$5)+J58),(J58*1)) -> 2630181.3 | L58: =IF(K58>12,(((K58)*$H$5)+K58),(K58*1)) -> 2761690.4 | M58: =IF(L58>12,(((L58)*$H$5)+L58),(L58*1)) -> 2899774.9 | N58: =IF(C58="","",C58) -> Signature Based Authorizations | O58: 0.021554 | P58: =Q58/12 -> 4285.0286 | Q58: =IF(O58>0,PRODUCT(I58,$O58),0) -> 51420.343 | R58: =IF(Q58>0,PRODUCT(J58,$O58),0) -> 53991.36 | S58: =IF(R58>0,PRODUCT(K58,$O58),0) -> 56690.928 | T58: =IF(S58>0,PRODUCT(L58,$O58),0) -> 59525.475 | U58: =IF(T58>0,PRODUCT(M58,$O58),0) -> 62501.749 | V58: =SUM(Q58:U58) -> 284129.86 | X58: =C58 -> Signature Based Authorizations | Y58: 0.0175 | Z58: =AA58/12 -> 3479.0758 | AA58: =IF(Y58>0,PRODUCT(I58,$Y58),0) -> 41748.91 | AB58: =IF(AA58>0,PRODUCT(J58,$Y58),0) -> 43836.356 | AC58: =IF(AB58>0,PRODUCT(K58,$Y58),0) -> 46028.173 | AD58: =IF(AC58>0,PRODUCT(L58,$Y58),0) -> 48329.582 | AE58: =IF(AD58>0,PRODUCT(M58,$Y58),0) -> 50746.061 | AF58: =SUM(AA58:AE58) -> 230689.08 | AI58: =C58 -> Signature Based Authorizations | AJ58: 0.0175 | AK58: =AL58/12 -> 3479.0758 | AL58: {=_xlfn.IFS($AJ58="NO CHARGE",0,$AJ58=0,0,$AJ58>0,PRODUCT(I58,$AJ58))} -> 41748.91 | AM58: {=_xlfn.IFS($AJ58="NO CHARGE",0,$AJ58=0,0,$AJ58>0,PRODUCT(J58,$AJ58))} -> 43836.356 | AN58: {=_xlfn.IFS($AJ58="NO CHARGE",0,$AJ58=0,0,$AJ58>0,PRODUCT(K58,$AJ58))} -> 46028.173 | AO58: {=_xlfn.IFS($AJ58="NO CHARGE",0,$AJ58=0,0,$AJ58>0,PRODUCT(L58,$AJ58))} -> 48329.582 | AP58: {=_xlfn.IFS($AJ58="NO CHARGE",0,$AJ58=0,0,$AJ58>0,PRODUCT(M58,$AJ58))} -> 50746.061 | AQ58: =SUM(AL58:AP58) -> 230689.08
B59: PaymentsOne | C59: PIN-Based Transaction Volumes | E59: 144259 | F59: 139967 | G59: 146274 | H59: =AVERAGE(E59:G59) -> 143500 | I59: =H59*12 -> 1722000 | J59: =IF(I59>12,(((I59)*$H$5)+I59),(I59*1)) -> 1808100 | K59: =IF(J59>12,(((J59)*$H$5)+J59),(J59*1)) -> 1898505 | L59: =IF(K59>12,(((K59)*$H$5)+K59),(K59*1)) -> 1993430.2 | M59: =IF(L59>12,(((L59)*$H$5)+L59),(L59*1)) -> 2093101.8 | N59: =IF(C59="","",C59) -> PIN-Based Transaction Volumes | O59: 0.021554 | P59: =Q59/12 -> 3092.999 | Q59: =IF(O59>0,PRODUCT(I59,$O59),0) -> 37115.988 | R59: =IF(Q59>0,PRODUCT(J59,$O59),0) -> 38971.787 | S59: =IF(R59>0,PRODUCT(K59,$O59),0) -> 40920.377 | T59: =IF(S59>0,PRODUCT(L59,$O59),0) -> 42966.396 | U59: =IF(T59>0,PRODUCT(M59,$O59),0) -> 45114.715 | V59: =SUM(Q59:U59) -> 205089.26 | X59: =C59 -> PIN-Based Transaction Volumes | Y59: 0.0175 | Z59: =AA59/12 -> 2511.25 | AA59: =IF(Y59>0,PRODUCT(I59,$Y59),0) -> 30135 | AB59: =IF(AA59>0,PRODUCT(J59,$Y59),0) -> 31641.75 | AC59: =IF(AB59>0,PRODUCT(K59,$Y59),0) -> 33223.838 | AD59: =IF(AC59>0,PRODUCT(L59,$Y59),0) -> 34885.029 | AE59: =IF(AD59>0,PRODUCT(M59,$Y59),0) -> 36629.281 | AF59: =SUM(AA59:AE59) -> 166514.9 | AI59: =C59 -> PIN-Based Transaction Volumes | AJ59: 0.019 | AK59: =AL59/12 -> 2726.5 | AL59: {=_xlfn.IFS($AJ59="NO CHARGE",0,$AJ59=0,0,$AJ59>0,PRODUCT(I59,$AJ59))} -> 32718 | AM59: {=_xlfn.IFS($AJ59="NO CHARGE",0,$AJ59=0,0,$AJ59>0,PRODUCT(J59,$AJ59))} -> 34353.9 | AN59: {=_xlfn.IFS($AJ59="NO CHARGE",0,$AJ59=0,0,$AJ59>0,PRODUCT(K59,$AJ59))} -> 36071.595 | AO59: {=_xlfn.IFS($AJ59="NO CHARGE",0,$AJ59=0,0,$AJ59>0,PRODUCT(L59,$AJ59))} -> 37875.175 | AP59: {=_xlfn.IFS($AJ59="NO CHARGE",0,$AJ59=0,0,$AJ59>0,PRODUCT(M59,$AJ59))} -> 39768.933 | AQ59: =SUM(AL59:AP59) -> 180787.6
B60: PaymentsOne | C60: Settlement/Clearing Based Transaction Volumes | E60: 224162 | F60: 211184 | G60: 216309 | H60: =AVERAGE(E60:G60) -> 217218.33 | I60: =H60*12 -> 2606620 | J60: =IF(I60>12,(((I60)*$H$5)+I60),(I60*1)) -> 2736951 | K60: =IF(J60>12,(((J60)*$H$5)+J60),(J60*1)) -> 2873798.5 | L60: =IF(K60>12,(((K60)*$H$5)+K60),(K60*1)) -> 3017488.5 | M60: =IF(L60>12,(((L60)*$H$5)+L60),(L60*1)) -> 3168362.9 | N60: =IF(C60="","",C60) -> Settlement/Clearing Based Transaction Volumes | O60: 0.0107768 | P60: =Q60/12 -> 2340.9185 | Q60: =IF(O60>0,PRODUCT(I60,$O60),0) -> 28091.022 | R60: =IF(Q60>0,PRODUCT(J60,$O60),0) -> 29495.574 | S60: =IF(R60>0,PRODUCT(K60,$O60),0) -> 30970.352 | T60: =IF(S60>0,PRODUCT(L60,$O60),0) -> 32518.87 | U60: =IF(T60>0,PRODUCT(M60,$O60),0) -> 34144.813 | V60: =SUM(Q60:U60) -> 155220.63 | X60: =C60 -> Settlement/Clearing Based Transaction Volumes | Y60: 0.009 | Z60: =AA60/12 -> 1954.965 | AA60: =IF(Y60>0,PRODUCT(I60,$Y60),0) -> 23459.58 | AB60: =IF(AA60>0,PRODUCT(J60,$Y60),0) -> 24632.559 | AC60: =IF(AB60>0,PRODUCT(K60,$Y60),0) -> 25864.187 | AD60: =IF(AC60>0,PRODUCT(L60,$Y60),0) -> 27157.396 | AE60: =IF(AD60>0,PRODUCT(M60,$Y60),0) -> 28515.266 | AF60: =SUM(AA60:AE60) -> 129628.99 | AI60: =C60 -> Settlement/Clearing Based Transaction Volumes | AJ60: 0.009 | AK60: =AL60/12 -> 1954.965 | AL60: {=_xlfn.IFS($AJ60="NO CHARGE",0,$AJ60=0,0,$AJ60>0,PRODUCT(I60,$AJ60))} -> 23459.58 | AM60: {=_xlfn.IFS($AJ60="NO CHARGE",0,$AJ60=0,0,$AJ60>0,PRODUCT(J60,$AJ60))} -> 24632.559 | AN60: {=_xlfn.IFS($AJ60="NO CHARGE",0,$AJ60=0,0,$AJ60>0,PRODUCT(K60,$AJ60))} -> 25864.187 | AO60: {=_xlfn.IFS($AJ60="NO CHARGE",0,$AJ60=0,0,$AJ60>0,PRODUCT(L60,$AJ60))} -> 27157.396 | AP60: {=_xlfn.IFS($AJ60="NO CHARGE",0,$AJ60=0,0,$AJ60>0,PRODUCT(M60,$AJ60))} -> 28515.266 | AQ60: =SUM(AL60:AP60) -> 129628.99
B61: PaymentsOne | C61: EMV/Chip Authorizations - Standard | E61: 285217 | F61: 275794 | G61: 282378 | H61: =AVERAGE(E61:G61) -> 281129.67 | I61: =H61*12 -> 3373556 | J61: =IF(I61>12,(((I61)*$H$5)+I61),(I61*1)) -> 3542233.8 | K61: =IF(J61>12,(((J61)*$H$5)+J61),(J61*1)) -> 3719345.5 | L61: =IF(K61>12,(((K61)*$H$5)+K61),(K61*1)) -> 3905312.8 | M61: =IF(L61>12,(((L61)*$H$5)+L61),(L61*1)) -> 4100578.4 | N61: =IF(C61="","",C61) -> EMV/Chip Authorizations - Standard | O61: 0.001832 | P61: =Q61/12 -> 515.02955 | Q61: =IF(O61>0,PRODUCT(I61,$O61),0) -> 6180.3546 | R61: =IF(Q61>0,PRODUCT(J61,$O61),0) -> 6489.3723 | S61: =IF(R61>0,PRODUCT(K61,$O61),0) -> 6813.8409 | T61: =IF(S61>0,PRODUCT(L61,$O61),0) -> 7154.533 | U61: =IF(T61>0,PRODUCT(M61,$O61),0) -> 7512.2596 | V61: =SUM(Q61:U61) -> 34150.36 | X61: =C61 -> EMV/Chip Authorizations - Standard | Y61: 0.001 | Z61: =AA61/12 -> 281.12967 | AA61: =IF(Y61>0,PRODUCT(I61,$Y61),0) -> 3373.556 | AB61: =IF(AA61>0,PRODUCT(J61,$Y61),0) -> 3542.2338 | AC61: =IF(AB61>0,PRODUCT(K61,$Y61),0) -> 3719.3455 | AD61: =IF(AC61>0,PRODUCT(L61,$Y61),0) -> 3905.3128 | AE61: =IF(AD61>0,PRODUCT(M61,$Y61),0) -> 4100.5784 | AF61: =SUM(AA61:AE61) -> 18641.026 | AI61: =C61 -> EMV/Chip Authorizations - Standard | AJ61: 0.001 | AK61: =AL61/12 -> 281.12967 | AL61: {=_xlfn.IFS($AJ61="NO CHARGE",0,$AJ61=0,0,$AJ61>0,PRODUCT(I61,$AJ61))} -> 3373.556 | AM61: {=_xlfn.IFS($AJ61="NO CHARGE",0,$AJ61=0,0,$AJ61>0,PRODUCT(J61,$AJ61))} -> 3542.2338 | AN61: {=_xlfn.IFS($AJ61="NO CHARGE",0,$AJ61=0,0,$AJ61>0,PRODUCT(K61,$AJ61))} -> 3719.3455 | AO61: {=_xlfn.IFS($AJ61="NO CHARGE",0,$AJ61=0,0,$AJ61>0,PRODUCT(L61,$AJ61))} -> 3905.3128 | AP61: {=_xlfn.IFS($AJ61="NO CHARGE",0,$AJ61=0,0,$AJ61>0,PRODUCT(M61,$AJ61))} -> 4100.5784 | AQ61: =SUM(AL61:AP61) -> 18641.026
B62: PaymentsOne | C62: Card File Residency [QTY CALCULATIONS] | E62: =SUM(E63:E64) -> 20227 | F62: =SUM(F63:F64) -> 19794 | G62: =SUM(G63:G64) -> 19301 | H62: =AVERAGE(E62:G62) -> 19774 | I62: =H62*12 -> 237288 | J62: =IF(I62>12,(((I62)*$H$5)+I62),(I62*1)) -> 249152.4 | K62: =IF(J62>12,(((J62)*$H$5)+J62),(J62*1)) -> 261610.02 | L62: =IF(K62>12,(((K62)*$H$5)+K62),(K62*1)) -> 274690.52 | M62: =IF(L62>12,(((L62)*$H$5)+L62),(L62*1)) -> 288425.05 | N62: Card File Residency [TIERED] | P62: =Q62/12 -> 0 | Q62: =IF(O62>0,PRODUCT(I62,$O62),0) -> 0 | R62: =IF(Q62>0,PRODUCT(J62,$O62),0) -> 0 | S62: =IF(R62>0,PRODUCT(K62,$O62),0) -> 0 | T62: =IF(S62>0,PRODUCT(L62,$O62),0) -> 0 | U62: =IF(T62>0,PRODUCT(M62,$O62),0) -> 0 | V62: =SUM(Q62:U62) -> 0 | X62: Card File Residency [TIERED] | Z62: =AA62/12 -> 0 | AA62: =IF(Y62>0,PRODUCT(I62,$Y62),0) -> 0 | AB62: =IF(AA62>0,PRODUCT(J62,$Y62),0) -> 0 | AC62: =IF(AB62>0,PRODUCT(K62,$Y62),0) -> 0 | AD62: =IF(AC62>0,PRODUCT(L62,$Y62),0) -> 0 | AE62: =IF(AD62>0,PRODUCT(M62,$Y62),0) -> 0 | AF62: =SUM(AA62:AE62) -> 0 | AI62: =C62 -> Card File Residency [QTY CALCULATIONS] | AK62: =AL62/12 -> 0 | AL62: {=_xlfn.IFS($AJ62="NO CHARGE",0,$AJ62=0,0,$AJ62>0,PRODUCT(I62,$AJ62))} -> 0 | AM62: {=_xlfn.IFS($AJ62="NO CHARGE",0,$AJ62=0,0,$AJ62>0,PRODUCT(J62,$AJ62))} -> 0 | AN62: {=_xlfn.IFS($AJ62="NO CHARGE",0,$AJ62=0,0,$AJ62>0,PRODUCT(K62,$AJ62))} -> 0 | AO62: {=_xlfn.IFS($AJ62="NO CHARGE",0,$AJ62=0,0,$AJ62>0,PRODUCT(L62,$AJ62))} -> 0 | AP62: {=_xlfn.IFS($AJ62="NO CHARGE",0,$AJ62=0,0,$AJ62>0,PRODUCT(M62,$AJ62))} -> 0 | AQ62: =SUM(AL62:AP62) -> 0 | AV62: =IF(AU62>0,PRODUCT(I62,$AU62),0) -> 0 | AW62: =IF(AV62>0,PRODUCT(J62,$AU62),0) -> 0 | AX62: =IF(AW62>0,PRODUCT(K62,$AU62),0) -> 0 | AY62: =IF(AX62>0,PRODUCT(L62,$AU62),0) -> 0 | AZ62: =IF(AY62>0,PRODUCT(M62,$AU62),0) -> 0 | BA62: =SUM(AV62:AZ62) -> 0
B63: PaymentsOne | C63: [Tiered] Card File Residency 0 - 7,500 | E63: 7500 | F63: 7500 | G63: 7500 | H63: 7500 | I63: =IF(I62>($H63*12),$H63*12,I62) -> 90000 | J63: =IF(J62>($H63*12),$H63*12,J62) -> 90000 | K63: =IF(K62>($H63*12),$H63*12,K62) -> 90000 | L63: =IF(L62>($H63*12),$H63*12,L62) -> 90000 | M63: =IF(M62>($H63*12),$H63*12,M62) -> 90000 | N63: =IF(C63="","",C63) -> [Tiered] Card File Residency 0 - 7,500 | O63: 0.0269421 | P63: =Q63/12 -> 202.06575 | Q63: =IF(O63>0,PRODUCT(I63,$O63),0) -> 2424.789 | R63: =IF(Q63>0,PRODUCT(J63,$O63),0) -> 2424.789 | S63: =IF(R63>0,PRODUCT(K63,$O63),0) -> 2424.789 | T63: =IF(S63>0,PRODUCT(L63,$O63),0) -> 2424.789 | U63: =IF(T63>0,PRODUCT(M63,$O63),0) -> 2424.789 | V63: =SUM(Q63:U63) -> 12123.945 | X63: =C63 -> [Tiered] Card File Residency 0 - 7,500 | Y63: 0.02 | Z63: =AA63/12 -> 150 | AA63: =IF(Y63>0,PRODUCT(I63,$Y63),0) -> 1800 | AB63: =IF(AA63>0,PRODUCT(J63,$Y63),0) -> 1800 | AC63: =IF(AB63>0,PRODUCT(K63,$Y63),0) -> 1800 | AD63: =IF(AC63>0,PRODUCT(L63,$Y63),0) -> 1800 | AE63: =IF(AD63>0,PRODUCT(M63,$Y63),0) -> 1800 | AF63: =SUM(AA63:AE63) -> 9000 | AI63: =C63 -> [Tiered] Card File Residency 0 - 7,500 | AJ63: 0.02 | AK63: =AL63/12 -> 150 | AL63: {=_xlfn.IFS($AJ63="NO CHARGE",0,$AJ63=0,0,$AJ63>0,PRODUCT(I63,$AJ63))} -> 1800 | AM63: {=_xlfn.IFS($AJ63="NO CHARGE",0,$AJ63=0,0,$AJ63>0,PRODUCT(J63,$AJ63))} -> 1800 | AN63: {=_xlfn.IFS($AJ63="NO CHARGE",0,$AJ63=0,0,$AJ63>0,PRODUCT(K63,$AJ63))} -> 1800 | AO63: {=_xlfn.IFS($AJ63="NO CHARGE",0,$AJ63=0,0,$AJ63>0,PRODUCT(L63,$AJ63))} -> 1800 | AP63: {=_xlfn.IFS($AJ63="NO CHARGE",0,$AJ63=0,0,$AJ63>0,PRODUCT(M63,$AJ63))} -> 1800 | AQ63: =SUM(AL63:AP63) -> 9000
B64: PaymentsOne | C64: [Tiered] Card File Residency Beyond 7,500 | E64: 12727 | F64: 12294 | G64: 11801 | I64: {=_xlfn.IFS(I62>(($H63)*12),I62-I63, I62<(($H63)*12),0, I62=(($H63)*12),0)} -> 147288 | J64: {=_xlfn.IFS(J62>(($H63)*12),J62-J63, J62<(($H63)*12),0, J62=(($H63)*12),0)} -> 159152.4 | K64: {=_xlfn.IFS(K62>(($H63)*12),K62-K63, K62<(($H63)*12),0, K62=(($H63)*12),0)} -> 171610.02 | L64: {=_xlfn.IFS(L62>(($H63)*12),L62-L63, L62<(($H63)*12),0, L62=(($H63)*12),0)} -> 184690.52 | M64: {=_xlfn.IFS(M62>(($H63)*12),M62-M63, M62<(($H63)*12),0, M62=(($H63)*12),0)} -> 198425.05 | N64: =IF(C64="","",C64) -> [Tiered] Card File Residency Beyond 7,500 | O64: 0.0242479 | P64: =Q64/12 -> 297.61872 | Q64: =IF(O64>0,PRODUCT(I64,$O64),0) -> 3571.4247 | R64: =IF(Q64>0,PRODUCT(J64,$O64),0) -> 3859.1115 | S64: =IF(R64>0,PRODUCT(K64,$O64),0) -> 4161.1826 | T64: =IF(S64>0,PRODUCT(L64,$O64),0) -> 4478.3573 | U64: =IF(T64>0,PRODUCT(M64,$O64),0) -> 4811.3907 | V64: =SUM(Q64:U64) -> 20881.467 | X64: =C64 -> [Tiered] Card File Residency Beyond 7,500 | Y64: 0.02 | Z64: =AA64/12 -> 245.48 | AA64: =IF(Y64>0,PRODUCT(I64,$Y64),0) -> 2945.76 | AB64: =IF(AA64>0,PRODUCT(J64,$Y64),0) -> 3183.048 | AC64: =IF(AB64>0,PRODUCT(K64,$Y64),0) -> 3432.2004 | AD64: =IF(AC64>0,PRODUCT(L64,$Y64),0) -> 3693.8104 | AE64: =IF(AD64>0,PRODUCT(M64,$Y64),0) -> 3968.5009 | AF64: =SUM(AA64:AE64) -> 17223.32 | AH64: FIS PROPOSAL MISSING PER UNIT RATE | AI64: =C64 -> [Tiered] Card File Residency Beyond 7,500 | AJ64: 0.02 | AK64: =AL64/12 -> 245.48 | AL64: {=_xlfn.IFS($AJ64="NO CHARGE",0,$AJ64=0,0,$AJ64>0,PRODUCT(I64,$AJ64))} -> 2945.76 | AM64: {=_xlfn.IFS($AJ64="NO CHARGE",0,$AJ64=0,0,$AJ64>0,PRODUCT(J64,$AJ64))} -> 3183.048 | AN64: {=_xlfn.IFS($AJ64="NO CHARGE",0,$AJ64=0,0,$AJ64>0,PRODUCT(K64,$AJ64))} -> 3432.2004 | AO64: {=_xlfn.IFS($AJ64="NO CHARGE",0,$AJ64=0,0,$AJ64>0,PRODUCT(L64,$AJ64))} -> 3693.8104 | AP64: {=_xlfn.IFS($AJ64="NO CHARGE",0,$AJ64=0,0,$AJ64>0,PRODUCT(M64,$AJ64))} -> 3968.5009 | AQ64: =SUM(AL64:AP64) -> 17223.32 | AS64: FIS PROPOSAL MISSING PER UNIT RATE
B65: PaymentsOne | C65: Card Activation Processing | E65: 883 | F65: 849 | G65: 979 | H65: =IFERROR(AVERAGE(D65:G65),0) -> 903.66667 | I65: =H65*12 -> 10844 | J65: =IF(I65>12,(((I65)*$H$5)+I65),(I65*1)) -> 11386.2 | K65: =IF(J65>12,(((J65)*$H$5)+J65),(J65*1)) -> 11955.51 | L65: =IF(K65>12,(((K65)*$H$5)+K65),(K65*1)) -> 12553.285 | M65: =IF(L65>12,(((L65)*$H$5)+L65),(L65*1)) -> 13180.95 | N65: =IF(C65="","",C65) -> Card Activation Processing | O65: 0.5388412 | P65: =Q65/12 -> 486.93283 | Q65: =IF(O65>0,PRODUCT(I65,$O65),0) -> 5843.194 | R65: =IF(Q65>0,PRODUCT(J65,$O65),0) -> 6135.3537 | S65: =IF(R65>0,PRODUCT(K65,$O65),0) -> 6442.1214 | T65: =IF(S65>0,PRODUCT(L65,$O65),0) -> 6764.2274 | U65: =IF(T65>0,PRODUCT(M65,$O65),0) -> 7102.4388 | V65: =SUM(Q65:U65) -> 32287.335 | X65: =C65 -> Card Activation Processing | Y65: 0.5388 | Z65: =AA65/12 -> 486.8956 | AA65: =IF(Y65>0,PRODUCT(I65,$Y65),0) -> 5842.7472 | AB65: =IF(AA65>0,PRODUCT(J65,$Y65),0) -> 6134.8846 | AC65: =IF(AB65>0,PRODUCT(K65,$Y65),0) -> 6441.6288 | AD65: =IF(AC65>0,PRODUCT(L65,$Y65),0) -> 6763.7102 | AE65: =IF(AD65>0,PRODUCT(M65,$Y65),0) -> 7101.8957 | AF65: =SUM(AA65:AE65) -> 32284.867 | AI65: =C65 -> Card Activation Processing | AJ65: 0.5388 | AK65: =AL65/12 -> 486.8956 | AL65: {=_xlfn.IFS($AJ65="NO CHARGE",0,$AJ65=0,0,$AJ65>0,PRODUCT(I65,$AJ65))} -> 5842.7472 | AM65: {=_xlfn.IFS($AJ65="NO CHARGE",0,$AJ65=0,0,$AJ65>0,PRODUCT(J65,$AJ65))} -> 6134.8846 | AN65: {=_xlfn.IFS($AJ65="NO CHARGE",0,$AJ65=0,0,$AJ65>0,PRODUCT(K65,$AJ65))} -> 6441.6288 | AO65: {=_xlfn.IFS($AJ65="NO CHARGE",0,$AJ65=0,0,$AJ65>0,PRODUCT(L65,$AJ65))} -> 6763.7102 | AP65: {=_xlfn.IFS($AJ65="NO CHARGE",0,$AJ65=0,0,$AJ65>0,PRODUCT(M65,$AJ65))} -> 7101.8957 | AQ65: =SUM(AL65:AP65) -> 32284.867
B66: PaymentsOne | C66: ATM Monitoring User Interface | E66: 10 | F66: 10 | G66: 10 | H66: =IFERROR(AVERAGE(D66:G66),0) -> 10 | I66: =H66*12 -> 120 | J66: =IF(I66>12,(((I66)*$H$5)+I66),(I66*1)) -> 126 | K66: =IF(J66>12,(((J66)*$H$5)+J66),(J66*1)) -> 132.3 | L66: =IF(K66>12,(((K66)*$H$5)+K66),(K66*1)) -> 138.915 | M66: =IF(L66>12,(((L66)*$H$5)+L66),(L66*1)) -> 145.86075 | N66: =IF(C66="","",C66) -> ATM Monitoring User Interface | O66: NO CHARGE | P66: =Q66/12 -> 0 | Q66: {=_xlfn.IFS($O66="NO CHARGE",0,$O66>0,$O66*I66)} -> 0 | R66: {=_xlfn.IFS($O66="NO CHARGE",0,$O66>0,$O66*J66)} -> 0 | S66: {=_xlfn.IFS($O66="NO CHARGE",0,$O66>0,$O66*K66)} -> 0 | T66: {=_xlfn.IFS($O66="NO CHARGE",0,$O66>0,$O66*L66)} -> 0 | U66: {=_xlfn.IFS($O66="NO CHARGE",0,$O66>0,$O66*M66)} -> 0 | V66: =SUM(Q66:U66) -> 0 | X66: =C66 -> ATM Monitoring User Interface | Y66: 10 | Z66: =AA66/12 -> 100 | AA66: =IF(Y66>0,PRODUCT(I66,$Y66),0) -> 1200 | AB66: =IF(AA66>0,PRODUCT(J66,$Y66),0) -> 1260 | AC66: =IF(AB66>0,PRODUCT(K66,$Y66),0) -> 1323 | AD66: =IF(AC66>0,PRODUCT(L66,$Y66),0) -> 1389.15 | AE66: =IF(AD66>0,PRODUCT(M66,$Y66),0) -> 1458.6075 | AF66: =SUM(AA66:AE66) -> 6630.7575 | AI66: =C66 -> ATM Monitoring User Interface | AJ66: 10 | AK66: =AL66/12 -> 100 | AL66: {=_xlfn.IFS($AJ66="NO CHARGE",0,$AJ66=0,0,$AJ66>0,PRODUCT(I66,$AJ66))} -> 1200 | AM66: {=_xlfn.IFS($AJ66="NO CHARGE",0,$AJ66=0,0,$AJ66>0,PRODUCT(J66,$AJ66))} -> 1260 | AN66: {=_xlfn.IFS($AJ66="NO CHARGE",0,$AJ66=0,0,$AJ66>0,PRODUCT(K66,$AJ66))} -> 1323 | AO66: {=_xlfn.IFS($AJ66="NO CHARGE",0,$AJ66=0,0,$AJ66>0,PRODUCT(L66,$AJ66))} -> 1389.15 | AP66: {=_xlfn.IFS($AJ66="NO CHARGE",0,$AJ66=0,0,$AJ66>0,PRODUCT(M66,$AJ66))} -> 1458.6075 | AQ66: =SUM(AL66:AP66) -> 6630.7575
B67: PaymentsOne | C67: ATM Terminal Support | E67: 10 | F67: 10 | G67: 10 | H67: =IFERROR(AVERAGE(D67:G67),0) -> 10 | I67: =H67*12 -> 120 | J67: =IF(I67>12,(((I67)*$H$5)+I67),(I67*1)) -> 126 | K67: =IF(J67>12,(((J67)*$H$5)+J67),(J67*1)) -> 132.3 | L67: =IF(K67>12,(((K67)*$H$5)+K67),(K67*1)) -> 138.915 | M67: =IF(L67>12,(((L67)*$H$5)+L67),(L67*1)) -> 145.86075 | N67: =IF(C67="","",C67) -> ATM Terminal Support | O67: 43.107293 | P67: =Q67/12 -> 431.07293 | Q67: =IF(O67>0,PRODUCT(I67,$O67),0) -> 5172.8751 | R67: =IF(Q67>0,PRODUCT(J67,$O67),0) -> 5431.5189 | S67: =IF(R67>0,PRODUCT(K67,$O67),0) -> 5703.0948 | T67: =IF(S67>0,PRODUCT(L67,$O67),0) -> 5988.2496 | U67: =IF(T67>0,PRODUCT(M67,$O67),0) -> 6287.6621 | V67: =SUM(Q67:U67) -> 28583.401 | X67: =C67 -> ATM Terminal Support | Y67: 43.1073 | Z67: =AA67/12 -> 431.073 | AA67: =IF(Y67>0,PRODUCT(I67,$Y67),0) -> 5172.876 | AB67: =IF(AA67>0,PRODUCT(J67,$Y67),0) -> 5431.5198 | AC67: =IF(AB67>0,PRODUCT(K67,$Y67),0) -> 5703.0958 | AD67: =IF(AC67>0,PRODUCT(L67,$Y67),0) -> 5988.2506 | AE67: =IF(AD67>0,PRODUCT(M67,$Y67),0) -> 6287.6631 | AF67: =SUM(AA67:AE67) -> 28583.405 | AI67: =C67 -> ATM Terminal Support | AJ67: 43.1073 | AK67: =AL67/12 -> 431.073 | AL67: {=_xlfn.IFS($AJ67="NO CHARGE",0,$AJ67=0,0,$AJ67>0,PRODUCT(I67,$AJ67))} -> 5172.876 | AM67: {=_xlfn.IFS($AJ67="NO CHARGE",0,$AJ67=0,0,$AJ67>0,PRODUCT(J67,$AJ67))} -> 5431.5198 | AN67: {=_xlfn.IFS($AJ67="NO CHARGE",0,$AJ67=0,0,$AJ67>0,PRODUCT(K67,$AJ67))} -> 5703.0958 | AO67: {=_xlfn.IFS($AJ67="NO CHARGE",0,$AJ67=0,0,$AJ67>0,PRODUCT(L67,$AJ67))} -> 5988.2506 | AP67: {=_xlfn.IFS($AJ67="NO CHARGE",0,$AJ67=0,0,$AJ67>0,PRODUCT(M67,$AJ67))} -> 6287.6631 | AQ67: =SUM(AL67:AP67) -> 28583.405
B68: PaymentsOne | C68: Surcharged Transactions | E68: 4789 | F68: 4618 | G68: 4763 | H68: =IFERROR(AVERAGE(D68:G68),0) -> 4723.3333 | I68: =H68*12 -> 56680 | J68: =IF(I68>12,(((I68)*$H$5)+I68),(I68*1)) -> 59514 | K68: =IF(J68>12,(((J68)*$H$5)+J68),(J68*1)) -> 62489.7 | L68: =IF(K68>12,(((K68)*$H$5)+K68),(K68*1)) -> 65614.185 | M68: =IF(L68>12,(((L68)*$H$5)+L68),(L68*1)) -> 68894.894 | N68: =IF(C68="","",C68) -> Surcharged Transactions | O68: 0.0269421 | P68: =Q68/12 -> 127.25652 | Q68: =IF(O68>0,PRODUCT(I68,$O68),0) -> 1527.0782 | R68: =IF(Q68>0,PRODUCT(J68,$O68),0) -> 1603.4321 | S68: =IF(R68>0,PRODUCT(K68,$O68),0) -> 1683.6037 | T68: =IF(S68>0,PRODUCT(L68,$O68),0) -> 1767.7839 | U68: =IF(T68>0,PRODUCT(M68,$O68),0) -> 1856.1731 | V68: =SUM(Q68:U68) -> 8438.0712 | X68: =C68 -> Surcharged Transactions | Y68: NO CHARGE | Z68: =AA68/12 -> 0 | AA68: {=_xlfn.IFS($Y68="NO CHARGE",0,$Y68>0,$Y68*I68)} -> 0 | AB68: {=_xlfn.IFS($Y68="NO CHARGE",0,$Y68>0,$Y68*J68)} -> 0 | AC68: {=_xlfn.IFS($Y68="NO CHARGE",0,$Y68>0,$Y68*K68)} -> 0 | AD68: {=_xlfn.IFS($Y68="NO CHARGE",0,$Y68>0,$Y68*L68)} -> 0 | AE68: {=_xlfn.IFS($Y68="NO CHARGE",0,$Y68>0,$Y68*M68)} -> 0 | AF68: =SUM(AA68:AE68) -> 0 | AI68: =C68 -> Surcharged Transactions | AJ68: NO CHARGE | AK68: =AL68/12 -> 0 | AL68: {=_xlfn.IFS($AJ68="NO CHARGE",0,$AJ68=0,0,$AJ68>0,PRODUCT(I68,$AJ68))} -> 0 | AM68: {=_xlfn.IFS($AJ68="NO CHARGE",0,$AJ68=0,0,$AJ68>0,PRODUCT(J68,$AJ68))} -> 0 | AN68: {=_xlfn.IFS($AJ68="NO CHARGE",0,$AJ68=0,0,$AJ68>0,PRODUCT(K68,$AJ68))} -> 0 | AO68: {=_xlfn.IFS($AJ68="NO CHARGE",0,$AJ68=0,0,$AJ68>0,PRODUCT(L68,$AJ68))} -> 0 | AP68: {=_xlfn.IFS($AJ68="NO CHARGE",0,$AJ68=0,0,$AJ68>0,PRODUCT(M68,$AJ68))} -> 0 | AQ68: =SUM(AL68:AP68) -> 0
B69: PaymentsOne | C69: Stand-In Transactions | E69: 16006 | F69: 2580 | G69: 4654 | H69: =IFERROR(AVERAGE(D69:G69),0) -> 7746.6667 | I69: =H69*12 -> 92960 | J69: =IF(I69>12,(((I69)*$H$5)+I69),(I69*1)) -> 97608 | K69: =IF(J69>12,(((J69)*$H$5)+J69),(J69*1)) -> 102488.4 | L69: =IF(K69>12,(((K69)*$H$5)+K69),(K69*1)) -> 107612.82 | M69: =IF(L69>12,(((L69)*$H$5)+L69),(L69*1)) -> 112993.46 | N69: =IF(C69="","",C69) -> Stand-In Transactions | O69: 0.0269421 | P69: =Q69/12 -> 208.71147 | Q69: =IF(O69>0,PRODUCT(I69,$O69),0) -> 2504.5376 | R69: =IF(Q69>0,PRODUCT(J69,$O69),0) -> 2629.7645 | S69: =IF(R69>0,PRODUCT(K69,$O69),0) -> 2761.2527 | T69: =IF(S69>0,PRODUCT(L69,$O69),0) -> 2899.3154 | U69: =IF(T69>0,PRODUCT(M69,$O69),0) -> 3044.2811 | V69: =SUM(Q69:U69) -> 13839.151 | X69: =C69 -> Stand-In Transactions | Y69: NO CHARGE | Z69: =AA69/12 -> 0 | AA69: {=_xlfn.IFS($Y69="NO CHARGE",0,$Y69>0,$Y69*I69)} -> 0 | AB69: {=_xlfn.IFS($Y69="NO CHARGE",0,$Y69>0,$Y69*J69)} -> 0 | AC69: {=_xlfn.IFS($Y69="NO CHARGE",0,$Y69>0,$Y69*K69)} -> 0 | AD69: {=_xlfn.IFS($Y69="NO CHARGE",0,$Y69>0,$Y69*L69)} -> 0 | AE69: {=_xlfn.IFS($Y69="NO CHARGE",0,$Y69>0,$Y69*M69)} -> 0 | AF69: =SUM(AA69:AE69) -> 0 | AI69: =C69 -> Stand-In Transactions | AJ69: NO CHARGE | AK69: =AL69/12 -> 0 | AL69: {=_xlfn.IFS($AJ69="NO CHARGE",0,$AJ69=0,0,$AJ69>0,PRODUCT(I69,$AJ69))} -> 0 | AM69: {=_xlfn.IFS($AJ69="NO CHARGE",0,$AJ69=0,0,$AJ69>0,PRODUCT(J69,$AJ69))} -> 0 | AN69: {=_xlfn.IFS($AJ69="NO CHARGE",0,$AJ69=0,0,$AJ69>0,PRODUCT(K69,$AJ69))} -> 0 | AO69: {=_xlfn.IFS($AJ69="NO CHARGE",0,$AJ69=0,0,$AJ69>0,PRODUCT(L69,$AJ69))} -> 0 | AP69: {=_xlfn.IFS($AJ69="NO CHARGE",0,$AJ69=0,0,$AJ69>0,PRODUCT(M69,$AJ69))} -> 0 | AQ69: =SUM(AL69:AP69) -> 0
B70: PaymentsOne | C70: PIN Select/Change at IVR | E70: 556 | F70: 573 | G70: 710 | H70: =IFERROR(AVERAGE(D70:G70),0) -> 613 | I70: =H70*12 -> 7356 | J70: =IF(I70>12,(((I70)*$H$5)+I70),(I70*1)) -> 7723.8 | K70: =IF(J70>12,(((J70)*$H$5)+J70),(J70*1)) -> 8109.99 | L70: =IF(K70>12,(((K70)*$H$5)+K70),(K70*1)) -> 8515.4895 | M70: =IF(L70>12,(((L70)*$H$5)+L70),(L70*1)) -> 8941.264 | N70: =IF(C70="","",C70) -> PIN Select/Change at IVR | O70: 0.538841 | P70: =Q70/12 -> 330.30953 | Q70: =IF(O70>0,PRODUCT(I70,$O70),0) -> 3963.7144 | R70: =IF(Q70>0,PRODUCT(J70,$O70),0) -> 4161.9001 | S70: =IF(R70>0,PRODUCT(K70,$O70),0) -> 4369.9951 | T70: =IF(S70>0,PRODUCT(L70,$O70),0) -> 4588.4949 | U70: =IF(T70>0,PRODUCT(M70,$O70),0) -> 4817.9196 | V70: =SUM(Q70:U70) -> 21902.024 | X70: =C70 -> PIN Select/Change at IVR | Y70: 0.5388 | Z70: =AA70/12 -> 330.2844 | AA70: =IF(Y70>0,PRODUCT(I70,$Y70),0) -> 3963.4128 | AB70: =IF(AA70>0,PRODUCT(J70,$Y70),0) -> 4161.5834 | AC70: =IF(AB70>0,PRODUCT(K70,$Y70),0) -> 4369.6626 | AD70: =IF(AC70>0,PRODUCT(L70,$Y70),0) -> 4588.1457 | AE70: =IF(AD70>0,PRODUCT(M70,$Y70),0) -> 4817.553 | AF70: =SUM(AA70:AE70) -> 21900.358 | AI70: =C70 -> PIN Select/Change at IVR | AJ70: 0.5388 | AK70: =AL70/12 -> 330.2844 | AL70: {=_xlfn.IFS($AJ70="NO CHARGE",0,$AJ70=0,0,$AJ70>0,PRODUCT(I70,$AJ70))} -> 3963.4128 | AM70: {=_xlfn.IFS($AJ70="NO CHARGE",0,$AJ70=0,0,$AJ70>0,PRODUCT(J70,$AJ70))} -> 4161.5834 | AN70: {=_xlfn.IFS($AJ70="NO CHARGE",0,$AJ70=0,0,$AJ70>0,PRODUCT(K70,$AJ70))} -> 4369.6626 | AO70: {=_xlfn.IFS($AJ70="NO CHARGE",0,$AJ70=0,0,$AJ70>0,PRODUCT(L70,$AJ70))} -> 4588.1457 | AP70: {=_xlfn.IFS($AJ70="NO CHARGE",0,$AJ70=0,0,$AJ70>0,PRODUCT(M70,$AJ70))} -> 4817.553 | AQ70: =SUM(AL70:AP70) -> 21900.358
B71: PaymentsOne | C71: Network Connection - CIRRUS | E71: 1 | F71: 1 | G71: 1 | H71: =IFERROR(AVERAGE(D71:G71),0) -> 1 | I71: =H71*12 -> 12 | J71: =IF(I71>12,(((I71)*$H$5)+I71),(I71*1)) -> 12 | K71: =IF(J71>12,(((J71)*$H$5)+J71),(J71*1)) -> 12 | L71: =IF(K71>12,(((K71)*$H$5)+K71),(K71*1)) -> 12 | M71: =IF(L71>12,(((L71)*$H$5)+L71),(L71*1)) -> 12 | N71: =IF(C71="","",C71) -> Network Connection - CIRRUS | O71: 53.88 | P71: =Q71/12 -> 53.88 | Q71: =IF(O71>0,PRODUCT(I71,$O71),0) -> 646.56 | R71: =IF(Q71>0,PRODUCT(J71,$O71),0) -> 646.56 | S71: =IF(R71>0,PRODUCT(K71,$O71),0) -> 646.56 | T71: =IF(S71>0,PRODUCT(L71,$O71),0) -> 646.56 | U71: =IF(T71>0,PRODUCT(M71,$O71),0) -> 646.56 | V71: =SUM(Q71:U71) -> 3232.8 | X71: =C71 -> Network Connection - CIRRUS | Y71: 53.88 | Z71: =AA71/12 -> 53.88 | AA71: =IF(Y71>0,PRODUCT(I71,$Y71),0) -> 646.56 | AB71: =IF(AA71>0,PRODUCT(J71,$Y71),0) -> 646.56 | AC71: =IF(AB71>0,PRODUCT(K71,$Y71),0) -> 646.56 | AD71: =IF(AC71>0,PRODUCT(L71,$Y71),0) -> 646.56 | AE71: =IF(AD71>0,PRODUCT(M71,$Y71),0) -> 646.56 | AF71: =SUM(AA71:AE71) -> 3232.8 | AI71: =C71 -> Network Connection - CIRRUS | AJ71: 53.88 | AK71: =AL71/12 -> 53.88 | AL71: {=_xlfn.IFS($AJ71="NO CHARGE",0,$AJ71=0,0,$AJ71>0,PRODUCT(I71,$AJ71))} -> 646.56 | AM71: {=_xlfn.IFS($AJ71="NO CHARGE",0,$AJ71=0,0,$AJ71>0,PRODUCT(J71,$AJ71))} -> 646.56 | AN71: {=_xlfn.IFS($AJ71="NO CHARGE",0,$AJ71=0,0,$AJ71>0,PRODUCT(K71,$AJ71))} -> 646.56 | AO71: {=_xlfn.IFS($AJ71="NO CHARGE",0,$AJ71=0,0,$AJ71>0,PRODUCT(L71,$AJ71))} -> 646.56 | AP71: {=_xlfn.IFS($AJ71="NO CHARGE",0,$AJ71=0,0,$AJ71>0,PRODUCT(M71,$AJ71))} -> 646.56 | AQ71: =SUM(AL71:AP71) -> 3232.8
B72: PaymentsOne | C72: Network Connection - NYCE | E72: 1 | F72: 1 | G72: 1 | H72: =IFERROR(AVERAGE(D72:G72),0) -> 1 | I72: =H72*12 -> 12 | J72: =IF(I72>12,(((I72)*$H$5)+I72),(I72*1)) -> 12 | K72: =IF(J72>12,(((J72)*$H$5)+J72),(J72*1)) -> 12 | L72: =IF(K72>12,(((K72)*$H$5)+K72),(K72*1)) -> 12 | M72: =IF(L72>12,(((L72)*$H$5)+L72),(L72*1)) -> 12 | N72: =IF(C72="","",C72) -> Network Connection - NYCE | O72: 53.88 | P72: =Q72/12 -> 53.88 | Q72: =IF(O72>0,PRODUCT(I72,$O72),0) -> 646.56 | R72: =IF(Q72>0,PRODUCT(J72,$O72),0) -> 646.56 | S72: =IF(R72>0,PRODUCT(K72,$O72),0) -> 646.56 | T72: =IF(S72>0,PRODUCT(L72,$O72),0) -> 646.56 | U72: =IF(T72>0,PRODUCT(M72,$O72),0) -> 646.56 | V72: =SUM(Q72:U72) -> 3232.8 | X72: =C72 -> Network Connection - NYCE | Y72: 53.88 | Z72: =AA72/12 -> 53.88 | AA72: =IF(Y72>0,PRODUCT(I72,$Y72),0) -> 646.56 | AB72: =IF(AA72>0,PRODUCT(J72,$Y72),0) -> 646.56 | AC72: =IF(AB72>0,PRODUCT(K72,$Y72),0) -> 646.56 | AD72: =IF(AC72>0,PRODUCT(L72,$Y72),0) -> 646.56 | AE72: =IF(AD72>0,PRODUCT(M72,$Y72),0) -> 646.56 | AF72: =SUM(AA72:AE72) -> 3232.8 | AI72: =C72 -> Network Connection - NYCE | AJ72: 53.88 | AK72: =AL72/12 -> 53.88 | AL72: {=_xlfn.IFS($AJ72="NO CHARGE",0,$AJ72=0,0,$AJ72>0,PRODUCT(I72,$AJ72))} -> 646.56 | AM72: {=_xlfn.IFS($AJ72="NO CHARGE",0,$AJ72=0,0,$AJ72>0,PRODUCT(J72,$AJ72))} -> 646.56 | AN72: {=_xlfn.IFS($AJ72="NO CHARGE",0,$AJ72=0,0,$AJ72>0,PRODUCT(K72,$AJ72))} -> 646.56 | AO72: {=_xlfn.IFS($AJ72="NO CHARGE",0,$AJ72=0,0,$AJ72>0,PRODUCT(L72,$AJ72))} -> 646.56 | AP72: {=_xlfn.IFS($AJ72="NO CHARGE",0,$AJ72=0,0,$AJ72>0,PRODUCT(M72,$AJ72))} -> 646.56 | AQ72: =SUM(AL72:AP72) -> 3232.8
B73: PaymentsOne | C73: Network Connection - PLUS | E73: 1 | F73: 1 | G73: 1 | H73: =IFERROR(AVERAGE(D73:G73),0) -> 1 | I73: =H73*12 -> 12 | J73: =IF(I73>12,(((I73)*$H$5)+I73),(I73*1)) -> 12 | K73: =IF(J73>12,(((J73)*$H$5)+J73),(J73*1)) -> 12 | L73: =IF(K73>12,(((K73)*$H$5)+K73),(K73*1)) -> 12 | M73: =IF(L73>12,(((L73)*$H$5)+L73),(L73*1)) -> 12 | N73: =IF(C73="","",C73) -> Network Connection - PLUS | O73: 53.88 | P73: =Q73/12 -> 53.88 | Q73: =IF(O73>0,PRODUCT(I73,$O73),0) -> 646.56 | R73: =IF(Q73>0,PRODUCT(J73,$O73),0) -> 646.56 | S73: =IF(R73>0,PRODUCT(K73,$O73),0) -> 646.56 | T73: =IF(S73>0,PRODUCT(L73,$O73),0) -> 646.56 | U73: =IF(T73>0,PRODUCT(M73,$O73),0) -> 646.56 | V73: =SUM(Q73:U73) -> 3232.8 | X73: =C73 -> Network Connection - PLUS | Y73: 53.88 | Z73: =AA73/12 -> 53.88 | AA73: =IF(Y73>0,PRODUCT(I73,$Y73),0) -> 646.56 | AB73: =IF(AA73>0,PRODUCT(J73,$Y73),0) -> 646.56 | AC73: =IF(AB73>0,PRODUCT(K73,$Y73),0) -> 646.56 | AD73: =IF(AC73>0,PRODUCT(L73,$Y73),0) -> 646.56 | AE73: =IF(AD73>0,PRODUCT(M73,$Y73),0) -> 646.56 | AF73: =SUM(AA73:AE73) -> 3232.8 | AI73: =C73 -> Network Connection - PLUS | AJ73: 53.88 | AK73: =AL73/12 -> 53.88 | AL73: {=_xlfn.IFS($AJ73="NO CHARGE",0,$AJ73=0,0,$AJ73>0,PRODUCT(I73,$AJ73))} -> 646.56 | AM73: {=_xlfn.IFS($AJ73="NO CHARGE",0,$AJ73=0,0,$AJ73>0,PRODUCT(J73,$AJ73))} -> 646.56 | AN73: {=_xlfn.IFS($AJ73="NO CHARGE",0,$AJ73=0,0,$AJ73>0,PRODUCT(K73,$AJ73))} -> 646.56 | AO73: {=_xlfn.IFS($AJ73="NO CHARGE",0,$AJ73=0,0,$AJ73>0,PRODUCT(L73,$AJ73))} -> 646.56 | AP73: {=_xlfn.IFS($AJ73="NO CHARGE",0,$AJ73=0,0,$AJ73>0,PRODUCT(M73,$AJ73))} -> 646.56 | AQ73: =SUM(AL73:AP73) -> 3232.8
B74: PaymentsOne | C74: Quarterly Reporting | E74: 1 | F74: 1 | G74: 1 | H74: =IFERROR(AVERAGE(D74:G74),0) -> 1 | I74: =H74*12 -> 12 | J74: =IF(I74>12,(((I74)*$H$5)+I74),(I74*1)) -> 12 | K74: =IF(J74>12,(((J74)*$H$5)+J74),(J74*1)) -> 12 | L74: =IF(K74>12,(((K74)*$H$5)+K74),(K74*1)) -> 12 | M74: =IF(L74>12,(((L74)*$H$5)+L74),(L74*1)) -> 12 | N74: =IF(C74="","",C74) -> Quarterly Reporting | O74: 35.92 | P74: =Q74/12 -> 35.92 | Q74: =IF(O74>0,PRODUCT(I74,$O74),0) -> 431.04 | R74: =IF(Q74>0,PRODUCT(J74,$O74),0) -> 431.04 | S74: =IF(R74>0,PRODUCT(K74,$O74),0) -> 431.04 | T74: =IF(S74>0,PRODUCT(L74,$O74),0) -> 431.04 | U74: =IF(T74>0,PRODUCT(M74,$O74),0) -> 431.04 | V74: =SUM(Q74:U74) -> 2155.2 | X74: =C74 -> Quarterly Reporting | Y74: 35.92 | Z74: =AA74/12 -> 35.92 | AA74: =IF(Y74>0,PRODUCT(I74,$Y74),0) -> 431.04 | AB74: =IF(AA74>0,PRODUCT(J74,$Y74),0) -> 431.04 | AC74: =IF(AB74>0,PRODUCT(K74,$Y74),0) -> 431.04 | AD74: =IF(AC74>0,PRODUCT(L74,$Y74),0) -> 431.04 | AE74: =IF(AD74>0,PRODUCT(M74,$Y74),0) -> 431.04 | AF74: =SUM(AA74:AE74) -> 2155.2 | AI74: =C74 -> Quarterly Reporting | AJ74: 35.92 | AK74: =AL74/12 -> 35.92 | AL74: {=_xlfn.IFS($AJ74="NO CHARGE",0,$AJ74=0,0,$AJ74>0,PRODUCT(I74,$AJ74))} -> 431.04 | AM74: {=_xlfn.IFS($AJ74="NO CHARGE",0,$AJ74=0,0,$AJ74>0,PRODUCT(J74,$AJ74))} -> 431.04 | AN74: {=_xlfn.IFS($AJ74="NO CHARGE",0,$AJ74=0,0,$AJ74>0,PRODUCT(K74,$AJ74))} -> 431.04 | AO74: {=_xlfn.IFS($AJ74="NO CHARGE",0,$AJ74=0,0,$AJ74>0,PRODUCT(L74,$AJ74))} -> 431.04 | AP74: {=_xlfn.IFS($AJ74="NO CHARGE",0,$AJ74=0,0,$AJ74>0,PRODUCT(M74,$AJ74))} -> 431.04 | AQ74: =SUM(AL74:AP74) -> 2155.2
B75: PaymentsOne | C75: Billing Account Updater - Accounts on File (Need Estimated QTY) | H75: 1 | I75: =H75*12 -> 12 | J75: =IF(I75>12,(((I75)*$H$5)+I75),(I75*1)) -> 12 | K75: =IF(J75>12,(((J75)*$H$5)+J75),(J75*1)) -> 12 | L75: =IF(K75>12,(((K75)*$H$5)+K75),(K75*1)) -> 12 | M75: =IF(L75>12,(((L75)*$H$5)+L75),(L75*1)) -> 12 | N75: (Item is not in Invoices Currently) | P75: =Q75/12 -> 0 | Q75: =IF(O75>0,PRODUCT(I75,$O75),0) -> 0 | R75: =IF(Q75>0,PRODUCT(J75,$O75),0) -> 0 | S75: =IF(R75>0,PRODUCT(K75,$O75),0) -> 0 | T75: =IF(S75>0,PRODUCT(L75,$O75),0) -> 0 | U75: =IF(T75>0,PRODUCT(M75,$O75),0) -> 0 | V75: =SUM(Q75:U75) -> 0 | X75: =C75 -> Billing Account Updater - Accounts on File (Need Estimated QTY) | Y75: 0.0059 | Z75: =AA75/12 -> 0.0059 | AA75: =IF(Y75>0,PRODUCT(I75,$Y75),0) -> 0.0708 | AB75: =IF(AA75>0,PRODUCT(J75,$Y75),0) -> 0.0708 | AC75: =IF(AB75>0,PRODUCT(K75,$Y75),0) -> 0.0708 | AD75: =IF(AC75>0,PRODUCT(L75,$Y75),0) -> 0.0708 | AE75: =IF(AD75>0,PRODUCT(M75,$Y75),0) -> 0.0708 | AF75: =SUM(AA75:AE75) -> 0.354 | AI75: =C75 -> Billing Account Updater - Accounts on File (Need Estimated QTY) | AJ75: 0.0059 | AK75: =AL75/12 -> 0.0059 | AL75: {=_xlfn.IFS($AJ75="NO CHARGE",0,$AJ75=0,0,$AJ75>0,PRODUCT(I75,$AJ75))} -> 0.0708 | AM75: {=_xlfn.IFS($AJ75="NO CHARGE",0,$AJ75=0,0,$AJ75>0,PRODUCT(J75,$AJ75))} -> 0.0708 | AN75: {=_xlfn.IFS($AJ75="NO CHARGE",0,$AJ75=0,0,$AJ75>0,PRODUCT(K75,$AJ75))} -> 0.0708 | AO75: {=_xlfn.IFS($AJ75="NO CHARGE",0,$AJ75=0,0,$AJ75>0,PRODUCT(L75,$AJ75))} -> 0.0708 | AP75: {=_xlfn.IFS($AJ75="NO CHARGE",0,$AJ75=0,0,$AJ75>0,PRODUCT(M75,$AJ75))} -> 0.0708 | AQ75: =SUM(AL75:AP75) -> 0.354 | AV75: =IF(AU75>0,PRODUCT(I75,$AU75),0) -> 0 | AW75: =IF(AV75>0,PRODUCT(J75,$AU75),0) -> 0 | AX75: =IF(AW75>0,PRODUCT(K75,$AU75),0) -> 0 | AY75: =IF(AX75>0,PRODUCT(L75,$AU75),0) -> 0 | AZ75: =IF(AY75>0,PRODUCT(M75,$AU75),0) -> 0 | BA75: =SUM(AV75:AZ75) -> 0
B76: PaymentsOne | C76: Billing Account Updater - Records on File (Need Estimated QTY) | H76: 1 | I76: =H76*12 -> 12 | J76: =IF(I76>12,(((I76)*$H$5)+I76),(I76*1)) -> 12 | K76: =IF(J76>12,(((J76)*$H$5)+J76),(J76*1)) -> 12 | L76: =IF(K76>12,(((K76)*$H$5)+K76),(K76*1)) -> 12 | M76: =IF(L76>12,(((L76)*$H$5)+L76),(L76*1)) -> 12 | N76: (Item is not in Invoices Currently) | P76: =Q76/12 -> 0 | Q76: =IF(O76>0,PRODUCT(I76,$O76),0) -> 0 | R76: =IF(Q76>0,PRODUCT(J76,$O76),0) -> 0 | S76: =IF(R76>0,PRODUCT(K76,$O76),0) -> 0 | T76: =IF(S76>0,PRODUCT(L76,$O76),0) -> 0 | U76: =IF(T76>0,PRODUCT(M76,$O76),0) -> 0 | V76: =SUM(Q76:U76) -> 0 | X76: =C76 -> Billing Account Updater - Records on File (Need Estimated QTY) | Y76: 0.066 | Z76: =AA76/12 -> 0.066 | AA76: =IF(Y76>0,PRODUCT(I76,$Y76),0) -> 0.792 | AB76: =IF(AA76>0,PRODUCT(J76,$Y76),0) -> 0.792 | AC76: =IF(AB76>0,PRODUCT(K76,$Y76),0) -> 0.792 | AD76: =IF(AC76>0,PRODUCT(L76,$Y76),0) -> 0.792 | AE76: =IF(AD76>0,PRODUCT(M76,$Y76),0) -> 0.792 | AF76: =SUM(AA76:AE76) -> 3.96 | AI76: =C76 -> Billing Account Updater - Records on File (Need Estimated QTY) | AJ76: 0.066 | AK76: =AL76/12 -> 0.066 | AL76: {=_xlfn.IFS($AJ76="NO CHARGE",0,$AJ76=0,0,$AJ76>0,PRODUCT(I76,$AJ76))} -> 0.792 | AM76: {=_xlfn.IFS($AJ76="NO CHARGE",0,$AJ76=0,0,$AJ76>0,PRODUCT(J76,$AJ76))} -> 0.792 | AN76: {=_xlfn.IFS($AJ76="NO CHARGE",0,$AJ76=0,0,$AJ76>0,PRODUCT(K76,$AJ76))} -> 0.792 | AO76: {=_xlfn.IFS($AJ76="NO CHARGE",0,$AJ76=0,0,$AJ76>0,PRODUCT(L76,$AJ76))} -> 0.792 | AP76: {=_xlfn.IFS($AJ76="NO CHARGE",0,$AJ76=0,0,$AJ76>0,PRODUCT(M76,$AJ76))} -> 0.792 | AQ76: =SUM(AL76:AP76) -> 3.96 | AV76: =IF(AU76>0,PRODUCT(I76,$AU76),0) -> 0 | AW76: =IF(AV76>0,PRODUCT(J76,$AU76),0) -> 0 | AX76: =IF(AW76>0,PRODUCT(K76,$AU76),0) -> 0 | AY76: =IF(AX76>0,PRODUCT(L76,$AU76),0) -> 0 | AZ76: =IF(AY76>0,PRODUCT(M76,$AU76),0) -> 0 | BA76: =SUM(AV76:AZ76) -> 0
B77: PaymentsOne | C77: Lost/Stolen Card Reporting | E77: 13 | F77: 12 | G77: 8 | H77: =IFERROR(AVERAGE(D77:G77),0) -> 11 | I77: =H77*12 -> 132 | J77: =IF(I77>12,(((I77)*$H$5)+I77),(I77*1)) -> 138.6 | K77: =IF(J77>12,(((J77)*$H$5)+J77),(J77*1)) -> 145.53 | L77: =IF(K77>12,(((K77)*$H$5)+K77),(K77*1)) -> 152.8065 | M77: =IF(L77>12,(((L77)*$H$5)+L77),(L77*1)) -> 160.44682 | N77: =IF(C77="","",C77) -> Lost/Stolen Card Reporting | O77: 8.8908791 | P77: =Q77/12 -> 97.79967 | Q77: =IF(O77>0,PRODUCT(I77,$O77),0) -> 1173.596 | R77: =IF(Q77>0,PRODUCT(J77,$O77),0) -> 1232.2758 | S77: =IF(R77>0,PRODUCT(K77,$O77),0) -> 1293.8896 | T77: =IF(S77>0,PRODUCT(L77,$O77),0) -> 1358.5841 | U77: =IF(T77>0,PRODUCT(M77,$O77),0) -> 1426.5133 | V77: =SUM(Q77:U77) -> 6484.859 | X77: =C77 -> Lost/Stolen Card Reporting | Y77: 8.8909 | Z77: =AA77/12 -> 97.7999 | AA77: =IF(Y77>0,PRODUCT(I77,$Y77),0) -> 1173.5988 | AB77: =IF(AA77>0,PRODUCT(J77,$Y77),0) -> 1232.2787 | AC77: =IF(AB77>0,PRODUCT(K77,$Y77),0) -> 1293.8927 | AD77: =IF(AC77>0,PRODUCT(L77,$Y77),0) -> 1358.5873 | AE77: =IF(AD77>0,PRODUCT(M77,$Y77),0) -> 1426.5167 | AF77: =SUM(AA77:AE77) -> 6484.8742 | AI77: =C77 -> Lost/Stolen Card Reporting | AJ77: 8.8909 | AK77: =AL77/12 -> 97.7999 | AL77: {=_xlfn.IFS($AJ77="NO CHARGE",0,$AJ77=0,0,$AJ77>0,PRODUCT(I77,$AJ77))} -> 1173.5988 | AM77: {=_xlfn.IFS($AJ77="NO CHARGE",0,$AJ77=0,0,$AJ77>0,PRODUCT(J77,$AJ77))} -> 1232.2787 | AN77: {=_xlfn.IFS($AJ77="NO CHARGE",0,$AJ77=0,0,$AJ77>0,PRODUCT(K77,$AJ77))} -> 1293.8927 | AO77: {=_xlfn.IFS($AJ77="NO CHARGE",0,$AJ77=0,0,$AJ77>0,PRODUCT(L77,$AJ77))} -> 1358.5873 | AP77: {=_xlfn.IFS($AJ77="NO CHARGE",0,$AJ77=0,0,$AJ77>0,PRODUCT(M77,$AJ77))} -> 1426.5167 | AQ77: =SUM(AL77:AP77) -> 6484.8742
B78: PaymentsOne | C78: Lost/Stolen Services | E78: 1 | F78: 1 | G78: 1 | H78: =IFERROR(AVERAGE(D78:G78),0) -> 1 | I78: =H78*12 -> 12 | J78: =IF(I78>12,(((I78)*$H$5)+I78),(I78*1)) -> 12 | K78: =IF(J78>12,(((J78)*$H$5)+J78),(J78*1)) -> 12 | L78: =IF(K78>12,(((K78)*$H$5)+K78),(K78*1)) -> 12 | M78: =IF(L78>12,(((L78)*$H$5)+L78),(L78*1)) -> 12 | N78: =IF(C78="","",C78) -> Lost/Stolen Services | O78: 26.94 | P78: =Q78/12 -> 26.94 | Q78: =IF(O78>0,PRODUCT(I78,$O78),0) -> 323.28 | R78: =IF(Q78>0,PRODUCT(J78,$O78),0) -> 323.28 | S78: =IF(R78>0,PRODUCT(K78,$O78),0) -> 323.28 | T78: =IF(S78>0,PRODUCT(L78,$O78),0) -> 323.28 | U78: =IF(T78>0,PRODUCT(M78,$O78),0) -> 323.28 | V78: =SUM(Q78:U78) -> 1616.4 | X78: =C78 -> Lost/Stolen Services | Y78: NO CHARGE | Z78: =AA78/12 -> 0 | AA78: {=_xlfn.IFS($Y78="NO CHARGE",0,$Y78>0,$Y78*I78)} -> 0 | AB78: {=_xlfn.IFS($Y78="NO CHARGE",0,$Y78>0,$Y78*J78)} -> 0 | AC78: {=_xlfn.IFS($Y78="NO CHARGE",0,$Y78>0,$Y78*K78)} -> 0 | AD78: {=_xlfn.IFS($Y78="NO CHARGE",0,$Y78>0,$Y78*L78)} -> 0 | AE78: {=_xlfn.IFS($Y78="NO CHARGE",0,$Y78>0,$Y78*M78)} -> 0 | AF78: =SUM(AA78:AE78) -> 0 | AI78: =C78 -> Lost/Stolen Services | AJ78: NO CHARGE | AK78: =AL78/12 -> 0 | AL78: {=_xlfn.IFS($AJ78="NO CHARGE",0,$AJ78=0,0,$AJ78>0,PRODUCT(I78,$AJ78))} -> 0 | AM78: {=_xlfn.IFS($AJ78="NO CHARGE",0,$AJ78=0,0,$AJ78>0,PRODUCT(J78,$AJ78))} -> 0 | AN78: {=_xlfn.IFS($AJ78="NO CHARGE",0,$AJ78=0,0,$AJ78>0,PRODUCT(K78,$AJ78))} -> 0 | AO78: {=_xlfn.IFS($AJ78="NO CHARGE",0,$AJ78=0,0,$AJ78>0,PRODUCT(L78,$AJ78))} -> 0 | AP78: {=_xlfn.IFS($AJ78="NO CHARGE",0,$AJ78=0,0,$AJ78>0,PRODUCT(M78,$AJ78))} -> 0 | AQ78: =SUM(AL78:AP78) -> 0
B79: PaymentsOne | C79: Electronic Journaling (EJ) Report | E79: 1 | F79: 1 | G79: 1 | H79: =IFERROR(AVERAGE(D79:G79),0) -> 1 | I79: =H79*12 -> 12 | J79: =IF(I79>12,(((I79)*$H$5)+I79),(I79*1)) -> 12 | K79: =IF(J79>12,(((J79)*$H$5)+J79),(J79*1)) -> 12 | L79: =IF(K79>12,(((K79)*$H$5)+K79),(K79*1)) -> 12 | M79: =IF(L79>12,(((L79)*$H$5)+L79),(L79*1)) -> 12 | N79: =IF(C79="","",C79) -> Electronic Journaling (EJ) Report | O79: 8.890879 | P79: =Q79/12 -> 8.890879 | Q79: =IF(O79>0,PRODUCT(I79,$O79),0) -> 106.69055 | R79: =IF(Q79>0,PRODUCT(J79,$O79),0) -> 106.69055 | S79: =IF(R79>0,PRODUCT(K79,$O79),0) -> 106.69055 | T79: =IF(S79>0,PRODUCT(L79,$O79),0) -> 106.69055 | U79: =IF(T79>0,PRODUCT(M79,$O79),0) -> 106.69055 | V79: =SUM(Q79:U79) -> 533.45274 | X79: =C79 -> Electronic Journaling (EJ) Report | Y79: NO CHARGE | Z79: =AA79/12 -> 0 | AA79: {=_xlfn.IFS($Y79="NO CHARGE",0,$Y79>0,$Y79*I79)} -> 0 | AB79: {=_xlfn.IFS($Y79="NO CHARGE",0,$Y79>0,$Y79*J79)} -> 0 | AC79: {=_xlfn.IFS($Y79="NO CHARGE",0,$Y79>0,$Y79*K79)} -> 0 | AD79: {=_xlfn.IFS($Y79="NO CHARGE",0,$Y79>0,$Y79*L79)} -> 0 | AE79: {=_xlfn.IFS($Y79="NO CHARGE",0,$Y79>0,$Y79*M79)} -> 0 | AF79: =SUM(AA79:AE79) -> 0 | AI79: =C79 -> Electronic Journaling (EJ) Report | AJ79: NO CHARGE | AK79: =AL79/12 -> 0 | AL79: {=_xlfn.IFS($AJ79="NO CHARGE",0,$AJ79=0,0,$AJ79>0,PRODUCT(I79,$AJ79))} -> 0 | AM79: {=_xlfn.IFS($AJ79="NO CHARGE",0,$AJ79=0,0,$AJ79>0,PRODUCT(J79,$AJ79))} -> 0 | AN79: {=_xlfn.IFS($AJ79="NO CHARGE",0,$AJ79=0,0,$AJ79>0,PRODUCT(K79,$AJ79))} -> 0 | AO79: {=_xlfn.IFS($AJ79="NO CHARGE",0,$AJ79=0,0,$AJ79>0,PRODUCT(L79,$AJ79))} -> 0 | AP79: {=_xlfn.IFS($AJ79="NO CHARGE",0,$AJ79=0,0,$AJ79>0,PRODUCT(M79,$AJ79))} -> 0 | AQ79: =SUM(AL79:AP79) -> 0
B80: PaymentsOne | C80: Electronic Journaling (EJ) Support | E80: 7 | F80: 7 | G80: 7 | H80: =IFERROR(AVERAGE(D80:G80),0) -> 7 | I80: =H80*12 -> 84 | J80: =IF(I80>12,(((I80)*$H$5)+I80),(I80*1)) -> 88.2 | K80: =IF(J80>12,(((J80)*$H$5)+J80),(J80*1)) -> 92.61 | L80: =IF(K80>12,(((K80)*$H$5)+K80),(K80*1)) -> 97.2405 | M80: =IF(L80>12,(((L80)*$H$5)+L80),(L80*1)) -> 102.10252 | N80: =IF(C80="","",C80) -> Electronic Journaling (EJ) Support | O80: 10.776823 | P80: =Q80/12 -> 75.437762 | Q80: =IF(O80>0,PRODUCT(I80,$O80),0) -> 905.25315 | R80: =IF(Q80>0,PRODUCT(J80,$O80),0) -> 950.51581 | S80: =IF(R80>0,PRODUCT(K80,$O80),0) -> 998.0416 | T80: =IF(S80>0,PRODUCT(L80,$O80),0) -> 1047.9437 | U80: =IF(T80>0,PRODUCT(M80,$O80),0) -> 1100.3409 | V80: =SUM(Q80:U80) -> 5002.0951 | X80: =C80 -> Electronic Journaling (EJ) Support | Y80: 10.7768 | Z80: =AA80/12 -> 75.4376 | AA80: =IF(Y80>0,PRODUCT(I80,$Y80),0) -> 905.2512 | AB80: =IF(AA80>0,PRODUCT(J80,$Y80),0) -> 950.51376 | AC80: =IF(AB80>0,PRODUCT(K80,$Y80),0) -> 998.03945 | AD80: =IF(AC80>0,PRODUCT(L80,$Y80),0) -> 1047.9414 | AE80: =IF(AD80>0,PRODUCT(M80,$Y80),0) -> 1100.3385 | AF80: =SUM(AA80:AE80) -> 5002.0843 | AI80: =C80 -> Electronic Journaling (EJ) Support | AJ80: 10.7768 | AK80: =AL80/12 -> 75.4376 | AL80: {=_xlfn.IFS($AJ80="NO CHARGE",0,$AJ80=0,0,$AJ80>0,PRODUCT(I80,$AJ80))} -> 905.2512 | AM80: {=_xlfn.IFS($AJ80="NO CHARGE",0,$AJ80=0,0,$AJ80>0,PRODUCT(J80,$AJ80))} -> 950.51376 | AN80: {=_xlfn.IFS($AJ80="NO CHARGE",0,$AJ80=0,0,$AJ80>0,PRODUCT(K80,$AJ80))} -> 998.03945 | AO80: {=_xlfn.IFS($AJ80="NO CHARGE",0,$AJ80=0,0,$AJ80>0,PRODUCT(L80,$AJ80))} -> 1047.9414 | AP80: {=_xlfn.IFS($AJ80="NO CHARGE",0,$AJ80=0,0,$AJ80>0,PRODUCT(M80,$AJ80))} -> 1100.3385 | AQ80: =SUM(AL80:AP80) -> 5002.0843
B81: PaymentsOne | C81: Debit Card Base-Consumer | E81: 3 | F81: 3 | G81: 3 | H81: =IFERROR(AVERAGE(D81:G81),0) -> 3 | I81: =H81*12 -> 36 | J81: =IF(I81>12,(((I81)*$H$5)+I81),(I81*1)) -> 37.8 | K81: =IF(J81>12,(((J81)*$H$5)+J81),(J81*1)) -> 39.69 | L81: =IF(K81>12,(((K81)*$H$5)+K81),(K81*1)) -> 41.6745 | M81: =IF(L81>12,(((L81)*$H$5)+L81),(L81*1)) -> 43.758225 | N81: =IF(C81="","",C81) -> Debit Card Base-Consumer | O81: 96.99 | P81: =Q81/12 -> 290.97 | Q81: =IF(O81>0,PRODUCT(I81,$O81),0) -> 3491.64 | R81: =IF(Q81>0,PRODUCT(J81,$O81),0) -> 3666.222 | S81: =IF(R81>0,PRODUCT(K81,$O81),0) -> 3849.5331 | T81: =IF(S81>0,PRODUCT(L81,$O81),0) -> 4042.0098 | U81: =IF(T81>0,PRODUCT(M81,$O81),0) -> 4244.1102 | V81: =SUM(Q81:U81) -> 19293.515 | X81: =C81 -> Debit Card Base-Consumer | Y81: NO CHARGE | Z81: =AA81/12 -> 0 | AA81: {=_xlfn.IFS($Y81="NO CHARGE",0,$Y81>0,$Y81*I81)} -> 0 | AB81: {=_xlfn.IFS($Y81="NO CHARGE",0,$Y81>0,$Y81*J81)} -> 0 | AC81: {=_xlfn.IFS($Y81="NO CHARGE",0,$Y81>0,$Y81*K81)} -> 0 | AD81: {=_xlfn.IFS($Y81="NO CHARGE",0,$Y81>0,$Y81*L81)} -> 0 | AE81: {=_xlfn.IFS($Y81="NO CHARGE",0,$Y81>0,$Y81*M81)} -> 0 | AF81: =SUM(AA81:AE81) -> 0 | AI81: =C81 -> Debit Card Base-Consumer | AJ81: NO CHARGE | AK81: =AL81/12 -> 0 | AL81: {=_xlfn.IFS($AJ81="NO CHARGE",0,$AJ81=0,0,$AJ81>0,PRODUCT(I81,$AJ81))} -> 0 | AM81: {=_xlfn.IFS($AJ81="NO CHARGE",0,$AJ81=0,0,$AJ81>0,PRODUCT(J81,$AJ81))} -> 0 | AN81: {=_xlfn.IFS($AJ81="NO CHARGE",0,$AJ81=0,0,$AJ81>0,PRODUCT(K81,$AJ81))} -> 0 | AO81: {=_xlfn.IFS($AJ81="NO CHARGE",0,$AJ81=0,0,$AJ81>0,PRODUCT(L81,$AJ81))} -> 0 | AP81: {=_xlfn.IFS($AJ81="NO CHARGE",0,$AJ81=0,0,$AJ81>0,PRODUCT(M81,$AJ81))} -> 0 | AQ81: =SUM(AL81:AP81) -> 0
B82: PaymentsOne | C82: Affiliate Management Fee | E82: 224162 | F82: 211184 | G82: 216309 | H82: 1 | I82: =H82*12 -> 12 | J82: =IF(I82>12,(((I82)*$H$5)+I82),(I82*1)) -> 12 | K82: =IF(J82>12,(((J82)*$H$5)+J82),(J82*1)) -> 12 | L82: =IF(K82>12,(((K82)*$H$5)+K82),(K82*1)) -> 12 | M82: =IF(L82>12,(((L82)*$H$5)+L82),(L82*1)) -> 12 | N82: =IF(C82="","",C82) -> Affiliate Management Fee | O82: 26.94 | P82: =Q82/12 -> 26.94 | Q82: =IF(O82>0,PRODUCT(I82,$O82),0) -> 323.28 | R82: =IF(Q82>0,PRODUCT(J82,$O82),0) -> 323.28 | S82: =IF(R82>0,PRODUCT(K82,$O82),0) -> 323.28 | T82: =IF(S82>0,PRODUCT(L82,$O82),0) -> 323.28 | U82: =IF(T82>0,PRODUCT(M82,$O82),0) -> 323.28 | V82: =SUM(Q82:U82) -> 1616.4 | X82: =C82 -> Affiliate Management Fee | Y82: NO CHARGE | Z82: =AA82/12 -> 0 | AA82: {=_xlfn.IFS($Y82="NO CHARGE",0,$Y82>0,$Y82*I82)} -> 0 | AB82: {=_xlfn.IFS($Y82="NO CHARGE",0,$Y82>0,$Y82*J82)} -> 0 | AC82: {=_xlfn.IFS($Y82="NO CHARGE",0,$Y82>0,$Y82*K82)} -> 0 | AD82: {=_xlfn.IFS($Y82="NO CHARGE",0,$Y82>0,$Y82*L82)} -> 0 | AE82: {=_xlfn.IFS($Y82="NO CHARGE",0,$Y82>0,$Y82*M82)} -> 0 | AF82: =SUM(AA82:AE82) -> 0 | AI82: =C82 -> Affiliate Management Fee | AJ82: NO CHARGE | AK82: =AL82/12 -> 0 | AL82: {=_xlfn.IFS($AJ82="NO CHARGE",0,$AJ82=0,0,$AJ82>0,PRODUCT(I82,$AJ82))} -> 0 | AM82: {=_xlfn.IFS($AJ82="NO CHARGE",0,$AJ82=0,0,$AJ82>0,PRODUCT(J82,$AJ82))} -> 0 | AN82: {=_xlfn.IFS($AJ82="NO CHARGE",0,$AJ82=0,0,$AJ82>0,PRODUCT(K82,$AJ82))} -> 0 | AO82: {=_xlfn.IFS($AJ82="NO CHARGE",0,$AJ82=0,0,$AJ82>0,PRODUCT(L82,$AJ82))} -> 0 | AP82: {=_xlfn.IFS($AJ82="NO CHARGE",0,$AJ82=0,0,$AJ82>0,PRODUCT(M82,$AJ82))} -> 0 | AQ82: =SUM(AL82:AP82) -> 0
B83: PaymentsOne | C83: Automated General Ledger (GL) Entries | E83: 1 | F83: 1 | G83: 1 | H83: =IFERROR(AVERAGE(D83:G83),0) -> 1 | I83: =H83*12 -> 12 | J83: =IF(I83>12,(((I83)*$H$5)+I83),(I83*1)) -> 12 | K83: =IF(J83>12,(((J83)*$H$5)+J83),(J83*1)) -> 12 | L83: =IF(K83>12,(((K83)*$H$5)+K83),(K83*1)) -> 12 | M83: =IF(L83>12,(((L83)*$H$5)+L83),(L83*1)) -> 12 | N83: =IF(C83="","",C83) -> Automated General Ledger (GL) Entries | O83: 53.88 | P83: =Q83/12 -> 53.88 | Q83: =IF(O83>0,PRODUCT(I83,$O83),0) -> 646.56 | R83: =IF(Q83>0,PRODUCT(J83,$O83),0) -> 646.56 | S83: =IF(R83>0,PRODUCT(K83,$O83),0) -> 646.56 | T83: =IF(S83>0,PRODUCT(L83,$O83),0) -> 646.56 | U83: =IF(T83>0,PRODUCT(M83,$O83),0) -> 646.56 | V83: =SUM(Q83:U83) -> 3232.8 | X83: =C83 -> Automated General Ledger (GL) Entries | Y83: NO CHARGE | Z83: =AA83/12 -> 0 | AA83: {=_xlfn.IFS($Y83="NO CHARGE",0,$Y83>0,$Y83*I83)} -> 0 | AB83: {=_xlfn.IFS($Y83="NO CHARGE",0,$Y83>0,$Y83*J83)} -> 0 | AC83: {=_xlfn.IFS($Y83="NO CHARGE",0,$Y83>0,$Y83*K83)} -> 0 | AD83: {=_xlfn.IFS($Y83="NO CHARGE",0,$Y83>0,$Y83*L83)} -> 0 | AE83: {=_xlfn.IFS($Y83="NO CHARGE",0,$Y83>0,$Y83*M83)} -> 0 | AF83: =SUM(AA83:AE83) -> 0 | AI83: =C83 -> Automated General Ledger (GL) Entries | AJ83: NO CHARGE | AK83: =AL83/12 -> 0 | AL83: {=_xlfn.IFS($AJ83="NO CHARGE",0,$AJ83=0,0,$AJ83>0,PRODUCT(I83,$AJ83))} -> 0 | AM83: {=_xlfn.IFS($AJ83="NO CHARGE",0,$AJ83=0,0,$AJ83>0,PRODUCT(J83,$AJ83))} -> 0 | AN83: {=_xlfn.IFS($AJ83="NO CHARGE",0,$AJ83=0,0,$AJ83>0,PRODUCT(K83,$AJ83))} -> 0 | AO83: {=_xlfn.IFS($AJ83="NO CHARGE",0,$AJ83=0,0,$AJ83>0,PRODUCT(L83,$AJ83))} -> 0 | AP83: {=_xlfn.IFS($AJ83="NO CHARGE",0,$AJ83=0,0,$AJ83>0,PRODUCT(M83,$AJ83))} -> 0 | AQ83: =SUM(AL83:AP83) -> 0
B84: PaymentsOne | C84: CARD Access Services | H84: 1 | I84: =H84*12 -> 12 | J84: =IF(I84>12,(((I84)*$H$5)+I84),(I84*1)) -> 12 | K84: =IF(J84>12,(((J84)*$H$5)+J84),(J84*1)) -> 12 | L84: =IF(K84>12,(((K84)*$H$5)+K84),(K84*1)) -> 12 | M84: =IF(L84>12,(((L84)*$H$5)+L84),(L84*1)) -> 12 | N84: =IF(C84="","",C84) -> CARD Access Services | O84: 107.77 | P84: =Q84/12 -> 107.77 | Q84: =IF(O84>0,PRODUCT(I84,$O84),0) -> 1293.24 | R84: =IF(Q84>0,PRODUCT(J84,$O84),0) -> 1293.24 | S84: =IF(R84>0,PRODUCT(K84,$O84),0) -> 1293.24 | T84: =IF(S84>0,PRODUCT(L84,$O84),0) -> 1293.24 | U84: =IF(T84>0,PRODUCT(M84,$O84),0) -> 1293.24 | V84: =SUM(Q84:U84) -> 6466.2 | W84: From 04/14/2023 Invoice#101101310 | X84: =C84 -> CARD Access Services | Y84: NO CHARGE | Z84: =AA84/12 -> 0 | AA84: {=_xlfn.IFS($Y84="NO CHARGE",0,$Y84>0,$Y84*I84)} -> 0 | AB84: {=_xlfn.IFS($Y84="NO CHARGE",0,$Y84>0,$Y84*J84)} -> 0 | AC84: {=_xlfn.IFS($Y84="NO CHARGE",0,$Y84>0,$Y84*K84)} -> 0 | AD84: {=_xlfn.IFS($Y84="NO CHARGE",0,$Y84>0,$Y84*L84)} -> 0 | AE84: {=_xlfn.IFS($Y84="NO CHARGE",0,$Y84>0,$Y84*M84)} -> 0 | AF84: =SUM(AA84:AE84) -> 0 | AI84: =C84 -> CARD Access Services | AJ84: NO CHARGE | AK84: =AL84/12 -> 0 | AL84: {=_xlfn.IFS($AJ84="NO CHARGE",0,$AJ84=0,0,$AJ84>0,PRODUCT(I84,$AJ84))} -> 0 | AM84: {=_xlfn.IFS($AJ84="NO CHARGE",0,$AJ84=0,0,$AJ84>0,PRODUCT(J84,$AJ84))} -> 0 | AN84: {=_xlfn.IFS($AJ84="NO CHARGE",0,$AJ84=0,0,$AJ84>0,PRODUCT(K84,$AJ84))} -> 0 | AO84: {=_xlfn.IFS($AJ84="NO CHARGE",0,$AJ84=0,0,$AJ84>0,PRODUCT(L84,$AJ84))} -> 0 | AP84: {=_xlfn.IFS($AJ84="NO CHARGE",0,$AJ84=0,0,$AJ84>0,PRODUCT(M84,$AJ84))} -> 0 | AQ84: =SUM(AL84:AP84) -> 0 | AV84: =IF(AU84>0,PRODUCT(I84,$AU84),0) -> 0 | AW84: =IF(AV84>0,PRODUCT(J84,$AU84),0) -> 0 | AX84: =IF(AW84>0,PRODUCT(K84,$AU84),0) -> 0 | AY84: =IF(AX84>0,PRODUCT(L84,$AU84),0) -> 0 | AZ84: =IF(AY84>0,PRODUCT(M84,$AU84),0) -> 0 | BA84: =SUM(AV84:AZ84) -> 0
B85: PaymentsOne | C85: File Delivery - File and Non Package File Handling (Need Estimated QTY) | H85: 1 | I85: =H85*12 -> 12 | J85: =IF(I85>12,(((I85)*$H$5)+I85),(I85*1)) -> 12 | K85: =IF(J85>12,(((J85)*$H$5)+J85),(J85*1)) -> 12 | L85: =IF(K85>12,(((K85)*$H$5)+K85),(K85*1)) -> 12 | M85: =IF(L85>12,(((L85)*$H$5)+L85),(L85*1)) -> 12 | N85: (Item is not in Invoices Currently) | P85: =Q85/12 -> 0 | Q85: =IF(O85>0,PRODUCT(I85,$O85),0) -> 0 | R85: =IF(Q85>0,PRODUCT(J85,$O85),0) -> 0 | S85: =IF(R85>0,PRODUCT(K85,$O85),0) -> 0 | T85: =IF(S85>0,PRODUCT(L85,$O85),0) -> 0 | U85: =IF(T85>0,PRODUCT(M85,$O85),0) -> 0 | V85: =SUM(Q85:U85) -> 0 | X85: =C85 -> File Delivery - File and Non Package File Handling (Need Estimated QTY) | Y85: 10 | Z85: =AA85/12 -> 10 | AA85: =IF(Y85>0,PRODUCT(I85,$Y85),0) -> 120 | AB85: =IF(AA85>0,PRODUCT(J85,$Y85),0) -> 120 | AC85: =IF(AB85>0,PRODUCT(K85,$Y85),0) -> 120 | AD85: =IF(AC85>0,PRODUCT(L85,$Y85),0) -> 120 | AE85: =IF(AD85>0,PRODUCT(M85,$Y85),0) -> 120 | AF85: =SUM(AA85:AE85) -> 600 | AI85: =C85 -> File Delivery - File and Non Package File Handling (Need Estimated QTY) | AJ85: 10 | AK85: =AL85/12 -> 10 | AL85: {=_xlfn.IFS($AJ85="NO CHARGE",0,$AJ85=0,0,$AJ85>0,PRODUCT(I85,$AJ85))} -> 120 | AM85: {=_xlfn.IFS($AJ85="NO CHARGE",0,$AJ85=0,0,$AJ85>0,PRODUCT(J85,$AJ85))} -> 120 | AN85: {=_xlfn.IFS($AJ85="NO CHARGE",0,$AJ85=0,0,$AJ85>0,PRODUCT(K85,$AJ85))} -> 120 | AO85: {=_xlfn.IFS($AJ85="NO CHARGE",0,$AJ85=0,0,$AJ85>0,PRODUCT(L85,$AJ85))} -> 120 | AP85: {=_xlfn.IFS($AJ85="NO CHARGE",0,$AJ85=0,0,$AJ85>0,PRODUCT(M85,$AJ85))} -> 120 | AQ85: =SUM(AL85:AP85) -> 600 | AV85: =IF(AU85>0,PRODUCT(I85,$AU85),0) -> 0 | AW85: =IF(AV85>0,PRODUCT(J85,$AU85),0) -> 0 | AX85: =IF(AW85>0,PRODUCT(K85,$AU85),0) -> 0 | AY85: =IF(AX85>0,PRODUCT(L85,$AU85),0) -> 0 | AZ85: =IF(AY85>0,PRODUCT(M85,$AU85),0) -> 0 | BA85: =SUM(AV85:AZ85) -> 0
H86: =IFERROR(AVERAGE(D86:G86),0) -> 0 | I86: =H86*12 -> 0 | J86: =IF(I86>12,(((I86)*$H$5)+I86),(I86*1)) -> 0 | K86: =IF(J86>12,(((J86)*$H$5)+J86),(J86*1)) -> 0 | L86: =IF(K86>12,(((K86)*$H$5)+K86),(K86*1)) -> 0 | M86: =IF(L86>12,(((L86)*$H$5)+L86),(L86*1)) -> 0 | N86: =IF(C86="","",C86) | P86: =Q86/12 -> 0 | Q86: =IF(O86>0,PRODUCT(I86,$O86),0) -> 0 | R86: =IF(Q86>0,PRODUCT(J86,$O86),0) -> 0 | S86: =IF(R86>0,PRODUCT(K86,$O86),0) -> 0 | T86: =IF(S86>0,PRODUCT(L86,$O86),0) -> 0 | U86: =IF(T86>0,PRODUCT(M86,$O86),0) -> 0 | V86: =SUM(Q86:U86) -> 0 | Z86: =AA86/12 -> 0 | AA86: =IF(Y86>0,PRODUCT(I86,$Y86),0) -> 0 | AB86: =IF(AA86>0,PRODUCT(J86,$Y86),0) -> 0 | AC86: =IF(AB86>0,PRODUCT(K86,$Y86),0) -> 0 | AD86: =IF(AC86>0,PRODUCT(L86,$Y86),0) -> 0 | AE86: =IF(AD86>0,PRODUCT(M86,$Y86),0) -> 0 | AF86: =SUM(AA86:AE86) -> 0 | AK86: =AL86/12 -> 0 | AL86: {=_xlfn.IFS($AJ86="NO CHARGE",0,$AJ86=0,0,$AJ86>0,PRODUCT(I86,$AJ86))} -> 0 | AM86: {=_xlfn.IFS($AJ86="NO CHARGE",0,$AJ86=0,0,$AJ86>0,PRODUCT(J86,$AJ86))} -> 0 | AN86: {=_xlfn.IFS($AJ86="NO CHARGE",0,$AJ86=0,0,$AJ86>0,PRODUCT(K86,$AJ86))} -> 0 | AO86: {=_xlfn.IFS($AJ86="NO CHARGE",0,$AJ86=0,0,$AJ86>0,PRODUCT(L86,$AJ86))} -> 0 | AP86: {=_xlfn.IFS($AJ86="NO CHARGE",0,$AJ86=0,0,$AJ86>0,PRODUCT(M86,$AJ86))} -> 0 | AQ86: =SUM(AL86:AP86) -> 0 | AV86: =IF(AU86>0,PRODUCT(I86,$AU86),0) -> 0 | AW86: =IF(AV86>0,PRODUCT(J86,$AU86),0) -> 0 | AX86: =IF(AW86>0,PRODUCT(K86,$AU86),0) -> 0 | AY86: =IF(AX86>0,PRODUCT(L86,$AU86),0) -> 0 | AZ86: =IF(AY86>0,PRODUCT(M86,$AU86),0) -> 0 | BA86: =SUM(AV86:AZ86) -> 0
B87: 3D Secure | C87: 3-D Secure Monthly Base Issuers Fee Hosted | H87: 1 | I87: =H87*12 -> 12 | J87: =IF(I87>12,(((I87)*$H$5)+I87),(I87*1)) -> 12 | K87: =IF(J87>12,(((J87)*$H$5)+J87),(J87*1)) -> 12 | L87: =IF(K87>12,(((K87)*$H$5)+K87),(K87*1)) -> 12 | M87: =IF(L87>12,(((L87)*$H$5)+L87),(L87*1)) -> 12 | N87: (Item is not in Invoices Currently) | P87: =Q87/12 -> 0 | Q87: =IF(O87>0,PRODUCT(I87,$O87),0) -> 0 | R87: =IF(Q87>0,PRODUCT(J87,$O87),0) -> 0 | S87: =IF(R87>0,PRODUCT(K87,$O87),0) -> 0 | T87: =IF(S87>0,PRODUCT(L87,$O87),0) -> 0 | U87: =IF(T87>0,PRODUCT(M87,$O87),0) -> 0 | V87: =SUM(Q87:U87) -> 0 | X87: =C87 -> 3-D Secure Monthly Base Issuers Fee Hosted | Y87: 150 | Z87: =AA87/12 -> 150 | AA87: =IF(Y87>0,PRODUCT(I87,$Y87),0) -> 1800 | AB87: =IF(AA87>0,PRODUCT(J87,$Y87),0) -> 1800 | AC87: =IF(AB87>0,PRODUCT(K87,$Y87),0) -> 1800 | AD87: =IF(AC87>0,PRODUCT(L87,$Y87),0) -> 1800 | AE87: =IF(AD87>0,PRODUCT(M87,$Y87),0) -> 1800 | AF87: =SUM(AA87:AE87) -> 9000 | AI87: =C87 -> 3-D Secure Monthly Base Issuers Fee Hosted | AJ87: 150 | AK87: =AL87/12 -> 150 | AL87: {=_xlfn.IFS($AJ87="NO CHARGE",0,$AJ87=0,0,$AJ87>0,PRODUCT(I87,$AJ87))} -> 1800 | AM87: {=_xlfn.IFS($AJ87="NO CHARGE",0,$AJ87=0,0,$AJ87>0,PRODUCT(J87,$AJ87))} -> 1800 | AN87: {=_xlfn.IFS($AJ87="NO CHARGE",0,$AJ87=0,0,$AJ87>0,PRODUCT(K87,$AJ87))} -> 1800 | AO87: {=_xlfn.IFS($AJ87="NO CHARGE",0,$AJ87=0,0,$AJ87>0,PRODUCT(L87,$AJ87))} -> 1800 | AP87: {=_xlfn.IFS($AJ87="NO CHARGE",0,$AJ87=0,0,$AJ87>0,PRODUCT(M87,$AJ87))} -> 1800 | AQ87: =SUM(AL87:AP87) -> 9000 | AV87: =IF(AU87>0,PRODUCT(I87,$AU87),0) -> 0 | AW87: =IF(AV87>0,PRODUCT(J87,$AU87),0) -> 0 | AX87: =IF(AW87>0,PRODUCT(K87,$AU87),0) -> 0 | AY87: =IF(AX87>0,PRODUCT(L87,$AU87),0) -> 0 | AZ87: =IF(AY87>0,PRODUCT(M87,$AU87),0) -> 0 | BA87: =SUM(AV87:AZ87) -> 0
B88: 3D Secure | C88: 3-D Secure Authentication Transaction Fee | H88: 2717 | I88: =H88*12 -> 32604 | J88: =IF(I88>12,(((I88)*$H$5)+I88),(I88*1)) -> 34234.2 | K88: =IF(J88>12,(((J88)*$H$5)+J88),(J88*1)) -> 35945.91 | L88: =IF(K88>12,(((K88)*$H$5)+K88),(K88*1)) -> 37743.205 | M88: =IF(L88>12,(((L88)*$H$5)+L88),(L88*1)) -> 39630.366 | N88: (Item is not in Invoices Currently) | P88: =Q88/12 -> 0 | Q88: =IF(O88>0,PRODUCT(I88,$O88),0) -> 0 | R88: =IF(Q88>0,PRODUCT(J88,$O88),0) -> 0 | S88: =IF(R88>0,PRODUCT(K88,$O88),0) -> 0 | T88: =IF(S88>0,PRODUCT(L88,$O88),0) -> 0 | U88: =IF(T88>0,PRODUCT(M88,$O88),0) -> 0 | V88: =SUM(Q88:U88) -> 0 | X88: =C88 -> 3-D Secure Authentication Transaction Fee | Y88: 0.1 | Z88: =AA88/12 -> 271.7 | AA88: =IF(Y88>0,PRODUCT(I88,$Y88),0) -> 3260.4 | AB88: =IF(AA88>0,PRODUCT(J88,$Y88),0) -> 3423.42 | AC88: =IF(AB88>0,PRODUCT(K88,$Y88),0) -> 3594.591 | AD88: =IF(AC88>0,PRODUCT(L88,$Y88),0) -> 3774.3205 | AE88: =IF(AD88>0,PRODUCT(M88,$Y88),0) -> 3963.0366 | AF88: =SUM(AA88:AE88) -> 18015.768 | AI88: =C88 -> 3-D Secure Authentication Transaction Fee | AJ88: 0.1 | AK88: =AL88/12 -> 271.7 | AL88: {=_xlfn.IFS($AJ88="NO CHARGE",0,$AJ88=0,0,$AJ88>0,PRODUCT(I88,$AJ88))} -> 3260.4 | AM88: {=_xlfn.IFS($AJ88="NO CHARGE",0,$AJ88=0,0,$AJ88>0,PRODUCT(J88,$AJ88))} -> 3423.42 | AN88: {=_xlfn.IFS($AJ88="NO CHARGE",0,$AJ88=0,0,$AJ88>0,PRODUCT(K88,$AJ88))} -> 3594.591 | AO88: {=_xlfn.IFS($AJ88="NO CHARGE",0,$AJ88=0,0,$AJ88>0,PRODUCT(L88,$AJ88))} -> 3774.3205 | AP88: {=_xlfn.IFS($AJ88="NO CHARGE",0,$AJ88=0,0,$AJ88>0,PRODUCT(M88,$AJ88))} -> 3963.0366 | AQ88: =SUM(AL88:AP88) -> 18015.768 | AV88: =IF(AU88>0,PRODUCT(I88,$AU88),0) -> 0 | AW88: =IF(AV88>0,PRODUCT(J88,$AU88),0) -> 0 | AX88: =IF(AW88>0,PRODUCT(K88,$AU88),0) -> 0 | AY88: =IF(AX88>0,PRODUCT(L88,$AU88),0) -> 0 | AZ88: =IF(AY88>0,PRODUCT(M88,$AU88),0) -> 0 | BA88: =SUM(AV88:AZ88) -> 0
B89: 3D Secure | C89: 3-D Secure One Time Passcode (OTP) | H89: 271 | I89: =H89*12 -> 3252 | J89: =IF(I89>12,(((I89)*$H$5)+I89),(I89*1)) -> 3414.6 | K89: =IF(J89>12,(((J89)*$H$5)+J89),(J89*1)) -> 3585.33 | L89: =IF(K89>12,(((K89)*$H$5)+K89),(K89*1)) -> 3764.5965 | M89: =IF(L89>12,(((L89)*$H$5)+L89),(L89*1)) -> 3952.8263 | N89: =IF(C89="","",C89) -> 3-D Secure One Time Passcode (OTP) | O89: 0.0215536 | P89: =Q89/12 -> 5.8410256 | Q89: =IF(O89>0,PRODUCT(I89,$O89),0) -> 70.092307 | R89: =IF(Q89>0,PRODUCT(J89,$O89),0) -> 73.596923 | S89: =IF(R89>0,PRODUCT(K89,$O89),0) -> 77.276769 | T89: =IF(S89>0,PRODUCT(L89,$O89),0) -> 81.140607 | U89: =IF(T89>0,PRODUCT(M89,$O89),0) -> 85.197637 | V89: =SUM(Q89:U89) -> 387.30424 | X89: =C89 -> 3-D Secure One Time Passcode (OTP) | Y89: 0.05 | Z89: =AA89/12 -> 13.55 | AA89: =IF(Y89>0,PRODUCT(I89,$Y89),0) -> 162.6 | AB89: =IF(AA89>0,PRODUCT(J89,$Y89),0) -> 170.73 | AC89: =IF(AB89>0,PRODUCT(K89,$Y89),0) -> 179.2665 | AD89: =IF(AC89>0,PRODUCT(L89,$Y89),0) -> 188.22983 | AE89: =IF(AD89>0,PRODUCT(M89,$Y89),0) -> 197.64132 | AF89: =SUM(AA89:AE89) -> 898.46764 | AI89: =C89 -> 3-D Secure One Time Passcode (OTP) | AJ89: 0.05 | AK89: =AL89/12 -> 13.55 | AL89: {=_xlfn.IFS($AJ89="NO CHARGE",0,$AJ89=0,0,$AJ89>0,PRODUCT(I89,$AJ89))} -> 162.6 | AM89: {=_xlfn.IFS($AJ89="NO CHARGE",0,$AJ89=0,0,$AJ89>0,PRODUCT(J89,$AJ89))} -> 170.73 | AN89: {=_xlfn.IFS($AJ89="NO CHARGE",0,$AJ89=0,0,$AJ89>0,PRODUCT(K89,$AJ89))} -> 179.2665 | AO89: {=_xlfn.IFS($AJ89="NO CHARGE",0,$AJ89=0,0,$AJ89>0,PRODUCT(L89,$AJ89))} -> 188.22983 | AP89: {=_xlfn.IFS($AJ89="NO CHARGE",0,$AJ89=0,0,$AJ89>0,PRODUCT(M89,$AJ89))} -> 197.64132 | AQ89: =SUM(AL89:AP89) -> 898.46764 | AV89: =IF(AU89>0,PRODUCT(I89,$AU89),0) -> 0 | AW89: =IF(AV89>0,PRODUCT(J89,$AU89),0) -> 0 | AX89: =IF(AW89>0,PRODUCT(K89,$AU89),0) -> 0 | AY89: =IF(AX89>0,PRODUCT(L89,$AU89),0) -> 0 | AZ89: =IF(AY89>0,PRODUCT(M89,$AU89),0) -> 0 | BA89: =SUM(AV89:AZ89) -> 0
H90: =IFERROR(AVERAGE(D90:G90),0) -> 0 | I90: =H90*12 -> 0 | J90: =IF(I90>12,(((I90)*$H$5)+I90),(I90*1)) -> 0 | K90: =IF(J90>12,(((J90)*$H$5)+J90),(J90*1)) -> 0 | L90: =IF(K90>12,(((K90)*$H$5)+K90),(K90*1)) -> 0 | M90: =IF(L90>12,(((L90)*$H$5)+L90),(L90*1)) -> 0 | N90: =IF(C90="","",C90) | P90: =Q90/12 -> 0 | Q90: =IF(O90>0,PRODUCT(I90,$O90),0) -> 0 | R90: =IF(Q90>0,PRODUCT(J90,$O90),0) -> 0 | S90: =IF(R90>0,PRODUCT(K90,$O90),0) -> 0 | T90: =IF(S90>0,PRODUCT(L90,$O90),0) -> 0 | U90: =IF(T90>0,PRODUCT(M90,$O90),0) -> 0 | V90: =SUM(Q90:U90) -> 0 | Z90: =AA90/12 -> 0 | AA90: =IF(Y90>0,PRODUCT(I90,$Y90),0) -> 0 | AB90: =IF(AA90>0,PRODUCT(J90,$Y90),0) -> 0 | AC90: =IF(AB90>0,PRODUCT(K90,$Y90),0) -> 0 | AD90: =IF(AC90>0,PRODUCT(L90,$Y90),0) -> 0 | AE90: =IF(AD90>0,PRODUCT(M90,$Y90),0) -> 0 | AF90: =SUM(AA90:AE90) -> 0 | AK90: =AL90/12 -> 0 | AL90: {=_xlfn.IFS($AJ90="NO CHARGE",0,$AJ90=0,0,$AJ90>0,PRODUCT(I90,$AJ90))} -> 0 | AM90: {=_xlfn.IFS($AJ90="NO CHARGE",0,$AJ90=0,0,$AJ90>0,PRODUCT(J90,$AJ90))} -> 0 | AN90: {=_xlfn.IFS($AJ90="NO CHARGE",0,$AJ90=0,0,$AJ90>0,PRODUCT(K90,$AJ90))} -> 0 | AO90: {=_xlfn.IFS($AJ90="NO CHARGE",0,$AJ90=0,0,$AJ90>0,PRODUCT(L90,$AJ90))} -> 0 | AP90: {=_xlfn.IFS($AJ90="NO CHARGE",0,$AJ90=0,0,$AJ90>0,PRODUCT(M90,$AJ90))} -> 0 | AQ90: =SUM(AL90:AP90) -> 0 | AV90: =IF(AU90>0,PRODUCT(I90,$AU90),0) -> 0 | AW90: =IF(AV90>0,PRODUCT(J90,$AU90),0) -> 0 | AX90: =IF(AW90>0,PRODUCT(K90,$AU90),0) -> 0 | AY90: =IF(AX90>0,PRODUCT(L90,$AU90),0) -> 0 | AZ90: =IF(AY90>0,PRODUCT(M90,$AU90),0) -> 0 | BA90: =SUM(AV90:AZ90) -> 0
B91: Card Suite Lite Card Controls | C91: =B91&" [QTY CALCULATIONS YOY]" -> Card Suite Lite Card Controls [QTY CALCULATIONS YOY] | H91: 1110 | I91: =H91*12 -> 13320 | J91: =IF(I91>12,(((I91)*$H$5)+I91),(I91*1)) -> 13986 | K91: =IF(J91>12,(((J91)*$H$5)+J91),(J91*1)) -> 14685.3 | L91: =IF(K91>12,(((K91)*$H$5)+K91),(K91*1)) -> 15419.565 | M91: =IF(L91>12,(((L91)*$H$5)+L91),(L91*1)) -> 16190.543 | N91: =B91&" [TIERED]" -> Card Suite Lite Card Controls [TIERED] | P91: =Q91/12 -> 0 | Q91: =IF(O91>0,PRODUCT(I91,$O91),0) -> 0 | R91: =IF(Q91>0,PRODUCT(J91,$O91),0) -> 0 | S91: =IF(R91>0,PRODUCT(K91,$O91),0) -> 0 | T91: =IF(S91>0,PRODUCT(L91,$O91),0) -> 0 | U91: =IF(T91>0,PRODUCT(M91,$O91),0) -> 0 | V91: =SUM(Q91:U91) -> 0 | X91: =B91&" [TIERED]" -> Card Suite Lite Card Controls [TIERED] | Z91: =AA91/12 -> 0 | AA91: =IF(Y91>0,PRODUCT(I91,$Y91),0) -> 0 | AB91: =IF(AA91>0,PRODUCT(J91,$Y91),0) -> 0 | AC91: =IF(AB91>0,PRODUCT(K91,$Y91),0) -> 0 | AD91: =IF(AC91>0,PRODUCT(L91,$Y91),0) -> 0 | AE91: =IF(AD91>0,PRODUCT(M91,$Y91),0) -> 0 | AF91: =SUM(AA91:AE91) -> 0 | AI91: =C91 -> Card Suite Lite Card Controls [QTY CALCULATIONS YOY] | AK91: =AL91/12 -> 0 | AL91: {=_xlfn.IFS($AJ91="NO CHARGE",0,$AJ91=0,0,$AJ91>0,PRODUCT(I91,$AJ91))} -> 0 | AM91: {=_xlfn.IFS($AJ91="NO CHARGE",0,$AJ91=0,0,$AJ91>0,PRODUCT(J91,$AJ91))} -> 0 | AN91: {=_xlfn.IFS($AJ91="NO CHARGE",0,$AJ91=0,0,$AJ91>0,PRODUCT(K91,$AJ91))} -> 0 | AO91: {=_xlfn.IFS($AJ91="NO CHARGE",0,$AJ91=0,0,$AJ91>0,PRODUCT(L91,$AJ91))} -> 0 | AP91: {=_xlfn.IFS($AJ91="NO CHARGE",0,$AJ91=0,0,$AJ91>0,PRODUCT(M91,$AJ91))} -> 0 | AQ91: =SUM(AL91:AP91) -> 0 | AV91: =IF(AU91>0,PRODUCT(I91,$AU91),0) -> 0 | AW91: =IF(AV91>0,PRODUCT(J91,$AU91),0) -> 0 | AX91: =IF(AW91>0,PRODUCT(K91,$AU91),0) -> 0 | AY91: =IF(AX91>0,PRODUCT(L91,$AU91),0) -> 0 | AZ91: =IF(AY91>0,PRODUCT(M91,$AU91),0) -> 0 | BA91: =SUM(AV91:AZ91) -> 0
B92: Card Suite Lite Card Controls | C92: [Tiered] 0 - 50k | H92: 50000 | I92: =IF(I91>($H92*12),$H92*12,I91) -> 13320 | J92: =IF(J91>($H92*12),$H92*12,J91) -> 13986 | K92: =IF(K91>($H92*12),$H92*12,K91) -> 14685.3 | L92: =IF(L91>($H92*12),$H92*12,L91) -> 15419.565 | M92: =IF(M91>($H92*12),$H92*12,M91) -> 16190.543 | N92: =C92 -> [Tiered] 0 - 50k | O92: 0.592725 | P92: =Q92/12 -> 657.92475 | Q92: =IF(O92>0,PRODUCT(I92,$O92),0) -> 7895.097 | R92: =IF(Q92>0,PRODUCT(J92,$O92),0) -> 8289.8518 | S92: =IF(R92>0,PRODUCT(K92,$O92),0) -> 8704.3444 | T92: =IF(S92>0,PRODUCT(L92,$O92),0) -> 9139.5617 | U92: =IF(T92>0,PRODUCT(M92,$O92),0) -> 9596.5397 | V92: =SUM(Q92:U92) -> 43625.395 | X92: =C92 -> [Tiered] 0 - 50k | Y92: 0.5927 | Z92: =AA92/12 -> 657.897 | AA92: =IF(Y92>0,PRODUCT(I92,$Y92),0) -> 7894.764 | AB92: =IF(AA92>0,PRODUCT(J92,$Y92),0) -> 8289.5022 | AC92: =IF(AB92>0,PRODUCT(K92,$Y92),0) -> 8703.9773 | AD92: =IF(AC92>0,PRODUCT(L92,$Y92),0) -> 9139.1762 | AE92: =IF(AD92>0,PRODUCT(M92,$Y92),0) -> 9596.135 | AF92: =SUM(AA92:AE92) -> 43623.555 | AI92: =C92 -> [Tiered] 0 - 50k | AJ92: 0.5927 | AK92: =AL92/12 -> 657.897 | AL92: {=_xlfn.IFS($AJ92="NO CHARGE",0,$AJ92=0,0,$AJ92>0,PRODUCT(I92,$AJ92))} -> 7894.764 | AM92: {=_xlfn.IFS($AJ92="NO CHARGE",0,$AJ92=0,0,$AJ92>0,PRODUCT(J92,$AJ92))} -> 8289.5022 | AN92: {=_xlfn.IFS($AJ92="NO CHARGE",0,$AJ92=0,0,$AJ92>0,PRODUCT(K92,$AJ92))} -> 8703.9773 | AO92: {=_xlfn.IFS($AJ92="NO CHARGE",0,$AJ92=0,0,$AJ92>0,PRODUCT(L92,$AJ92))} -> 9139.1762 | AP92: {=_xlfn.IFS($AJ92="NO CHARGE",0,$AJ92=0,0,$AJ92>0,PRODUCT(M92,$AJ92))} -> 9596.135 | AQ92: =SUM(AL92:AP92) -> 43623.555 | AV92: =IF(AU92>0,PRODUCT(I92,$AU92),0) -> 0 | AW92: =IF(AV92>0,PRODUCT(J92,$AU92),0) -> 0 | AX92: =IF(AW92>0,PRODUCT(K92,$AU92),0) -> 0 | AY92: =IF(AX92>0,PRODUCT(L92,$AU92),0) -> 0 | AZ92: =IF(AY92>0,PRODUCT(M92,$AU92),0) -> 0 | BA92: =SUM(AV92:AZ92) -> 0
B93: Card Suite Lite Card Controls | C93: [Tiered] 50,001 - 175k | H93: =175000-50001 -> 124999 | I93: {=_xlfn.IFS(I91>(SUM($H92:$H93)*12),$H93*12, I91<(SUM(H92:H93)*12),0, I91=(SUM(H92:H93*12)),0)} -> 0 | J93: {=_xlfn.IFS(J91>(SUM($H92:$H93)*12),$H93*12, J91<(SUM(I92:I93)*12),0, J91=(SUM(I92:I93*12)),0)} -> 0 | K93: {=_xlfn.IFS(K91>(SUM($H92:$H93)*12),$H93*12, K91<(SUM(J92:J93)*12),0, K91=(SUM(J92:J93*12)),0)} -> 0 | L93: {=_xlfn.IFS(L91>(SUM($H92:$H93)*12),$H93*12, L91<(SUM(K92:K93)*12),0, L91=(SUM(K92:K93*12)),0)} -> 0 | M93: {=_xlfn.IFS(M91>(SUM($H92:$H93)*12),$H93*12, M91<(SUM(L92:L93)*12),0, M91=(SUM(L92:L93*12)),0)} -> 0 | N93: =C93 -> [Tiered] 50,001 - 175k | O93: 0.59273 | P93: =Q93/12 -> 0 | Q93: =IF(O93>0,PRODUCT(I93,$O93),0) -> 0 | R93: =IF(Q93>0,PRODUCT(J93,$O93),0) -> 0 | S93: =IF(R93>0,PRODUCT(K93,$O93),0) -> 0 | T93: =IF(S93>0,PRODUCT(L93,$O93),0) -> 0 | U93: =IF(T93>0,PRODUCT(M93,$O93),0) -> 0 | V93: =SUM(Q93:U93) -> 0 | X93: =C93 -> [Tiered] 50,001 - 175k | Y93: 0.5927 | Z93: =AA93/12 -> 0 | AA93: =IF(Y93>0,PRODUCT(I93,$Y93),0) -> 0 | AB93: =IF(AA93>0,PRODUCT(J93,$Y93),0) -> 0 | AC93: =IF(AB93>0,PRODUCT(K93,$Y93),0) -> 0 | AD93: =IF(AC93>0,PRODUCT(L93,$Y93),0) -> 0 | AE93: =IF(AD93>0,PRODUCT(M93,$Y93),0) -> 0 | AF93: =SUM(AA93:AE93) -> 0 | AI93: =C93 -> [Tiered] 50,001 - 175k | AJ93: 0.5927 | AK93: =AL93/12 -> 0 | AL93: {=_xlfn.IFS($AJ93="NO CHARGE",0,$AJ93=0,0,$AJ93>0,PRODUCT(I93,$AJ93))} -> 0 | AM93: {=_xlfn.IFS($AJ93="NO CHARGE",0,$AJ93=0,0,$AJ93>0,PRODUCT(J93,$AJ93))} -> 0 | AN93: {=_xlfn.IFS($AJ93="NO CHARGE",0,$AJ93=0,0,$AJ93>0,PRODUCT(K93,$AJ93))} -> 0 | AO93: {=_xlfn.IFS($AJ93="NO CHARGE",0,$AJ93=0,0,$AJ93>0,PRODUCT(L93,$AJ93))} -> 0 | AP93: {=_xlfn.IFS($AJ93="NO CHARGE",0,$AJ93=0,0,$AJ93>0,PRODUCT(M93,$AJ93))} -> 0 | AQ93: =SUM(AL93:AP93) -> 0 | AV93: =IF(AU93>0,PRODUCT(I93,$AU93),0) -> 0 | AW93: =IF(AV93>0,PRODUCT(J93,$AU93),0) -> 0 | AX93: =IF(AW93>0,PRODUCT(K93,$AU93),0) -> 0 | AY93: =IF(AX93>0,PRODUCT(L93,$AU93),0) -> 0 | AZ93: =IF(AY93>0,PRODUCT(M93,$AU93),0) -> 0 | BA93: =SUM(AV93:AZ93) -> 0
B94: Card Suite Lite Card Controls | C94: [Tiered] 175,001 - 500k | H94: =500000-175001 -> 324999 | I94: {=_xlfn.IFS(I91>(SUM($H92:$H94)*12),$H94*12, I91<(SUM(H92:H94)*12),0, I91=(SUM(H92:H94*12)),0)} -> 0 | J94: {=_xlfn.IFS(J91>(SUM($H92:$H94)*12),$H94*12, J91<(SUM(I92:I94)*12),0, J91=(SUM(I92:I94*12)),0)} -> 0 | K94: {=_xlfn.IFS(K91>(SUM($H92:$H94)*12),$H94*12, K91<(SUM(J92:J94)*12),0, K91=(SUM(J92:J94*12)),0)} -> 0 | L94: {=_xlfn.IFS(L91>(SUM($H92:$H94)*12),$H94*12, L91<(SUM(K92:K94)*12),0, L91=(SUM(K92:K94*12)),0)} -> 0 | M94: {=_xlfn.IFS(M91>(SUM($H92:$H94)*12),$H94*12, M91<(SUM(L92:L94)*12),0, M91=(SUM(L92:L94*12)),0)} -> 0 | N94: =C94 -> [Tiered] 175,001 - 500k | P94: =Q94/12 -> 0 | Q94: =IF(O94>0,PRODUCT(I94,$O94),0) -> 0 | R94: =IF(Q94>0,PRODUCT(J94,$O94),0) -> 0 | S94: =IF(R94>0,PRODUCT(K94,$O94),0) -> 0 | T94: =IF(S94>0,PRODUCT(L94,$O94),0) -> 0 | U94: =IF(T94>0,PRODUCT(M94,$O94),0) -> 0 | V94: =SUM(Q94:U94) -> 0 | X94: =C94 -> [Tiered] 175,001 - 500k | Y94: 0.45 | Z94: =AA94/12 -> 0 | AA94: =IF(Y94>0,PRODUCT(I94,$Y94),0) -> 0 | AB94: =IF(AA94>0,PRODUCT(J94,$Y94),0) -> 0 | AC94: =IF(AB94>0,PRODUCT(K94,$Y94),0) -> 0 | AD94: =IF(AC94>0,PRODUCT(L94,$Y94),0) -> 0 | AE94: =IF(AD94>0,PRODUCT(M94,$Y94),0) -> 0 | AF94: =SUM(AA94:AE94) -> 0 | AI94: =C94 -> [Tiered] 175,001 - 500k | AJ94: 0.45 | AK94: =AL94/12 -> 0 | AL94: {=_xlfn.IFS($AJ94="NO CHARGE",0,$AJ94=0,0,$AJ94>0,PRODUCT(I94,$AJ94))} -> 0 | AM94: {=_xlfn.IFS($AJ94="NO CHARGE",0,$AJ94=0,0,$AJ94>0,PRODUCT(J94,$AJ94))} -> 0 | AN94: {=_xlfn.IFS($AJ94="NO CHARGE",0,$AJ94=0,0,$AJ94>0,PRODUCT(K94,$AJ94))} -> 0 | AO94: {=_xlfn.IFS($AJ94="NO CHARGE",0,$AJ94=0,0,$AJ94>0,PRODUCT(L94,$AJ94))} -> 0 | AP94: {=_xlfn.IFS($AJ94="NO CHARGE",0,$AJ94=0,0,$AJ94>0,PRODUCT(M94,$AJ94))} -> 0 | AQ94: =SUM(AL94:AP94) -> 0 | AV94: =IF(AU94>0,PRODUCT(I94,$AU94),0) -> 0 | AW94: =IF(AV94>0,PRODUCT(J94,$AU94),0) -> 0 | AX94: =IF(AW94>0,PRODUCT(K94,$AU94),0) -> 0 | AY94: =IF(AX94>0,PRODUCT(L94,$AU94),0) -> 0 | AZ94: =IF(AY94>0,PRODUCT(M94,$AU94),0) -> 0 | BA94: =SUM(AV94:AZ94) -> 0
B95: Card Suite Lite Card Controls | C95: [Tiered] Beyond 500k | I95: {=_xlfn.IFS(I91>SUM($H92:$H94)*12, I91-SUM(I92:I94), I91<SUM($H92:$H94)*12, 0, I91=SUM($H92:$H94)*12,0)} -> 0 | J95: {=_xlfn.IFS(J91>SUM($H92:$H94)*12, J91-SUM(J92:J94), J91<SUM($H92:$H94)*12, 0, J91=SUM($H92:$H94)*12,0)} -> 0 | K95: {=_xlfn.IFS(K91>SUM($H92:$H94)*12, K91-SUM(K92:K94), K91<SUM($H92:$H94)*12, 0, K91=SUM($H92:$H94)*12,0)} -> 0 | L95: {=_xlfn.IFS(L91>SUM($H92:$H94)*12, L91-SUM(L92:L94), L91<SUM($H92:$H94)*12, 0, L91=SUM($H92:$H94)*12,0)} -> 0 | M95: {=_xlfn.IFS(M91>SUM($H92:$H94)*12, M91-SUM(M92:M94), M91<SUM($H92:$H94)*12, 0, M91=SUM($H92:$H94)*12,0)} -> 0 | N95: =C95 -> [Tiered] Beyond 500k | P95: =Q95/12 -> 0 | Q95: =IF(O95>0,PRODUCT(I95,$O95),0) -> 0 | R95: =IF(Q95>0,PRODUCT(J95,$O95),0) -> 0 | S95: =IF(R95>0,PRODUCT(K95,$O95),0) -> 0 | T95: =IF(S95>0,PRODUCT(L95,$O95),0) -> 0 | U95: =IF(T95>0,PRODUCT(M95,$O95),0) -> 0 | V95: =SUM(Q95:U95) -> 0 | X95: =C95 -> [Tiered] Beyond 500k | Y95: 0.45 | Z95: =AA95/12 -> 0 | AA95: =IF(Y95>0,PRODUCT(I95,$Y95),0) -> 0 | AB95: =IF(AA95>0,PRODUCT(J95,$Y95),0) -> 0 | AC95: =IF(AB95>0,PRODUCT(K95,$Y95),0) -> 0 | AD95: =IF(AC95>0,PRODUCT(L95,$Y95),0) -> 0 | AE95: =IF(AD95>0,PRODUCT(M95,$Y95),0) -> 0 | AF95: =SUM(AA95:AE95) -> 0 | AI95: =C95 -> [Tiered] Beyond 500k | AJ95: 0.4 | AK95: =AL95/12 -> 0 | AL95: {=_xlfn.IFS($AJ95="NO CHARGE",0,$AJ95=0,0,$AJ95>0,PRODUCT(I95,$AJ95))} -> 0 | AM95: {=_xlfn.IFS($AJ95="NO CHARGE",0,$AJ95=0,0,$AJ95>0,PRODUCT(J95,$AJ95))} -> 0 | AN95: {=_xlfn.IFS($AJ95="NO CHARGE",0,$AJ95=0,0,$AJ95>0,PRODUCT(K95,$AJ95))} -> 0 | AO95: {=_xlfn.IFS($AJ95="NO CHARGE",0,$AJ95=0,0,$AJ95>0,PRODUCT(L95,$AJ95))} -> 0 | AP95: {=_xlfn.IFS($AJ95="NO CHARGE",0,$AJ95=0,0,$AJ95>0,PRODUCT(M95,$AJ95))} -> 0 | AQ95: =SUM(AL95:AP95) -> 0 | AV95: =IF(AU95>0,PRODUCT(I95,$AU95),0) -> 0 | AW95: =IF(AV95>0,PRODUCT(J95,$AU95),0) -> 0 | AX95: =IF(AW95>0,PRODUCT(K95,$AU95),0) -> 0 | AY95: =IF(AX95>0,PRODUCT(L95,$AU95),0) -> 0 | AZ95: =IF(AY95>0,PRODUCT(M95,$AU95),0) -> 0 | BA95: =SUM(AV95:AZ95) -> 0
H96: =IFERROR(AVERAGE(D96:G96),0) -> 0 | I96: =H96*12 -> 0 | J96: =IF(I96>12,(((I96)*$H$5)+I96),(I96*1)) -> 0 | K96: =IF(J96>12,(((J96)*$H$5)+J96),(J96*1)) -> 0 | L96: =IF(K96>12,(((K96)*$H$5)+K96),(K96*1)) -> 0 | M96: =IF(L96>12,(((L96)*$H$5)+L96),(L96*1)) -> 0 | N96: =IF(C96="","",C96) | P96: =Q96/12 -> 0 | Q96: =IF(O96>0,PRODUCT(I96,$O96),0) -> 0 | R96: =IF(Q96>0,PRODUCT(J96,$O96),0) -> 0 | S96: =IF(R96>0,PRODUCT(K96,$O96),0) -> 0 | T96: =IF(S96>0,PRODUCT(L96,$O96),0) -> 0 | U96: =IF(T96>0,PRODUCT(M96,$O96),0) -> 0 | V96: =SUM(Q96:U96) -> 0 | Z96: =AA96/12 -> 0 | AA96: =IF(Y96>0,PRODUCT(I96,$Y96),0) -> 0 | AB96: =IF(AA96>0,PRODUCT(J96,$Y96),0) -> 0 | AC96: =IF(AB96>0,PRODUCT(K96,$Y96),0) -> 0 | AD96: =IF(AC96>0,PRODUCT(L96,$Y96),0) -> 0 | AE96: =IF(AD96>0,PRODUCT(M96,$Y96),0) -> 0 | AF96: =SUM(AA96:AE96) -> 0 | AK96: =AL96/12 -> 0 | AL96: {=_xlfn.IFS($AJ96="NO CHARGE",0,$AJ96=0,0,$AJ96>0,PRODUCT(I96,$AJ96))} -> 0 | AM96: {=_xlfn.IFS($AJ96="NO CHARGE",0,$AJ96=0,0,$AJ96>0,PRODUCT(J96,$AJ96))} -> 0 | AN96: {=_xlfn.IFS($AJ96="NO CHARGE",0,$AJ96=0,0,$AJ96>0,PRODUCT(K96,$AJ96))} -> 0 | AO96: {=_xlfn.IFS($AJ96="NO CHARGE",0,$AJ96=0,0,$AJ96>0,PRODUCT(L96,$AJ96))} -> 0 | AP96: {=_xlfn.IFS($AJ96="NO CHARGE",0,$AJ96=0,0,$AJ96>0,PRODUCT(M96,$AJ96))} -> 0 | AQ96: =SUM(AL96:AP96) -> 0 | AV96: =IF(AU96>0,PRODUCT(I96,$AU96),0) -> 0 | AW96: =IF(AV96>0,PRODUCT(J96,$AU96),0) -> 0 | AX96: =IF(AW96>0,PRODUCT(K96,$AU96),0) -> 0 | AY96: =IF(AX96>0,PRODUCT(L96,$AU96),0) -> 0 | AZ96: =IF(AY96>0,PRODUCT(M96,$AU96),0) -> 0 | BA96: =SUM(AV96:AZ96) -> 0
B97: SecurLock (SL) | C97: =B97&" [QTY CALCULATIONS YOY]" -> SecurLock (SL) [QTY CALCULATIONS YOY] | E97: =SUM(E98:E99) -> 1128 | F97: =SUM(F98:F99) -> 1130 | G97: =SUM(G98:G99) -> 1089 | H97: =IFERROR(AVERAGE(D97:G97),0) -> 1115.6667 | I97: =H97*12 -> 13388 | J97: =IF(I97>12,(((I97)*$H$5)+I97),(I97*1)) -> 14057.4 | K97: =IF(J97>12,(((J97)*$H$5)+J97),(J97*1)) -> 14760.27 | L97: =IF(K97>12,(((K97)*$H$5)+K97),(K97*1)) -> 15498.284 | M97: =IF(L97>12,(((L97)*$H$5)+L97),(L97*1)) -> 16273.198 | N97: =B97&" [TIERED]" -> SecurLock (SL) [TIERED] | P97: =Q97/12 -> 0 | Q97: =IF(O97>0,PRODUCT(I97,$O97),0) -> 0 | R97: =IF(Q97>0,PRODUCT(J97,$O97),0) -> 0 | S97: =IF(R97>0,PRODUCT(K97,$O97),0) -> 0 | T97: =IF(S97>0,PRODUCT(L97,$O97),0) -> 0 | U97: =IF(T97>0,PRODUCT(M97,$O97),0) -> 0 | V97: =SUM(Q97:U97) -> 0 | X97: =B97&" [TIERED]" -> SecurLock (SL) [TIERED] | AI97: =C97 -> SecurLock (SL) [QTY CALCULATIONS YOY] | AK97: =AL97/12 -> 0 | AL97: {=_xlfn.IFS($AJ97="NO CHARGE",0,$AJ97=0,0,$AJ97>0,PRODUCT(I97,$AJ97))} -> 0 | AM97: {=_xlfn.IFS($AJ97="NO CHARGE",0,$AJ97=0,0,$AJ97>0,PRODUCT(J97,$AJ97))} -> 0 | AN97: {=_xlfn.IFS($AJ97="NO CHARGE",0,$AJ97=0,0,$AJ97>0,PRODUCT(K97,$AJ97))} -> 0 | AO97: {=_xlfn.IFS($AJ97="NO CHARGE",0,$AJ97=0,0,$AJ97>0,PRODUCT(L97,$AJ97))} -> 0 | AP97: {=_xlfn.IFS($AJ97="NO CHARGE",0,$AJ97=0,0,$AJ97>0,PRODUCT(M97,$AJ97))} -> 0 | AQ97: =SUM(AL97:AP97) -> 0 | AV97: =IF(AU97>0,PRODUCT(I97,$AU97),0) -> 0 | AW97: =IF(AV97>0,PRODUCT(J97,$AU97),0) -> 0 | AX97: =IF(AW97>0,PRODUCT(K97,$AU97),0) -> 0 | AY97: =IF(AX97>0,PRODUCT(L97,$AU97),0) -> 0 | AZ97: =IF(AY97>0,PRODUCT(M97,$AU97),0) -> 0 | BA97: =SUM(AV97:AZ97) -> 0
B98: SecurLock (SL) | C98: [Tiered] SECURLOCK EQUIP - STANDARD 0 - 500 | E98: 500 | F98: 500 | G98: 500 | H98: 500 | I98: =IF(I97>($H98*12),$H98*12,I97) -> 6000 | J98: =IF(J97>($H98*12),$H98*12,J97) -> 6000 | K98: =IF(K97>($H98*12),$H98*12,K97) -> 6000 | L98: =IF(L97>($H98*12),$H98*12,L97) -> 6000 | M98: =IF(M97>($H98*12),$H98*12,M97) -> 6000 | N98: =IF(C98="","",C98) -> [Tiered] SECURLOCK EQUIP - STANDARD 0 - 500 | O98: 0 | P98: =Q98/12 -> 0 | Q98: =IF(O98>0,PRODUCT(I98,$O98),0) -> 0 | R98: =IF(Q98>0,PRODUCT(J98,$O98),0) -> 0 | S98: =IF(R98>0,PRODUCT(K98,$O98),0) -> 0 | T98: =IF(S98>0,PRODUCT(L98,$O98),0) -> 0 | U98: =IF(T98>0,PRODUCT(M98,$O98),0) -> 0 | V98: =SUM(Q98:U98) -> 0 | X98: =C98 -> [Tiered] SECURLOCK EQUIP - STANDARD 0 - 500 | Y98: (FIS DID NOT QUOTE) | AH98: FIS DID NOT QUOTE | AI98: =C98 -> [Tiered] SECURLOCK EQUIP - STANDARD 0 - 500
B99: SecurLock (SL) | C99: [Tiered] SECURLOCK EQUIP - STANDARD Beyond 500 | E99: 628 | F99: 630 | G99: 589 | I99: {=_xlfn.IFS(I97>(($H98)*12),I97-I98, I97<(($H98)*12),0, I97=(($H98)*12),0)} -> 7388 | J99: {=_xlfn.IFS(J97>(($H98)*12),J97-J98, J97<(($H98)*12),0, J97=(($H98)*12),0)} -> 8057.4 | K99: {=_xlfn.IFS(K97>(($H98)*12),K97-K98, K97<(($H98)*12),0, K97=(($H98)*12),0)} -> 8760.27 | L99: {=_xlfn.IFS(L97>(($H98)*12),L97-L98, L97<(($H98)*12),0, L97=(($H98)*12),0)} -> 9498.2835 | M99: {=_xlfn.IFS(M97>(($H98)*12),M97-M98, M97<(($H98)*12),0, M97=(($H98)*12),0)} -> 10273.198 | N99: =IF(C99="","",C99) -> [Tiered] SECURLOCK EQUIP - STANDARD Beyond 500 | O99: 0.5927253 | P99: =Q99/12 -> 364.92121 | Q99: =IF(O99>0,PRODUCT(I99,$O99),0) -> 4379.0545 | R99: =IF(Q99>0,PRODUCT(J99,$O99),0) -> 4775.8248 | S99: =IF(R99>0,PRODUCT(K99,$O99),0) -> 5192.4337 | T99: =IF(S99>0,PRODUCT(L99,$O99),0) -> 5629.8729 | U99: =IF(T99>0,PRODUCT(M99,$O99),0) -> 6089.1842 | V99: =SUM(Q99:U99) -> 26066.37 | X99: =C99 -> [Tiered] SECURLOCK EQUIP - STANDARD Beyond 500 | Y99: 0.5927253 | Z99: =AA99/12 -> 364.92121 | AA99: =IF(AJ99>0,PRODUCT(I99,$O99),0) -> 4379.0545 | AB99: =IF(AK99>0,PRODUCT(J99,$O99),0) -> 4775.8248 | AC99: =IF(AL99>0,PRODUCT(K99,$O99),0) -> 5192.4337 | AD99: =IF(AM99>0,PRODUCT(L99,$O99),0) -> 5629.8729 | AE99: =IF(AN99>0,PRODUCT(M99,$O99),0) -> 6089.1842 | AF99: =SUM(AA99:AE99) -> 26066.37 | AH99: FIS DID NOT QUOTE | AI99: =C99 -> [Tiered] SECURLOCK EQUIP - STANDARD Beyond 500 | AJ99: 0.5927253 | AK99: =+AL99/12 -> 364.92121 | AL99: =IF(AJ99>0,PRODUCT(I99,$O99),0) -> 4379.0545 | AM99: =IF(AL99>0,PRODUCT(J99,$AJ99),0) -> 4775.8248 | AN99: =IF(AM99>0,PRODUCT(K99,$AJ99),0) -> 5192.4337 | AO99: =IF(AN99>0,PRODUCT(L99,$AJ99),0) -> 5629.8729 | AP99: =IF(AO99>0,PRODUCT(M99,$AJ99),0) -> 6089.1842 | AQ99: =SUM(AL99:AP99) -> 26066.37
B100: SecurLock (SL) | C100: Securlock (SL) Fraud Premium Accounts On File / Residency | E100: 33749 | F100: 33645 | G100: 33410 | H100: =IFERROR(AVERAGE(D100:G100),0) -> 33601.333 | I100: =H100*12 -> 403216 | J100: =IF(I100>12,(((I100)*$H$5)+I100),(I100*1)) -> 423376.8 | K100: =IF(J100>12,(((J100)*$H$5)+J100),(J100*1)) -> 444545.64 | L100: =IF(K100>12,(((K100)*$H$5)+K100),(K100*1)) -> 466772.92 | M100: =IF(L100>12,(((L100)*$H$5)+L100),(L100*1)) -> 490111.57 | N100: =IF(C100="","",C100) -> Securlock (SL) Fraud Premium Accounts On File / Residency | O100: 0.041868 | P100: =Q100/12 -> 1406.8206 | Q100: =IF(O100>0,PRODUCT(I100,$O100),0) -> 16881.847 | R100: =IF(Q100>0,PRODUCT(J100,$O100),0) -> 17725.94 | S100: =IF(R100>0,PRODUCT(K100,$O100),0) -> 18612.237 | T100: =IF(S100>0,PRODUCT(L100,$O100),0) -> 19542.849 | U100: =IF(T100>0,PRODUCT(M100,$O100),0) -> 20519.991 | V100: =SUM(Q100:U100) -> 93282.864 | X100: =C100 -> Securlock (SL) Fraud Premium Accounts On File / Residency | Y100: 0.0419 | Z100: =AA100/12 -> 1407.8959 | AA100: =IF(Y100>0,PRODUCT(I100,$Y100),0) -> 16894.75 | AB100: =IF(AA100>0,PRODUCT(J100,$Y100),0) -> 17739.488 | AC100: =IF(AB100>0,PRODUCT(K100,$Y100),0) -> 18626.462 | AD100: =IF(AC100>0,PRODUCT(L100,$Y100),0) -> 19557.785 | AE100: =IF(AD100>0,PRODUCT(M100,$Y100),0) -> 20535.675 | AF100: =SUM(AA100:AE100) -> 93354.161 | AI100: =C100 -> Securlock (SL) Fraud Premium Accounts On File / Residency | AJ100: 0.0419 | AK100: =AL100/12 -> 1407.8959 | AL100: {=_xlfn.IFS($AJ100="NO CHARGE",0,$AJ100=0,0,$AJ100>0,PRODUCT(I100,$AJ100))} -> 16894.75 | AM100: {=_xlfn.IFS($AJ100="NO CHARGE",0,$AJ100=0,0,$AJ100>0,PRODUCT(J100,$AJ100))} -> 17739.488 | AN100: {=_xlfn.IFS($AJ100="NO CHARGE",0,$AJ100=0,0,$AJ100>0,PRODUCT(K100,$AJ100))} -> 18626.462 | AO100: {=_xlfn.IFS($AJ100="NO CHARGE",0,$AJ100=0,0,$AJ100>0,PRODUCT(L100,$AJ100))} -> 19557.785 | AP100: {=_xlfn.IFS($AJ100="NO CHARGE",0,$AJ100=0,0,$AJ100>0,PRODUCT(M100,$AJ100))} -> 20535.675 | AQ100: =SUM(AL100:AP100) -> 93354.161
B101: SecurLock (SL) | C101: Securlock (SL) Fraud Case Investigation Sheets | E101: 622 | F101: 815 | G101: 655 | H101: =IFERROR(AVERAGE(D101:G101),0) -> 697.33333 | I101: =H101*12 -> 8368 | J101: =IF(I101>12,(((I101)*$H$5)+I101),(I101*1)) -> 8786.4 | K101: =IF(J101>12,(((J101)*$H$5)+J101),(J101*1)) -> 9225.72 | L101: =IF(K101>12,(((K101)*$H$5)+K101),(K101*1)) -> 9687.006 | M101: =IF(L101>12,(((L101)*$H$5)+L101),(L101*1)) -> 10171.356 | N101: =IF(C101="","",C101) -> Securlock (SL) Fraud Case Investigation Sheets | O101: 10.467 | P101: =Q101/12 -> 7298.988 | Q101: =IF(O101>0,PRODUCT(I101,$O101),0) -> 87587.856 | R101: =IF(Q101>0,PRODUCT(J101,$O101),0) -> 91967.249 | S101: =IF(R101>0,PRODUCT(K101,$O101),0) -> 96565.611 | T101: =IF(S101>0,PRODUCT(L101,$O101),0) -> 101393.89 | U101: =IF(T101>0,PRODUCT(M101,$O101),0) -> 106463.59 | V101: =SUM(Q101:U101) -> 483978.19 | X101: =C101 -> Securlock (SL) Fraud Case Investigation Sheets | Y101: 8 | Z101: =AA101/12 -> 5578.6667 | AA101: =IF(Y101>0,PRODUCT(I101,$Y101),0) -> 66944 | AB101: =IF(AA101>0,PRODUCT(J101,$Y101),0) -> 70291.2 | AC101: =IF(AB101>0,PRODUCT(K101,$Y101),0) -> 73805.76 | AD101: =IF(AC101>0,PRODUCT(L101,$Y101),0) -> 77496.048 | AE101: =IF(AD101>0,PRODUCT(M101,$Y101),0) -> 81370.85 | AF101: =SUM(AA101:AE101) -> 369907.86 | AI101: =C101 -> Securlock (SL) Fraud Case Investigation Sheets | AJ101: 8.5 | AK101: =AL101/12 -> 5927.3333 | AL101: {=_xlfn.IFS($AJ101="NO CHARGE",0,$AJ101=0,0,$AJ101>0,PRODUCT(I101,$AJ101))} -> 71128 | AM101: {=_xlfn.IFS($AJ101="NO CHARGE",0,$AJ101=0,0,$AJ101>0,PRODUCT(J101,$AJ101))} -> 74684.4 | AN101: {=_xlfn.IFS($AJ101="NO CHARGE",0,$AJ101=0,0,$AJ101>0,PRODUCT(K101,$AJ101))} -> 78418.62 | AO101: {=_xlfn.IFS($AJ101="NO CHARGE",0,$AJ101=0,0,$AJ101>0,PRODUCT(L101,$AJ101))} -> 82339.551 | AP101: {=_xlfn.IFS($AJ101="NO CHARGE",0,$AJ101=0,0,$AJ101>0,PRODUCT(M101,$AJ101))} -> 86456.529 | AQ101: =SUM(AL101:AP101) -> 393027.1
B102: SecurLock (SL) | C102: Securlock (SL) Fraud Transaction Scoring / Real-Time Scoring | E102: 376348 | F102: 363876 | G102: 375804 | H102: =IFERROR(AVERAGE(D102:G102),0) -> 372009.33 | I102: =H102*12 -> 4464112 | J102: =IF(I102>12,(((I102)*$H$5)+I102),(I102*1)) -> 4687317.6 | K102: =IF(J102>12,(((J102)*$H$5)+J102),(J102*1)) -> 4921683.5 | L102: =IF(K102>12,(((K102)*$H$5)+K102),(K102*1)) -> 5167767.7 | M102: =IF(L102>12,(((L102)*$H$5)+L102),(L102*1)) -> 5426156 | N102: =IF(C102="","",C102) -> Securlock (SL) Fraud Transaction Scoring / Real-Time Scoring | O102: 0.010467 | P102: =Q102/12 -> 3893.8217 | Q102: =IF(O102>0,PRODUCT(I102,$O102),0) -> 46725.86 | R102: =IF(Q102>0,PRODUCT(J102,$O102),0) -> 49062.153 | S102: =IF(R102>0,PRODUCT(K102,$O102),0) -> 51515.261 | T102: =IF(S102>0,PRODUCT(L102,$O102),0) -> 54091.024 | U102: =IF(T102>0,PRODUCT(M102,$O102),0) -> 56795.575 | V102: =SUM(Q102:U102) -> 258189.87 | X102: =C102 -> Securlock (SL) Fraud Transaction Scoring / Real-Time Scoring | Y102: 0.0105 | Z102: =AA102/12 -> 3906.098 | AA102: =IF(Y102>0,PRODUCT(I102,$Y102),0) -> 46873.176 | AB102: =IF(AA102>0,PRODUCT(J102,$Y102),0) -> 49216.835 | AC102: =IF(AB102>0,PRODUCT(K102,$Y102),0) -> 51677.677 | AD102: =IF(AC102>0,PRODUCT(L102,$Y102),0) -> 54261.56 | AE102: =IF(AD102>0,PRODUCT(M102,$Y102),0) -> 56974.638 | AF102: =SUM(AA102:AE102) -> 259003.89 | AI102: =C102 -> Securlock (SL) Fraud Transaction Scoring / Real-Time Scoring | AJ102: 0.0105 | AK102: =AL102/12 -> 3906.098 | AL102: {=_xlfn.IFS($AJ102="NO CHARGE",0,$AJ102=0,0,$AJ102>0,PRODUCT(I102,$AJ102))} -> 46873.176 | AM102: {=_xlfn.IFS($AJ102="NO CHARGE",0,$AJ102=0,0,$AJ102>0,PRODUCT(J102,$AJ102))} -> 49216.835 | AN102: {=_xlfn.IFS($AJ102="NO CHARGE",0,$AJ102=0,0,$AJ102>0,PRODUCT(K102,$AJ102))} -> 51677.677 | AO102: {=_xlfn.IFS($AJ102="NO CHARGE",0,$AJ102=0,0,$AJ102>0,PRODUCT(L102,$AJ102))} -> 54261.56 | AP102: {=_xlfn.IFS($AJ102="NO CHARGE",0,$AJ102=0,0,$AJ102>0,PRODUCT(M102,$AJ102))} -> 56974.638 | AQ102: =SUM(AL102:AP102) -> 259003.89
B103: SecurLock (SL) | C103: Securlock (SL) Block Self-Service Auth Fee | E103: 376348 | F103: 363876 | G103: 375804 | H103: =IFERROR(AVERAGE(D103:G103),0) -> 372009.33 | I103: =H103*12 -> 4464112 | J103: =IF(I103>12,(((I103)*$H$5)+I103),(I103*1)) -> 4687317.6 | K103: =IF(J103>12,(((J103)*$H$5)+J103),(J103*1)) -> 4921683.5 | L103: =IF(K103>12,(((K103)*$H$5)+K103),(K103*1)) -> 5167767.7 | M103: =IF(L103>12,(((L103)*$H$5)+L103),(L103*1)) -> 5426156 | N103: =IF(C103="","",C103) -> Securlock (SL) Block Self-Service Auth Fee | O103: 0.0015701 | P103: =Q103/12 -> 584.09185 | Q103: =IF(O103>0,PRODUCT(I103,$O103),0) -> 7009.1023 | R103: =IF(Q103>0,PRODUCT(J103,$O103),0) -> 7359.5574 | S103: =IF(R103>0,PRODUCT(K103,$O103),0) -> 7727.5352 | T103: =IF(S103>0,PRODUCT(L103,$O103),0) -> 8113.912 | U103: =IF(T103>0,PRODUCT(M103,$O103),0) -> 8519.6076 | V103: =SUM(Q103:U103) -> 38729.714 | X103: =C103 -> Securlock (SL) Block Self-Service Auth Fee | Y103: 0.0016 | Z103: =AA103/12 -> 595.21493 | AA103: =IF(Y103>0,PRODUCT(I103,$Y103),0) -> 7142.5792 | AB103: =IF(AA103>0,PRODUCT(J103,$Y103),0) -> 7499.7082 | AC103: =IF(AB103>0,PRODUCT(K103,$Y103),0) -> 7874.6936 | AD103: =IF(AC103>0,PRODUCT(L103,$Y103),0) -> 8268.4282 | AE103: =IF(AD103>0,PRODUCT(M103,$Y103),0) -> 8681.8497 | AF103: =SUM(AA103:AE103) -> 39467.259 | AI103: =C103 -> Securlock (SL) Block Self-Service Auth Fee | AJ103: 0.0016 | AK103: =AL103/12 -> 595.21493 | AL103: {=_xlfn.IFS($AJ103="NO CHARGE",0,$AJ103=0,0,$AJ103>0,PRODUCT(I103,$AJ103))} -> 7142.5792 | AM103: {=_xlfn.IFS($AJ103="NO CHARGE",0,$AJ103=0,0,$AJ103>0,PRODUCT(J103,$AJ103))} -> 7499.7082 | AN103: {=_xlfn.IFS($AJ103="NO CHARGE",0,$AJ103=0,0,$AJ103>0,PRODUCT(K103,$AJ103))} -> 7874.6936 | AO103: {=_xlfn.IFS($AJ103="NO CHARGE",0,$AJ103=0,0,$AJ103>0,PRODUCT(L103,$AJ103))} -> 8268.4282 | AP103: {=_xlfn.IFS($AJ103="NO CHARGE",0,$AJ103=0,0,$AJ103>0,PRODUCT(M103,$AJ103))} -> 8681.8497 | AQ103: =SUM(AL103:AP103) -> 39467.259
B104: SecurLock (SL) | C104: Securlock (SL) Detect | E104: 376348 | F104: 363876 | G104: 375804 | H104: =IFERROR(AVERAGE(D104:G104),0) -> 372009.33 | I104: =H104*12 -> 4464112 | J104: =IF(I104>12,(((I104)*$H$5)+I104),(I104*1)) -> 4687317.6 | K104: =IF(J104>12,(((J104)*$H$5)+J104),(J104*1)) -> 4921683.5 | L104: =IF(K104>12,(((K104)*$H$5)+K104),(K104*1)) -> 5167767.7 | M104: =IF(L104>12,(((L104)*$H$5)+L104),(L104*1)) -> 5426156 | N104: =IF(C104="","",C104) -> Securlock (SL) Detect | O104: 0.002802 | P104: =Q104/12 -> 1042.3702 | Q104: =IF(O104>0,PRODUCT(I104,$O104),0) -> 12508.442 | R104: =IF(Q104>0,PRODUCT(J104,$O104),0) -> 13133.864 | S104: =IF(R104>0,PRODUCT(K104,$O104),0) -> 13790.557 | T104: =IF(S104>0,PRODUCT(L104,$O104),0) -> 14480.085 | U104: =IF(T104>0,PRODUCT(M104,$O104),0) -> 15204.089 | V104: =SUM(Q104:U104) -> 69117.037 | X104: =C104 -> Securlock (SL) Detect | Y104: 0.0028 | Z104: =AA104/12 -> 1041.6261 | AA104: =IF(Y104>0,PRODUCT(I104,$Y104),0) -> 12499.514 | AB104: =IF(AA104>0,PRODUCT(J104,$Y104),0) -> 13124.489 | AC104: =IF(AB104>0,PRODUCT(K104,$Y104),0) -> 13780.714 | AD104: =IF(AC104>0,PRODUCT(L104,$Y104),0) -> 14469.749 | AE104: =IF(AD104>0,PRODUCT(M104,$Y104),0) -> 15193.237 | AF104: =SUM(AA104:AE104) -> 69067.703 | AI104: =C104 -> Securlock (SL) Detect | AJ104: 0.0028 | AK104: =AL104/12 -> 1041.6261 | AL104: {=_xlfn.IFS($AJ104="NO CHARGE",0,$AJ104=0,0,$AJ104>0,PRODUCT(I104,$AJ104))} -> 12499.514 | AM104: {=_xlfn.IFS($AJ104="NO CHARGE",0,$AJ104=0,0,$AJ104>0,PRODUCT(J104,$AJ104))} -> 13124.489 | AN104: {=_xlfn.IFS($AJ104="NO CHARGE",0,$AJ104=0,0,$AJ104>0,PRODUCT(K104,$AJ104))} -> 13780.714 | AO104: {=_xlfn.IFS($AJ104="NO CHARGE",0,$AJ104=0,0,$AJ104>0,PRODUCT(L104,$AJ104))} -> 14469.749 | AP104: {=_xlfn.IFS($AJ104="NO CHARGE",0,$AJ104=0,0,$AJ104>0,PRODUCT(M104,$AJ104))} -> 15193.237 | AQ104: =SUM(AL104:AP104) -> 69067.703
H105: =IFERROR(AVERAGE(D105:G105),0) -> 0 | I105: =H105*12 -> 0 | J105: =IF(I105>12,(((I105)*$H$5)+I105),(I105*1)) -> 0 | K105: =IF(J105>12,(((J105)*$H$5)+J105),(J105*1)) -> 0 | L105: =IF(K105>12,(((K105)*$H$5)+K105),(K105*1)) -> 0 | M105: =IF(L105>12,(((L105)*$H$5)+L105),(L105*1)) -> 0 | N105: =IF(C105="","",C105) | P105: =Q105/12 -> 0 | Q105: =IF(O105>0,PRODUCT(I105,$O105),0) -> 0 | R105: =IF(Q105>0,PRODUCT(J105,$O105),0) -> 0 | S105: =IF(R105>0,PRODUCT(K105,$O105),0) -> 0 | T105: =IF(S105>0,PRODUCT(L105,$O105),0) -> 0 | U105: =IF(T105>0,PRODUCT(M105,$O105),0) -> 0 | V105: =SUM(Q105:U105) -> 0 | Z105: =AA105/12 -> 0 | AA105: =IF(Y105>0,PRODUCT(I105,$Y105),0) -> 0 | AB105: =IF(AA105>0,PRODUCT(J105,$Y105),0) -> 0 | AC105: =IF(AB105>0,PRODUCT(K105,$Y105),0) -> 0 | AD105: =IF(AC105>0,PRODUCT(L105,$Y105),0) -> 0 | AE105: =IF(AD105>0,PRODUCT(M105,$Y105),0) -> 0 | AF105: =SUM(AA105:AE105) -> 0 | AK105: =AL105/12 -> 0 | AL105: {=_xlfn.IFS($AJ105="NO CHARGE",0,$AJ105=0,0,$AJ105>0,PRODUCT(I105,$AJ105))} -> 0 | AM105: {=_xlfn.IFS($AJ105="NO CHARGE",0,$AJ105=0,0,$AJ105>0,PRODUCT(J105,$AJ105))} -> 0 | AN105: {=_xlfn.IFS($AJ105="NO CHARGE",0,$AJ105=0,0,$AJ105>0,PRODUCT(K105,$AJ105))} -> 0 | AO105: {=_xlfn.IFS($AJ105="NO CHARGE",0,$AJ105=0,0,$AJ105>0,PRODUCT(L105,$AJ105))} -> 0 | AP105: {=_xlfn.IFS($AJ105="NO CHARGE",0,$AJ105=0,0,$AJ105>0,PRODUCT(M105,$AJ105))} -> 0 | AQ105: =SUM(AL105:AP105) -> 0 | AV105: =IF(AU105>0,PRODUCT(I105,$AU105),0) -> 0 | AW105: =IF(AV105>0,PRODUCT(J105,$AU105),0) -> 0 | AX105: =IF(AW105>0,PRODUCT(K105,$AU105),0) -> 0 | AY105: =IF(AX105>0,PRODUCT(L105,$AU105),0) -> 0 | AZ105: =IF(AY105>0,PRODUCT(M105,$AU105),0) -> 0 | BA105: =SUM(AV105:AZ105) -> 0
...

Sheet CORE One Time Items
C2: CORE: One Time Items
C3: ='(INTERNAL) Basic Entry '!$C$7 -> First State Bank of Waynesboro | G3: One-Time Fees | K3: ='(INTERNAL) Basic Entry '!$C$19 -> FIS Horizon with D1 Flex | O3: ='(INTERNAL) Basic Entry '!C21 -> FIS Horizon WITHOUT D1 Flex | S3: ='(INTERNAL) Basic Entry '!C23 -> Vendor #3
C4: ='(INTERNAL) Basic Entry '!$C$9&" Pricing Analysis" -> CORE & DIGITAL Pricing Analysis | G4: Baseline for One-Time Fees from Proposed Pre-Negotiation | K4: ='(INTERNAL) Basic Entry '!F19 -> Proposal Dated 12/13/2023 | O4: ='(INTERNAL) Basic Entry '!F21 -> Proposal Dated 12/13/2023 | S4: ='(INTERNAL) Basic Entry '!F23 -> Month Year
A5: LoB | B5: Category | C5: IMPLEMENTATION, SETUP, DECONVERSION FEES | D5: Term Quantity | E5: Depreciation & Amortization Term (months) | F5: % that can be Depreciated Amortized | G5: =C5 -> IMPLEMENTATION, SETUP, DECONVERSION FEES | H5: Per Unit Rate | I5: Total Term Cost | J5: Line Item Note | K5: =C5 -> IMPLEMENTATION, SETUP, DECONVERSION FEES | L5: Per Unit Rate | M5: Term Total Cost | N5: Line Item Note | O5: =C5 -> IMPLEMENTATION, SETUP, DECONVERSION FEES | P5: Per Unit Rate | Q5: Term Total Cost | R5: Line Item Note | S5: =C5 -> IMPLEMENTATION, SETUP, DECONVERSION FEES | T5: Per Unit Rate | U5: Year 1 Cost | V5: Year 2 Cost | W5: Year 3 Cost | X5: Year 4 Cost | Y5: Year 5 Cost | Z5: Term Total Cost | AA5: Line Item Note
C7: RENEWAL FEES / CONVERSION FEES | K7: =C7 -> RENEWAL FEES / CONVERSION FEES | M7: {=_xlfn.IFS(L7="WAIVED",0,L7>0,$L7*$D7, L7=0,0)} -> 0 | O7: =C7 -> RENEWAL FEES / CONVERSION FEES | Q7: {=_xlfn.IFS(P7="WAIVED",0,P7>0,$P7*$D7, P7=0,0)} -> 0 | Z7: =$T7*$D7 -> 0
C8: Horizon Core Service Bureau Processing | D8: 1 | E8: 60 | F8: 1 | K8: =C8 -> Horizon Core Service Bureau Processing | M8: Included | O8: =C8 -> Horizon Core Service Bureau Processing | Q8: Included | Z8: =$T8*$D8 -> 0
C9: Horizon Products and Services (Open/Closed) Graduated | D9: 1 | E9: 60 | F9: 1 | K9: =C9 -> Horizon Products and Services (Open/Closed) Graduated | M9: Included | O9: =C9 -> Horizon Products and Services (Open/Closed) Graduated | Q9: Included | Z9: =$T9*$D9 -> 0
C10: Same Day ACH Settlement | D10: 1 | E10: 60 | F10: 1 | K10: =C10 -> Same Day ACH Settlement | M10: Included | O10: =C10 -> Same Day ACH Settlement | Q10: Included | Z10: =$T10*$D10 -> 0
C11: Deposit Origination (DO) | D11: 1 | E11: 60 | F11: 1 | K11: =C11 -> Deposit Origination (DO) | M11: Included | O11: =C11 -> Deposit Origination (DO) | Q11: Included | Z11: =$T11*$D11 -> 0
C12: CSi Simplicity Hosting | D12: 1 | E12: 60 | F12: 1 | K12: =C12 -> CSi Simplicity Hosting | M12: Included | O12: =C12 -> CSi Simplicity Hosting | Q12: Included | Z12: =$T12*$D12 -> 0
C13: SmartSign | D13: 1 | E13: 60 | F13: 1 | K13: =C13 -> SmartSign | M13: Included | O13: =C13 -> SmartSign | Q13: Included | Z13: =$T13*$D13 -> 0
C14: Horizon 360 BI Enterprise License | D14: 1 | E14: 60 | F14: 1 | K14: =C14 -> Horizon 360 BI Enterprise License | M14: Included | O14: =C14 -> Horizon 360 BI Enterprise License | Q14: Included | Z14: =$T14*$D14 -> 0
C15: Horizon 360 BI Web Administrator | D15: 1 | E15: 60 | F15: 1 | K15: =C15 -> Horizon 360 BI Web Administrator | M15: Included | O15: =C15 -> Horizon 360 BI Web Administrator | Q15: Included | Z15: =$T15*$D15 -> 0
C16: 3rd Party Interface: CASS Certification - WorksRight | D16: 1 | E16: 60 | F16: 1 | K16: =C16 -> 3rd Party Interface: CASS Certification - WorksRight | M16: Included | O16: =C16 -> 3rd Party Interface: CASS Certification - WorksRight | Q16: Included | Z16: =$T16*$D16 -> 0
C17: 3rd Party Interface: Internet Banking - Q2 eBanking | D17: 1 | E17: 60 | F17: 1 | K17: =C17 -> 3rd Party Interface: Internet Banking - Q2 eBanking | M17: Included | O17: =C17 -> 3rd Party Interface: Internet Banking - Q2 eBanking | Q17: Included | Z17: =$T17*$D17 -> 0
C18: Item Processing Services (NEW Format) | D18: 1 | E18: 60 | F18: 1 | K18: =C18 -> Item Processing Services (NEW Format) | M18: Included | O18: =C18 -> Item Processing Services (NEW Format) | Q18: Included | Z18: =$T18*$D18 -> 0
C19: DirectLINK Merchant | D19: 1 | E19: 60 | F19: 1 | K19: =C19 -> DirectLINK Merchant | M19: Included | O19: =C19 -> DirectLINK Merchant | Q19: Included | Z19: =$T19*$D19 -> 0
C20: Network Services | D20: 1 | E20: 60 | F20: 1 | K20: =C20 -> Network Services | M20: Included | O20: =C20 -> Network Services | Q20: Included | Z20: =$T20*$D20 -> 0
C21: One time fee | D21: 1 | E21: 60 | F21: 1 | K21: =C21 -> One time fee | L21: 184401 | M21: {=_xlfn.IFS(L21="WAIVED",0,L21>0,$L21*$D21, L21=0,0)} -> 184401 | O21: =C21 -> One time fee | P21: 206901 | Q21: {=_xlfn.IFS(P21="WAIVED",0,P21>0,$P21*$D21, P21=0,0)} -> 206901 | Z21: =$T21*$D21 -> 0
B22: SOW One Time Investment Fees Itemized | C22: Mobile | D22: 1 | E22: 60 | F22: 1 | N22: Itemized Breakdown of SOW Migration Fee | O22: Mobile | Q22: Included | R22: Itemized Breakdown of SOW Migration Fee | Z22: =$T22*$D22 -> 0
B23: SOW One Time Investment Fees Itemized | C23: OLB | D23: 1 | E23: 60 | F23: 1 | N23: Itemized Breakdown of SOW Migration Fee | O23: OLB | Q23: Included | R23: Itemized Breakdown of SOW Migration Fee | Z23: =$T23*$D23 -> 0
B24: SOW One Time Investment Fees Itemized | C24: Bill Pay Consumer | D24: 1 | E24: 60 | F24: 1 | N24: Itemized Breakdown of SOW Migration Fee | O24: Bill Pay Consumer | Q24: Included | R24: Itemized Breakdown of SOW Migration Fee | Z24: =$T24*$D24 -> 0
B25: SOW One Time Investment Fees Itemized | C25: Content Management | D25: 1 | E25: 60 | F25: 1 | K25: =C25 -> Content Management | M25: Included | N25: Itemized Breakdown of SOW Migration Fee | O25: =K25 -> Content Management | Q25: Included | R25: Itemized Breakdown of SOW Migration Fee | Z25: =$T25*$D25 -> 0
B26: SOW One Time Investment Fees Itemized | C26: DL Merchant | D26: 1 | E26: 60 | F26: 1 | K26: =C26 -> DL Merchant | M26: Included | N26: Itemized Breakdown of SOW Migration Fee | O26: =K26 -> DL Merchant | Q26: Included | R26: Itemized Breakdown of SOW Migration Fee | Z26: =$T26*$D26 -> 0
B27: SOW One Time Investment Fees Itemized | C27: EFT | D27: 1 | E27: 60 | F27: 1 | K27: =C27 -> EFT | M27: Included | N27: Itemized Breakdown of SOW Migration Fee | O27: =K27 -> EFT | Q27: Included | R27: Itemized Breakdown of SOW Migration Fee | Z27: =$T27*$D27 -> 0
B28: SOW One Time Investment Fees Itemized | C28: Voice Response | D28: 1 | E28: 60 | F28: 1 | K28: =C28 -> Voice Response | M28: Included | N28: Itemized Breakdown of SOW Migration Fee | O28: =K28 -> Voice Response | Q28: Included | R28: Itemized Breakdown of SOW Migration Fee | Z28: =$T28*$D28 -> 0
B29: SOW One Time Investment Fees Itemized | C29: FXD | D29: 1 | E29: 60 | F29: 1 | K29: =C29 -> FXD | M29: Included | N29: Itemized Breakdown of SOW Migration Fee | O29: =K29 -> FXD | Q29: Included | R29: Itemized Breakdown of SOW Migration Fee | Z29: =$T29*$D29 -> 0
B30: SOW One Time Investment Fees Itemized | C30: IP | D30: 1 | E30: 60 | F30: 1 | K30: =C30 -> IP | M30: Included | N30: Itemized Breakdown of SOW Migration Fee | O30: =K30 -> IP | Q30: Included | R30: Itemized Breakdown of SOW Migration Fee | Z30: =$T30*$D30 -> 0
C31: Legacy Conversion | D31: 1 | E31: 60 | F31: 1 | K31: =C31 -> Legacy Conversion | L31: TBD per Proposal | M31: {=_xlfn.IFS(L31="TBD per Proposal",0,L31>0,$L31*$D31, L31=0,0)} -> 0 | O31: =C31 -> Legacy Conversion | Q31: {=_xlfn.IFS(P31="TBD",0,P31>0,$P31*$D31, P31=0,0)} -> 0 | Z31: =$T31*$D31 -> 0
M32: {=_xlfn.IFS(L32="WAIVED",0,L32>0,$L32*$D32, L32=0,0)} -> 0 | Q32: {=_xlfn.IFS(P32="WAIVED",0,P32>0,$P32*$D32, P32=0,0)} -> 0 | Z32: =$T32*$D32 -> 0
M33: {=_xlfn.IFS(L33="WAIVED",0,L33>0,$L33*$D33, L33=0,0)} -> 0 | Q33: {=_xlfn.IFS(P33="WAIVED",0,P33>0,$P33*$D33, P33=0,0)} -> 0 | Z33: =$T33*$D33 -> 0
M34: {=_xlfn.IFS(L34="WAIVED",0,L34>0,$L34*$D34, L34=0,0)} -> 0 | Q34: {=_xlfn.IFS(P34="WAIVED",0,P34>0,$P34*$D34, P34=0,0)} -> 0 | Z34: =$T34*$D34 -> 0
C36: Implementation and Setup Fees Sum: | G36: =C36 -> Implementation and Setup Fees Sum: | I36: =SUM(I7:I34) -> 0 | K36: =C36 -> Implementation and Setup Fees Sum: | M36: =SUM(M7:M34) -> 184401 | O36: =C36 -> Implementation and Setup Fees Sum: | Q36: =SUM(Q7:Q34) -> 206901 | S36: =C36 -> Implementation and Setup Fees Sum: | Z36: =SUM(Z7:Z34) -> 0
C38: INCENTIVES, REBATES, TERM DISCOUNTS | D38: Term Quantity | E38: Depreciation & Amortization Term (months) | F38: % that can be Depreciated Amortized | G38: =C38 -> INCENTIVES, REBATES, TERM DISCOUNTS | H38: Per Unit Rate | I38: Total Term Cost | K38: =C38 -> INCENTIVES, REBATES, TERM DISCOUNTS | L38: Per Unit Rate | M38: Term Total Cost | O38: =C38 -> INCENTIVES, REBATES, TERM DISCOUNTS | P38: Per Unit Rate | Q38: Term Total Cost | S38: =C38 -> INCENTIVES, REBATES, TERM DISCOUNTS | T38: Per Unit Rate | Z38: Term Total Cost
B39: INCENTIVE | C39: ONE TIME CREDIT - TO OFFSET ONE TIME FEES OR ADDITIONAL COSTS | D39: 1 | E39: 60 | F39: 1 | I39: =$H39*$D39 -> 0 | K39: =C39 -> ONE TIME CREDIT - TO OFFSET ONE TIME FEES OR ADDITIONAL COSTS | L39: =M36*-1 -> -184401 | M39: =$L39*D39 -> -184401
B40: INCENTIVE | C40: ONE TIME CREDIT - REMAINING CAN BE APPLIED TO RECURRING COSTS | D40: 1 | E40: 60 | F40: 1 | I40: =$H40*$D40 -> 0 | K40: =C40 -> ONE TIME CREDIT - REMAINING CAN BE APPLIED TO RECURRING COSTS | L40: =-400000-L39 -> -215599 | M40: =$L40*D40 -> -215599
B41: INCENTIVE | C41: MC BRAND FLIP - REMAINING CREDITS TO CONTINUE WITH RENEWAL | D41: 1 | E41: 60 | F41: 1 | K41: =C41 -> MC BRAND FLIP - REMAINING CREDITS TO CONTINUE WITH RENEWAL | L41: -259866 | M41: =$L41*D41 -> -259866
B42: INCENTIVE | C42: EARLY RENEWAL - 17 MONTHS IF SIGNED MARCH 2024 | K42: =C42 -> EARLY RENEWAL - 17 MONTHS IF SIGNED MARCH 2024 | M42: =$L42*$D42 -> 0 | N42: THIS ITEM IS CALCULATED IN ITS OWN WORKSHEET
B43: INCENTIVE | C43: ONE TIME CREDIT - TO OFFSET ONE TIME FEES OR ADDITIONAL COSTS | D43: 1 | E43: 60 | F43: 1 | O43: =C43 -> ONE TIME CREDIT - TO OFFSET ONE TIME FEES OR ADDITIONAL COSTS | P43: =Q36*-1 -> -206901 | Q43: =P43*D43 -> -206901
B44: INCENTIVE | C44: ONE TIME CREDIT - REMAINING CAN BE APPLIED TO RECURRING COSTS | D44: 1 | E44: 60 | F44: 1 | O44: =C44 -> ONE TIME CREDIT - REMAINING CAN BE APPLIED TO RECURRING COSTS | P44: =-400000-P43 -> -193099 | Q44: =P44*D44 -> -193099
B45: INCENTIVE | C45: MC BRAND FLIP - REMAINING CREDITS TO CONTINUE WITH RENEWAL | D45: 1 | E45: 60 | F45: 1 | I45: =$H45*$D45 -> 0 | O45: =C45 -> MC BRAND FLIP - REMAINING CREDITS TO CONTINUE WITH RENEWAL | P45: -259866 | Q45: =P45*D45 -> -259866
B46: INCENTIVE | C46: EARLY RENEWAL - 17 MONTHS IF SIGNED MARCH 2024 | I46: =$H46*$D46 -> 0 | O46: =C46 -> EARLY RENEWAL - 17 MONTHS IF SIGNED MARCH 2024 | Q46: =P46*D46 -> 0 | R46: THIS ITEM IS CALCULATED IN ITS OWN WORKSHEET
I47: =$H47*$D47 -> 0
C49: Incentives Sum: | G49: =C49 -> Incentives Sum: | I49: =SUM(I39:I47) -> 0 | K49: =C49 -> Incentives Sum: | M49: =SUM(M39:M47) -> -659866 | O49: =C49 -> Incentives Sum: | Q49: =SUM(Q39:Q47) -> -659866 | S49: =C49 -> Incentives Sum: | Z49: =SUM(Z39:Z47) -> 0
C51: Term Totals | G51: Term Totals | I51: =SUM(I36,I49) -> 0 | K51: Term Totals | M51: =SUM(M36,M49) -> -475465 | O51: Term Totals | Q51: =SUM(Q36,Q49) -> -452965 | Z51: =SUM(#REF!,#REF!,#REF!,Z36,Z49) -> #REF!
I53: =I51/60 -> 0 | K53: Monthly Estimations | M53: =M51/60 -> -7924.4167 | O53: Monthly Estimations | Q53: =Q51/60 -> -7549.4167 | Z53: =Z51/60 -> #REF!

Sheet Optional Items - DESIRED
C3: Optional Items - Desired/Must Haves | E3: QTY YOY Growth % | F3: CPI Rates
C4: ='(INTERNAL) Basic Entry '!$C$7 -> First State Bank of Waynesboro | F4: Current | G4: Vendor #1 Proposed | H4: Vendor #2 Proposed | I4: Vendor #3 Proposed | J4: ='(INTERNAL) Basic Entry '!$C$17 -> Current (FIS Bankway) | R4: ='(INTERNAL) Basic Entry '!$C$19 -> FIS Horizon with D1 Flex | AA4: ='(INTERNAL) Basic Entry '!C21 -> FIS Horizon WITHOUT D1 Flex | AJ4: ='(INTERNAL) Basic Entry '!C23 -> Vendor #3
C5: ='(INTERNAL) Basic Entry '!$C$9&" Pricing Analysis" -> CORE & DIGITAL Pricing Analysis | E5: 0 | F5: 0 | G5: 0 | H5: 0 | I5: 0 | J5: ='(INTERNAL) Basic Entry '!$B$14 -> Baseline from Current Invoices | R5: ='(INTERNAL) Basic Entry '!F19 -> Proposal Dated 12/13/2023 | AA5: ='(INTERNAL) Basic Entry '!F21 -> Proposal Dated 12/13/2023 | AJ5: ='(INTERNAL) Basic Entry '!F23 -> Month Year
A6: Vendor | B6: Code | C6: Item Name | D6: Average Monthly QTY | E6: Year 1 Quantity | F6: Year 2 Quantity | G6: Year 3 Quantity | H6: Year 4 Quantity | I6: Year 5 Quantity | J6: Item Name | K6: Per Unit Rate | L6: Year 1 Cost | M6: Year 2 Cost | N6: Year 3 Cost | O6: Year 4 Cost | P6: Year 5 Cost | Q6: Total Term Cost | R6: Product Name | S6: Per Unit Rate | T6: Year 1 Cost | U6: Year 2 Cost | V6: Year 3 Cost | W6: Year 4 Cost | X6: Year 5 Cost | Y6: Term Total Cost | Z6: Line Item Notes | AA6: Product Name | AB6: Per Unit Rate | AC6: Year 1 Cost | AD6: Year 2 Cost | AE6: Year 3 Cost | AF6: Year 4 Cost | AG6: Year 5 Cost | AH6: Term Total Cost | AI6: Line Item Notes | AJ6: Product Name | AK6: Per Unit Rate | AL6: Year 1 Cost | AM6: Year 2 Cost | AN6: Year 3 Cost | AO6: Year 4 Cost | AP6: Year 5 Cost | AQ6: Term Total Cost | AR6: Line Item Notes
C8: IHC ITEMS | R8: =C8 -> IHC ITEMS | AA8: IHC ITEMS | AJ8: IHC ITEMS
E9: =D9*12 -> 0 | F9: =IF(E9>12,(((E9)*$E$5)+E9),(E9*1)) -> 0 | G9: =IF(F9>12,(((F9)*$E$5)+F9),(F9*1)) -> 0 | H9: =IF(G9>12,(((G9)*$E$5)+G9),(G9*1)) -> 0 | I9: =IF(H9>12,(((H9)*$E$5)+H9),(H9*1)) -> 0 | T9: =IF($S9>0,PRODUCT(E9,$S9),0) -> 0 | U9: =IF($S9>0,PRODUCT(F9,$S9),0) -> 0 | V9: =IF($S9>0,PRODUCT(G9,$S9),0) -> 0 | W9: =IF($S9>0,PRODUCT(H9,$S9),0) -> 0 | X9: =IF($S9>0,PRODUCT(I9,$S9),0) -> 0 | Y9: =SUM(T9:X9) -> 0 | AC9: =IF(AB9>0,PRODUCT(E9,$AB9),0) -> 0 | AD9: =IF(AC9>0,PRODUCT(F9,$AB9),0) -> 0 | AE9: =IF(AD9>0,PRODUCT(G9,$AB9),0) -> 0 | AF9: =IF(AE9>0,PRODUCT(H9,$AB9),0) -> 0 | AG9: =IF(AF9>0,PRODUCT(I9,$AB9),0) -> 0 | AH9: =SUM(AC9:AG9) -> 0
E10: =D10*12 -> 0 | F10: =IF(E10>12,(((E10)*$E$5)+E10),(E10*1)) -> 0 | G10: =IF(F10>12,(((F10)*$E$5)+F10),(F10*1)) -> 0 | H10: =IF(G10>12,(((G10)*$E$5)+G10),(G10*1)) -> 0 | I10: =IF(H10>12,(((H10)*$E$5)+H10),(H10*1)) -> 0 | T10: =IF($S10>0,PRODUCT(E10,$S10),0) -> 0 | U10: =IF($S10>0,PRODUCT(F10,$S10),0) -> 0 | V10: =IF($S10>0,PRODUCT(G10,$S10),0) -> 0 | W10: =IF($S10>0,PRODUCT(H10,$S10),0) -> 0 | X10: =IF($S10>0,PRODUCT(I10,$S10),0) -> 0 | Y10: =SUM(T10:X10) -> 0
E11: =D11*12 -> 0 | F11: =IF(E11>12,(((E11)*$E$5)+E11),(E11*1)) -> 0 | G11: =IF(F11>12,(((F11)*$E$5)+F11),(F11*1)) -> 0 | H11: =IF(G11>12,(((G11)*$E$5)+G11),(G11*1)) -> 0 | I11: =IF(H11>12,(((H11)*$E$5)+H11),(H11*1)) -> 0 | T11: =IF($S11>0,PRODUCT(E11,$S11),0) -> 0 | U11: =IF($S11>0,PRODUCT(F11,$S11),0) -> 0 | V11: =IF($S11>0,PRODUCT(G11,$S11),0) -> 0 | W11: =IF($S11>0,PRODUCT(H11,$S11),0) -> 0 | X11: =IF($S11>0,PRODUCT(I11,$S11),0) -> 0 | Y11: =SUM(T11:X11) -> 0 | AC11: =IF(AB11>0,PRODUCT(E11,$AB11),0) -> 0 | AD11: =IF(AC11>0,PRODUCT(F11,$AB11),0) -> 0 | AE11: =IF(AD11>0,PRODUCT(G11,$AB11),0) -> 0 | AF11: =IF(AE11>0,PRODUCT(H11,$AB11),0) -> 0 | AG11: =IF(AF11>0,PRODUCT(I11,$AB11),0) -> 0 | AH11: =SUM(AC11:AG11) -> 0
E12: =D12*12 -> 0 | F12: =IF(E12>12,(((E12)*$E$5)+E12),(E12*1)) -> 0 | G12: =IF(F12>12,(((F12)*$E$5)+F12),(F12*1)) -> 0 | H12: =IF(G12>12,(((G12)*$E$5)+G12),(G12*1)) -> 0 | I12: =IF(H12>12,(((H12)*$E$5)+H12),(H12*1)) -> 0 | T12: =IF($S12>0,PRODUCT(E12,$S12),0) -> 0 | U12: =IF($S12>0,PRODUCT(F12,$S12),0) -> 0 | V12: =IF($S12>0,PRODUCT(G12,$S12),0) -> 0 | W12: =IF($S12>0,PRODUCT(H12,$S12),0) -> 0 | X12: =IF($S12>0,PRODUCT(I12,$S12),0) -> 0 | Y12: =SUM(T12:X12) -> 0 | AC12: =IF(AB12>0,PRODUCT(E12,$AB12),0) -> 0 | AD12: =IF(AC12>0,PRODUCT(F12,$AB12),0) -> 0 | AE12: =IF(AD12>0,PRODUCT(G12,$AB12),0) -> 0 | AF12: =IF(AE12>0,PRODUCT(H12,$AB12),0) -> 0 | AG12: =IF(AF12>0,PRODUCT(I12,$AB12),0) -> 0 | AH12: =SUM(AC12:AG12) -> 0
E13: =D13*12 -> 0 | F13: =IF(E13>12,(((E13)*#REF!)+E13),(E13*1)) -> 0 | G13: =IF(F13>12,(((F13)*#REF!)+F13),(F13*1)) -> 0 | H13: =IF(G13>12,(((G13)*#REF!)+G13),(G13*1)) -> 0 | I13: =IF(H13>12,(((H13)*#REF!)+H13),(H13*1)) -> 0 | AC13: =IF(AB13>0,PRODUCT(E13,$AB13),0) -> 0 | AD13: =IF(AC13>0,PRODUCT(F13,$AB13),0) -> 0 | AE13: =IF(AD13>0,PRODUCT(G13,$AB13),0) -> 0 | AF13: =IF(AE13>0,PRODUCT(H13,$AB13),0) -> 0 | AG13: =IF(AF13>0,PRODUCT(I13,$AB13),0) -> 0 | AH13: =SUM(AC13:AG13) -> 0
E14: =D14*12 -> 0 | F14: =IF(E14>12,(((E14)*#REF!)+E14),(E14*1)) -> 0 | G14: =IF(F14>12,(((F14)*#REF!)+F14),(F14*1)) -> 0 | H14: =IF(G14>12,(((G14)*#REF!)+G14),(G14*1)) -> 0 | I14: =IF(H14>12,(((H14)*#REF!)+H14),(H14*1)) -> 0 | AC14: =IF(AB14>0,PRODUCT(E14,$AB14),0) -> 0 | AD14: =IF(AC14>0,PRODUCT(F14,$AB14),0) -> 0 | AE14: =IF(AD14>0,PRODUCT(G14,$AB14),0) -> 0 | AF14: =IF(AE14>0,PRODUCT(H14,$AB14),0) -> 0 | AG14: =IF(AF14>0,PRODUCT(I14,$AB14),0) -> 0 | AH14: =SUM(AC14:AG14) -> 0
E15: =D15*12 -> 0 | F15: =IF(E15>12,(((E15)*#REF!)+E15),(E15*1)) -> 0 | G15: =IF(F15>12,(((F15)*#REF!)+F15),(F15*1)) -> 0 | H15: =IF(G15>12,(((G15)*#REF!)+G15),(G15*1)) -> 0 | I15: =IF(H15>12,(((H15)*#REF!)+H15),(H15*1)) -> 0 | AC15: =IF(AB15>0,PRODUCT(E15,$AB15),0) -> 0 | AD15: =IF(AC15>0,PRODUCT(F15,$AB15),0) -> 0 | AE15: =IF(AD15>0,PRODUCT(G15,$AB15),0) -> 0 | AF15: =IF(AE15>0,PRODUCT(H15,$AB15),0) -> 0 | AG15: =IF(AF15>0,PRODUCT(I15,$AB15),0) -> 0 | AH15: =SUM(AC15:AG15) -> 0
C17: IHC - REWARDS UPGRADE | R17: =C17 -> IHC - REWARDS UPGRADE | AA17: IHC ITEMS | AJ17: IHC ITEMS
E18: =D18*12 -> 0 | F18: =IF(E18>12,(((E18)*$E$5)+E18),(E18*1)) -> 0 | G18: =IF(F18>12,(((F18)*$E$5)+F18),(F18*1)) -> 0 | H18: =IF(G18>12,(((G18)*$E$5)+G18),(G18*1)) -> 0 | I18: =IF(H18>12,(((H18)*$E$5)+H18),(H18*1)) -> 0 | T18: =IF($S18>0,PRODUCT(E18,$S18),0) -> 0 | U18: =IF($S18>0,PRODUCT(F18,$S18),0) -> 0 | V18: =IF($S18>0,PRODUCT(G18,$S18),0) -> 0 | W18: =IF($S18>0,PRODUCT(H18,$S18),0) -> 0 | X18: =IF($S18>0,PRODUCT(I18,$S18),0) -> 0 | Y18: =SUM(T18:X18) -> 0
E19: =D19*12 -> 0 | F19: =IF(E19>12,(((E19)*$E$5)+E19),(E19*1)) -> 0 | G19: =IF(F19>12,(((F19)*$E$5)+F19),(F19*1)) -> 0 | H19: =IF(G19>12,(((G19)*$E$5)+G19),(G19*1)) -> 0 | I19: =IF(H19>12,(((H19)*$E$5)+H19),(H19*1)) -> 0 | T19: =IF($S19>0,PRODUCT(E19,$S19),0) -> 0 | U19: =IF($S19>0,PRODUCT(F19,$S19),0) -> 0 | V19: =IF($S19>0,PRODUCT(G19,$S19),0) -> 0 | W19: =IF($S19>0,PRODUCT(H19,$S19),0) -> 0 | X19: =IF($S19>0,PRODUCT(I19,$S19),0) -> 0 | Y19: =SUM(T19:X19) -> 0
T20: =SUM(#REF!,#REF!,#REF!)*-1 -> #REF! | U20: =SUM(#REF!,#REF!,#REF!)*-1 -> #REF! | V20: =SUM(#REF!,#REF!,#REF!)*-1 -> #REF! | W20: =SUM(#REF!,#REF!,#REF!)*-1 -> #REF! | X20: =SUM(#REF!,#REF!,#REF!)*-1 -> #REF! | Y20: =SUM(T20:X20) -> #REF!
C22: APIs & INTEGRATIONS | R22: =C22 -> APIs & INTEGRATIONS | AA22: =C22 -> APIs & INTEGRATIONS | AJ22: =C22 -> APIs & INTEGRATIONS
E23: =D23*12 -> 0 | F23: =IF(E23>12,(((E23)*$E$5)+E23),(E23*1)) -> 0 | G23: =IF(F23>12,(((F23)*$E$5)+F23),(F23*1)) -> 0 | H23: =IF(G23>12,(((G23)*$E$5)+G23),(G23*1)) -> 0 | I23: =IF(H23>12,(((H23)*$E$5)+H23),(H23*1)) -> 0 | T23: =IF($S23>0,PRODUCT(E23,$S23),0) -> 0 | U23: =IF($S23>0,PRODUCT(F23,$S23),0) -> 0 | V23: =IF($S23>0,PRODUCT(G23,$S23),0) -> 0 | W23: =IF($S23>0,PRODUCT(H23,$S23),0) -> 0 | X23: =IF($S23>0,PRODUCT(I23,$S23),0) -> 0 | Y23: =SUM(T23:X23) -> 0
E24: =D24*12 -> 0 | F24: =IF(E24>12,(((E24)*$E$5)+E24),(E24*1)) -> 0 | G24: =IF(F24>12,(((F24)*$E$5)+F24),(F24*1)) -> 0 | H24: =IF(G24>12,(((G24)*$E$5)+G24),(G24*1)) -> 0 | I24: =IF(H24>12,(((H24)*$E$5)+H24),(H24*1)) -> 0 | T24: =IF($S24>0,PRODUCT(E24,$S24),0) -> 0 | U24: =IF($S24>0,PRODUCT(F24,$S24),0) -> 0 | V24: =IF($S24>0,PRODUCT(G24,$S24),0) -> 0 | W24: =IF($S24>0,PRODUCT(H24,$S24),0) -> 0 | X24: =IF($S24>0,PRODUCT(I24,$S24),0) -> 0 | Y24: =SUM(T24:X24) -> 0
E25: =D25*12 -> 0 | F25: =IF(E25>12,(((E25)*$E$5)+E25),(E25*1)) -> 0 | G25: =IF(F25>12,(((F25)*$E$5)+F25),(F25*1)) -> 0 | H25: =IF(G25>12,(((G25)*$E$5)+G25),(G25*1)) -> 0 | I25: =IF(H25>12,(((H25)*$E$5)+H25),(H25*1)) -> 0 | T25: =IF($S25>0,PRODUCT(E25,$S25),0) -> 0 | U25: =IF($S25>0,PRODUCT(F25,$S25),0) -> 0 | V25: =IF($S25>0,PRODUCT(G25,$S25),0) -> 0 | W25: =IF($S25>0,PRODUCT(H25,$S25),0) -> 0 | X25: =IF($S25>0,PRODUCT(I25,$S25),0) -> 0 | Y25: =SUM(T25:X25) -> 0
E26: =D26*12 -> 0 | F26: =IF(E26>12,(((E26)*$E$5)+E26),(E26*1)) -> 0 | G26: =IF(F26>12,(((F26)*$E$5)+F26),(F26*1)) -> 0 | H26: =IF(G26>12,(((G26)*$E$5)+G26),(G26*1)) -> 0 | I26: =IF(H26>12,(((H26)*$E$5)+H26),(H26*1)) -> 0
E27: =D27*12 -> 0 | F27: =IF(E27>12,(((E27)*$E$5)+E27),(E27*1)) -> 0 | G27: =IF(F27>12,(((F27)*$E$5)+F27),(F27*1)) -> 0 | H27: =IF(G27>12,(((G27)*$E$5)+G27),(G27*1)) -> 0 | I27: =IF(H27>12,(((H27)*$E$5)+H27),(H27*1)) -> 0
E28: =D28*12 -> 0 | F28: =IF(E28>12,(((E28)*$E$5)+E28),(E28*1)) -> 0 | G28: =IF(F28>12,(((F28)*$E$5)+F28),(F28*1)) -> 0 | H28: =IF(G28>12,(((G28)*$E$5)+G28),(G28*1)) -> 0 | I28: =IF(H28>12,(((H28)*$E$5)+H28),(H28*1)) -> 0 | T28: =IF($S28>0,PRODUCT(E28,$S28),0) -> 0 | U28: =IF($S28>0,PRODUCT(F28,$S28),0) -> 0 | V28: =IF($S28>0,PRODUCT(G28,$S28),0) -> 0 | W28: =IF($S28>0,PRODUCT(H28,$S28),0) -> 0 | X28: =IF($S28>0,PRODUCT(I28,$S28),0) -> 0 | Y28: =SUM(T28:X28) -> 0
E29: =D29*12 -> 0 | F29: =IF(E29>12,(((E29)*'CORE Recurring Items'!$H$5)+E29),(E29*1)) -> 0 | G29: =IF(F29>12,(((F29)*'CORE Recurring Items'!$H$5)+F29),(F29*1)) -> 0 | H29: =IF(G29>12,(((G29)*'CORE Recurring Items'!$H$5)+G29),(G29*1)) -> 0 | I29: =IF(H29>12,(((H29)*'CORE Recurring Items'!$H$5)+H29),(H29*1)) -> 0 | L29: =IF(K29>0,PRODUCT(E29,$K29),0) -> 0 | M29: =IF(L29>0,PRODUCT(F29,$K29),0) -> 0 | N29: =IF(M29>0,PRODUCT(G29,$K29),0) -> 0 | O29: =IF(N29>0,PRODUCT(H29,$K29),0) -> 0 | P29: =IF(O29>0,PRODUCT(I29,$K29),0) -> 0 | Q29: =SUM(L29:P29) -> 0 | AC29: =IF(AB29>0,PRODUCT(E29,$AB29),0) -> 0 | AD29: =IF(AC29>0,PRODUCT(F29,$AB29),0) -> 0 | AE29: =IF(AD29>0,PRODUCT(G29,$AB29),0) -> 0 | AF29: =IF(AE29>0,PRODUCT(H29,$AB29),0) -> 0 | AG29: =IF(AF29>0,PRODUCT(I29,$AB29),0) -> 0 | AH29: =SUM(AC29:AG29) -> 0 | AL29: =IF(AK29>0,PRODUCT(E29,$AK29),0) -> 0 | AM29: =IF(AL29>0,PRODUCT(F29,$AK29),0) -> 0 | AN29: =IF(AM29>0,PRODUCT(G29,$AK29),0) -> 0 | AO29: =IF(AN29>0,PRODUCT(H29,$AK29),0) -> 0 | AP29: =IF(AO29>0,PRODUCT(I29,$AK29),0) -> 0 | AQ29: =SUM(AL29:AP29) -> 0
E30: =D30*12 -> 0 | F30: =IF(E30>12,(((E30)*'CORE Recurring Items'!$H$5)+E30),(E30*1)) -> 0 | G30: =IF(F30>12,(((F30)*'CORE Recurring Items'!$H$5)+F30),(F30*1)) -> 0 | H30: =IF(G30>12,(((G30)*'CORE Recurring Items'!$H$5)+G30),(G30*1)) -> 0 | I30: =IF(H30>12,(((H30)*'CORE Recurring Items'!$H$5)+H30),(H30*1)) -> 0 | L30: =IF(K30>0,PRODUCT(E30,$K30),0) -> 0 | M30: =IF(L30>0,PRODUCT(F30,$K30),0) -> 0 | N30: =IF(M30>0,PRODUCT(G30,$K30),0) -> 0 | O30: =IF(N30>0,PRODUCT(H30,$K30),0) -> 0 | P30: =IF(O30>0,PRODUCT(I30,$K30),0) -> 0 | Q30: =SUM(L30:P30) -> 0 | AC30: =IF(AB30>0,PRODUCT(E30,$AB30),0) -> 0 | AD30: =IF(AC30>0,PRODUCT(F30,$AB30),0) -> 0 | AE30: =IF(AD30>0,PRODUCT(G30,$AB30),0) -> 0 | AF30: =IF(AE30>0,PRODUCT(H30,$AB30),0) -> 0 | AG30: =IF(AF30>0,PRODUCT(I30,$AB30),0) -> 0 | AH30: =SUM(AC30:AG30) -> 0 | AL30: =IF(AK30>0,PRODUCT(E30,$AK30),0) -> 0 | AM30: =IF(AL30>0,PRODUCT(F30,$AK30),0) -> 0 | AN30: =IF(AM30>0,PRODUCT(G30,$AK30),0) -> 0 | AO30: =IF(AN30>0,PRODUCT(H30,$AK30),0) -> 0 | AP30: =IF(AO30>0,PRODUCT(I30,$AK30),0) -> 0 | AQ30: =SUM(AL30:AP30) -> 0
E31: =D31*12 -> 0 | F31: =IF(E31>12,(((E31)*'CORE Recurring Items'!$H$5)+E31),(E31*1)) -> 0 | G31: =IF(F31>12,(((F31)*'CORE Recurring Items'!$H$5)+F31),(F31*1)) -> 0 | H31: =IF(G31>12,(((G31)*'CORE Recurring Items'!$H$5)+G31),(G31*1)) -> 0 | I31: =IF(H31>12,(((H31)*'CORE Recurring Items'!$H$5)+H31),(H31*1)) -> 0 | L31: =IF(K31>0,PRODUCT(E31,$K31),0) -> 0 | M31: =IF(L31>0,PRODUCT(F31,$K31),0) -> 0 | N31: =IF(M31>0,PRODUCT(G31,$K31),0) -> 0 | O31: =IF(N31>0,PRODUCT(H31,$K31),0) -> 0 | P31: =IF(O31>0,PRODUCT(I31,$K31),0) -> 0 | Q31: =SUM(L31:P31) -> 0 | AC31: =IF(AB31>0,PRODUCT(E31,$AB31),0) -> 0 | AD31: =IF(AC31>0,PRODUCT(F31,$AB31),0) -> 0 | AE31: =IF(AD31>0,PRODUCT(G31,$AB31),0) -> 0 | AF31: =IF(AE31>0,PRODUCT(H31,$AB31),0) -> 0 | AG31: =IF(AF31>0,PRODUCT(I31,$AB31),0) -> 0 | AH31: =SUM(AC31:AG31) -> 0 | AL31: =IF(AK31>0,PRODUCT(E31,$AK31),0) -> 0 | AM31: =IF(AL31>0,PRODUCT(F31,$AK31),0) -> 0 | AN31: =IF(AM31>0,PRODUCT(G31,$AK31),0) -> 0 | AO31: =IF(AN31>0,PRODUCT(H31,$AK31),0) -> 0 | AP31: =IF(AO31>0,PRODUCT(I31,$AK31),0) -> 0 | AQ31: =SUM(AL31:AP31) -> 0
E32: =D32*12 -> 0 | F32: =IF(E32>12,(((E32)*'CORE Recurring Items'!$H$5)+E32),(E32*1)) -> 0 | G32: =IF(F32>12,(((F32)*'CORE Recurring Items'!$H$5)+F32),(F32*1)) -> 0 | H32: =IF(G32>12,(((G32)*'CORE Recurring Items'!$H$5)+G32),(G32*1)) -> 0 | I32: =IF(H32>12,(((H32)*'CORE Recurring Items'!$H$5)+H32),(H32*1)) -> 0 | L32: =IF(K32>0,PRODUCT(E32,$K32),0) -> 0 | M32: =IF(L32>0,PRODUCT(F32,$K32),0) -> 0 | N32: =IF(M32>0,PRODUCT(G32,$K32),0) -> 0 | O32: =IF(N32>0,PRODUCT(H32,$K32),0) -> 0 | P32: =IF(O32>0,PRODUCT(I32,$K32),0) -> 0 | Q32: =SUM(L32:P32) -> 0 | AC32: =IF(AB32>0,PRODUCT(E32,$AB32),0) -> 0 | AD32: =IF(AC32>0,PRODUCT(F32,$AB32),0) -> 0 | AE32: =IF(AD32>0,PRODUCT(G32,$AB32),0) -> 0 | AF32: =IF(AE32>0,PRODUCT(H32,$AB32),0) -> 0 | AG32: =IF(AF32>0,PRODUCT(I32,$AB32),0) -> 0 | AH32: =SUM(AC32:AG32) -> 0 | AL32: =IF(AK32>0,PRODUCT(E32,$AK32),0) -> 0 | AM32: =IF(AL32>0,PRODUCT(F32,$AK32),0) -> 0 | AN32: =IF(AM32>0,PRODUCT(G32,$AK32),0) -> 0 | AO32: =IF(AN32>0,PRODUCT(H32,$AK32),0) -> 0 | AP32: =IF(AO32>0,PRODUCT(I32,$AK32),0) -> 0 | AQ32: =SUM(AL32:AP32) -> 0
C34: TOKENS & PROVISIONING | R34: =C34 -> TOKENS & PROVISIONING | AA34: =C34 -> TOKENS & PROVISIONING | AJ34: =C34 -> TOKENS & PROVISIONING
E35: =D35*12 -> 0 | F35: =IF(E35>12,(((E35)*$E$5)+E35),(E35*1)) -> 0 | G35: =IF(F35>12,(((F35)*$E$5)+F35),(F35*1)) -> 0 | H35: =IF(G35>12,(((G35)*$E$5)+G35),(G35*1)) -> 0 | I35: =IF(H35>12,(((H35)*$E$5)+H35),(H35*1)) -> 0 | T35: =IF($S35>0,PRODUCT(E35,$S35),0) -> 0 | U35: =IF($S35>0,PRODUCT(F35,$S35),0) -> 0 | V35: =IF($S35>0,PRODUCT(G35,$S35),0) -> 0 | W35: =IF($S35>0,PRODUCT(H35,$S35),0) -> 0 | X35: =IF($S35>0,PRODUCT(I35,$S35),0) -> 0 | Y35: =SUM(T35:X35) -> 0 | AC35: =IF(AB35>0,PRODUCT(E35,$AB35),0) -> 0 | AD35: =IF(AC35>0,PRODUCT(F35,$AB35),0) -> 0 | AE35: =IF(AD35>0,PRODUCT(G35,$AB35),0) -> 0 | AF35: =IF(AE35>0,PRODUCT(H35,$AB35),0) -> 0 | AG35: =IF(AF35>0,PRODUCT(I35,$AB35),0) -> 0 | AH35: =SUM(AC35:AG35) -> 0 | AL35: =IF(AK35>0,PRODUCT(E35,$AK35),0) -> 0 | AM35: =IF(AL35>0,PRODUCT(F35,$AK35),0) -> 0 | AN35: =IF(AM35>0,PRODUCT(G35,$AK35),0) -> 0 | AO35: =IF(AN35>0,PRODUCT(H35,$AK35),0) -> 0 | AP35: =IF(AO35>0,PRODUCT(I35,$AK35),0) -> 0 | AQ35: =SUM(AL35:AP35) -> 0
E36: =D36*12 -> 0 | F36: =IF(E36>12,(((E36)*'CORE Recurring Items'!$H$5)+E36),(E36*1)) -> 0 | G36: =IF(F36>12,(((F36)*'CORE Recurring Items'!$H$5)+F36),(F36*1)) -> 0 | H36: =IF(G36>12,(((G36)*'CORE Recurring Items'!$H$5)+G36),(G36*1)) -> 0 | I36: =IF(H36>12,(((H36)*'CORE Recurring Items'!$H$5)+H36),(H36*1)) -> 0 | AC36: =IF(AB36>0,PRODUCT(E36,$AB36),0) -> 0 | AD36: =IF(AC36>0,PRODUCT(F36,$AB36),0) -> 0 | AE36: =IF(AD36>0,PRODUCT(G36,$AB36),0) -> 0 | AF36: =IF(AE36>0,PRODUCT(H36,$AB36),0) -> 0 | AG36: =IF(AF36>0,PRODUCT(I36,$AB36),0) -> 0 | AH36: =SUM(AC36:AG36) -> 0 | AL36: =IF(AK36>0,PRODUCT(E36,$AK36),0) -> 0 | AM36: =IF(AL36>0,PRODUCT(F36,$AK36),0) -> 0 | AN36: =IF(AM36>0,PRODUCT(G36,$AK36),0) -> 0 | AO36: =IF(AN36>0,PRODUCT(H36,$AK36),0) -> 0 | AP36: =IF(AO36>0,PRODUCT(I36,$AK36),0) -> 0 | AQ36: =SUM(AL36:AP36) -> 0
E37: =D37*12 -> 0 | F37: =IF(E37>12,(((E37)*'CORE Recurring Items'!$H$5)+E37),(E37*1)) -> 0 | G37: =IF(F37>12,(((F37)*'CORE Recurring Items'!$H$5)+F37),(F37*1)) -> 0 | H37: =IF(G37>12,(((G37)*'CORE Recurring Items'!$H$5)+G37),(G37*1)) -> 0 | I37: =IF(H37>12,(((H37)*'CORE Recurring Items'!$H$5)+H37),(H37*1)) -> 0 | AC37: =IF(AB37>0,PRODUCT(E37,$AB37),0) -> 0 | AD37: =IF(AC37>0,PRODUCT(F37,$AB37),0) -> 0 | AE37: =IF(AD37>0,PRODUCT(G37,$AB37),0) -> 0 | AF37: =IF(AE37>0,PRODUCT(H37,$AB37),0) -> 0 | AG37: =IF(AF37>0,PRODUCT(I37,$AB37),0) -> 0 | AH37: =SUM(AC37:AG37) -> 0 | AL37: =IF(AK37>0,PRODUCT(E37,$AK37),0) -> 0 | AM37: =IF(AL37>0,PRODUCT(F37,$AK37),0) -> 0 | AN37: =IF(AM37>0,PRODUCT(G37,$AK37),0) -> 0 | AO37: =IF(AN37>0,PRODUCT(H37,$AK37),0) -> 0 | AP37: =IF(AO37>0,PRODUCT(I37,$AK37),0) -> 0 | AQ37: =SUM(AL37:AP37) -> 0
E38: =D38*12 -> 0 | F38: =IF(E38>12,(((E38)*$E$5)+E38),(E38*1)) -> 0 | G38: =IF(F38>12,(((F38)*$E$5)+F38),(F38*1)) -> 0 | H38: =IF(G38>12,(((G38)*$E$5)+G38),(G38*1)) -> 0 | I38: =IF(H38>12,(((H38)*$E$5)+H38),(H38*1)) -> 0 | AC38: =IF(AB38>0,PRODUCT(E38,$AB38),0) -> 0 | AD38: =IF(AC38>0,PRODUCT(F38,$AB38),0) -> 0 | AE38: =IF(AD38>0,PRODUCT(G38,$AB38),0) -> 0 | AF38: =IF(AE38>0,PRODUCT(H38,$AB38),0) -> 0 | AG38: =IF(AF38>0,PRODUCT(I38,$AB38),0) -> 0 | AH38: =SUM(AC38:AG38) -> 0 | AL38: =IF(AK38>0,PRODUCT(E38,$AK38),0) -> 0 | AM38: =IF(AL38>0,PRODUCT(F38,$AK38),0) -> 0 | AN38: =IF(AM38>0,PRODUCT(G38,$AK38),0) -> 0 | AO38: =IF(AN38>0,PRODUCT(H38,$AK38),0) -> 0 | AP38: =IF(AO38>0,PRODUCT(I38,$AK38),0) -> 0 | AQ38: =SUM(AL38:AP38) -> 0
E39: =D39*12 -> 0 | F39: =IF(E39>12,(((E39)*$E$5)+E39),(E39*1)) -> 0 | G39: =IF(F39>12,(((F39)*$E$5)+F39),(F39*1)) -> 0 | H39: =IF(G39>12,(((G39)*$E$5)+G39),(G39*1)) -> 0 | I39: =IF(H39>12,(((H39)*$E$5)+H39),(H39*1)) -> 0 | AC39: =IF(AB39>0,PRODUCT(E39,$AB39),0) -> 0 | AD39: =IF(AC39>0,PRODUCT(F39,$AB39),0) -> 0 | AE39: =IF(AD39>0,PRODUCT(G39,$AB39),0) -> 0 | AF39: =IF(AE39>0,PRODUCT(H39,$AB39),0) -> 0 | AG39: =IF(AF39>0,PRODUCT(I39,$AB39),0) -> 0 | AH39: =SUM(AC39:AG39) -> 0 | AL39: =IF(AK39>0,PRODUCT(E39,$AK39),0) -> 0 | AM39: =IF(AL39>0,PRODUCT(F39,$AK39),0) -> 0 | AN39: =IF(AM39>0,PRODUCT(G39,$AK39),0) -> 0 | AO39: =IF(AN39>0,PRODUCT(H39,$AK39),0) -> 0 | AP39: =IF(AO39>0,PRODUCT(I39,$AK39),0) -> 0 | AQ39: =SUM(AL39:AP39) -> 0
C41: INSIGHT CENTER WILL REPLACE TOTAL REVELATION PROGRAM | R41: =C41 -> INSIGHT CENTER WILL REPLACE TOTAL REVELATION PROGRAM | AA41: =C41 -> INSIGHT CENTER WILL REPLACE TOTAL REVELATION PROGRAM | AJ41: =C41 -> INSIGHT CENTER WILL REPLACE TOTAL REVELATION PROGRAM
E42: =D42*12 -> 0 | F42: =IF(E42>12,(((E42)*$E$5)+E42),(E42*1)) -> 0 | G42: =IF(F42>12,(((F42)*$E$5)+F42),(F42*1)) -> 0 | H42: =IF(G42>12,(((G42)*$E$5)+G42),(G42*1)) -> 0 | I42: =IF(H42>12,(((H42)*$E$5)+H42),(H42*1)) -> 0 | T42: =PRODUCT(E42,$S42) -> 0 | U42: =PRODUCT(F42,$S42) -> 0 | V42: =PRODUCT(G42,$S42) -> 0 | W42: =PRODUCT(H42,$S42) -> 0 | X42: =PRODUCT(I42,$S42) -> 0 | Y42: =SUM(T42:X42) -> 0
E43: =D43*12 -> 0 | F43: =IF(E43>12,(((E43)*$E$5)+E43),(E43*1)) -> 0 | G43: =IF(F43>12,(((F43)*$E$5)+F43),(F43*1)) -> 0 | H43: =IF(G43>12,(((G43)*$E$5)+G43),(G43*1)) -> 0 | I43: =IF(H43>12,(((H43)*$E$5)+H43),(H43*1)) -> 0 | T43: =IF($S43>0,PRODUCT(E43,$S43),0) -> 0 | U43: =IF($S43>0,PRODUCT(F43,$S43),0) -> 0 | V43: =IF($S43>0,PRODUCT(G43,$S43),0) -> 0 | W43: =IF($S43>0,PRODUCT(H43,$S43),0) -> 0 | X43: =IF($S43>0,PRODUCT(I43,$S43),0) -> 0 | Y43: =SUM(T43:X43) -> 0
C45: EMV CONTACT TO EMV CONTACTLESS | R45: =C45 -> EMV CONTACT TO EMV CONTACTLESS | AA45: =C45 -> EMV CONTACT TO EMV CONTACTLESS | AJ45: =C45 -> EMV CONTACT TO EMV CONTACTLESS
E46: =D46*12 -> 0 | F46: =IF(E46>12,(((E46)*'CORE Recurring Items'!$H$5)+E46),(E46*1)) -> 0 | G46: =IF(F46>12,(((F46)*'CORE Recurring Items'!$H$5)+F46),(F46*1)) -> 0 | H46: =IF(G46>12,(((G46)*'CORE Recurring Items'!$H$5)+G46),(G46*1)) -> 0 | I46: =IF(H46>12,(((H46)*'CORE Recurring Items'!$H$5)+H46),(H46*1)) -> 0 | AC46: =IF(AB46>0,PRODUCT(E46,$AB46),0) -> 0 | AD46: =IF(AC46>0,PRODUCT(F46,$AB46),0) -> 0 | AE46: =IF(AD46>0,PRODUCT(G46,$AB46),0) -> 0 | AF46: =IF(AE46>0,PRODUCT(H46,$AB46),0) -> 0 | AG46: =IF(AF46>0,PRODUCT(I46,$AB46),0) -> 0 | AH46: =SUM(AC46:AG46) -> 0 | AL46: =IF(AK46>0,PRODUCT(E46,$AK46),0) -> 0 | AM46: =IF(AL46>0,PRODUCT(F46,$AK46),0) -> 0 | AN46: =IF(AM46>0,PRODUCT(G46,$AK46),0) -> 0 | AO46: =IF(AN46>0,PRODUCT(H46,$AK46),0) -> 0 | AP46: =IF(AO46>0,PRODUCT(I46,$AK46),0) -> 0 | AQ46: =SUM(AL46:AP46) -> 0
E47: =D47*12 -> 0 | F47: =IF(E47>12,(((E47)*$E$5)+E47),(E47*1)) -> 0 | G47: =IF(F47>12,(((F47)*$E$5)+F47),(F47*1)) -> 0 | H47: =IF(G47>12,(((G47)*$E$5)+G47),(G47*1)) -> 0 | I47: =IF(H47>12,(((H47)*$E$5)+H47),(H47*1)) -> 0 | T47: =IF($S47>0,PRODUCT(E47,$S47),0) -> 0 | U47: =IF($S47>0,PRODUCT(F47,$S47),0) -> 0 | V47: =IF($S47>0,PRODUCT(G47,$S47),0) -> 0 | W47: =IF($S47>0,PRODUCT(H47,$S47),0) -> 0 | X47: =IF($S47>0,PRODUCT(I47,$S47),0) -> 0 | Y47: =SUM(T47:X47) -> 0
C49: 3D SECURE | R49: =C49 -> 3D SECURE | AA49: =C49 -> 3D SECURE | AJ49: =C49 -> 3D SECURE
